Workbook

Sheet H
A1: Meituan financial disclosure | P1: CEQ (*only account for E that we can consolidate)
A2: (RMB millions) | B2: Jan to Apr 2017 | C2: Jan to Apr 2018 | D2: YoY | F2: 1H 2017 | G2: 1H 2018 | H2: YoY | J2: May to Jun 2017 | K2: May to Jun 2018 | L2: YoY | N2: Comments | P2: Jan.-Apr. 2017 | Q2: Jan.-Apr. 2018 | R2: YoY
A3: Meituan hotels only:
A4: Room Nights | B4: 57 | C4: 87 | D4: =C4/B4-1 -> 0.52631579 | F4: 89.4 | G4: 133.5 | H4: =G4/F4-1 -> 0.49328859 | J4: =F4-B4 -> 32.4 | K4: =G4-C4 -> 46.5 | L4: =K4/J4-1 -> 0.43518519 | N4: Slight deceleration of RNs growth
A5: GMV | B5: 9964 | C5: 16255 | D5: =C5/B5-1 -> 0.63137294 | G5: 23000 | K5: =G5-C5 -> 6745
A6: ADR | B6: =B5/B4 -> 174.80702 | C6: =C5/C4 -> 186.83908 | D6: =C6/B6-1 -> 0.068830549 | G6: =G5/G4 -> 172.28464 | K6: =K5/K4 -> 145.05376 | N6: ADR mgmt. stated is increasing
A7: Take-rate | B7: 0.072 | C7: 0.072 | D7: =C7/B7-1 -> 0 | H7: Increasing
A9: Active Hotels | B9: 0.3 | C9: 0.3 | D9: =C9/B9-1 -> 0
A11: Revenue | B11: 720 | C11: 1176 | D11: =C11/B11-1 -> 0.63333333
A12: Cost of Revenue | B12: 91 | C12: 182 | D12: =C12/B12-1 -> 1
A14: Gross Profit | B14: 629 | C14: 994 | D14: =C14/B14-1 -> 0.58028617
A15: Gross Margin | B15: 0.873 | C15: 0.845 | D15: =C15/B15-1 -> -0.03207331
A17: 1Q2018 RN mkt share | C17: 0.336 | D17: #1
A18: % of transactions from cross-sell | C18: 0.8
A20: China hotel online penetration | C20: 20.17 | D20: 0.32
A22: Total Meituan Group:
A23: Total revenues | B23: 8120 | C23: 15824 | D23: =C23/B23-1 -> 0.94876847 | F23: 13779 | G23: 26348 | H23: =G23/F23-1 -> 0.91218521 | J23: =F23-B23 -> 5659 | K23: =G23-C23 -> 10524 | L23: =K23/J23-1 -> 0.85969253
A24: Total operating loss | B24: -769 | C24: -2526 | D24: =C24/B24-1 -> 2.2847854 | F24: -1250 | G24: -3900 | H24: =G24/F24-1 -> 2.12 | J24: =F24-B24 -> -481 | K24: =G24-C24 -> -1374 | L24: =K24/J24-1 -> 1.8565489 | N24: Slight improvement in profitability
A25: Total adjusted EBITDA | B25: -263 | C25: -1727 | D25: =C25/B25-1 -> 5.5665399 | F25: -493 | G25: -2707 | H25: =G25/F25-1 -> 4.4908722 | J25: =F25-B25 -> -230 | K25: =G25-C25 -> -980 | L25: =K25/J25-1 -> 3.2608696
A27: In-store, hotel & travel:
A28: GMV | B28: 50.5 | C28: 55.1 | D28: =C28/B28-1 -> 0.091089109 | F28: 74.9 | G28: 82.8 | H28: =G28/F28-1 -> 0.10547397 | J28: =F28-B28 -> 24.4 | K28: =G28-C28 -> 27.7 | L28: =K28/J28-1 -> 0.1352459
A29: Revenues | B29: 3041 | C29: 4351 | D29: =C29/B29-1 -> 0.43077935 | F29: =4727033/1000 -> 4727.033 | G29: 6811 | H29: =G29/F29-1 -> 0.44086153 | J29: =F29-B29 -> 1686.033 | K29: =G29-C29 -> 2460 | L29: =K29/J29-1 -> 0.45904618
A30: Gross profit/loss | B30: 2670 | C30: 3829 | D30: =C30/B30-1 -> 0.4340824 | F30: =4183770/1000 -> 4183.77 | G30: 6090 | H30: =G30/F30-1 -> 0.45562495 | J30: =F30-B30 -> 1513.77 | K30: =G30-C30 -> 2261 | L30: =K30/J30-1 -> 0.49362188
A31: Gross margin | B31: =B30/B29 -> 0.87800066 | C31: =C30/C29 -> 0.88002758 | F31: =F30/F29 -> 0.88507315 | G31: =G30/G29 -> 0.89414183 | J31: =J30/J29 -> 0.8978294 | K31: =K30/K29 -> 0.91910569
A33: * Hotel entering maturity stage and margins are stable bc of economies of scale
A34: * Traffic source: 80% of hotel transactions and 74% of lifestyle transactions from food delivery/in-store dining
A35: * Hotel RN mkt share 33.6% in 1Q2018 - they said they are the largest hotel booking platform in China
A36: * Expanding steadily to mid to high-end hotels to satisfy consumer needs

Sheet Key Financial Data
B1: 总则： | C1: 黑色数字为历史数字，请自行输入或导入；绿色数字为计算项，无需改动；蓝色字体部分需要做出合理估计、或者需要从会计报表附注中查找、等；
A2: Unit: Thousand | W2: =W5/K5-1 -> 1.2436707
B3: 17Q1 | C3: 17Q2 | D3: 17Q3 | E3: 17Q4 | F3: 18Q1 | G3: 18Q2 | H3: 18Q3 | I3: 18Q4 | J3: 19Q1 | K3: 19Q2 | L3: 19Q3 | M3: 19Q4 | N3: 20Q1 | O3: 20Q2 | P3: 20Q3 | Q3: 20Q4 | R3: 21Q1 | S3: 21Q2 | T3: 21Q3 | U3: 21Q4 | V3: 22Q1 | W3: 22Q2 | X3: 22Q3 | Y3: 22Q4 | Z3: 23Q1 | AA3: 23Q2 | AB3: 23Q3 | AC3: 23Q4 | AD3: 24Q1 | AE3: 24Q2 | AF3: 24Q3 | AG3: 24Q4 | AH3: 25Q1 | AI3: 25Q2 | AJ3: 25Q3 | AK3: 25Q4 | AL3: 26Q1 | AM3: 26Q2 | AN3: 2017 1H | AO3: 2017 2H | AP3: 2018 1H | AQ3: 2018 2H | AR3: 2019 1H | AS3: 2020 1H | AU3: 2017 YTD-Q3 | AV3: 2018 YTD-Q3 | AX3: 2015 FY | AY3: 2016 FY | AZ3: 2017 FY | BA3: 2018 FY | BB3: 2019 FY | BC3: 2020 FY | BD3: 2021 FY | BE3: 2022 FY | BF3: 2023FY
A4: P&L | F4: (倒减) | X4: =X5/L5-1 -> 1.2775783 | Y4: =Y5/M5-1 -> 1.1353931 | Z4: =Z5/J5-1 -> 2.057211 | AA4: =AA5/K5-1 -> 1.9936226 | AB4: =AB5/L5-1 -> 1.7812591 | AC4: =AC5/M5-1 -> 1.6172061 | AD4: =AD5/J5-1 -> 2.8217247 | AO4: (倒减) | AU4: (加总) | AV4: (加总)
A5: Revenues | D5: 9673796 | E5: 10475378 | F5: =AP5-G5 -> 11275063 | G5: 15072764 | H5: 19075999 | I5: 19803452 | J5: 19173512 | K5: 22703137 | L5: 27493629 | M5: 28158253 | N5: 16753887 | O5: 24721837 | P5: 35401282 | Q5: 37917504 | R5: 37016262 | S5: 43759232 | T5: 48829370 | U5: 49523133 | V5: 46268754 | W5: 50938363 | X5: 62618892 | Y5: 60128939 | Z5: 58617472 | AA5: 67964624 | AB5: 76466907 | AC5: 73695951 | AD5: 73275884 | AE5: 82251077 | AF5: 93577319 | AG5: 88487296 | AH5: 86557126 | AI5: 91840480 | AJ5: 95488113 | AK5: 92096429 | AL5: 91038906 | AM5: 104643044 | AN5: 13778813 | AO5: =AZ5-AN5 -> 20149174 | AP5: 26347827 | AQ5: =BA5-AP5 -> 38879451 | AR5: 41876649 | AU5: =D5+AN5 -> 23452609 | AV5: =H5+AP5 -> 45423826 | AX5: 4018959 | AY5: 12988077 | AZ5: 33927987 | BA5: 65227278 | BB5: 97528531 | BC5: 114794510 | BD5: 179127997 | BE5: 219954948
A6: Cost of revenues | D6: -6240679 | E6: -7123869 | F6: =AP6-G6 -> -8063090 | G6: -12232014 | H6: -14504758 | I6: -15322458 | J6: -14104172 | K6: -14762502 | L6: -17901345 | M6: -18440124 | N6: -11557421 | O6: -16146879 | P6: -24578273 | Q6: -28461795 | R6: -29816095 | S6: -31245861 | T6: -38051383 | U6: -37540530 | V6: -35528467 | W6: -35363935 | X6: -44114024 | Y6: -43195543 | Z6: -38800047 | AA6: -42566619 | AB6: -49484515 | AC6: -48702612 | AD6: -47579144 | AE6: -48361233 | AF6: -56823456 | AG6: -55043149 | AH6: -54143437 | AI6: -61426477 | AJ6: -70307050 | AK6: -67969156 | AL6: -65068834 | AM6: -69548247 | AN6: -8343935 | AO6: =AZ6-AN6 -> -13364548 | AP6: -20295104 | AQ6: =BA6-AP6 -> -29827216 | AR6: -28866674 | AU6: =D6+AN6 -> -14584614 | AV6: =H6+AP6 -> -34799862 | AX6: -1239504 | AY6: -7046841 | AZ6: -21708483 | BA6: -50122320 | BB6: -65208143 | BC6: -80744368 | BD6: -136653869 | BE6: -158201969
A8: Gross profit | D8: =D5+D6 -> 3433117 | E8: =E5+E6 -> 3351509 | F8: =AP8-G8 -> 3211973 | G8: =G5+G6 -> 2840750 | H8: =H5+H6 -> 4571241 | I8: =I5+I6 -> 4480994 | J8: =J5+J6 -> 5069340 | K8: =K5+K6 -> 7940635 | L8: =L5+L6 -> 9592284 | M8: =M5+M6 -> 9718129 | N8: =N5+N6 -> 5196466 | ... Y8: =Y5+Y6 -> 16933396 | Z8: 19817425 | AA8: 25398005 | AB8: =AB5+AB6 -> 26982392 | AC8: =AC5+AC6 -> 24993339 | AD8: =AD5+AD6 -> 25696740 | AE8: =AE5+AE6 -> 33889844 | AF8: =AF5+AF6 -> 36753863 | AG8: =AG5+AG6 -> 33444147 | AH8: =AH5+AH6 -> 32413689 | AI8: =AI5+AI6 -> 30414003 | AJ8: 25181063 | AK8: =AK5+AK6 -> 24127273 | AL8: =AL5+AL6 -> 25970072 | AM8: =AM5+AM6 -> 35094797 | AN8: =AN5+AN6 -> 5434878 | AO8: =AZ8-AN8 -> 6784626 | AP8: =AP5+AP6 -> 6052723 | AQ8: =BA8-AP8 -> 9052235 | AR8: =AR5+AR6 -> 13009975 | AT8: =AT5+AT6 -> 0 | AU8: =D8+AN8 -> 8867995 | AV8: =H8+AP8 -> 10623964 | AW8: =AW5+AW6 -> 0 | AX8: =AX5+AX6 -> 2779455 | AY8: =AY5+AY6 -> 5941236 | AZ8: =AZ5+AZ6 -> 12219504 | BA8: =BA5+BA6 -> 15104958 | BB8: =BB5+BB6 -> 32320388 | BC8: =BC5+BC6 -> 34050142 | BD8: =BD5+BD6 -> 42474128 | BE8: =BE5+BE6 -> 61752979
A9: Selling and marketing expenses | D9: -3183558 | E9: -3362229 | F9: =AP9-G9 -> -2846353 | G9: -3868230 | H9: -4622267 | I9: -4535051 | J9: -3706112 | K9: -4149110 | L9: -5614750 | M9: -5349095 | N9: -3199439 | O9: -4172332 | P9: -5835574 | Q9: -7675340 | R9: -7206408 | S9: -10848627 | T9: -11388227 | U9: -11239904 | V9: -9105728 | W9: -8986036 | X9: -10886422 | Y9: -10766926 | Z9: -10433070 | AA9: -14553195 | AB9: -16905422 | AC9: -16725310 | AD9: -13888302 | AE9: -14832448 | AF9: -17953163 | AG9: -17301322 | AH9: -15550016 | AI9: -22518913 | AJ9: -34266826 | AK9: -31725691 | AL9: -22968519 | AM9: -24723345 | AN9: -4362901 | AO9: =AZ9-AN9 -> -6545787 | AP9: -6714583 | AQ9: =BA9-AP9 -> -9157318 | AR9: -7855222 | AU9: =D9+AN9 -> -7546459 | AV9: =H9+AP9 -> -11336850 | AX9: -7140962 | AY9: -8337132 | AZ9: -10908688 | BA9: -15871901 | BB9: -18819067 | BC9: -20882685 | BD9: -40683166 | BE9: -39745979
A10: Research and development expenses | D10: -1026987 | E10: -1149301 | F10: =AP10-G10 -> -1382740 | G10: -1703837 | H10: -2003497 | I10: -1981826 | J10: -2036100 | K10: -2032330 | L10: -2137349 | M10: -2239885 | N10: -2296458 | O10: -2376737 | P10: -2970120 | Q10: -3249199 | R10: -3477290 | S10: -3900794 | T10: -4715550 | U10: -4581961 | V10: -4879033 | W10: -5203533 | X10: -5414371 | Y10: -5242928 | Z10: -5047387 | AA10: -5407176 | AB10: -5321157 | AC10: -5425285 | AD10: -5000153 | AE10: -5339680 | AF10: -5293483 | AG10: -5420285 | AH10: -5772030 | AI10: -6260087 | AJ10: -6936845 | AK10: -7029303 | AL10: -7043098 | AM10: -7670045 | AN10: -1470346 | AO10: =AZ10-AN10 -> -2176288 | AP10: -3086577 | AQ10: =BA10-AP10 -> -3985323 | AR10: -4068430 | AU10: =D10+AN10 -> -2497333 | AV10: =H10+AP10 -> -5090074 | AX10: -1204033 | AY10: -2366674 | AZ10: -3646634 | BA10: -7071900 | BB10: -8445664 | BC10: -10892514 | BD10: -16675595 | BE10: -20739865
A11: General and administrative expenses | D11: -524435 | E11: -914441 | F11: =AP11-G11 -> -667281 | G11: -996210 | H11: -1238040 | I11: -2846080 | J11: -1075193 | K11: -1038298 | L11: -1055969 | M11: -1564478 | N11: =-(1069741+237542) -> -1307283 | O11: =-1158092-45676 -> -1203768 | P11: =-1415119-130285 -> -1545404 | Q11: =-1950943-54187 -> -2005130 | R11: =-1737403+33775 -> -1703628 | S11: =-2053024-104355 -> -2157379 | T11: -2387116 | U11: =-2435083-52489 -> -2487572 | V11: =-2312289-153316 -> -2465605 | W11: =-2503552-50437 -> -2553989 | X11: -2505272 | Y11: -2450697 | Z11: -1994953 | AA11: -2139084 | AB11: -2537785 | AC11: -2700281 | AD11: -2298323 | AE11: -2694931 | AF11: -2797760 | AG11: -2938189 | AH11: -2627017 | AI11: -2678950 | AJ11: -2957804 | AK11: -3652661 | AL11: -2938393 | AM11: -3238070 | AN11: -732532 | AO11: =AZ11-AN11 -> -1438876 | AP11: -1663491 | AQ11: =BA11-AP11 -> -4168201 | AR11: -2050511 | AU11: =D11+AN11 -> -1256967 | AV11: =H11+AP11 -> -2901531 | AX11: -2905420 | AY11: -1722605 | AZ11: -2171408 | BA11: -5831692 | BB11: -4984639 | BC11: =-5593895-467690 -> -6061585 | BD11: =-8612626-259953 -> -8872579 | BE11: -9771810
A12: Share-based compensation | D12: -231222 | F12: =AP12-G12 -> -294678 | G12: -387580 | H12: -539632 | I12: -643223 | J12: -438068 | K12: -515501 | L12: -537169 | M12: -700133 | N12: -691676 | O12: -705420 | P12: -838709 | Q12: -1041671 | R12: -937902 | S12: -1140658 | T12: -1481159 | U12: -1634141 | V12: -1618334 | W12: -2357747 | X12: -2445766 | Y12: -2321115 | Z12: -1936848 | AA12: -2450640 | AB12: -2138443 | AC12: -1857422 | AD12: -1851012 | AE12: -2069327 | AF12: -1890022 | AG12: -1772332 | AH12: -1707846 | AI12: -1387416 | AJ12: -1558306 | AK12: -1348299 | AL12: -1383006 | AM12: -1918583 | AN12: -279881 | AO12: =AZ12-AN12 -> -691219 | AP12: -682258 | AQ12: =BA12-AP12 -> -1182855 | AR12: -953569 | AU12: =D12+AN12 -> -511103 | AV12: =H12+AP12 -> -1221890 | AX12: -2599378 | AY12: -913075 | AZ12: -971100 | BA12: -1865113 | BB12: -2190871 | BC12: -3277476 | BD12: -5193860 | BE12: -468620
T13: =T8/T5 -> 0.22072755 | X13: =X8/X5 -> 0.29551574 | Y13: =Y8/Y5 -> 0.28161807 | Z13: =Z8/Z5 -> 0.33808051 | AA13: =AA8/AA5 -> 0.37369448 | AB13: =AB8/AB5 -> 0.35286365 | AC13: =AC8/AC5 -> 0.33914128 | AD13: =AD8/AD5 -> 0.35068482 | AE13: =AE8/AE5 -> 0.41202918 | ... AM13: =AM8/AM5 -> 0.3353763
A15: Operating Income (Loss) - comparable to Ctrip | D15: =SUM(D8,D9,D10,D11) -> -1301863 | E15: =SUM(E8,E9,E10,E11) -> -2074462 | F15: =AP15-G15 -> -1684401 | G15: =SUM(G8,G9,G10,G11) -> -3727527 | H15: =SUM(H8,H9,H10,H11) -> -3292563 | I15: =SUM(I8,I9,I10,I11) -> -4881963 | J15: =SUM(J8,J9,J10,J11) -> -1748065 | K15: =SUM(K8,K9,K10,K11) -> 720897 | L15: =SUM(L8,L9,L10,L11) -> 784216 | M15: =SUM(M8,M9,M10,M11) -> 564671 | N15: =SUM(N8,N9,N10,N11) -> -1606714 | ... AN15: =SUM(AN8,AN9,AN10,AN11) -> -1130901 | AO15: =AZ15-AN15 -> -3376325 | AP15: =SUM(AP8,AP9,AP10,AP11) -> -5411928 | AQ15: =SUM(AQ8,AQ9,AQ10,AQ11) -> -8258607 | AR15: =SUM(AR8,AR9,AR10,AR11) -> -964188 | AT15: =SUM(AT8,AT9,AT10,AT11) -> 0 | AU15: =D15+AN15 -> -2432764 | AV15: =H15+AP15 -> -8704491 | AW15: =SUM(AW8,AW9,AW10,AW11) -> 0 | AX15: =SUM(AX8,AX9,AX10,AX11) -> -8470960 | AY15: =SUM(AY8,AY9,AY10,AY11) -> -6485175 | AZ15: =SUM(AZ8,AZ9,AZ10,AZ11) -> -4507226 | BA15: =SUM(BA8,BA9,BA10,BA11) -> -13670535 | BB15: =SUM(BB8,BB9,BB10,BB11) -> 71018 | BC15: =SUM(BC8,BC9,BC10,BC11) -> -3786642 | BD15: =SUM(BD8,BD9,BD10,BD11) -> -23757212 | BE15: =SUM(BE8,BE9,BE10,BE11) -> -8504675
A16: Non-GAAP Operating Income(Loss) - comparable to Ctrip | D16: =D15-D12 -> -1070641 | E16: =E15-E12 -> -2074462 | F16: =F15-F12 -> -1389723 | G16: =G15-G12 -> -3339947 | H16: =H15-H12 -> -2752931 | I16: =I15-I12 -> -4238740 | J16: =J15-J12 -> -1309997 | K16: =K15-K12 -> 1236398 | ... AN16: =AN15-AN12 -> -851020 | AO16: =AZ16-AN16 -> -2685106 | AP16: =AP15-AP12 -> -4729670 | AQ16: =AQ15-AQ12 -> -7075752 | AR16: =AR15-AR12 -> -10619 | AU16: =D16+AN16 -> -1921661 | AV16: =H16+AP16 -> -7482601 | AX16: =AX15-AX12 -> -5871582 | AY16: =AY15-AY12 -> -5572100 | AZ16: =AZ15-AZ12 -> -3536126 | BA16: =BA15-BA12 -> -11805422 | BB16: =BB15-BB12 -> 2261889 | BC16: =BC15-BC12 -> -509166 | BD16: =BD15-BD12 -> -18563352 | BE16: =BE15-BE12 -> -8036055
A17: Fair value changes on investments measured at fair value through profit or loss | D17: 484045 | E17: 241006 | F17: =AP17-G17 -> 471066 | G17: 715216 | H17: -340553 | I17: 990653 | J17: 165292 | K17: -323651 | L17: 163615 | M17: 72443 | N17: -508261 | O17: 346689 | P17: 5779364 | Q17: -661883 | R17: 42034 | S17: 164748 | T17: -117990 | U17: 726955 | V17: -802894 | W17: -292183 | X17: -105922 | Y17: 187942 | Z17: 164029 | AA17: 103761 | AB17: 28089 | AC17: -61652 | AD17: -517116 | AE17: -120037 | AF17: 765239 | AG17: 12835 | AH17: 804820 | AI17: 481537 | AJ17: -389928 | AK17: 1496964 | AL17: 392441 | AM17: 54814 | AN17: -252177 | AO17: =AZ17-AN17 -> 725051 | AP17: 1186282 | AQ17: =BA17-AP17 -> 650100 | AR17: 1186282 | AU17: =D17+AN17 -> 231868 | AV17: =H17+AP17 -> 845729 | AX17: 46953 | AY17: 23550 | AZ17: 472874 | BA17: 1836382 | BB17: 77699 | BC17: 4955909 | BD17: 815747 | BE17: -1013057
A18: Other gains, net | D18: -227558 | E18: 302857 | F18: =AP18-G18 -> 164911 | G18: 160894 | H18: 265759 | I18: 156792 | J18: 279131 | K18: 854043 | L18: 611223 | M18: 786746 | N18: 399445 | O18: 1005835 | P18: 472408 | Q18: 1283147 | R18: 378118 | S18: 976976 | T18: -2134851 | U18: 594023 | V18: 928731 | W18: 968475 | X18: 1679376 | Y18: 588455 | Z18: 1335024 | AA18: 1505916 | AB18: 1388793 | AC18: 2085740 | AD18: 1391932 | AE18: 630572 | AF18: 2485778 | AG18: -933297 | AH18: 1418138 | AI18: 807979 | AJ18: -96233 | AK18: 1147736 | AL18: 598697 | AM18: 3493946 | AN18: 132961 | AO18: =AZ18-AN18 -> 75299 | AP18: 325805 | AQ18: =BA18-AP18 -> 422551 | AR18: 1133174 | AU18: =D18+AN18 -> -94597 | AV18: =H18+AP18 -> 591564 | AX18: -49928 | AY18: 206212 | AZ18: 208260 | BA18: 748356 | BB18: 2531143 | BC18: 3160835 | BD18: -185734 | BE18: 4165037
A19: Meituan Reported Operating Income (Loss) | D19: =SUM(D15,D17,D18) -> -1045376 | E19: =SUM(E15,E17,E18) -> -1530599 | F19: =AP19-G19 -> -1048424 | G19: =SUM(G15,G17,G18) -> -2851417 | H19: =SUM(H15,H17,H18) -> -3367357 | I19: =SUM(I15,I17,I18) -> -3734518 | J19: =SUM(J15,J17,J18) -> -1303642 | K19: =SUM(K15,K17,K18) -> 1251289 | L19: =SUM(L15,L17,L18) -> 1559054 | M19: =SUM(M15,M17,M18) -> 1423860 | N19: =SUM(N15,N17,N18) -> -1715530 | ... AC19: =SUM(AC15,AC17,AC18) -> 2166551 | AE19: =SUM(AE15,AE17,AE18) -> 11533320 | AF19: =SUM(AF15,AF17,AF18) -> 13960474 | AG19: =SUM(AG15,AG17,AG18) -> 6863889 | AH19: =SUM(AH15,AH17,AH18) -> 10687584 | AI19: =SUM(AI15,AI17,AI18) -> 245569 | AJ19: =SUM(AJ15,AJ17,AJ18) -> -19466573 | AK19: -16074247 | AL19: -6469811 | AM19: 2691166 | AN19: =SUM(AN15,AN17,AN18) -> -1250117 | AO19: =SUM(AO15,AO17,AO18) -> -2575975 | AP19: =SUM(AP15,AP17,AP18) -> -3899841 | AQ19: =SUM(AQ15,AQ17,AQ18) -> -7185956 | AR19: =SUM(AR15,AR17,AR18) -> 1355268 | AT19: =SUM(AT15,AT17,AT18) -> 0 | AU19: =D19+AN19 -> -2295493 | AV19: =H19+AP19 -> -7267198 | AW19: =SUM(AW15,AW17,AW18) -> 0 | AX19: =SUM(AX15,AX17,AX18) -> -8473935 | AY19: =SUM(AY15,AY17,AY18) -> -6255413 | AZ19: =SUM(AZ15,AZ17,AZ18) -> -3826092 | BA19: =SUM(BA15,BA17,BA18) -> -11085797 | BB19: =SUM(BB15,BB17,BB18) -> 2679860 | BC19: =SUM(BC15,BC17,BC18) -> 4330102 | BD19: =SUM(BD15,BD17,BD18) -> -23127199 | BE19: -5820448
A20: Meituan reported Adjusted EBITDA | D20: -839675 | E20: -1358685 | F20: =AP20-G20 -> -1116486 | G20: -1590839 | H20: -1171905 | I20: -854601 | J20: 458874 | K20: 2330809 | L20: 2285301 | M20: 2178650 | N20: 41311 | O20: 2610255 | P20: 2675399 | Q20: -589128 | R20: -2382683 | S20: -1239986 | T20: -4061659 | U20: -2009748 | V20: -1840771 | W20: 3802741 | X20: 4801736 | Y20: 2960883 | Z20: 6262060 | AA20: 7682351 | AB20: 6189201 | AC20: 3744406 | AD20: 8070343 | AE20: 14997268 | AF20: 14529197 | AG20: 11522592 | AH20: 12301686 | AI20: 2781961 | AJ20: -14841897 | AK20: -14024955 | AL20: -3049429 | AM20: 4098050 | AN20: -493451 | AO20: =AZ20-AN20 -> -2198360 | AP20: -2707325 | AQ20: =BA20-AP20 -> -2026506 | AR20: 2789683 | AX20: -5693387 | AY20: -4998311 | AZ20: -2691811 | BA20: -4733831 | BB20: 7253634 | BC20: 4737837 | BD20: -9694076 | BE20: 9724589
T21: =T20/T5 -> -0.083180655 | W21: =W20/W5 -> 0.074653773 | X21: =X20/X5 -> 0.076681906 | Y21: =Y20/Y5 -> 0.049242229 | Z21: =Z20/Z5 -> 0.10682924 | AA21: =AA20/AA5 -> 0.11303455 | AB21: =AB20/AB5 -> 0.080939602 | AC21: =AC20/AC5 -> 0.050808843 | AD21: =AD20/AD5 -> 0.11013641 | ... AM21: =AM20/AM5 -> 0.039162183
A22: Finance income | D22: 11892 | E22: 36179 | F22: =AP22-G22 -> 47178 | G22: 61991 | H22: 68451 | I22: 116427 | J22: 52922 | K22: 21541 | L22: 38235 | M22: 53519 | N22: 57930 | O22: 40352 | P22: 45678 | Q22: 69724 | R22: 77855 | S22: 112118 | T22: 198890 | U22: 157174 | V22: 110359 | W22: 190412 | X22: 209746 | Y22: 147391 | Z22: 184419 | AA22: 217189 | AB22: 201225 | AC22: 216153 | AD22: 279755 | AE22: 344494 | AF22: 313088 | AG22: 354470 | AH22: 491358 | AI22: 508307 | AJ22: 513372 | AK22: 498498 | AL22: 481926 | AM22: 505919 | AN22: 12814 | AO22: =AZ22-AN22 -> 48071 | AP22: 109169 | AQ22: =BA22-AP22 -> 184878 | AR22: -74463 | AU22: =D22+AN22 -> 24706 | AV22: =H22+AP22 -> 177620 | AX22: 13541 | AY22: 21681 | AZ22: 60885 | BA22: 294047 | BB22: 166217 | BC22: 213684 | BD22: 546037 | BE22: 657908
A23: Finance costs | D23: -2768 | E23: -13200 | F23: =AP23-G23 -> -8412 | G23: -5427 | H23: -15486 | I23: -15407 | J23: -46821 | K23: -50115 | L23: -49011 | M23: -45095 | N23: -48044 | O23: -60731 | P23: -111506 | Q23: -149735 | R23: -166052 | S23: -263269 | T23: -369942 | U23: -331672 | V23: -330317 | W23: -418612 | X23: -474728 | Y23: -405168 | Z23: -353479 | AA23: -354003 | AB23: -350950 | AC23: -366725 | AD23: -321863 | AE23: -285373 | AF23: -261651 | AG23: -468151 | AH23: -475120 | AI23: -430214 | AJ23: -413987 | AK23: -567481 | AL23: -786977 | AM23: -806365 | AN23: -3246 | AO23: =AZ23-AN23 -> -15968 | AP23: -13839 | AQ23: =BA23-AP23 -> -30893 | AR23: -96936 | AU23: =D23+AN23 -> -6014 | AV23: =H23+AP23 -> -29325 | AX23: -56561 | AY23: -55981 | AZ23: -19214 | BA23: -44732 | BB23: -191042 | BC23: -370016 | BD23: -1130935 | BE23: -1628825
A24: Fair value changes of convertible redeemable preferred shares | D24: -3283180 | E24: -663781 | F24: =AP24-G24 -> -20213076 | G24: -4637019 | H24: -79755963 | I24: 0 | J24: 0 | K24: 0 | L24: 0 | M24: 0 | N24: 0 | O24: 0 | P24: 0 | Q24: 0 | AN24: -11191863 | AO24: =AZ24-AN24 -> -3946961 | AP24: -24850095 | AQ24: =BA24-AP24 -> -79755963 | AR24: 0 | AU24: =D24+AN24 -> -14475043 | AV24: =H24+AP24 -> -104606058 | AX24: -725113 | AY24: -4313365 | AZ24: -15138824 | BA24: -104606058 | BB24: 0
A25: Share of gains of investments accounted for using equity method | D25: -19727 | E25: -31263 | F25: =AP25-G25 -> -575 | G25: 7425 | H25: 1758 | I25: -56875 | J25: 7530 | K25: 17848 | L25: 24329 | M25: 57646 | N25: 11128 | O25: 42881 | P25: 92698 | Q25: 117398 | R25: 2013 | S25: 38251 | T25: 273237 | U25: -163855 | V25: 46411 | W25: -400052 | X25: 485362 | Y25: -95873 | Z25: -49759 | AA25: 122406 | AB25: 434521 | AC25: 705484 | AD25: 314197 | AE25: 341204 | AF25: 213821 | AG25: 316482 | AH25: 18453 | AI25: 89223 | AJ25: 9541 | AK25: -38325 | AL25: -502001 | AM25: -86573 | AN25: 40572 | AO25: =AZ25-AN25 -> -50990 | AP25: 6850 | AQ25: =BA25-AP25 -> -55117 | AR25: 25378 | AU25: =D25+AN25 -> 20845 | AV25: =H25+AP25 -> 8608 | AX25: -661 | AY25: -28018 | AZ25: -10418 | BA25: -48267 | BB25: 107353 | BC25: 264105 | BD25: 145620 | BE25: 35858
A27: Gain (Loss) before income tax | D27: =SUM(D19,D22,D23,D24,D25) -> -4339159 | E27: =SUM(E19,E22,E23,E24,E25) -> -2202664 | F27: =AP27-G27 -> 14320747 | G27: =SUM(G19,G22,G23,G24,G25) -> -7424447 | H27: =SUM(H19,H22,H23,H24,H25) -> -83068597 | I27: =SUM(I19,I22,I23,I24,I25) -> -3690373 | J27: =SUM(J19,J22,J23,J24,J25) -> -1290011 | K27: =SUM(K19,K22,K23,K24,K25) -> 1240563 | L27: =SUM(L19,L22,L23,L24,L25) -> 1572607 | M27: =SUM(M19,M22,M23,M24,M25) -> 1489930 | N27: =SUM(N19,N22,N23,N24,N25) -> -1694516 | ... Y27: =SUM(Y19,Y22,Y23,Y24,Y25) -> -1104408 | Z27: 3366902 | AA27: 4688619 | AB27: 3643329 | AC27: 3643329 | AD27: 5481481 | AE27: 11657214 | AF27: 13950434 | AG27: 6896300 | AH27: 10600801 | AI27: 393666 | AJ27: -19650424 | AK27: -16181555 | AL27: -7276863 | AM27: 2304147 | AN27: 6896300 | AO27: 6896300 | AP27: 6896300 | AQ27: 6896300 | AR27: 6896300 | AS27: 6896300 | AT27: 6896300 | AU27: 6896300 | AV27: 6896300 | AW27: 6896300 | AX27: =SUM(AX19,AX22,AX23,AX24,AX25) -> -9242729 | AY27: =SUM(AY19,AY22,AY23,AY24,AY25) -> -10631096 | AZ27: =SUM(AZ19,AZ22,AZ23,AZ24,AZ25) -> -18933663 | BA27: =SUM(BA19,BA22,BA23,BA24,BA25) -> -115490807 | BB27: =SUM(BB19,BB22,BB23,BB24,BB25) -> 2762388 | BC27: =SUM(BC19,BC22,BC23,BC24,BC25) -> 4437875 | BD27: =SUM(BD19,BD22,BD23,BD24,BD25) -> -23566477 | BE27: -6755517
A28: Income tax expenses | D28: -30746 | E28: 21846 | F28: =AP28-G28 -> 158503 | G28: -292034 | H28: -144478 | I28: 276121 | J28: -143319 | K28: -226024 | L28: -127235 | M28: -29645 | N28: 115238 | O28: 13034 | P28: -429552 | Q28: 571017 | R28: 10955 | S28: 8230 | T28: 6036 | U28: 5058 | V28: 55223 | W28: 5063 | X28: 8209 | Y28: 1699 | Z28: -8411 | AA28: -9972 | AB28: -50095 | AC28: -96059 | AD28: -112502 | AE28: -304876 | AF28: -1085480 | AG28: -674249 | AH28: -543921 | AI28: -28370 | AJ28: 1018336 | AK28: 1037273 | AL28: 449605 | AM28: -148925 | AN28: -45318 | AO28: =AZ28-AN28 -> -8900 | AP28: -133531 | AQ28: =BA28-AP28 -> 131643 | AR28: -369343 | AU28: =D28+AN28 -> -76064 | AV28: =H28+AP28 -> -278009 | AX28: 11648 | AY28: -267903 | AZ28: -54218 | BA28: -1888 | BB28: -526223 | BC28: 269737 | BD28: 30279 | BE28: 70194
A30: Loss for the year/period from contuning operations | D30: =SUM(D27,D28) -> -4369905 | E30: =SUM(E27,E28) -> -2180818 | F30: =AP30-G30 -> 14479250 | G30: =SUM(G27,G28) -> -7716481 | H30: =SUM(H27,H28) -> -83213075 | I30: =SUM(I27,I28) -> -3414252 | J30: =SUM(J27,J28) -> -1433330 | K30: =SUM(K27,K28) -> 1014539 | L30: =SUM(L27,L28) -> 1445372 | M30: =SUM(M27,M28) -> 1460285 | N30: =SUM(N27,N28) -> -1579278 | ... AC30: =SUM(AC27,AC28) -> 3547270 | AD30: 5368979 | AE30: 11352338 | AF30: 12864954 | AG30: 6222051 | AH30: =AH27+AH28 -> 10056880 | AI30: =AI27+AI28 -> 365296 | AJ30: -18632088 | AK30: -15144282 | AL30: -6827258 | AM30: 2155222 | AN30: =SUM(AN27,AN28) -> 6850982 | AO30: =AZ30-AN30 -> -25838863 | AP30: =SUM(AP27,AP28) -> 6762769 | AQ30: =SUM(AQ27,AQ28) -> 7027943 | AR30: =SUM(AR27,AR28) -> 6526957 | AT30: =SUM(AT27,AT28) -> 6896300 | AU30: =D30+AN30 -> 2481077 | AV30: =H30+AP30 -> -76450306 | AW30: =SUM(AW27,AW28) -> 6896300 | AX30: =SUM(AX27,AX28) -> -9231081 | AY30: =SUM(AY27,AY28) -> -10898999 | AZ30: =SUM(AZ27,AZ28) -> -18987881 | BA30: =SUM(BA27,BA28) -> -115492695 | BB30: =SUM(BB27,BB28) -> 2236165 | BC30: =SUM(BC27,BC28) -> 4707612 | BD30: =SUM(BD27,BD28) -> -23536198 | BE30: -6685323
A31: (Loss)/profit from discontuning operation | AX31: -1288257 | AY31: 5104001
A33: Gain (Loss) for the period | D33: =SUM(D30,D31) -> -4369905 | E33: =SUM(E30,E31) -> -2180818 | F33: =AP33-G33 -> 14479250 | G33: =SUM(G30,G31) -> -7716481 | H33: =SUM(H30,H31) -> -83213075 | I33: =SUM(I30,I31) -> -3414252 | J33: =SUM(J30,J31) -> -1433330 | K33: =SUM(K30,K31) -> 1014539 | L33: =SUM(L30,L31) -> 1445372 | M33: =SUM(M30,M31) -> 1460285 | N33: =SUM(N30,N31) -> -1579278 | ... AC33: =SUM(AC30,AC31) -> 3547270 | AD33: 5368979 | AE33: 11352338 | AF33: 12864954 | AG33: 6222051 | AH33: =AH30 -> 10056880 | AI33: =AI30 -> 365296 | AJ33: =AJ30 -> -18632088 | AK33: -15144282 | AL33: -6827258 | AM33: 2155222 | AN33: =SUM(AN30,AN31) -> 6850982 | AO33: =SUM(AO30,AO31) -> -25838863 | AP33: =SUM(AP30,AP31) -> 6762769 | AQ33: =SUM(AQ30,AQ31) -> 7027943 | AR33: =SUM(AR30,AR31) -> 6526957 | AS33: =SUM(AS30,AS31) -> 0 | AT33: =SUM(AT30,AT31) -> 6896300 | AU33: =SUM(AU30,AU31) -> 2481077 | ... BC33: =SUM(BC30,BC31) -> 4707612 | BD33: -23536198 | BE33: -6685323
A34: Loss for the period attributable to:
A35: Equity holders of the Company | D35: -4351661 | F35: =AP35-G35 -> -21051147 | G35: -7705707 | H35: -83295010 | J35: -1431777 | K35: 877415 | L35: 1335202 | M35: =BB35-SUM(J35:L35) -> 1457929 | N35: -1578336 | O35: 2209747 | P35: 6321603 | Q35: =BC35-SUM(N35:P35) -> -2244701 | R35: -4847283 | S35: -3357323 | T35: -9994660 | U35: =U33-U36 -> -5339113 | V35: =V33-V36 -> -5702489 | W35: =W33-W36 -> -1116519 | X35: 1216442 | Y35: -1083544 | Z35: 3358233 | AK35: -23355015 | AN35: -12403508 | AP35: -28756854 | AR35: -554362 | AU35: =D35+AN35 -> -16755169 | AV35: =H35+AP35 -> -112051864 | AX35: -10519338 | AY35: -5789900 | AZ35: -18916617 | BA35: -115477171 | BB35: 2238769 | BC35: 4708313 | BD35: -23538379 | BE35: -6686110
A36: Non-controlling interests | D36: -18244 | F36: =AP36-G36 -> -122757 | G36: -10774 | H36: -2146 | J36: -1553 | K36: -1587 | L36: -1820 | M36: =BB36-SUM(J36:L36) -> 2320 | N36: -942 | O36: 434 | P36: -602 | Q36: =BC36-SUM(N36:P36) -> 409 | R36: 1021 | S36: 948 | T36: 250 | U36: =BD36-R36-S36-T36 -> -38 | V36: -77 | W36: 492 | X36: 369 | Y36: 3 | Z36: 258 | AK36: 821 | AN36: -33650 | AP36: -133531 | AR36: -369343 | AU36: =D36+AN36 -> -51894 | AV36: =H36+AP36 -> -135677 | AX36: 0 | AY36: -5098 | AZ36: -71264 | BA36: -15524 | BB36: -2640 | BC36: -701 | BD36: 2181 | BE36: 787
A37: Fair value (gains)/losses on investments | D37: -547092 | F37: =AP37-G37 -> -475274 | G37: -715216 | H37: -340553 | I37: 984359 | J37: -211158 | K37: 278157 | L37: 163615 | M37: 72443 | N37: 508261 | O37: -347393 | P37: -5779364 | Q37: -191031 | R37: 42034 | S37: 164748 | T37: -580615 | U37: -471908 | V37: -575657 | W37: -292183 | X37: -533376 | Y37: 390604 | Z37: 113490 | AA37: 103761 | AB37: -95835 | AC37: -98933 | AD37: 359322 | AE37: -62507 | AF37: -567679 | AG37: 78069 | AH37: -777438 | AI37: -355455 | AJ37: 335243 | AK37: -1537272 | AL37: 389746 | AM37: -1604473 | AN37: 291045 | AP37: -1190490 | AR37: 66999 | AU37: =D37+AN37 -> -256047 | AV37: =H37+AP37 -> -1531043 | AX37: -46953 | AY37: 25789 | AZ37: -541731 | BA37: -1834296 | BB37: -169059 | BC37: -5809527 | BD37: -1247255 | BE37: 193472
A38: Non-GAAP Loss for the period attributable to Equity holders of the Company - comparable to Ctrip | D38: =D35+D37-D12 -> -4667531 | F38: =AP38-G38 -> -21231743 | G38: =G35+G37-G12 -> -8033343 | H38: =H35+H37-H12 -> -83095931 | J38: =J35+J37-J12 -> -1204867 | K38: =K35+K37-K12 -> 1671073 | L38: =L35+L37-L12 -> 2035986 | M38: =M35+M37-M12 -> 2230505 | N38: =N35+N37-N12 -> -378399 | O38: =O35+O37-O12 -> 2567774 | P38: =P35+P37-P12 -> 1380948 | Q38: =Q35+Q37-Q12 -> -1394061 | ... AV38: =AV35+AV37-AV12 -> -112361017 | AX38: =AX35+AX37-AX12 -> -7966913 | AY38: =AY35+AY37-AY12 -> -4851036 | AZ38: =AZ35+AZ37-AZ12 -> -18487248 | BA38: =BA35+BA37-BA12 -> -115446354 | BB38: =BB35+BB37-BB12 -> 4260581 | BC38: =BC35+BC37-BC12 -> 2176262 | BD38: =BD35+BD37-BD12 -> -19591774 | BE38: =BE35+BE37-BE12 -> -6024018
A39: EPS to equity shareholoders
A40: Basic EPS | AN40: -8.21 | AP40: -18.53 | AR40: -0.1 | AX40: -9.89 | AY40: -3.98 | AZ40: -12.37 | BA40: -42.4 | BB40: 0.39 | BC40: 0.81 | BD40: -3.9 | BE40: -1.09
A41: Diluted EPS | AN41: -8.21 | AP41: -18.53 | AR41: -0.1 | AX41: -9.89 | AY41: -3.98 | AZ41: -12.37 | BA41: -42.4 | BB41: 0.38 | BC41: 0.78 | BD41: -3.9 | BE41: -1.09
A43: YoY Growth | AP43: =IFERROR(AN5/#REF!-1,"")
A44: Revenues | H44: =H5/D5-1 -> 0.97192488 | I44: =I5/E5-1 -> 0.89047612 | J44: =J5/F5-1 -> 0.70052371 | K44: =K5/G5-1 -> 0.50623582 | L44: =L5/H5-1 -> 0.44126811 | M44: =M5/I5-1 -> 0.42188609 | N44: =N5/J5-1 -> -0.12619623 | O44: =O5/K5-1 -> 0.088917228 | ... AM44: =AM5/AI5-1 -> 0.13940001 | AN44: =AN5/N5-1 -> -0.17757515 | AO44: =AO5/O5-1 -> -0.18496453 | AP44: =AP5/P5-1 -> -0.25573805 | AQ44: =AQ5/Q5-1 -> 0.025369471 | AR44: =AR5/AN5-1 -> 2.0392058 | AS44: =AS5/AO5-1 -> -1 | AT44: =AT5/AP5-1 -> -1 | AU44: =AU5/AQ5-1 -> -0.39678652 | AV44: =AV5/AR5-1 -> 0.084705369 | AW44: =AW5/AS5-1 -> #DIV/0! | AY44: =AY5/AX5-1 -> 2.2317018 | AZ44: =AZ5/AY5-1 -> 1.612241 | BA44: =BA5/AZ5-1 -> 0.92252131 | BB44: =BB5/BA5-1 -> 0.49521081 | BC44: =BC5/BB5-1 -> 0.17703516 | BD44: =BD5/BC5-1 -> 0.56042303 | BE44: =BE5/BD5-1 -> 0.22792055
A45: Revenues Yo2Y | R45: =R5/J5-1 -> 0.93059373 | S45: =S5/K5-1 -> 0.92745311 | T45: =T5/L5-1 -> 0.77602491 | U45: =U5/M5-1 -> 0.75874309 | V45: =V5/J5-1 -> 1.4131601 | W45: =W5/K5-1 -> 1.2436707 | X45: =X5/L5-1 -> 1.2775783 | Y45: =Y5/M5-1 -> 1.1353931 | Z45: =Z5/J5-1 -> 2.057211 | AA45: =AA5/K5-1 -> 1.9936226 | AB45: =AB5/L5-1 -> 1.7812591 | AC45: =AC5/M5-1 -> 1.6172061 | AD45: =AD5/J5-1 -> 2.8217247 | AE45: =AE5/K5-1 -> 2.6228948 | AF45: =AF5/L5-1 -> 2.4036001 | AG45: =AG5/M5-1 -> 2.1424995 | AH45: =AH5/J5-1 -> 3.5144117 | AI45: =AI5/K5-1 -> 3.0452771 | AJ45: =AJ5/L5-1 -> 2.4730996 | AK45: =AK5/M5-1 -> 2.2706727 | AL45: =AL5/N5-1 -> 4.4338976 | AM45: =AM5/O5-1 -> 3.2328183 | BD45: =BD5/BB5-1 -> 0.83667277 | BE45: =BE5/BC5-1 -> 0.9160755
A46: Revenuea QoQ Growth | E46: =E5/D5-1 -> 0.082861164 | F46: =F5/E5-1 -> 0.076339489 | G46: =G5/F5-1 -> 0.33682304 | H46: =H5/G5-1 -> 0.26559395 | I46: =I5/H5-1 -> 0.038134464 | J46: =J5/I5-1 -> -0.031809606 | K46: =K5/J5-1 -> 0.1840886 | L46: =L5/K5-1 -> 0.21100573 | ... AM46: =AM5/AL5-1 -> 0.14943213 | AN46: =AN5/Q5-1 -> -0.63661076 | AO46: =AO5/AN5-1 -> 0.46233017 | AP46: =AP5/AO5-1 -> 0.30763807 | AQ46: =AQ5/AP5-1 -> 0.47562268 | AR46: =AR5/AQ5-1 -> 0.077089514 | AS46: =AS5/AR5-1 -> -1 | AT46: =AT5/AS5-1 -> #DIV/0! | AU46: =AU5/AT5-1 -> #DIV/0! | AV46: =AV5/AU5-1 -> 0.93683466 | AW46: =AW5/AV5-1 -> -1
A47: Gross Profit | H47: =H8/D8-1 -> 0.33151332 | I47: =I8/E8-1 -> 0.3370079 | J47: =J8/F8-1 -> 0.57826358 | K47: =K8/G8-1 -> 1.7952601 | L47: =L8/H8-1 -> 1.0983982 | M47: =M8/I8-1 -> 1.168744 | N47: =N8/J8-1 -> 0.025077426 | O47: =O8/K8-1 -> 0.079883158 | ... AM47: =AM8/AI8-1 -> 0.1539026 | AN47: =AN8/N8-1 -> 0.045879642 | AO47: =AO8/O8-1 -> -0.2087861 | AP47: =AP8/P8-1 -> -0.44075414 | AQ47: =AQ8/Q8-1 -> -0.042669883 | AR47: =AR8/AN8-1 -> 1.3937934 | AS47: =AS8/AO8-1 -> -1 | AT47: =AT8/AP8-1 -> -1 | AU47: =AU8/AQ8-1 -> -0.020352985 | AV47: =AV8/AR8-1 -> -0.18339858 | AW47: =AW8/AS8-1 -> #DIV/0! | AY47: =AY8/AX8-1 -> 1.1375543 | AZ47: =AZ8/AY8-1 -> 1.0567276 | BA47: =BA8/AZ8-1 -> 0.23613512 | BB47: =BB8/BA8-1 -> 1.1397205 | BC47: =BC8/BB8-1 -> 0.053518974 | BD47: =BD8/BC8-1 -> 0.24739944 | BE47: =BE8/BD8-1 -> 0.45389633
A48: Selling and marketing expenses | H48: =H9/D9-1 -> 0.45191858 | I48: =I9/E9-1 -> 0.34882276 | J48: =J9/F9-1 -> 0.30205635 | K48: =K9/G9-1 -> 0.072612022 | L48: =L9/H9-1 -> 0.2147178 | M48: =M9/I9-1 -> 0.17950052 | N48: =N9/J9-1 -> -0.13671281 | O48: =O9/K9-1 -> 0.0055968629 | ... AM48: =AM9/AI9-1 -> 0.097892469 | AN48: =AN9/N9-1 -> 0.36364563 | AO48: =AO9/O9-1 -> 0.56885574 | AP48: =AP9/P9-1 -> 0.1506294 | AQ48: =AQ9/Q9-1 -> 0.19308304 | AR48: =AR9/AN9-1 -> 0.80045846 | AS48: =AS9/AO9-1 -> -1 | AT48: =AT9/AP9-1 -> -1 | AU48: =AU9/AQ9-1 -> -0.17590947 | AV48: =AV9/AR9-1 -> 0.44322465 | AW48: =AW9/AS9-1 -> #DIV/0! | AY48: =AY9/AX9-1 -> 0.16750824 | AZ48: =AZ9/AY9-1 -> 0.30844612 | BA48: =BA9/AZ9-1 -> 0.454978 | BB48: =BB9/BA9-1 -> 0.1856845 | BC48: =BC9/BB9-1 -> 0.1096557 | BD48: =BD9/BC9-1 -> 0.94817697 | BE48: =BE9/BD9-1 -> -0.023036236
A49: Research and development expenses | H49: =H10/D10-1 -> 0.95084943 | I49: =I10/E10-1 -> 0.72437508 | J49: =J10/F10-1 -> 0.4725111 | K49: =K10/G10-1 -> 0.19279602 | L49: =L10/H10-1 -> 0.066809184 | M49: =M10/I10-1 -> 0.13021274 | N49: =N10/J10-1 -> 0.12787093 | O49: =O10/K10-1 -> 0.16946411 | ... AM49: =AM10/AI10-1 -> 0.22522978 | AN49: =AN10/N10-1 -> -0.35973312 | AO49: =AO10/O10-1 -> -0.084337897 | AP49: =AP10/P10-1 -> 0.039209527 | AQ49: =AQ10/Q10-1 -> 0.22655553 | AR49: =AR10/AN10-1 -> 1.7669882 | AS49: =AS10/AO10-1 -> -1 | AT49: =AT10/AP10-1 -> -1 | AU49: =AU10/AQ10-1 -> -0.37336748 | AV49: =AV10/AR10-1 -> 0.25111505 | AW49: =AW10/AS10-1 -> #DIV/0! | AY49: =AY10/AX10-1 -> 0.9656222 | AZ49: =AZ10/AY10-1 -> 0.54082649 | BA49: =BA10/AZ10-1 -> 0.93929525 | BB49: =BB10/BA10-1 -> 0.19425671 | BC49: =BC10/BB10-1 -> 0.28971671 | BD49: =BD10/BC10-1 -> 0.53092252 | BE49: =BE10/BD10-1 -> 0.24372564
A50: General and administrative expenses | H50: =H11/D11-1 -> 1.360712 | I50: =I11/E11-1 -> 2.1123714 | J50: =J11/F11-1 -> 0.61130468 | K50: =K11/G11-1 -> 0.04224812 | L50: =L11/H11-1 -> -0.14706391 | M50: =M11/I11-1 -> -0.45030428 | N50: =N11/J11-1 -> 0.21585892 | O50: =O11/K11-1 -> 0.15936658 | ... AM50: =AM11/AI11-1 -> 0.20870864 | AN50: =AN11/N11-1 -> -0.43965308 | AO50: =AO11/O11-1 -> 0.19531006 | AP50: =AP11/P11-1 -> 0.076411734 | AQ50: =AQ11/Q11-1 -> 1.0787685 | AR50: =AR11/AN11-1 -> 1.7992101 | AS50: =AS11/AO11-1 -> -1 | AT50: =AT11/AP11-1 -> -1 | AU50: =AU11/AQ11-1 -> -0.69843897 | AV50: =AV11/AR11-1 -> 0.41502825 | AW50: =AW11/AS11-1 -> #DIV/0! | AY50: =AY11/AX11-1 -> -0.40710637 | AZ50: =AZ11/AY11-1 -> 0.26053738 | BA50: =BA11/AZ11-1 -> 1.6856731 | BB50: =BB11/BA11-1 -> -0.14524995 | BC50: =BC11/BB11-1 -> 0.21605296 | BD50: =BD11/BC11-1 -> 0.4637391 | BE50: =BE11/BD11-1 -> 0.10134945
A51: Operating Income (Loss)
A52: Non-GAAP Operating Income(Loss) - comparable to Ctrip | H52: =H16/D16-1 -> 1.5712923 | I52: =I16/E16-1 -> 1.043296 | J52: =J16/F16-1 -> -0.057368267 | K52: =K16/G16-1 -> -1.3701849 | L52: =L16/H16-1 -> -1.4799921 | M52: =M16/I16-1 -> -1.2983915 | N52: =N16/J16-1 -> -0.30149611 | O52: =O16/K16-1 -> 0.23547676 | ... AM52: =AM16/AI16-1 -> 3.0234199 | AN52: =AN16/N16-1 -> -0.069962122 | AO52: =AO16/O16-1 -> -2.7577964 | AP52: =AP16/P16-1 -> -4.6087272 | AQ52: =AQ16/Q16-1 -> 1.9090918 | AR52: =AR16/AN16-1 -> -0.98752203 | AS52: =AS16/AO16-1 -> -1 | AT52: =AT16/AP16-1 -> -1 | AU52: =AU16/AQ16-1 -> -0.728416 | AV52: =AV16/AR16-1 -> 703.64272 | AW52: =AW16/AS16-1 -> #DIV/0! | AY52: =AY16/AX16-1 -> -0.051005334 | AZ52: =AZ16/AY16-1 -> -0.3653872 | BA52: =BA16/AZ16-1 -> 2.3385185 | BB52: =BB16/BA16-1 -> -1.1915975 | BC52: =BC16/BB16-1 -> -1.2251065 | BD52: =BD16/BC16-1 -> 35.45835 | BE52: =BE16/BD16-1 -> -0.56710108
A53: Meituan reported Adjusted EBITDA | H53: =1-H20/D20 -> -0.39566499 | I53: =1-I20/E20 -> 0.37100873 | J53: =1-J20/F20 -> 1.4109984 | K53: =1-K20/G20 -> 2.4651445 | L53: =1-L20/H20 -> 2.9500736 | M53: =1-M20/I20 -> 3.5493183 | N53: =1-N20/J20 -> 0.90997311 | O53: =1-O20/K20 -> -0.11989228 | ... AM53: =1-AM20/AI20 -> -0.4730796 | AN53: =1-AN20/N20 -> 12.944785 | AO53: =1-AO20/O20 -> 1.8422012 | AP53: =1-AP20/P20 -> 2.0119332 | AQ53: =1-AQ20/Q20 -> -2.4398399 | AR53: =1-AR20/AN20 -> 6.6534144 | AS53: =1-AS20/AO20 -> 1 | AT53: =1-AT20/AP20 -> 1 | AU53: =1-AU20/AQ20 -> 1 | AV53: =1-AV20/AR20 -> 1 | AW53: =1-AW20/AS20 -> #DIV/0! | AY53: =AY20/AX20-1 -> -0.1220848 | AZ53: =AZ20/AY20-1 -> -0.46145588 | BA53: =BA20/AZ20-1 -> 0.75860452 | BB53: =BB20/BA20-1 -> -2.5322968 | BC53: =BC20/BB20-1 -> -0.34683264 | BD53: =BD20/BC20-1 -> -3.0460974 | BE53: =BE20/BD20-1 -> -2.0031476
A54: Gain (Loss) for the period | H54: =H33/D33-1 -> 18.042308 | I54: =I33/E33-1 -> 0.56558319 | J54: =J33/F33-1 -> -1.098992 | K54: =K33/G33-1 -> -1.1314769 | L54: =L33/H33-1 -> -1.0173695 | M54: =M33/I33-1 -> -1.4277028 | N54: =N33/J33-1 -> 0.10182442 | O54: =O33/K33-1 -> 1.1785077 | ... AM54: =AM33/AI33-1 -> 4.8999332 | AN54: =AN33/O33-1 -> 2.099738 | AO54: =AO33/P33-1 -> -5.0877802 | AP54: =AP33/Q33-1 -> -4.0133196 | AQ54: =AQ33/R33-1 -> -2.4513838 | AR54: =AR33/AN33-1 -> -0.047296139 | AS54: =AS33/AO33-1 -> -1 | AT54: =AT33/AP33-1 -> 0.019745019 | AU54: =AU33/AQ33-1 -> -0.64696968 | AV54: =AV33/AR33-1 -> -12.713009 | AW54: =AW33/AS33-1 -> #DIV/0!
A55: Non-GAAP Loss for the period attributable to Equity holders of the Company | H55: =H38/D38-1 -> 16.802974 | AP55: =AP38/AN38-1 -> 1.4732629 | AR55: =AR38/AP38-1 -> -1.0159305 | AV55: =AV38/AU38-1 -> 5.809712 | AY55: =AY38/AX38-1 -> -0.39110217 | AZ55: =AZ38/AY38-1 -> 2.8109897 | BA55: =BA38/AZ38-1 -> 5.2446479 | BB55: =BB38/BA38-1 -> -1.0369053 | BC55: =BC38/BB38-1 -> -0.48921004 | BD55: =BD38/BC38-1 -> -10.002489 | BE55: =BE38/BD38-1 -> -0.6925231
A57: Margins and Ratios
A58: Gross Margin | D58: =IFERROR(D8/D5,"") -> 0.3548883 | E58: =IFERROR(E8/E5,"") -> 0.31994158 | F58: =IFERROR(F8/F5,"") -> 0.28487406 | G58: =IFERROR(G8/G5,"") -> 0.18846908 | H58: =IFERROR(H8/H5,"") -> 0.23963311 | I58: =IFERROR(I8/I5,"") -> 0.22627338 | J58: =IFERROR(J8/J5,"") -> 0.26439288 | K58: =IFERROR(K8/K5,"") -> 0.34975937 | ... AR58: =IFERROR(AR8/AR5,"") -> 0.31067374 | AT58: =IFERROR(AT8/AT5,"") | AU58: =IFERROR(AU8/AU5,"") -> 0.37812403 | AV58: =IFERROR(AV8/AV5,"") -> 0.23388527 | AW58: =IFERROR(AW8/AW5,"") | AX58: =IFERROR(AX8/AX5,"") -> 0.69158581 | AY58: =IFERROR(AY8/AY5,"") -> 0.45743769 | AZ58: =IFERROR(AZ8/AZ5,"") -> 0.36016001 | BA58: =IFERROR(BA8/BA5,"") -> 0.23157425 | ... BE58: =IFERROR(BE8/BE5,"") -> 0.28075285
A59: Opex as % of revenue
A60: Selling and marketing expenses | D60: =IFERROR(-D9/D5,"") -> 0.32909088 | E60: =IFERROR(-E9/E5,"") -> 0.32096493 | F60: =IFERROR(-F9/F5,"") -> 0.25244675 | G60: =IFERROR(-G9/G5,"") -> 0.25663707 | H60: =IFERROR(-H9/H5,"") -> 0.24230799 | I60: =IFERROR(-I9/I5,"") -> 0.22900305 | J60: =IFERROR(-J9/J5,"") -> 0.19329333 | K60: =IFERROR(-K9/K5,"") -> 0.18275492 | ... AM60: =IFERROR(-AM9/AM5,"") -> 0.23626363 | AN60: =IFERROR(-AN9/$AN$5,"") -> 0.31663838 | AO60: =IFERROR(-AO9/$AN$5,"") -> 0.47506175 | AP60: =IFERROR(-AP9/AP5,"") -> 0.2548439 | AQ60: =IFERROR(-AQ9/AQ5,"") -> 0.23553105 | AR60: =IFERROR(-AR9/AR5,"") -> 0.18758 | AT60: =IFERROR(-AT9/AT5,"") | AU60: =IFERROR(-AU9/AU5,"") -> 0.32177482 | AV60: =IFERROR(-AV9/AV5,"") -> 0.24957937 | AW60: =IFERROR(-AW9/AW5,"") | AX60: =IFERROR(-AX9/AX5,"") -> 1.7768188 | AY60: =IFERROR(-AY9/AY5,"") -> 0.64190657 | AZ60: =IFERROR(-AZ9/AZ5,"") -> 0.32152476 | BA60: =IFERROR(-BA9/BA5,"") -> 0.24333226 | ... BE60: =IFERROR(-BE9/BE5,"") -> 0.18070055
A61: Research and development expenses | D61: =IFERROR(-D10/D5,"") -> 0.10616174 | E61: =IFERROR(-E10/E5,"") -> 0.10971451 | F61: =IFERROR(-F10/F5,"") -> 0.12263701 | G61: =IFERROR(-G10/G5,"") -> 0.11304078 | H61: =IFERROR(-H10/H5,"") -> 0.10502711 | I61: =IFERROR(-I10/I5,"") -> 0.10007477 | J61: =IFERROR(-J10/J5,"") -> 0.10619338 | K61: =IFERROR(-K10/K5,"") -> 0.089517585 | ... AM61: =IFERROR(-AM10/AM5,"") -> 0.073297227 | AN61: =IFERROR(-AN10/$AN$5,"") -> 0.10671064 | AO61: =IFERROR(-AO10/$AN$5,"") -> 0.15794452 | AP61: =IFERROR(-AP10/AP5,"") -> 0.11714731 | AQ61: =IFERROR(-AQ10/AQ5,"") -> 0.10250461 | AR61: =IFERROR(-AR10/AR5,"") -> 0.097152712 | AT61: =IFERROR(-AT10/$AN$5,"") -> 0 | AU61: =IFERROR(-AU10/AU5,"") -> 0.10648423 | AV61: =IFERROR(-AV10/AV5,"") -> 0.11205736 | AW61: =IFERROR(-AW10/$AN$5,"") -> 0 | AX61: =IFERROR(-AX10/$AN$5,"") -> 0.087382926 | AY61: =IFERROR(-AY10/$AN$5,"") -> 0.17176182 | AZ61: =IFERROR(-AZ10/$AN$5,"") -> 0.26465516 | BA61: =IFERROR(-BA10/$AN$5,"") -> 0.5132445 | BB61: =IFERROR(-BB10/$AN$5,"") -> 0.61294569 | BC61: =IFERROR(-BC10/$AN$5,"") -> 0.7905263 | BD61: =IFERROR(-BD10/$AN$5,"") -> 1.2102345 | BE61: =IFERROR(-BE10/$AN$5,"") -> 1.5051997
A62: General and administrative expenses | D62: =IFERROR(-D11/D5,"") -> 0.054211914 | E62: =IFERROR(-E11/E5,"") -> 0.08729432 | F62: =IFERROR(-F11/F5,"") -> 0.05918202 | G62: =IFERROR(-G11/G5,"") -> 0.066093385 | H62: =IFERROR(-H11/H5,"") -> 0.064900402 | I62: =IFERROR(-I11/I5,"") -> 0.14371636 | J62: =IFERROR(-J11/J5,"") -> 0.056076998 | K62: =IFERROR(-K11/K5,"") -> 0.04573368 | ... AM62: =IFERROR(-AM11/AM5,"") -> 0.030943958 | AN62: =IFERROR(-AN11/$AN$5,"") -> 0.053163651 | AO62: =IFERROR(-AO11/$AN$5,"") -> 0.1044267 | AP62: =IFERROR(-AP11/AP5,"") -> 0.063135795 | AQ62: =IFERROR(-AQ11/AQ5,"") -> 0.10720833 | AR62: =IFERROR(-AR11/AR5,"") -> 0.048965499 | AT62: =IFERROR(-AT11/$AN$5,"") -> 0 | AU62: =IFERROR(-AU11/AU5,"") -> 0.053596041 | AV62: =IFERROR(-AV11/AV5,"") -> 0.063876852 | AW62: =IFERROR(-AW11/$AN$5,"") -> 0 | AX62: =IFERROR(-AX11/$AN$5,"") -> 0.21086141 | AY62: =IFERROR(-AY11/$AN$5,"") -> 0.12501839 | AZ62: =IFERROR(-AZ11/$AN$5,"") -> 0.15759035 | BA62: =IFERROR(-BA11/$AN$5,"") -> 0.42323617 | BB62: =IFERROR(-BB11/$AN$5,"") -> 0.36176113 | BC62: =IFERROR(-BC11/$AN$5,"") -> 0.4399207 | BD62: =IFERROR(-BD11/$AN$5,"") -> 0.64392913 | BE62: =IFERROR(-BE11/$AN$5,"") -> 0.70919099
A63: Operating Margin (Comparable to Ctrip) | D63: =IFERROR(D15/D5,"") -> -0.13457623 | E63: =IFERROR(E15/E5,"") -> -0.19803219 | F63: =IFERROR(F15/F5,"") -> -0.14939172 | G63: =IFERROR(G15/G5,"") -> -0.24730215 | H63: =IFERROR(H15/H5,"") -> -0.17260239 | I63: =IFERROR(I15/I5,"") -> -0.24652081 | J63: =IFERROR(J15/J5,"") -> -0.09117083 | K63: =IFERROR(K15/K5,"") -> 0.031753189 | ... AR63: =IFERROR(AR15/AR5,"") -> -0.023024478 | AT63: =IFERROR(AT15/AT5,"") | AU63: =IFERROR(AU15/AU5,"") -> -0.10373106 | AV63: =IFERROR(AV15/AV5,"") -> -0.19162831 | AW63: =IFERROR(AW15/AW5,"") | AX63: =IFERROR(AX15/AX5,"") -> -2.1077498 | AY63: =IFERROR(AY15/AY5,"") -> -0.49931757 | AZ63: =IFERROR(AZ15/AZ5,"") -> -0.13284684 | BA63: =IFERROR(BA15/BA5,"") -> -0.2095831 | ... BE63: =IFERROR(BE15/BE5,"") -> -0.038665532
A64: Non-GAAP Operating Margin (Comparable to Ctrip) | D64: =IFERROR(D16/D5,"") -> -0.11067434 | E64: =IFERROR(E16/E5,"") -> -0.19803219 | F64: =IFERROR(F16/F5,"") -> -0.12325634 | G64: =IFERROR(G16/G5,"") -> -0.22158822 | H64: =IFERROR(H16/H5,"") -> -0.14431386 | I64: =IFERROR(I16/I5,"") -> -0.21404046 | J64: =IFERROR(J16/J5,"") -> -0.068323268 | K64: =IFERROR(K16/K5,"") -> 0.054459346 | ... AR64: =IFERROR(AR16/AR5,"") -> -0.00025357807 | AT64: =IFERROR(AT16/AT5,"") | AU64: =IFERROR(AU16/AU5,"") -> -0.081938048 | AV64: =IFERROR(AV16/AV5,"") -> -0.16472855 | AW64: =IFERROR(AW16/AW5,"") | AX64: =IFERROR(AX16/AX5,"") -> -1.4609709 | AY64: =IFERROR(AY16/AY5,"") -> -0.42901655 | AZ64: =IFERROR(AZ16/AZ5,"") -> -0.10422446 | BA64: =IFERROR(BA16/BA5,"") -> -0.18098903 | ... BE64: =IFERROR(BE16/BE5,"") -> -0.036535004
A65: Operating Margin (MT version) | D65: =IFERROR(D19/D5,"") -> -0.10806265 | E65: =IFERROR(E19/E5,"") -> -0.14611396 | F65: =IFERROR(F19/F5,"") -> -0.092986088 | G65: =IFERROR(G19/G5,"") -> -0.18917678 | H65: =IFERROR(H19/H5,"") -> -0.17652323 | I65: =IFERROR(I19/I5,"") -> -0.18857914 | J65: =IFERROR(J19/J5,"") -> -0.067991821 | K65: =IFERROR(K19/K5,"") -> 0.055115247 | ... AR65: =IFERROR(AR19/AR5,"") -> 0.032363335 | AT65: =IFERROR(AT19/AT5,"") | AU65: =IFERROR(AU19/AU5,"") -> -0.097877938 | AV65: =IFERROR(AV19/AV5,"") -> -0.15998648 | AW65: =IFERROR(AW19/AW5,"") | AX65: =IFERROR(AX19/AX5,"") -> -2.10849 | AY65: =IFERROR(AY19/AY5,"") -> -0.48162734 | AZ65: =IFERROR(AZ19/AZ5,"") -> -0.11277097 | BA65: =IFERROR(BA19/BA5,"") -> -0.16995646 | ... BE65: =IFERROR(BE19/BE5,"") -> -0.026462001
A66: Meituan reported adjusted EBITDA Margin | D66: =IFERROR(D20/D5,"") -> -0.086798915 | E66: =IFERROR(E20/E5,"") -> -0.12970272 | F66: =IFERROR(F20/F5,"") -> -0.099022595 | G66: =IFERROR(G20/G5,"") -> -0.10554395 | H66: =IFERROR(H20/H5,"") -> -0.06143348 | I66: =IFERROR(I20/I5,"") -> -0.043154143 | J66: =IFERROR(J20/J5,"") -> 0.023932705 | K66: =IFERROR(K20/K5,"") -> 0.10266462 | ... AR66: =IFERROR(AR20/AR5,"") -> 0.066616672 | AT66: =IFERROR(AT20/AT5,"") | AU66: =IFERROR(AU20/AU5,"") -> 0 | AV66: =IFERROR(AV20/AV5,"") -> 0 | AW66: =IFERROR(AW20/AW5,"") | AX66: =IFERROR(AX20/AX5,"") -> -1.4166323 | AY66: =IFERROR(AY20/AY5,"") -> -0.38483842 | AZ66: =IFERROR(AZ20/AZ5,"") -> -0.079338954 | BA66: =IFERROR(BA20/BA5,"") -> -0.072574407 | ... BE66: =IFERROR(BE20/BE5,"") -> 0.044211731
A67: Net Margin to equity shareholders | D67: =IFERROR(D35/D5,"") -> -0.44984006 | F67: =IFERROR(F35/F5,"") -> -1.8670536 | G67: =IFERROR(G35/G5,"") -> -0.51123384 | H67: =IFERROR(H35/H5,"") -> -4.3664822 | L67: =IFERROR(L35/L5,"") -> 0.048564051 | M67: =IFERROR(M35/M5,"") -> 0.051776259 | N67: =IFERROR(N35/N5,"") -> -0.094207153 | O67: =IFERROR(O35/O5,"") -> 0.089384418 | P67: =IFERROR(P35/P5,"") -> 0.17856989 | Q67: =IFERROR(Q35/Q5,"") -> -0.059199598 | R67: =IFERROR(R35/R5,"") -> -0.13095009 | S67: =IFERROR(S35/S5,"") -> -0.076722622 | ... AC67: =IFERROR(AC35/AC5,"") -> 0 | AN67: =IFERROR(AN35/AN5,"") -> -0.90018698 | AO67: =IFERROR(AO35/AO5,"") -> 0 | AP67: =IFERROR(AP35/AP5,"") -> -1.0914317 | AQ67: =IFERROR(AQ35/AQ5,"") -> 0 | AR67: =IFERROR(AR35/AR5,"") -> -0.013237974 | AT67: =IFERROR(AT35/AT5,"") | AU67: =IFERROR(AU35/AU5,"") -> -0.71442666 | AV67: =IFERROR(AV35/AV5,"") -> -2.4668081 | AW67: =IFERROR(AW35/AW5,"") | AX67: =IFERROR(AX35/AX5,"") -> -2.6174285 | AY67: =IFERROR(AY35/AY5,"") -> -0.44578578 | AZ67: =IFERROR(AZ35/AZ5,"") -> -0.557552 | BA67: =IFERROR(BA35/BA5,"") -> -1.7703816 | ... BE67: =IFERROR(BE35/BE5,"") -> -0.030397634
A69: Balance Sheet
A70: Cash and cash equivalents | C70: 19408839 | E70: 19408839 | G70: 26276846 | H70: 46921404 | I70: 17043692 | J70: 10802498 | K70: 10237250 | L70: 15139821 | M70: 13396185 | N70: 14137828 | O70: 13935056 | P70: 19689601 | Q70: 17093559 | R70: 17792902 | S70: 71387869 | T70: 50937433 | U70: 32513428 | V70: 35405971 | Z70: 26862612 | AN70: 19408839 | AP70: 26276846 | AR70: 10237250 | AX70: 16804326 | AY70: 9376575 | AZ70: 19408839 | BA70: 17043692 | BB70: =M70 -> 13396185 | BC70: =Q70 -> 17093559 | BD70: =U70 -> 32513428 | BE70: =V70 -> 35405971
A71: Restricted cash | C71: 4458781 | E71: 4458761 | G71: 4909606 | H71: 4560975 | I71: 4256120 | J71: 4689775 | K71: 5752754 | L71: 5779041 | M71: 8760115 | N71: 5814831 | O71: 8509705 | P71: 11061099 | Q71: 12775667 | R71: 11022524 | S71: 12435628 | T71: 12914679 | U71: 13276919 | V71: 11112442 | Z71: 13240142 | AN71: 4458781 | AP71: 4909606 | AR71: 5752754 | AX71: 2502 | AY71: 325287 | AZ71: 4458761 | BA71: 4256120 | BB71: =M71 -> 8760115 | BC71: =Q71 -> 12775667 | BD71: =U71 -> 13276919 | BE71: =V71 -> 11112442
A72: Short-term investments | C72: 25838177 | E72: 25838177 | G72: 7901373 | H72: 12711264 | I72: 41829964 | J72: 43161145 | K72: 48359889 | L72: 46053824 | M72: 49435599 | N72: 42376152 | O72: 44522946 | P72: 33702049 | Q72: 43999364 | R72: 35332854 | S72: 51121790 | T72: 69955148 | U72: 84282016 | V72: 68042120 | AN72: 25838177 | AP72: 7901373 | AR72: 48359889 | AX72: 784400 | AY72: 12607872 | AZ72: 25838177 | BA72: 41829964 | BB72: =M72 -> 49435599 | BC72: =Q72 -> 43999364 | BD72: =U72 -> 84282016 | BE72: =V72 -> 68042120
A73: Cash, restricted cash and short-term investments | C73: =SUM(C72,C71,C70) -> 49705797 | E73: =SUM(E72,E71,E70) -> 49705777 | G73: =SUM(G72,G71,G70) -> 39087825 | H73: =SUM(H72,H71,H70) -> 64193643 | I73: =SUM(I72,I71,I70) -> 63129776 | J73: =SUM(J72,J71,J70) -> 58653418 | K73: =SUM(K72,K71,K70) -> 64349893 | L73: =SUM(L72,L71,L70) -> 66972686 | M73: =SUM(M72,M71,M70) -> 71591899 | N73: =SUM(N72,N71,N70) -> 62328811 | ... V73: =SUM(V72,V71,V70) -> 114560533 | AN73: =SUM(AN72,AN71,AN70) -> 49705797 | AP73: =SUM(AP72,AP71,AP70) -> 39087825 | AR73: =SUM(AR72,AR71,AR70) -> 64349893 | AT73: =SUM(AT72,AT71,AT70) -> 0 | AW73: =SUM(AW72,AW71,AW70) -> 0 | AX73: =SUM(AX72,AX71,AX70) -> 17591228 | AY73: =SUM(AY72,AY71,AY70) -> 22309734 | AZ73: =SUM(AZ72,AZ71,AZ70) -> 49705777 | BA73: =SUM(BA72,BA71,BA70) -> 63129776 | BB73: =SUM(BB72,BB71,BB70) -> 71591899 | BC73: =Q73 -> 73868590 | BD73: =U73 -> 130072363 | BE73: =V73 -> 114560533
A75: Total assets | C75: 83634163 | E75: 83634163 | G75: 95916325 | H75: 121813736 | I75: 120661511 | J75: 118161193 | K75: 123997559 | L75: 127871900 | M75: 132012915 | N75: 123205063 | O75: 133584285 | P75: 150085145 | Q75: 166574802 | R75: 160241093 | S75: 237128126 | T75: 242609769 | U75: 240653269 | V75: 230880141 | Z75: 250014760 | AN75: 83634163 | AP75: 95916325 | AR75: 23997559 | AX75: 42889847 | AY75: 51716560 | AZ75: 83634163 | BA75: 120661511 | BB75: =M75 -> 132012915 | BC75: =Q75 -> 166574802 | BD75: =U75 -> 240653269 | BE75: =V75 -> 230880141
A77: Total equity | C77: -40501382 | E77: =-40559116+57734 -> -40501382 | G77: -72313887 | H77: 89432522 | I77: -86509772 | J77: -84702062 | K77: -87123343 | L77: -90385540 | M77: -92054394 | N77: -91989829 | O77: -95003319 | P77: -100683339 | Q77: -97634275 | R77: -94047864 | S77: -134829103 | T77: -129241154 | U77: -125556762 | V77: -121087690 | Z77: -134143350 | AN77: -40501382 | AP77: -72313887 | AR77: 87123343 | AX77: -17669672 | AY77: =-25622386+47035 -> -25575351 | AZ77: =-40559116+57734 -> -40501382 | BA77: -86509772 | BB77: =M77 -> -92054394 | BC77: =Q77 -> -97634275 | BD77: =U77 -> -125556762 | BE77: =V77 -> -121087690
A79: Borrowings (current) | C79: 162000 | E79: 162000 | G79: 1117000 | H79: 1545000 | I79: 1800000 | J79: 2100000 | K79: 3000000 | L79: 3140000 | M79: 3552587 | N79: 3557738 | O79: 3323694 | P79: 7864604 | Q79: 6395002 | R79: 7074497 | S79: 11562939 | T79: 13733389 | U79: 11565200 | V79: 11716262 | Z79: 17638409 | AN79: 162000 | AP79: 1117000 | AR79: 3000000 | AY79: 1000 | AZ79: 162000 | BA79: 1800000 | BB79: =M79 -> 3552587 | BC79: =Q79 -> 6395002 | BD79: =U79 -> 11565200 | BE79: =V79 -> 11716262
A80: Borrowings (non-current) | I80: 470056 | J80: 470179 | K80: 936854 | L80: 937043 | M80: 466676 | N80: 466738 | O80: 0 | P80: 0 | Q80: 1957470 | R80: 1971390 | S80: 7591910 | T80: 10635570 | U80: 12219667 | V80: 15338680 | Z80: 1625178 | BB80: 466676 | BC80: 1957470 | BD80: =U80 -> 12219667 | BE80: =V80 -> 15338680
A81: Total liabilities | C81: 124135545 | E81: =E75-E77 -> 124135545 | G81: 168230212 | H81: 32381214 | I81: =I75+I77 -> 34151739 | J81: =J75+J77 -> 33459131 | K81: =K75+K77 -> 36874216 | L81: =L75+L77 -> 37486360 | M81: =M75+M77 -> 39958521 | N81: =N75+N77 -> 31215234 | O81: =O75+O77 -> 38580966 | P81: =P75+P77 -> 49401806 | Q81: 68940527 | R81: 66193229 | S81: 102299023 | T81: 102299023 | U81: 115096507 | V81: 109792451 | Z81: 115871410 | AN81: 124135545 | AP81: 168230212 | AR81: 36874216 | AX81: =AX75-AX77 -> 60559519 | AY81: =AY75-AY77 -> 77291911 | AZ81: =AZ75-AZ77 -> 124135545 | BA81: 34151739 | BB81: =M81 -> 39958521 | BC81: =Q81 -> 68940527 | BD81: =U81 -> 115096507 | BE81: =V81 -> 109792451
A83: Cash Flow
A84: Net cash flows (used in)/generated from operating activities | I84: -9179818 | J84: -3280850 | K84: 3131073 | L84: 2609272 | M84: 5574220 | Q84: 8475013 | AN84: -1442802 | AP84: -5513676 | AR84: -149777 | AX84: -4004434 | AY84: -1918024 | AZ84: -310200 | BA84: -9179818 | BB84: =M84 -> 5574220 | BC84: =Q84 -> 8475013 | BD84: -4011457 | BE84: 11411448
A85: Net cash flows generated/(used in) from investing activities | I85: -23438686 | J85: -2791839 | K85: -4993985 | L85: 2184297 | M85: -10174018 | Q85: -21232004 | AN85: -3061049 | AP85: 12627023 | AR85: -7785824 | AX85: 852664 | AY85: 9556784 | AZ85: -15157090 | BA85: -23438686 | BB85: =M85 -> -10174018 | BC85: =Q85 -> -21232004 | BD85: -58491834 | BE85: -14713569
A86: CAPEX (Investment in PPE) | AN86: -210071 | AP86: -847162 | AX86: -356082 | AY86: -352806 | AZ86: -737680 | BA86: -2200000
A87: Net cash flows generated from/(used in) financing activities | I87: 29295294 | J87: 46000 | K87: 1253230 | L87: 43065 | M87: 1114267 | Q87: 17418081 | AN87: 157147 | AP87: -466934 | AR87: 1299230 | AX87: 18505796 | AY87: 3805222 | AZ87: 25507781 | BA87: 29295294 | BB87: =M87 -> 1114267 | BC87: =Q87 -> 17418081 | BD87: 78598331 | BE87: -9990201

Sheet Segment Reporting
B1: 总则： | C1: 蓝色数字为历史数字，请自行输入或导入；黑色数字为计算项，无需改动；红色字体部分需要做出合理估计、或者需要从会计报表附注中查找、等；
B3: 17Q1 | C3: 17Q2 | D3: 17Q3 | E3: 17Q4 | F3: 18Q1 | G3: 18Q2 | H3: 18Q3 | I3: 18Q4 | J3: 19Q1 | K3: 19Q2 | L3: 19Q3 | M3: 19Q4 | N3: 20Q1 | O3: 20Q2 | P3: 20Q3 | Q3: 20Q4 | R3: 21Q1 | S3: 21Q2 | T3: 21Q3 | U3: 21Q4 | V3: 22Q1 | W3: 22Q2 | X3: 22Q3 | Y3: 22Q4 | Z3: 23Q1 | AA3: 23Q2 | AB3: 23Q3 | AC3: 23Q4 | AD3: 24Q1 | AE3: 24Q2 | AF3: 24Q3 | AG3: 24Q4 | AJ3: 2017 1H | AK3: 2017 2H | AL3: 2018 1H | AM3: 2018 2H | AN3: 2019 1H | AO3: 2020 1H | AQ3: 2017YTD-Q3 | AR3: 2018YTD-Q3 | AT3: 2015 | AU3: 2016 | AV3: 2017 | AW3: 2018 | AX3: 2019 | AY3: 2020 | AZ3: 2021 | BA3: 2022
A4: Food Delivery | AK4: (倒减)
A5: Numer of Food delivery orders (million) | D5: 1204.1 | E5: =AV5-AJ5-D5 -> 1354.4 | F5: =AL5-G5 -> 1224.4 | G5: 1549.2 | H5: 1787.5 | I5: 1832.3 | J5: 1662.6 | K5: 2085.1 | L5: 2469.1 | M5: 2505.3 | N5: 1374.5 | O5: 2228.9 | P5: 3212.7 | Q5: 3331.3 | R5: 2902.7 | S5: 3541.4 | T5: 4013 | U5: 3910.6 | V5: 3361.6 | AJ5: 1531.5 | AK5: =AV5-AJ5 -> 2558.5 | AL5: 2773.6 | AM5: =AW5-AL5 -> 3619.8 | AN5: =1662.6+2085.1 -> 3747.7 | AQ5: =AJ5+D5 -> 2735.6 | AR5: =AL5+H5 -> 4561.1 | AT5: 637 | AU5: 1585 | AV5: 4090 | AW5: 6393.4 | AX5: 8722.1 | AY5: 10147.4 | AZ5: 14367.6
A6: Gross Transaction Value (RMB bn) | D6: 51.8 | E6: =AV6-AJ6-D6 -> 57 | F6: =AL6-G6 -> 54.5 | G6: 68.2 | H6: 80 | I6: 80.2 | J6: 75.6 | K6: 93.1 | L6: 111.9 | M6: 112.1 | N6: 71.504 | O6: 108.8271 | P6: 152.2325 | Q6: 156.2873 | R6: =142735.4*10^(-3) -> 142.7354 | S6: =173603.3/1000 -> 173.6033 | T6: 197.098 | U6: 188.6208 | AJ6: 62.3 | AK6: =AV6-AJ6 -> 108.8 | AL6: 122.7 | AM6: =AW6-AL6 -> 160.1 | AN6: =75.6+93.1 -> 168.7 | AQ6: =AJ6+D6 -> 114.1 | AR6: =AL6+H6 -> 202.7 | AT6: 15.6 | AU6: 58.7 | AV6: 171.1 | AW6: 282.8 | AX6: 392.7 | AY6: 488.8512 | AZ6: 702.0574
A7: Average Order Value (RMB) | D7: =D6*1000/D5 -> 43.019683 | E7: =E6*1000/E5 -> 42.085056 | F7: =F6*1000/F5 -> 44.511598 | G7: =G6*1000/G5 -> 44.022721 | H7: =H6*1000/H5 -> 44.755245 | I7: =I6*1000/I5 -> 43.770125 | J7: =J6*1000/J5 -> 45.470949 | K7: =K6*1000/K5 -> 44.650137 | ... U7: =U6*1000/U5 -> 48.233212 | AJ7: =AJ6*1000/AJ5 -> 40.679073 | AK7: =AK6*1000/AK5 -> 42.524917 | AL7: =AL6*1000/AL5 -> 44.238535 | AM7: =AM6*1000/AM5 -> 44.228963 | AN7: =AN6*1000/AN5 -> 45.014275 | AQ7: =AQ6*1000/AQ5 -> 41.709314 | AR7: =AR6*1000/AR5 -> 44.441034 | AT7: =AT6*1000/AT5 -> 24.489796 | AU7: =AU6*1000/AU5 -> 37.0347 | AV7: =AV6*1000/AV5 -> 41.833741 | AW7: =AW6*1000/AW5 -> 44.233115 | AX7: =AX6*1000/AX5 -> 45.023561 | AY7: =AY6*1000/AY5 -> 48.17502 | AZ7: =AZ6*1000/AZ5 -> 48.86393
A9: Commission (RMB '000) | M9: 13963448 | N9: 8563624 | O9: 12719014 | P9: 18251171 | Q9: 19058227 | R9: 18370710 | S9: 20353682 | T9: 23222843 | U9: =14254546+7768614 -> 22023160 | V9: =V10+V11 -> 20706770 | AJ9: 8138117 | AK9: =AV9-AJ9 -> 12145847 | AL9: 15219665 | AM9: =AW9-AL9 -> 20499543 | AN9: 21632175 | AT9: 174754 | AU9: 5208994 | AV9: 20283964 | AW9: 35719208 | AX9: 49646589 | AY9: 58592036 | AZ9: =AZ10+AZ11 -> 82750914
A10: - Food delivery services | Q10: 12664562 | R10: 12165172 | U10: 14254546 | V10: 13500013 | AD10: =U10/U16 -> 0.54559428 | AH10: =V10/V16 -> 0.5588512 | AY10: 39116411 | AZ10: 54203640
A11: - Commission | Q11: 6029499 | R11: 5809915 | U11: 7768614 | V11: 7206757 | AD11: =U11/U16 -> 0.29734454 | AH11: =V11/V16 -> 0.2983334 | AY11: 18502868 | AZ11: 28547274
A12: % of segment revenue | N12: =N9/N16 -> 0.90234376 | O12: =O9/O16 -> 0.87451395 | P12: =P9/P16 -> 0.88200518 | Q12: =Q9/Q16 -> 0.88486583 | R12: =R9/R16 -> 0.89284782 | S12: =S9/S16 -> 0.88015602 | T12: =T9/T16 -> 0.87684184 | U12: =U9/U16 -> 0.84293882 | V12: =V9/V16 -> 0.8571846
A13: Online Marketing Service (RMB '000) | M13: 1732259 | N13: 919519 | O13: 1795740 | P13: 2407888 | Q13: 2441964 | R13: 2192127 | S13: 2764255 | T13: 3255079 | U13: 3223472 | V13: 2639206 | AJ13: 213399 | AK13: =AV13-AJ13 -> 496804 | AL13: 703842 | AM13: =AW13-AL13 -> 1631157 | AN13: 1867796 | AT13: 0 | AU13: 82975 | AV13: 710203 | AW13: 2334999 | AX13: 5103794 | AY13: 7565111 | AZ13: 11434933
A14: % of segment revenue | N14: =N13/N16 -> 0.096889148 | O14: =O13/O16 -> 0.12346867 | P14: =P13/P16 -> 0.11636348 | Q14: =Q13/Q16 -> 0.11337941 | R14: =R13/R16 -> 0.10654111 | S14: =S13/S16 -> 0.11953492 | T14: =T13/T16 -> 0.12290439 | U14: =U13/U16 -> 0.12337874 | V14: =V13/V16 -> 0.10925348 | AJ14: =AJ13/AJ16 -> 0.025516115 | AK14: =AK13/AK16 -> 0.03921529 | AL14: =AL13/AL16 -> 0.04408842 | AM14: =AM13/AM16 -> 0.073545923 | AN14: =AN13/AN16 -> 0.079310171 | AT14: =AT13/AT16 -> 0 | AU14: =AU13/AU16 -> 0.015652728 | AV14: =AV13/AV16 -> 0.033767842 | AW14: =AW13/AW16 -> 0.06121684 | AX14: =AX13/AX16 -> 0.093061556 | AY14: =AY13/AY16 -> 0.11416396 | AZ14: =AZ13/AZ16 -> 0.11872829
A15: Other services and sales (RMB '000) | M15: 20003 | N15: 7280 | O15: 29341 | P15: 33757 | Q15: 37794 | R15: 12573 | S15: 7147 | T15: 6721 | U15: 880009 | V15: 810746 | AJ15: 11787 | AK15: =AV15-AJ15 -> 25979 | AL15: 40821 | AM15: =AW15-AL15 -> 48055 | AN15: 50552 | AT15: 0 | AU15: 9024 | AV15: 37766 | AW15: 88876 | AX15: 92822 | AY15: 108172 | AZ15: 2125931
A16: Revenue in Total (RMB '000) | D16: 6044214 | E16: 6624416 | F16: 7056361 | G16: =AL16-F16 -> 8907967 | H16: 11172478 | I16: 11006277 | J16: 10705803 | K16: 12844720 | L16: 15576972 | M16: 15715710 | N16: 9490423 | O16: 14544095 | P16: 20692816 | Q16: 21537985 | R16: 20575410 | S16: 23125084 | T16: 26484643 | U16: 26126641 | V16: 24156722 | AJ16: =SUM(AJ9,AJ13,AJ15) -> 8363303 | AK16: =SUM(AK9,AK13,AK15) -> 12668630 | AL16: =SUM(AL9,AL13,AL15) -> 15964328 | AM16: =SUM(AM9,AM13,AM15) -> 22178755 | AN16: =SUM(AN9,AN13,AN15) -> 23550523 | AQ16: =AJ16+D16 -> 14407517 | AR16: =AL16+H16 -> 27136806 | AT16: =SUM(AT9,AT13,AT15) -> 174754 | AU16: =SUM(AU9,AU13,AU15) -> 5300993 | AV16: =SUM(AV9,AV13,AV15) -> 21031933 | AW16: 38143083 | AX16: 54843205 | AY16: 66265319 | AZ16: 96311778
A17: % Total revenue | D17: =D16/D143 -> 0.62480271 | E17: =E16/E143 -> 0.63237966 | F17: =F16/F143 -> 0.62583783 | G17: =G16/G143 -> 0.59099758 | H17: =H16/H143 -> 0.58568246 | I17: =I16/I143 -> 0.55577568 | J17: =J16/J143 -> 0.55836422 | K17: =K16/K143 -> 0.56576851 | ... V17: =V16/V143 -> 0.5220958 | AJ17: =AJ16/AJ143 -> 0.60696832 | AK17: =AK16/AK143 -> 0.6287419 | AL17: =AL16/AL143 -> 0.60590682 | AM17: =AM16/AM143 -> 0.57044928 | AN17: =AN16/AN143 -> 0.5623784 | AQ17: =AQ16/AQ143 -> 0.6143247 | AR17: =AR16/AR143 -> 0.59741348 | AT17: =AT16/AT143 -> 0.043482404 | AU17: =AU16/AU143 -> 0.40814302 | AV17: =AV16/AV143 -> 0.61989923 | AW17: =AW16/AW143 -> 0.58477196 | AX17: =AX16/AX143 -> 0.56232986 | AY17: =AY16/AY143 -> 0.57725164 | AZ17: =AZ16/AZ143 -> 0.53767016
A18: Food Delivery Rider Cost (RMB'000) | AJ18: 7172635 | AK18: =AV18-AJ18 -> 11151430 | AL18: 13042195 | AM18: =AW18-AL18 -> 17473860 | AN18: 17745098 | AT18: 276779 | AU18: 5134840 | AV18: 18324065 | AW18: 30516055 | AX18: 41041513 | AY18: 48692295
A19: Average rider cost/order | AJ19: =AJ18/AJ5/1000 -> 4.6834052 | AK19: =AK18/AK5/1000 -> 4.3585812 | AL19: =AL18/AL5/1000 -> 4.7022624 | AM19: =AM18/AM5/1000 -> 4.8272999 | AN19: =AN18/AN5/1000 -> 4.7349302 | AT19: =AT18/AT5/1000 -> 0.43450392 | AU19: =AU18/AU5/1000 -> 3.2396467 | AV19: =AV18/AV5/1000 -> 4.4802115 | AW19: =AW18/AW5/1000 -> 4.7730558 | AX19: =AX18/AX5/1000 -> 4.7054623 | AY19: =AY18/AY5/1000 -> 4.7984996
A21: Cost of Revenues (RMB '000) | D21: -5566225 | E21: -6208427 | F21: =F22-F16 -> -6521266 | G21: =AL21-F21 -> -7497661 | H21: -9321403 | I21: -9534556 | J21: =J22-J16 -> -9165049 | K21: =K22-K16 -> -9984444 | L21: -12531750 | M21: -12928774 | Q21: -20655633 | AJ21: -7557862 | AK21: =AV21-AJ21 -> -11774652 | AL21: -14018927 | AM21: =AW21-AL21 -> -18855959 | AN21: -19149493 | AT21: -391010 | AU21: -5706544 | AV21: -19332514 | AW21: -32874886 | AX21: -44610017
A22: Gross Profit (Loss) (RMB '000) | D22: =SUM(D16,D21) -> 477989 | E22: =SUM(E16,E21) -> 415989 | F22: 535095 | G22: =AL22-F22 -> 1410306 | H22: =SUM(H16,H21) -> 1851075 | I22: =SUM(I16,I21) -> 1471721 | J22: 1540754 | K22: 2860276 | L22: 3045222 | M22: =SUM(M16,M21) -> 2786936 | Q22: =SUM(Q16,Q21) -> 882352 | AJ22: =SUM(AJ16,AJ21) -> 805441 | AK22: =SUM(AK16,AK21) -> 893978 | AL22: =SUM(AL16,AL21) -> 1945401 | AM22: =SUM(AM16,AM21) -> 3322796 | AN22: =SUM(AN16,AN21) -> 4401030 | AQ22: =AJ22+D22 -> 1283430 | AR22: =AL22+H22 -> 3796476 | AT22: =SUM(AT16,AT21) -> -216256 | AU22: =SUM(AU16,AU21) -> -405551 | AV22: =SUM(AV16,AV21) -> 1699419 | AW22: =SUM(AW16,AW21) -> 5268197 | AX22: =SUM(AX16,AX21) -> 10233188
A24: Operating Profit | J24: -154203 | K24: 756347 | L24: 330907 | M24: 482829 | N24: -70881 | O24: 1253421 | P24: 768477 | Q24: 882352 | R24: 1115885 | S24: 2447076 | T24: 876103 | U24: 1735577 | V24: 1577143 | AX24: 1415880 | AY24: 2833369 | AZ24: 6174641
A25: OPM | J25: =J24/J16 -> -0.014403684 | K25: =K24/K16 -> 0.058883884 | L25: =L24/L16 -> 0.021243346 | M25: =M24/M16 -> 0.030722697 | N25: =N24/N16 -> -0.0074686871 | O25: =O24/O16 -> 0.086180749 | P25: =P24/P16 -> 0.037137381 | Q25: =Q24/Q16 -> 0.040967249 | ... V25: =V24/V16 -> 0.065287956 | AX25: =AX24/AX16 -> 0.025816872 | AY25: =AY24/AY16 -> 0.042757947 | AZ25: =AZ24/AZ16 -> 0.064110965
A26: YoY Growth
A27: Number of Transactions | H27: =IFERROR(H5/D5-1,"") -> 0.48451125 | I27: =IFERROR(I5/E5-1,"") -> 0.35284997 | J27: =IFERROR(J5/F5-1,"") -> 0.35788958 | K27: =IFERROR(K5/G5-1,"") -> 0.34592048 | L27: =IFERROR(L5/H5-1,"") -> 0.38131469 | M27: =IFERROR(M5/I5-1,"") -> 0.36729793 | N27: =IFERROR(N5/J5-1,"") -> -0.17328281 | O27: =IFERROR(O5/K5-1,"") -> 0.068965517 | ... V27: =IFERROR(V5/R5-1,"") -> 0.15809419 | AL27: =IFERROR(AL5/AJ5-1,"") -> 0.81103493 | AM27: =IFERROR(AM5/AK5-1,"") -> 0.41481337 | AN27: =IFERROR(AN5/AL5-1,"") -> 0.35120421 | AU27: =IFERROR(AU5/AT5-1,"") -> 1.4882261 | AV27: =IFERROR(AV5/AU5-1,"") -> 1.5804416 | AW27: =IFERROR(AW5/AV5-1,"") -> 0.56317848 | AX27: =IFERROR(AX5/AW5-1,"") -> 0.36423499 | AY27: =IFERROR(AY5/AX5-1,"") -> 0.16341248 | AZ27: =IFERROR(AZ5/AY5-1,"") -> 0.41588978
A28: Gross Transaction Value | B28: =IFERROR(B6/#REF!,"") | C28: =IFERROR(C6/#REF!,"") | H28: =IFERROR(H6/D6-1,"") -> 0.54440154 | I28: =IFERROR(I6/E6-1,"") -> 0.40701754 | J28: =IFERROR(J6/F6-1,"") -> 0.38715596 | K28: =IFERROR(K6/G6-1,"") -> 0.36510264 | L28: =IFERROR(L6/H6-1,"") -> 0.39875 | M28: =IFERROR(M6/I6-1,"") -> 0.39775561 | N28: =IFERROR(N6/J6-1,"") -> -0.054179894 | O28: =IFERROR(O6/K6-1,"") -> 0.16892696 | ... V28: =IFERROR(V6/R6-1,"") -> -1 | AL28: =IFERROR(AL6/AJ6-1,"") -> 0.96950241 | AM28: =IFERROR(AM6/AK6-1,"") -> 0.47150735 | AN28: =IFERROR(AN6/AL6-1,"") -> 0.37489813 | AU28: =IFERROR(AU6/AT6-1,"") -> 2.7628205 | AV28: =IFERROR(AV6/AU6-1,"") -> 1.9148211 | AW28: =IFERROR(AW6/AV6-1,"") -> 0.6528346 | AX28: =IFERROR(AX6/AW6-1,"") -> 0.38861386 | AY28: =IFERROR(AY6/AX6-1,"") -> 0.24484645 | AZ28: =IFERROR(AZ6/AY6-1,"") -> 0.43613721
A29: Gross Transaction Value vs 2019 | R29: =R6/J6-1 -> 0.88803439 | S29: =S6/K6-1 -> 0.8646971 | T29: =T6/L6-1 -> 0.76137623 | U29: =U6/M6-1 -> 0.68261195 | V29: =V6/J6-1 -> -1 | AZ29: =AZ6/AX6-1 -> 0.78777031
A30: QoQ Growth | E30: =IFERROR(E5/D5-1,"") -> 0.12482352 | F30: =IFERROR(F5/E5-1,"") -> -0.095983461 | G30: =IFERROR(G5/F5-1,"") -> 0.26527279 | H30: =IFERROR(H5/G5-1,"") -> 0.15382133 | I30: =IFERROR(I5/H5-1,"") -> 0.025062937 | J30: =IFERROR(J5/I5-1,"") -> -0.092615838 | K30: =IFERROR(K5/J5-1,"") -> 0.25412005 | L30: =IFERROR(L5/K5-1,"") -> 0.18416383 | ... V30: =IFERROR(V5/U5-1,"") -> -0.14038766
A31: Average Order Value (RMB) | H31: =IFERROR(H7/D7-1,"") -> 0.04034344 | I31: =IFERROR(I7/E7-1,"") -> 0.040039601 | J31: =IFERROR(J7/F7-1,"") -> 0.021552846 | K31: =IFERROR(K7/G7-1,"") -> 0.014252078 | L31: =IFERROR(L7/H7-1,"") -> 0.012622261 | M31: =IFERROR(M7/I7-1,"") -> 0.022275818 | N31: =IFERROR(N7/J7-1,"") -> 0.1440673 | O31: =IFERROR(O7/K7-1,"") -> 0.093512318 | ... V31: =IFERROR(V7/R7-1,"") -> -1 | AL31: =IFERROR(AL7/AJ7-1,"") -> 0.087501059 | AM31: =IFERROR(AM7/AK7-1,"") -> 0.040071706 | AN31: =IFERROR(AN7/AL7-1,"") -> 0.017535406 | AU31: =IFERROR(AU7/AT7-1,"") -> 0.51225026 | AV31: =IFERROR(AV7/AU7-1,"") -> 0.12958227 | AW31: =IFERROR(AW7/AV7-1,"") -> 0.057355009 | AX31: =IFERROR(AX7/AW7-1,"") -> 0.017869992 | AY31: =IFERROR(AY7/AX7-1,"") -> 0.069995782 | AZ31: =IFERROR(AZ7/AY7-1,"") -> 0.014300145
A32: Commission | B32: =IFERROR(B9/#REF!,"") | C32: =IFERROR(C9/#REF!,"") | D32: =IFERROR(D9/B9,"") | F32: =IFERROR(F9/C9,"") | H32: =IFERROR(H9/F9-1,"") | I32: =IFERROR(I9/G9-1,"") | J32: =IFERROR(J9/H9-1,"") | R32: =R9/N9-1 -> 1.1452028 | S32: =S9/O9-1 -> 0.60025628 | T32: =T9/P9-1 -> 0.2724029 | U32: =U9/Q9-1 -> 0.15557234 | V32: =V9/R9-1 -> 0.12716221 | AL32: =IFERROR(AL9/AJ9-1,"") -> 0.87017034 | AM32: =IFERROR(AM9/AK9-1,"") -> 0.68778209 | AN32: =IFERROR(AN9/AL9-1,"") -> 0.42133056 | AU32: =IFERROR(AU9/AT9-1,"") -> 28.807581 | AV32: =IFERROR(AV9/AU9-1,"") -> 2.8940271 | AW32: =IFERROR(AW9/AV9-1,"") -> 0.76095797 | AX32: =IFERROR(AX9/AW9-1,"") -> 0.38991293 | AY32: =IFERROR(AY9/AX9-1,"") -> 0.18018251 | AZ32: =IFERROR(AZ9/AY9-1,"") -> 0.41232358
A33: - Food delivery services | U33: =U10/Q10-1 -> 0.12554591 | V33: =V10/R10-1 -> 0.10972644
A34: - Commission | U34: =U11/Q11-1 -> 0.28843441 | V34: =V11/R11-1 -> 0.24042383
A35: Online Marketing Service | B35: =IFERROR(B13/#REF!,"") | C35: =IFERROR(C13/#REF!,"") | D35: =IFERROR(D13/B13,"") | F35: =IFERROR(F13/C13,"") | H35: =IFERROR(H13/F13-1,"") | I35: =IFERROR(I13/G13-1,"") | J35: =IFERROR(J13/H13-1,"") | R35: =R13/N13-1 -> 1.3839932 | S35: =S13/O13-1 -> 0.53934033 | T35: =T13/P13-1 -> 0.35183987 | U35: =U13/Q13-1 -> 0.32003256 | V35: =V13/R13-1 -> 0.20394758 | AL35: =IFERROR(AL13/AJ13-1,"") -> 2.2982441 | AM35: =IFERROR(AM13/AK13-1,"") -> 2.2833009 | AN35: =IFERROR(AN13/AL13-1,"") -> 1.6537149 | AU35: =IFERROR(AU13/AT13-1,"") | AV35: =IFERROR(AV13/AU13-1,"") -> 7.5592407 | AW35: =IFERROR(AW13/AV13-1,"") -> 2.287791 | AX35: =IFERROR(AX13/AW13-1,"") -> 1.18578 | AY35: =IFERROR(AY13/AX13-1,"") -> 0.48225242 | AZ35: =IFERROR(AZ13/AY13-1,"") -> 0.51153539
A36: Other services and sales | B36: =IFERROR(B15/#REF!,"") | C36: =IFERROR(C15/#REF!,"") | D36: =IFERROR(D15/B15,"") | F36: =IFERROR(F15/C15,"") | H36: =IFERROR(H15/F15-1,"") | I36: =IFERROR(I15/G15-1,"") | J36: =IFERROR(J15/H15-1,"") | AL36: =IFERROR(AL15/AJ15-1,"") -> 2.4632222 | AM36: =IFERROR(AM15/AK15-1,"") -> 0.84976327 | AN36: =IFERROR(AN15/AL15-1,"") -> 0.23838221 | AU36: =IFERROR(AU15/AT15-1,"") | AV36: =IFERROR(AV15/AU15-1,"") -> 3.1850621 | AW36: =IFERROR(AW15/AV15-1,"") -> 1.3533337 | AX36: =IFERROR(AX15/AW15-1,"") -> 0.044398938 | AY36: =IFERROR(AY15/AX15-1,"") -> 0.16537028 | AZ36: =IFERROR(AZ15/AY15-1,"") -> 18.653247
A37: Revenue in Total | B37: =IFERROR(B16/#REF!,"") | C37: =IFERROR(C16/#REF!,"") | H37: =IFERROR(H16/D16-1,"") -> 0.84845838 | I37: =IFERROR(I16/E16-1,"") -> 0.66147129 | J37: =IFERROR(J16/F16-1,"") -> 0.51718471 | K37: =IFERROR(K16/G16-1,"") -> 0.44193619 | L37: =IFERROR(L16/H16-1,"") -> 0.39422714 | M37: =IFERROR(M16/I16-1,"") -> 0.42788611 | N37: =IFERROR(N16/J16-1,"") -> -0.11352535 | O37: =IFERROR(O16/K16-1,"") -> 0.13230144 | ... V37: =IFERROR(V16/R16-1,"") -> 0.17405787 | AL37: =IFERROR(AL16/AJ16-1,"") -> 0.90885443 | AM37: =IFERROR(AM16/AK16-1,"") -> 0.75068299 | AN37: =IFERROR(AN16/AL16-1,"") -> 0.47519664 | AV37: =IFERROR(AV16/AU16-1,"") -> 2.9675459 | AW37: =IFERROR(AW16/AV16-1,"") -> 0.81357952 | AX37: =IFERROR(AX16/AW16-1,"") -> 0.43782832 | AY37: =IFERROR(AY16/AX16-1,"") -> 0.20826854 | AZ37: =IFERROR(AZ16/AY16-1,"") -> 0.45342661
A38: Revenue in Total vs 2019 | R38: =R16/J16-1 -> 0.9218932 | S38: =S16/K16-1 -> 0.80035719 | T38: =T16/L16-1 -> 0.70024335 | U38: =U16/M16-1 -> 0.66245375 | V38: =V16/J16-1 -> 1.2564138
A40: Operating Income/Loss | N40: =N24/J24-1 -> -0.54033968 | O40: =O24/K24-1 -> 0.65720364 | P40: =P24/L24-1 -> 1.3223353 | Q40: =Q24/M24-1 -> 0.82746272 | R40: =R24/N24-1 -> -16.743076 | S40: =S24/O24-1 -> 0.9523177 | T40: =T24/P24-1 -> 0.14005104 | U40: =U24/Q24-1 -> 0.96698936 | V40: =V24/R24-1 -> 0.41335622 | AX40: =IFERROR(AX24/AW24-1,"") | AY40: =IFERROR(AY24/AX24-1,"") -> 1.0011364 | AZ40: =IFERROR(AZ24/AY24-1,"") -> 1.1792576
A42: Margins
A43: Commssion Rate | B43: =IFERROR(B9/B6,"") | C43: =IFERROR(C9/C6,"") | F43: =IFERROR(F9/F6,"") -> 0 | AJ43: =IFERROR(AJ9/(AJ6*1000000),"") -> 0.13062788 | AK43: =IFERROR(AK9/(AK6*1000000),"") -> 0.11163462 | AL43: =IFERROR(AL9/(AL6*1000000),"") -> 0.12403965 | AM43: =IFERROR(AM9/(AM6*1000000),"") -> 0.12804212 | AN43: =IFERROR(AN9/(AN6*1000000),"") -> 0.12822866 | AR43: =IFERROR(AR9/(AR6*1000000),"") -> 0 | AT43: =IFERROR(AT9/(AT6*1000000),"") -> 0.011202179 | AU43: =IFERROR(AU9/(AU6*1000000),"") -> 0.08873925 | AV43: =IFERROR(AV9/(AV6*1000000),"") -> 0.11855034 | AW43: =IFERROR(AW9/(AW6*1000000),"") -> 0.12630554 | AX43: =IFERROR(AX9/(AX6*1000000),"") -> 0.12642371 | AY43: =IFERROR(AY9/(AY6*1000000),"") -> 0.11985659 | AZ43: =IFERROR(AZ9/(AZ6*1000000),"") -> 0.11786916
A44: Monetization Rate | D44: =IFERROR(D16/(D6*1000000),"") -> 0.11668367 | E44: =IFERROR(E16/(E6*1000000),"") -> 0.11621782 | F44: =IFERROR(F16/(F6*1000000),"") -> 0.12947451 | G44: =IFERROR(G16/(G6*1000000),"") -> 0.13061535 | H44: =IFERROR(H16/(H6*1000000),"") -> 0.13965597 | I44: =IFERROR(I16/(I6*1000000),"") -> 0.13723537 | J44: =IFERROR(J16/(J6*1000000),"") -> 0.14161115 | K44: =IFERROR(K16/(K6*1000000),"") -> 0.13796692 | ... V44: =IFERROR(V16/(V6*1000000),"") | AJ44: =IFERROR(AJ16/(AJ6*1000000),"") -> 0.13424242 | AK44: =IFERROR(AK16/(AK6*1000000),"") -> 0.11643961 | AL44: =IFERROR(AL16/(AL6*1000000),"") -> 0.13010862 | AM44: =IFERROR(AM16/(AM6*1000000),"") -> 0.13853064 | AN44: =IFERROR(AN16/(AN6*1000000),"") -> 0.13960002 | AQ44: =IFERROR(AQ16/(AQ6*1000000),"") -> 0.12627096 | AT44: =IFERROR(AT16/(AT6*1000000),"") -> 0.011202179 | AU44: =IFERROR(AU16/(AU6*1000000),"") -> 0.090306525 | AV44: =IFERROR(AV16/(AV6*1000000),"") -> 0.12292188 | AW44: =IFERROR(AW16/(AW6*1000000),"") -> 0.13487653 | AX44: =IFERROR(AX16/(AX6*1000000),"") -> 0.13965675 | AY44: =IFERROR(AY16/(AY6*1000000),"") -> 0.13555315 | AZ44: =IFERROR(AZ16/(AZ6*1000000),"") -> 0.13718505
A45: Gross Margin | B45: =IFERROR(B22/B16,"") | C45: =IFERROR(C22/C16,"") | D45: =IFERROR(D22/D16,"") -> 0.079082078 | E45: =IFERROR(E22/E16,"") -> 0.062796328 | F45: =IFERROR(F22/F16,"") -> 0.075831579 | G45: =IFERROR(G22/G16,"") -> 0.15831963 | H45: =IFERROR(H22/H16,"") -> 0.16568169 | I45: =IFERROR(I22/I16,"") -> 0.13371651 | ... M45: =IFERROR(M22/M16,"") -> 0.1773344 | AJ45: =IFERROR(AJ22/AJ16,"") -> 0.096306567 | AK45: =IFERROR(AK22/AK16,"") -> 0.070566273 | AL45: =IFERROR(AL22/AL16,"") -> 0.12185925 | AM45: =IFERROR(AM22/AM16,"") -> 0.14981887 | AN45: =IFERROR(AN22/AN16,"") -> 0.1868761 | AQ45: =IFERROR(AQ22/AQ16,"") -> 0.089080582 | AR45: =IFERROR(AR22/AR16,"") -> 0.13990136 | AT45: =IFERROR(AT22/AT16,"") -> -1.2374881 | AU45: =IFERROR(AU22/AU16,"") -> -0.076504723 | AV45: =IFERROR(AV22/AV16,"") -> 0.080801845 | AW45: =IFERROR(AW22/AW16,"") -> 0.13811671 | AX45: =IFERROR(AX22/AX16,"") -> 0.1865899
A46: OPM | J46: =J24/J16 -> -0.014403684 | N46: =N24/N16 -> -0.0074686871 | O46: =O24/O16 -> 0.086180749 | P46: =P24/P16 -> 0.037137381 | Q46: =Q24/Q16 -> 0.040967249 | R46: =R24/R16 -> 0.054233913 | S46: =S24/S16 -> 0.10581912 | T46: =T24/T16 -> 0.033079661 | U46: =U24/U16 -> 0.066429397 | V46: =V24/V16 -> 0.065287956 | AX46: =AX24/AX16 -> 0.025816872 | AY46: =AY24/AY16 -> 0.042757947 | AZ46: =AZ24/AZ16 -> 0.064110965
A47: Instore, Hotels and Travel
A48: Numer of Transactions (million) | AT48: 1290 | AU48: 1439 | AV48: 1394
A49: Gross Transaction Value (RMB bn) | D49: 43.3 | E49: =AV49-AJ49-D49 -> 39.9 | F49: =AL49-G49 -> 40.3 | G49: 42.5 | H49: 49.3 | I49: 44.7 | J49: 46.4 | K49: 51.3 | L49: 63.9 | M49: 60.4 | AJ49: 74.9 | AK49: =AV49-AJ49 -> 83.2 | AL49: 82.8 | AM49: 82.8 | AN49: 97.7 | AQ49: =AJ49+D49 -> 118.2 | AR49: =AL49+H49 -> 132.1 | AT49: 127.5 | AU49: 158.4 | AV49: 158.1 | AW49: 176.8 | AX49: 222.1
A51: Commission (RMB '000) | M51: 3203847 | N51: 1196998 | O51: 2092858 | P51: 3321348 | Q51: 3581958 | R51: 3255587 | S51: 4352601 | T51: 4124543 | U51: 4066205 | V51: 3542896 | AJ51: 3220393 | AK51: =AV51-AJ51 -> 3915577 | AL51: 4060551 | AM51: =AW51-AL51 -> 4981752 | AN51: 5168087 | AT51: 3426056 | AU51: 4869575 | AV51: 7135970 | AW51: 9042303 | AX51: 11679344 | AY51: 10193162 | AZ51: 15798936
A52: % of segment revenue | N52: =N51/N56 -> 0.38675493 | O52: =O51/O56 -> 0.46057797 | P52: =P51/P56 -> 0.51270577 | Q52: =Q51/Q56 -> 0.50200102 | R52: =R51/R56 -> 0.49444011 | S52: =S51/S56 -> 0.50598819 | T52: =T51/T56 -> 0.47841156 | U52: =U51/U56 -> 0.46617816 | V52: =V51/V56 -> 0.46485493 | AX52: =AX51/AX56 -> 0.5243141 | AY52: =AY51/AY56 -> 0.47962409 | AZ52: =AZ51/AZ56 -> 0.48566794
A53: Online Marketing Service (RMB '000) | M53: 3131896 | N53: 1886831 | O53: 2445305 | P53: 3147357 | Q53: 3538844 | R53: 3315840 | S53: 4234620 | T53: 4480794 | U53: 4636167 | V53: 4063588 | AJ53: 1469143 | AK53: =AV53-AJ53 -> 2180853 | AL53: 2729072 | AM53: =AW53-AL53 -> 4005829 | AN53: 4534423 | AT53: 345259 | AU53: 2113106 | AV53: 3649996 | AW53: 6734901 | AX53: 10516428 | AY53: 11018337 | AZ53: 16667421
A54: % of segment revenue | N54: =N53/N56 -> 0.60964278 | O54: =O53/O56 -> 0.53814144 | P54: =P53/P56 -> 0.48584735 | Q54: =Q53/Q56 -> 0.49595872 | R54: =R53/R56 -> 0.50359099 | S54: =S53/S56 -> 0.49227295 | T54: =T53/T56 -> 0.51973362 | U54: =U53/U56 -> 0.53152259 | V54: =V53/V56 -> 0.53317368 | AJ54: =AJ53/AJ56 -> 0.31079601 | AK54: =AK53/AK56 -> 0.35601247 | AL54: =AL53/AL56 -> 0.40071542 | AM54: =AM53/AM56 -> 0.44362018 | AN54: =AN53/AN56 -> 0.46567034 | AT54: =AT53/AT56 -> 0.091490335 | AU54: =AU53/AU56 -> 0.3010276 | AV54: =AV53/AV56 -> 0.33631806 | AW54: =AW53/AW56 -> 0.42517345 | AX54: =AX53/AX56 -> 0.47210798 | AY54: =AY53/AY56 -> 0.51845147 | AZ54: =AZ53/AZ56 -> 0.51236565
A55: Other services and sales (RMB '000) | M55: 21202 | N55: 11149 | O55: 5819 | P55: 9373 | Q55: 14558 | R55: 12964 | S55: 14958 | T55: 15991 | U55: 20055 | V55: 15025 | Y55: =Y56/'New Segment Reporting'!H8 -> 0.16452615 | AJ55: 37497 | AK55: =AV55-AJ55 -> 29347 | AL55: 20876 | AM55: =AW55-AL55 -> 42281 | AN55: 34900 | AT55: 2406 | AU55: 36961 | AV55: 66844 | AW55: 63157 | AX55: 79700 | AY55: 40899 | AZ55: 63968
A56: Revenue in Total (RMB '000) | D56: 3022586 | E56: 3103191 | F56: 3137805 | G56: =AL56-F56 -> 3672694 | H56: 4435730 | I56: 4594132 | J56: 4492102 | K56: 5245308 | L56: 6181117 | M56: 6356945 | N56: 3094978 | O56: 4543982 | P56: 6478078 | Q56: 7135360 | R56: 6584391 | S56: 8602179 | T56: 8621328 | U56: 8722427 | V56: 7621509 | W56: =S56*(1-18.6%) -> 7002173.7 | X56: =X57*X143 -> 10645212 | Y56: =U56*(1+Y59) -> 7152390.1 | Z56: =Z57*Z143 -> 9085708.2 | AA56: =AA57*AA143 -> 11553986 | AB56: =AB57*AB143 -> 13764043 | AC56: =AC57*AC143 -> 11054393 | AD56: =Z56*(1+AD58) -> 11902278 | AE56: =AE57*AE143 -> 13160172 | AF56: =AF57*AF143 -> 14036598 | AG56: =AG57*AG143 -> 13273094 | AJ56: =SUM(AJ51,AJ53,AJ55) -> 4727033 | AK56: =SUM(AK51,AK53,AK55) -> 6125777 | AL56: =SUM(AL51,AL53,AL55) -> 6810499 | AM56: =SUM(AM51,AM53,AM55) -> 9029862 | AN56: =SUM(AN51,AN53,AN55) -> 9737410 | AQ56: =AJ56+D56 -> 7749619 | AR56: =AL56+H56 -> 11246229 | AT56: =SUM(AT51,AT53,AT55) -> 3773721 | AU56: =SUM(AU51,AU53,AU55) -> 7019642 | AV56: =SUM(AV51,AV53,AV55) -> 10852810 | AW56: 15840361 | AX56: 22275472 | AY56: 21252398 | AZ56: 32530325
A57: % Total revenue | D57: =D56/D143 -> 0.31245087 | E57: =E56/E143 -> 0.29623666 | F57: =F56/F143 -> 0.27829601 | G57: =G56/G143 -> 0.24366427 | H57: =H56/H143 -> 0.23252937 | I57: =I56/I143 -> 0.23198642 | J57: =J56/J143 -> 0.23428686 | K57: =K56/K143 -> 0.23103891 | ... W57: =W56/W143 -> 0.13746366 | X57: 0.17 | Y57: =Y56/Y143 -> 0.11895088 | Z57: 0.155 | AA57: 0.17 | AB57: 0.18 | AC57: 0.15 | AE57: 0.16 | AF57: 0.15 | AG57: 0.15 | AJ57: =AJ56/AJ143 -> 0.34306533 | AK57: =AK56/AK143 -> 0.30402125 | AL57: =AL56/AL143 -> 0.25848428 | AM57: =AM56/AM143 -> 0.23225282 | AN57: =AN56/AN143 -> 0.23252601 | AQ57: =AQ56/AQ143 -> 0.33043739 | AR57: =AR56/AR143 -> 0.24758436 | AS57: =AS56/AS143 -> #DIV/0! | AT57: =AT56/AT143 -> 0.93897972 | AU57: =AU56/AU143 -> 0.54046815 | AV57: =AV56/AV143 -> 0.3198778 | AW57: =AW56/AW143 -> 0.24284872 | AX57: =AX56/AX143 -> 0.22839954 | ... AZ57: =AZ56/AZ143 -> 0.1816038
Z58: =Z56/V56-1 -> 0.19211408 | AA58: =AA56/W56-1 -> 0.65005705 | AB58: =AB56/X56-1 -> 0.29297977 | AC58: =AC56/Y56-1 -> 0.54555225 | AD58: 0.31 | AE58: =AE56/AA56-1 -> 0.13901577
A59: Cost of Revenues (RMB '000) | D59: -347707 | E59: -382361 | F59: =F60-F56 -> -381846 | G59: =AL59-F59 -> -338675 | H59: -418611 | I59: -605874 | J59: =J60-J56 -> -523726 | K59: =K60-K56 -> -586041 | L59: -704900 | M59: -714450 | U59: -4825411 | W59: =W56/S56-1 -> -0.186 | Y59: -0.18 | AJ59: -543263 | AK59: =AV59-AJ59 -> -730068 | AL59: -720521 | AM59: -720520 | AN59: -1109767 | AT59: -740686 | AU59: -1080917 | AV59: -1273331 | AW59: -1745006 | AX59: -2529117
A60: Gross Profit (Loss) (RMB '000) | D60: =SUM(D56,D59) -> 2674879 | E60: =SUM(E56,E59) -> 2720830 | F60: 2755959 | G60: =AL60-F60 -> 3334019 | H60: =SUM(H56,H59) -> 4017119 | I60: =SUM(I56,I59) -> 3988258 | J60: 3968376 | K60: 4659267 | L60: 5476217 | M60: =SUM(M56,M59) -> 5642495 | AJ60: =SUM(AJ56,AJ59) -> 4183770 | AK60: =SUM(AK56,AK59) -> 5395709 | AL60: =SUM(AL56,AL59) -> 6089978 | AM60: =SUM(AM56,AM59) -> 8309342 | AN60: =SUM(AN56,AN59) -> 8627643 | AQ60: =AJ60+D60 -> 6858649 | AR60: =AL60+H60 -> 10107097 | AT60: =SUM(AT56,AT59) -> 3033035 | AU60: =SUM(AU56,AU59) -> 5938725 | AV60: =SUM(AV56,AV59) -> 9579479 | AW60: =SUM(AW56,AW59) -> 14095355 | AX60: =SUM(AX56,AX59) -> 19746355
A62: Operating Income / Loss | J62: 1592878 | K62: 2147499 | L62: 2331639 | M62: 2331277 | N62: 680179 | O62: 1891563 | P62: 2787256 | Q62: 2821935 | R62: 2748205 | S62: 3663818 | T62: 3784074 | U62: 3897016 | V62: 3473546 | AX62: 8403293 | AY62: 8180933 | AZ62: 14093113
J63: =J62/J56 -> 0.35459524 | K63: =K62/K56 -> 0.40941333 | L63: =L62/L56 -> 0.37721968 | M63: =M62/M56 -> 0.36672914 | N63: =N62/N56 -> 0.21976861 | O63: =O62/O56 -> 0.41627872 | P63: =P62/P56 -> 0.43025972 | Q63: =Q62/Q56 -> 0.395486 | ... V63: =V62/V56 -> 0.45575568 | AX63: =AX62/AX56 -> 0.37724422 | AY63: =AY62/AY56 -> 0.38494164 | AZ63: =AZ62/AZ56 -> 0.43323001
A64: YoY Growth
A65: Number of Transactions | B65: =IFERROR(B48/#REF!,"") | C65: =IFERROR(C48/#REF!,"") | D65: =IFERROR(D48/#REF!,"") | F65: =IFERROR(F48/#REF!,"") | AJ65: =IFERROR(AJ48/#REF!,"") | AL65: =IFERROR(AL48/AJ48-1,"") | AM65: =IFERROR(AM48/#REF!,"") | AU65: =IFERROR(AU48/AT48-1,"") -> 0.11550388 | AV65: =IFERROR(AV48/AU48-1,"") -> -0.031271716
A66: Gross Transaction Value | B66: =IFERROR(B49/#REF!,"") | C66: =IFERROR(C49/#REF!,"") | H66: =H49/D49-1 -> 0.13856813 | I66: =I49/E49-1 -> 0.12030075 | J66: =J49/F49-1 -> 0.15136476 | K66: =K49/G49-1 -> 0.20705882 | L66: =L49/H49-1 -> 0.29614604 | M66: =M49/I49-1 -> 0.35123043 | AL66: =IFERROR(AL49/AJ49-1,"") -> 0.10547397 | AM66: =IFERROR(AM49/AK49-1,"") -> -0.0048076923 | AN66: =IFERROR(AN49/AL49-1,"") -> 0.17995169 | AU66: =IFERROR(AU49/AT49-1,"") -> 0.24235294 | AV66: =IFERROR(AV49/AU49-1,"") -> -0.0018939394 | AW66: =IFERROR(AW49/AV49-1,"") -> 0.11827957 | AX66: =IFERROR(AX49/AW49-1,"") -> 0.25622172
A67: QoQ Growth | E67: =IFERROR(E49/D49-1,"") -> -0.07852194 | F67: =IFERROR(F49/E49-1,"") -> 0.010025063 | G67: =IFERROR(G49/F49-1,"") -> 0.054590571 | H67: =IFERROR(H49/G49-1,"") -> 0.16 | I67: =IFERROR(I49/H49-1,"") -> -0.093306288 | J67: =IFERROR(J49/I49-1,"") -> 0.03803132 | K67: =IFERROR(K49/J49-1,"") -> 0.10560345 | L67: =IFERROR(L49/K49-1,"") -> 0.24561404 | M67: =IFERROR(M49/L49-1,"") -> -0.054773083
A68: Commission | B68: =IFERROR(B51/#REF!,"") | C68: =IFERROR(C51/#REF!,"") | D68: =IFERROR(D51/#REF!,"") | F68: =IFERROR(F51/#REF!,"") | R68: =R51/N51-1 -> 1.7197932 | S68: =S51/O51-1 -> 1.0797402 | T68: =T51/P51-1 -> 0.24182802 | U68: =U51/Q51-1 -> 0.13519059 | V68: =V51/R51-1 -> 0.088251059 | AL68: =IFERROR(AL51/AJ51-1,"") -> 0.26088679 | AM68: =IFERROR(AM51/AK51-1,"") -> 0.27229065 | AN68: =IFERROR(AN51/AL51-1,"") -> 0.2727551 | AU68: =IFERROR(AU51/AT51-1,"") -> 0.42133549 | AV68: =IFERROR(AV51/AU51-1,"") -> 0.46541947 | AW68: =IFERROR(AW51/AV51-1,"") -> 0.2671442 | AX68: =IFERROR(AX51/AW51-1,"") -> 0.29163378 | AY68: =IFERROR(AY51/AX51-1,"") -> -0.12724876 | AZ68: =IFERROR(AZ51/AY51-1,"") -> 0.54995437
A69: Online Marketing Service | B69: =IFERROR(B53/#REF!,"") | C69: =IFERROR(C53/#REF!,"") | D69: =IFERROR(D53/#REF!,"") | F69: =IFERROR(F53/#REF!,"") | R69: =R53/N53-1 -> 0.7573593 | S69: =S53/O53-1 -> 0.7317349 | T69: =T53/P53-1 -> 0.42366881 | U69: =U53/Q53-1 -> 0.31007951 | V69: =V53/R53-1 -> 0.22550787 | AL69: =IFERROR(AL53/AJ53-1,"") -> 0.85759453 | AM69: =IFERROR(AM53/AK53-1,"") -> 0.83681752 | AN69: =IFERROR(AN53/AL53-1,"") -> 0.6615256 | AU69: =IFERROR(AU53/AT53-1,"") -> 5.1203502 | AV69: =IFERROR(AV53/AU53-1,"") -> 0.72731325 | AW69: =IFERROR(AW53/AV53-1,"") -> 0.84518038 | AX69: =IFERROR(AX53/AW53-1,"") -> 0.5614822 | AY69: =IFERROR(AY53/AX53-1,"") -> 0.047726186 | AZ69: =IFERROR(AZ53/AY53-1,"") -> 0.51269842
A70: Other services and sales | B70: =IFERROR(B55/#REF!,"") | C70: =IFERROR(C55/#REF!,"") | D70: =IFERROR(D55/#REF!,"") | F70: =IFERROR(F55/#REF!,"") | AL70: =IFERROR(AL55/AJ55-1,"") -> -0.44326213 | AM70: =IFERROR(AM55/AK55-1,"") -> 0.44072648 | AN70: =IFERROR(AN55/AL55-1,"") -> 0.6717762 | AU70: =IFERROR(AU55/AT55-1,"") -> 14.362012 | AV70: =IFERROR(AV55/AU55-1,"") -> 0.80850085 | AW70: =IFERROR(AW55/AV55-1,"") -> -0.055158279 | AX70: =IFERROR(AX55/AW55-1,"") -> 0.26193454 | AY70: =IFERROR(AY55/AX55-1,"") -> -0.48683814 | AZ70: =IFERROR(AZ55/AY55-1,"") -> 0.56404802
A71: Revenue in Total | B71: =IFERROR(B56/#REF!,"") | C71: =IFERROR(C56/#REF!,"") | H71: =H56/D56-1 -> 0.46752814 | I71: =I56/E56-1 -> 0.48045415 | J71: =J56/F56-1 -> 0.43160649 | K71: =K56/G56-1 -> 0.42819086 | L71: =L56/H56-1 -> 0.3934836 | M71: =M56/I56-1 -> 0.3837097 | N71: =N56/J56-1 -> -0.31101787 | O71: =O56/K56-1 -> -0.1337054 | ... V71: =V56/R56-1 -> 0.15751161 | AL71: =IFERROR(AL56/AJ56-1,"") -> 0.44075554 | AM71: =IFERROR(AM56/AK56-1,"") -> 0.47407619 | AN71: =IFERROR(AN56/AL56-1,"") -> 0.42976454 | AU71: =IFERROR(AU56/AT56-1,"") -> 0.86013804 | AV71: =IFERROR(AV56/AU56-1,"") -> 0.54606318 | AW71: =IFERROR(AW56/AV56-1,"") -> 0.4595631 | AX71: =IFERROR(AX56/AW56-1,"") -> 0.40624775 | AY71: =IFERROR(AY56/AX56-1,"") -> -0.045928275 | AZ71: =IFERROR(AZ56/AY56-1,"") -> 0.53066609
A72: Revenue in Total vs 2019 | R72: =R56/J56-1 -> 0.46577059 | S72: =S56/K56-1 -> 0.63997596 | T72: =T56/L56-1 -> 0.39478479 | U72: =U56/M56-1 -> 0.37210987 | V72: =V56/J56-1 -> 0.69664647 | AZ72: =AZ56/AX56-1 -> 0.46036524
A73: Operating Income / Loss | N73: NM | S73: =S62/O62-1 -> 0.93692624 | T73: =T62/P62-1 -> 0.35763417 | U73: =U62/Q62-1 -> 0.38097298 | V73: =V62/R62-1 -> 0.26393264
A74: Margins | Q74: =Q62/M62-1 -> 0.21046748 | R74: =R62/N62-1 -> 3.0404144 | S74: =S62/O62-1 -> 0.93692624 | T74: =T62/P62-1 -> 0.35763417 | U74: =U62/Q62-1 -> 0.38097298 | V74: =V62/R62-1 -> 0.26393264
A75: Commssion Rate | B75: =IFERROR(B51/B49,"") | C75: =IFERROR(C51/C49,"") | F75: =IFERROR(F51/F49,"") -> 0 | AJ75: =IFERROR(AJ51/(AJ49*1000000),"") -> 0.042995901 | AK75: =IFERROR(AK51/(AK49*1000000),"") -> 0.047062224 | AL75: =IFERROR(AL51/(AL49*1000000),"") -> 0.049040471 | AM75: =IFERROR(AM51/(AM49*1000000),"") -> 0.060166087 | AN75: =IFERROR(AN51/(AN49*1000000),"") -> 0.052897513 | AT75: =IFERROR(AT51/(AT49*1000000),"") -> 0.026871027 | AU75: =IFERROR(AU51/(AU49*1000000),"") -> 0.030742266 | AV75: =IFERROR(AV51/(AV49*1000000),"") -> 0.0451358 | AW75: =IFERROR(AW51/(AW49*1000000),"") -> 0.051144248 | AX75: =IFERROR(AX51/(AX49*1000000),"") -> 0.05258597 | AY75: =IFERROR(AY51/(AY49*1000000),"")
A76: Monetization Rate | D76: =IFERROR(D56/(D49*1000000),"") -> 0.069805681 | E76: =IFERROR(E56/(E49*1000000),"") -> 0.077774211 | F76: =IFERROR(F56/(F49*1000000),"") -> 0.077861166 | G76: =IFERROR(G56/(G49*1000000),"") -> 0.086416329 | H76: =IFERROR(H56/(H49*1000000),"") -> 0.089974239 | I76: =IFERROR(I56/(I49*1000000),"") -> 0.102777 | J76: =IFERROR(J56/(J49*1000000),"") -> 0.096812543 | K76: =IFERROR(K56/(K49*1000000),"") -> 0.10224772 | ... N76: =IFERROR(N56/(N49*1000000),"") | AJ76: =IFERROR(AJ56/(AJ49*1000000),"") -> 0.063111255 | AK76: =IFERROR(AK56/(AK49*1000000),"") -> 0.073627127 | AL76: =IFERROR(AL56/(AL49*1000000),"") -> 0.082252403 | AM76: =IFERROR(AM56/(AM49*1000000),"") -> 0.1090563 | AN76: =IFERROR(AN56/(AN49*1000000),"") -> 0.099666428 | AQ76: =IFERROR(AQ56/(AQ49*1000000),"") -> 0.065563613 | AT76: =IFERROR(AT56/(AT49*1000000),"") -> 0.029597812 | AU76: =IFERROR(AU56/(AU49*1000000),"") -> 0.044315922 | AV76: =IFERROR(AV56/(AV49*1000000),"") -> 0.068645225 | AW76: =IFERROR(AW56/(AW49*1000000),"") -> 0.089594802 | AX76: =IFERROR(AX56/(AX49*1000000),"") -> 0.10029479 | AY76: =IFERROR(AY56/(AY49*1000000),"")
B77: =IFERROR(B60/B56,"") | C77: =IFERROR(C60/C56,"") | D77: =IFERROR(D60/D56,"") -> 0.88496374 | E77: =IFERROR(E60/E56,"") -> 0.87678457 | F77: =IFERROR(F60/F56,"") -> 0.87830793 | G77: =IFERROR(G60/G56,"") -> 0.90778567 | H77: =IFERROR(H60/H56,"") -> 0.90562748 | I77: =IFERROR(I60/I56,"") -> 0.86812003 | ... M77: =IFERROR(M60/M56,"") -> 0.88761111 | AJ77: =IFERROR(AJ60/AJ56,"") -> 0.88507315 | AK77: =IFERROR(AK60/AK56,"") -> 0.88082034 | AL77: =IFERROR(AL60/AL56,"") -> 0.89420437 | AM77: =IFERROR(AM60/AM56,"") -> 0.92020698 | AN77: =IFERROR(AN60/AN56,"") -> 0.88603058 | AQ77: =IFERROR(AQ60/AQ56,"") -> 0.88503048 | AT77: =IFERROR(AT60/AT56,"") -> 0.80372529 | AU77: =IFERROR(AU60/AU56,"") -> 0.84601537 | AV77: =IFERROR(AV60/AV56,"") -> 0.88267269 | AW77: =IFERROR(AW60/AW56,"") -> 0.88983799 | AX77: =IFERROR(AX60/AX56,"") -> 0.8864618
A78: OPM | J78: =J62/J56 -> 0.35459524 | K78: =K62/K56 -> 0.40941333 | L78: =L62/L56 -> 0.37721968 | M78: =M62/M56 -> 0.36672914 | N78: =N62/N56 -> 0.21976861 | O78: =O62/O56 -> 0.41627872 | P78: =P62/P56 -> 0.43025972 | Q78: =Q62/Q56 -> 0.395486 | ... V78: =V62/V56 -> 0.45575568 | AX78: =AX62/AX56 -> 0.37724422 | AY78: =AY62/AY56 -> 0.38494164 | AZ78: =AZ62/AZ56 -> 0.43323001
A79: Hotel Sepecific matrix
A80: Hotel GTV (RMB bn) | AT80: 13.448 | AU80: 21.791 | AV80: 36.531
A81: Number of domestic hotel room nights (in millions) | D81: 56.4 | E81: =AV81-AJ81-D81 -> 59.2 | F81: =AL81-G81 -> 60.6 | G81: 72.9 | H81: 76.1 | I81: 74.4 | J81: 78.6 | K81: 94 | L81: 109.8 | M81: 110 | N81: 42.8 | O81: 78 | P81: 113.9 | Q81: 119.7 | R81: 101 | S81: 140.8 | T81: 119.8 | U81: 115.3 | V81: =R81*(1+V83) -> 96.96 | W81: =S81*(1+W83) -> 91.52 | X81: =T81*(1+X83) -> 117.404 | Y81: =U81*(1+Y83) -> 83.016 | Z81: =[1]TTM酒店对比!$F$109 -> 129.69 | AA81: =W81*(1+AA83) -> 155.584 | AJ81: 89.4 | AK81: =AV81-AJ81 -> 115.6 | AL81: 133.5 | AM81: =AW81-AL81 -> 150.4 | AN81: 172.6 | AQ81: =D81+AJ81 -> 145.8 | AR81: =AL81+H81 -> 209.6 | AT81: 82 | AU81: 132 | AV81: 205 | AW81: 283.9 | AX81: 392.5 | AY81: 354.5 | AZ81: 476.9
A82: QoQ Growth | E82: =E81/D81-1 -> 0.04964539 | F82: =F81/E81-1 -> 0.023648649 | G82: =G81/F81-1 -> 0.2029703 | H82: =H81/G81-1 -> 0.043895748 | I82: =I81/H81-1 -> -0.022339028 | J82: =J81/I81-1 -> 0.056451613 | K82: =K81/J81-1 -> 0.19592875 | L82: =L81/K81-1 -> 0.16808511 | ... X82: =X81/W81-1 -> 0.28282343 | AJ82: =AJ81/Q81-1 -> -0.25313283 | AK82: =AK81/AJ81-1 -> 0.29306488 | AL82: =AL81/AK81-1 -> 0.15484429 | AM82: =AM81/AL81-1 -> 0.12659176 | AN82: =AN81/AM81-1 -> 0.14760638 | AO82: =AO81/AN81-1 -> -1 | AP82: =AP81/AO81-1 -> #DIV/0! | AQ82: =AQ81/AP81-1 -> #DIV/0! | AR82: =AR81/AQ81-1 -> 0.43758573 | AS82: =AS81/AR81-1 -> -1
A83: YoY Growth | H83: =H81/D81-1 -> 0.34929078 | I83: =I81/E81-1 -> 0.25675676 | J83: =J81/F81-1 -> 0.2970297 | K83: =K81/G81-1 -> 0.28943759 | L83: =L81/H81-1 -> 0.44283837 | M83: =M81/I81-1 -> 0.47849462 | N83: =N81/J81-1 -> -0.45547074 | O83: =O81/K81-1 -> -0.17021277 | ... U83: =U81/Q81-1 -> -0.036758563 | V83: -0.04 | W83: -0.35 | X83: -0.02 | Y83: -0.28 | AA83: 0.7 | AJ83: =AJ81/N81-1 -> 1.088785 | AK83: =AK81/O81-1 -> 0.48205128 | AL83: =AL81/P81-1 -> 0.17208077 | AM83: =AM81/Q81-1 -> 0.25647452 | AN83: =AN81/AJ81-1 -> 0.93064877 | AO83: =AO81/AK81-1 -> -1 | AP83: =AP81/AL81-1 -> -1 | AQ83: =AQ81/AM81-1 -> -0.030585106 | AR83: =AR81/AN81-1 -> 0.21436848 | AS83: =AS81/AO81-1 -> #DIV/0! | AT83: =AT80*1000/AT81 -> 164 | AU83: =AU80*1000/AU81 -> 165.08333 | AV83: =AV80*1000/AV81 -> 178.2 | AX83: =AX81/AW81-1 -> 0.38252906 | AY83: =AY81/AX81-1 -> -0.096815287 | AZ83: =AZ81/AY81-1 -> 0.34527504
A84: YoY Growth vs 2019 | R84: =R81/J81-1 -> 0.28498728 | S84: =S81/K81-1 -> 0.49787234 | T84: =T81/L81-1 -> 0.091074681 | U84: =U81/M81-1 -> 0.048181818 | V84: =V81/J81-1 -> 0.23358779 | W84: =W81/K81-1 -> -0.026382979 | X84: =X81/L81-1 -> 0.069253188 | Y84: =Y81/M81-1 -> -0.24530909 | AA84: =AA81/K81-1 -> 0.65514894 | AZ84: =AZ81/AX81-1 -> 0.21503185
A86: 高星占比 | J86: 0.125 | M86: 0.13 | N86: 0.15 | O86: 0.15 | P86: 0.15 | Q86: 0.15 | R86: 0.167 | T86: 0.16 | V86: 0.174 | X86: 0.15 | Y86: 0.17 | Z86: 0.19 | AZ86: 0.165
J87: =J86*J81 -> 9.825 | M87: =M86*M81 -> 14.3 | N87: =N86*N81 -> 6.42 | P87: =P86*P81 -> 17.085 | Q87: =Q86*Q81 -> 17.955 | R87: =R86*R81 -> 16.867 | T87: =T86*T81 -> 19.168 | V87: =V86*V81 -> 16.87104 | X87: =X86*X81 -> 17.6106 | Y87: =Y86*Y81 -> 14.11272 | Z87: =Z86*Z81 -> 24.6411
A88: 本地占比 | J88: =J89/J81 -> 0.35844382 | R88: 0.53
J89: =R89/(1+90%) -> 28.173684 | R89: =R88*R81 -> 53.53
A90: 异地占比 | J90: =J91/J81 -> 0.64155618 | R90: =1-R88 -> 0.47
J91: =J81-J89 -> 50.426316 | R91: =R90*R81 -> 47.47
A92: Active Merchants (million) | V92: =V87/R87-1 -> 0.00023952096 | AT92: 0.2 | AU92: 0.3 | AV92: 0.3
A94: Revenue (RMB ‘'000) | AT94: 764000 | AU94: 1418000 | AV94: 2713000
A95: Cost of revenues (RMB ‘'000) | AT95: -122000 | AU95: -193000 | AV95: -356000
A96: Gross profit (RMB ‘'000) | AT96: =SUM(AT94:AT95) -> 642000 | AU96: =SUM(AU94:AU95) -> 1225000 | AV96: =SUM(AV94:AV95) -> 2357000
A98: Growth
A99: - Hotel GTV | AU99: =AU80/AT80-1 -> 0.62038965 | AV99: =AV80/AU80-1 -> 0.67642605 | AW99: =AW80/AV80-1 -> -1
A100: - Number of domestic hotel room nights | H100: =IFERROR(H81/D81-1,"") -> 0.34929078 | I100: =IFERROR(I81/E81-1,"") -> 0.25675676 | J100: =IFERROR(J81/F81-1,"") -> 0.2970297 | K100: =IFERROR(K81/G81-1,"") -> 0.28943759 | L100: =IFERROR(L81/H81-1,"") -> 0.44283837 | M100: =IFERROR(M81/I81-1,"") -> 0.47849462 | N100: =IFERROR(N81/J81-1,"") -> -0.45547074 | O100: =IFERROR(O81/K81-1,"") -> -0.17021277 | ... U100: =IFERROR(U81/Q81-1,"") -> -0.036758563 | AR100: =AR81/AQ81-1 -> 0.43758573 | AU100: =AU81/AT81-1 -> 0.6097561 | AV100: =AV81/AU81-1 -> 0.5530303 | AW100: =AW81/AV81-1 -> 0.38487805 | AX100: =AX81/AW81-1 -> 0.38252906 | AY100: =AY81/AX81-1 -> -0.096815287 | AZ100: =AZ81/AY81-1 -> 0.34527504
A101: - Average Daily Room Rate | AU101: =AU83/AT83-1 -> 0.0066056911 | AV101: =AV83/AU83-1 -> 0.079454821 | AW101: =AW83/AV83-1 -> -1
A102: - Revenue | AU102: =AU94/AT94-1 -> 0.85602094 | AV102: =AV94/AU94-1 -> 0.91325811 | AW102: =AW94/AV94-1 -> -1
A104: Hotel monetization rate | AT104: =AT94/1000000/AT80 -> 0.056811422 | AU104: =AU94/1000000/AU80 -> 0.065072736 | AV104: =AV94/1000000/AV80 -> 0.074265692
A105: Hotel gross margin | AT105: =AT96/AT94 -> 0.84031414 | AU105: =AU96/AU94 -> 0.86389281 | AV105: =AV96/AV94 -> 0.86877995
A107: New Initiatives and Others
A108: Gross Transaction Value (RMB bn) | D108: 9 | E108: =AV108-AJ108-D108 -> 7.2 | F108: =AL108-G108 -> 13.4 | G108: 13 | H108: 16.4 | I108: 13.1 | J108: 16.4 | K108: 14.8 | L108: 18.8 | M108: 17.4 | AJ108: 11.8 | AK108: =AV108-AJ108 -> 16.2 | AL108: 26.4 | AM108: =AW108-AL108 -> 29.6 | AN108: 31.2 | AQ108: =AJ108+D108 -> 20.8 | AR108: =AL108+H108 -> 42.8 | AT108: 18 | AU108: 19.5 | AV108: 28 | AW108: 56 | AX108: 67.3
A110: Commission (RMB '000) | N110: 1039479 | O110: 1099492 | P110: 1555759 | Q110: 1733424 | R110: 1828163 | S110: 2193767 | T110: 2211138 | U110: 2325479 | V110: 2282426 | AJ110: 154656 | AK110: =AV110-AJ110 -> 434540 | AL110: 1013523 | AM110: =AW110-AL110 -> 1237215 | AN110: 1794030 | AT110: 0 | AU110: 152143 | AV110: 589196 | AW110: 2250738 | AX110: 4200064 | AY110: 5428154 | AZ110: 8558547
A111: Online Marketing Service (RMB '000) | N111: 58059 | O111: 81966 | P111: 104697 | Q111: 79875 | R111: 157168 | S111: 216821 | T111: 285837 | U111: 322990 | V111: 316088 | AJ111: 201185 | AK111: =AV111-AJ111 -> 140291 | AL111: 163086 | AM111: =AW111-AL111 -> 158420 | AN111: 90818 | AT111: 31739 | AU111: 268918 | AV111: 341476 | AW111: 321506 | AX111: 219856 | AY111: 324597 | AZ111: 982816
A112: % of segment revenue | N112: =N111/N114 -> 0.013928078 | O112: =O111/O114 -> 0.014549076 | P112: =P111/P114 -> 0.012720785 | Q112: =Q111/Q114 -> 0.0086405913 | R112: =R111/R114 -> 0.015945683 | S112: =S111/S114 -> 0.018020409 | T112: =T111/T114 -> 0.020828441 | U112: =U111/U114 -> 0.022010942 | V112: =V111/V114 -> 0.021813429 | AJ112: =AJ111/AJ114 -> 0.29221746 | AK112: =AK111/AK114 -> 0.1035536 | AL112: =AL111/AL114 -> 0.045643997 | AM112: =AM111/AM114 -> 0.020652252 | AN112: =AN111/AN114 -> 0.010574107 | AT112: =AT111/AT114 -> 0.45030078 | AU112: =AU111/AU114 -> 0.40290842 | AV112: =AV111/AV114 -> 0.16712444 | AW112: =AW111/AW114 -> 0.028593983 | AX112: =AX111/AX114 -> 0.010772052 | AY112: =AY111/AY114 -> 0.011900116 | AZ112: =AZ111/AZ114 -> 0.019544567
A113: Other services and sales (RMB '000) | N113: 3070948 | O113: 4452302 | P113: 6569932 | Q113: 7430860 | R113: 7871130 | S113: 9621381 | T113: 11226424 | U113: 12025596 | V113: 11892009 | AJ113: 332636 | AK113: =AV113-AJ113 -> 779936 | AL113: 2396391 | AM113: =AW113-AL113 -> 6275199 | AN113: 6703868 | AT113: 38745 | AU113: 246381 | AV113: 1112572 | AW113: 8671590 | AX113: 15989934 | AY113: 21524042 | AZ113: 40744531
A114: Revenue in Total (RMB '000) | D114: 606996 | E114: 747771 | F114: 1080897 | G114: =AL114-F114 -> 2492103 | H114: 3467791 | I114: 4203043 | J114: 3975607 | K114: 4613109 | L114: 5735540 | M114: 6085598 | N114: 4168486 | O114: 5633760 | P114: 8230388 | Q114: 9244159 | R114: 9856461 | S114: 12031969 | T114: 13723399 | U114: 14674065 | V114: 14490523 | AJ114: =SUM(AJ110,AJ111,AJ113) -> 688477 | AK114: =SUM(AK110,AK111,AK113) -> 1354767 | AL114: =SUM(AL110,AL111,AL113) -> 3573000 | AM114: =SUM(AM110,AM111,AM113) -> 7670834 | AN114: =SUM(AN110,AN111,AN113) -> 8588716 | AQ114: =AJ114+D114 -> 1295473 | AR114: =AL114+H114 -> 7040791 | AT114: =SUM(AT110,AT111,AT113) -> 70484 | AU114: =SUM(AU110,AU111,AU113) -> 667442 | AV114: =SUM(AV110,AV111,AV113) -> 2043244 | AW114: 11243834 | AX114: 20409854 | AY114: 27276793 | AZ114: 50285894
...

Sheet Sheet5
L2: 拍的
C3: 19Q4 | D3: 20Q1 | E3: 20Q2 | F3: 20Q3 | G3: 20Q4 | H3: 21Q1 | I3: 22Q1 | J3: 22Q3 | K3: 23Q1 | L3: 23Q2
B4: 高星占比 | C4: 0.13 | D4: 0.15 | E4: 0.15 | F4: 0.15 | G4: 0.15 | H4: 0.167 | I4: 0.174 | J4: 0.15 | K4: 0.19 | L4: 0.15

Sheet New Segment Reporting
A2: Core Local Commerce | B2: 21Q2 | C2: 21Q3 | D2: 21Q4 | E2: 22Q1 | F2: 22Q2 | G2: 22Q3 | H2: 22Q4 | I2: 23Q1 | J2: 23Q2 | K2: 23Q3 | L2: 23Q4 | M2: 24Q1 | N2: 24Q2 | O2: 24Q3 | P2: 24Q4 | Q2: 25Q1 | R2: 25Q2 | S2: 25Q3 | T2: 25Q4 | U2: 26Q1 | V2: 26Q2
A3: Revenue | G3: =G8/C8-1 -> 0.24641 | H3: =H8/D8-1 -> 0.17386332
A4: Delivery Services | B4: 13861207 | C4: 15392015 | D4: 14990397 | E4: 14233209 | F4: 15950770 | G4: 20107197 | H4: 19772732 | I4: 16905291 | J4: 20374970 | K4: 22983696 | L4: 21927023 | M4: 21065057 | N4: 23021272 | O4: 27784111 | P4: 26194820 | Q4: 25722683 | R4: 23655555 | S4: 23021931 | T4: 23594886 | U4: 24081149 | V4: 26781224
A5: Commission | B5: 12170487 | C5: 13191289 | D5: 12878761 | E5: 11948724 | F5: 12478501 | G5: 16079265 | H5: 14636518 | I5: 15815292 | J5: 18402189 | K5: 20986527 | L5: 19426729 | M5: 20034039 | N5: 22108369 | O5: 26889908 | P5: 24066077 | Q5: 24051420 | R5: 24950978 | S5: 26375119 | T5: 23778171 | U5: 35608836 | V5: 39630201
A6: Online marketing services | B6: 7194528 | C6: 8001353 | D6: 8137460 | E6: 7004924 | F6: 7295796 | G6: 8637608 | H6: 7744751 | I6: 7746614 | J6: 10243600 | K6: 11369580 | L6: 10907096 | M6: 10307416 | N6: 12262733 | O6: 13423641 | P6: 12842276 | Q6: 11862473 | R6: 13547279 | S6: 14193343 | T6: 13136940
A7: Other services and sales | B7: 468840 | C7: 584115 | D7: 1027220 | E7: 992729 | F7: 1054176 | G7: 1503459 | H7: 1318663 | I7: 2418139 | J7: 2179187 | K7: 2351205 | L7: 2869794 | M7: 3219195 | N7: 3289484 | O7: 2085212 | P7: 2463659 | Q7: 2688138 | R7: 3193471 | S7: 3856473 | T7: 4324636 | U7: 4373301 | V7: 5119130
A8: Total Revenue | B8: =SUM(B4:B7) -> 33695062 | C8: =SUM(C4:C7) -> 37168772 | D8: =SUM(D4:D7) -> 37033838 | E8: 34179586 | F8: =SUM(F4:F7) -> 36779243 | G8: =SUM(G4:G7) -> 46327529 | H8: =SUM(H4:H7) -> 43472664 | I8: 42885336 | J8: 51199946 | K8: 57691008 | L8: =SUM(L4:L7) -> 55130642 | M8: 54625707 | N8: 60681858 | O8: 69373099 | P8: 65566832 | Q8: =SUM(Q4:Q7) -> 64324714 | R8: =SUM(R4:R7) -> 65347283 | S8: =SUM(S4:S7) -> 67446866 | T8: =SUM(T4:T7) -> 64834633 | U8: =SUM(U4:U7) -> 64063286 | V8: =SUM(V4:V7) -> 71530555
A10: Cost of Revenues, operating expenses and uncllocated items | C10: -33017764 | D10: -31916464 | E10: -29474445 | F10: -28518250 | G10: -37006236 | H10: -36257422 | I10: -33440266 | J10: -40061425 | K10: 47595177 | L10: 47111217 | M10: -44926860 | N10: -45448273 | O10: -54790696 | P10: 52666505 | Q10: -50833234 | R10: -61626153 | S10: -81517876 | T10: -74880316 | U10: =U12-U8 -> -66093228 | V10: =V12-V8 -> -65862280
A12: Operating Profit | B12: 5914471 | C12: =C8+C10 -> 4151008 | D12: =D8+D10 -> 5117374 | E12: 4705141 | F12: 8260993 | G12: =G8+G10 -> 9321293 | H12: =H8+H10 -> 7215242 | I12: 9445070 | J12: 11138521 | K12: 10095831 | L12: =L8-L10 -> 8019425 | M12: 9698847 | N12: 15233585 | O12: 14582403 | P12: 12900327 | Q12: 13491480 | R12: 3721130 | S12: -14071010 | T12: -10045683 | U12: -2029942 | V12: 5668275
A13: OPM | B13: =B12/B8 -> 0.17552931 | C13: =C12/C8 -> 0.11167999 | D13: =D12/D8 -> 0.13818103 | E13: =E12/E8 -> 0.13765939 | F13: =F12/F8 -> 0.2246102 | G13: =G12/G8 -> 0.20120419 | H13: =H12/H8 -> 0.16597193 | I13: =I12/I8 -> 0.22024008 | ... V13: =V12/V8 -> 0.07924271
A14: Rev YoY Growth | L14: =L8/H8-1 -> 0.26816801 | O14: =O8/K8-1 -> 0.20249414 | P14: =P8/L8-1 -> 0.18929926 | Q14: =Q8/M8-1 -> 0.17755389 | R14: =R8/N8-1 -> 0.076883358 | S14: =S8/O8-1 -> -0.027766282 | T14: =T8/P8-1 -> -0.011167216 | U14: =U8/Q8-1 -> -0.0040641922 | V14: =V8/R8-1 -> 0.094621715
S15: =S13-O13 -> -0.41882619 | T15: =T13-P13 -> -0.35169397 | U15: =U13-Q13 -> -0.24142674 | V15: =V13-R13 -> 0.022298797
A16: New Initiatives | B16: 21Q2 | C16: 21Q3 | D16: 21Q4 | E16: 22Q1 | F16: 22Q2 | G16: 22Q3 | H16: 22Q4 | I16: 23Q1 | J16: 23Q2 | K16: 23Q3 | L16: 23Q4 | M16: 24Q1 | N16: 24Q2 | O16: 24Q3 | P16: 24Q4 | Q16: 25Q1 | R16: 25Q2 | S16: 25Q3 | T16: 25Q4 | U16: 26Q1 | V16: 26Q2
A17: Commission | B17: 418123 | C17: 410618 | D17: 438259 | E17: 350159 | F17: 315518 | G17: 403673 | H17: 297341 | I17: 427765 | J17: 510284 | K17: 550181 | L17: 569576 | M17: 623234 | N17: 716909 | O17: 809773 | P17: 902420 | Q17: 1155584 | R17: 1520537 | S17: 1627723 | T17: 1939056 | U17: 2450084 | V17: 2753081
A18: Online marketing services | B18: 21168 | C18: 20357 | D18: 45169 | E18: 13958 | F18: 20891 | G18: 25821 | H18: 24841 | I18: 36203 | J18: 63577 | K18: 69641 | L18: 76905 | M18: 83482 | N18: 97115 | O18: 115499 | P18: 108230 | Q18: 84548 | R18: 102478 | S18: 133193 | T18: 138186
A19: Other services and sales | B19: 9624879 | C19: 11229623 | D19: 12005867 | E19: 11725051 | F19: 13822711 | G19: 15861869 | H19: 16334093 | I19: 15268168 | J19: 16190817 | K19: 18156077 | L19: 17918828 | M19: 17943461 | N19: 20755195 | O19: 23278948 | P19: 21909814 | Q19: 20992280 | R19: 24870182 | S19: 26280331 | T19: 25184554 | U19: 24525536 | V19: 30359408
A20: Total Revenue | B20: =SUM(B17:B19) -> 10064170 | C20: =SUM(C17:C19) -> 11660598 | D20: =SUM(D17:D19) -> 12489295 | E20: 12089168 | F20: =SUM(F17:F19) -> 14159120 | G20: =SUM(G17:G19) -> 16291363 | H20: =SUM(H17:H19) -> 16656275 | I20: 15732136 | J20: 16764678 | K20: 18775899 | L20: =SUM(L17:L19) -> 18565309 | M20: 18650177 | N20: 21569219 | O20: =24204220 -> 24204220 | P20: 22920464 | Q20: 22232412 | R20: 26493197 | S20: 28041247 | T20: =SUM(T17:T19) -> 27261796 | U20: =SUM(U17:U19) -> 26975620 | V20: =SUM(V17:V19) -> 33112489
A22: Cost of Revenues, operating expenses and uncllocated items | C22: -21688827 | D22: -21850963 | E22: -20542452 | F22: -20948666 | G22: -23062723 | H22: -23021295 | I22: -20761030 | J22: -21957600 | K22: 23887875 | L22: 23398001 | M22: -21407076 | N22: -22883578 | O22: -25230262 | P22: -25096478 | Q22: -24505679 | R22: -28374515 | S22: -29319156 | T22: -31911642 | U22: =U24-U20 -> -29091435 | V22: =V24-V20 -> -34851404
A24: Operating Profit | B24: -8785436 | C24: =C20+C22 -> -10028229 | D24: =D20+D22 -> -9361668 | E24: -8453284 | F24: =F20+F22 -> -6789546 | G24: =G20+G22 -> -6771360 | H24: =H20+H22 -> -6365020 | I24: -5028894 | J24: -5192922 | K24: -5111976 | L24: =L20-L22 -> -4832692 | M24: -2756899 | N24: -1314359 | O24: -1026042 | P24: -2176014 | Q24: -2273267 | R24: -1881318 | S24: -1277909 | T24: =T20+T22 -> -4649846 | U24: -2115815 | V24: -1738915
A25: OPM | B25: =B24/B20 -> -0.87294193 | C25: =C24/C20 -> -0.86000984 | D25: =D24/D20 -> -0.74957538 | E25: =E24/E20 -> -0.69924448 | F25: =F24/F20 -> -0.47951751 | G25: =G24/G20 -> -0.4156411 | H25: =H24/H20 -> -0.38213946 | I25: =I24/I20 -> -0.31965742 | ... V25: =V24/V20 -> -0.052515382
T26: =T25-P25 -> -0.07562511 | U26: =U25-Q25 -> 0.023815787 | V26: =V25-R25 -> 0.01849598
A27: Rev YoY | G27: =G20/C20-1 -> 0.39712929 | H27: =H20/D20-1 -> 0.33364413 | I27: =I20/E20-1 -> 0.3013415 | J27: =J20/F20-1 -> 0.18401977 | K27: =K20/G20-1 -> 0.15250633 | L27: =L20/H20-1 -> 0.1146135 | M27: =M20/I20-1 -> 0.18548282 | N27: =N20/J20-1 -> 0.28658713 | ... V27: =V20/R20-1 -> 0.24984874
A29: Core Local Commerce
A30: Revenue
A31: Delivery Services | P31: =P4/$P$8 -> 0.39951328 | Q31: =Q4/$P$8 -> 0.39231243 | R31: =R4/R$8 -> 0.36199753 | S31: =S4/S$8 -> 0.34133433 | T31: =T4/T$8 -> 0.36392411 | U31: =U4/U$8 -> 0.37589625 | V31: =V4/V$8 -> 0.37440258
A32: Commission | P32: =P5/$P$8 -> 0.36704651 | Q32: =Q5/$P$8 -> 0.36682297 | R32: =R5/R$8 -> 0.3818212 | S32: =S5/S$8 -> 0.39105033 | T32: =T5/T$8 -> 0.36675107 | U32: =U5/U$8 -> 0.55583843 | V32: =V5/V$8 -> 0.55403178
A33: Online marketing services | P33: =P6/$P$8 -> 0.19586543 | Q33: =Q6/$P$8 -> 0.18092186 | R33: =R6/R$8 -> 0.20731205 | S33: =S6/S$8 -> 0.2104374 | T33: =T6/T$8 -> 0.20262226 | U33: =U6/U$8 -> 0 | V33: =V6/V$8 -> 0
A34: Other services and sales | P34: =P7/$P$8 -> 0.037574776 | Q34: =Q7/$P$8 -> 0.040998443 | R34: =R7/R$8 -> 0.048869224 | S34: =S7/S$8 -> 0.057177942 | T34: =T7/T$8 -> 0.06670256 | U34: =U7/U$8 -> 0.068265324 | V34: =V7/V$8 -> 0.071565641
A35: Total Revenue | P35: =P8/$P$8 -> 1 | Q35: =Q8/$P$8 -> 0.9810557 | R35: =R8/R$8 -> 1 | S35: =S8/S$8 -> 1 | T35: =T8/T$8 -> 1 | U35: =U8/U$8 -> 1 | V35: =V8/V$8 -> 1
A36: YoY
A37: Delivery Services | P37: =P4/L4-1 -> 0.19463641 | Q37: =Q4/M4-1 -> 0.22110674 | R37: =R4/N4-1 -> 0.02755204 | S37: =S4/O4-1 -> -0.1713994 | T37: =T4/P4-1 -> -0.099253746 | U37: =U4/Q4-1 -> -0.063816593 | V37: =V4/R4-1 -> 0.13213256
A38: Commission | P38: =P5/L5-1 -> 0.23881262 | Q38: =Q5/M5-1 -> 0.20052776 | R38: =R5/N5-1 -> 0.12857615 | S38: =S5/O5-1 -> -0.01914432 | T38: =T5/P5-1 -> -0.011963146 | U38: =U5/Q5-1 -> 0.48052947 | V38: =V5/R5-1 -> 0.58832255
A39: Online marketing services | P39: =P6/L6-1 -> 0.17742394 | Q39: =Q6/M6-1 -> 0.15086778 | R39: =R6/N6-1 -> 0.10475202 | S39: =S6/O6-1 -> 0.057339287 | T39: =T6/P6-1 -> 0.022944842 | U39: =U6/Q6-1 -> -1 | V39: =V6/R6-1 -> -1
A40: Other services and sales | P40: =P7/L7-1 -> -0.14152061 | Q40: =Q7/M7-1 -> -0.16496578 | R40: =R7/N7-1 -> -0.02918786 | S40: =S7/O7-1 -> 0.84943929 | T40: =T7/P7-1 -> 0.75537118 | U40: =U7/Q7-1 -> 0.62688857 | V40: =V7/R7-1 -> 0.60299874
A41: Total Revenue | P41: =P8/L8-1 -> 0.18929926 | Q41: =Q8/M8-1 -> 0.17755389 | R41: =R8/N8-1 -> 0.076883358 | S41: =S8/O8-1 -> -0.027766282 | T41: =T8/P8-1 -> -0.011167216 | U41: =U8/Q8-1 -> -0.0040641922 | V41: =V8/R8-1 -> 0.094621715
A42: New Initiatives
A43: Commission | O43: =O17/K17-1 -> 0.47183018 | P43: =P17/L17-1 -> 0.58437153 | Q43: =Q17/M17-1 -> 0.85417355 | R43: =R17/N17-1 -> 1.1209624 | S43: =S17/O17-1 -> 1.0100979 | T43: =T17/P17-1 -> 1.148729 | U43: =U17/Q17-1 -> 1.1202128 | V43: =V17/R17-1 -> 0.81059783
A44: Online marketing services | O44: =O18/K18-1 -> 0.65849141 | P44: =P18/L18-1 -> 0.40732072 | Q44: =Q18/M18-1 -> 0.01276922 | R44: =R18/N18-1 -> 0.055223189 | S44: =S18/O18-1 -> 0.15319613 | T44: =T18/P18-1 -> 0.27678093 | U44: =U18/Q18-1 -> -1 | V44: =V18/R18-1 -> -1
A45: Other services and sales | O45: =O19/K19-1 -> 0.28215737 | P45: =P19/L19-1 -> 0.22272584 | Q45: =Q19/M19-1 -> 0.16991254 | R45: =R19/N19-1 -> 0.19826299 | S45: =S19/O19-1 -> 0.12893121 | T45: =T19/P19-1 -> 0.14946453 | U45: =U19/Q19-1 -> 0.16831216 | V45: =V19/R19-1 -> 0.22071515
A46: Total Revenue | P46: =P20/L20-1 -> 0.23458565 | Q46: =Q20/M20-1 -> 0.19207512 | R46: =R20/N20-1 -> 0.22828726 | S46: =S20/O20-1 -> 0.15852719 | T46: =T20/P20-1 -> 0.18940856 | U46: =U20/Q20-1 -> 0.21334653 | V46: =V20/R20-1 -> 0.24984874

Sheet charts

Sheet Sheet1
G7: Ctrip GMV RMB 725bn (US$106 bn) | H7: 2018 (bn) | I7: Ctrip %
F8: WTTC | G8: Global Travel Spending | H8: 5685 | I8: =106/H8 -> 0.018645558
F9: PhoCusWright | G9: Global Travel (Hotel/Air/Rail/Car) | H9: 1400 | I9: =106/H9 -> 0.075714286
F10: PhoCusWright | G10: Online Travel (Hotel/Air/Rail/Car) | H10: 642 | I10: =106/H10 -> 0.16510903
F11: 国家文旅部 | G11: China Travel Spending

Sheet Sheet2
A1: Meituan Hotel
B2: 1-4月 2017 | C2: 1-4月 2018 | D2: 1H 2018 | E2: Q2 2019 | F2: Q3 2019 | G2: Q4 2019
A3: ADR | B3: 175 | C3: 187 | D3: 172 | E3: 192 | F3: 185
A4: Take Rate | B4: 0.072 | C4: 0.072 | E4: 0.086 | F4: 0.076
A6: High-end | C6: 9%-10% | E6: 0.12 | F6: 0.13 | G6: >13%
A7: % In store revenue | E7: 0.3 | F7: 0.25

Sheet Sheet3
A1: 美团 | B1: 18Q4 | C1: 19Q1 | D1: 19Q2 | E1: 19Q3 | F1: 19Q4
A2: 间夜量（百万） | B2: 74.4 | C2: 78.6 | D2: 94 | E2: 109.8 | F2: 110
A3: 同比增速 | B3: 0.25675676 | C3: 0.2970297 | D3: 0.28943759 | E3: 0.44283837 | F3: 0.47849462
A4: 高星占比 | B4: 超10% | C4: ”进一步提升“ | D4: ”同比有所提升“ | F4: 超13%
A6: 携程 | B6: 18Q4 | C6: 19Q1 | D6: 19Q2 | E6: 19Q3 | F6: 19Q4
A7: 酒店收入（RMB 百万） | B7: 2656.235 | C7: 3018.5691 | D7: 3410.2567 | E7: 4117.0545 | F7: 2968.1219
A8: 同比增速 | B8: 0.21611722 | C8: 0.21357506 | D8: 0.2135386 | E8: 0.13518335 | F8: 0.1174169
A9: 低星间夜增速 | B9: 0.5 | C9: 约60% | D9: 超50% | E9: / | F9: 约50%

Sheet Sheet4
AQ1: MS
B2: (RMB mn) | C2: 2Q26 实际 | D2: 2Q26 市场预期 | E2: 实际/ 预期 | F2: 1Q26 实际 | G2: 1Q26 市场预期 | H2: 实际/ 预期 | I2: 4Q25 实际 | J2: 4Q25 市场预期 | K2: 实际/ 预期 | L2: 3Q25 实际 | M2: 3Q25 市场预期 | N2: 实际/ 预期 | O2: 2Q25 实际 | P2: 2Q25 市场预期 | Q2: 实际/ 预期 | R2: 1Q25 实际 | S2: 1Q25 市场预期 | T2: 实际/ 预期 | U2: 4Q24 实际 | V2: 4Q24 市场预期 | W2: 实际/ 预期 | X2: 4Q23 实际 | Y2: 4Q23 市场预期 | Z2: 实际/ 预期 | AA2: 3Q23 实际 | AB2: 3Q23 市场预期 | AC2: 实际/ 预期 | AD2: 2Q23 实际 | AE2: 2Q23 市场预期 | AF2: 实际/ 预期 | AG2: 1Q23 实际 | AH2: 1Q23 市场预期 | AI2: 实际/ 预期 | AJ2: 4Q22 实际 | AK2: 4Q22 市场预期 | AL2: 实际/ 预期 | AM2: 3Q22 实际 | AN2: 3Q22 市场预期 | AO2: 实际/ 预期 | AP2: 2Q22 实际 | AQ2: 2Q22 市场预期 | AR2: 实际/ 预期 | AS2: 1Q22 实际 | AT2: 1Q22 市场预期 | AU2: 实际/ 预期 | AV2: 4Q21 实际 | AW2: 4Q21 市场预期 | AX2: 实际/ 预期 | AY2: 3Q21 实际 | AZ2: 3Q21 市场预期 | BA2: 实际/ 预期 | BB2: 2Q21 实际 | BC2: 2Q21 市场预期 | BD2: 实际/ 预期 | BE2: 1Q21 实际 | BF2: 1Q21 市场预期 | BG2: 实际/ 预期
B3: Revenue | C3: 104643.04 | D3: 100793.4 | E3: =IFERROR(C3/D3-1,"") -> 0.038193413 | F3: 91038.9 | G3: 91136.2 | H3: =F3/G3-1 -> -0.0010676328 | I3: 92096.429 | J3: 92177.9 | K3: =I3/J3-1 -> -0.00088384526 | L3: 95488.1 | M3: 93154.7 | N3: =L3/M3-1 -> 0.025048656 | O3: =91840480/1000 -> 91840.48 | P3: 93689.4 | Q3: =O3/P3-1 -> -0.01973457 | R3: 86557 | S3: 85443 | T3: =R3/S3-1 -> 0.013037932 | U3: 73696 | V3: 72276 | W3: =U3/V3-1 -> 0.019646909 | X3: 73696 | Y3: 72276 | Z3: =X3/Y3-1 -> 0.019646909 | AA3: 76746 | AB3: 76009 | AC3: =AA3/AB3-1 -> 0.0096962202 | AD3: 67965 | AE3: 67200 | AF3: =AD3/AE3-1 -> 0.011383929 | AG3: 58617.472 | AH3: 56481.4 | AI3: =AG3/AH3-1 -> 0.037819034 | AJ3: 60128.9 | AK3: 57923 | AL3: =AJ3/AK3-1 -> 0.038083318 | AM3: 62619 | AN3: 62390 | AO3: =AM3/AN3-1 -> 0.00367046 | AP3: ='Key Financial Data'!Z5/1000 -> 58617.472 | AQ3: 48585 | AR3: =AP3/AQ3-1 -> 0.2064932 | AS3: ='Key Financial Data'!Y5/1000 -> 60128.939 | AT3: 45562 | AU3: =AS3/AT3-1 -> 0.31971685 | AV3: ='Key Financial Data'!X5/1000 -> 62618.892 | AW3: 49236 | AX3: =AV3/AW3-1 -> 0.27181111 | AY3: ='Key Financial Data'!W5/1000 -> 50938.363 | AZ3: 48361 | BA3: =AY3/AZ3-1 -> 0.053294245 | BB3: ='Key Financial Data'!V5/1000 -> 46268.754 | BC3: 42357 | BD3: =BB3/BC3-1 -> 0.092352008 | BE3: 37016 | BF3: 35674 | BG3: =BE3/BF3-1 -> 0.037618434
B4: Gross Profit | C4: 35094.797 | D4: 30368.7 | E4: =IFERROR(C4/D4-1,"") -> 0.15562395 | F4: 25970 | G4: 27027 | H4: =F4/G4-1 -> -0.039109039 | I4: 24127.273 | J4: 25113.6 | K4: =I4/J4-1 -> -0.039274616 | L4: 25181 | M4: 30709.2 | N4: =L4/M4-1 -> -0.18001771 | AF4: =AD4/AE4-1 -> #DIV/0! | AI4: =AG4/AH4-1 -> #DIV/0! | AL4: =AJ4/AK4-1 -> #DIV/0! | AO4: =AM4/AN4-1 -> #DIV/0! | AP4: ='Key Financial Data'!Z8/1000 -> 19817.425 | AQ4: 12415 | AR4: =AP4/AQ4-1 -> 0.59624849 | AS4: ='Key Financial Data'!Y8/1000 -> 16933.396 | AT4: 10476 | AU4: =AS4/AT4-1 -> 0.61639901 | AV4: ='Key Financial Data'!X8/1000 -> 18504.868 | AW4: 10930 | AX4: =AV4/AW4-1 -> 0.69303458 | AY4: ='Key Financial Data'!W8/1000 -> 15574.428 | AZ4: 10326 | BA4: =AY4/AZ4-1 -> 0.5082731 | BB4: ='Key Financial Data'!V8/1000 -> 10740.287 | BC4: 9700 | BD4: =BB4/BC4-1 -> 0.10724608 | BE4: 7200 | BF4: 6956 | BG4: =BE4/BF4-1 -> 0.035077631
B5: 营业利润 | AF5: =AD5/AE5-1 -> #DIV/0! | AI5: =AG5/AH5-1 -> #DIV/0! | AL5: =AJ5/AK5-1 -> #DIV/0! | AO5: =AM5/AN5-1 -> #DIV/0! | AP5: ='Key Financial Data'!Z19/1000 -> 3841.068 | AR5: =-(AP5/AQ5-1) -> #DIV/0! | AS5: ='Key Financial Data'!Y19/1000 -> -750.758 | AT5: -5722 | AU5: =-(AS5/AT5-1) -> 0.86879448 | AV5: ='Key Financial Data'!X19/1000 -> 1272.257 | AW5: -7622 | AX5: =-(AV5/AW5-1) -> 1.1669191 | AY5: ='Key Financial Data'!W19/1000 -> -492.838 | AZ5: -8246 | BA5: =-(AY5/AZ5-1) -> 0.94023308 | BB5: ='Key Financial Data'!V19/1000 -> -5584.242 | BE5: -4767 | BF5: -4031 | BG5: =-(BE5/BF5-1) -> -0.18258497
B6: Operating Profit | C6: 2691.166 | D6: -965.2 | E6: =IFERROR((C6-D6)/ABS(D6),"") -> 3.7881952 | F6: -6469.8 | G6: -7902.5 | H6: =-(F6/G6-1) -> 0.18129706 | I6: -16074.247 | J6: -12645.7 | K6: =-(I6/J6-1) -> -0.27112354 | L6: -19759 | M6: -8870.6 | N6: =-(L6/M6-1) -> -1.2274705 | O6: 226 | P6: 8277 | Q6: =O6/P6-1 -> -0.97269542 | R6: 11218 | S6: 9983 | T6: =R6/S6-1 -> 0.12371031 | U6: 3187 | V6: 2015 | W6: =U6/V6-1 -> 0.58163772 | X6: 3187 | Y6: 2015 | Z6: =X6/Y6-1 -> 0.58163772 | AA6: 6189 | AB6: 7131 | AC6: =AA6/AB6-1 -> -0.13209928 | AD6: 7683 | AE6: 6663 | AF6: =AD6/AE6-1 -> 0.1530842 | AG6: 6262.06 | AH6: 2861.1 | AI6: =AG6/AH6-1 -> 1.1886897 | AJ6: 2960.883 | AK6: 2711 | AL6: =AJ6/AK6-1 -> 0.092173737 | AM6: 4802 | AN6: 2753 | AO6: =AM6/AN6-1 -> 0.74427897 | AP6: ='Key Financial Data'!Z20/1000 -> 6262.06 | AQ6: -108 | AR6: N/A | AS6: ='Key Financial Data'!Y20/1000 -> 2960.883 | AT6: -2539 | AU6: =-(AS6/AT6-1) -> 2.1661611 | AV6: ='Key Financial Data'!X20/1000 -> 4801.736 | AW6: -3930 | AX6: =-(AV6/AW6-1) -> 2.2218158 | AY6: ='Key Financial Data'!W20/1000 -> 3802.741 | AZ6: -4509 | BA6: =-(AY6/AZ6-1) -> 1.8433668 | BB6: ='Key Financial Data'!V20/1000 -> -1840.771 | BC6: -2672 | BD6: =-(BB6/BC6-1) -> 0.3110887 | BE6: -2383 | BF6: -3500 | BG6: =-(BE6/BF6-1) -> 0.31914286
B7: Adj EBITDA | C7: 4098.05 | D7: 2982.3 | E7: =IFERROR((C7-D7)/ABS(D7),"") -> 0.374124 | F7: -3049.4 | G7: -5191.6 | H7: =-(F7/G7-1) -> 0.41262809 | I7: -14024.955 | J7: -11724.1 | K7: =-(I7/J7-1) -> -0.19625003 | L7: -14841.9 | M7: -5323.7 | N7: =-(L7/M7-1) -> -1.7878919 | O7: =2781961/1000 -> 2781.961 | P7: 12221.1 | Q7: =O7/P7-1 -> -0.77236411
B8: Adj Net Profit | C8: 2523.716 | D8: 208 | E8: =IFERROR((C8-D8)/ABS(D8),"") -> 11.13325 | F8: -4967.9 | G8: -5706.9 | H8: =-(F8/G8-1) -> 0.12949237 | I8: -15079.906 | J8: -12864 | K8: =-(I8/J8-1) -> -0.17225637 | L8: -16009.6 | M8: -6019.8 | N8: =-(L8/M8-1) -> -1.6594903 | O8: =1493035/1000 -> 1493.035 | P8: 9851 | Q8: =O8/P8-1 -> -0.84843823 | R8: 10949 | S8: 9727 | T8: =R8/S8-1 -> 0.12562969 | U8: 4375 | V8: 2938 | W8: =U8/V8-1 -> 0.48910824 | X8: 4375 | Y8: 2938 | Z8: =X8/Y8-1 -> 0.48910824 | AA8: 5727 | AB8: 5289 | AC8: =AA8/AB8-1 -> 0.082813386 | AD8: 7660 | AE8: 4517 | AF8: =AD8/AE8-1 -> 0.69581581 | AG8: 5491.44 | AH8: 1617 | AI8: =AG8/AH8-1 -> 2.3960668 | AJ8: 829.1 | AK8: 544 | AL8: =AJ8/AK8-1 -> 0.52408088 | AM8: 3527 | AN8: 838 | AO8: =AM8/AN8-1 -> 3.2088305 | AP8: 2058 | AQ8: -2173 | AR8: N/A | AS8: -3586.252 | AT8: -4133 | AU8: =-(AS8/AT8-1) -> 0.13228841 | AV8: =-3935732/1000 -> -3935.732 | AW8: -5771 | AX8: =-(AV8/AW8-1) -> 0.3180156 | AY8: =-5527 -> -5527 | AZ8: -5580 | BA8: =-(AY8/AZ8-1) -> 0.0094982079 | BB8: =-2217 -> -2217 | BC8: -4043 | BD8: =-(BB8/BC8-1) -> 0.45164482 | BE8: -3892 | BF8: -3972 | BG8: =-(BE8/BF8-1) -> 0.020140987
B9: Margin | AF9: (ppt) | AI9: (ppt) | AL9: (ppt) | AO9: (ppt) | AR9: (ppt) | AU9: (ppt) | AX9: (ppt) | BA9: (ppt) | BD9: (ppt) | BG9: (ppt)
B10: Gross Profit | C10: =C4/C3 -> 0.3353763 | D10: =IFERROR(D4/D3,"") -> 0.30129651 | E10: =IFERROR((C10-D10)*100,"") -> 3.4079787 | F10: =F4/F3 -> 0.28526267 | G10: =G4/G3 -> 0.29655614 | H10: =28.5-29.7 -> -1.2 | I10: =I4/I3 -> 0.26197838 | J10: =J4/J3 -> 0.27244708 | K10: =26.2-27.2 -> -1 | L10: =L4/L3 -> 0.26370825 | M10: =M4/M3 -> 0.32965808 | N10: =26.4-33 -> -6.6 | AF10: =(AD10-AE10)*100 -> 0 | AG10: =AG4/AG3 -> 0 | AH10: =AH4/AH3 -> 0 | AI10: =(AG10-AH10)*100 -> 0 | AJ10: =AJ4/AJ3 -> 0 | AK10: =AK4/AK3 -> 0 | AL10: =(AJ10-AK10)*100 -> 0 | AM10: =AM4/AM3 -> 0 | AN10: =AN4/AN3 -> 0 | AO10: =(AM10-AN10)*100 -> 0 | AP10: =AP4/AP3 -> 0.33808051 | AQ10: =AQ4/AQ3 -> 0.25553154 | AR10: =(AP10-AQ10)*100 -> 8.254897 | AS10: =AS4/AS3 -> 0.28161807 | AT10: =AT4/AT3 -> 0.22992845 | AU10: =(AS10-AT10)*100 -> 5.1689625 | AV10: =AV4/AV3 -> 0.29551574 | AW10: =AW4/AW3 -> 0.22199204 | AX10: =(AV10-AW10)*100 -> 7.3523698 | AY10: =AY4/AY3 -> 0.30575046 | AZ10: =AZ4/AZ3 -> 0.21351916 | BA10: =(AY10-AZ10)*100 -> 9.2231304 | BB10: =BB4/BB3 -> 0.2321283 | BC10: =BC4/BC3 -> 0.22900583 | BD10: =(BB10-BC10)*100 -> 0.31224641 | BE10: =BE4/BE3 -> 0.19451048 | BF10: =BF4/BF3 -> 0.19498795 | BG10: 0
B11: 营业利润率 | C11: =C6/C3 -> 0.025717581 | D11: =IFERROR(D6/D3,"") -> -0.0095760238 | E11: =IFERROR((C11-D11)*100,"") -> 3.5293605 | AF11: =(AD11-AE11)*100 -> 0 | AG11: =AG5/AG3 -> 0 | AH11: =AH5/AH3 -> 0 | AI11: =(AG11-AH11)*100 -> 0 | AJ11: =AJ5/AJ3 -> 0 | AK11: =AK5/AK3 -> 0 | AL11: =(AJ11-AK11)*100 -> 0 | AM11: =AM5/AM3 -> 0 | AN11: =AN5/AN3 -> 0 | AO11: =(AM11-AN11)*100 -> 0 | AP11: =AP5/AP3 -> 0.065527698 | AQ11: =AQ5/AQ3 -> 0 | AR11: =(AP11-AQ11)*100 -> 6.5527698 | AS11: =AS5/AS3 -> -0.012485802 | AT11: =AT5/AT3 -> -0.12558711 | AU11: =(AS11-AT11)*100 -> 11.310131 | AV11: =AV5/AV3 -> 0.020317463 | AW11: =AW5/AW3 -> -0.15480543 | AX11: =(AV11-AW11)*100 -> 17.512289 | AY11: =AY5/AY3 -> -0.0096751833 | AZ11: =AZ5/AZ3 -> -0.17050929 | BA11: =(AY11-AZ11)*100 -> 16.083411 | BB11: =BB5/BB3 -> -0.12069143 | BE11: =BE5/BE3 -> -0.12878215 | BF11: =BF5/BF3 -> -0.11299546 | BG11: -2
B12: Operating Profit | C12: =C7/C3 -> 0.039162183 | D12: =IFERROR(D7/D3,"") -> 0.029588247 | E12: =IFERROR((C12-D12)*100,"") -> 0.95739358 | F12: =F6/F3 -> -0.071066324 | G12: =G6/G3 -> -0.086710879 | H12: =-7.1+8.7 -> 1.6 | I12: =I6/I3 -> -0.17453714 | J12: =J6/J3 -> -0.13718798 | K12: =-17.5+13.7 -> -3.8 | L12: =L6/L3 -> -0.20692631 | M12: =M6/M3 -> -0.095224396 | N12: =-20.7+9.5 -> -11.2 | O12: =O6/O3 -> 0.0024607885 | P12: =P6/P3 -> 0.088345106 | Q12: =0.2-8.8 -> -8.6 | R12: =R6/R3 -> 0.12960246 | S12: =S6/S3 -> 0.11683813 | T12: =13-11.7 -> 1.3 | U12: =U6/U3 -> 0.043245224 | V12: =V6/V3 -> 0.027879241 | W12: =4.3-2.8 -> 1.5 | X12: =X6/X3 -> 0.043245224 | Y12: =Y6/Y3 -> 0.027879241 | Z12: =4.3-2.8 -> 1.5 | AA12: 0.081 | AB12: 0.094 | AC12: -1.3 | AD12: =AD6/AD3 -> 0.11304348 | AE12: =AE6/AE3 -> 0.099151786 | AF12: =(AD12-AE12)*100 -> 1.3891693 | AG12: =AG6/AG3 -> 0.10682924 | AH12: =AH6/AH3 -> 0.050655614 | AI12: =(AG12-AH12)*100 -> 5.6173626 | AJ12: =AJ6/AJ3 -> 0.049242261 | AK12: =AK6/AK3 -> 0.046803515 | AL12: =(AJ12-AK12)*100 -> 0.24387462 | AM12: =AM6/AM3 -> 0.07668599 | AN12: =AN6/AN3 -> 0.044125661 | AO12: =(AM12-AN12)*100 -> 3.2560329 | AP12: =AP6/AP3 -> 0.10682924 | AQ12: =AQ6/AQ3 -> -0.0022229083 | AR12: =(AP12-AQ12)*100 -> 10.905215 | AS12: =AS6/AS3 -> 0.049242229 | AT12: =AT6/AT3 -> -0.055726263 | AU12: =(AS12-AT12)*100 -> 10.496849 | AV12: =AV6/AV3 -> 0.076681906 | AW12: =AW6/AW3 -> -0.079819644 | AX12: =(AV12-AW12)*100 -> 15.650155 | AY12: =AY6/AY3 -> 0.074653773 | AZ12: =AZ6/AZ3 -> -0.093236285 | BA12: =(AY12-AZ12)*100 -> 16.789006 | BB12: =BB6/BB3 -> -0.039784322 | BC12: =BC6/BC3 -> -0.063082843 | BD12: =(BB12-BC12)*100 -> 2.3298522 | BE12: =BE6/BE3 -> -0.064377566 | BF12: =BF6/BF3 -> -0.098110669 | BG12: 4
B13: Adj EBITDA | C13: 0.039 | D13: 0.03 | E13: 0.9 | F13: =F7/F3 -> -0.033495572 | G13: =G7/G3 -> -0.056965289 | H13: =-3.3+5.7 -> 2.4 | I13: =I7/I3 -> -0.15228555 | J13: =J7/J3 -> -0.12718992 | K13: =-15.2+12.7 -> -2.5 | L13: =L7/L3 -> -0.15543193 | M13: =M7/M3 -> -0.057149022 | N13: =-15.5+5.7 -> -9.8 | O13: =O7/O3 -> 0.030291229 | P13: =P7/P3 -> 0.13044272 | Q13: =3-13 -> -10
B14: Adj Net Profit | C14: =C8/C3 -> 0.024117379 | D14: =IFERROR(D8/D3,"") -> 0.0020636272 | E14: =IFERROR((C14-D14)*100,"") -> 2.2053752 | F14: =F8/F3 -> -0.054568981 | G14: =G8/G3 -> -0.062619464 | H14: =-5.5+6.3 -> 0.8 | I14: =I8/I3 -> -0.1637404 | J14: =J8/J3 -> -0.13955623 | K14: =-16.4+14 -> -2.4 | L14: =L8/L3 -> -0.16766068 | M14: =M8/M3 -> -0.064621538 | N14: =-16.8+6.5 -> -10.3 | O14: =O8/O3 -> 0.016256829 | P14: =P8/P3 -> 0.1051453 | Q14: =1.6-10.5 -> -8.9 | R14: =R8/R3 -> 0.12649468 | S14: =S8/S3 -> 0.11384198 | T14: =12.6-11.4 -> 1.2 | U14: =U8/U3 -> 0.059365502 | V14: =V8/V3 -> 0.040649732 | W14: =5.9-4.1 -> 1.8 | X14: =X8/X3 -> 0.059365502 | Y14: =Y8/Y3 -> 0.040649732 | Z14: =5.9-4.1 -> 1.8 | AA14: 0.075 | AB14: 0.07 | AC14: 0.5 | AD14: =AD8/AD3 -> 0.11270507 | AE14: =AE8/AE3 -> 0.067217262 | AF14: 4.6 | AG14: =AG8/AG3 -> 0.093682648 | AH14: =AH8/AH3 -> 0.028628894 | AI14: =(AG14-AH14)*100 -> 6.5053754 | AJ14: =AJ8/AJ3 -> 0.013788711 | AK14: =AK8/AK3 -> 0.0093917787 | AL14: =(AJ14-AK14)*100 -> 0.43969318 | AM14: =AM8/AM3 -> 0.056324758 | AN14: =AN8/AN3 -> 0.01343164 | AO14: =(AM14-AN14)*100 -> 4.2893118 | AP14: =AP8/AP3 -> 0.035108986 | AQ14: =AQ8/AQ3 -> -0.044725738 | AR14: =(AP14-AQ14)*100 -> 7.9834724 | AS14: =AS8/AS3 -> -0.059642696 | AT14: =AT8/AT3 -> -0.090711558 | AU14: =(AS14-AT14)*100 -> 3.1068862 | AV14: =AV8/AV3 -> -0.06285215 | AW14: =AW8/AW3 -> -0.11721098 | AX14: =(AV14-AW14)*100 -> 5.4358834 | AY14: =AY8/AY3 -> -0.10850368 | AZ14: =AZ8/AZ3 -> -0.11538223 | BA14: =(AY14-AZ14)*100 -> 0.68785463 | BB14: =BB8/BB3 -> -0.047915706 | BC14: =BC8/BC3 -> -0.095450575 | BD14: =(BB14-BC14)*100 -> 4.7534869 | BE14: =BE8/BE3 -> -0.10514372 | BF14: =BF8/BF3 -> -0.11134159 | BG14: 0
AA18: ADR | AB18: GTV
X19: High | Y19: 16 | AA19: 420 | AB19: =Y19*AA19 -> 6720 | AC19: =AB19/AB21 -> 0.30769231
Y20: =Y21-Y19 -> 84 | AA20: 180 | AB20: =Y20*AA20 -> 15120
Y21: 100 | AA21: =AB21/Y21 -> 218.4 | AB21: =AB20+AB19 -> 21840
