Workbook
Name _1994: #REF!
Name _1994: #REF!
Name _1994: #REF!
Name _1994: #REF!
Name _1994: #REF!
Name _1994: #REF!
Name _1994: #REF!
Name _1994: #REF!
Name _1994: #REF!
Name _1994: #REF!
Name _1994: #REF!
Name _1994: #REF!
Name _1994: #REF!
Name _1994: #REF!
Name _1994: #REF!
Name _1995: #REF!
Name _1995: #REF!
Name _1995: #REF!
Name _1995: #REF!
Name _1995: #REF!
Name _1995: #REF!
Name _1995: #REF!
Name _1995: #REF!
Name _1995: #REF!
Name _1995: #REF!
Name _1995: #REF!
Name _1995: #REF!
Name _1995: #REF!
Name _1995: #REF!
Name _1995: #REF!
Name _1996: #REF!
Name _1996: #REF!
Name _1996: #REF!
Name _1996: #REF!
Name _1996: #REF!
Name _1996: #REF!
Name _1996: #REF!
Name _1996: #REF!
Name _1996: #REF!
Name _1996: #REF!
Name _1996: #REF!
Name _1996: #REF!
Name _1996: #REF!
Name _1996: #REF!
Name _1996: #REF!
Name _1997: #REF!
Name _1997: #REF!
Name _1997: #REF!
Name _1997: #REF!
Name _1997: #REF!
Name _1997: #REF!
Name _1997: #REF!
Name _1997: #REF!
Name _1997: #REF!
Name _1997: #REF!
Name _1997: #REF!
Name _1997: #REF!
Name _1997: #REF!
Name _1997: #REF!
Name _1997: #REF!

Sheet 同程艺龙
C2: Unit: RMB in million | D2: 2015 | E2: 2016 | F2: 2017 | G2: 2018 | H2: 2019 | J2: 2018Q1 | K2: 2018Q2 | L2: 2018H1 | M2: 2018Q3 | N2: 2018Q4 | O2: 2019Q1 | P2: 2019Q2 | Q2: 2019Q3 | R2: 2019Q4
C3: GMV Break Down (RMB in million) - combined basis | D3: =+D6+D18 -> 36831.5 | E3: =+E6+E18 -> 67795.6 | F3: =+F6+F18 -> 102313.6 | G3: 131500 | H3: =SUM(O3:R3) -> 166100 | J3: 29000 | K3: 28900 | L3: =+L6+L18 -> 57962.9 | M3: 39100 | N3: 34500 | O3: 35900 | P3: 41300 | Q3: 47600 | R3: 41300 | S3: in thousand initial, need to divide 1000 to get mm numbers
C4: Growth | E4: =E3/D3-1 -> 0.84069614 | F4: =F3/E3-1 -> 0.50914809 | G4: =G3/F3-1 -> 0.28526413 | H4: =H3/G3-1 -> 0.26311787 | O4: =O3/J3-1 -> 0.23793103 | P4: =P3/K3-1 -> 0.42906574 | Q4: =Q3/M3-1 -> 0.2173913 | R4: =R3/N3-1 -> 0.19710145
C6: 交通交易额 | D6: 22553.7 | E6: 50525.1 | F6: 80013.4 | H6: =SUM(O6:R6) -> 138642.96 | L6: 47231 | O6: =O246 -> 30607 | P6: =P3-P18 -> 34789.882 | Q6: =Q3-Q18 -> 39438.4 | R6: =R3-R18 -> 33807.675
C7: Growth | E7: =E6/D6-1 -> 1.2402134 | F7: =F6/E6-1 -> 0.58363665
C9: - 机票交易额 | D9: 14778.9 | E9: 28067.6 | F9: 39502.5 | L9: 22697.6
C10: -机票出售数量 segments | D10: 17.9 | E10: 35.4 | F10: 48.5 | L10: 31.1
C11: 机票交易额占交通交易额比例 | D11: =D9/D6 -> 0.65527607 | E11: =E9/E6 -> 0.55551795 | F11: =F9/F6 -> 0.49369856 | L11: =L9/L6 -> 0.48056573
C13: - 来自同城 | D13: 18824.6 | E13: 48068.6 | F13: 77977.7
C14: Growth | E14: =E13/D13-1 -> 1.5534991 | F14: =F13/E13-1 -> 0.622217
C15: - 来自艺龙 | D15: 3729.1 | E15: 2456.5 | F15: 2035.7
C16: Growth | E16: =E15/D15-1 -> -0.34126197 | F16: =F15/E15-1 -> -0.17130063
C18: 住宿交易额 | D18: 14277.8 | E18: 17270.5 | F18: 22300.2 | H18: =SUM(O18:R18) -> 27457.043 | L18: 10731.9 | O18: =O3-O6 -> 5293 | P18: =P70/P86 -> 6510.1176 | Q18: =Q70/Q86 -> 8161.6 | R18: =R70/R86 -> 7492.3253
C19: Growth | E19: =E18/D18-1 -> 0.20960512 | F19: =F18/E18-1 -> 0.29123071
R20: =R18/265 -> 28.272926
C21: - 来自同城 | D21: 901.4 | E21: 1379.7 | F21: 1784.5
C22: Growth | E22: =E21/D21-1 -> 0.53061904 | F22: =F21/E21-1 -> 0.29339712
C23: - 来自艺龙 | D23: 13376.4 | E23: 15890.7 | F23: 20515.7
C24: Growth | E24: =E23/D23-1 -> 0.18796537 | F24: =F23/E23-1 -> 0.29105074
C26: Rev Break Down (RMB in million) - 同程艺龙 combined basis
C27: Revenue (combined basis，同程+艺龙) | D27: =+D126+D201 -> 1606.647 | E27: =+E126+E201 -> 3639.522 | F27: =+F126+F201 -> 5226.09 | G27: 6090.8 | H27: =SUM(O27:R27) -> 7392.932 | J27: 1517.512 | K27: 1314.48 | L27: 2831.992 | M27: 1686.397 | N27: =G27-J27-K27-M27 -> 1572.411 | O27: 1783.411 | P27: 1590.898 | Q27: 2062.13 | R27: 1956.493 | S27: =N27*(1+0.275) -> 2004.824 | T27: =S27+Q27+P27+O27 -> 7441.263
C28: Growth | E28: =E27/D27-1 -> 1.2652904 | F28: =F27/E27-1 -> 0.43592758 | G28: =G27/F27-1 -> 0.16546022 | H28: =H27/G27-1 -> 0.21378669 | O28: =O27/J27-1 -> 0.17522036 | P28: =P27/K27-1 -> 0.21028696 | Q28: =Q27/M27-1 -> 0.22280222 | T28: =T27/G27-1 -> 0.22172178
C30: Cost of revenue | D30: =+D135+D208 -> -868.188 | E30: =+E135+E208 -> -1563.124 | F30: =+F135+F208 -> -1670.587 | H30: =SUM(O30:R30) -> 2317.746 | K30: 370.531 | M30: 479.543 | N30: 556.354 | O30: 498.27 | P30: 561.16 | Q30: 683.255 | R30: 575.061
C32: Gross profit | D32: =D27+D30 -> 738.459 | E32: =E27+E30 -> 2076.398 | F32: =F27+F30 -> 3555.503 | H32: =SUM(O32:R32) -> 5075.186 | K32: 943.949 | M32: 1206.854 | N32: 1016.044 | O32: 1285.141 | P32: 1029.738 | Q32: 1378.875 | R32: 1381.432
C33: Growth | E33: =E32/D32-1 -> 1.8117986 | F33: =F32/E32-1 -> 0.71234176
C34: Margin | D34: =D32/D$27 -> 0.45962741 | E34: =E32/E$27 -> 0.57051393 | F34: =F32/F$27 -> 0.68033712
C36: Total expense | D36: =+D39+D42+D45 -> -2248.992 | E36: =+E39+E42+E45 -> -4276.777 | F36: =+F39+F42+F45 -> -3032.678
C37: Growth | E37: =E36/D36-1 -> 0.90164171 | F37: =F36/E36-1 -> -0.29089639
C38: % of revenue | D38: =D36/D$27*-1 -> 1.3998047 | E38: =E36/E$27*-1 -> 1.175093 | F38: =F36/F$27*-1 -> 0.58029579
C39: R&D | D39: =+D154+D214 -> -563.35 | E39: =+E154+E214 -> -889.368 | F39: =+F154+F214 -> -1036.818 | K39: -317.5 | M39: -403.346 | N39: -439.855 | O39: -430.052 | P39: -352.154 | Q39: -359.587 | R39: -377.316
C40: Growth | E40: =E39/D39-1 -> 0.57871306 | F40: =F39/E39-1 -> 0.16579189
C41: % of revenue | D41: =D39/D$27*-1 -> 0.35063707 | E41: =E39/E$27*-1 -> 0.24436396 | F41: =F39/F$27*-1 -> 0.19839268
C42: S&M | D42: =+D156+D215 -> -1356.228 | E42: =+E156+E215 -> -2397.953 | F42: =+F156+F215 -> -1765.709 | K42: -464.096 | M42: -576.207 | N42: -559.02 | O42: -469.723 | P42: -407.187 | Q42: -627.565 | R42: -741.975
C43: Growth | E43: =E42/D42-1 -> 0.76810463 | F43: =F42/E42-1 -> -0.26365988
C44: % of revenue | D44: =D42/D$27*-1 -> 0.84413564 | E44: =E42/E$27*-1 -> 0.65886482 | F44: =F42/F$27*-1 -> 0.33786425
C45: G&A | D45: =+D158+D216 -> -329.414 | E45: =+E158+E216 -> -989.456 | F45: =+F158+F216 -> -230.151 | K45: -133.749 | M45: -163.476 | N45: -255.571 | O45: -228.322 | P45: -99.805 | Q45: -97.516 | R45: -199.51
C46: Growth | E46: =E45/D45-1 -> 2.0036853 | F46: =F45/E45-1 -> -0.76739643
C47: % of revenue | D47: =D45/D$27*-1 -> 0.20503197 | E47: =E45/E$27*-1 -> 0.27186427 | F47: =F45/F$27*-1 -> 0.044038851
C49: Operating (loss)/profit | D49: =+D163+D221 -> -1390.0943 | E49: =+E163+E221 -> -2190.4373 | F49: =+F163+F221 -> 597.55031 | K49: 63.617 | M49: 104.515 | N49: -167.296 | O49: 187.452 | P49: 218.174 | Q49: 347.219 | R49: 106.682
C50: Growth | E50: =E49/D49-1 -> 0.57574732 | F50: =F49/E49-1 -> -1.2727995
C51: Margin | D51: =D49/D$27 -> -0.8652145 | E51: =E49/E$27 -> -0.60184753 | F51: =F49/F$27 -> 0.11433984
C54: Adjusted EBITDA | D54: =+D165+D240 -> -998.50448 | E54: =+E165+E240 -> -46.551765 | F54: =+F165+F240 -> 952.054 | G54: 1481.649 | H54: =SUM(O54:R54) -> 2018.532 | J54: 459.449 | K54: 312.705 | M54: 428.471 | N54: =G54-J54-K54-M54 -> 281.024 | O54: 615.57 | P54: 440.536 | Q54: 547.317 | R54: 415.109
C55: Growth | E55: =E54/D54-1 -> -0.95337851 | F55: =F54/E54-1 -> -21.451512 | G55: =G54/F54-1 -> 0.55626572 | H55: =H54/G54-1 -> 0.36235505 | O55: =O54/J54-1 -> 0.3398005 | P55: =P54/K54-1 -> 0.40879103 | Q55: =Q54/M54-1 -> 0.27737233 | R55: =R54/N54-1 -> 0.47713007
C56: Margin | D56: =D54/D$27 -> -0.62148343 | E56: =E54/E$27 -> -0.012790626 | F56: =F54/F$27 -> 0.18217329 | G56: =G54/G$27 -> 0.24326016 | H56: =H54/H$27 -> 0.27303538 | J56: =J54/J27 -> 0.30276466 | K56: =K54/K27 -> 0.23789255 | M56: =M54/M27 -> 0.25407481 | N56: =N54/N27 -> 0.17872172 | O56: =O54/O27 -> 0.34516441 | P56: =P54/P27 -> 0.27691027 | Q56: =Q54/Q27 -> 0.26541343 | R56: =R54/R27 -> 0.21216994
C58: Adjusted profit for the year | D58: =+D171+D230 -> -1298.128 | E58: =+E171+E230 -> -2251.694 | F58: 683.995 | G58: 1140.689 | H58: =SUM(O58:R58) -> 1396.92 | J58: 412.498 | K58: -32.71 | M58: 314.729 | N58: 197.442 | O58: 448.45 | P58: 198.161 | Q58: 419.234 | R58: 331.075
C59: Growth | E59: =E58/D58-1 -> 0.73457009 | F59: =F58/E58-1 -> -1.3037691 | G59: =G58/F58-1 -> 0.66768617 | H59: =H58/G58-1 -> 0.22462827 | O59: =O58/J58-1 -> 0.087156786 | P59: =P58/K58-1 -> -7.0581168 | Q59: =Q58/M58-1 -> 0.33204757 | R59: =R58/N58-1 -> 0.67682155
C60: Margin | D60: =D58/D$27 -> -0.80797338 | E60: =E58/E$27 -> -0.6186785 | F60: =F58/F$27 -> 0.13088083 | G60: =G58/G$27 -> 0.18728065 | H60: =H58/H$27 -> 0.18895345 | J60: =J58/J27 -> 0.2718252 | K60: =K58/K27 -> -0.024884365 | M60: =M58/M27 -> 0.18662806 | N60: =N58/N27 -> 0.12556641 | O60: =O58/O27 -> 0.25145634 | P60: =P58/P27 -> 0.12455921 | Q60: =Q58/Q27 -> 0.20330144 | R60: =R58/R27 -> 0.1692186
C62: Rev Break Down (RMB in million) - accounting basis
C63: 总收入 - accounting | D63: =+D66+D70+D77 -> 1026.149 | E63: =+E66+E70+E77 -> 2204.65 | F63: =+F66+F70+F77 -> 2518.625 | G63: =+G66+G70+G77 -> 5255.639 | H63: =SUM(O63:R63) -> 7392.932 | J63: 682.364 | K63: =K27 -> 1314.48 | L63: =+L66+L70+L77 -> 1996.9 | M63: =M27 -> 1686.397 | N63: =5255.639-M63-K63-J63 -> 1572.398 | O63: 1783.411 | P63: =P27 -> 1590.898 | Q63: =Q27 -> 2062.13 | R63: =7392.932-Q63-P63-O63 -> 1956.493
C64: Growth | E64: =E63/D63-1 -> 1.1484697 | F64: =F63/E63-1 -> 0.1424149 | G64: =G63/F63-1 -> 1.0867096 | H64: =H63/G63-1 -> 0.40666663 | O64: =O63/J63-1 -> 1.6135772 | P64: =P63/K63-1 -> 0.21028696 | Q64: =Q63/M63-1 -> 0.22280222
C66: 交通收入 | D66: 89.4 | E66: 86.7 | F66: 61.3 | G66: 3232.521 | H66: =SUM(O66:R66) -> 4517.658 | J66: 208.169 | K66: 829.487 | L66: 1037.7 | M66: 1122.15 | N66: =3232.521-M66-K66-J66 -> 1072.715 | O66: 1258.948 | P66: 937.092 | Q66: 1139.621 | R66: =4517.658-Q66-P66-O66 -> 1181.997
C67: Growth | E67: =E66/D66-1 -> -0.030201342 | F67: =F66/E66-1 -> -0.29296424 | G67: =G66/F66-1 -> 51.732806 | H67: =H66/G66-1 -> 0.39756493 | O67: =O66/J66-1 -> 5.0477208 | P67: =P66/K66-1 -> 0.12972476 | Q67: =Q66/M66-1 -> 0.01556922 | R67: =R66/N66-1 -> 0.10187422
C68: 交通收入占比 | D68: =D66/D$63 -> 0.087121851 | E68: =E66/E$63 -> 0.03932597 | F68: =F66/F$63 -> 0.024338677 | G68: =G66/G$63 -> 0.61505766 | H68: =H66/H$63 -> 0.61107799 | J68: =J66/J63 -> 0.30507031 | K68: =K66/K63 -> 0.63103813 | L68: =L66/L$63 -> 0.51965547 | M68: =M66/M63 -> 0.66541271 | N68: =N66/N63 -> 0.68221595 | O68: =O66/O63 -> 0.70592141 | P68: =P66/P63 -> 0.58903336 | Q68: =Q66/Q63 -> 0.55264266 | R68: =R66/R63 -> 0.60414067
C70: 住宿收入 | D70: 907.649 | E70: 2094.05 | F70: 2361.625 | G70: 1830.37 | H70: =SUM(O70:R70) -> 2358.123 | J70: 449.586 | K70: 440.982 | L70: 890.6 | M70: 515.722 | N70: =1830.37-M70-K70-J70 -> 424.08 | O70: 489.164 | P70: 553.36 | Q70: 693.736 | R70: =2358.123-Q70-P70-O70 -> 621.863
C71: Growth | E71: =E70/D70-1 -> 1.3071143 | F71: =F70/E70-1 -> 0.12777871 | G71: =G70/F70-1 -> -0.22495316 | H71: =H70/G70-1 -> 0.28833132 | O71: =O70/J70-1 -> 0.088032101 | P71: =P70/K70-1 -> 0.2548358 | Q71: =Q70/M70-1 -> 0.34517434 | R71: =R70/N70-1 -> 0.46638134
C72: 住宿收入占比 | D72: =D70/D$63 -> 0.88451969 | E72: =E70/E$63 -> 0.94983331 | F72: =F70/F$63 -> 0.9376644 | G72: =G70/G$63 -> 0.34826783 | H72: =H70/H$63 -> 0.31896993 | J72: =J70/J63 -> 0.65886536 | K72: =K70/K63 -> 0.33548019 | L72: =L70/L$63 -> 0.44599129 | M72: =M70/M63 -> 0.30581293 | N72: =N70/N63 -> 0.26970271 | O72: =O70/O63 -> 0.27428562 | P72: =P70/P63 -> 0.34782871 | Q72: =Q70/Q63 -> 0.3364172 | R72: =R70/R63 -> 0.31784576
C73: % of Distribution Channel Revenue as Total Accommodation Revenue | F73: 0.4 | G73: 0.2 | H73: 0.2 | Q73: 0.08
C77: 其他业务收入 | D77: 29.1 | E77: 23.9 | F77: 95.7 | G77: 192.748 | H77: =SUM(O77:R77) -> 517.151 | J77: 24.609 | K77: 44.011 | L77: 68.6 | M77: 48.525 | N77: =192.748-M77-K77-J77 -> 75.603 | O77: 35.299 | P77: 100.446 | Q77: 228.773 | R77: =517.151-Q77-P77-O77 -> 152.633
C78: Growth | E78: =E77/D77-1 -> -0.17869416 | F78: =F77/E77-1 -> 3.0041841 | G78: =G77/F77-1 -> 1.0140857 | H78: =H77/G77-1 -> 1.6830421 | O78: =O77/J77-1 -> 0.43439392 | P78: =P77/K77-1 -> 1.2822931 | Q78: =Q77/M77-1 -> 3.7145389 | R78: =R77/N77-1 -> 1.0188749
C79: 其他业务收入占比 | D79: =D77/D$63 -> 0.028358455 | E79: =E77/E$63 -> 0.010840723 | F79: =F77/F$63 -> 0.037996923 | G79: =G77/G$63 -> 0.036674513 | H79: =H77/H$63 -> 0.069952084 | J79: =J77/J63 -> 0.036064329 | K79: =K77/K63 -> 0.033481681 | L79: =L77/L$63 -> 0.034353248 | M79: =M77/M63 -> 0.028774363 | N79: =N77/N63 -> 0.048081338 | O79: =O77/O63 -> 0.01979297 | P79: =P77/P63 -> 0.063137926 | Q79: =Q77/Q63 -> 0.11094014 | R79: =R77/R63 -> 0.078013568
C81: Take rate （变现率 = 收入 / 交易额）
C83: Blended take rate | D83: =D27/D3 -> 0.043621547 | E83: =E27/E3 -> 0.053683749 | F83: =F27/F3 -> 0.051079133 | G83: =G27/G3 -> 0.046317871 | H83: =H27/H3 -> 0.044508922 | J83: =J27/J3 -> 0.052328 | K83: =K27/K3 -> 0.045483737 | M83: =M27/M3 -> 0.043130358 | N83: =N27/N3 -> 0.04557713 | O83: =O63/O3 -> 0.049677187 | P83: =P63/P3 -> 0.038520533 | Q83: =Q63/Q3 -> 0.043322059 | R83: =R63/R3 -> 0.047372712
C85: Transportation take rate | O85: =O66/O6 -> 0.041132682 | P85: =P66/P6 -> 0.026935762 | Q85: =Q66/Q6 -> 0.028896228 | R85: =R66/R6 -> 0.034962387
C86: Accommodation take rate | O86: =O70/O18 -> 0.092417155 | P86: 0.085 | Q86: 0.085 | R86: 0.083
C88: 同程 | S88: 腾讯平台MAU按入口划分
C89: 交通 | D89: 0.027 | E89: 0.028 | F89: 0.032 | S89: 微信钱包 | T89: 0.528
C90: 住宿 | D90: 0.078 | E90: 0.06 | F90: 0.057 | S90: 可交互广告/微信广告 | T90: 0.349
C91: 艺龙 | S91: 微信的分享与搜索功能 | T91: 0.123
C92: 交通 | D92: 0.024 | E92: 0.035 | F92: 0.03
C93: 住宿 | D93: 0.05 | E93: 0.089 | F93: 0.089
D94: 2015 | E94: 2016 | F94: 2017 | G94: 2018 | H94: 2019 | J94: 2018Q1 | K94: 2018Q2 | L94: 2018H1 | M94: 2018Q3 | N94: 2018Q4 | O94: 2019Q1 | P94: 2019Q2 | Q94: 2019Q3 | R94: 2019Q4 | S94: 2020Q1
C95: Users (mm) - Combined basis
C96: MAU | D96: 88.7 | E96: 99.5 | F96: 121.2 | G96: 175.2 | H96: =AVERAGE(O96:R96) -> 205.2 | J96: 163.4 | K96: 157.4 | L96: 160.4 | M96: 206.3 | N96: 173.7 | O96: 199.3 | P96: 181.6 | Q96: 234 | R96: 205.9 | S96: 148.4
C97: Growth | E97: =E96/D96-1 -> 0.12175874 | F97: =F96/E96-1 -> 0.21809045 | G97: =G96/F96-1 -> 0.44554455 | H97: =H96/G96-1 -> 0.17123288 | O97: =O96/J96-1 -> 0.21970624 | P97: =P96/K96-1 -> 0.15374841 | Q97: =Q96/M96-1 -> 0.13427048 | R97: =R96/N96-1 -> 0.18537709 | S97: =S96/O96-1 -> -0.25539388
C98: MPU | D98: 3.9 | E98: 9.1 | F98: 15.6 | G98: 20 | H98: =AVERAGE(O98:R98) -> 26.925 | J98: 16.9 | K98: 18 | L98: 17.5 | M98: 22.6 | N98: 22.3 | O98: 23.1 | P98: 27.7 | Q98: 29.8 | R98: 27.1 | S98: 14.8
C99: Growth | E99: =E98/D98-1 -> 1.3333333 | F99: =F98/E98-1 -> 0.71428571 | G99: =G98/F98-1 -> 0.28205128 | H99: =H98/G98-1 -> 0.34625 | O99: =O98/J98-1 -> 0.36686391 | P99: =P98/K98-1 -> 0.53888889 | Q99: =Q98/M98-1 -> 0.31858407 | R99: =R98/N98-1 -> 0.21524664 | S99: =S98/O98-1 -> -0.35930736
C100: Paying ratio | D100: =D98/D96 -> 0.043968433 | E100: =E98/E96 -> 0.091457286 | F100: =F98/F96 -> 0.12871287 | G100: =G98/G96 -> 0.11415525 | H100: =H98/H96 -> 0.13121345 | J100: =J98/J96 -> 0.10342717 | K100: =K98/K96 -> 0.11435832 | L100: =L98/L96 -> 0.10910224 | M100: =M98/M96 -> 0.1095492 | N100: =N98/N96 -> 0.12838227 | O100: =O98/O96 -> 0.11590567 | P100: =P98/P96 -> 0.15253304 | Q100: =Q98/Q96 -> 0.12735043 | R100: =R98/R96 -> 0.13161729 | S100: =S99/O99-1 -> -1.9794023
C102: MAU（来自腾讯平台, Tencent-based platforms） | F102: 79.6 | G102: =74.2/0.528 -> 140.5303 | H102: =AVERAGE(O102:R102) -> 172.90715 | L102: 123.6 | O102: =105.2+35.1+32.8 -> 173.1 | P102: =97.2/P107 -> 152.59027 | Q102: 192.15 | R102: =113.6/0.657*4-Q102-P102-O102 -> 173.78835 | S102: =+S96*S104 -> 122.43
C103: Growth | G103: =G102/F102-1 -> 0.76545607 | H103: =H102/G102-1 -> 0.23039053 | S103: =S102/O102-1 -> -0.29272097
C104: % of total MAU | F104: =F102/F$96 -> 0.65676568 | G104: =G102/G$96 -> 0.8021136 | H104: =H102/H$96 -> 0.84262745 | O104: =O102/O96 -> 0.86853989 | P104: =P102/P96 -> 0.84025477 | Q104: =Q102/Q96 -> 0.82115385 | R104: =R102/R96 -> 0.84404249 | S104: 0.825
C106: Among total average MAUs of our Tencent-based platforms
C107: Weixin Payment (Wallet) | G107: 0.528 | H107: =AVERAGE(O107:R107) -> 0.638 | J107: =$G$102*G107 -> 74.2 | M107: 0.503 | O107: 0.608 | P107: 0.637 | Q107: 0.65 | R107: 0.657 | S107: 0.833
C108: Interactive advertisements / Weixin based ad | G108: 0.349 | H108: =AVERAGE(O108:R108) -> 0.2255 | J108: =$G$102*G108 -> 49.045076 | M108: 0.305 | O108: 0.203 | P108: 0.228 | Q108: 0.252 | R108: 0.219 | S108: 0.096
C109: Sharing and search functions in Weixin | G109: 0.123 | H109: =AVERAGE(O109:R109) -> 0.1365 | J109: =$G$102*G109 -> 17.285227 | M109: =1-M107-M108 -> 0.192 | O109: 0.189 | P109: 0.135 | Q109: 0.098 | R109: 0.124 | S109: 0.071
C111: MAU（非腾讯平台） | F111: =+F96-F102 -> 41.6 | G111: =+G96-G102 -> 34.669697 | H111: =+H96-H102 -> 32.292846 | O111: =+O96-O102 -> 26.2 | P111: =+P96-P102 -> 29.009733 | Q111: =+Q96-Q102 -> 41.85 | R111: =+R96-R102 -> 32.111652 | S111: =+S96-S102 -> 25.97
C112: Growth | G112: =G111/F111-1 -> -0.16659382 | H112: =H111/G111-1 -> -0.068557008 | S112: =S111/O111-1 -> -0.008778626
C113: % of total MAU | F113: =F111/F$96 -> 0.34323432 | G113: =G111/G$96 -> 0.1978864 | H113: =H111/H$96 -> 0.15737255 | O113: =O111/O$96 -> 0.13146011 | P113: =P111/P$96 -> 0.15974523 | Q113: =Q111/Q$96 -> 0.17884615 | R113: =R111/R$96 -> 0.15595751 | S113: =S111/S$96 -> 0.175
C118: MPU（来自腾讯平台） | F118: 14 | L118: 16.2 | M118: 21.2
C119: Growth
C120: Paying ratio | F120: =F118/F102 -> 0.1758794 | L120: =L118/L102 -> 0.13106796
C122: 复购率（占GMV） | D122: 0.391 | F122: 0.503 | G122: 0.67 | L122: 0.647 | M122: 0.753
C123: Cross-selling ratio | J123: 0.12 | M123: 0.16 | N123: 0.2 | O123: 0.21 | P123: 0.23 | Q123: 0.26 | R123: 0.28
D124: 2015 | E124: 2016 | F124: 2017 | G124: 2018 | J124: 2018Q1 | K124: 2018Q2 | L124: 2018H1 | M124: 2018Q3 | N124: 2018Q4 | O124: 2019Q1 | P124: 2019Q2 | Q124: 2019Q3 | R124: 2019Q4
C125: Financials (RMB in million) - accounting basis
C126: Total Revenue | D126: 1026.124 | E126: 2204.565 | F126: 2518.591 | G126: 5255.639 | J126: 682.364 | K126: 1314.48 | L126: 1996.844 | M126: 1686.397 | N126: 1572.398 | O126: 1783.411 | P126: 1590.898 | Q126: 2062.13 | R126: 1956.493
C127: Growth | E127: =(E126-D126)/D126 -> 1.1484392 | F127: =(F126-E126)/E126 -> 0.14244352 | L127: 0.6 | O127: =O126/J126-1 -> 1.6135772 | P127: =P126/K126-1 -> 0.21028696 | Q127: =Q126/M126-1 -> 0.22280222 | R127: =R126/N126-1 -> 0.2442734
C128: Accommodation | J128: 449.586 | K128: 440.982 | L128: =J128+K128 -> 890.568 | M128: 515.722 | N128: 424.08 | O128: 489.164 | P128: 553.36 | Q128: 693.736 | R128: 621.863
J129: =J128/J126 -> 0.65886536 | K129: =K128/K126 -> 0.33548019 | M129: =M128/M126 -> 0.30581293 | N129: =N128/N126 -> 0.26970271 | O129: =O128/O126 -> 0.27428562 | P129: =P128/P126 -> 0.34782871 | Q129: =Q128/Q126 -> 0.3364172 | R129: =R128/R126 -> 0.31784576
C130: Transportation | J130: 208.169 | K130: 829.487 | L130: =J130+K130 -> 1037.656 | M130: 1122.15 | N130: 1072.715 | O130: 1258.948 | P130: 937.092 | Q130: 1139.621 | R130: 1181.997
J131: =J130/J126 -> 0.30507031 | K131: =K130/K126 -> 0.63103813 | M131: =M130/M126 -> 0.66541271 | N131: =N130/N126 -> 0.68221595 | O131: =O130/O126 -> 0.70592141 | P131: =P130/P126 -> 0.58903336 | Q131: =Q130/Q126 -> 0.55264266 | R131: =R130/R126 -> 0.60414067
...

Sheet 同程艺龙 Peers
C2: 2019Q3
C3: Tongcheng-Elong | D3: Meituan In-store, Hotel & Travel | E3: Ctrip
B4: GMV (mn) | C4: =同程艺龙!Q3 -> 47600 | D4: 63900
B5: YoY Growth | C5: =同程艺龙!Q4 -> 0.2173913 | D5: 0.3
B6: Transportation | C6: =同程艺龙!Q6 -> 39438.4
B7: Accommodation | C7: =同程艺龙!Q18 -> 8161.6 | D7: =D36*D37 -> 21960 | G7: 同程控股
G8: 旅行社收入 | H8: 198
B9: Revenue | C9: =同程艺龙!Q27 -> 2062.13 | D9: 6181.117 | E9: =E11+E14+E17+E23+E20 -> 10499 | G9: 航空 | H9: 6.2
B10: YoY Growth | C10: =同程艺龙!Q28 -> 0.22280222 | D10: 0.39 | E10: =E9/9396-1 -> 0.11739038 | G10: 金服 | H10: 3.9
B11: Transportation Revenue | C11: =同程艺龙!Q66 -> 1139.621 | E11: 3721 | H11: =SUM(H8:H10) -> 208.1
B12: YoY Growth | C12: =同程艺龙!Q67 -> 0.01556922 | E12: 0.03
B13: as % of Total Revenue | C13: =C11/C9 -> 0.55264266 | E13: =E11/E9 -> 0.35441471
B14: Accommodation Revenue | C14: =同程艺龙!Q70 -> 693.736 | D14: =D7*D29 -> 1756.8 | E14: 4117
B15: YoY Growth | C15: =同程艺龙!Q71 -> 0.34517434 | D15: 0.444 | E15: 0.14
B16: as % of Total Revenue | C16: =C14/C9 -> 0.3364172 | D16: =D14/D9 -> 0.28422047 | E16: =E14/E9 -> 0.39213258
B17: Packaged Tour | E17: 1638
B18: YoY Growth | E18: 0.19
B19: as % of Total Revenue | E19: =E17/E9 -> 0.15601486
B20: Corporate Travel | E20: 335
B21: YoY Growth | E21: 0.26
B22: as % of Total Revenue | E22: =E20/E9 -> 0.031907801
B23: Others | C23: =同程艺龙!Q77 -> 228.773 | E23: 688
B24: YoY Growth | C24: =同程艺龙!Q78 -> 3.7145389 | E24: =688/503-1 -> 0.36779324
B25: as % of Total Revenue | C25: =C23/C9 -> 0.11094014 | E25: =E23/E9 -> 0.06553005
B27: Take Rate
B28: Transportation Revenue | C28: =C11/C6 -> 0.028896228
B29: Accommodation Revenue | C29: =C14/C7 -> 0.085 | D29: 0.08
B31: Gross Profit | C31: =同程艺龙!Q150 -> 1378.875 | E31: 8319
B32: Gross Margin | C32: =C31/C9 -> 0.66866541 | E32: =E31/E9 -> 0.79236118
B33: Operating Profit | C33: =同程艺龙!Q163 -> 347.219 | E33: 2242
B34: Operating Margin | C34: =C33/C9 -> 0.16837881 | E34: =E33/E9 -> 0.21354415
B36: Hotel Room Nights (mn) | C36: =C7/C37 -> 30.798491 | D36: 109.8
B37: ADR | C37: 265 | D37: 200

Sheet 同程艺龙Charts
I1: 2018Q3 | J1: 2019Q2 | K1: 2019Q3 | L1: 2019Q4
H2: Transportation | I2: 1122.15 | J2: 937.092 | K2: 1139.621 | L2: 1956.493
H3: Accommodation | I3: 515.722 | J3: 553.36 | K3: 693.736 | L3: 1181.997
H4: Others | I4: 48.525 | J4: 100.446 | K4: 228.773 | L4: 621.863
B30: Q1 | D30: Q2 | F30: Q3 | H30: Q4
B31: 2018 | C31: 2019 | D31: 2018 | E31: 2019 | F31: 2018 | G31: 2019 | H31: 2018 | I31: 2019
A32: GMV | B32: =同程艺龙!J3 -> 29000 | C32: =同程艺龙!O3 -> 35900 | D32: =同程艺龙!K3 -> 28900 | E32: =同程艺龙!P3 -> 41300 | F32: =同程艺龙!M3 -> 39100 | G32: =同程艺龙!Q3 -> 47600 | H32: =同程艺龙!N3 -> 34500 | I32: =同程艺龙!R3 -> 41300
A33: Revenue | B33: =同程艺龙!J27 -> 1517.512 | C33: =同程艺龙!O27 -> 1783.411 | D33: =同程艺龙!K27 -> 1314.48 | E33: =同程艺龙!P27 -> 1590.898 | F33: =同程艺龙!M27 -> 1686.397 | G33: =同程艺龙!Q27 -> 2062.13 | H33: =同程艺龙!N27 -> 1572.411 | I33: =同程艺龙!R27 -> 1956.493
A34: GMV YoY Growth | C34: =C32/B32-1 -> 0.23793103 | E34: =E32/D32-1 -> 0.42906574 | G34: =G32/F32-1 -> 0.2173913 | I34: =I32/H32-1 -> 0.19710145
A35: Revenue YoY Growth | C35: =C33/B33-1 -> 0.17522036 | E35: =E33/D33-1 -> 0.21028696 | G35: =G33/F33-1 -> 0.22280222 | I35: =I33/H33-1 -> 0.24426311
A36: Take Rate | B36: =B33/B32 -> 0.052328 | C36: =C33/C32 -> 0.049677187 | D36: =D33/D32 -> 0.045483737 | E36: =E33/E32 -> 0.038520533 | F36: =F33/F32 -> 0.043130358 | G36: =G33/G32 -> 0.043322059 | H36: =H33/H32 -> 0.04557713 | I36: =I33/I32 -> 0.047372712
B39: 2018Q2 | C39: 2018Q3 | D39: 2018Q4 | E39: 2019Q2 | F39: 2019Q3 | G39: 2019Q4
A40: Employee benefit expenses | B40: 55.89 | C40: 72.935 | D40: 137.136 | E40: 61.647 | F40: 68.342 | G40: 33.912
A41: Order processing cost | B41: 195.027 | C41: 240.546 | D41: 208.369 | E41: 243.566 | F41: 277.125 | G41: 223.966
A42: Cost of pre-purchased inventory risk taking products | B42: 28.823 | C42: 64.508 | D42: 57.562 | E42: 101.801 | F42: 151.619 | G42: 129.774
A43: Depreciations of PP&E | B43: 23.87 | C43: 26.186 | D43: 39.65 | E43: 31.165 | F43: 29.519 | G43: 29.084
A44: Procurement cost | B44: 35.639 | C44: 19.112 | D44: 20.578 | E44: 64.713 | F44: 77.336 | G44: 92.256
A45: Others | B45: 31.282 | C45: 56.256 | D45: 93.059 | E45: 58.268 | F45: 79.314 | G45: 66.06
B46: =同程艺龙!K126 -> 1314.48 | C46: =同程艺龙!M126 -> 1686.397 | D46: =同程艺龙!N126 -> 1572.398 | E46: =同程艺龙!P126 -> 1590.898 | F46: =同程艺龙!Q126 -> 2062.13 | G46: =同程艺龙!R126 -> 1956.493
B48: 2018Q2 | C48: 2018Q3 | D48: 2018Q4 | E48: 2019Q2 | F48: 2019Q3 | G48: 2019Q4
A49: Employee benefit expenses | B49: =B40/$B$46 -> 0.042518715 | C49: =C40/$C$46 -> 0.04324901 | D49: =D40/$D$46 -> 0.08721456 | E49: =E40/$E$46 -> 0.038749813 | F49: =F40/$F$46 -> 0.033141461 | G49: =G40/$G$46 -> 0.017333055
A50: Order processing cost | B50: =B41/$B$46 -> 0.14836818 | C50: =C41/$C$46 -> 0.14263901 | D50: =D41/$D$46 -> 0.1325167 | E50: =E41/$E$46 -> 0.1530997 | F50: =F41/$F$46 -> 0.13438774 | G50: =G41/$G$46 -> 0.11447319
A51: Cost of pre-purchased inventory risk taking products | B51: =B42/$B$46 -> 0.021927302 | C51: =C42/$C$46 -> 0.038251966 | D51: =D42/$D$46 -> 0.03660778 | E51: =E42/$E$46 -> 0.063989646 | F51: =F42/$F$46 -> 0.073525432 | G51: =G42/$G$46 -> 0.066329908
A52: Depreciations of PP&E | B52: =B43/$B$46 -> 0.018159272 | C52: =C43/$C$46 -> 0.015527779 | D52: =D43/$D$46 -> 0.025216262 | E52: =E43/$E$46 -> 0.019589565 | F52: =F43/$F$46 -> 0.01431481 | G52: =G43/$G$46 -> 0.014865374
A53: Procurement cost | B53: =B44/$B$46 -> 0.027112622 | C53: =C44/$C$46 -> 0.011333037 | D53: =D44/$D$46 -> 0.013087017 | E53: =E44/$E$46 -> 0.040677026 | F53: =F44/$F$46 -> 0.03750297 | G53: =G44/$G$46 -> 0.047153759
A54: Others | B54: =B45/$B$46 -> 0.023798004 | C54: =C45/$C$46 -> 0.033358693 | D54: =D45/$D$46 -> 0.059182853 | E54: =E45/$E$46 -> 0.036625855 | F54: =F45/$F$46 -> 0.038462173 | G54: =G45/$G$46 -> 0.033764496
B58: 2018Q2 | C58: 2018Q3 | D58: 2018Q4 | E58: 2019Q1 | F58: 2019Q2 | G58: 2019Q3 | H58: 2019Q4
A59: Gross Margin | B59: =同程艺龙!K152 -> 0.71811591 | C59: =同程艺龙!M152 -> 0.7156405 | D59: =同程艺龙!N152 -> 0.64617482 | E59: =同程艺龙!O152 -> 0.72060843 | F59: =同程艺龙!P152 -> 0.6472684 | G59: =同程艺龙!Q152 -> 0.66866541 | H59: =同程艺龙!R152 -> 0.70607562
A60: R&D Cost as % of Revenue | B60: =-同程艺龙!K155 -> 0.24154038 | C60: =-同程艺龙!M155 -> 0.23917618 | D60: =-同程艺龙!N155 -> 0.27973516 | E60: =-同程艺龙!O155 -> 0.24114015 | F60: =-同程艺龙!P155 -> 0.22135549 | G60: =-同程艺龙!Q155 -> 0.17437649 | H60: =-同程艺龙!R155 -> 0.19285323
A61: S&M Cost as % of Revenue | B61: =-同程艺龙!K157 -> 0.35306433 | C61: =-同程艺龙!M157 -> 0.34167933 | D61: =-同程艺龙!N157 -> 0.35552068 | E61: =-同程艺龙!O157 -> 0.2633846 | F61: =-同程艺龙!P157 -> 0.2559479 | G61: =-同程艺龙!Q157 -> 0.30432853 | H61: =-同程艺龙!R157 -> 0.37923724
A62: G&A Cost as % of Revenue | B62: =-同程艺龙!K159 -> 0.1017505 | C62: =-同程艺龙!M159 -> 0.096938028 | D62: =-同程艺龙!N159 -> 0.16253582 | E62: =-同程艺龙!O159 -> 0.12802545 | F62: =-同程艺龙!P159 -> 0.062735009 | G62: =-同程艺龙!Q159 -> 0.047288968 | H62: =-同程艺龙!R159 -> 0.10197328
A63: Operating Margin | B63: =同程艺龙!K164 -> 0.048397085 | C63: =同程艺龙!M164 -> 0.061975324 | D63: =同程艺龙!N164 -> -0.10639545 | E63: =同程艺龙!O164 -> 0.10510869 | F63: =同程艺龙!P164 -> 0.1371389 | G63: =同程艺龙!Q164 -> 0.16837881 | H63: =同程艺龙!R164 -> 0.054527156
B68: 2018Q1 | C68: 2018Q2 | D68: 2018Q3 | E68: 2018Q4 | F68: 2019Q1 | G68: 2019Q2 | H68: 2019Q3 | I68: 2019Q4
A69: Paying Ratio | B69: =同程艺龙!J100 -> 0.10342717 | C69: =同程艺龙!K100 -> 0.11435832 | D69: =同程艺龙!M100 -> 0.1095492 | E69: =同程艺龙!N100 -> 0.12838227 | F69: =同程艺龙!O100 -> 0.11590567 | G69: =同程艺龙!P100 -> 0.15253304 | H69: =同程艺龙!Q100 -> 0.12735043 | I69: =同程艺龙!R100 -> 0.13161729
B71: 2017 | C71: 2018 | D71: 2019Q1 | E71: 2019Q2 | F71: 2019Q3 | G71: 2019Q4
A72: MAU from Tencent | B72: =同程艺龙!F102 -> 79.6 | C72: =同程艺龙!G102 -> 140.5303 | D72: =同程艺龙!O102 -> 173.1 | E72: =同程艺龙!P102 -> 152.59027 | F72: =同程艺龙!Q102 -> 192.15 | G72: =同程艺龙!R102 -> 173.78835
A73: MAU from Own Channel | B73: =同程艺龙!F96-同程艺龙!F102 -> 41.6 | C73: =同程艺龙!G96-同程艺龙!G102 -> 34.669697 | D73: =同程艺龙!O96-同程艺龙!O102 -> 26.2 | E73: =同程艺龙!P96-同程艺龙!P102 -> 29.009733 | F73: =同程艺龙!Q96-同程艺龙!Q102 -> 41.85 | G73: =同程艺龙!R96-同程艺龙!R102 -> 32.111652
A74: % of Tencent Traffic | B74: =B72/SUM(B72:B73) -> 0.65676568 | C74: =C72/SUM(C72:C73) -> 0.8021136 | D74: =D72/SUM(D72:D73) -> 0.86853989 | E74: =E72/SUM(E72:E73) -> 0.84025477 | F74: =F72/SUM(F72:F73) -> 0.82115385 | G74: =G72/SUM(G72:G73) -> 0.84404249
B82: 2018 | C82: 2019Q1 | D82: 2019Q2 | E82: 2019Q3 | F82: 2019Q4
A83: Weixin Payment (Wallet) | B83: =同程艺龙!G107 -> 0.528 | C83: =同程艺龙!O107 -> 0.608 | D83: =同程艺龙!P107 -> 0.637 | E83: =同程艺龙!Q107 -> 0.65 | F83: =同程艺龙!R107 -> 0.657
A84: Interactive advertisements / Weixin based ad | B84: =同程艺龙!G108 -> 0.349 | C84: =同程艺龙!O108 -> 0.203 | D84: =同程艺龙!P108 -> 0.228 | E84: =同程艺龙!Q108 -> 0.252 | F84: =同程艺龙!R108 -> 0.219
A85: Sharing and search functions in Weixin | B85: =同程艺龙!G109 -> 0.123 | C85: =同程艺龙!O109 -> 0.189 | D85: =同程艺龙!P109 -> 0.135 | E85: =同程艺龙!Q109 -> 0.098 | F85: =同程艺龙!R109 -> 0.124
B94: 2018Q3 | C94: 2018Q4 | D94: 2019Q1 | E94: 2019Q2 | F94: 2019Q3 | G94: 2019Q4
A95: Cross-selling Rate | B95: =同程艺龙!M123 -> 0.16 | C95: =同程艺龙!N123 -> 0.2 | D95: =同程艺龙!O123 -> 0.21 | E95: =同程艺龙!P123 -> 0.23 | F95: =同程艺龙!Q123 -> 0.26 | G95: 0.28
B97: 2017 | C97: 2018 | D97: 2019Q3
A98: % of Distribution Channel Revenue as Total Accommodation Revenue | B98: 0.4 | C98: 0.2 | D98: 0.08

Sheet DESP Quarterly
A1: Year | B1: Q1-15 | C1: Q2-15 | D1: Q3-15 | E1: Q4-15 | F1: Q1-16 | G1: Q2-16 | H1: Q3-16 | I1: Q4-16 | J1: Q1-17 | K1: Q2-17 | L1: Q3-17 | M1: Q4-17 | N1: Q1-18 | O1: Q2-18 | P1: Q3-18 | Q1: Q4-18 | R1: Q1-19 | S1: Q2-19 | T1: Q3-19 | U1: Q4-19
A2: Company Data (in million of USD, unless specified)
A3: Gross booking value | B3: 810.961 | C3: 868.562 | D3: 941.076 | E3: 970.195 | F3: 661.409 | G3: 755.433 | H3: 844.866 | I3: 998.526 | J3: 1019.102 | K3: 1061.026 | L3: 1116.022 | M3: 1258.398 | N3: 1231.497 | O3: 1184.355 | P3: 1092.3 | Q3: 1207.2 | R3: 1157.5 | S3: 1118.1 | T3: 1177.7 | U3: 1280.9
A4: YoY change | F4: =(F3-B3)/B3 -> -0.18441331 | G4: =(G3-C3)/C3 -> -0.13024862 | H4: =(H3-D3)/D3 -> -0.10223404 | I4: =(I3-E3)/E3 -> 0.029201346 | J4: =(J3-F3)/F3 -> 0.54080456 | K4: =(K3-G3)/G3 -> 0.40452694 | L4: =(L3-H3)/H3 -> 0.32094557 | M4: =(M3-I3)/I3 -> 0.26025562 | ... U4: =(U3-Q3)/Q3 -> 0.061050364
A5: Revenue | B5: 96.777 | C5: 102.509 | D5: 108.367 | E5: 114.058 | F5: 95.115 | G5: 98.797 | H5: 106.088 | I5: 111.162 | J5: 124.999 | K5: 123.462 | L5: 131.468 | M5: 144.011 | N5: 148.593 | O5: 128.259 | P5: 121.2 | Q5: 132.515 | R5: 133.114 | S5: 114.087 | T5: 132.048 | U5: 145.627
A6: Revenue recognition adjustment | J6: -3.321 | K6: -0.059 | L6: 1.31 | M6: 7.578
A7: Revenue after Adjustment | J7: =J5+J6 -> 121.678 | K7: =K5+K6 -> 123.403 | L7: =L5+L6 -> 132.778 | M7: =M5+M6 -> 151.589 | N7: =N5+N6 -> 148.593 | O7: =O5+O6 -> 128.259 | P7: =P5+P6 -> 121.2 | Q7: =Q5+Q6 -> 132.515 | ... U7: =U5+U6 -> 145.627
A8: Air | J8: =J46*J49/1000 -> 56.8176 | K8: =K46*K49/1000 -> 59.89 | L8: =L46*L49/1000 -> 58.8304 | M8: =M46*M49/1000 -> 66.1122 | N8: =N46*N49/1000 -> 60.8814 | O8: =O46*O49/1000 -> 53.1063 | P8: =P46*P49/1000 -> 50.5008 | Q8: =Q46*Q49/1000 -> 50.2911 | ... U8: =U46*U49/1000 -> 53.3876
J9: =J8/J7 -> 0.46695048 | K9: =K8/K7 -> 0.48532045 | L9: =L8/L7 -> 0.4430734 | M9: =M8/M7 -> 0.43612795 | N9: =N8/N7 -> 0.40971917 | O9: =O8/O7 -> 0.41405515 | P9: =P8/P7 -> 0.41667327 | Q9: =Q8/Q7 -> 0.37951251 | ... U9: =U8/U7 -> 0.36660509
A10: Packages, Hotels & Other Travel Products | J10: =J47*J50/1000 -> 64.9005 | K10: =K47*K50/1000 -> 63.543 | L10: =L47*L50/1000 -> 73.914 | M10: =M47*M50/1000 -> 85.4291 | N10: =N47*N50/1000 -> 87.7824 | O10: =O47*O50/1000 -> 75.0484 | P10: =P47*P50/1000 -> 70.742 | Q10: =Q47*Q50/1000 -> 82.2465 | ... U10: =U47*U50/1000 -> 92.2887
J11: =J10/J7 -> 0.53337908 | K11: =K10/K7 -> 0.51492265 | L11: =L10/L7 -> 0.55667355 | M11: =M10/M7 -> 0.56355738 | N11: =N10/N7 -> 0.5907573 | O11: =O10/O7 -> 0.58513165 | P11: =P10/P7 -> 0.58367987 | Q11: =Q10/Q7 -> 0.62065804 | ... U11: =U10/U7 -> 0.63373344
A12: Take rate | B12: =B5/B3 -> 0.11933619 | C12: =C5/C3 -> 0.11802151 | D12: =D5/D3 -> 0.11515223 | E12: =E5/E3 -> 0.11756193 | F12: =F5/F3 -> 0.14380663 | G12: =G5/G3 -> 0.13078195 | H12: =H5/H3 -> 0.12556784 | I12: =I5/I3 -> 0.11132609 | ... U12: =U5/U3 -> 0.11369115
A13: Cost of revenue | B13: -29.248 | C13: -27.61 | D13: -34.681 | E13: -62.674 | F13: -33.494 | G13: -33.752 | H13: -26.15 | I13: -33.279 | J13: -31.14 | K13: -35.087 | L13: -37.869 | M13: -38.383 | N13: -43.646 | O13: -42.088 | P13: -36.7 | Q13: -49.703 | R13: -45.245 | S13: -40.342 | T13: -42.591 | U13: -51.387
A14: Gross profit | B14: =B5+B13 -> 67.529 | C14: =C5+C13 -> 74.899 | D14: =D5+D13 -> 73.686 | E14: =E5+E13 -> 51.384 | F14: =F5+F13 -> 61.621 | G14: =G5+G13 -> 65.045 | H14: =H5+H13 -> 79.938 | I14: =I5+I13 -> 77.883 | J14: 90.538 | K14: 88.316 | L14: 94.909 | M14: 113.206 | N14: 104.947 | O14: 86.171 | P14: =P5+P13 -> 84.5 | Q14: =Q5+Q13 -> 82.812 | R14: =R5+R13 -> 87.869 | S14: =S5+S13 -> 73.745 | T14: =T5+T13 -> 89.457 | U14: =U5+U13 -> 94.24
A15: Gross margin | B15: =B14/B5 -> 0.69777943 | C15: =C14/C5 -> 0.7306578 | D15: =D14/D5 -> 0.67996715 | E15: =E14/E5 -> 0.45050764 | F15: =F14/F5 -> 0.64785786 | G15: =G14/G5 -> 0.65837019 | H15: =H14/H5 -> 0.75350652 | I15: =I14/I5 -> 0.70062611 | ... U15: =U14/U5 -> 0.64713274
A17: Operating expenses (GAAP)
A18: General and administrative | B18: -19.606 | C18: -16.991 | D18: -13.36 | E18: -28.224 | F18: -15.186 | G18: -13.96 | H18: -13.576 | I18: -21.961 | J18: -18.869 | K18: -18.618 | L18: -15.318 | M18: -19.821 | N18: -15.888 | O18: -16.986 | P18: -17.1 | Q18: -17.599 | R18: -20.638 | S18: -21.254 | T18: -25.09 | U18: -25.98
A19: as % of Revenue | J19: =J18/J7 -> -0.15507323 | K19: =K18/K7 -> -0.15087153 | L19: =L18/L7 -> -0.1153655 | M19: =M18/M7 -> -0.13075487 | N19: =N18/N7 -> -0.10692294 | O19: =O18/O7 -> -0.13243515 | P19: =P18/P7 -> -0.14108911 | Q19: =Q18/Q7 -> -0.13280761 | ... U19: =U18/U7 -> -0.17840098
A20: Technology and content | B20: -19.07 | C20: -20.055 | D20: -15.262 | E20: -19.148 | F20: -15.561 | G20: -15.943 | H20: -15.718 | I20: -16.03 | J20: -15.408 | K20: -17.644 | L20: -18.907 | M20: -19.349 | N20: -19.225 | O20: -18.732 | P20: -16.8 | Q20: -16.376 | R20: -18.713 | S20: -18.077 | T20: -17.922 | U20: -18.663
A21: as % of Revenue | J21: =J20/J7 -> -0.1266293 | K21: =K20/K7 -> -0.1429787 | L21: =L20/L7 -> -0.14239558 | M21: =M20/M7 -> -0.12764119 | N21: =N20/N7 -> -0.12938025 | O21: =O20/O7 -> -0.14604823 | P21: =P20/P7 -> -0.13861386 | Q21: =Q20/Q7 -> -0.12357846 | ... U21: =U20/U7 -> -0.12815618
A22: Selling and marketing expenses | B22: -45.178 | C22: -52.893 | D22: -36.185 | E22: -35.893 | F22: -28.577 | G22: -29.133 | H22: -31.374 | I22: -32.382 | J22: -35.546 | K22: -43.289 | L22: -41.097 | M22: -46.356 | N22: -46.41 | O22: -43.45 | P22: -41.6 | Q22: -42.925 | R22: -40.933 | S22: -50.701 | T22: -46.656 | U22: -49.604
A23: as % of Revenue | J23: =J22/J7 -> -0.29213169 | K23: =K22/K7 -> -0.35079374 | L23: =L22/L7 -> -0.30951664 | M23: =M22/M7 -> -0.30580055 | N23: =N22/N7 -> -0.31232965 | O23: =O22/O7 -> -0.33876765 | P23: =P22/P7 -> -0.34323432 | Q23: =Q22/Q7 -> -0.32392559 | ... U23: =U22/U7 -> -0.34062365
A24: Marketing and sales promotion expenses as % of GMV | B24: =-B22/B3 -> 0.055709214 | C24: =-C22/C3 -> 0.060897207 | D24: =-D22/D3 -> 0.038450667 | E24: =-E22/E3 -> 0.036995656 | F24: =-F22/F3 -> 0.043206246 | G24: =-G22/G3 -> 0.038564638 | H24: =-H22/H3 -> 0.037134883 | I24: =-I22/I3 -> 0.032429802 | ... U24: =-U22/U3 -> 0.038725896
A26: Total operating expenses | B26: =B18+B20+B22 -> -83.854 | C26: =C18+C20+C22 -> -89.939 | D26: =D18+D20+D22 -> -64.807 | E26: =E18+E20+E22 -> -83.265 | F26: =F18+F20+F22 -> -59.324 | G26: =G18+G20+G22 -> -59.036 | H26: =H18+H20+H22 -> -60.668 | I26: =I18+I20+I22 -> -70.373 | ... U26: =U18+U20+U22 -> -94.247
A27: Operating income/loss | B27: =B14+B26 -> -16.325 | C27: =C14+C26 -> -15.04 | D27: =D14+D26 -> 8.879 | E27: =E14+E26 -> -31.881 | F27: =F14+F26 -> 2.297 | G27: =G14+G26 -> 6.009 | H27: =H14+H26 -> 19.27 | I27: =I14+I26 -> 7.51 | ... U27: =U14+U26 -> -0.007
A29: Depreciation, amortization and impairment | B29: =-1.267-2.367 -> -3.634 | C29: =-1.371-2.371 -> -3.742 | D29: =-1.253-2.389 -> -3.642 | E29: =-1.261-2.16 -> -3.421 | F29: =-1.265-1.728 -> -2.993 | G29: =-1.255-1.918 -> -3.173 | H29: =-1.45-2.06 -> -3.51 | I29: =-1.111-2.129 -> -3.24 | J29: =-1.343-1.517 -> -2.86 | K29: =-1.362-2.039 -> -3.401 | L29: =-1.337-2.454 -> -3.791 | M29: =-1.033-2.741 -> -3.774 | N29: =-0.859-2.018 -> -2.877 | O29: =-1.475-2.228 -> -3.703 | P29: =-1.3-2.7 -> -4 | Q29: =-1.7-3.2 -> -4.9 | R29: =-0.8-3.8 -> -4.6 | S29: =-2.7-3.1 -> -5.8 | T29: =-2-4.2 -> -6.2 | U29: =-1.094-5.1 -> -6.194
A30: Share-based compensation | B30: -0.321 | C30: -0.374 | D30: -0.374 | E30: 0.208 | F30: -0.05 | G30: -0.05 | H30: -0.05 | I30: -0.424 | J30: -1.176 | K30: -0.93 | L30: -0.959 | M30: -1.224 | N30: -0.983 | O30: -1.266 | P30: -1.4 | Q30: -3.1 | R30: -3 | S30: =-3.2 -> -3.2 | T30: -3.4 | U30: =-2.105 -> -2.105
A31: Total operating expenses (GAAP) | B31: =B18+B20+B22+B29 -> -87.488 | C31: =C18+C20+C22+C29 -> -93.681 | D31: =D18+D20+D22+D29 -> -68.449 | E31: =E18+E20+E22+E29 -> -86.686 | F31: =F18+F20+F22+F29 -> -62.317 | G31: =G18+G20+G22+G29 -> -62.209 | H31: =H18+H20+H22+H29 -> -64.178 | I31: =I18+I20+I22+I29 -> -73.613 | ... U31: =U18+U20+U22+U29 -> -100.441
A32: Total operating expenses (non-GAAP) | B32: =B31-B30 -> -87.167 | C32: =C31-C30 -> -93.307 | D32: =D31-D30 -> -68.075 | E32: =E31-E30 -> -86.894 | F32: =F31-F30 -> -62.267 | G32: =G31-G30 -> -62.159 | H32: =H31-H30 -> -64.128 | I32: =I31-I30 -> -73.189 | ... U32: =U31-U30 -> -98.336
A34: Income (loss) from Operations (GAAP) | B34: -16.325 | C34: -15.04 | D34: 8.879 | E34: -31.881 | F34: 2.297 | G34: 6.009 | H34: 19.27 | I34: 7.51 | J34: 20.715 | K34: 8.765 | L34: 19.587 | M34: 27.68 | N34: 23.424 | O34: 7.003 | P34: 9.051 | Q34: 5.912 | R34: 7.585 | S34: -16.287 | T34: -0.211 | U34: -0.007
A35: OP Margin GAAP (OP/Revenue) | B35: =B34/B5 -> -0.16868677 | C35: =C34/C5 -> -0.14671882 | D35: =D34/D5 -> 0.081934537 | E35: =E34/E5 -> -0.27951569 | F35: =F34/F5 -> 0.024149714 | G35: =G34/G5 -> 0.060821685 | H35: =H34/H5 -> 0.18164166 | I35: =I34/I5 -> 0.067559058 | ... U35: =U34/U5 -> -4.8068009e-05
A37: Net income (GAAP) | B37: -26.221 | C37: -15.954 | D37: -1.652 | E37: -41.449 | F37: -0.735 | G37: 0.179 | H37: 14.353 | I37: 4 | J37: 12.141 | K37: 2.9 | L37: 12.334 | M37: 18.831 | N37: 16.358 | O37: 1.24 | P37: -1.474 | Q37: 3.03 | R37: 1.886 | S37: -16.467 | T37: -3.684 | U37: -2.645
A38: Net profit margin GAAP (/ Revenue) | B38: =B37/B5 -> -0.27094248 | C38: =C37/C5 -> -0.15563511 | D38: =D37/D5 -> -0.015244493 | E38: =E37/E5 -> -0.36340283 | F38: =F37/F5 -> -0.0077274878 | G38: =G37/G5 -> 0.0018117959 | H38: =H37/H5 -> 0.13529334 | I38: =I37/I5 -> 0.03598352 | ... U38: =U37/U5 -> -0.018162841
A40: Adjusted EBITDA | B40: -12.265 | C40: -10.999 | D40: 12.637 | E40: 28.44 | F40: 5.34 | G40: 9.232 | H40: 22.831 | I40: 11.173 | J40: 24.751 | K40: 13.097 | L40: 24.337 | M40: 32.678 | N40: 27.284 | O40: 11.972 | P40: 14.5 | Q40: 13.9 | R40: 15.2 | S40: -7.3 | T40: 9.4 | U40: 8.292
A41: Adjusted EBITDA margin | J41: =J40/J5 -> 0.19800958 | K41: =K40/K5 -> 0.10608122 | L41: =L40/L5 -> 0.18511729 | M41: =M40/M5 -> 0.22691322 | N41: =N40/N5 -> 0.18361565 | O41: =O40/O5 -> 0.093342378 | P41: =P40/P5 -> 0.11963696 | Q41: =Q40/Q5 -> 0.10489379 | ... U41: =U40/U5 -> 0.056939991
A43: Operating Metrics | P43: =P45/1000 -> 2.596 | Q43: =Q45/1000 -> 2.676 | R43: =R45/1000 -> 2.652 | S43: =S45/1000 -> 2.448 | T43: =T45/1000 -> 2.723 | U43: =U45/1000 -> 2.855
A44: ASPs | F44: =F3*1000/F45 -> 405.27512 | G44: =G3*1000/G45 -> 442.8095 | H44: =H3*1000/H45 -> 459.41599 | I44: =I3*1000/I45 -> 490.67617 | J44: =J3*1000/J45 -> 478.67637 | K44: =K3*1000/K45 -> 480.10226 | L44: =L3*1000/L45 -> 485.64926 | M44: =M3*1000/M45 -> 520.21414 | ... U44: =U3*1000/U45 -> 448.65149
A45: Number of transactions ('000) | F45: 1632 | G45: 1706 | H45: 1839 | I45: 2035 | J45: 2129 | K45: 2210 | L45: 2298 | M45: 2419 | N45: 2514 | O45: 2607 | P45: 2596 | Q45: 2676 | R45: 2652 | S45: 2448 | T45: 2723 | U45: 2855
A46: Air | J46: 1246 | K46: 1325 | L46: 1328 | M46: 1386 | N46: 1362 | O46: 1513 | P46: 1512 | Q46: 1557 | R46: 1517 | S46: 1459 | T46: 1586 | U46: 1658
A47: Package, Hotels & Other | J47: 883 | K47: 885 | L47: 970 | M47: 1033 | N47: 1152 | O47: 1094 | P47: 1085 | Q47: 1119 | R47: 1135 | S47: 989 | T47: 1137 | U47: 1197
A48: Revenue per Transaction | J48: 57.2 | K48: 55.8 | L48: 57.8 | M48: 62.7 | N48: 59.1 | O48: 49.2 | P48: 46.7 | Q48: 49.5 | R48: 50.2 | S48: 46.6 | T48: 48.5 | U48: 51
A49: Air | J49: 45.6 | K49: 45.2 | L49: 44.3 | M49: 47.7 | N49: 44.7 | O49: 35.1 | P49: 33.4 | Q49: 32.3 | R49: 32.8 | S49: 32.5 | T49: 32.3 | U49: 32.2
A50: Package, Hotels & Other | J50: 73.5 | K50: 71.8 | L50: 76.2 | M50: 82.7 | N50: 76.2 | O50: 68.6 | P50: 65.2 | Q50: 73.5 | R50: 73.5 | S50: 67.5 | T50: 71.1 | U50: 77.1
A52: Geographical Breakdown (as reported) | J52: Q1-17 | K52: Q2-17 | L52: Q3-17 | M52: Q4-17 | N52: Q1-18 | O52: Q2-18 | P52: Q3-18 | Q52: Q4-18 | R52: Q1-19 | S52: Q2-19 | T52: Q3-19 | U52: Q4-19
A53: Transactions ('000) | J53: 2129 | K53: 2210 | L53: 2298 | M53: =M55+M58+M61 -> 2400 | N53: =N55+N58+N61 -> 2514 | O53: =O55+O58+O61 -> 2607 | P53: =P55+P58+P61 -> 2597 | Q53: =Q55+Q58+Q61 -> 2675 | R53: =R55+R58+R61 -> 2652 | S53: =S55+S58+S61 -> 2448 | T53: =T55+T58+T61 -> 2723 | U53: =U55+U58+U61 -> 2854
A54: YoY % Change | N54: =N53/J53-1 -> 0.18083607 | O54: =O53/K53-1 -> 0.17963801 | P54: =P53/L53-1 -> 0.13011314 | Q54: =Q53/M53-1 -> 0.11458333 | R54: =R53/N53-1 -> 0.054892601 | S54: =S53/O53-1 -> -0.060989643 | T54: =T53/P53-1 -> 0.04851752 | U54: =U53/Q53-1 -> 0.066915888
A55: Argentina | J55: =N55/(1+N56) -> 557.85124 | K55: =O55/(1+O56) -> 519.81982 | L55: =P55/(1+P56) -> 550 | M55: 632 | N55: 675 | O55: 577 | P55: 572 | Q55: 558 | R55: 618 | S55: 496 | T55: 551 | U55: 629
A56: YoY % Change | L56: 0.24 | M56: 0.22 | N56: 0.21 | O56: 0.11 | P56: 0.04 | Q56: =Q55/M55-1 -> -0.11708861 | R56: =R55/N55-1 -> -0.084444444 | S56: =S55/O55-1 -> -0.14038128 | T56: =T55/P55-1 -> -0.036713287 | U56: =U55/Q55-1 -> 0.12724014
A57: as % of total | M57: =M55/M53 -> 0.26333333 | N57: =N55/N53 -> 0.26849642 | O57: =O55/O53 -> 0.2213272 | P57: =P55/P53 -> 0.22025414 | Q57: =Q55/Q53 -> 0.20859813 | R57: =R55/R53 -> 0.23303167 | S57: =S55/S53 -> 0.20261438 | T57: =T55/T53 -> 0.20235035 | U57: =U55/U53 -> 0.22039243
A58: Brazil | J58: =N58/(1+N59) -> 888.59649 | K58: =O58/(1+O59) -> 907.43802 | L58: =P58/(1+P59) -> 937.83784 | M58: 966 | N58: 1013 | O58: 1098 | P58: 1041 | Q58: 1085 | R58: 1045 | S58: 948 | T58: 1070 | U58: 1105
A59: YoY % Change | L59: 0.29 | M59: 0.18 | N59: 0.14 | O59: 0.21 | P59: 0.11 | Q59: =Q58/M58-1 -> 0.12318841 | R59: =R58/N58-1 -> 0.031589339 | S59: =S58/O58-1 -> -0.13661202 | T59: =T58/P58-1 -> 0.027857829 | U59: =U58/Q58-1 -> 0.01843318
A60: as % of total | M60: =M58/M53 -> 0.4025 | N60: =N58/N53 -> 0.40294352 | O60: =O58/O53 -> 0.42117376 | P60: =P58/P53 -> 0.40084713 | Q60: =Q58/Q53 -> 0.40560748 | R60: =R58/R53 -> 0.39404223 | S60: =S58/S53 -> 0.3872549 | T60: =T58/T53 -> 0.39294895 | U60: =U58/U53 -> 0.38717589
A61: Rest of LATAM | J61: =J53-J55-J58 -> 682.55227 | K61: =K53-K55-K58 -> 782.74216 | L61: =L53-L55-L58 -> 810.16216 | M61: 802 | N61: 826 | O61: 932 | P61: 984 | Q61: 1032 | R61: 989 | S61: 1004 | T61: 1102 | U61: 1120
A62: YoY % Change | N62: =N61/J61-1 -> 0.21016373 | O62: =O61/K61-1 -> 0.19068583 | P62: =P61/L61-1 -> 0.21457166 | Q62: =Q61/M61-1 -> 0.28678304 | R62: =R61/N61-1 -> 0.19733656 | S62: =S61/O61-1 -> 0.077253219 | T62: =T61/P61-1 -> 0.1199187 | U62: =U61/Q61-1 -> 0.085271318
A63: as % of total | M63: =M61/M53 -> 0.33416667 | N63: =N61/N53 -> 0.32856006 | O63: =O61/O53 -> 0.35749904 | P63: =P61/P53 -> 0.37889873 | Q63: =Q61/Q53 -> 0.38579439 | R63: =R61/R53 -> 0.37292609 | S63: =S61/S53 -> 0.41013072 | T63: =T61/T53 -> 0.4047007 | U63: =U61/U53 -> 0.39243167
A64: Gross Booking | M64: =M66+M69+M72 -> 1259 | N64: =N66+N69+N72 -> 1232 | O64: =O66+O69+O72 -> 1184 | P64: =P66+P69+P72 -> 1092.7 | Q64: =Q66+Q69+Q72 -> 1208 | R64: =R66+R69+R72 -> 1157 | S64: =S66+S69+S72 -> 1118 | T64: =T66+T69+T72 -> 1178 | U64: =U66+U69+U72 -> 1280.5
A65: YoY % Change | Q65: =Q64/M64-1 -> -0.04050834 | R65: =R64/N64-1 -> -0.060876623 | S65: =S64/O64-1 -> -0.055743243 | T65: =T64/P64-1 -> 0.078063512 | U65: =U64/Q64-1 -> 0.060016556
A66: Argentina | M66: 451 | N66: 407 | O66: 312 | P66: 262 | Q66: 269 | R66: 275 | S66: 216 | T66: 232 | U66: 304.6
A67: YoY % Change | Q67: =Q66/M66-1 -> -0.40354767 | R67: =R66/N66-1 -> -0.32432432 | S67: =S66/O66-1 -> -0.30769231 | T67: =T66/P66-1 -> -0.11450382 | U67: =U66/Q66-1 -> 0.13234201
A68: as % of total | M68: =M66/M64 -> 0.35822081 | N68: =N66/N64 -> 0.33035714 | O68: =O66/O64 -> 0.26351351 | P68: =P66/P64 -> 0.23977304 | Q68: =Q66/Q64 -> 0.22268212 | R68: =R66/R64 -> 0.23768366 | S68: =S66/S64 -> 0.19320215 | T68: =T66/T64 -> 0.19694397 | U68: =U66/U64 -> 0.23787583
A69: Brazil | M69: 441 | N69: 452 | O69: 435 | P69: 407.9 | Q69: 496 | R69: 466 | S69: 452 | T69: 468 | U69: 492.5
A70: YoY % Change | O70: 0.13 | P70: 0 | Q70: =Q69/M69-1 -> 0.12471655 | R70: =R69/N69-1 -> 0.030973451 | S70: =S69/O69-1 -> 0.03908046 | T70: =T69/P69-1 -> 0.14734003 | U70: =U69/Q69-1 -> -0.0070564516
A71: as % of total | M71: =M69/M64 -> 0.350278 | N71: =N69/N64 -> 0.36688312 | O71: =O69/O64 -> 0.36739865 | P71: =P69/P64 -> 0.37329551 | Q71: =Q69/Q64 -> 0.41059603 | R71: =R69/R64 -> 0.40276577 | S71: =S69/S64 -> 0.40429338 | T71: =T69/T64 -> 0.39728353 | U71: =U69/U64 -> 0.38461538
A72: Rest of LATAM | M72: 367 | N72: 373 | O72: 437 | P72: 422.8 | Q72: 443 | R72: 416 | S72: 450 | T72: 478 | U72: 483.4
A73: YoY % Change | Q73: =Q72/M72-1 -> 0.20708447 | R73: =R72/N72-1 -> 0.1152815 | S73: =S72/O72-1 -> 0.029748284 | T73: =T72/P72-1 -> 0.13055818 | U73: =U72/Q72-1 -> 0.091196388
A74: as % of total | M74: =M72/M64 -> 0.29150119 | N74: =N72/N64 -> 0.30275974 | O74: =O72/O64 -> 0.36908784 | P74: =P72/P64 -> 0.38693145 | Q74: =Q72/Q64 -> 0.36672185 | R74: =R72/R64 -> 0.35955056 | S74: =S72/S64 -> 0.40250447 | T74: =T72/T64 -> 0.4057725 | U74: =U72/U64 -> 0.37750879
M75: =M69+M72 -> 808 | N75: =N69+N72 -> 825 | O75: =O69+O72 -> 872 | P75: =P69+P72 -> 830.7 | Q75: =Q69+Q72 -> 939 | R75: =R69+R72 -> 882 | S75: =S69+S72 -> 902 | T75: =T69+T72 -> 946 | U75: =U69+U72 -> 975.9
A76: YoY % Change | Q76: =Q75/M75-1 -> 0.16212871 | R76: =R75/N75-1 -> 0.069090909 | S76: =S75/O75-1 -> 0.03440367 | T76: =T75/P75-1 -> 0.1387986 | U76: =U75/Q75-1 -> 0.039297125
A79: ASP ($)
A80: Argentina | M80: =M66*1000000/M55/1000 -> 713.60759 | N80: =N66*1000000/N55/1000 -> 602.96296 | O80: =O66*1000000/O55/1000 -> 540.7279 | P80: =P66*1000000/P55/1000 -> 458.04196 | Q80: =Q66*1000000/Q55/1000 -> 482.07885 | R80: =R66*1000000/R55/1000 -> 444.98382 | S80: =S66*1000000/S55/1000 -> 435.48387 | T80: =T66*1000000/T55/1000 -> 421.05263 | U80: =U66*1000000/U55/1000 -> 484.26073
A81: Brazil | M81: =M69*1000000/M58/1000 -> 456.52174 | N81: =N69*1000000/N58/1000 -> 446.19941 | O81: =O69*1000000/O58/1000 -> 396.17486 | P81: =P69*1000000/P58/1000 -> 391.83477 | Q81: =Q69*1000000/Q58/1000 -> 457.14286 | R81: =R69*1000000/R58/1000 -> 445.93301 | S81: =S69*1000000/S58/1000 -> 476.79325 | T81: =T69*1000000/T58/1000 -> 437.38318 | U81: =U69*1000000/U58/1000 -> 445.70136
A82: Rest of LATAM | M82: =M72*1000000/M61/1000 -> 457.60599 | N82: =N72*1000000/N61/1000 -> 451.57385 | O82: =O72*1000000/O61/1000 -> 468.88412 | P82: =P72*1000000/P61/1000 -> 429.6748 | Q82: =Q72*1000000/Q61/1000 -> 429.26357 | R82: =R72*1000000/R61/1000 -> 420.6269 | S82: =S72*1000000/S61/1000 -> 448.20717 | T82: =T72*1000000/T61/1000 -> 433.75681 | U82: =U72*1000000/U61/1000 -> 431.60714
A84: Geographical Breakdown (FX neutral basis) | M84: Q4-17 | N84: Q1-18 | O84: Q2-18 | P84: Q3-18 | Q84: Q4-18 | R84: Q1-19 | S84: Q2-19 | T84: Q3-19 | U84: Q4-19
A85: Transactions ('000) | M85: =M86+M88+M90 -> 2400 | N85: =N86+N88+N90 -> 2514 | O85: =O86+O88+O90 -> 2607 | P85: =P86+P88+P90 -> 2597 | Q85: =Q86+Q88+Q90 -> 2675 | R85: =R86+R88+R90 -> 2652 | S85: =S86+S88+S90 -> 2448 | T85: =T86+T88+T90 -> 2723 | U85: =U86+U88+U90 -> 2854
A86: Argentina | M86: 632 | N86: 675 | O86: 577 | P86: 572 | Q86: 558 | R86: 618 | S86: 496 | T86: 551 | U86: 629
A87: as % of total | M87: =M86/M85 -> 0.26333333 | N87: =N86/N85 -> 0.26849642 | O87: =O86/O85 -> 0.2213272 | P87: =P86/P85 -> 0.22025414 | Q87: =Q86/Q85 -> 0.20859813 | R87: =R86/R85 -> 0.23303167 | S87: =S86/S85 -> 0.20261438 | T87: =T86/T85 -> 0.20235035 | U87: =U86/U85 -> 0.22039243
A88: Brazil | M88: 966 | N88: 1013 | O88: 1098 | P88: 1041 | Q88: 1085 | R88: 1045 | S88: 948 | T88: 1070 | U88: 1105
A89: as % of total | M89: =M88/M85 -> 0.4025 | N89: =N88/N85 -> 0.40294352 | O89: =O88/O85 -> 0.42117376 | P89: =P88/P85 -> 0.40084713 | Q89: =Q88/Q85 -> 0.40560748 | R89: =R88/R85 -> 0.39404223 | S89: =S88/S85 -> 0.3872549 | T89: =T88/T85 -> 0.39294895 | U89: =U88/U85 -> 0.38717589
A90: Rest of LATAM | M90: 802 | N90: 826 | O90: 932 | P90: 984 | Q90: 1032 | R90: 989 | S90: 1004 | T90: 1102 | U90: 1120
A91: as % of total | M91: =M90/M85 -> 0.33416667 | N91: =N90/N85 -> 0.32856006 | O91: =O90/O85 -> 0.35749904 | P91: =P90/P85 -> 0.37889873 | Q91: =Q90/Q85 -> 0.38579439 | R91: =R90/R85 -> 0.37292609 | S91: =S90/S85 -> 0.41013072 | T91: =T90/T85 -> 0.4047007 | U91: =U90/U85 -> 0.39243167
A92: Gross Booking | M92: =M93+M95+M97 -> 1259 | N92: =N93+N95+N97 -> 1232 | O92: =O93+O95+O97 -> 1184 | P92: =P93+P95+P97 -> 1062 | Q92: =Q93+Q95+Q97 -> 1208 | R92: =R93+R95+R97 -> 1526 | S92: =S93+S95+S97 -> 1366 | T92: =T93+T95+T97 -> 1326 | U92: =U93+U95+U97 -> 1517
A93: Argentina | M93: 451 | N93: 407 | O93: 312 | P93: 262 | Q93: 269 | R93: 545 | S93: 405 | T93: 384 | U93: 487
A94: as % of total | M94: =M93/M92 -> 0.35822081 | N94: =N93/N92 -> 0.33035714 | O94: =O93/O92 -> 0.26351351 | P94: =P93/P92 -> 0.24670433 | Q94: =Q93/Q92 -> 0.22268212 | R94: =R93/R92 -> 0.35714286 | S94: =S93/S92 -> 0.29648609 | T94: =T93/T92 -> 0.28959276 | U94: =U93/U92 -> 0.32102835
A95: Brazil | M95: 441 | N95: 452 | O95: 435 | P95: 408 | Q95: 496 | R95: 541 | S95: 490 | T95: 487 | U95: 532
A96: as % of total | M96: =M95/M92 -> 0.350278 | N96: =N95/N92 -> 0.36688312 | O96: =O95/O92 -> 0.36739865 | P96: =P95/P92 -> 0.38418079 | Q96: =Q95/Q92 -> 0.41059603 | R96: =R95/R92 -> 0.35452163 | S96: =S95/S92 -> 0.35871157 | T96: =T95/T92 -> 0.36726998 | U96: =U95/U92 -> 0.35069216
A97: Rest of LATAM | M97: 367 | N97: 373 | O97: 437 | P97: 392 | Q97: 443 | R97: 440 | S97: 471 | T97: 455 | U97: 498
A98: as % of total | M98: =M97/M92 -> 0.29150119 | N98: =N97/N92 -> 0.30275974 | O98: =O97/O92 -> 0.36908784 | P98: =P97/P92 -> 0.36911488 | Q98: =Q97/Q92 -> 0.36672185 | R98: =R97/R92 -> 0.28833552 | S98: =S97/S92 -> 0.34480234 | T98: =T97/T92 -> 0.34313725 | U98: =U97/U92 -> 0.3282795
A99: ASP ($)
A100: Argentina | M100: =M93*1000000/M86/1000 -> 713.60759 | N100: =N93*1000000/N86/1000 -> 602.96296 | O100: =O93*1000000/O86/1000 -> 540.7279 | P100: =P93*1000000/P86/1000 -> 458.04196 | Q100: =Q93*1000000/Q86/1000 -> 482.07885 | R100: =R93*1000000/R86/1000 -> 881.87702 | S100: =S93*1000000/S86/1000 -> 816.53226 | T100: =T93*1000000/T86/1000 -> 696.9147 | U100: =U93*1000000/U86/1000 -> 774.24483 | AA100: -0.223 | AB100: =Z101-AA100 -> -0.18054767
A101: Brazil | M101: =M95*1000000/M88/1000 -> 456.52174 | N101: =N95*1000000/N88/1000 -> 446.19941 | O101: =O95*1000000/O88/1000 -> 396.17486 | P101: =P95*1000000/P88/1000 -> 391.93084 | Q101: =Q95*1000000/Q88/1000 -> 457.14286 | R101: =R95*1000000/R88/1000 -> 517.70335 | S101: =S95*1000000/S88/1000 -> 516.87764 | T101: =T95*1000000/T88/1000 -> 455.14019 | U101: =U95*1000000/U88/1000 -> 481.44796 | Y101: 2018 | Z101: =Q67 -> -0.40354767 | AA101: -0.037 | AB101: =Z102-AA101 -> 0.16171655
A102: Rest of LATAM | M102: =M97*1000000/M90/1000 -> 457.60599 | N102: =N97*1000000/N90/1000 -> 451.57385 | O102: =O97*1000000/O90/1000 -> 468.88412 | P102: =P97*1000000/P90/1000 -> 398.37398 | Q102: =Q97*1000000/Q90/1000 -> 429.26357 | R102: =R97*1000000/R90/1000 -> 444.89383 | S102: =S97*1000000/S90/1000 -> 469.12351 | T102: =T97*1000000/T90/1000 -> 412.88566 | U102: =U97*1000000/U90/1000 -> 444.64286 | Y102: Argentina | Z102: =Q70 -> 0.12471655
Y103: Brazil
A104: Depreciation, amortization and impairment | B104: - | C104: - | D104: - | E104: - | F104: =(F29-B29)/B29 -> -0.17638965 | G104: =(G29-C29)/C29 -> -0.15205772 | H104: =(H29-D29)/D29 -> -0.036243822 | I104: =(I29-E29)/E29 -> -0.052908506 | J104: =(J29-F29)/F29 -> -0.04443702 | K104: =(K29-G29)/G29 -> 0.071856287 | L104: =(L29-H29)/H29 -> 0.08005698 | M104: =(M29-I29)/I29 -> 0.16481481 | ... U104: =(U29-Q29)/Q29 -> 0.26408163 | Y104: 2019 | Z104: =SUM(R66:U66)/SUM(N66:Q66)-1 -> -0.17792
A105: Share-based compensation | B105: - | C105: - | D105: - | E105: - | F105: =(F30-B30)/B30 -> -0.84423676 | G105: =(G30-C30)/C30 -> -0.86631016 | H105: =(H30-D30)/D30 -> -0.86631016 | I105: =(I30-E30)/E30 -> -3.0384615 | J105: =(J30-F30)/F30 -> 22.52 | K105: =(K30-G30)/G30 -> 17.6 | L105: =(L30-H30)/H30 -> 18.18 | M105: =(M30-I30)/I30 -> 1.8867925 | ... U105: =(U30-Q30)/Q30 -> -0.32096774 | Z105: =SUM(R69:U69)/SUM(N69:Q69)-1 -> 0.048913954
A106: Income (loss) from Operations (GAAP) | B106: - | C106: - | D106: - | E106: - | F106: =(F34-B34)/B34 -> -1.1407044 | G106: =(G34-C34)/C34 -> -1.3995346 | H106: =(H34-D34)/D34 -> 1.1702894 | I106: =(I34-E34)/E34 -> -1.2355635 | J106: =(J34-F34)/F34 -> 8.0182847 | K106: =(K34-G34)/G34 -> 0.45864537 | L106: =(L34-H34)/H34 -> 0.016450441 | M106: =(M34-I34)/I34 -> 2.6857523 | ... U106: =(U34-Q34)/Q34 -> -1.001184
A107: Net income (GAAP) | B107: - | C107: - | D107: - | E107: - | F107: =(F37-B37)/B37 -> -0.97196903 | G107: =(G37-C37)/C37 -> -1.0112198 | H107: =(H37-D37)/D37 -> -9.6882567 | I107: =(I37-E37)/E37 -> -1.0965041 | J107: =(J37-F37)/F37 -> -17.518367 | K107: =(K37-G37)/G37 -> 15.201117 | L107: =(L37-H37)/H37 -> -0.14066746 | M107: =(M37-I37)/I37 -> 3.70775 | ... U107: =(U37-Q37)/Q37 -> -1.8729373
A108: Number of transactions | J108: =J45/F45-1 -> 0.30453431 | K108: =K45/G45-1 -> 0.2954279 | L108: =L45/H45-1 -> 0.24959217 | M108: =M45/I45-1 -> 0.18869779 | N108: =N45/J45-1 -> 0.18083607 | O108: =O45/K45-1 -> 0.17963801 | P108: =P45/L45-1 -> 0.12967798 | Q108: =Q45/M45-1 -> 0.10624225 | ... U108: =U45/Q45-1 -> 0.066890882
A109: ASPs | J109: =J44/F44-1 -> 0.18111462 | K109: =K44/G44-1 -> 0.084218534 | L109: =L44/H44-1 -> 0.05710135 | M109: =M44/I44-1 -> 0.060198504 | N109: =N44/J44-1 -> 0.023354474 | O109: =O44/K44-1 -> -0.053747338 | P109: =P44/L44-1 -> -0.13360784 | Q109: =Q44/M44-1 -> -0.13281658 | ... U109: =U44/Q44-1 -> -0.0054743344
A111: Mix of Mobile Share of Transaction | M111: 0.3 | N111: 0.31 | O111: 0.33 | P111: 0.35 | Q111: 0.36 | R111: 0.38 | S111: 0.38 | T111: 0.39 | U111: 0.41
A113: Room Night Growth | P113: 0.12 | Q113: 0.08 | R113: 0.04 | S113: -0.08 | T113: 0.05 | U113: 0.03

Sheet DESP Annual
B1: Full year
A2: Year | B2: 2015 | C2: 2016 | D2: 2017 | E2: 2018 | F2: 2019
A3: Company Data
A4: Gross booking value | B4: 3596.26 | C4: 3260.234 | D4: 4454.548 | E4: 4715.235 | F4: =SUM('DESP Quarterly'!R3:U3) -> 4734.2
A5: YoY change | C5: =(C4-B4)/B4 -> -0.093437627 | D5: =(D4-C4)/C4 -> 0.36632769 | E5: =(E4-D4)/D4 -> 0.058521538 | F5: =(F4-E4)/E4 -> 0.0040220689
A6: Revenue | B6: =B7+B8 -> 425.538 | C6: =C7+C8 -> 407.335 | D6: =D7+D8 -> 523.94 | E6: =E7+E8 -> 530.614 | F6: =SUM('DESP Quarterly'!R5:U5) -> 524.876
A7: Air | B7: 219.817 | C7: 201.894 | D7: 241.015 | E7: 214.804 | F7: 201.6
A8: Packages, hotels, and other travel products | B8: 205.721 | C8: 205.441 | D8: 282.925 | E8: 315.81 | F8: 323.2
A9: Cost of revenue | B9: 154.213 | C9: 126.675 | D9: 142.479 | E9: 172.11 | F9: =SUM('DESP Quarterly'!R13:U13) -> -179.565
A10: Unallocated corporate expenses | B10: -20.021 | C10: -5.555
A12: % of hotel gross bookings supplied through Expedia | C12: 0.095
A14: Gross profit | B14: 267.498 | C14: 284.487 | D14: 381.461 | E14: 358.504 | F14: =SUM('DESP Quarterly'!R14:U14) -> 345.311
A15: Gross profit margin | B15: =B14/B6 -> 0.62861131 | C15: =C14/C6 -> 0.6984104 | D15: =D14/D6 -> 0.72806237 | E15: =E14/E6 -> 0.67563992 | F15: =F14/F6 -> 0.65789063
A17: Operating expenses (GAAP)
A18: General and administrative | B18: -78.181 | C18: -64.683 | D18: -72.626 | E18: -67.24 | F18: =SUM('DESP Quarterly'!R18:U18) -> -92.962
A19: Technology and content | B19: -73.535 | C19: -63.251 | D19: -71.308 | E19: -71.154 | F19: =SUM('DESP Quarterly'!R20:U20) -> -73.375
A20: Selling and marketing expenses | B20: -170.149 | C20: -121.466 | D20: -166.288 | E20: -174.357 | F20: =SUM('DESP Quarterly'!R22:U22) -> -187.894
A21: Marketing and sales promotion expenses as % of GMV | B21: =-B20/B4 -> 0.047312764 | C21: =-C20/C4 -> 0.037256835 | D21: =-D20/D4 -> 0.037329938 | E21: =-E20/E4 -> 0.036977372 | F21: =-F20/F4 -> 0.039688649
A23: Depreciation, amortization and impairment | B23: -5.512 | C23: -5.089 | D23: =-5.075-8.751 -> -13.826 | E23: =-5.348-10.14 -> -15.488 | F23: =SUM('DESP Quarterly'!R29:U29) -> -22.794
A24: Share-based compensation | B24: -0.861 | C24: -0.574 | D24: -4.289 | E24: -6.766 | F24: =SUM('DESP Quarterly'!R30:U30) -> -11.705
A25: Total operating expenses (GAAP) | B25: =B18+B19+B20+B23 -> -327.377 | C25: =C18+C19+C20+C23 -> -254.489 | D25: =D18+D19+D20+D23 -> -324.048 | E25: =E18+E19+E20+E23 -> -328.239 | F25: =F18+F19+F20+F23 -> -377.025
A26: Total operating expenses (non-GAAP) | B26: =B25+B24 -> -328.238 | C26: =C25+C24 -> -255.063 | D26: =D25+D24 -> -328.337 | E26: =E25+E24 -> -335.005 | F26: =F25+F24 -> -388.73
A28: Income (loss) from Operations (GAAP) | B28: -54.367 | C28: 35.087 | D28: 71.239 | E28: 45.39 | F28: =SUM('DESP Quarterly'!R34:U34) -> -8.92
A29: OP Margin GAAP (OP/revenue) | B29: =B28/B6 -> -0.12776062 | C29: =C28/C6 -> 0.086137945 | D29: =D28/D6 -> 0.13596786 | E29: =E28/E6 -> 0.085542409 | F29: =F28/F6 -> -0.01699449
A31: Net income (GAAP) | B31: -85.276 | C31: 17.797 | D31: 42.366 | E31: 19.154 | F31: =SUM('DESP Quarterly'!R37:U37) -> -20.91
A32: Net profit margin GAAP (/revenue) | B32: =B31/B6 -> -0.20039573 | C32: =C31/C6 -> 0.043691311 | D32: =D31/D6 -> 0.080860404 | E32: =E31/E6 -> 0.036097804 | F32: =F31/F6 -> -0.039837981
A34: Adjusted EBITDA | B34: -39.067 | C34: 48.585 | D34: 89.354 | E34: 67.329 | F34: =SUM('DESP Quarterly'!R40:U40) -> 25.592
A35: Adjusted EBITDA margin | B35: =B34/B6 -> -0.091806137 | C35: =C34/C6 -> 0.11927529 | D35: =D34/D6 -> 0.17054243 | E35: =E34/E6 -> 0.12688885 | F35: =F34/F6 -> 0.048758183
A37: Shares used in computing earnings per share-Diluted (thousands) | B37: 57078 | C37: 58609 | D37: 61548 | E37: 71254 | F37: 70689
A38: Earning per ADS
A39: - Basic | B39: -1.49 | C39: 0.3 | D39: 0.69 | E39: 0.28 | F39: -0.3
A40: - Diluted EPS | B40: -1.49 | C40: 0.3 | D40: 0.69 | E40: 0.27 | F40: -0.3
A45: Balance Sheet (in million, USD) | C45: 2016 | D45: 2017 | E45: 2018 | F45: 2019
A46: ASSETS
A47: Current assets:
A48: Cash | B48: 102.116 | C48: 75.968 | D48: 371.013 | E48: 346.48 | F48: 309.187
A49: Restricted cash | B49: 19.075 | C49: 22.738 | D49: 29.764 | E49: 5.709 | F49: 4.457
A50: Short-term investment | B50: 40.013 | C50: 0 | D50: 0 | E50: 0 | F50: 0
A51: Cash, Restricted cash and short-term investment | B51: =B50+B49+B48 -> 161.204 | C51: =C50+C49+C48 -> 98.706 | D51: =D50+D49+D48 -> 400.777 | E51: =E50+E49+E48 -> 352.189 | F51: =F50+F49+F48 -> 313.644
A52: Account receivable, net of allowance | C52: 121.098 | D52: 198.273 | E52: 228.448 | F52: 213.551
A53: Related parties receivables (receivables from Expedia) | C53: 2.24 | D53: 5.253 | E53: 8.653 | F53: 19.555
A54: Prepayments and other current assets | B54: 34.434 | C54: 23.587 | D54: 29.405 | E54: 68.471 | F54: 69.694
A55: Total Current Asset | C55: =C51+C52+C53+C54 -> 245.631 | D55: =D51+D52+D53+D54 -> 633.708 | E55: =E51+E52+E53+E54 -> 657.761 | F55: =F51+F52+F53+F54 -> 616.444
A56: Other Assets | C56: 3.597 | D56: 4.658 | E56: 12.751 | F56: 25.351
A57: Restricted cash and cash equivalent | C57: 20.459 | D57: 10 | E57: 0 | F57: 0
A58: Right of use | C58: 0 | D58: 0 | E58: 0 | F58: 7.89
A59: PP&E, net | C59: 13.717 | D59: 16.171 | E59: 19.712 | F59: 21.205
A60: Intangible asset, net | C60: 31.412 | D60: 35.424 | E60: 37.512 | F60: 49.619
A61: Goodwill | C61: 38.894 | D61: 38.733 | E61: 36.207 | F61: 47.326
A62: Total Non-current Asset | C62: =C56+C57+C58+C59+C60+C61 -> 108.079 | D62: =D56+D57+D58+D59+D60+D61 -> 104.986 | E62: =E56+E57+E58+E59+E60+E61 -> 106.182 | F62: =F56+F57+F58+F59+F60+F61 -> 151.391
A63: Total assets | B63: 252.57 | C63: =C62+C55 -> 353.71 | D63: =D62+D55 -> 738.694 | E63: =E62+E55 -> 763.943 | F63: =F62+F55 -> 767.835
A65: LIABILITIES
A66: Current Liabilities
A67: Account payable and accrued expenses | C67: 25.335 | D67: 45.609 | E67: 42.353 | F67: 54.495
A68: Travel supplier payable | C68: 102.237 | D68: 174.817 | E68: 185.45 | F68: 206.954
A69: Related party payable (payables to Expedia) | C69: 71.006 | D69: 84.364 | E69: 83.904 | F69: 86.602
A70: Loans and other financial liabilities | B70: 2.019 | C70: 7.179 | D70: 8.22 | E70: 31.162 | F70: 19.209
A71: Deferred revenue | C71: 29.095 | D71: 30.113 | E71: 8.229 | F71: 8.853
A72: Other liabilities | C72: 48.684 | D72: 39.751 | E72: 33.27 | F72: 57.119
A73: Contingent liabilities | C73: 3.613 | D73: 4.732 | E73: 4.794 | F73: 6.297
A74: Lease liabilities | C74: 0 | D74: 0 | E74: 0 | F74: 4.555
A75: Total current liabilities | C75: =SUM(C67,C68,C69,C70,C71,C72,C73,C74) -> 287.149 | D75: =SUM(D67,D68,D69,D70,D71,D72,D73,D74) -> 387.606 | E75: =SUM(E67,E68,E69,E70,E71,E72,E73,E74) -> 389.162 | F75: =SUM(F67,F68,F69,F70,F71,F72,F73,F74) -> 444.084
A76: Other liabilities | C76: 1.411 | D76: 1.015 | E76: 0.243 | F76: 1.427
A77: Contingent liabilities | C77: 22.413 | D77: 7.115 | E77: 1.968 | F77: 0.054
A78: Lease liabilities | C78: 0 | D78: 0 | E78: 0 | F78: 3.034
A79: Related party liabilities | C79: 125 | D79: 125 | E79: 125 | F79: 125
A80: Total non-current liabilities | C80: =SUM(C79,C78,C77,C76,) -> 148.824 | D80: =SUM(D79,D78,D77,D76,) -> 133.13 | E80: =SUM(E79,E78,E77,E76,) -> 127.211 | F80: =SUM(F79,F78,F77,F76,) -> 129.515
A81: Total liabilities | B81: 431.348 | C81: 435.973 | D81: =D75+D80 -> 520.736 | E81: =E75+E80 -> 516.373 | F81: =F75+F80 -> 573.599
A83: EQUITY
A84: Common stock | C84: =6/1000 -> 0.006 | D84: 253.535 | E84: 255.254 | F84: 261.608
A85: Additional paid-in capital | C85: 312.155 | D85: 316.444 | E85: 321.627 | F85: 326.959
A86: Other reserves | C86: -0.728 | D86: -0.728 | E86: -0.728 | F86: -0.728
A87: Accumulated other comprehensive income | C87: 16.286 | D87: 16.323 | E87: 3.051 | F87: 1.175
A88: Accumulated losses | C88: -409.982 | D88: -367.616 | E88: -305.6 | F88: -326.511
A89: Treasury stock | C89: 0 | D89: 0 | E89: -26.03 | F89: -68.267
A90: Total shareholder's equity | B90: =SUM(B84,B85,B86,B87,B88,B89) -> 0 | C90: =SUM(C84,C85,C86,C87,C88,C89) -> -82.263 | D90: =SUM(D84,D85,D86,D87,D88,D89) -> 217.958 | E90: =SUM(E84,E85,E86,E87,E88,E89) -> 247.574 | F90: =SUM(F84,F85,F86,F87,F88,F89) -> 194.236
A92: Total liabilities and shareholders' equity | C92: =C90+C81 -> 353.71 | D92: =D90+D81 -> 738.694 | E92: =E90+E81 -> 763.947 | F92: =F90+F81 -> 767.835
A94: Working Capital | C94: =C52+C53-C67-C68-C69 -> -75.24 | D94: =D52+D53-D67-D68-D69 -> -101.264 | E94: =E52+E53-E67-E68-E69 -> -74.606 | F94: =F52+F53-F67-F68-F69 -> -114.945
A95: Change in NWC | D95: =D94-C94 -> -26.024 | E95: =E94-D94 -> 26.658 | F95: =F94-E94 -> -40.339
A98: (in million USD)
A99: Cash Flow
A100: Cash Flow from (used in) Operating | B100: -24.249 | C100: -43.292 | D100: 61.226 | E100: -17.62 | F100: 51.565
A101: Cash Flow from (used in) Investing | B101: -80.986 | C101: 14.38 | D101: -18.261 | E101: -26.579 | F101: -36.867
A102: Cash Flow from (used in) Financing | B102: 198.793 | C102: 5.142 | D102: 254.114 | E102: -1.257 | F102: -54.24
A105: Operating Data
A106: Number of transactions by countries | B106: =B107+B108+B109 -> 7.705 | C106: =C107+C108+C109 -> 7.212 | D106: =D107+D108+D109 -> 9.056 | E106: =E107+E108+E109 -> 10.393 | F106: =F107+F108+F109 -> 10.677
A107: Brazil | B107: 3.62 | C107: 2.924 | D107: 3.713 | E107: 4.23 | F107: =SUM('DESP Quarterly'!R58:U58)/1000 -> 4.168
A108: Argentina | B108: 1.787 | C108: 1.798 | D108: 2.264 | E108: 2.378 | F108: =SUM('DESP Quarterly'!R55:U55)/1000 -> 2.294
A109: Other | B109: 2.298 | C109: 2.49 | D109: 3.079 | E109: 3.785 | F109: =SUM('DESP Quarterly'!R61:U61)/1000 -> 4.215
A111: Brazilian share of transactions | B111: =B107/B106 -> 0.46982479 | C111: =C107/C106 -> 0.40543539 | D111: =D107/D106 -> 0.41000442 | E111: =E107/E106 -> 0.40700471 | F111: =F107/F106 -> 0.39037183
A112: Argentinian share of transactions | B112: =B108/B106 -> 0.23192732 | C112: =C108/C106 -> 0.24930671 | D112: =D108/D106 -> 0.25 | E112: =E108/E106 -> 0.22880785 | F112: =F108/F106 -> 0.21485436
A114: Search engine keyword share (Latin America)
A115: Brazil
A116: Argentina
A117: Chile
A118: Colombia
A119: Mexico
A121: Mobile app downloads
A122: Mobile share of visits
A123: Mobile share of transactions | D123: 0.28 | E123: 0.34 | F123: 0.39
...

Sheet DESP Charts
A99: GMV | B99: Q4-17 | C99: Q1-18 | D99: Q2-18 | E99: Q3-18 | F99: Q4-18 | G99: Q1-19 | H99: Q2-19 | I99: Q3-19 | J99: Q4-19
A100: Argentina | B100: 451 | C100: 407 | D100: 312 | E100: 262 | F100: 269 | G100: 275 | H100: 216 | I100: 232 | J100: 304.6
A101: Brazil | B101: 441 | C101: 452 | D101: 435 | E101: 407.9 | F101: 496 | G101: 466 | H101: 452 | I101: 468 | J101: 492.5
A102: Rest of LATAM | B102: 367 | C102: 373 | D102: 437 | E102: 422.8 | F102: 443 | G102: 416 | H102: 450 | I102: 478 | J102: 483.4
B104: Q4-17 | C104: Q1-18 | D104: Q2-18 | E104: Q3-18 | F104: Q4-18 | G104: Q1-19 | H104: Q2-19 | I104: Q3-19 | J104: Q4-19
A105: GMV | B105: 1258.398 | C105: 1231.497 | D105: 1184.355 | E105: 1092.3 | F105: 1207.2 | G105: 1157.5 | H105: 1118.1 | I105: 1177.7 | J105: 1280.9
A106: Revenue | B106: 144.011 | C106: 148.593 | D106: 128.259 | E106: 121.2 | F106: 132.515 | G106: 133.114 | H106: 114.087 | I106: 132.048 | J106: 145.627
A107: GMV Growth | C107: ='DESP Quarterly'!N4 -> 0.20841388 | D107: ='DESP Quarterly'!O4 -> 0.11623561 | E107: ='DESP Quarterly'!P4 -> -0.021255853 | F107: =F105/B105-1 -> -0.040685061 | G107: =G105/C105-1 -> -0.060087032 | H107: =H105/D105-1 -> -0.055941842 | I107: =I105/E105-1 -> 0.078183649 | J107: =J105/F105-1 -> 0.061050364
A108: Revenue Growth | C108: ='DESP Quarterly'!N7/'DESP Quarterly'!J7-1 -> 0.22119857 | D108: ='DESP Quarterly'!O7/'DESP Quarterly'!K7-1 -> 0.039350745 | E108: ='DESP Quarterly'!P7/'DESP Quarterly'!L7-1 -> -0.08719818 | F108: =F106/B106-1 -> -0.079827235 | G108: =G106/C106-1 -> -0.10417045 | H108: =H106/D106-1 -> -0.11049517 | I108: =I106/E106-1 -> 0.08950495 | J108: =J106/F106-1 -> 0.098947289
A109: Blended Take Rate | B109: =B106/B105 -> 0.11443995 | C109: =C106/C105 -> 0.12066046 | D109: =D106/D105 -> 0.10829439 | E109: =E106/E105 -> 0.11095853 | F109: =F106/F105 -> 0.10977054 | G109: =G106/G105 -> 0.1150013 | H109: =H106/H105 -> 0.10203649 | I109: =I106/I105 -> 0.11212363 | J109: =J106/J105 -> 0.11369115
B110: Revenue Breakdown
A111: From Customers | B111: 0.25
A112: From Suppliers | B112: =1-B111 -> 0.75
B113: Q4-17 | C113: Q1-18 | D113: Q2-18 | E113: Q3-18 | F113: Q4-18 | G113: Q1-19 | H113: Q2-19 | I113: Q3-19 | J113: Q4-19
A114: Argentina GMV (as reported) | B114: 451 | C114: 407 | D114: 312 | E114: 262 | F114: 269 | G114: 275 | H114: 216 | I114: 232 | J114: 304.6
A115: Growth (as reported) | G115: =G114/C114-1 -> -0.32432432 | H115: =H114/D114-1 -> -0.30769231 | I115: =I114/E114-1 -> -0.11450382 | J115: =J114/F114-1 -> 0.13234201
A116: Growth (FX Neutral) | G116: =G117/C117-1 -> 0.33906634 | H116: =H117/D117-1 -> 0.29807692 | I116: =I117/E117-1 -> 0.46564885 | J116: =J117/F117-1 -> 0.81040892
A117: Argentina GMV (FX Neutral) | B117: 451 | C117: 407 | D117: 312 | E117: 262 | F117: 269 | G117: 545 | H117: 405 | I117: 384 | J117: 487
B119: Q4-17 | C119: Q1-18 | D119: Q2-18 | E119: Q3-18 | F119: Q4-18 | G119: Q1-19 | H119: Q2-19 | I119: Q3-19 | J119: Q4-19
A120: Brazil GMV (as reported) | B120: 441 | C120: 452 | D120: 435 | E120: 407.9 | F120: 496 | G120: 466 | H120: 452 | I120: 468 | J120: 492.5
A121: Growth (as reported) | G121: =G120/C120-1 -> 0.030973451 | H121: =H120/D120-1 -> 0.03908046 | I121: =I120/E120-1 -> 0.14734003 | J121: =J120/F120-1 -> -0.0070564516
A122: Growth (FX Neutral) | G122: =G123/C123-1 -> 0.19690265 | H122: =H123/D123-1 -> 0.12643678 | I122: =I123/E123-1 -> 0.19362745 | J122: =J123/F123-1 -> 0.072580645
A123: Brazil GMV (FX Neutral) | B123: 441 | C123: 452 | D123: 435 | E123: 408 | F123: 496 | G123: 541 | H123: 490 | I123: 487 | J123: 532
B125: Q4-17 | C125: Q1-18 | D125: Q2-18 | E125: Q3-18 | F125: Q4-18 | G125: Q1-19 | H125: Q2-19 | I125: Q3-19 | J125: Q4-19
A126: Rest of Latam GMV (as reported) | B126: 367 | C126: 373 | D126: 437 | E126: 422.8 | F126: 443 | G126: 416 | H126: 450 | I126: 478 | J126: 483.4
A127: Growth (as reported) | G127: =G126/C126-1 -> 0.1152815 | H127: =H126/D126-1 -> 0.029748284 | I127: =I126/E126-1 -> 0.13055818 | J127: =J126/F126-1 -> 0.091196388
A128: Growth (FX Neutral) | G128: =G129/C129-1 -> 0.17962466 | H128: =H129/D129-1 -> 0.077803204 | I128: =I129/E129-1 -> 0.16071429 | J128: =J129/F129-1 -> 0.1241535
A129: Rest of Latam GMV (FX Neutral) | B129: 367 | C129: 373 | D129: 437 | E129: 392 | F129: 443 | G129: 440 | H129: 471 | I129: 455 | J129: 498
B132: 2017 | C132: 2018 | D132: 2019
A133: Paid Traffic | B133: 0.35 | C133: 0.38 | D133: 0.31
A134: Non-Paid Traffic | B134: =1-B133 -> 0.65 | C134: =1-C133 -> 0.62 | D134: =1-D133 -> 0.69
B136: 2017 | C136: 2018 | D136: 2019
A137: App | B137: 0.27 | C137: 0.34 | D137: 0.37
A138: Site | B138: =1-B137 -> 0.73 | C138: =1-C137 -> 0.66 | D138: =1-D137 -> 0.63
B140: 2017 | C140: 2018 | D140: 2019
A141: Mobile | B141: 0.28 | C141: 0.34 | D141: 0.39
A142: Desktop | B142: =1-B141 -> 0.72 | C142: =1-C141 -> 0.66 | D142: =1-D141 -> 0.61
A145: Argentina | B145: Q4-17 | C145: Q1-18 | D145: Q2-18 | E145: Q3-18 | F145: Q4-18 | G145: Q1-19 | H145: Q2-19 | I145: Q3-19 | J145: Q4-19
A146: # of Transaction ('000) | B146: ='DESP Quarterly'!M55 -> 632 | C146: ='DESP Quarterly'!N55 -> 675 | D146: ='DESP Quarterly'!O55 -> 577 | E146: ='DESP Quarterly'!P55 -> 572 | F146: ='DESP Quarterly'!Q55 -> 558 | G146: ='DESP Quarterly'!R55 -> 618 | H146: ='DESP Quarterly'!S55 -> 496 | I146: ='DESP Quarterly'!T55 -> 551 | J146: ='DESP Quarterly'!U55 -> 629
A147: Transaction Growth | G147: =G146/C146-1 -> -0.084444444 | H147: =H146/D146-1 -> -0.14038128 | I147: =I146/E146-1 -> -0.036713287 | J147: =J146/F146-1 -> 0.12724014
A148: ASP (USD) | B148: ='DESP Quarterly'!M80 -> 713.60759 | C148: ='DESP Quarterly'!N80 -> 602.96296 | D148: ='DESP Quarterly'!O80 -> 540.7279 | E148: ='DESP Quarterly'!P80 -> 458.04196 | F148: ='DESP Quarterly'!Q80 -> 482.07885 | G148: ='DESP Quarterly'!R80 -> 444.98382 | H148: ='DESP Quarterly'!S80 -> 435.48387 | I148: ='DESP Quarterly'!T80 -> 421.05263 | J148: ='DESP Quarterly'!U80 -> 484.26073
A149: ASP Growth | G149: =G148/C148-1 -> -0.26200472 | H149: =H148/D148-1 -> -0.194634 | I149: =I148/E148-1 -> -0.080755323 | J149: =J148/F148-1 -> 0.004525978
A151: Brazil | B151: Q4-17 | C151: Q1-18 | D151: Q2-18 | E151: Q3-18 | F151: Q4-18 | G151: Q1-19 | H151: Q2-19 | I151: Q3-19 | J151: Q4-19
A152: # of Transaction ('000) | B152: ='DESP Quarterly'!M58 -> 966 | C152: ='DESP Quarterly'!N58 -> 1013 | D152: ='DESP Quarterly'!O58 -> 1098 | E152: ='DESP Quarterly'!P58 -> 1041 | F152: ='DESP Quarterly'!Q58 -> 1085 | G152: ='DESP Quarterly'!R58 -> 1045 | H152: ='DESP Quarterly'!S58 -> 948 | I152: ='DESP Quarterly'!T58 -> 1070 | J152: ='DESP Quarterly'!U58 -> 1105
A153: Transaction Growth | G153: =G152/C152-1 -> 0.031589339 | H153: =H152/D152-1 -> -0.13661202 | I153: =I152/E152-1 -> 0.027857829 | J153: =J152/F152-1 -> 0.01843318
A154: ASP (USD) | B154: ='DESP Quarterly'!M81 -> 456.52174 | C154: ='DESP Quarterly'!N81 -> 446.19941 | D154: ='DESP Quarterly'!O81 -> 396.17486 | E154: ='DESP Quarterly'!P81 -> 391.83477 | F154: ='DESP Quarterly'!Q81 -> 457.14286 | G154: ='DESP Quarterly'!R81 -> 445.93301 | H154: ='DESP Quarterly'!S81 -> 476.79325 | I154: ='DESP Quarterly'!T81 -> 437.38318 | J154: ='DESP Quarterly'!U81 -> 445.70136
A155: ASP Growth | G155: =G154/C154-1 -> -0.00059702756 | H155: =H154/D154-1 -> 0.20349192 | I155: =I154/E154-1 -> 0.1162439 | J155: =J154/F154-1 -> -0.025028281
A157: Rest of Latam | B157: Q4-17 | C157: Q1-18 | D157: Q2-18 | E157: Q3-18 | F157: Q4-18 | G157: Q1-19 | H157: Q2-19 | I157: Q3-19 | J157: Q4-19
A158: # of Transaction ('000) | B158: ='DESP Quarterly'!M61 -> 802 | C158: ='DESP Quarterly'!N61 -> 826 | D158: ='DESP Quarterly'!O61 -> 932 | E158: ='DESP Quarterly'!P61 -> 984 | F158: ='DESP Quarterly'!Q61 -> 1032 | G158: ='DESP Quarterly'!R61 -> 989 | H158: ='DESP Quarterly'!S61 -> 1004 | I158: ='DESP Quarterly'!T61 -> 1102 | J158: ='DESP Quarterly'!U61 -> 1120
A159: Transaction Growth | G159: =G158/C158-1 -> 0.19733656 | H159: =H158/D158-1 -> 0.077253219 | I159: =I158/E158-1 -> 0.1199187 | J159: =J158/F158-1 -> 0.085271318
A160: ASP (USD) | B160: ='DESP Quarterly'!M82 -> 457.60599 | C160: ='DESP Quarterly'!N82 -> 451.57385 | D160: ='DESP Quarterly'!O82 -> 468.88412 | E160: ='DESP Quarterly'!P82 -> 429.6748 | F160: ='DESP Quarterly'!Q82 -> 429.26357 | G160: ='DESP Quarterly'!R82 -> 420.6269 | H160: ='DESP Quarterly'!S82 -> 448.20717 | I160: ='DESP Quarterly'!T82 -> 433.75681 | J160: ='DESP Quarterly'!U82 -> 431.60714
A161: ASP Growth | G161: =G160/C160-1 -> -0.068531324 | H161: =H160/D160-1 -> -0.044098207 | I161: =I160/E160-1 -> 0.0095002292 | J161: =J160/F160-1 -> 0.0054595292

Sheet MMYT (2)
A2: (in million, USD, except EPS data)
B3: MMYT | C3: MMYT | D3: MMYT | E3: MMYT | F3: MMYT | G3: MMYT | H3: MMYT | I3: MMYT | J3: MMYT | K3: MMYT | L3: MMYT | M3: MMYT | N3: MMYT | O3: MMYT | P3: MMYT | Q3: MMYT | R3: MMYT | S3: MMYT | T3: MMYT | U3: MMYT | V3: MMYT | W3: MMYT | X3: MMYT | Y3: MMYT | Z3: MMYT | AA3: MMYT | AB3: MMYT
A4: P&L | B4: 14Q1 | C4: 14Q2 | D4: 14Q3 | E4: 14Q4 | F4: 15Q1 | G4: 15Q2 | H4: 15Q3 | I4: 15Q4 | J4: 16Q1 | K4: 16Q2 | L4: 16Q3 | M4: 16Q4 | N4: 1Q17 | O4: 2Q17 | P4: 3Q17 | Q4: 4Q17 | R4: 1Q18 | S4: 2Q18 | T4: 3Q18 | U4: 4Q18 | V4: 1Q19 | W4: 2Q19 | X4: 3Q19 | Y4: 4Q19 | Z4: 1Q20 | AA4: 2Q20 | AB4: 3Q20 | AD4: 43555 | AE4: 43585 | AF4: 43616 | AG4: 43646 | AH4: 43677 | AI4: 43708 | AJ4: 43738 | AK4: 43769 | AL4: 43799 | AM4: 43830 | AN4: 43861 | AO4: 43890 | AP4: 43921
B5: 4QF14 | C5: 1QF15 | D5: 2QF15 | E5: 3QF15 | F5: 4QF15 | G5: 1QF16 | H5: 2QF16 | I5: 3QF16 | J5: 4QF16 | K5: 1QF17 | L5: 2QF17 | M5: 3QF17 | N5: 4QF17 | O5: 1QF18 | P5: 2QF18 | Q5: 3QF18 | R5: 4QF18 | S5: 1QF19 | T5: 2QF19 | U5: 3QF19 | V5: 4QF19 | W5: 1QF20 | X5: 2QF20 | Y5: 3QF20 | Z5: 4QF20 | AA5: 1QF21 | AB5: 2QF21 | AQ5: 43951 | AR5: 43982 | AS5: 44012 | AT5: 44043 | AU5: 44074 | AV5: 44104 | AW5: 44135
N6: Consolidated ibibo at the end of January | X6: 8月 | AB6: 8月
A7: Industry Data
A8: Travel Market | Y8: 67
A9: Online Travel Market | Y9: 23
A10: Online Penetration Rate (%) | W10: 9月 | X10: =+SUM(V18:X18)-AI17 -> 11553454 | Y10: =Y9/Y8 -> 0.34328358 | AA10: 9月 | AB10: =+SUM(Z18:AB18)-AU17 -> 3943000
AA11: Vs 2019 | AB11: =+AB10/X10 -> 0.34128322
A13: COVID cases in India - 现有确诊 | AQ13: 24640 | AR13: 93359 | AS13: 217663 | AT13: 563031 | AU13: 784017 | AV13: 941599 | AW13: 680087
A14: COVID cases in India - 累积确诊 | AQ14: 34682 | AR14: 189765 | AS14: 574926 | AT14: 1690546 | AU14: 3649639 | AV14: 6245404 | AW14: 7829226
A15: COVID cases in India - 新增累计确诊 | AR15: =+AR14-AQ14 -> 155083 | AS15: =+AS14-AR14 -> 385161 | AT15: =+AT14-AS14 -> 1115620 | AU15: =+AU14-AT14 -> 1959093 | AV15: =+AV14-AU14 -> 2595765 | AW15: =+AW14-AV14 -> 1583822
AE16: 464.47 | AF16: 586.34 | AH16: 825.64 | AI16: 943.58 | AK16: 1182.06 | AL16: 1311.54 | AN16: 127.83 | AO16: 251.5 | AR16: 331.94 | AT16: 372.85 | AU16: 401.17
A17: 累积 # of domestic air passengers | AD17: =+V18 -> 35453454 | AE17: =+AE16*100000 -> 46447000 | AF17: =+AF16*100000 -> 58634000 | AG17: =+V18+W18 -> 70680454 | AH17: =+AH16*100000 -> 82564000 | AI17: =+AI16*100000 -> 94358000 | AJ17: =+V18+W18+X18 -> 105911454 | AK17: =+AK16*100000 -> 118206000 | AL17: =+AL16*100000 -> 131154000 | AM17: =+V18+W18+X18+Y18 -> 144100000 | AN17: =+AN16*100000 -> 12783000 | AO17: =+AO16*100000 -> 25150000 | AP17: =+Z18 -> 32912000 | AQ17: N.A. | AR17: =+AR16*100000 -> 33194000 | AS17: =+Z18+AA18 -> 35178000 | AT17: =+AT16*100000 -> 37285000 | AU17: =+AU16*100000 -> 40117000 | AV17: =+Z18+AA18+AB18 -> 44060000
A18: Number of domestic air passengers (scheduled and non-scheduled) | B18: =5062143+4874364+5208065 -> 15144572 | C18: =5247143+5936825+5594898 -> 16778866 | D18: =5172742+5648739+5745441 -> 16566922 | E18: =5830052+5782353+6339272 -> 17951677 | F18: 18547627 | G18: 20291493 | H18: 20198401 | I18: 22070502 | J18: 23005883 | K18: 24570663 | L18: 25118743 | M18: 27190531 | N18: 27279358 | O18: 28876367 | P18: =9533226+9663380+9550493+32174+27747+32108 -> 28839128 | Q18: =10418436+10453411+11206075+32114+36059+36884 -> 32182979 | R18: 33790317 | S18: 34693820 | T18: 34447828 | U18: 36188079 | V18: 35453454 | W18: 35227000 | X18: 35231000 | Y18: =144100000-V18-W18-X18 -> 38188546 | Z18: 32912000 | AA18: =35178000-Z18 -> 2266000 | AB18: =44060000-Z18-AA18 -> 8882000 | AE18: =+AE17-AD17 -> 10993546 | AF18: =+AF17-AE17 -> 12187000 | AG18: =+AG17-AF17 -> 12046454 | AH18: =+AH17-AG17 -> 11883546 | AI18: =+AI17-AH17 -> 11794000 | AJ18: =+AJ17-AI17 -> 11553454 | AK18: =+AK17-AJ17 -> 12294546 | AL18: =+AL17-AK17 -> 12948000 | AM18: =+AM17-AL17 -> 12946000 | AN18: =+AN17 -> 12783000 | AO18: =+AO17-AN17 -> 12367000 | AP18: =+AP17-AO17 -> 7762000 | AR18: =+AR17-AP17 -> 282000 | AS18: =+AS17-AR17 -> 1984000 | AT18: =+AT17-AS17 -> 2107000 | AU18: =+AU17-AT17 -> 2832000 | AV18: =+AV17-AU17 -> 3943000
A19: YoY % growth rate | F19: =F18/B18-1 -> 0.2247046 | G19: =G18/C18-1 -> 0.2093483 | H19: =H18/D18-1 -> 0.21920059 | I19: =I18/E18-1 -> 0.22943957 | J19: =J18/F18-1 -> 0.240368 | K19: =K18/G18-1 -> 0.21088493 | L19: =L18/H18-1 -> 0.24360057 | M19: =M18/I18-1 -> 0.23198516 | ... AB19: =AB18/X18-1 -> -0.74789248 | AQ19: % of 2019 level | AR19: =+AR18/AF18 -> 0.023139411 | AS19: =+AS18/AG18 -> 0.16469577 | AT19: =+AT18/AH18 -> 0.17730398 | AU19: =+AU18/AI18 -> 0.2401221 | AV19: =+AV18/AJ18 -> 0.34128322
A20: Inbound (Domestic & Foreign) | M20: 7170031 | N20: 6778304 | O20: 7357808 | P20: 7091845 | Q20: 8029759 | R20: 7635602 | S20: 7828650 | T20: 7396880 | U20: 8503427 | V20: 7844578 | W20: 7750138 | X20: 7603221 | Y20: 8464724 | Z20: 6044021
A21: YoY % growth rate | Q21: =Q20/M20-1 -> 0.11990576 | R21: =R20/N20-1 -> 0.12647677 | S21: =S20/O20-1 -> 0.063992156 | T21: =T20/P20-1 -> 0.043012079 | U21: =U20/Q20-1 -> 0.058989068 | V21: =V20/R20-1 -> 0.027368634 | W21: =W20/S20-1 -> -0.010028804 | X21: =X20/T20-1 -> 0.02789568 | ... Z21: =Z20/V20-1 -> -0.22952885
A22: Outbound (Domestic & Foreign) | M22: 6672921 | N22: 7424671 | O22: 7252972 | P22: 7507393 | Q22: 7498821 | R22: 8209584 | S22: 7901884 | T22: 7901701 | U22: 7833113 | V22: 8548440 | W22: 7809958 | X22: 8133436 | Y22: 8023714 | Z22: 6523668
A23: YoY % growth rate | Q23: =Q22/M22-1 -> 0.12376889 | R23: =R22/N22-1 -> 0.10571687 | S23: =S22/O22-1 -> 0.089468428 | T23: =T22/P22-1 -> 0.052522627 | U23: =U22/Q22-1 -> 0.044579275 | V23: =V22/R22-1 -> 0.04127566 | W23: =W22/S22-1 -> -0.011633428 | X23: =X22/T22-1 -> 0.02932723 | ... Z23: =Z22/V22-1 -> -0.23685865
A24: Total cross border | M24: =M20+M22 -> 13842952 | N24: =N20+N22 -> 14202975 | O24: =O20+O22 -> 14610780 | P24: =P20+P22 -> 14599238 | Q24: =Q20+Q22 -> 15528580 | R24: =R20+R22 -> 15845186 | S24: =S20+S22 -> 15730534 | T24: =T20+T22 -> 15298581 | ... Z24: =Z20+Z22 -> 12567689
AD25: 1000000
A26: Number of international air passengers(scheduled) | F26: 12088595 | G26: 12153343 | H26: 11775585 | I26: 12623073 | J26: 13214818 | K26: 13296993 | L26: 13318377 | M26: 13842952 | N26: 14202975 | O26: =7351315+7245837 -> 14597152 | P26: =7101550+7513721 -> 14615271 | Q26: =8007419+7481372 -> 15488791 | R26: =7615097+8188071 -> 15803168 | S26: =7828650+7901884 -> 15730534 | T26: 15298581 | U26: 16336540 | V26: 16393018 | W26: 15560096 | X26: 15736657 | Y26: 16488438 | Z26: 12567689 | AD26: (mm) | AE26: 3Q19 | AF26: 4Q19 | AG26: 1Q20 | AH26: 2Q20 | AI26: 3Q20
A27: YoY % growth rate | J27: =J26/F26-1 -> 0.093164094 | K27: =K26/G26-1 -> 0.094101681 | L27: =L26/H26-1 -> 0.13101617 | M27: =M26/I26-1 -> 0.09663883 | N27: =N26/J26-1 -> 0.074776437 | O27: =O26/K26-1 -> 0.097778423 | P27: =P26/L26-1 -> 0.097376279 | Q27: =Q26/M26-1 -> 0.11889364 | ... Z27: =Z26/V26-1 -> -0.23335111 | AD27: # of domestic air passengers | AE27: =(+X18)/1000000 -> 35.231 | AF27: =(+Y18)/1000000 -> 38.188546 | AG27: =(+Z18)/1000000 -> 32.912 | AH27: =(+AA18)/1000000 -> 2.266 | AI27: =(+AB18)/1000000 -> 8.882
M28: =M18+M22 -> 33863452 | N28: =N18+N22 -> 34704029 | O28: =O18+O22 -> 36129339 | P28: =P18+P22 -> 36346521 | Q28: =Q18+Q22 -> 39681800 | R28: =R18+R22 -> 41999901 | S28: =S18+S22 -> 42595704 | T28: =T18+T22 -> 42349529 | ... Z28: =Z18+Z22 -> 39435668 | AD28: Est. MMYT domestic air passengers | AE28: =(+X40)/1000000 -> 9.16006 | AF28: =(+Y40)/1000000 -> 10.310907 | AG28: =(+Z40)/1000000 -> 9.017888 | AI28: =(+AB40)/1000000 -> 2.5307443
AD29: Market share % | AE29: =AE28/AE27 -> 0.26 | AF29: =AF28/AF27 -> 0.27 | AG29: =AG28/AG27 -> 0.274 | AI29: =AI28/AI27 -> 0.28492956
A30: Number of air passengers | F30: =F18+F26 -> 30636222 | G30: =G18+G26 -> 32444836 | H30: =H18+H26 -> 31973986 | I30: =I18+I26 -> 34693575 | J30: =J18+J26 -> 36220701 | K30: =K18+K26 -> 37867656 | L30: =L18+L26 -> 38437120 | M30: =M18+M26 -> 41033483 | ... Z30: =Z18+Z26 -> 45479689
A31: YoY % growth rate | J31: =J30/F30-1 -> 0.18228354 | K31: =K30/G30-1 -> 0.1671397 | L31: =L30/H30-1 -> 0.20213726 | M31: =M30/I30-1 -> 0.18274012 | N31: =N30/J30-1 -> 0.14526588 | O31: =O30/K30-1 -> 0.14803829 | P31: =P30/L30-1 -> 0.13053213 | Q31: =Q30/M30-1 -> 0.16177732 | ... Z31: =Z30/V30-1 -> -0.1228007 | BG31: 1000
A32: Number of roomnights
BE33: 1000
A34: Market Share
A35: % share of domestic air market | B35: 0.12 | C35: 0.13 | D35: 0.13 | E35: 0.15 | F35: 0.15 | G35: 0.15 | H35: 0.15 | I35: 0.15 | J35: 0.158 | K35: 0.162 | M35: 0.17 | O35: 0.23 | P35: 0.23 | Q35: 0.24 | S35: 0.24 | T35: 0.25 | X35: 0.26 | Y35: 0.27 | Z35: 0.274 | AB35: =+AB40/AB18 -> 0.28492956
A36: % share of outbound air market | K36: 0.5
A37: % share of domestic hotel transactions booked via OTAs | F37: 0.226 | I37: 0.25 | J37: 0.29 | K37: 0.28 | L37: 0.27
A38: % share of domestic hotel market(offline+online) | I38: 0.023 | M38: 0.05
A39: % share of OTA market | G39: 0.4
A40: Implied MMYT domestic air passengers | O40: =O35*O18 -> 6641564.4 | P40: =P35*P18 -> 6632999.4 | Q40: =Q35*Q18 -> 7723915 | S40: =S35*S18 -> 8326516.8 | T40: =T35*T18 -> 8611957 | X40: =X35*X18 -> 9160060 | Y40: =Y35*Y18 -> 10310907 | Z40: =Z35*Z18 -> 9017888 | AA40: =+AA55/AA41*1000000 -> 746980.79 | AB40: =+AB55/AB41*1000000 -> 2530744.3
A41: Segments / passengers | O41: =O55/O40*1000000 -> 1.1796769 | P41: =P55/P40*1000000 -> 1.16433 | Q41: =Q55/Q40*1000000 -> 1.0956879 | S41: =S55/S40*1000000 -> 1.1014209 | T41: =T55/T40*1000000 -> 1.1617568 | X41: =X55/X40*1000000 -> 1.2184418 | Y41: =Y55/Y40*1000000 -> 1.1296775 | Z41: =Z55/Z40*1000000 -> 0.95776306 | AA41: =+AVERAGE(X41:Y41) -> 1.1740596 | AB41: 0.927
A43: MMYT air volume - Full FY | R43: =SUM(R44:R45) -> 33.3 | V43: =SUM(V44:V45) -> 39.5 | Z43: =SUM(Z44:Z45) -> 42.2
A44: Indian domestic air travel | R44: 28.6 | V44: 33.5 | Z44: 35.4
A45: Outbound air travel | R45: 4.7 | V45: 6 | Z45: 6.8
A46: Domestic % | R46: =R44/R43 -> 0.85885886 | V46: =V44/V43 -> 0.84810127 | Z46: =Z44/Z43 -> 0.83886256 | AA46: 1 | AB46: 1
A48: MMYT air volume - Quarterly | O48: =O55 -> 7.8349 | P48: =P55 -> 7.723 | Q48: =Q55 -> 8.463 | R48: =R55 -> 9.318 | S48: =S55 -> 9.171 | T48: =T55 -> 10.005 | U48: =U55 -> 10.104 | V48: =V55 -> 10.205 | ... AB48: =AB55 -> 2.346
A49: Indian domestic air travel | O49: =O48*O51 -> 6.7290733 | P49: =P48*P51 -> 6.632967 | Q49: =Q48*Q51 -> 7.2685225 | R49: =R48*R51 -> 8.0028468 | S49: =S48*S51 -> 7.7779367 | T49: =T48*T51 -> 8.4852532 | U49: =U48*U51 -> 8.5692152 | V49: =V48*V51 -> 8.6548734 | ... AB49: =AB48*AB51 -> 2.346
A50: Outbound air travel | O50: =O48-O49 -> 1.1058267 | P50: =P48-P49 -> 1.090033 | Q50: =Q48-Q49 -> 1.1944775 | R50: =R48-R49 -> 1.3151532 | S50: =S48-S49 -> 1.3930633 | T50: =T48-T49 -> 1.5197468 | U50: =U48-U49 -> 1.5347848 | V50: =V48-V49 -> 1.5501266 | ... AB50: =AB48-AB49 -> 0
A51: Domestic % | O51: =P51 -> 0.85885886 | P51: =Q51 -> 0.85885886 | Q51: =R51 -> 0.85885886 | R51: =R46 -> 0.85885886 | S51: =T51 -> 0.84810127 | T51: =U51 -> 0.84810127 | U51: =V51 -> 0.84810127 | V51: =V46 -> 0.84810127 | W51: =X51 -> 0.83886256 | X51: =Y51 -> 0.83886256 | Y51: =Z51 -> 0.83886256 | Z51: =Z46 -> 0.83886256 | AA51: 1 | AB51: 1
A54: Volumes
A55: Air ticketing - flight segments | K55: 4.7275 | L55: 4.692 | O55: 7.8349 | P55: 7.723 | Q55: 8.463 | R55: 9.318 | S55: 9.171 | T55: 10.005 | U55: 10.104 | V55: 10.205 | W55: 10.609 | X55: 11.161 | Y55: 11.648 | Z55: 8.637 | AA55: 0.877 | AB55: 2.346
A56: Flight segments YoY % growth rate | O56: =O55/K55-1 -> 0.65730301 | P56: 0.646 | Q56: 0.649 | R56: 0.551 | S56: =S55/O55-1 -> 0.17053185 | T56: =T55/P55-1 -> 0.29548103 | U56: =U55/Q55-1 -> 0.19390287 | V56: =V55/R55-1 -> 0.095192101 | W56: =W55/S55-1 -> 0.1567986 | X56: =X55/T55-1 -> 0.11554223 | Y56: =Y55/U55-1 -> 0.15281077 | Z56: =Z55/V55-1 -> -0.15365017 | ... AB56: =AB55/X55-1 -> -0.78980378
A57: Flight segments Pro Forma growth rate | O57: 0.222 | P57: 0.15 | Q57: 0.16 | R57: 0.4 | S57: =S55/O55-1 -> 0.17053185 | T57: =T55/P55-1 -> 0.29548103 | U57: =U55/Q55-1 -> 0.19390287 | V57: =V55/R55-1 -> 0.095192101 | W57: =W55/S55-1 -> 0.1567986 | X57: =X55/T55-1 -> 0.11554223 | Y57: =Y55/U55-1 -> 0.15281077 | Z57: =Z55/V55-1 -> -0.15365017 | ... AB57: =AB55/X55-1 -> -0.78980378
A59: Total Roomnights - Hotels & Packages | K59: 2.3451 | L59: 2.211 | O59: 5.7998 | P59: 5.632 | Q59: 5.592 | R59: 4.887 | S59: 6.746 | T59: 6.706 | U59: 7.018 | V59: 6.141 | W59: 7.558 | X59: 7.51 | Y59: 8.472 | Z59: 6.107 | AA59: 0.133 | AB59: 0.855
A60: Total Roomnights - Hotels & Packages YoY % growth rate | O60: =O59/K59-1 -> 1.4731568 | P60: 1.548 | Q60: 1.319 | R60: 0.37 | S60: =S59/O59-1 -> 0.16314356 | T60: =T59/P59-1 -> 0.19069602 | U60: =U59/Q59-1 -> 0.25500715 | V60: =V59/R59-1 -> 0.25659914 | W60: =W59/S59-1 -> 0.12036763 | X60: =X59/T59-1 -> 0.11989263 | Y60: =Y59/U59-1 -> 0.20718153 | Z60: =Z59/V59-1 -> -0.0055365576 | ... AB60: =AB59/X59-1 -> -0.8861518
A61: Standalone hotels booked online -room nights | K61: 1.8814 | L61: 1.888 | O61: 5.4973 | P61: 5.398 | Q61: 5.392 | R61: 4.712 | S61: 6.494 | T61: 6.574 | U61: 6.851 | V61: 5.993 | W61: 7.38 | X61: 7.385 | Y61: 8.295 | Z61: 5.983 | AA61: 0.133 | AB61: 0.854
A62: Standalone hotels booked online -room nights YoY % growth rate | O62: 1.922 | P62: 1.859 | Q62: 1.663 | R62: 1.327 | S62: =S61/O61-1 -> 0.18130719 | T62: =T61/P61-1 -> 0.21785847 | U62: =U61/Q61-1 -> 0.27058605 | V62: =V61/R61-1 -> 0.27185908 | W62: =W61/S61-1 -> 0.13643363 | X62: =X61/T61-1 -> 0.12336477 | Y62: =Y61/U61-1 -> 0.21077215 | Z62: =Z61/V61-1 -> -0.0016686134 | ... AB62: =AB61/X61-1 -> -0.88436019
A63: Standalone hotels booked online -room nights Pro Forma growth rate | O63: 0.36 | P63: 0.29 | Q63: 0.28 | R63: 0.19 | S63: =S61/O61-1 -> 0.18130719 | T63: =T61/P61-1 -> 0.21785847 | U63: =U61/Q61-1 -> 0.27058605 | V63: =V61/R61-1 -> 0.27185908 | W63: =W61/S61-1 -> 0.13643363 | X63: =X61/T61-1 -> 0.12336477 | Y63: =Y61/U61-1 -> 0.21077215 | Z63: =Z61/V61-1 -> -0.0016686134 | ... AB63: =AB61/X61-1 -> -0.88436019
A64: Bus | O64: 9.671 | P64: 8.638 | Q64: 10.248 | R64: 11.013 | S64: 14.894 | T64: 13.24 | U64: 16.219 | V64: 17.111 | W64: 20.98 | X64: 17.682 | Y64: 21.338 | Z64: 18.582 | AA64: 0.429 | AB64: 2.972
A65: YoY % growth rate | S65: =S64/O64-1 -> 0.54006825 | T65: =T64/P64-1 -> 0.53276221 | U65: =U64/Q64-1 -> 0.58265027 | V65: =V64/R64-1 -> 0.55370925 | W65: =W64/S64-1 -> 0.40862092 | X65: =X64/T64-1 -> 0.33549849 | Y65: =Y64/U64-1 -> 0.31561749 | Z65: =Z64/V64-1 -> 0.085968091 | ... AB65: =AB64/X64-1 -> -0.83191947
A66: Pro Forma growth rate | P66: 0.45 | Q66: 0.34 | R66: 0.55 | S66: =S64/O64-1 -> 0.54006825 | T66: =T64/P64-1 -> 0.53276221 | U66: =U64/Q64-1 -> 0.58265027 | V66: =V64/R64-1 -> 0.55370925 | W66: =W64/S64-1 -> 0.40862092 | X66: =X64/T64-1 -> 0.33549849 | Y66: =Y64/U64-1 -> 0.31561749 | Z66: =Z64/V64-1 -> 0.085968091 | ... AB66: =AB64/X64-1 -> -0.83191947
A68: OYO | I68: 0.895 | J68: 0.984 | K68: 1.128 | L68: 1.189 | M68: 1.327 | N68: 1.439 | O68: 1.86 | P68: 2.019 | Q68: 2.789 | R68: 3.488 | S68: =61530*30*(1+1/1.2+1/1.2/1.2)/1000000 -> 4.666025 | T68: =66519*90/1000000 -> 5.98671
A69: vs. MMYT standalone rooms | K69: =K68/K61 -> 0.59955352 | L69: =L68/L61 -> 0.62976695 | O69: =O68/O61 -> 0.33834792 | P69: =P68/P61 -> 0.37402742 | Q69: =Q68/Q61 -> 0.51724777 | R69: =R68/R61 -> 0.74023769 | S69: =S68/S61 -> 0.71851324 | T69: =T68/T61 -> 0.91066474
BF70: 1000
A72: Adjusted revenue(Revenue less service cost):
A73: Air ticketing | B73: 16.094 | C73: 16.4752 | D73: 18.2313 | E73: 18.127 | F73: 18.6757 | G73: 18.262 | H73: 18.1637 | I73: 16.9882 | J73: 22.1954 | K73: 23.88 | L73: 23.556 | M73: 38.216 | N73: 32.862 | O73: 45.613 | P73: 47.053 | Q73: 50.924 | R73: 58.5 | S73: 54.398 | T73: 56.517 | U73: 60.764 | V73: 62.474 | W73: 65.033 | X73: 65.952 | Y73: 70.94 | Z73: 47.795 | AA73: 4.065 | AB73: 11.918
A74: YoY % growth rate | F74: =F73/B73-1 -> 0.16041382 | G74: =G73/C73-1 -> 0.10845392 | H74: =H73/D73-1 -> -0.0037079089 | I74: =I73/E73-1 -> -0.062823413 | J74: =J73/F73-1 -> 0.18846415 | K74: =K73/G73-1 -> 0.30763334 | L74: =L73/H73-1 -> 0.29687233 | M74: =M73/I73-1 -> 1.2495615 | ... AB74: =AB73/X73-1 -> -0.81929282
A75: YoY % Growth on a constant currency basis | B75: 0.391 | C75: 0.239 | D75: 0.164 | E75: 0.102 | F75: 0.17 | G75: 0.176 | H75: 0.069 | I75: -0.001 | J75: 0.282 | K75: 0.381 | L75: 0.332 | M75: 0.102 | N75: 0.472 | O75: 0.861 | P75: 0.947 | Q75: 0.302 | R75: 0.738 | S75: 0.239 | T75: 0.307 | U75: 0.322 | V75: 0.168 | W75: 0.242 | X75: 0.172 | Y75: 0.153 | Z75: -0.207
A76: Hotels and packages | B76: 11.0607 | C76: 17.8729 | D76: 12.5117 | E76: 15.777 | F76: 16.4532 | G76: 18.3681 | H76: 13.4254 | I76: 17.6986 | J76: 27.822 | K76: 33.2133 | L76: 27.715 | M76: 35.472 | N76: 43.935 | O76: 81.263 | P76: 79.194 | Q76: 83.861 | R76: 69.4 | S76: 93.839 | T76: 85.47 | U76: 95.45 | V76: 76.856 | W76: 101.375 | X76: 87.07 | Y76: 106.294 | Z76: 65.377 | AA76: 1.216 | AB76: 5.54 | BG76: =X76/T76-1 -> 0.018720019
A77: YoY % growth rate | F77: =F76/B76-1 -> 0.48753696 | G77: =G76/C76-1 -> 0.027706752 | H77: =H76/D76-1 -> 0.073027646 | I77: =I76/E76-1 -> 0.12179755 | J77: =J76/F76-1 -> 0.69097805 | K77: =K76/G76-1 -> 0.80820553 | L77: =L76/H76-1 -> 1.0643705 | M77: =M76/I76-1 -> 1.0042263 | ... AB77: =AB76/X76-1 -> -0.93637303
A78: YoY % Growth on a constant currency basis | B78: 0.546 | C78: 0.709 | D78: 0.752 | E78: 0.435 | F78: 0.495 | G78: 0.104 | H78: 0.159 | I78: 0.183 | J78: 0.791 | K78: 0.898 | L78: 0.734 | M78: 0.435 | N78: 0.572 | O78: 1.397 | P78: 1.804 | Q78: 1.315 | R78: 0.545 | S78: 0.198 | T78: 0.177 | U78: 0.26 | V78: 0.212 | W78: 0.121 | X78: 0.024 | Y78: 0.098 | Z78: -0.118
A79: Bus ticketing | O79: 11.182 | P79: 9.626 | Q79: 11.584 | R79: 12.01 | S79: 16.056 | T79: 12.12 | U79: 15.073 | V79: 15.576 | W79: 21.351 | X79: 16.647 | Y79: 20.817 | Z79: 16.822 | AA79: 0.332 | AB79: 2.502
A80: YoY % growth rate | S80: =S79/O79-1 -> 0.43587909 | T80: =T79/P79-1 -> 0.25908996 | U80: =U79/Q79-1 -> 0.3011913 | V80: =V79/R79-1 -> 0.29691923 | W80: =W79/S79-1 -> 0.32978326 | X80: =X79/T79-1 -> 0.37351485 | Y80: =Y79/U79-1 -> 0.38107875 | Z80: =Z79/V79-1 -> 0.079994864 | AA80: =AA79/W79-1 -> -0.98445038
A81: YoY % Growth on a constant currency basis | S81: 0.489 | T81: 0.374 | U81: 0.434 | V81: 0.408 | W81: 0.37 | X81: 0.383 | Y81: 0.364 | Z81: 0.115
A82: Other revenues | B82: 1.373 | C82: 1.1046 | D82: 1.3062 | E82: 1.176 | F82: 1.2381 | G82: 1.4727 | H82: 1.6153 | I82: 1.6044 | J82: 1.4485 | K82: 1.775 | L82: 1.925 | M82: 2.857 | N82: 8.291 | O82: 14.338 | P82: 12.945 | Q82: 5.038 | R82: 5.457 | S82: 5.796 | T82: 5.99 | U82: 8.602 | V82: 8.443 | W82: 10.74 | X82: 11.409 | Y82: 8.611 | Z82: 7.187 | AA82: 1.146 | AB82: 3.13
A83: YoY % Growth on a constant currency basis | B83: 0.497 | C83: 0.313 | D83: 0.29 | E83: 0.083 | F83: -0.089 | G83: 0.413 | H83: 0.328 | I83: 0.452 | J83: 0.268 | K83: 0.271 | L83: 0.22 | M83: 0.083 | N83: 4.707 | O83: 7.027 | P83: 5.675 | Q83: 4.758 | S83: 0.906 | T83: 0.958 | U83: 0.869 | V83: 0.679 | W83: 0.919 | X83: 0.912 | Y83: -0.008 | Z83: -0.117
A84: Total | F84: =F73+F76+F79+F82 -> 36.367 | G84: =G73+G76+G79+G82 -> 38.1028 | H84: =H73+H76+H79+H82 -> 33.2044 | I84: =I73+I76+I79+I82 -> 36.2912 | J84: =J73+J76+J79+J82 -> 51.4659 | K84: =K73+K76+K79+K82 -> 58.8683 | L84: =L73+L76+L79+L82 -> 53.196 | M84: =M73+M76+M79+M82 -> 76.545 | ... AA84: =AA73+AA76+AA79+AA82 -> 6.759
A85: YoY % Growth on a constant currency basis | B85: 0.451 | C85: 0.438 | D85: 0.348 | E85: 0.229 | F85: 0.284 | G85: =G194 -> 0.147 | H85: 0.115 | I85: 0.097 | J85: 0.512 | K85: 0.626 | L85: 0.509 | M85: 0.229 | N85: 0.645 | O85: 1.35 | P85: 1.565 | Q85: 0.938 | R85: 0.672 | S85: 0.25 | T85: 0.253 | U85: 0.314 | V85: 0.228 | W85: 0.21 | X85: 0.136 | Y85: 0.134 | Z85: -0.13
A87: Air ticketing % | B87: =B73/B136 -> 0.56415393 | C87: =C73/C136 -> 0.46471004 | D87: =D73/D136 -> 0.56885394 | E87: =E73/E136 -> 0.51673349 | F87: =F73/F136 -> 0.51354837 | G87: =G73/G136 -> 0.44416879 | H87: =H73/H136 -> 0.54703349 | I87: =I73/I136 -> 0.46809765 | ... AB87: =AB73/AB136 -> 0.51615418
A88: Hotels and packages % | B88: =B76/B136 -> 0.38771824 | C88: =C76/C136 -> 0.50413446 | D88: =D76/D136 -> 0.39039069 | E88: =E76/E136 -> 0.44974371 | F88: =F76/F136 -> 0.45243359 | G88: =G76/G136 -> 0.44674936 | H88: =H76/H136 -> 0.4043308 | I88: =I76/I136 -> 0.48767221 | ... AB88: =AB76/AB136 -> 0.23993071
A89: Other revenues % | B89: =B82/B136 -> 0.048128703 | C89: =C82/C136 -> 0.031157055 | D89: =D82/D136 -> 0.040756118 | E89: =E82/E136 -> 0.033523395 | F89: =F82/F136 -> 0.034045537 | G89: =G82/G136 -> 0.035819044 | H89: =H82/H136 -> 0.048647753 | I89: =I82/I136 -> 0.04420809 | ... AB89: =AB82/AB136 -> 0.13555652
A91: Gross bookings | U91: =SUM(U92:U94) -> 1413.537 | V91: =SUM(V92:V94) -> 1372.809 | W91: =SUM(W92:W94) -> 1693.593 | X91: =SUM(X92:X94) -> 1492.918 | Y91: =SUM(Y92:Y94) -> 1700.547 | Z91: =SUM(Z92:Z94) -> 1206.677 | AA91: =SUM(AA92:AA94) -> 64.478 | AB91: =SUM(AB92:AB94) -> 212.958
A92: Air ticketing | B92: 250.7216 | C92: 282.0749 | D92: 291.7579 | E92: 301808.4 | F92: 209.7381 | G92: 329.3536 | H92: 315.2897 | I92: 311.4313 | J92: 318.8807 | K92: 369.2534 | L92: 341.821 | M92: 378.172 | N92: 455.906 | O92: 649.966 | P92: 621.72 | Q92: 689.647 | R92: 743.189 | S92: 804.739 | T92: 749.092 | U92: 821.153 | V92: =V107 -> 839.561 | W92: =W107 -> 985.621 | X92: =X107 -> 916.947 | Y92: =Y107 -> 986.587 | Z92: =Z107 -> 692.112 | AA92: =AA107 -> 54.914 | AB92: =AB107 -> 149.339 | BF92: =X92/X91 -> 0.61419783
A93: Hotels and packages | B93: 91.1208 | C93: 150.1007 | D93: 100.9161 | E93: 117344.8 | F93: 104.636 | G93: 138.529 | H93: 116.0317 | I93: 143.8093 | J93: 158.2599 | K93: 196.691 | L93: 151.6701 | M93: 182.572 | N93: 214.21 | O93: 374.3513 | P93: 342.3025 | Q93: 367.85 | R93: 305.121 | S93: 424.054 | T93: 350.24 | U93: 402.204 | V93: =V112 -> 338.966 | W93: =W112 -> 454.585 | X93: =X112 -> 383.717 | Y93: =Y112 -> 471.707 | Z93: =Z112 -> 316.723 | AA93: =AA112 -> 5.706 | AB93: =AB112 -> 32.801 | BF93: =X93/X91 -> 0.25702483 | BG93: =X93/T93-1 -> 0.095583029
A94: Bus | Q94: 129.843 | T94: 144.11 | U94: 190.18 | V94: =V117 -> 194.282 | W94: =W117 -> 253.387 | X94: =X117 -> 192.254 | Y94: =Y117 -> 242.253 | Z94: =Z117 -> 197.842 | AA94: =AA117 -> 3.858 | AB94: =AB117 -> 30.818 | BF94: =X94/X91 -> 0.12877733
A96: Net revenue margins(take rates)
A97: Air ticketing | B97: 0.064 | C97: 0.058 | D97: 0.062 | E97: 0.06 | F97: 0.062 | G97: 0.055 | H97: 0.058 | I97: 0.055 | J97: 0.07 | K97: 0.065 | L97: 0.069 | M97: 0.101 | N97: =N73/N92 -> 0.072080648 | O97: =O73/O92 -> 0.070177517 | P97: 0.076 | Q97: 0.074 | R97: =R73/R92 -> 0.078714836 | S97: =S73/S92 -> 0.067597072 | T97: =T73/T92 -> 0.075447342 | U97: =U73/U92 -> 0.07399839 | V97: =V73/V92 -> 0.074412699 | W97: =W73/W92 -> 0.065981752 | X97: =X73/X92 -> 0.07192564 | Y97: =Y73/Y92 -> 0.071904454 | ... AA97: =AA73/AA92 -> 0.074024839 | AB97: 0.08
A98: Hotels and packages | B98: 0.121 | C98: 0.119 | D98: 0.124 | E98: 0.134 | F98: 0.157 | G98: 0.133 | H98: 0.116 | I98: 0.123 | J98: 0.176 | K98: 0.133 | L98: 0.183 | M98: 0.194 | N98: =N76/N93 -> 0.20510247 | O98: =O76/O93 -> 0.21707685 | P98: 0.231 | Q98: 0.228 | R98: =R76/R93 -> 0.22745075 | S98: =S76/S93 -> 0.22129021 | T98: =T76/T93 -> 0.24403266 | U98: =U76/U93 -> 0.23731738 | V98: =V76/V93 -> 0.2267366 | W98: =W76/W93 -> 0.2230056 | X98: =X76/X93 -> 0.22691202 | Y98: =Y76/Y93 -> 0.22533903 | ... AA98: =AA76/AA93 -> 0.21310901 | AB98: 0.169
A99: Air Hotel Combined | B99: =SUM(B73,B76)/SUM(B92,B93) -> 0.079436313 | C99: =SUM(C73,C76)/SUM(C92,C93) -> 0.079477185 | D99: =SUM(D73,D76)/SUM(D92,D93) -> 0.078291407 | E99: =SUM(E73,E76)/SUM(E92,E93) -> 8.0886893e-05 | F99: =SUM(F73,F76)/SUM(F92,F93) -> 0.11174235 | G99: =SUM(G73,G76)/SUM(G92,G93) -> 0.078289084 | H99: =SUM(H73,H76)/SUM(H92,H93) -> 0.073237961 | I99: =SUM(I73,I76)/SUM(I92,I93) -> 0.076194434 | ... AB99: =SUM(AB73,AB76)/SUM(AB92,AB93) -> 0.095849347
A100: Bus | Q100: =+Q79/Q94 -> 0.089215437 | T100: =+T79/T94 -> 0.084102422 | U100: =+U79/U94 -> 0.079256494 | V100: =+V79/V94 -> 0.080172121 | W100: =+W79/W94 -> 0.084262413 | X100: =+X79/X94 -> 0.086588576 | Y100: =+Y79/Y94 -> 0.085930824 | Z100: =+Z79/Z94 -> 0.085027446 | AA100: =+AA79/AA94 -> 0.086054951 | AB100: 0.081
A102: Company Data
A103: Gross booking value | B103: 341.8 | C103: 432.2 | D103: 392.7 | E103: 419.2 | F103: 404.4 | G103: 467.9 | H103: 431.3 | I103: 455.2 | J103: 477 | K103: 565.9448 | L103: 493.4901 | M103: 560.74 | N103: 670.11 | O103: =O107+O112+O117 -> 1149.64 | P103: =P107+P112+P117 -> 1070.162 | Q103: =Q107+Q112+Q117 -> 1187.34 | R103: =R107+R112+R117 -> 1183.924 | S103: 1416.36 | T103: 1243 | U103: 1413.537 | V103: =V107+V112+V117 -> 1372.809 | W103: =W107+W112+W117 -> 1693.593 | X103: =X107+X112+X117 -> 1492.918 | Y103: =Y107+Y112+Y117 -> 1700.547 | Z103: =Z107+Z112+Z117 -> 1206.677 | AA103: =AA107+AA112+AA117 -> 64.478 | AB103: =AB107+AB112+AB117 -> 212.958
A104: Gross booking value YoY Growth on a non-constant currency basis | B104: 0.097 | C104: 0.288 | D104: 0.441 | E104: 0.346 | F104: 0.183 | G104: 0.083 | H104: 0.098 | I104: 0.086 | J104: 0.117 | K104: 0.21 | L104: 0.136 | M104: 0.213 | N104: 0.404 | O104: 0.81 | P104: =P103/L103-1 -> 1.1685582 | Q104: =Q103/M103-1 -> 1.1174519 | R104: =R103/N103-1 -> 0.76676068 | S104: =S103/O103-1 -> 0.23200306 | T104: =T103/P103-1 -> 0.16150639 | U104: =U103/Q103-1 -> 0.19050735 | V104: =V103/R103-1 -> 0.15954149 | W104: =W103/S103-1 -> 0.19573625 | ... AB104: =AB103/X103-1 -> -0.85735452
A105: Gross booking value YoY Growth on a constant currency basis | B105: 0.23 | C105: 0.367 | D105: 0.409 | E105: 0.347 | F105: 0.194 | G105: 0.156 | H105: 0.184 | I105: 0.156 | J105: 0.195 | K105: 0.274 | L105: 0.169 | M105: 0.24 | N105: 0.397 | O105: 0.766 | P105: =(P108+P113)/L103-1 -> 0.89892257 | Q105: =(Q108+Q113)/M103-1 -> 0.83050289 | R105: =(R108+R113)/N103-1 -> 0.45419507 | S105: 0.267 | T105: 0.269 | U105: 0.319 | V105: 0.267 | W105: 0.24 | X105: 0.206 | Y105: 0.188 | Z105: -0.09 | AA105: =+AA104 -> -0.96192828 | AB105: =+AB104 -> -0.85735452
A107: Air ticketing gross booking value - reported | J107: 319 | K107: 369.253 | L107: 341.82 | M107: 378.172 | N107: 455.906 | O107: 649.966 | P107: 621.72 | Q107: 689.647 | R107: 743.189 | S107: 804.739 | T107: 749.092 | U107: 821.153 | V107: 839.561 | W107: 985.621 | X107: 916.947 | Y107: 986.587 | Z107: 692.112 | AA107: 54.914 | AB107: 149.339
A108: Air ticketing GBV on a constant currency basis | P108: =341.82*(1+P109) -> 602.97048 | Q108: =378.172*(1+Q109) -> 668.22992 | R108: =455.906*(1+R109) -> 721.24329 | S108: =649.966*(1+S109) -> 827.40672 | T108: =649.966*(1+T109) -> 854.70529 | U108: =Q107*(1+U109) -> 910.33404 | V108: =R107*(1+V109) -> 917.83841 | W108: =S107*(1+W109) -> 1023.628 | X108: =T107*(1+X109) -> 921.38316 | Y108: =U107*(1+Y109) -> 974.70861 | Z108: =V107*(1+Z109) -> 716.98509
A109: Air ticketing GBV YoY Growth on a constant currency basis | P109: 0.764 | Q109: 0.767 | R109: 0.582 | S109: 0.273 | T109: 0.315 | U109: 0.32 | V109: 0.235 | W109: 0.272 | X109: 0.23 | Y109: 0.187 | Z109: -0.146
R110: =R108/R55 -> 77.403229 | S110: =S108/S55 -> 90.219902 | T110: =T108/T55 -> 85.427815 | U110: =U108/U55 -> 90.096401 | V110: =V108/V55 -> 89.94007 | W110: =W108/W55 -> 96.486757 | X110: =X108/X55 -> 82.553818 | Y110: =Y108/Y55 -> 83.680341 | Z110: =Z108/Z55 -> 83.01321
A112: Hotels & Packages gross booking value - reported | J112: 158 | K112: 196.691 | L112: 151.67 | M112: 182.572 | N112: 214.202 | O112: 374.351 | P112: 342.303 | Q112: 367.85 | R112: 305.121 | S112: 424.054 | T112: 350.24 | U112: 402.204 | V112: 338.966 | W112: 454.585 | X112: 383.717 | Y112: 471.707 | Z112: 316.723 | AA112: 5.706 | AB112: 32.801
A113: Hotels & Packages GBV on a constant currency basis | P113: =151.67*(1+P114) -> 334.12901 | Q113: =182.572*(1+Q114) -> 358.20626 | R113: =182.572*(1+R114) -> 253.22736 | S113: =374.351*(1+S114) -> 434.24716 | T113: =374.351*(1+T114) -> 418.15007 | U113: =Q112*(1+U114) -> 445.46635 | V113: =R112*(1+V114) -> 370.72201 | W113: =S112*(1+W114) -> 469.00372 | X113: =T112*(1+X114) -> 385.61424 | Y113: =U112*(1+Y114) -> 465.35003 | Z113: =V112*(1+Z114) -> 328.11909
A114: Hotels & Packages GBV YoY Growth on a constant currency basis | P114: 1.203 | Q114: 0.962 | R114: 0.387 | S114: 0.16 | T114: 0.117 | U114: 0.211 | V114: 0.215 | W114: 0.106 | X114: 0.101 | Y114: 0.157 | Z114: -0.032
R115: =R113/R59 -> 51.816526 | S115: =S113/S59 -> 64.371058 | T115: =T113/T59 -> 62.354618 | U115: =U113/U59 -> 63.474829 | V115: =V113/V59 -> 60.368346 | W115: =W113/W59 -> 62.053946 | X115: =X113/X59 -> 51.34677 | Y115: =Y113/Y59 -> 54.928001 | Z115: =Z113/Z59 -> 53.728359
...

Sheet MMYT charts (2)
AC3: Unit：mn | AD3: 16Q2 | AE3: 17Q2 | AF3: 17Q3 | AG3: 17Q4 | AH3: 18Q1 | AI3: 18Q2 | AJ3: 18Q3 | AK3: 18Q4 | AL3: 19Q1 | AM3: 19Q2 | AN3: 19Q3 | AO3: 19Q4 | AP3: 20Q1 | AQ3: 20Q2 | AR3: 20Q3
AC5: Air ticketing - flight segments | AD5: 4.7275 | AE5: ='MMYT (2)'!O213 -> 0 | AF5: ='MMYT (2)'!P213 -> 0 | AG5: ='MMYT (2)'!Q213 -> 0 | AH5: ='[29]MMYT (2)'!R55 -> 9.318 | AI5: ='[29]MMYT (2)'!S55 -> 9.171 | AJ5: ='[29]MMYT (2)'!T55 -> 10.005 | AK5: ='[29]MMYT (2)'!U55 -> 10.104 | AL5: ='[29]MMYT (2)'!V55 -> 10.205 | AM5: ='[29]MMYT (2)'!W55 -> 10.609 | AN5: ='[29]MMYT (2)'!X55 -> 11.161 | AO5: ='[29]MMYT (2)'!Y55 -> 11.648 | ... AR5: ='[29]MMYT (2)'!AB55 -> 2.346
AC6: YoY % growth rate | AE6: ='MMYT (2)'!O214 -> 1839.692 | AF6: ='MMYT (2)'!P214 -> 1793.97 | AG6: ='MMYT (2)'!Q214 -> 1801.831 | AH6: ='[29]MMYT (2)'!R56 -> 0.551 | AI6: ='[29]MMYT (2)'!S56 -> 0.17053185 | AJ6: ='[29]MMYT (2)'!T56 -> 0.29548103 | AK6: ='[29]MMYT (2)'!U56 -> 0.19390287 | AL6: ='[29]MMYT (2)'!V56 -> 0.095192101 | AM6: ='[29]MMYT (2)'!W56 -> 0.1567986 | AN6: ='[29]MMYT (2)'!X56 -> 0.11554223 | AO6: ='[29]MMYT (2)'!Y56 -> 0.15281077 | ... AR6: ='[29]MMYT (2)'!AB56 -> -0.78980378
AC7: Air ticheting (Pro Forma) growth rate | AE7: ='MMYT (2)'!O215 -> 0 | AF7: ='MMYT (2)'!P215 -> 0 | AG7: ='MMYT (2)'!Q215 -> 0 | AH7: ='[29]MMYT (2)'!R57 -> 0.4 | AI7: ='[29]MMYT (2)'!S57 -> 0.17053185 | AJ7: ='[29]MMYT (2)'!T57 -> 0.29548103 | AK7: ='[29]MMYT (2)'!U57 -> 0.19390287 | AL7: ='[29]MMYT (2)'!V57 -> 0.095192101 | AM7: ='[29]MMYT (2)'!W57 -> 0.1567986 | AN7: ='[29]MMYT (2)'!X57 -> 0.11554223 | AO7: ='[29]MMYT (2)'!Y57 -> 0.15281077 | ... AR7: ='[29]MMYT (2)'!AB57 -> -0.78980378
AC8: Total Roomnights | AD8: 2.3451 | AE8: ='MMYT (2)'!O217 -> 0 | AF8: ='MMYT (2)'!P217 -> 0 | AG8: ='MMYT (2)'!Q217 -> 0 | AH8: ='[29]MMYT (2)'!R59 -> 4.887 | AI8: ='[29]MMYT (2)'!S59 -> 6.746 | AJ8: ='[29]MMYT (2)'!T59 -> 6.706 | AK8: ='[29]MMYT (2)'!U59 -> 7.018 | AL8: ='[29]MMYT (2)'!V59 -> 6.141 | AM8: ='[29]MMYT (2)'!W59 -> 7.558 | AN8: ='[29]MMYT (2)'!X59 -> 7.51 | AO8: ='[29]MMYT (2)'!Y59 -> 8.472 | ... AR8: ='[29]MMYT (2)'!AB59 -> 0.855
AC9: YoY % growth rate | AE9: ='MMYT (2)'!O218 -> 0.655 | AF9: ='MMYT (2)'!P218 -> 0.589 | AG9: ='MMYT (2)'!Q218 -> 0.537 | AH9: ='[29]MMYT (2)'!R60 -> 0.37 | AI9: ='[29]MMYT (2)'!S60 -> 0.16314356 | AJ9: ='[29]MMYT (2)'!T60 -> 0.19069602 | AK9: ='[29]MMYT (2)'!U60 -> 0.25500715 | AL9: ='[29]MMYT (2)'!V60 -> 0.25659914 | AM9: ='[29]MMYT (2)'!W60 -> 0.12036763 | AN9: ='[29]MMYT (2)'!X60 -> 0.11989263 | AO9: ='[29]MMYT (2)'!Y60 -> 0.20718153 | ... AR9: ='[29]MMYT (2)'!AB60 -> -0.8861518
AC10: Standalone hotels booked online -room nights | AD10: 1.8814 | AE10: ='MMYT (2)'!O219 -> 0.254 | AF10: ='MMYT (2)'!P219 -> 0.25 | AG10: ='MMYT (2)'!Q219 -> 0.252 | AH10: ='[29]MMYT (2)'!R61 -> 4.712 | AI10: ='[29]MMYT (2)'!S61 -> 6.494 | AJ10: ='[29]MMYT (2)'!T61 -> 6.574 | AK10: ='[29]MMYT (2)'!U61 -> 6.851 | AL10: ='[29]MMYT (2)'!V61 -> 5.993 | AM10: ='[29]MMYT (2)'!W61 -> 7.38 | AN10: ='[29]MMYT (2)'!X61 -> 7.385 | AO10: ='[29]MMYT (2)'!Y61 -> 8.295 | ... AR10: ='[29]MMYT (2)'!AB61 -> 0.854
AC11: YoY % growth rate | AE11: ='MMYT (2)'!O220 -> 0.909 | AF11: ='MMYT (2)'!P220 -> 0.839 | AG11: ='MMYT (2)'!Q220 -> 0.789 | AH11: ='[29]MMYT (2)'!R62 -> 1.327 | AI11: ='[29]MMYT (2)'!S62 -> 0.18130719 | AJ11: ='[29]MMYT (2)'!T62 -> 0.21785847 | AK11: ='[29]MMYT (2)'!U62 -> 0.27058605 | AL11: ='[29]MMYT (2)'!V62 -> 0.27185908 | AM11: ='[29]MMYT (2)'!W62 -> 0.13643363 | AN11: ='[29]MMYT (2)'!X62 -> 0.12336477 | AO11: ='[29]MMYT (2)'!Y62 -> 0.21077215 | ... AR11: ='[29]MMYT (2)'!AB62 -> -0.88436019
AC12: Standalone hotels (Pro Forma) growth rate | AE12: ='MMYT (2)'!O221 -> 163.183 | AF12: ='MMYT (2)'!P221 -> 176.197 | AG12: ='MMYT (2)'!Q221 -> 190.738 | AH12: ='[29]MMYT (2)'!R63 -> 0.19 | AI12: ='[29]MMYT (2)'!S63 -> 0.18130719 | AJ12: ='[29]MMYT (2)'!T63 -> 0.21785847 | AK12: ='[29]MMYT (2)'!U63 -> 0.27058605 | AL12: ='[29]MMYT (2)'!V63 -> 0.27185908 | AM12: ='[29]MMYT (2)'!W63 -> 0.13643363 | AN12: ='[29]MMYT (2)'!X63 -> 0.12336477 | AO12: ='[29]MMYT (2)'!Y63 -> 0.21077215 | ... AR12: ='[29]MMYT (2)'!AB63 -> -0.88436019
AC13: Bus tickets sold | AE13: ='MMYT (2)'!O222 -> 0 | AF13: ='MMYT (2)'!P222 -> 0 | AG13: ='MMYT (2)'!Q222 -> 0 | AH13: ='[29]MMYT (2)'!R64 -> 11.013 | AI13: ='[29]MMYT (2)'!S64 -> 14.894 | AJ13: ='[29]MMYT (2)'!T64 -> 13.24 | AK13: ='[29]MMYT (2)'!U64 -> 16.219 | AL13: ='[29]MMYT (2)'!V64 -> 17.111 | AM13: ='[29]MMYT (2)'!W64 -> 20.98 | AN13: ='[29]MMYT (2)'!X64 -> 17.682 | AO13: ='[29]MMYT (2)'!Y64 -> 21.338 | ... AR13: ='[29]MMYT (2)'!AB64 -> 2.972
AC14: Bus tickets (Pro Forma) growth rate | AF14: ='MMYT (2)'!P224 -> 1793.97 | AG14: ='MMYT (2)'!Q224 -> 1801.831 | AH14: ='[29]MMYT (2)'!R66 -> 0.55 | AI14: ='[29]MMYT (2)'!S66 -> 0.54006825 | AJ14: ='[29]MMYT (2)'!T66 -> 0.53276221 | AK14: ='[29]MMYT (2)'!U66 -> 0.58265027 | AL14: ='[29]MMYT (2)'!V66 -> 0.55370925 | AM14: ='[29]MMYT (2)'!W66 -> 0.40862092 | AN14: ='[29]MMYT (2)'!X66 -> 0.33549849 | AO14: ='[29]MMYT (2)'!Y66 -> 0.31561749 | ... AR14: ='[29]MMYT (2)'!AB66 -> -0.83191947

Sheet BKNG
A2: (in million, USD, except EPS data) | B2: 182Q1
A3: P&L | B3: Priceline | C3: Priceline | D3: Priceline | E3: Priceline | F3: Priceline | G3: Priceline | H3: Priceline | I3: Priceline | J3: Priceline | K3: Priceline | L3: Priceline | M3: Priceline | N3: Priceline | O3: Priceline | P3: Priceline | Q3: Priceline | R3: Priceline | S3: Priceline | T3: Priceline | U3: Priceline | V3: Priceline | W3: Priceline | X3: Priceline | Y3: Priceline | Z3: Priceline | AA3: Priceline | AB3: Priceline | AC3: Priceline | AD3: Priceline | AE3: Priceline | AF3: Priceline | AG3: Priceline | AH3: Priceline | AI3: Priceline | AJ3: Priceline | AK3: Priceline | AL3: Priceline | AM3: Priceline | AN3: Priceline | AO3: Priceline | AP3: Priceline | AQ3: Priceline | AR3: Priceline | AS3: Priceline | AT3: Priceline | AU3: Priceline | AV3: Priceline | AW3: Priceline | AX3: Priceline | AY3: Priceline | AZ3: Priceline | BA3: Priceline | BB3: Priceline | BC3: Priceline | BD3: Priceline | BE3: Priceline | BF3: Priceline | BG3: Priceline | BH3: Priceline | BI3: Priceline | BJ3: Priceline | BK3: Priceline | BL3: Priceline | BN3: Priceline | BO3: Priceline | BP3: Priceline | BQ3: Priceline | BR3: Priceline | BS3: Priceline | BT3: Priceline | BU3: Priceline | BV3: Priceline | BW3: Priceline
B4: 1999 | C4: 2000 | D4: 2001 | E4: 2002 | F4: 2003 | G4: 2004 | H4: 2005 | I4: 2006 | J4: 2007 | K4: 2008 | L4: 2009 | M4: 2010 | N4: 2011 | O4: 2012 | P4: 2013 | Q4: 2014 | R4: 2015Q1 | S4: 2015Q2 | T4: 2015Q3 | U4: 2015Q4 | V4: 2015 | W4: 2016Q1 | X4: 2016Q2 | Y4: 2016Q3 | Z4: 2016Q4 | AA4: 2017Q1 | AB4: 2017Q2 | AC4: 2017Q3 | AD4: 2017Q4 | AE4: 2018Q1 | AF4: 2018Q2 | AG4: 2018Q3 | AH4: 2018Q4 | AI4: 2019Q1 | AJ4: 2019Q2 | AK4: 2019Q3 | AL4: 2019Q4 | AM4: 2020Q1 | AN4: 2020Q2 | AO4: 2020Q3 | AP4: 2020Q4 | AQ4: 2021Q1 | AR4: 2021Q2 | AS4: 2021Q3 | AT4: 2021Q4 | AU4: 2022Q1 | AV4: 2022Q2 | AW4: 2022Q3 | AX4: 2022Q4 | AY4: 2023Q1 | AZ4: 2023Q2 | BA4: 2023Q3 | BB4: 2023Q4 | BC4: 2024Q1 | BD4: 2024Q2 | BE4: 2024Q3 | BF4: 2024Q4 | BG4: 2025Q1 | BH4: 2025Q2 | BI4: 2025Q3 | BJ4: 2025Q4 | BK4: 2026Q1 | BL4: 2026Q2 | BN4: 2016 | BO4: 2017 | BP4: 2018 | BQ4: 2019 | BR4: 2020 | BS4: 2021 | BT4: 2022 | BU4: 2023 | BV4: 2024 | BW4: 2025
A5: Transaction volume
A6: Gross booking value(mn) | K6: =61%*M6 -> 8324.06 | L6: 9310 | M6: 13646 | N6: 21657 | O6: 28500 | P6: =9153+10118+10765+9138 -> 39174 | Q6: 50300 | R6: 13775 | S6: 14960 | T6: 14778 | U6: 12015 | V6: 55528 | W6: 16653 | X6: 17862 | Y6: 18460 | Z6: 15112 | AA6: 20687 | AB6: 20797 | AC6: 21762 | AD6: 17980 | AE6: 25009 | AF6: 23896 | AG6: 24274 | AH6: 19552 | AI6: 25410 | AJ6: 25039 | AK6: 25281 | AL6: 20713 | AM6: 12393 | AN6: 2306 | AO6: 13382 | AP6: 7313 | AQ6: 11935 | AR6: 21956 | AS6: 23684 | AT6: 19011 | AU6: 27293 | AV6: 34545 | AW6: 32120 | AX6: 27294 | AY6: 39427 | AZ6: 39692 | BA6: 39813 | BB6: =BU6-SUM(AY6:BA6) -> 31695 | BC6: 43535 | BD6: 41431 | BE6: 43447 | BF6: =BV6-SUM(BC6:BE6) -> 37167 | BG6: 46669 | BH6: 46736 | BI6: 49668 | BJ6: =BW6-SUM(BG6:BI6) -> 43034 | BK6: 53758 | BL6: 51000 | BN6: =SUM(W6:Z6) -> 68087 | BO6: =SUM(AA6:AD6) -> 81226 | BP6: =SUM(AE6:AH6) -> 92731 | BQ6: =SUM(AI6:AL6) -> 96443 | BR6: 35395 | BS6: 76586 | BT6: =SUM(AU6:AX6) -> 121252 | BU6: 150627 | BV6: 165580 | BW6: 186107
A7: Gross booking value YoY Growth on a non-constant currency basis | Q7: 0.28 | R7: 0.12 | S7: 0.11 | T7: 0.07 | U7: 0.13 | V7: 0.1 | W7: 0.21 | X7: 0.19 | Y7: 0.25 | Z7: 0.26 | AA7: 0.24 | AB7: 0.164 | AC7: 0.18 | AD7: 0.19 | AE7: 0.209 | AF7: 0.149 | AG7: 0.115 | AH7: 0.087 | AI7: 0.016 | AJ7: 0.048 | AK7: 0.041 | AL7: 0.059 | AM7: -0.512 | AN7: -0.908 | AO7: -0.471 | AP7: -0.647 | AQ7: -0.037 | AR7: 8.517 | AS7: 0.77 | AT7: 1.6 | AU7: 1.287 | AV7: 0.573 | AW7: =AW6/AS6-1 -> 0.35618983 | AX7: 0.436 | AY7: 0.445 | AZ7: 0.149 | BA7: =BA6/AW6-1 -> 0.23950809 | BB7: =BB6/AX6-1 -> 0.16124423 | BC7: =BC6/AY6-1 -> 0.10419256 | BD7: =BD6/AZ6-1 -> 0.043812355 | BE7: =BE6/BA6-1 -> 0.091276719 | BF7: =BF6/BB6-1 -> 0.17264553 | BG7: =BG6/BC6-1 -> 0.071988056 | BH7: =BH6/BD6-1 -> 0.12804422 | ... BL7: =BL6/BH6-1 -> 0.091235878 | BN7: 0.23 | BO7: 0.19 | BP7: 0.14 | BQ7: 0.04 | BR7: =BR6/BQ6-1 -> -0.63299566 | BS7: =BS6/BR6-1 -> 1.1637519 | BT7: =BT6/BS6-1 -> 0.58321364 | BU7: =BU6/BT6-1 -> 0.24226405 | BV7: =BV6/BU6-1 -> 0.099271711 | BW7: =BW6/BV6-1 -> 0.12397029
A8: Gross booking value YoY Growth on a constant currency basis | N8: 0.531 | O8: 0.37 | P8: 0.38 | Q8: 0.3 | R8: 0.26 | S8: 0.26 | T8: 0.22 | U8: 0.24 | V8: 0.25 | W8: 0.26 | X8: 0.21 | Y8: 0.26 | Z8: 0.28 | AA8: 0.27 | AB8: 0.19 | AC8: 0.16 | AD8: 0.14 | AE8: 0.12 | AF8: 0.11 | AG8: 0.14 | AH8: 0.13 | AI8: 0.08 | AJ8: 0.1 | AK8: 0.07 | AL8: 0.07 | AM8: -0.5 | AN8: -0.91 | AO8: -0.48 | AP8: -0.65 | AQ8: -0.06 | AR8: 8.02 | AS8: 0.75 | AT8: 1.64 | AU8: 1.38 | AV8: 0.71 | AW8: 0.5 | AX8: 0.56 | AY8: 0.51 | AZ8: 0.15 | BA8: 0.2 | BB8: 0.13 | BC8: 0.1 | BD8: 0.06 | BE8: 0.09 | BF8: 0.18 | BG8: 0.1 | BH8: 0.09 | BI8: 0.1 | BJ8: 0.11 | BK8: 0.08 | BL8: 0.08 | BN8: 0.25 | BO8: 0.19 | BP8: 0.13 | BQ8: 0.08 | BR8: -0.63 | BW8: 0.1
A9: Growth vs.2019 | AQ9: =AQ6/AI6-1 -> -0.53030303 | AR9: =AR6/AJ6-1 -> -0.12312792 | AS9: =AS6/AK6-1 -> -0.06316997 | AT9: =AT6/AL6-1 -> -0.082170617 | AU9: =AU6/AI6-1 -> 0.074104683 | AV9: =AV6/AJ6-1 -> 0.37964775 | AW9: =AW6/AK6-1 -> 0.27051936 | AX9: =AX6/AL6-1 -> 0.31772317 | AY9: =AY6/AI6-1 -> 0.55163322 | AZ9: =AZ6/AJ6-1 -> 0.58520708 | BA9: =BA6/AK6-1 -> 0.57481903 | BB9: =BB6/AL6-1 -> 0.53019843 | BC9: =BC6/AI6-1 -> 0.71330185 | BD9: =BD6/AJ6-1 -> 0.65465873 | BE9: =BE6/AK6-1 -> 0.71856335 | BF9: =BF6/AL6-1 -> 0.79438034 | BG9: =BG6/$AI6-1 -> 0.83663912 | BH9: =BH6/AJ6-1 -> 0.86652822 | BI9: =BI6/AK6-1 -> 0.96463747 | BJ9: =BJ6/AL6-1 -> 1.0776324 | BK9: =BK6/$AI6-1 -> 1.1156238 | BL9: =BL6/$AJ6-1 -> 1.0368226
A10: Revenue / Gross booking ratio | L10: =L30/L6 -> 0.25115059 | M10: =M30/M6 -> 0.22606661 | N10: =N30/N6 -> 0.20111788 | O10: =O30/O6 -> 0.18459495 | P10: =P30/P6 -> 0.17341364 | Q10: =Q30/Q6 -> 0.16783243 | S10: =S30/S6 -> 0.15243295 | T10: =T30/T6 -> 0.20996759 | U10: =U30/U6 -> 0.16645818 | V10: =V30/V6 -> 0.16611416 | W10: =W30/W6 -> 0.12899291 | X10: =X30/X6 -> 0.14309159 | Y10: =Y30/Y6 -> 0.19992156 | Z10: =Z30/Z6 -> 0.15540187 | ... BE10: =BE30/BE6 -> 0.18399429 | BG10: =BG30/BG6 -> 0.10203776 | BH10: =BH30/BH6 -> 0.14545532 | BI10: =BI30/BI6 -> 0.18136426 | BL10: =BL30/BL6 -> 0.14415686 | BN10: =BN30/BN6 -> 0.15778351 | BO10: =BO30/BO6 -> 0.15612097 | BP10: =BP30/BP6 -> 0.15666061 | BQ10: =BQ30/BQ6 -> 0.15621663 | BR10: =BR30/BR6 -> 0.19200452 | BS10: =BS30/BS6 -> 0.14308098 | BT10: =BT30/BT6 -> 0.14094613 | BU10: =BU30/BU6 -> 0.14184044
A11: Gross profit / Gross booking ratio | L11: =L35/L6 -> 0.1354203 | M11: =M35/M6 -> 0.13989235 | N11: =N35/N6 -> 0.14221176 | O11: =O35/O6 -> 0.14328705 | P11: =P35/P6 -> 0.1459102 | Q11: =Q35/Q6 -> 0.15077793 | S11: =S35/S6 -> 0.13990013 | T11: =T35/T6 -> 0.19943714 | U11: =U35/U6 -> 0.15641973 | V11: =V35/V6 -> 0.15472927 | W11: =W35/W6 -> 0.12126644 | X11: =X35/X6 -> 0.13603281 | Y11: =Y35/Y6 -> 0.19442378 | Z11: =Z35/Z6 -> 0.15063268 | ... BE11: =BE35/BE6 -> 0.18399429 | BG11: =BG35/BG6 -> 0.10203776 | BH11: =BH35/BH6 -> 0.14545532 | BI11: =BI35/BI6 -> 0.18136426 | BL11: =BL35/BL6 -> 0.14415686 | BN11: =BN35/BN6 -> 0.15149283 | BO11: =BO35/BO6 -> 0.15303653 | BP11: =BP35/BP6 -> 0.15666061 | BQ11: =BQ35/BQ6 -> 0.15621663 | BR11: =BR35/BR6 -> 0.19200452 | BS11: =BS35/BS6 -> 0.14308098 | BT11: =BT35/BT6 -> 0.14094613 | BU11: =BU35/BU6 -> 0.14184044
A13: Gross booking breakdown by business model
A14: Agency | R14: 11908 | S14: 12867 | T14: 12850 | U14: 10344 | V14: 47969 | W14: 14534 | X14: 15369 | Y14: 15757 | Z14: 12978 | AA14: 18140 | AB14: 17947 | AC14: 18594 | AD14: 15015 | AE14: 20576 | AF14: 19090 | AG14: 19024 | AH14: 15230 | AI14: 19678 | AJ14: 18638 | AK14: 18118 | AL14: 14218 | AM14: 8320 | AN14: 1535 | AO14: 9521 | AP14: 5098 | AQ14: 8704 | AR14: 15290 | AS14: 14872 | AT14: 11875 | AU14: 16286 | AV14: 19448 | AW14: 17614 | AX14: 14031 | AY14: 19500 | AZ14: 18570 | BA14: 17542 | BB14: =BU14-SUM(AY14:BA14) -> 13294 | BC14: 17774 | BD14: 15601 | BE14: 15085 | BF14: =BV14-SUM(BC14:BE14) -> 12938 | BG14: 15500 | BH14: 14432 | BI14: 13932 | BJ14: =BW14-SUM(BG14:BI14) -> 12218 | BK14: 15022 | BL14: 13961 | BN14: 58638 | BO14: 69696 | BP14: =SUM(AE14:AH14) -> 73920 | BQ14: =SUM(AI14:AL14) -> 70652 | BR14: 24475 | BS14: 50741 | BT14: =SUM(AU14:AX14) -> 67379 | BU14: 68906 | BV14: 61398 | BW14: 56082
A15: Agency YoY growth | W15: =W14/R14-1 -> 0.22052402 | X15: =X14/S14-1 -> 0.19445092 | Y15: =Y14/T14-1 -> 0.22622568 | Z15: =Z14/U14-1 -> 0.25464037 | AA15: =AA14/W14-1 -> 0.24810788 | AB15: =AB14/X14-1 -> 0.16774026 | AC15: =AC14/Y14-1 -> 0.18004696 | AD15: =AD14/Z14-1 -> 0.15695793 | AE15: =AE14/AA14-1 -> 0.13428886 | AF15: =AF14/AB14-1 -> 0.063687524 | AG15: =AG14/AC14-1 -> 0.023125739 | AH15: =AH14/AD14-1 -> 0.014319014 | ... AL15: =AL14/AH14-1 -> -0.0664478 | AM15: -0.577 | AN15: -0.918 | AO15: 0.082 | AP15: =AP14/AL14-1 -> -0.64144043 | AQ15: =AQ14/AM14-1 -> 0.046153846 | AR15: =AR14/AN14-1 -> 8.9609121 | AS15: 0.562 | AT15: 1.329 | AU15: 0.871 | AV15: 0.272 | AW15: 0.184 | AX15: 0.182 | AY15: 0.197 | AZ15: -0.045 | BA15: -0.004 | BB15: =BB14/AX14-1 -> -0.052526548 | BC15: =BC14/AY14-1 -> -0.088512821 | BD15: =BD14/AZ14-1 -> -0.15988153 | BE15: =BE14/BA14-1 -> -0.14006385 | BF15: =BF14/BB14-1 -> -0.026778998 | BG15: =BG14/BC14-1 -> -0.12793969 | BH15: =BH14/BD14-1 -> -0.074931094 | BI15: =BI14/BE14-1 -> -0.076433543 | ... BL15: =BL14/BH14-1 -> -0.032635809 | BN15: =BN14/V14-1 -> 0.22241448 | BO15: =BO14/BN14-1 -> 0.18858078 | BP15: =BP14/BO14-1 -> 0.060606061 | BQ15: =BQ14/BP14-1 -> -0.044209957 | BR15: =BR14/BQ14-1 -> -0.65358376 | BS15: =BS14/BR14-1 -> 1.0731767 | BT15: =BT14/BS14-1 -> 0.32790051 | BU15: =BU14/BT14-1 -> 0.022662847 | BV15: =BV14/BU14-1 -> -0.10896003 | BW15: =BW14/BV14-1 -> -0.086582625
A16: Agency % | R16: =R14/R6 -> 0.86446461 | S16: =S14/S6 -> 0.86009358 | T16: =T14/T6 -> 0.8695358 | U16: =U14/U6 -> 0.86092385 | V16: =V14/V6 -> 0.86387048 | W16: =W14/W6 -> 0.87275566 | X16: =X14/X6 -> 0.86042996 | Y16: =Y14/Y6 -> 0.8535753 | ... BL16: =BL14/BL6 -> 0.2737451 | BN16: =BN14/BN6 -> 0.86122167 | BO16: =BO14/BO6 -> 0.85805038 | BP16: =BP14/BP6 -> 0.79714443 | BQ16: =BQ14/BQ6 -> 0.73257779 | BR16: =BR14/BR6 -> 0.69148185 | BS16: =BS14/BS6 -> 0.66253623 | BT16: =BT14/BT6 -> 0.55569393 | BU16: =BU14/BU6 -> 0.45746115 | ... BW16: =BW14/BW6 -> 0.30134278
A17: Merchant | R17: 1867 | S17: 2094 | T17: 1928 | U17: 1670 | V17: 7559 | W17: 2119 | X17: 2494 | Y17: 2703 | Z17: 2134 | AA17: 2546 | AB17: 2850 | AC17: 3168 | AD17: 2965 | AE17: 4434 | AF17: 4807 | AG17: 5250 | AH17: 4322 | AI17: 5732 | AJ17: 6401 | AK17: 7163 | AL17: 6495 | AM17: 4073 | AN17: 771 | AO17: 3861 | AP17: 2215 | AQ17: 3232 | AR17: 6665 | AS17: 8812 | AT17: 7136 | AU17: 11007 | AV17: 15097 | AW17: 14506 | AX17: 13263 | AY17: 19927 | AZ17: 21122 | BA17: 22271 | BB17: =BU17-SUM(AY17:BA17) -> 18401 | BC17: 25761 | BD17: 25830 | BE17: 28362 | BF17: =BV17-SUM(BC17:BE17) -> 24229 | BG17: 31170 | BH17: 32305 | BI17: 35737 | BJ17: =BW17-SUM(BG17:BI17) -> 30813 | BK17: 38736 | BL17: 36996 | BN17: 9450 | BO17: 11529 | BP17: =SUM(AE17:AH17) -> 18813 | BQ17: =SUM(AI17:AL17) -> 25791 | BR17: =SUM(AM17:AP17) -> 10920 | BS17: 25845 | BT17: =SUM(AU17:AX17) -> 53873 | BU17: 81721 | BV17: 104182 | BW17: 130025
A18: Merchant YoY growth | W18: =W17/R17-1 -> 0.1349759 | X18: =X17/S17-1 -> 0.19102197 | Y18: =Y17/T17-1 -> 0.40197095 | Z18: =Z17/U17-1 -> 0.27784431 | AA18: =AA17/W17-1 -> 0.20151015 | AB18: =AB17/X17-1 -> 0.14274258 | AC18: =AC17/Y17-1 -> 0.17203108 | AD18: =AD17/Z17-1 -> 0.38940956 | AE18: =AE17/AA17-1 -> 0.74155538 | AF18: =AF17/AB17-1 -> 0.68666667 | AG18: =AG17/AC17-1 -> 0.65719697 | AH18: =AH17/AD17-1 -> 0.45767285 | ... AR18: =AR17/AN17-1 -> 7.6446174 | AS18: 1.282 | AT18: 2.222 | AU18: 2.406 | AV18: 1.265 | AW18: 0.646 | AX18: 0.859 | AY18: 0.81 | AZ18: 0.399 | BA18: 0.533 | BB18: =BB17/AX17-1 -> 0.3873935 | BC18: =BC17/AY17-1 -> 0.29276861 | BD18: =BD17/AZ17-1 -> 0.22289556 | BE18: =BE17/BA17-1 -> 0.27349468 | BF18: =BF17/BB17-1 -> 0.31672192 | BG18: =BG17/BC17-1 -> 0.20996856 | BH18: =BH17/BD17-1 -> 0.25067751 | BI18: =BI17/BE17-1 -> 0.26003103 | ... BL18: =BL17/BH17-1 -> 0.14520972 | BN18: =BN17/V17-1 -> 0.25016537 | BO18: =BO17/BN17-1 -> 0.22 | BP18: =BP17/BO17-1 -> 0.63179807 | BQ18: =BQ17/BP17-1 -> 0.37091373 | BR18: =BR17/BQ17-1 -> -0.57659649 | BS18: =BS17/BR17-1 -> 1.3667582 | BT18: =BT17/BS17-1 -> 1.0844651 | BU18: =BU17/BT17-1 -> 0.51691942 | BV18: =BV17/BU17-1 -> 0.27484979 | BW18: =BW17/BV17-1 -> 0.24805629
A19: Merchant % | R19: =R17/R6 -> 0.13553539 | S19: =S17/S6 -> 0.13997326 | T19: =T17/T6 -> 0.1304642 | U19: =U17/U6 -> 0.13899293 | V19: =V17/V6 -> 0.13612952 | W19: =W17/W6 -> 0.12724434 | X19: =X17/X6 -> 0.13962602 | Y19: =Y17/Y6 -> 0.1464247 | ... BL19: =BL17/BL6 -> 0.72541176 | BN19: =BN17/BN6 -> 0.13879301 | BO19: =BO17/BO6 -> 0.14193731 | BP19: =BP17/BP6 -> 0.20287714 | BQ19: =BQ17/BQ6 -> 0.26742221 | BR19: =BR17/BR6 -> 0.30851815 | BS19: =BS17/BS6 -> 0.33746377 | BT19: =BT17/BT6 -> 0.44430607 | BU19: =BU17/BU6 -> 0.54253885 | ... BW19: =BW17/BW6 -> 0.69865722
A20: Merchant vs. Agency by
A21: Gross booking value | L21: 23% vs.77% | M21: 21% vs.79% | N21: 19% vs. 81% | O21: 18% vs. 82% | P21: 17% vs. 83% | Q21: 16%vs.84% | S21: 14%vs.86% | T21: 13%vs.87% | U21: 14%vs.86% | V21: 14%vs.86% | W21: 12.7%vs.87.2% | X21: 14%vs.86% | Y21: 14.6%vs.85.4% | Z21: 14.1% vs. 85.9% | AA21: 12.3% vs. 87.7% | AB21: 13.7% vs. 86.3% | AC21: 14.6% vs. 85.4% | AD21: 16.5% vs. 83.5% | BN21: 13.9% vs. 86.1% | BO21: 14.2% vs. 85.8%
A22: Revenue | L22: 37% vs.62% | M22: 45% vs. 55% | N22: 46% vs. 54% | O22: 40% va. 60% | P22: 32% va. 68% | Q22: 26%vs.69% | S22: 26%vs.74% | T22: 20%vs.80% | U22: 24%vs.76% | V22: 23%vs.71% | W22: 21.9%vs.79.1% | X22: 20.2%vs.72.5% | Y22: 16.8%vs.78.4% | Z22: 18.7% vs. 74.0% | AA22: 18.3% vs. 73.8% | AB22: 16.5% vs. 77.1% | AC22: 15.4% vs. 79.5% | AD22: 18.1% vs. 73.9% | BN22: 19.0% vs. 74.3% | BO22: 16.8% vs. 76.6%
BD23: =BA30*1.02 -> 7487.82 | BE23: =BB30*1.02 -> 4879.68
A24: Revenue
A25: Hotel reservation | L25: - | M25: - | N25: =N$30*N127 -> 3136.0392 | O25: =O$30*O127 -> 3893.1074 | P25: - | Q25: - | V25: -
A26: Air-ticketing | L26: - | M26: - | N26: =N$30*N128 -> 479.1171 | O26: =O$30*O128 -> 420.87648 | P26: - | Q26: - | V26: -
A27: Packaged tour | L27: - | M27: - | N27: - | O27: - | P27: - | Q27: - | V27: -
A28: Corporate travel | L28: - | M28: - | N28: - | O28: - | P28: - | Q28: - | V28: -
A29: Others | L29: - | M29: - | N29: =N$30*N131 -> 740.4537 | O29: =O$30*O131 -> 946.97208 | P29: - | Q29: - | V29: -
A30: Total revenues | B30: 482.41 | C30: 1235.396 | D30: 1171.753 | E30: 1003.606 | F30: 863.661 | G30: 914.372 | H30: 962.66 | I30: 1123.103 | J30: 1409.409 | K30: 1884.806 | L30: 2338.212 | M30: 3084.905 | N30: 4355.61 | O30: 5260.956 | P30: 6793.306 | Q30: 8441.971 | R30: 1840.694 | S30: 2280.397 | T30: 3102.901 | U30: 1999.995 | V30: 9223.987 | W30: 2148.119 | X30: 2555.902 | Y30: 3690.552 | Z30: 2348.433 | AA30: 2419.404 | AB30: 3024.556 | AC30: 4434.029 | AD30: 2803.093 | AE30: 2928.201 | AF30: 3537.094 | AG30: 4849 | AH30: 3213 | AI30: 2837 | AJ30: 3850 | AK30: 5040 | AL30: 3339 | AM30: 2288 | AN30: 630 | AO30: 2640 | AP30: 1238 | AQ30: 1141 | AR30: 2160 | AS30: 4676 | AT30: 2981 | AU30: 2695 | AV30: 4294 | AW30: 6052 | AX30: 4049 | AY30: 3778 | AZ30: 5462 | BA30: 7341 | BB30: 4784 | BC30: 4415 | BD30: 5859 | BE30: 7994 | BF30: 5471 | BG30: 4762 | BH30: 6798 | BI30: 9008 | BJ30: 6349 | BK30: 5532 | BL30: 7352 | BN30: =SUM(W30:Z30) -> 10743.006 | BO30: =SUM(AA30:AD30) -> 12681.082 | BP30: =SUM(AE30:AH30) -> 14527.295 | BQ30: =SUM(AI30:AL30) -> 15066 | BR30: =SUM(AM30:AP30) -> 6796 | BS30: 10958 | BT30: =SUM(AU30:AX30) -> 17090 | BU30: 21365 | BV30: 23739 | BW30: =SUM(BG30:BJ30) -> 26917
A31: Total revenue YoY growth | W31: 0 | X31: 0 | Y31: 0 | Z31: 0 | AA31: 0 | AB31: 0 | AC31: 0 | AD31: 0 | AE31: 0 | AF31: 0 | AG31: 0 | AH31: 0 | AI31: 0 | AJ31: 0 | AK31: 0 | AL31: 0 | AM31: 0 | AN31: 0 | AO31: 0 | AP31: 0 | AQ31: 0 | BF31: =BF30/BB30-1 -> 0.14360368 | BG31: =BG30/BC30-1 -> 0.078595696 | BH31: =BH30/BD30-1 -> 0.16026626 | BI31: =BI30/BE30-1 -> 0.12684513 | BJ31: =BJ30/BF30-1 -> 0.16048254 | BK31: =BK30/BG30-1 -> 0.16169677 | BL31: =BL30/BH30-1 -> 0.081494557 | BN31: 0
A32: Less: business tax and related surcharges
A33: Net revenues | B33: =B30+B31 -> 482.41 | C33: =SUM(C30:C31) -> 1235.396 | D33: =SUM(D30:D31) -> 1171.753 | E33: =SUM(E30:E31) -> 1003.606 | F33: =SUM(F30:F31) -> 863.661 | G33: =SUM(G30:G31) -> 914.372 | H33: =SUM(H30:H31) -> 962.66 | I33: =SUM(I30:I31) -> 1123.103 | J33: =SUM(J30:J31) -> 1409.409 | K33: =SUM(K30:K31) -> 1884.806 | L33: =L30+L31 -> 2338.212 | M33: =M30+M31 -> 3084.905 | N33: =N30+N31 -> 4355.61 | O33: 5260.956 | P33: 6793.306 | Q33: 8441.971 | R33: 1840.694 | S33: 2280.397 | T33: 3102.901 | U33: 1999.995 | V33: 9223.987 | W33: 2148.119 | X33: =X30 -> 2555.902 | Y33: =Y30 -> 3690.552 | Z33: =Z30 -> 2348.433 | AA33: =AA30 -> 2419.404 | AB33: =AB30 -> 3024.556 | AC33: =AC30 -> 4434.029 | AD33: =AD30 -> 2803.093 | AE33: =AE30 -> 2928.201 | AF33: =AF30 -> 3537.094 | AG33: 4849 | AH33: 3213 | AI33: =AI30+AI31 -> 2837 | AJ33: =AJ30+AJ31 -> 3850 | AK33: =AK30+AK31 -> 5040 | AL33: =AL30+AL31 -> 3339 | AM33: =AM30+AM31 -> 2288 | AN33: =AN30+AN31 -> 630 | AO33: =AO30+AO31 -> 2640 | AP33: =AP30+AP31 -> 1238 | ... BF33: =BF30+BF31 -> 5471.1436 | BG33: =BG30+BG32 -> 4762 | BH33: =BH30+BH32 -> 6798 | BI33: =BI30+BI32 -> 9008 | BJ33: =BJ30+BJ32 -> 6349 | BK33: =BK30+BK32 -> 5532 | BL33: =BL30+BL32 -> 7352 | BN33: =SUM(W33:Z33) -> 10743.006 | BO33: =SUM(AA33:AD33) -> 12681.082 | BP33: =SUM(AE33:AH33) -> 14527.295 | BQ33: =SUM(AI33:AL33) -> 15066 | BR33: =SUM(AM33:AP33) -> 6796 | BS33: =SUM(BS30:BS31) -> 10958 | BT33: =SUM(BT30:BT31) -> 17090 | BU33: 21365 | BV33: =SUM(BV30:BV31) -> 23739 | BW33: =SUM(BW30:BW31) -> 26917
A34: Cost of services | B34: -424.579 | C34: -1043.227 | D34: -978.847 | E34: -845.24 | F34: -717.716 | G34: -716.217 | H34: -694.797 | I34: -722.004 | J34: -769.997 | K34: -928.835 | L34: -1077.449 | M34: -1175.934 | N34: -1275.73 | O34: -1177.275 | P34: -1077.42 | Q34: -857.841 | R34: -168.458 | S34: -187.491 | T34: -155.619 | U34: 120.612 | V34: -632.18 | W34: 128.669 | X34: 126.084 | Y34: 101.489 | Z34: 72.072 | AA34: 85.169 | AB34: 72.742 | AC34: 59.476 | AD34: 33.15 | AE34: 0 | AF34: 0 | AG34: 0 | AH34: 0 | AI34: 0 | AJ34: 0 | AK34: 0 | AL34: 0 | AM34: 0 | AN34: 0 | AO34: 0 | AP34: 0 | AQ34: 0 | BN34: =SUM(W34:Z34) -> 428.314 | BO34: =SUM(AA34:AD34) -> 250.537 | BP34: =SUM(AE34:AH34) -> 0
A35: Net revenue/Gross profit | B35: =B30+B34 -> 57.831 | C35: =SUM(C33:C34) -> 192.169 | D35: =SUM(D33:D34) -> 192.906 | E35: =SUM(E33:E34) -> 158.366 | F35: =SUM(F33:F34) -> 145.945 | G35: =SUM(G33:G34) -> 198.155 | H35: =SUM(H33:H34) -> 267.863 | I35: =SUM(I33:I34) -> 401.099 | J35: =SUM(J33:J34) -> 639.412 | K35: =SUM(K33:K34) -> 955.971 | L35: =L30+L34 -> 1260.763 | M35: =M30+M34 -> 1908.971 | N35: =N30+N34 -> 3079.88 | O35: =O33+O34 -> 4083.681 | P35: 5715.886 | Q35: 7584.13 | R35: 1672.236 | S35: 2092.906 | T35: 2947.282 | U35: 1879.383 | V35: 8591.807 | W35: =W33-W34 -> 2019.45 | X35: =X33-X34 -> 2429.818 | Y35: =Y33-Y34 -> 3589.063 | Z35: =Z33-Z34 -> 2276.361 | AA35: =AA33-AA34 -> 2334.235 | AB35: =AB33-AB34 -> 2951.814 | AC35: =AC33-AC34 -> 4374.553 | AD35: =AD33-AD34 -> 2769.943 | ... BL35: =BL33-BL34 -> 7352 | BN35: =SUM(W35:Z35) -> 10314.692 | BO35: =SUM(AA35:AD35) -> 12430.545 | BP35: =SUM(AE35:AH35) -> 14527.295 | BQ35: =SUM(AI35:AL35) -> 15066 | BR35: =SUM(AM35:AP35) -> 6796 | BS35: =BS33 -> 10958 | BT35: =BT33 -> 17090 | BU35: 21365 | BV35: =BV33 -> 23739 | BW35: =BW33 -> 26917
A36: GP margin | B36: =B35/B33 -> 0.11987936 | C36: =C35/C33 -> 0.15555255 | D36: =D35/D33 -> 0.16463026 | E36: =E35/E33 -> 0.15779698 | F36: =F35/F33 -> 0.16898413 | G36: =G35/G33 -> 0.21671158 | H36: =H35/H33 -> 0.27825297 | I36: =I35/I33 -> 0.35713465 | ... AG36: =AG35/AG33 -> 1 | BN36: =BN35/BN33 -> 0.9601309 | BO36: =BO35/BO33 -> 0.98024325
A38: Revenue breakdown by business model
A39: Agency | R39: 1199.348 | S39: 1582.153 | T39: 2345.673 | U39: 1400.724 | V39: 6527.898 | W39: 1500.029 | X39: 1852.961 | Y39: 2892.449 | Z39: 1736.677 | AA39: 1785.313 | AB39: 2332.371 | AC39: 3523.706 | AD39: 2072.736 | AE39: 2113.339 | AF39: 2566.293 | AG39: 3540.874 | AH39: 2259 | AI39: 1949 | AJ39: 2607 | AK39: 3435 | AL39: 2126 | AM39: 1424 | AN39: 357 | AO39: 1723 | AP39: 810 | AQ39: 717 | AR39: 1328 | AS39: 2867 | AT39: 1751 | AU39: 1450 | AV39: 2301 | AW39: 3203 | AX39: 2049 | AY39: 1782 | AZ39: 2429 | BA39: 3135 | BB39: 2068 | BC39: 1763 | BD39: 2144 | BE39: 2753 | BF39: 1864 | BG39: 1564 | BH39: 2044 | BI39: 2569 | BJ39: 1791 | BK39: 1528 | BL39: 1903 | BN39: 7982.116 | BO39: 9714.126 | BP39: =SUM(AE39:AH39) -> 10479.506 | BQ39: =SUM(AI39:AL39) -> 10117 | BR39: 4314 | BS39: =SUM(AQ39:AT39) -> 6663 | BT39: =SUM(AU39:AX39) -> 9003 | BU39: 9414 | BV39: 8524 | BW39: =SUM(BG39:BJ39) -> 7968
A40: Agency YoY growth | W40: =W39/R39-1 -> 0.25070372 | X40: =X39/S39-1 -> 0.17116423 | Y40: =Y39/T39-1 -> 0.23309984 | Z40: =Z39/U39-1 -> 0.2398424 | AA40: =AA39/W39-1 -> 0.19018566 | AB40: =AB39/X39-1 -> 0.25872644 | AC40: =AC39/Y39-1 -> 0.21824309 | AD40: =AD39/Z39-1 -> 0.19350691 | AE40: =AE39/AA39-1 -> 0.18373585 | AF40: =AF39/AB39-1 -> 0.10029365 | AG40: =AG39/AC39-1 -> 0.0048721431 | AH40: =AH39/AD39-1 -> 0.089863832 | ... BL40: =BL39/BH39-1 -> -0.068982387 | BN40: =BN39/V39-1 -> 0.22276972 | BO40: =BO39/BN39-1 -> 0.21698632 | BP40: =BP39/BO39-1 -> 0.078790413 | BQ40: =BQ39/BP39-1 -> -0.034591898 | BR40: =BR39/BQ39-1 -> -0.57358901 | BS40: =BS39/BR39-1 -> 0.54450626 | BT40: =BT39/BS39-1 -> 0.35119316 | BU40: =BU39/BT39-1 -> 0.04565145 | BV40: =BV39/BU39-1 -> -0.094540047 | BW40: =BW39/BV39-1 -> -0.065227593
A41: Agency % | R41: =R39/R35 -> 0.71721216 | S41: =S39/S35 -> 0.75595989 | T41: =T39/T35 -> 0.79587668 | U41: =U39/U35 -> 0.74531056 | V41: =V39/V35 -> 0.75978173 | W41: =W39/W35 -> 0.74279086 | X41: =X39/X35 -> 0.76259251 | Y41: =Y39/Y35 -> 0.80590644 | ... BL41: =BL39/BL35 -> 0.25884113 | BN41: =BN39/BN35 -> 0.77385888 | BO41: =BO39/BO35 -> 0.78147225 | BP41: =BP39/BP35 -> 0.72136664 | BQ41: =BQ39/BQ35 -> 0.67151201 | BR41: =BR39/BR35 -> 0.63478517 | BS41: =BS39/BS35 -> 0.60804891 | BT41: =BT39/BT35 -> 0.5267993 | BU41: =BU39/BU35 -> 0.44062719 | ... BW41: =BW39/BW35 -> 0.2960211
A42: Merchant | R42: 494.675 | S42: 546.013 | T42: 596.503 | U42: 445.782 | V42: 2082.973 | W42: 470.032 | X42: 517.867 | Y42: 620.29 | Z42: 439.816 | AA42: 442.045 | AB42: 498.133 | AC42: 684.289 | AD42: 508.55 | AE42: 526.467 | AF42: 709.864 | AG42: 1049.661 | AH42: 701 | AI42: 603 | AJ42: 959 | AK42: 1313 | AL42: 955 | AM42: 659 | AN42: 245 | AO42: 837 | AP42: 376 | AQ42: 373 | AR42: 661 | AS42: 1622 | AT42: 1040 | AU42: 1050 | AV42: 1749 | AW42: 2614 | AX42: 1780 | AY42: 1752 | AZ42: 2770 | BA42: 3945 | BB42: 2469 | BC42: 2388 | BD42: 3446 | BE42: 4972 | BF42: 3336 | BG42: 2918 | BH42: 4457 | BI42: 6131 | BJ42: 4249 | BK42: 3698 | BL42: 5127 | BN42: 2048.005 | BO42: 2133.017 | BP42: =SUM(AE42:AH42) -> 2986.992 | BQ42: =SUM(AI42:AL42) -> 3830 | BR42: 2117 | BS42: 3696 | BT42: =SUM(AU42:AX42) -> 7193 | BU42: 10936 | BV42: 14142 | BW42: =SUM(BG42:BJ42) -> 17755
A43: Merchant YoY growth | W43: =W42/R42-1 -> -0.049816546 | X43: =X42/S42-1 -> -0.051548223 | Y43: =Y42/T42-1 -> 0.039877419 | Z43: =Z42/U42-1 -> -0.013383223 | AA43: =AA42/W42-1 -> -0.059542755 | AB43: =AB42/X42-1 -> -0.038106309 | AC43: =AC42/Y42-1 -> 0.10317593 | AD43: =AD42/Z42-1 -> 0.15627899 | AE43: =AE42/AA42-1 -> 0.19098056 | AF43: =AF42/AB42-1 -> 0.42504913 | AG43: =AG42/AC42-1 -> 0.53394399 | AH43: =AH42/AD42-1 -> 0.37842887 | ... BL43: =BL42/BH42-1 -> 0.15032533 | BN43: =BN42/V42-1 -> -0.016787544 | BO43: =BO42/BN42-1 -> 0.041509664 | BP43: =BP42/BO42-1 -> 0.40036015 | BQ43: =BQ42/BP42-1 -> 0.2822264 | BR43: =BR42/BQ42-1 -> -0.44725849 | BS43: =BS42/BR42-1 -> 0.74586679 | BT43: =BT42/BS42-1 -> 0.94615801 | BU43: =BU42/BT42-1 -> 0.52036702 | BV43: =BV42/BU42-1 -> 0.2931602 | BW43: =BW42/BV42-1 -> 0.25548013
A44: Merchant % | R44: =R42/R35 -> 0.2958165 | S44: =S42/S35 -> 0.26088749 | T44: =T42/T35 -> 0.20239088 | U44: =U42/U35 -> 0.23719593 | V44: =V42/V35 -> 0.24243713 | W44: =W42/W35 -> 0.23275248 | X44: =X42/X35 -> 0.21312995 | Y44: =Y42/Y35 -> 0.17282784 | ... BL44: =BL42/BL35 -> 0.69736126 | BN44: =BN42/BN35 -> 0.19855222 | BO44: =BO42/BO35 -> 0.17159481 | BP44: =BP42/BP35 -> 0.2056124 | BQ44: =BQ42/BQ35 -> 0.25421479 | BR44: =BR42/BR35 -> 0.31150677 | BS44: =BS42/BS35 -> 0.33728783 | BT44: =BT42/BT35 -> 0.42088941 | BU44: =BU42/BU35 -> 0.5118652 | ... BW44: =BW42/BW35 -> 0.65962031
A45: Advertising & Other revenues | R45: 146.671 | S45: 152.231 | T45: 160.725 | U45: 153.489 | V45: 613.116 | W45: 178.058 | X45: 185.074 | Y45: 177.813 | Z45: 171.94 | AA45: 192.046 | AB45: 194.052 | AC45: 226.034 | AD45: 221.807 | AE45: 288.395 | AF45: 260.937 | AG45: 258.555 | AH45: 253 | AI45: 285 | AJ45: 284 | AK45: 292 | AL45: 258 | AM45: 205 | AN45: 28 | AO45: 80 | AP45: 52 | AQ45: 51 | AR45: 171 | AS45: 187 | AT45: 190 | AU45: 195 | AV45: 244 | AW45: 235 | AX45: 220 | AY45: 244 | AZ45: 263 | BA45: 261 | BB45: 247 | BC45: 264 | BD45: 269 | BE45: 269 | BF45: 271 | BG45: 280 | BH45: 297 | BI45: 308 | BJ45: 309 | BK45: 306 | BL45: 322 | BN45: 712.885 | BO45: 833.939 | BP45: =SUM(AE45:AH45) -> 1060.887 | BQ45: =SUM(AI45:AL45) -> 1119 | BR45: 365 | BS45: 599 | BT45: =SUM(AU45:AX45) -> 894 | BU45: 1015 | BV45: 1073 | BW45: =SUM(BG45:BJ45) -> 1194
A46: Advertising&media YoY growth | W46: =W45/R45-1 -> 0.21399595 | X46: =X45/S45-1 -> 0.21574449 | Y46: =Y45/T45-1 -> 0.10631825 | Z46: =Z45/U45-1 -> 0.12021057 | AA46: =AA45/W45-1 -> 0.078558672 | AB46: =AB45/X45-1 -> 0.048510326 | AC46: =AC45/Y45-1 -> 0.2711894 | AD46: =AD45/Z45-1 -> 0.29002559 | AE46: =AE45/AA45-1 -> 0.50169751 | AF46: =AF45/AB45-1 -> 0.34467565 | AG46: =AG45/AC45-1 -> 0.14387658 | AH46: =AH45/AD45-1 -> 0.14063127 | ... BJ46: =BJ45/BF45-1 -> 0.1402214 | BK46: 0.096 | BL46: =BL45/BH45-1 -> 0.084175084 | BN46: =BN45/V45-1 -> 0.16272451 | BO46: =BO45/BN45-1 -> 0.16980859 | BP46: =BP45/BO45-1 -> 0.27213981 | BQ46: =BQ45/BP45-1 -> 0.054777747 | BR46: =BR45/BQ45-1 -> -0.67381591 | BS46: =BS45/BR45-1 -> 0.64109589 | BT46: =BT45/BS45-1 -> 0.49248748 | BU46: =BU45/BT45-1 -> 0.13534676 | BV46: =BV45/BU45-1 -> 0.057142857 | BW46: =BW45/BV45-1 -> 0.11276794
A47: Advertising&media % | R47: =R45/R35 -> 0.08770951 | S47: =S45/S35 -> 0.072736664 | T47: =T45/T35 -> 0.054533295 | U47: =U45/U35 -> 0.081669888 | V47: =V45/V35 -> 0.071360542 | W47: =W45/W35 -> 0.088171532 | X47: =X45/X35 -> 0.076167845 | Y47: =Y45/Y35 -> 0.049543014 | ... BL47: =BL45/BL35 -> 0.043797606 | BN47: =BN45/BN35 -> 0.069113552 | BO47: =BO45/BO35 -> 0.067087887 | BP47: =BP45/BP35 -> 0.073027153 | BQ47: =BQ45/BQ35 -> 0.074273198 | BR47: =BR45/BR35 -> 0.053708064 | BS47: =BS45/BS35 -> 0.05466326 | BT47: =BT45/BT35 -> 0.052311293 | BU47: =BU45/BU35 -> 0.047507606 | ... BW47: =BW45/BW35 -> 0.044358584
A49: Blended take rate | W49: =W35/W6 -> 0.12126644 | X49: =X35/X6 -> 0.13603281 | Y49: =Y35/Y6 -> 0.19442378 | Z49: =Z35/Z6 -> 0.15063268 | AA49: =AA35/AA6 -> 0.11283584 | AB49: =AB35/AB6 -> 0.14193461 | AC49: =AC35/AC6 -> 0.20101797 | AD49: =AD35/AD6 -> 0.1540569 | ... BL49: =BL35/BL6 -> 0.14415686 | BN49: =BN35/BN6 -> 0.15149283 | BO49: =BO35/BO6 -> 0.15303653 | BP49: =BP35/BP6 -> 0.15666061 | BQ49: =BQ35/BQ6 -> 0.15621663 | BR49: =BR35/BR6 -> 0.19200452 | BS49: =BS35/BS6 -> 0.14308098 | BT49: =BT35/BT6 -> 0.14094613 | BU49: =BU35/BU6 -> 0.14184044 | ... BW49: =BW35/BW6 -> 0.14463185
A50: Take rate by business model
A51: Agency | W51: =W39/W14 -> 0.10320827 | X51: =X39/X14 -> 0.12056484 | Y51: =Y39/Y14 -> 0.18356597 | Z51: =Z39/Z14 -> 0.133817 | AA51: =AA39/AA14 -> 0.098418578 | AB51: =AB39/AB14 -> 0.12995882 | AC51: =AC39/AC14 -> 0.18950769 | AD51: =AD39/AD14 -> 0.13804436 | ... BL51: =BL39/BL14 -> 0.13630829 | BN51: =BN39/BN14 -> 0.13612531 | BO51: =BO39/BO14 -> 0.13937853 | BP51: =BP39/BP14 -> 0.14176821 | BQ51: =BQ39/BQ14 -> 0.14319481 | BR51: =BR39/BR14 -> 0.17626149 | BS51: =BS39/BS14 -> 0.13131393 | BT51: =BT39/BT14 -> 0.1336173 | BU51: =BU39/BU14 -> 0.1366209 | ... BW51: =BW39/BW14 -> 0.14207767
A52: Merchant | W52: =W42/W17 -> 0.22181784 | X52: =X42/X17 -> 0.20764515 | Y52: =Y42/Y17 -> 0.22948206 | Z52: =Z42/Z17 -> 0.20609934 | AA52: =AA42/AA17 -> 0.17362333 | AB52: =AB42/AB17 -> 0.17478351 | AC52: =AC42/AC17 -> 0.21600032 | AD52: =AD42/AD17 -> 0.17151771 | ... BL52: =BL42/BL17 -> 0.13858255 | BN52: =BN42/BN17 -> 0.21672011 | BO52: =BO42/BO17 -> 0.18501318 | BP52: =BP42/BP17 -> 0.15877276 | BQ52: =BQ42/BQ17 -> 0.14850142 | BR52: =BR42/BR17 -> 0.19386447 | BS52: =BS42/BS17 -> 0.14300638 | BT52: =BT42/BT17 -> 0.13351772 | BU52: =BU42/BU17 -> 0.13382117 | ... BW52: =BW42/BW17 -> 0.13655066
A53: Blended take rate-TTM | AI53: =SUM(AF30:AI30)/SUM(AF6:AI6) -> 0.15500681 | AJ53: =SUM(AG30:AJ30)/SUM(AG6:AJ6) -> 0.15644657 | AK53: =SUM(AH30:AK30)/SUM(AH6:AK6) -> 0.15679772 | AL53: =SUM(AI30:AL30)/SUM(AI6:AL6) -> 0.15621663 | AM53: =SUM(AJ30:AM30)/SUM(AJ6:AM6) -> 0.1740105 | AN53: =SUM(AK30:AN30)/SUM(AK6:AN6) -> 0.18613349 | AO53: =SUM(AL30:AO30)/SUM(AL6:AO6) -> 0.18233799 | AP53: =SUM(AM30:AP30)/SUM(AM6:AP6) -> 0.19200995 | ... BL53: =SUM(BI30:BL30)/SUM(BI6:BL6) -> 0.14302137
A55: Operating expenses (GAAP)
A56: OPEX YoY growth | BC56: =BC60/AY60-1 -> 0.061305208 | BD56: =BD61/AZ61-1 -> 0.14365411 | BE56: =BE61/BA61-1 -> 0.20608575 | BF56: =BF61/BB61-1 -> 0.15384615 | BG56: =BG60/BC60-1 -> 0.10372671
A57: Opex reporting口径：
A58: Performance advertising | R58: 633.544 | S58: 758.69 | T58: 784.729 | U58: 561.255 | V58: 2775.437 | W58: 779.909 | X58: 920.763 | Y58: 1040.149 | Z58: 738.466 | AA58: 980.773 | AB58: 1147.589 | AC58: 1224.345 | AD58: 789.064 | AE58: 1106.207 | AF58: 1141.893 | AG58: 1314.055 | AH58: 885 | AI58: 1030 | AJ58: 1192 | AK58: 1291 | AL58: 906 | BN58: 3479.287 | BO58: 4141.771 | BP58: =SUM(AE58:AH58) -> 4447.155 | BQ58: =SUM(AI58:AL58) -> 4419
A59: Brand advertising | R59: 73.254 | S59: 78.431 | T59: 67.858 | U59: 54.161 | V59: 236.485 | W59: 69.845 | X59: 112.321 | Y59: 72.792 | Z59: 40.74 | AA59: 73.012 | AB59: 121.187 | AC59: 112.796 | AD59: 84.589 | AE59: 101.402 | AF59: 123.734 | AG59: 160.126 | AH59: 124 | AI59: 163 | AJ59: 175 | AK59: 124 | AL59: 86 | BN59: 295.698 | BO59: 391.584 | BP59: =SUM(AE59:AH59) -> 509.262 | BQ59: =SUM(AI59:AL59) -> 548
A60: Marketing expense | R60: =SUM(R58:R59) -> 706.798 | S60: =SUM(S58:S59) -> 837.121 | T60: =SUM(T58:T59) -> 852.587 | U60: =SUM(U58:U59) -> 615.416 | V60: =SUM(V58:V59) -> 3011.922 | W60: =SUM(W58:W59) -> 849.754 | X60: =SUM(X58:X59) -> 1033.084 | Y60: =SUM(Y58:Y59) -> 1112.941 | ... AL60: =SUM(AL58:AL59) -> 992 | AM60: 851 | AN60: 211 | AO60: 731 | AP60: 386 | AQ60: 461 | AR60: 988 | AS60: 1378 | AT60: 974 | AU60: 1147 | AV60: 1737 | AW60: 1795 | AX60: 1314 | AY60: 1517 | AZ60: 1801 | BA60: 2022 | BB60: 1433 | BC60: 1610 | BD60: 1939 | BE60: 2151 | BF60: 1578 | BG60: 1777 | BH60: 2139 | BI60: 2340 | BJ60: 1930 | BK60: 2068 | BL60: 2371 | BN60: =SUM(BN58:BN59) -> 3774.985 | BO60: =SUM(BO58:BO59) -> 4533.355 | BP60: =SUM(BP58:BP59) -> 4956.417 | BQ60: =SUM(BQ58:BQ59) -> 4967 | BR60: =SUM(AM60:AP60) -> 2179 | BS60: 3801 | BT60: =SUM(AU60:AX60) -> 5993 | BU60: 6773 | BV60: 7278 | BW60: =SUM(BG60:BJ60) -> 8186
A61: Sales and other expenses | R61: 81.944 | S61: 94.523 | T61: 93.069 | U61: 83.682 | V61: 353.218 | W61: 92.323 | X61: 105.522 | Y61: 124.865 | Z61: 112.515 | AA61: 114.036 | AB61: 131.734 | AC61: 165.539 | AD61: 150.649 | AE61: 165.8 | AF61: 203.593 | AG61: 242.974 | AH61: 218 | AI61: 215 | AJ61: 248 | AK61: 276 | AL61: 216 | AM61: 377 | AN61: 131 | AO61: 129 | AP61: 118 | AQ61: 112 | AR61: 206 | AS61: 302 | AT61: 261 | AU61: 339 | AV61: 465 | AW61: 540 | AX61: 511 | AY61: 570 | AZ61: 717 | BA61: 723 | BB61: 650 | BC61: 678 | BD61: 820 | BE61: 872 | BF61: 750 | BG61: 702 | BH61: 899 | BI61: 1022 | BJ61: 830 | BK61: 804 | BL61: 942 | BN61: 435.225 | BO61: 561.958 | BP61: =SUM(AE61:AH61) -> 830.367 | BQ61: =SUM(AI61:AL61) -> 955 | BR61: =SUM(AM61:AP61) -> 755 | BS61: 881 | BT61: 1986 | BU61: 2744 | BV61: 3120 | BW61: =SUM(BG61:BJ61) -> 3453
A62: Personnel | R62: 258.984 | S62: 289.156 | T62: 305.329 | U62: 312.757 | V62: 1166.226 | W62: 308.351 | X62: 332.654 | Y62: 347.61 | Z62: 361.417 | AA62: 351.03 | AB62: 385.708 | AC62: 483.438 | AD62: 439.405 | AE62: 498.887 | AF62: 522.25 | AG62: 536.735 | AH62: 484 | AI62: 501 | AJ62: 619 | AK62: 566 | AL62: 562 | AM62: 484 | AN62: 452 | AO62: 517 | AP62: 491 | AQ62: 552 | AR62: 686 | AS62: 591 | AT62: 485 | AU62: 596 | AV62: 635 | AW62: 636 | AX62: 598 | AY62: 722 | AZ62: 752 | BA62: 788 | BB62: =1032 -> 1032 | BC62: 826 | BD62: 807 | BE62: 868 | BF62: 853 | BG62: 693 | BH62: 896 | BI62: 945 | BJ62: 869 | BK62: 893 | BL62: 900 | BN62: 1350.032 | BO62: 1659.581 | BP62: =SUM(AE62:AH62) -> 2041.872 | BQ62: =SUM(AI62:AL62) -> 2248 | BR62: =SUM(AM62:AP62) -> 1944 | BS62: 2314 | BT62: =SUM(AU62:AX62) -> 2465 | BU62: 3294 | BV62: 3354 | BW62: =SUM(BG62:BJ62) -> 3403
A63: General and administrative | R63: 100.178 | S63: 98.945 | T63: 109.706 | U63: 106.591 | V63: 415.42 | W63: 113.045 | X63: 112.642 | Y63: 114.586 | Z63: 115.636 | AA63: 135.547 | AB63: 141.634 | AC63: 142.823 | AD63: 165.537 | AE63: 162.139 | AF63: 158.753 | AG63: 183.228 | AH63: 194 | AI63: 191 | AJ63: 180 | AK63: 225 | AL63: 201 | AM63: 201 | AN63: 104 | AO63: 148 | AP63: 128 | AQ63: 119 | AR63: 134 | AS63: 179 | AT63: 188 | AU63: 158 | AV63: 207 | AW63: 262 | AX63: 270 | AY63: 262 | AZ63: 254 | BA63: 387 | BB63: 738 | BC63: 186 | BD63: 112 | BE63: 575 | BF63: 163 | BG63: 142 | BH63: 199 | BI63: 254 | BJ63: 262 | BK63: 100 | BL63: 217 | BN63: 455.909 | BO63: 566.241 | BP63: =SUM(AE63:AH63) -> 698.12 | BQ63: =SUM(AI63:AL63) -> 797 | BR63: =SUM(AM63:AP63) -> 581 | BS63: 620 | BT63: 766 | BU63: 1555 | BV63: 1036 | BW63: =SUM(BG63:BJ63) -> 857
A64: Information technology | R64: 25.361 | S64: 27.156 | T64: 28.83 | U64: 32.27 | V64: 113.617 | W64: 32.788 | X64: 35.797 | Y64: 36.389 | Z64: 37.419 | AA64: 39.945 | AB64: 44.831 | AC64: 47.901 | AD64: 56.667 | AE64: 60.441 | AF64: 58.95 | AG64: 57.742 | AH64: 56 | AI64: 65 | AJ64: 70 | AK64: 71 | AL64: 79 | AM64: 78 | AN64: 70 | AO64: 71 | AP64: 80 | AQ64: 87 | AR64: 93 | AS64: 109 | AT64: 123 | AU64: 134 | AV64: 137 | AW64: 129 | AX64: 126 | AY64: 137 | AZ64: 144 | BA64: 187 | BB64: 187 | BC64: 187 | BD64: 183 | BE64: 194 | BF64: 207 | BG64: 200 | BH64: 219 | BI64: 242 | BJ64: 247 | BK64: 240 | BL64: 263 | BN64: 142.393 | BO64: 189.344 | BP64: =SUM(AE64:AH64) -> 233.133 | BQ64: =SUM(AI64:AL64) -> 285 | BR64: =SUM(AM64:AP64) -> 299 | BS64: 412 | BT64: =SUM(AU64:AX64) -> 526 | BU64: 655 | BV64: 771 | BW64: =SUM(BG64:BJ64) -> 908
A65: Depreciation and amortization | R65: 65.002 | S65: 67.674 | T65: 69.054 | U65: 70.764 | V65: 101.517 | W65: 72.871 | X65: 77.712 | Y65: 78.745 | Z65: 79.807 | AA65: 83.43 | AB65: 85.872 | AC65: 95.91 | AD65: 97.562 | AE65: 103.09 | AF65: 106.666 | AG65: 107.641 | AH65: 109 | AI65: 116 | AJ65: 119 | AK65: 117 | AL65: 117 | AM65: 117 | AN65: 112 | AO65: 115 | AP65: 114 | AQ65: 113 | AR65: 108 | AS65: 102 | AT65: 98 | AU65: 111 | AV65: 107 | AW65: 109 | AX65: 124 | AY65: 120 | AZ65: 121 | BA65: 129 | BB65: 134 | BC65: 137 | BD65: 142 | BE65: 155 | BF65: 157 | BG65: 154 | BH65: 158 | BI65: 160 | BJ65: 151 | BK65: 131 | BL65: 129 | BN65: =SUM(W65:Z65) -> 309.135 | BO65: =SUM(AA65:AD65) -> 362.774 | BP65: =SUM(AE65:AH65) -> 426.397 | BQ65: =SUM(AI65:AL65) -> 469 | BR65: =SUM(AM65:AP65) -> 458 | BS65: 421 | BT65: =SUM(AU65:AX65) -> 451 | BU65: 504 | BV65: 591 | BW65: =SUM(BG65:BJ65) -> 623
A66: Impairment | BI66: 457 | BW66: =SUM(BG66:BJ66) -> 457
A67: Transformation Costs | AI67: =SUM(AI60:AI64) -> 2165 | BG67: 32 | BH67: 38 | BI67: 105 | BJ67: 30 | BK67: 25 | BL67: 30 | BW67: =SUM(BG67:BK67) -> 230
A68: Opex 同Ctrip口径：
A69: Product development | B69: -14.023 | C69: -39.192 | D69: -41.293 | E69: -40.964 | F69: -8.898 | G69: -9.171 | H69: -10.622 | I69: -9.749 | J69: -13.779 | K69: -17.956 | L69: -19.139 | M69: -20.998 | N69: -33.813 | O69: -43.685 | P69: -71.89 | Q69: -97.498 | R69: =-R64 -> -25.361 | S69: =-S64 -> -27.156 | T69: =-T64 -> -28.83 | U69: =-U64 -> -32.27 | V69: =-V64 -> -113.617 | W69: =-W64 -> -32.788 | X69: =-X64 -> -35.797 | Y69: =-Y64 -> -36.389 | ... BL69: =-BL64 -> -263 | BN69: =SUM(W69:Z69) -> -142.393 | BO69: =SUM(AA69:AD69) -> -189.344 | BP69: =SUM(AE69:AH69) -> -233.133 | BQ69: =SUM(AI69:AL69) -> -285 | BR69: =SUM(AM69:AP69) -> -299 | BS69: =-BS64 -> -412 | BT69: =SUM(AU69:AX69) -> -526 | BU69: =SUM(AY69:BB69) -> -655 | BV69: =-BV64 -> -771 | BW69: =SUM(BG69:BJ69) -> -908
A70: Sales and marketing | B70: -79.577 | C70: -148.133 | D70: -115.366 | E70: -82.741 | F70: -75.689 | G70: -93.047 | H70: -123.787 | I70: -187.772 | J70: -255.797 | K70: -386.693 | L70: -482.889 | M70: -704.157 | N70: -1117.374 | O70: =-1273.637-35.492-195.934 -> -1505.063 | P70: =-1798.645-12.7459-235.817 -> -2047.2079 | Q70: -2902.44 | R70: =-SUM(R60:R61) -> -788.742 | S70: =-SUM(S60:S61) -> -931.644 | T70: =-SUM(T60:T61) -> -945.656 | U70: =-SUM(U60:U61) -> -699.098 | V70: =-SUM(V60:V61) -> -3365.14 | W70: =-SUM(W60:W61) -> -942.077 | X70: =-SUM(X60:X61) -> -1138.606 | Y70: =-SUM(Y60:Y61) -> -1237.806 | ... BL70: =-SUM(BL60:BL61) -> -3313 | BN70: =SUM(W70:Z70) -> -4210.21 | BO70: =SUM(AA70:AD70) -> -5095.313 | BP70: =SUM(AE70:AH70) -> -5786.784 | BQ70: =SUM(AI70:AL70) -> -5922 | BR70: =SUM(AM70:AP70) -> -2934 | BS70: =-SUM(BS60:BS61) -> -4682 | BT70: =SUM(AU70:AX70) -> -7848 | BU70: =SUM(AY70:BB70) -> -9433 | BV70: =-SUM(BV60:BV61) -> -10398 | BW70: =SUM(BG70:BJ70) -> -11639
A71: General and administrative (& Personnel for PCLN) | B71: -27.609 | C71: -60.982 | D71: -29.568 | E71: -29.273 | F71: -12.031 | G71: -16.452 | H71: -20.881 | I71: -28.587 | J71: -91.837 | K71: -55.267 | L71: =-180.152-68.555 -> -248.707 | M71: =-270.071-81 -> -351.071 | N71: =-123.652-352.295 -> -475.947 | O71: =-173.171-466.828 -> -639.999 | P71: =-252.994-698.692 -> -951.686 | Q71: -1303.06 | R71: =-SUM(R62:R63) -> -359.162 | S71: =-SUM(S62:S63) -> -388.101 | T71: =-SUM(T62:T63) -> -415.035 | U71: =-SUM(U62:U63) -> -419.348 | V71: =-SUM(V62:V63) -> -1581.646 | W71: =-SUM(W62:W63) -> -421.396 | X71: =-SUM(X62:X63) -> -445.296 | Y71: =-SUM(Y62:Y63) -> -462.196 | ... BL71: =-SUM(BL62:BL63) -> -1117 | BN71: =SUM(W71:Z71) -> -1805.941 | BO71: =SUM(AA71:AD71) -> -2245.122 | BP71: =SUM(AE71:AH71) -> -2739.992 | BQ71: =SUM(AI71:AL71) -> -3045 | BR71: =SUM(AM71:AP71) -> -2525 | BS71: =-SUM(BS62:BS63) -> -2934 | BT71: =-SUM(BT62:BT63) -> -3231 | BU71: =-SUM(BU62:BU63) -> -4849 | BV71: =-SUM(BV62:BV63) -> -4390 | BW71: =SUM(BG71:BJ71) -> -4260
A72: Amortization of intangible assets | F72: -11.533 | G72: -13.501 | H72: -25.366 | I72: -33.449 | J72: -37.072 | K72: -42.796 | L72: -39.193 | M72: -45.763 | N72: -53.824 | O72: -65.141 | P72: -117.975 | Q72: -207.82 | R72: =-R65 -> -65.002 | S72: =-S65 -> -67.674 | T72: =-T65 -> -69.054 | U72: =-U65 -> -70.764 | V72: =-V65 -> -101.517 | W72: =-W65 -> -72.871 | X72: =-X65 -> -77.712 | Y72: =-Y65 -> -78.745 | ... BL72: =-BL65 -> -129 | BN72: =SUM(W72:Z72) -> -309.135 | BO72: =SUM(AA72:AD72) -> -362.774 | BP72: =SUM(AE72:AH72) -> -426.397 | BQ72: =SUM(AI72:AL72) -> -469 | BR72: =SUM(AM72:AP72) -> -458 | BS72: =-BS65 -> -421 | BT72: =SUM(AU72:AX72) -> -451 | BU72: =SUM(AY72:BB72) -> -504 | BV72: =-BV65 -> -591 | BW72: =SUM(BG72:BJ72) -> -623
A73: Other expenses | B73: -998.832 | C73: -264.425 | D73: -4.058 | E73: -27.712 | F73: 0.186 | G73: 0.012 | H73: -1.664 | I73: -0.135 | L73: - | M73: - | N73: - | AN73: -34 | AO73: -41 | AP73: -74 | AQ73: -8 | AR73: -1 | AS73: 0 | AT73: -4 | AU73: -36 | AV73: -6 | AW73: 2 | AX73: 239 | AY73: -1 | AZ73: 0 | BA73: -2 | BB73: -1 | BF73: -34 | BR73: =SUM(AM73:AP73) -> -149 | BS73: -13 | BT73: =SUM(AU73:AX73) -> 199 | BU73: =SUM(AY73:BB73) -> -4 | BV73: -34 | BW73: =SUM(BG73:BJ73) -> 0
A74: Impairment | L74: - | M74: - | N74: - | Y74: -940.7 | Z74: 0 | AA74: 0 | AB74: 0 | AC74: 0 | AD74: 0 | AM74: -489 | AO74: -573 | AP74: 0 | AQ74: 0 | AR74: 0 | AS74: 0 | AT74: 0 | AU74: 0 | AV74: 0 | AW74: 0 | AX74: 0 | AY74: 0 | AZ74: 0 | BI74: =-BI66 -> -457 | BN74: =SUM(W74:Z74) -> -940.7 | BO74: =SUM(AA74:AD74) -> 0 | BP74: =SUM(AE74:AH74) -> 0 | BR74: -1062 | BW74: =SUM(BG74:BJ74) -> -457
A75: Share-based compensation | B75: 0 | C75: 1.711 | D75: 16.508 | E75: 1 | F75: 29.962 | G75: 35.574 | H75: 49.659 | I75: 79.421 | J75: 102.992 | K75: 163.785 | L75: 40.7 | M75: 68.2 | N75: 65.724 | O75: 71.565 | P75: 140.526 | Q75: 186.425 | R75: 54.008 | S75: 60.164 | T75: 58.274 | U75: 74.949 | V75: 247.395 | W75: 66 | X75: 54.976 | Y75: 54.074 | Z75: =BN75-SUM(W75:Y75) -> 74.676 | AA75: 59.059 | AB75: =126.047-AA75 -> 66.988 | AC75: =192.548-SUM(AA75:AB75) -> 66.501 | AD75: =BO75-SUM(AA75:AC75) -> 68.726 | AE75: =71.5 -> 71.5 | AF75: =149.501-AE75 -> 78.001 | AG75: =225.883-AF75-AE75 -> 76.382 | AH75: =331-AE75-AF75-AG75 -> 105.117 | AI75: 78 | AJ75: =162-AI75 -> 84 | AK75: =245-AJ75-AI75 -> 83 | AL75: =325-AK75-AJ75-AI75 -> 80 | AM75: 11 | AN75: =94-AM75 -> 83 | AO75: 79 | AP75: =255-SUM(AM75:AO75) -> 82 | AQ75: 109 | AR75: 90 | AS75: 85 | AT75: =376-SUM(AQ75:AS75) -> 92 | AU75: 93 | AV75: 108 | AW75: =302-AU75-AV75 -> 101 | AX75: =404-AV75-AW75-AU75 -> 102 | AY75: 113 | AZ75: 128 | BA75: 128 | BB75: =530-SUM(AY75:BA75) -> 161 | BC75: 144 | BD75: =284-BC75 -> 140 | BE75: 148 | BF75: 167 | BG75: 142 | BH75: 154 | BI75: 150 | BJ75: 167 | BK75: 141 | BL75: 140 | BN75: 249.726 | BO75: 261.274 | BP75: =SUM(AE75:AH75) -> 331 | BQ75: =SUM(AI75:AL75) -> 325 | BR75: =SUM(AM75:AP75) -> 255 | BS75: 376 | BT75: =SUM(AU75:AX75) -> 404 | BU75: =SUM(AY75:BB75) -> 530 | BV75: 599 | BW75: =SUM(BG75:BJ75) -> 613
A76: Total operating expenses (GAAP) | B76: =SUM(B69:B74)-B75 -> -1120.041 | C76: =SUM(C69:C74)-C75 -> -514.443 | D76: =SUM(D69:D74)-D75 -> -206.793 | E76: =SUM(E69:E74)-E75 -> -181.69 | F76: =SUM(F69:F74)-F75 -> -137.927 | G76: =SUM(G69:G74)-G75 -> -167.733 | H76: =SUM(H69:H74)-H75 -> -231.979 | I76: =SUM(I69:I74)-I75 -> -339.113 | ... K76: =SUM(K69:K74)-K75 -> -666.497 | L76: -789.928 | M76: -1122.174 | N76: =SUM(N69:N74) -> -1680.958 | O76: =SUM(O69:O74) -> -2253.888 | P76: =SUM(P69:P74) -> -3188.7589 | Q76: =SUM(Q69:Q74) -> -4510.818 | R76: =SUM(R69:R74) -> -1238.267 | S76: =SUM(S69:S74) -> -1414.575 | T76: =SUM(T69:T74) -> -1458.575 | U76: =SUM(U69:U74) -> -1221.48 | ... BF76: =SUM(BF69:BF74) -> -3742 | BG76: =SUM(BG69:BG74)-BG67 -> -3700 | BH76: =SUM(BH69:BH74)-BH67 -> -4548 | BI76: =SUM(BI69:BI74)-BI67 -> -5525 | BJ76: =SUM(BJ69:BJ74)-BJ67 -> -4319 | BK76: =SUM(BK69:BK74)-BK67 -> -4261 | BL76: =SUM(BL69:BL74)-BL67 -> -4852 | BN76: =SUM(BN69:BN74) -> -7408.379 | BO76: =SUM(BO69:BO74) -> -7892.553 | BP76: =SUM(AE76:AH76) -> -9186.306 | BQ76: =SUM(AI76:AL76) -> -9721 | BR76: =SUM(AM76:AP76) -> -7427 | BS76: =SUM(BS69:BS74) -> -8462 | BT76: =SUM(AU76:AX76) -> -11988 | BU76: =SUM(AY76:BB76) -> -15531 | BV76: =SUM(BV69:BV74) -> -16184 | BW76: =SUM(BG76:BJ76) -> -18092
A77: Total operating expenses (non-GAAP) | B77: =B76+B75 -> -1120.041 | C77: =C76+C75 -> -512.732 | D77: =D76+D75 -> -190.285 | E77: =E76+E75 -> -180.69 | F77: =F76+F75 -> -107.965 | G77: =G76+G75 -> -132.159 | H77: =H76+H75 -> -182.32 | I77: =I76+I75 -> -259.692 | ... BL77: =BL76+BL75 -> -4712 | BN77: =-(BN35-BN82) -> -7158.653 | BO77: =-(BO35-BO82) -> -7631.279 | BP77: =SUM(AE77:AH77) -> -8855.306 | BQ77: =SUM(AI77:AL77) -> -9396 | BR77: =SUM(AM77:AP77) -> -7172 | BS77: =BS76+BS75 -> -8086 | BT77: =SUM(AU77:AX77) -> -11584 | BU77: =SUM(AY77:BB77) -> -15001 | BV77: =BV76+BV75 -> -15585 | BW77: =SUM(BG77:BJ77) -> -17479
A79: Income (loss) from Operations (GAAP) | B79: =B35+B76 -> -1062.21 | C79: =C35+C76 -> -322.274 | D79: =D35+D76 -> -13.887 | E79: =E35+E76 -> -23.324 | F79: =F35+F76 -> 8.018 | G79: =G35+G76 -> 30.422 | H79: =H35+H76 -> 35.884 | I79: =I35+I76 -> 61.986 | ... K79: =K35+K76 -> 289.474 | L79: 470.835 | M79: 786.797 | N79: 1398.922 | O79: 1829.793 | P79: 2412.414 | Q79: 3073.312 | R79: =R35+R76 -> 433.969 | S79: =S35+S76 -> 678.331 | T79: =T35+T76 -> 1488.707 | U79: =U35+U76 -> 657.903 | V79: 3258.907 | W79: =W35+W76 -> 550.318 | X79: =X35+X76 -> 732.407 | Y79: =Y35+Y76 -> 833.227 | Z79: =Z35+Z76 -> 790.361 | AA79: =AA35+AA76 -> 556.462 | AB79: =AB35+AB76 -> 893.259 | AC79: =AC35+AC76 -> 2101.801 | AD79: =AD35+AD76 -> 986.47 | ... BL79: =BL35+BL76 -> 2500 | BN79: =SUM(W79:Z79) -> 2906.313 | BO79: =SUM(AA79:AD79) -> 4537.992 | BP79: =SUM(AE79:AH79) -> 5340.989 | BQ79: =SUM(AI79:AL79) -> 5345 | BR79: =SUM(AM79:AP79) -> -631 | BS79: =BS35+BS76 -> 2496 | BT79: =SUM(AU79:AX79) -> 5102 | BU79: =SUM(AY79:BB79) -> 5834 | BV79: =BV35+BV76 -> 7555 | BW79: =BW35+BW76 -> 8825
A80: OP Margin GAAP (OP/Revenue) | B80: - | C80: - | D80: - | E80: - | F80: =F79/F33 -> 0.0092837352 | G80: =G79/G33 -> 0.033270923 | H80: =H79/H33 -> 0.037275881 | I80: =I79/I33 -> 0.055191732 | J80: =J79/J33 -> 0.097867262 | K80: =K79/K33 -> 0.15358292 | L80: =L79/L30 -> 0.2013654 | M80: =M79/M30 -> 0.2550474 | N80: =N79/N30 -> 0.32117706 | O80: =O79/O30 -> 0.34780618 | P80: =P79/P30 -> 0.35511635 | Q80: =Q79/Q30 -> 0.36405148 | R80: =R79/R30 -> 0.23576379 | S80: =S79/S30 -> 0.2974618 | ... BL80: =BL79/BL30 -> 0.34004353 | BN80: =BN79/BN30 -> 0.27053071 | BO80: =BO79/BO30 -> 0.35785527 | BP80: =BP79/BP30 -> 0.367652 | BQ80: =BQ79/BQ30 -> 0.35477234 | BR80: =BR79/BR30 -> -0.092848735 | BS80: =BS79/BS30 -> 0.22777879 | BT80: =BT79/BT30 -> 0.29853716 | BU80: =BU79/BU30 -> 0.27306342 | ... BW80: =BW79/BW30 -> 0.32785972
A81: OP Margin GAAP (OP/Gross Profit) | B81: - | C81: - | D81: - | E81: - | L81: =L79/L35 -> 0.37345243 | M81: =M79/M35 -> 0.41215765 | N81: =N79/N35 -> 0.45421315 | O81: =O79/O35 -> 0.44807442 | P81: =P79/P35 -> 0.42205425 | Q81: =Q79/Q35 -> 0.40522934 | R81: =R79/R35 -> 0.25951421 | S81: =S79/S35 -> 0.32410964 | ... BL81: =BL79/BL35 -> 0.34004353 | BN81: =BN79/BN35 -> 0.2817644 | BO81: =BO79/BO35 -> 0.36506782 | BP81: =BP79/BP35 -> 0.367652 | BQ81: =BQ79/BQ35 -> 0.35477234 | BR81: =BR79/BR35 -> -0.092848735 | BS81: =BS79/BS35 -> 0.22777879 | BT81: =BT79/BT35 -> 0.29853716 | BU81: =BU79/BU35 -> 0.27306342 | ... BW81: =BW79/BW35 -> 0.32785972
A82: Income (loss) from Operations (non-GAAP) | B82: =B79+B75 -> -1062.21 | C82: =C79+C75 -> -320.563 | D82: =D79+D75 -> 2.621 | E82: =E79+E75 -> -22.324 | F82: =F79+F75 -> 37.98 | G82: =G79+G75 -> 65.996 | H82: =H79+H75 -> 85.543 | I82: =I79+I75 -> 141.407 | ... BL82: =BL79+BL75 -> 2640 | BN82: =SUM(W82:Z82) -> 3156.039 | BO82: =SUM(AA82:AD82) -> 4799.266 | BP82: =BP79+BP75 -> 5671.989 | BQ82: =SUM(AI82:AL82) -> 5670 | BR82: =SUM(AM82:AP82) -> -376 | BS82: =BS79+BS75 -> 2872 | BT82: =BT79+BT75 -> 5506 | BU82: =SUM(AY82:BB82) -> 6364 | BV82: =BV79+BV75 -> 8154 | BW82: =BW79+BW75 -> 9438
A83: OP Margin non- GAAP (OP/Revenue) | C83: - | D83: - | E83: - | F83: =F82/F33 -> 0.043975588 | G83: =G82/G33 -> 0.072176313 | H83: =H82/H33 -> 0.088861072 | I83: =I82/I33 -> 0.12590742 | J83: =J82/J33 -> 0.17094186 | K83: =K82/K33 -> 0.24048045 | M83: =M82/M30 -> 0.27715505 | N83: =N82/N30 -> 0.33626656 | O83: =O82/O30 -> 0.36140922 | P83: =P82/P30 -> 0.3758023 | Q83: =Q82/Q30 -> 0.38613459 | R83: =R82/R30 -> 0.2651049 | S83: =S82/S30 -> 0.32384493 | T83: =T82/T30 -> 0.49855957 | ... BL83: =BL82/BL30 -> 0.35908596 | BN83: =BN82/BN30 -> 0.29377616 | BO83: =BO82/BO30 -> 0.37845872 | BP83: =BP82/BP30 -> 0.39043669 | BQ83: =BQ82/BQ30 -> 0.37634409 | BR83: =BR82/BR30 -> -0.055326663 | BS83: =BS82/BS30 -> 0.26209162 | BT83: =BT82/BT30 -> 0.32217671 | BU83: =BU82/BU30 -> 0.29787035 | ... BW83: =BW82/BW30 -> 0.35063343
A84: OP Margin non - GAAP (OP/Gross Profit) | B84: =B82/B35 -> -18.367485 | C84: =C82/C35 -> -1.6681307 | D84: =D82/D35 -> 0.013586928 | E84: =E82/E35 -> -0.1409646 | F84: =F82/F35 -> 0.26023502 | G84: =G82/G35 -> 0.33305241 | H84: =H82/H35 -> 0.31935355 | I84: =I82/I35 -> 0.35254887 | ... BL84: =BL82/BL35 -> 0.35908596 | BN84: =BN82/BN35 -> 0.30597511 | BO84: =BO82/BO35 -> 0.38608653 | BP84: =BP82/BP35 -> 0.39043669 | BQ84: =BQ82/BQ35 -> 0.37634409 | BR84: =BR82/BR35 -> -0.055326663 | BS84: =BS82/BS35 -> 0.26209162 | BT84: =BT82/BT35 -> 0.32217671 | BU84: =BU82/BU35 -> 0.29787035 | ... BW84: =BW82/BW35 -> 0.35063343
AK85: =AK86*1.15 -> 2854.3
A86: Adjusted EBITDA(mn)-reported | Q86: 3464.383 | R86: 531.735 | S86: 804.725 | T86: 1596.597 | U86: 789.596 | V86: 3722.653 | W86: 676.261 | X86: 867.092 | Y86: 1848.241 | Z86: 868.617 | AA86: 634.765 | AB86: 974.137 | AC86: 2187.676 | AD86: 1070.654 | AE86: 798.205 | AF86: 1312.875 | AG86: 2360.275 | AH86: 1257 | AI86: 718 | AJ86: 1373 | AK86: 2482 | AL86: 1282 | AM86: 290 | AN86: -376 | AO86: 1003 | AP86: -38 | AQ86: -195 | AR86: 48 | AS86: 2111 | AT86: 940 | AU86: 310 | AV86: 1086 | AW86: 2658 | AX86: 1241 | AY86: 586 | AZ86: 1778 | BA86: 3284 | BB86: 1464 | BC86: 898 | BD86: 1895 | BE86: 3665 | BF86: 1848 | BG86: 1088 | BH86: 2423 | BI86: 4231 | BJ86: 2195 | BK86: 1290 | BL86: 2648 | BN86: =SUM(W86:Z86) -> 4260.211 | BO86: =SUM(AA86:AD86) -> 4867.232 | BP86: =SUM(AE86:AH86) -> 5728.355 | BQ86: =SUM(AI86:AL86) -> 5855 | BR86: 879 | BS86: =SUM(AQ86:AT86) -> 2904 | BT86: =SUM(AU86:AX86) -> 5295 | BU86: 7112 | BV86: 8306 | BW86: =SUM(BG86:BJ86) -> 9937
A87: Adjusted EBITDA YoY Growth | W87: =W86/R86-1 -> 0.2718008 | X87: =X86/S86-1 -> 0.07750101 | Y87: =Y86/T86-1 -> 0.15761272 | Z87: =Z86/U86-1 -> 0.10007776 | AA87: =AA86/W86-1 -> -0.061360924 | AB87: =AB86/X86-1 -> 0.12345287 | AC87: =AC86/Y86-1 -> 0.183653 | AD87: =AD86/Z86-1 -> 0.23259618 | AE87: =AE86/AA86-1 -> 0.25748112 | AF87: =AF86/AB86-1 -> 0.34773138 | AG87: =AG86/AC86-1 -> 0.078896052 | AH87: =AH86/AD86-1 -> 0.17404876 | ... AS87: =AS86/AO86-1 -> 1.1046859 | BN87: =BN86/V86-1 -> 0.14440186 | BO87: =BO86/BN86-1 -> 0.14248614 | BP87: =BP86/BO86-1 -> 0.17692253 | BQ87: =BQ86/BP86-1 -> 0.022108441 | BR87: =BR86/BQ86-1 -> -0.8498719 | BS87: =BS86/BR86-1 -> 2.3037543 | BT87: =BT86/BS86-1 -> 0.82334711 | BU87: =BU86/BT86-1 -> 0.34315392 | BV87: =BV86/BU86-1 -> 0.16788526 | BW87: =BW86/BV86-1 -> 0.19636407
A88: Adjusted EBITDA margin | W88: =W86/W35 -> 0.33487385 | X88: =X86/X35 -> 0.35685471 | Y88: =Y86/Y35 -> 0.51496477 | Z88: =Z86/Z35 -> 0.38158139 | AA88: =AA86/AA35 -> 0.27193706 | AB88: =AB86/AB35 -> 0.330013 | AC88: =AC86/AC35 -> 0.50009132 | AD88: =AD86/AD35 -> 0.38652564 | ... BC88: =BC86/BC35 -> 0.20339751 | BD88: 0.324 | BE88: 0.458 | BF88: =BF86/BF35 -> 0.33777216 | BG88: 0.229 | BH88: 0.356 | BI88: 0.47 | BJ88: 0.346 | BK88: 0.233 | BL88: 0.36 | BN88: =BN86/BN35 -> 0.41302358 | BO88: =BO86/BO35 -> 0.39155419 | BP88: =BP86/BP35 -> 0.3943167 | BQ88: =BQ86/BQ35 -> 0.38862339 | BR88: =BR86/BR35 -> 0.12934079 | BS88: =BS86/BS35 -> 0.26501186 | BT88: =BT86/BT35 -> 0.30983031 | BU88: =BU86/BU35 -> 0.33288088 | BV88: =BV86/BV30 -> 0.34988837 | BW88: =BW86/BW30 -> 0.3691719
A89: Depreciation & Amortization | Q89: 207.82 | R89: 65.002 | S89: 67.674 | T89: 69.054 | U89: 70.764 | V89: 272.494 | W89: 72 | X89: 77.712 | Y89: 78.745 | Z89: 79.807 | AA89: 83.43 | AB89: 85.872 | AC89: 95.91 | AD89: 97.562 | AE89: 103.09 | AF89: 106.666 | AG89: 107.641 | AH89: 109 | AI89: 116 | AJ89: 119 | AK89: 117 | AL89: 117 | AM89: 117 | AN89: 112 | AO89: 115 | AP89: 114 | AQ89: 113 | AR89: 108 | AS89: 102 | AT89: =AT65 -> 98 | AU89: 111 | AV89: 107 | AW89: 109 | AX89: 124 | AY89: 120 | AZ89: 121 | BA89: 129 | BB89: 134 | BC89: 137 | BD89: 142 | BE89: =BE65 -> 155 | BF89: =BF65 -> 157 | BG89: 154 | BH89: 158 | BI89: 160 | BJ89: 151 | BK89: 131 | BL89: 129 | BN89: =SUM(W89:Z89) -> 308.264 | BO89: =SUM(AA89:AD89) -> 362.774 | BP89: =SUM(AE89:AH89) -> 426.397 | BQ89: =SUM(AI89:AL89) -> 469 | BR89: 458 | BS89: =SUM(AQ89:AT89) -> 421 | BT89: =SUM(AU89:AX89) -> 451 | BU89: 504 | BV89: 591 | BW89: 623
A91: Adjusted EBIT | Q91: =Q86-Q89 -> 3256.563 | R91: =R86-R89 -> 466.733 | S91: =S86-S89 -> 737.051 | T91: =T86-T89 -> 1527.543 | U91: =U86-U89 -> 718.832 | V91: =V86-V89 -> 3450.159 | W91: =W86-W89 -> 604.261 | X91: =X86-X89 -> 789.38 | ... BL91: =BL86-BL89 -> 2519 | BN91: =BN86-BN89 -> 3951.947 | BO91: =BO86-BO89 -> 4504.458 | BP91: =SUM(AE91:AH91) -> 5301.958 | BQ91: =SUM(AI91:AL91) -> 5386 | BR91: =SUM(AM91:AP91) -> 421 | BS91: =SUM(AQ91:AT91) -> 2483 | BT91: =SUM(AU91:AX91) -> 4844 | BU91: =SUM(AY91:BB91) -> 6608 | BV91: =SUM(BC91:BF91) -> 7715 | BW91: =SUM(BG91:BJ91) -> 9314
A92: Adjusted EBIT margin | Q92: =Q91/Q35 -> 0.42939177 | R92: =R91/R35 -> 0.27910714 | S92: =S91/S35 -> 0.35216632 | T92: =T91/T35 -> 0.51828871 | U92: =U91/U35 -> 0.38248297 | V92: =V91/V35 -> 0.40156384 | W92: =W91/W35 -> 0.29922058 | X92: =X91/X35 -> 0.32487207 | ... BL92: =BL91/BL35 -> 0.34262786 | BN92: =BN91/BN35 -> 0.38313766 | BO92: =BO91/BO35 -> 0.36237011 | BP92: =BP91/BP35 -> 0.36496526 | BQ92: =BQ91/BQ35 -> 0.35749369 | BR92: =BR91/BR35 -> 0.061948205 | BS92: =BS91/BS35 -> 0.22659244 | BT92: =BT91/BT35 -> 0.28344061 | BU92: =BU91/BU35 -> 0.3092909 | ... BW92: =BW91/BW35 -> 0.34602667
A94: Interest and dividend income | B94: 7.501 | C94: 9.687 | D94: 6.996 | E94: 1.131 | F94: 2.474 | G94: 5.112 | H94: 5.55 | I94: 11.312 | J94: 25.776 | K94: 11.66 | L94: 2 | M94: 3.9 | N94: 8 | O94: 3.86 | P94: 4.167 | Q94: 13.933 | S94: 13.037 | T94: 14.682 | U94: 16.414 | V94: 55.729 | W94: 20.347 | X94: 21.292 | Y94: 24.218 | Z94: 29.089 | AA94: 31.992 | AB94: 36.821 | AC94: 41.483 | AD94: 46.898 | AE94: 46.879 | AF94: 45.69 | AG94: 48.641 | AH94: 46 | AI94: 35 | AJ94: 34 | AK94: 44 | AL94: 39 | AM94: 32 | AN94: 12 | AO94: 5 | AP94: 5 | AQ94: 4 | AR94: 4 | AS94: 4 | AT94: 4 | AU94: 3 | AV94: 24 | AW94: 61 | AX94: 131 | AY94: 228 | AZ94: 266 | BA94: 289 | BB94: 237 | BC94: 243 | BD94: 293 | BE94: 327 | BF94: 251 | BG94: 241 | BH94: 234 | BI94: 248 | BJ94: 198 | BK94: 187 | BL94: 201 | BN94: =SUM(W94:Z94) -> 94.946 | BO94: =SUM(AA94:AD94) -> 157.194 | BP94: =SUM(AE94:AH94) -> 187.21 | BQ94: 152 | BR94: =SUM(AM94:AP94) -> 54 | BS94: =SUM(AQ94:AT94) -> 16 | BT94: =SUM(AU94:AX94) -> 219 | BU94: =SUM(AY94:BB94) -> 1020 | BV94: 1114 | BW94: 921
A95: Interest (expense) | B95: -0.381 | F95: -0.907 | G95: -3.722 | H95: -5.075 | I95: -7.06 | J95: -10.412 | K95: -34.853 | L95: -24 | M95: -30 | N95: -32 | O95: -62.064 | P95: -83.289 | Q95: -88.353 | S95: -41.547 | T95: -41.436 | U95: -43.767 | V95: -160.229 | W95: -46.894 | X95: -50.29 | Y95: -55.48 | Z95: -55.236 | AA95: -55.717 | AB95: -60.942 | AC95: -66.338 | AD95: -70.979 | AE95: -70.235 | AF95: -64.837 | AG95: -68.17 | AH95: -66 | AI95: -66 | AJ95: -68 | AK95: -70 | AL95: -62 | AM95: -64 | AN95: -96 | AO95: -98 | AP95: -98 | AQ95: -98 | AR95: -81 | AS95: -80 | AT95: -75 | AU95: -68 | AV95: -76 | AW95: -102 | AX95: -145 | AY95: -194 | AZ95: -241 | BA95: -254 | BB95: -208 | BC95: -219 | BD95: -264 | BE95: -305 | BF95: -507 | BG95: -649 | BH95: -418 | BI95: -301 | BJ95: -249 | BK95: -253 | BL95: -300 | BN95: =SUM(W95:Z95) -> -207.9 | BO95: =SUM(AA95:AD95) -> -253.976 | BP95: =SUM(AE95:AH95) -> -269.242 | BQ95: -266 | BR95: -356 | BS95: =SUM(AQ95:AT95) -> -334 | BT95: =SUM(AU95:AX95) -> -391 | BU95: =SUM(AY95:BB95) -> -897 | BV95: -1295 | BW95: -1617
A96: Other income (expense) | C96: -2.558 | D96: -0.412 | E96: 3.009 | G96: 0.015 | H96: -0.656 | I96: -0.606 | J96: -3.276 | K96: 9.824 | N96: -7.526 | O96: -9.72 | P96: -36.755 | Q96: -9.444 | S96: -1.444 | T96: -5.783 | U96: -14.017 | V96: -26.087 | W96: =-12.928-50.35 -> -63.278 | X96: 1.997 | Y96: -4.4 | Z96: -1.551 | AA96: -5.127 | AB96: -30.142 | AC96: -10.101 | AD96: -14.042 | AE96: =54.514-8.056 -> 46.458 | AF96: =21.849-15.046 -> 6.803 | AG96: =30.858-17.072 -> 13.786 | AH96: =-474-17 -> -491 | AI96: =451-8 -> 443 | AJ96: =17-23 -> -6 | AK96: =-49+68 -> 19 | AL96: =310-39 -> 271 | AM96: =-307+26 -> -281 | AN96: =835-58 -> 777 | AO96: =730-117 -> 613 | AP96: =496-5 -> 491 | AQ96: =131-4 -> 127 | AR96: =96-AR94 -> 92 | AS96: =-967-AS94 -> -971 | AT96: =43-AT94 -> 39 | AU96: =-955-AU94 -> -958 | AV96: =220-AV94 -> 196 | AW96: =-305-AW94 -> -366 | AX96: =252-AX94 -> 121 | AY96: =47-AY94 -> -181 | AZ96: -80 | BA96: 16 | BB96: =10-BB94 -> -227 | BC96: 122 | BD96: 37 | BE96: -332 | BF96: 91 | BG96: -258 | BH96: -962 | BI96: 39 | BJ96: -116 | BK96: 194 | BL96: 159 | BN96: =SUM(W96:Z96) -> -67.232 | BO96: =SUM(AA96:AD96) -> -59.412 | BP96: =-367-57 -> -424 | BQ96: =745-18 -> 727 | BR96: =1811-207-4 -> 1600 | BS96: =SUM(AQ96:AT96) -> -713 | BT96: =SUM(AU96:AX96) -> -1007 | BU96: -477 | BV96: -82 | BW96: -1297
A97: Impairment of investment | AM97: -100 | AV97: 184 | BR97: -100 | BS97: =SUM(AQ97:AT97) -> 0 | BT97: =SUM(AU97:AX97) -> 184 | BU97: =SUM(AY97:BB97) -> 0
A98: Income before income tax expense and noncontrolling interests | B98: =B79+SUM(B94:B96) -> -1055.09 | C98: =C79+SUM(C94:C96) -> -315.145 | D98: =D79+SUM(D94:D96) -> -7.303 | E98: =E79+SUM(E94:E96) -> -19.184 | F98: =F79+SUM(F94:F96) -> 9.585 | G98: =G79+SUM(G94:G96) -> 31.827 | H98: =H79+SUM(H94:H96) -> 35.703 | I98: =I79+SUM(I94:I96) -> 65.632 | ... K98: =K79+SUM(K94:K96) -> 276.105 | L98: 442.302 | M98: 746.283 | N98: 1367.794 | O98: =O79+SUM(O94:O96) -> 1761.869 | P98: =P79+SUM(P94:P96) -> 2296.537 | Q98: =Q79+SUM(Q94:Q96) -> 2989.448 | S98: =S79+SUM(S94:S96) -> 648.377 | T98: =T79+SUM(T94:T96) -> 1456.17 | U98: =U79+SUM(U94:U96) -> 616.533 | V98: =V79+SUM(V94:V96) -> 3128.32 | W98: =W79+SUM(W94:W96) -> 460.493 | X98: =X79+SUM(X94:X96) -> 705.406 | Y98: =Y79+SUM(Y94:Y96) -> 797.565 | Z98: =Z79+SUM(Z94:Z96) -> 762.663 | ... AL98: =AL79+SUM(AL94:AL96) -> 1420 | AM98: =AM79+SUM(AM94:AM97) -> -722 | AN98: =AN79+SUM(AN94:AN97) -> 209 | AO98: =AO79+SUM(AO94:AO97) -> 835 | AP98: =AP79+SUM(AP94:AP97) -> 245 | AQ98: =AQ79+SUM(AQ94:AQ97) -> -278 | AR98: =AR79+SUM(AR94:AR97) -> -41 | AS98: =AS79+SUM(AS94:AS97) -> 968 | AT98: =AT79+SUM(AT94:AT97) -> 816 | AU98: =AU79+SUM(AU94:AU97) -> -849 | AV98: =AV79+SUM(AV94:AV96) -> 1144 | AW98: =AW79+SUM(AW94:AW96) -> 2176 | AX98: =AX79+SUM(AX94:AX96) -> 1452 | AY98: =AY79+SUM(AY94:AY96) -> 302 | AZ98: =AZ79+SUM(AZ94:AZ96) -> 1618 | BA98: =BA79+SUM(BA94:BA96) -> 3154 | BB98: =BB79+SUM(BB94:BB96) -> 411 | BC98: =BC79+SUM(BC94:BC96) -> 937 | ... BQ98: =BQ79+SUM(BQ94:BQ96) -> 5958 | BR98: =BR79+SUM(BR94:BR97) -> 567 | BS98: =BS79+SUM(BS94:BS97) -> 1465 | BT98: =BT79+SUM(BT94:BT97) -> 4107 | BU98: =BU79+SUM(BU94:BU97) -> 5480 | BV98: =BV79+SUM(BV94:BV97) -> 7292 | BW98: =BW79+SUM(BW94:BW97) -> 6832
A99: Income tax (expense) benefit | G99: 0.193 | H99: 156.277 | I99: 12.388 | J99: 12.059 | K99: -90.171 | L99: 47.168 | M99: -218.141 | N99: -308.663 | O99: -337.832 | P99: -403.739 | Q99: -567.695 | S99: -131.345 | T99: -259.438 | U99: -112.261 | V99: -576.96 | W99: -86.069 | X99: -111.91 | Y99: -291.517 | Z99: -88.755 | AA99: -71.987 | AB99: -142.908 | AC99: -346.454 | AD99: -1496.208 | AE99: -146.127 | AF99: -231.539 | AG99: -473.268 | AH99: 14 | AI99: -203 | AJ99: -228 | AK99: -413 | AL99: -249 | AM99: 23 | AN99: -87 | AO99: -34 | AP99: -410 | AQ99: 223 | AR99: -126 | AS99: -199 | AT99: -198 | AU99: 149 | AV99: -287 | AW99: -510 | AX99: -217 | AY99: -37 | AZ99: -328 | BA99: -638 | BB99: -189 | BC99: -161 | BD99: -401 | BE99: -352 | BF99: -496 | BG99: -63 | BH99: -209 | BI99: -721 | BJ99: -435 | BK99: -316 | BL99: -610 | BN99: =SUM(W99:Z99) -> -578.251 | BO99: =SUM(AA99:AD99) -> -2057.557 | BP99: =SUM(AE99:AH99) -> -836.934 | BQ99: -1093 | BR99: -508 | BS99: -300 | BT99: =SUM(AU99:AX99) -> -865 | BU99: =SUM(AV99:AY99) -> -1051 | BV99: =SUM(BC99:BF99) -> -1410 | BW99: =SUM(BG99:BJ99) -> -1428
A100: Equity in loss (gain) of affiliates | F100: 2.331 | G100: -0.511 | H100: 0.749 | I100: -3.554 | J100: -5 | K100: -3.688 | L100: 0.002 | M100: - | N100: - | O100: - | P100: -
A101: Income from continuing operations | B101: =SUM(B98:B100) -> -1055.09 | C101: =SUM(C98:C100) -> -315.145 | D101: =SUM(D98:D100) -> -7.303 | E101: =SUM(E98:E100) -> -19.184 | F101: =SUM(F98:F100) -> 11.916 | G101: =SUM(G98:G100) -> 31.509 | H101: =SUM(H98:H100) -> 192.729 | I101: =SUM(I98:I100) -> 74.466 | ... K101: =SUM(K98:K100) -> 182.246
A102: Discontinued operations, net of taxes
A103: Less: Noncontrolling interests | L103: - | M103: -0.601 | N103: -2.76 | O103: -4.471 | P103: 0.135 | Q103: - | V103: -
A104: Net income (GAAP) | B104: =SUM(B101:B102) -> -1055.09 | C104: =SUM(C101:C102) -> -315.145 | D104: =SUM(D101:D102) -> -7.303 | E104: =SUM(E101:E102) -> -19.184 | F104: 11.916 | G104: 31.509 | H104: =SUM(H101:H102) -> 192.729 | I104: =SUM(I101:I102) -> 74.466 | J104: =SUM(J101:J102) -> 157.082 | K104: =SUM(K101:K102) -> 182.246 | L104: 489.472 | M104: 528.142 | N104: 1056 | O104: 1419.566 | P104: 1892.798 | Q104: 2551.36 | S104: 517.032 | T104: 1196.732 | U104: 504.269 | V104: 2421.753 | W104: 374.424 | X104: 580.638 | Y104: 506.017 | Z104: 673.908 | AA104: 455.623 | AB104: 720.209 | AC104: 1720.391 | AD104: -555.458 | AE104: 607.21 | AF104: 977.372 | AG104: 1767.488 | AH104: 646 | AI104: 765 | AJ104: 979 | AK104: 1950 | AL104: 1171 | AM104: -699 | AN104: 122 | AO104: 801 | AP104: =BR104-SUM(AM104:AO104) -> -165 | AQ104: -55 | AR104: -167 | AS104: 769 | AT104: 618 | AU104: -700 | AV104: 857 | AW104: 1666 | AX104: 1235 | AY104: 266 | AZ104: 1290 | BA104: 2511 | BB104: 222 | BC104: 776 | BD104: 1521 | BE104: 2517 | BF104: 1068 | BG104: 333 | BH104: 895 | BI104: 2748 | BJ104: 1428 | BK104: 1083 | BL104: 1950 | BN104: =BN98+BN99 -> 2147.876 | BO104: =BO98+BO99 -> 2324.241 | BP104: =BP98+BP99 -> 3998.023 | BQ104: 4865 | BR104: =BR98+BR99 -> 59 | BS104: =BS98+BS99 -> 1165 | BT104: =BT98+BT99 -> 3242 | BU104: =BU98+BU99 -> 4429 | BV104: 5882 | BW104: 5404
A105: check | W105: =W98+W99-W104 -> 0 | X105: =X98+X99-X104 -> 12.858 | Y105: =Y98+Y99-Y104 -> 0.031 | Z105: =Z98+Z99-Z104 -> 0 | AA105: =AA98+AA99-AA104 -> 0 | AB105: =AB98+AB99-AB104 -> -24.121 | AC105: =AC98+AC99-AC104 -> 0 | AD105: =AD98+AD99-AD104 -> 7.597 | ... BL105: =BL98+BL99-BL104 -> 0 | BN105: =BN98+BN99-BN104 -> 0 | BO105: =BO98+BO99-BO104 -> 0 | BP105: =BP98+BP99-BP104 -> 0 | BQ105: =BQ98+BQ99-BQ104 -> 0 | BR105: =BR98+BR99-BR104 -> 0 | BS105: =BS98+BS99-BS104 -> 0 | BT105: =BT98+BT99-BT104 -> 0 | BU105: =BU98+BU99-BU104 -> 0 | ... BW105: =BW98+BW99-BW104 -> 0
A106: Preferred stock dividend | C106: -14.382 | D106: -8.563 | E106: -2.344 | F106: -1.491 | G106: -1.512 | H106: -1.854 | I106: -1.927 | J106: -1.854
A107: Accretion on preferred stock | B107: -8.354
A108: Net profit margin GAAP (/ Revenue) | B108: - | C108: - | D108: - | E108: - | F108: =#REF!/F33 -> #REF! | G108: =#REF!/G33 -> #REF! | H108: =#REF!/H33 -> #REF! | I108: =#REF!/I33 -> #REF! | J108: =#REF!/J33 -> #REF! | K108: =#REF!/K33 -> #REF! | L108: =L104/L30 -> 0.20933602 | M108: =M104/M30 -> 0.17120203 | N108: =N104/N30 -> 0.24244595 | O108: =O104/O30 -> 0.26983043 | P108: =P104/P30 -> 0.27862693 | Q108: =Q104/Q30 -> 0.30222326 | S108: =S104/S30 -> 0.22672894 | T108: =T104/T30 -> 0.38568166 | U108: =U104/U30 -> 0.25213513 | V108: =V104/V30 -> 0.26254948 | W108: =W104/W30 -> 0.17430319 | X108: =X104/X30 -> 0.22717538 | Y108: =Y104/Y30 -> 0.13711147 | Z108: =Z104/Z30 -> 0.28696071 | ... BL108: =BL104/BL30 -> 0.26523395 | BN108: =BN104/BN30 -> 0.1999325 | BO108: =BO104/BO30 -> 0.18328412 | BP108: =BP104/BP30 -> 0.27520767 | BQ108: =BQ104/BQ30 -> 0.32291252 | BR108: =BR104/BR30 -> 0.0086815774 | BS108: =BS104/BS30 -> 0.10631502 | BT108: =BT104/BT30 -> 0.18970158 | BU108: =BU104/BU30 -> 0.20730166 | ... BW108: =BW104/BW30 -> 0.20076532
...

Sheet BKNG Quarterly Charts

Sheet Sheet6
A1: (in million, USD) | H1: Priceline | I1: Priceline | J1: Priceline | K1: Priceline
B2: 2010 | C2: 2011 | D2: 2012 | E2: 2013 | F2: 2014 | G2: 2015 | H2: 2016 | I2: 2017 | J2: 2018 | K2: 2019
A3: Gross Booking | B3: 13646 | C3: 21658 | D3: =6712+7329+7831+6584 -> 28456 | E3: =9153+10118+10765+9138 -> 39174 | F3: =12280+13538+13823+10659 -> 50300 | G3: =13775+14960+14778+12015 -> 55528 | H3: 68087 | I3: 81226 | J3: 92731 | K3: 96443
A5: Advertising (Online+Offline) | B5: =552.14+35.714 -> 587.854 | C5: =919.214+35.47 -> 954.684 | D5: =1273.537+35.492 -> 1309.029 | E5: =1798.645+127.459 -> 1926.104 | F5: =2360.211+231.309 -> 2591.52 | G5: =2797.237+214.685 -> 3011.922 | H5: 3479.287 | I5: 4161 | J5: 4447 | K5: 4419
A6: Sales and marketing | B6: 116.303 | C6: 162.69 | D6: 195.934 | E6: 235.817 | F6: 310.91 | G6: 353.221 | H6: 295.698 | I6: 435 | J6: 509 | K6: 548
H7: 435.225 | I7: 517 | J7: 830 | K7: 955
A8: Gross Booking per Marketing Dollar | B8: =B3/(B6+B5) -> 19.379201 | C8: =C3/(C6+C5) -> 19.382946 | D8: =D3/(D6+D5) -> 18.908106 | E8: =E3/(E6+E5) -> 18.119996 | F8: =F3/(F6+F5) -> 17.330306 | G8: =G3/(G6+G5) -> 16.500933 | H8: =H3/SUM(H5:H7) -> 16.171877 | I8: =I3/SUM(I5:I7) -> 15.886173 | J8: =J3/SUM(J5:J7) -> 16.026789 | K8: =K3/SUM(K5:K7) -> 16.285545
A9: Incremental | C9: =(C3-B3)/(SUM(C5:C7)-SUM(B5:B7)) -> 19.389328 | D9: =(D3-C3)/(SUM(D5:D7)-SUM(C5:C7)) -> 17.539197 | E9: =(E3-D3)/(SUM(E5:E7)-SUM(D5:D7)) -> 16.314589 | F9: =(F3-E3)/(SUM(F5:F7)-SUM(E5:E7)) -> 15.024801 | G9: =(G3-F3)/(SUM(G5:G7)-SUM(F5:F7)) -> 11.29858 | H9: =(H3-G3)/(SUM(H5:H7)-SUM(G5:G7)) -> 14.861544 | I9: =(I3-H3)/(SUM(I5:I7)-SUM(H5:H7)) -> 14.553772 | J9: =(J3-I3)/(SUM(J5:J7)-SUM(I5:I7)) -> 17.095097 | K9: =(K3-J3)/(SUM(K5:K7)-SUM(J5:J7)) -> 27.294118
C11: =1/C8 -> 0.051591744 | K11: =1/K8 -> 0.061404145 | L11: =K11/C11-1 -> 0.19019324
A14: Total Revenue | D14: 5260.965 | E14: 6793.306 | F14: 8441.971 | G14: 9223.987 | H14: 10743.006 | I14: 12681.082 | J14: 14527.295 | K14: 15066
A15: Advertising & Other revenues | D15: 13.389 | E15: 171.143 | F15: 410.115 | G15: 613.116 | H15: 712.885 | I15: 833.939 | J15: 1060.887 | K15: 1119
A16: Advertising&media YoY growth | E16: =E15/D15-1 -> 11.782359 | F16: =F15/E15-1 -> 1.3963294 | G16: =G15/F15-1 -> 0.49498555 | H16: =H15/G15-1 -> 0.16272451 | I16: =I15/H15-1 -> 0.16980859 | J16: =J15/I15-1 -> 0.27213981 | K16: =K15/J15-1 -> 0.054777747
A17: Advertising&media % | E17: =E15/E14 -> 0.025192888 | F17: =F15/F14 -> 0.04858048 | G17: =G15/G14 -> 0.066469738 | H17: =H15/H14 -> 0.066358057 | I17: =I15/I14 -> 0.065762448 | J17: =J15/J14 -> 0.073027153 | K17: =K15/K14 -> 0.074273198

Sheet EXPE
A1: (in million, USD, except EPS data) | F1: ended Mar.31 | G1: ended Mar.31 | H1: ended Mar.31 | I1: ended Mar.31 | J1: ended Mar.31 | K1: ended Mar.31 | L1: ended Mar.31 | T1: exc. tripadv | U1: exc. tripadv | V1: exc. tripadv | X1: exc. tripadv | Y1: exc. tripadv | Z1: exc. tripadv | AA1: exc. tripadv | AB1: exc. tripadv | AD1: excl. eLong | AE1: excl. eLong | AF1: excl. eLong | AG1: excl. eLong | AH1: exc. eLong | AI1: excl. eLong | AJ1: excl. eLong | AL1: Consolidated AWAY room nights and gross bookings since 17Q1
A2: P&L | B2: eLong | C2: eLong | D2: eLong | E2: eLong | F2: MakeMyTrip | G2: 2024E | H2: MakeMyTrip | I2: MakeMyTrip | J2: MakeMyTrip | K2: MakeMyTrip | L2: MakeMyTrip | M2: Expedia | N2: Expedia | O2: Expedia | P2: Expedia | Q2: Expedia | R2: Expedia | S2: Expedia | T2: Expedia | U2: Expedia | V2: Expedia | W2: Expedia | X2: Expedia | Y2: Expedia | Z2: Expedia | AA2: Expedia | AB2: Expedia | AC2: Expedia | AD2: Expedia | AE2: Expedia | AF2: Expedia | AG2: Expedia | AH2: Expedia | AI2: Expedia | AJ2: Expedia | AK2: Expedia | AL2: Expedia | AM2: Expedia | AN2: Expedia | AO2: Expedia | AP2: Expedia | AQ2: Expedia | AR2: Expedia | AS2: Expedia | AT2: Expedia | AU2: Expedia | AV2: Expedia | AW2: Expedia | AX2: Expedia | AY2: Expedia | AZ2: Expedia | BA2: Expedia | BB2: Expedia | BC2: Expedia | BD2: Expedia | BE2: Expedia | BF2: Expedia | BG2: Expedia | BH2: Expedia | BI2: Expedia | BJ2: Expedia | BK2: Expedia | BL2: Expedia | BM2: Expedia | BN2: Expedia | BO2: Expedia | BP2: Expedia | BQ2: Expedia | BR2: Expedia | BS2: Expedia | BT2: Expedia | BU2: Expedia | BV2: Expedia | BW2: Expedia | BY2: Expedia | BZ2: Expedia | CA2: Expedia | CB2: Expedia | CC2: Expedia | CD2: Expedia | CE2: Expedia | CF2: Expedia | CG2: Expedia | CH2: Expedia
A3: (in million, USD, except EPS data) | B3: 2009 | C3: 2010 | D3: 2011 | E3: 2012 | F3: 2009 | G3: 2010 | H3: 2011 | I3: 2012 | J3: 2013 | K3: 2014 | L3: 2015 | M3: 1999 | N3: 2000 | O3: 2001 | P3: 2002 | Q3: 2003 | R3: 2004 | S3: 2005 | T3: 2006 | U3: 2007 | V3: 2008 | W3: 2009 | X3: 2010 | Y3: 2011 | Z3: 2012 | AA3: 2013 | AB3: 2014 | AC3: 2015Q1 | AD3: 2015Q2 | AE3: 2015Q3 | AF3: 2015Q4 | AG3: 2015 | AH3: 2016Q1 | AI3: 2016Q2 | AJ3: 2016Q3 | AK3: 2016Q4 | AL3: 2017Q1 | AM3: 2017Q2 | AN3: 2017Q3 | AO3: 2017Q4 | AP3: 2018Q1 | AQ3: 2018Q2 | AR3: 2018Q3 | AS3: 2018Q4 | AT3: 2019Q1 | AU3: 2019Q2 | AV3: 2019Q3 | AW3: 2019Q4 | AX3: 2020Q1 | AY3: 2020Q2 | AZ3: 2020Q3 | BA3: 2020Q4 | BB3: 2021Q1 | BC3: 2021Q2 | BD3: 2021Q3 | BE3: 2021Q4 | BF3: 2022Q1 | BG3: 2022Q2 | BH3: 2022Q3 | BI3: 2022Q4 | BJ3: 2023Q1 | BK3: 2023Q2 | BL3: 2023Q3 | BM3: 2023Q4 | BN3: 2024Q1 | BO3: 2024Q2 | BP3: 2024Q3 | BQ3: 2024Q4 | BR3: 2025Q1 | BS3: 2025Q2 | BT3: 2025Q3 | BU3: 2025Q4 | BV3: 2026Q1 | BW3: 2026Q2 | BY3: 2016 | BZ3: 2017 | CA3: 2018 | CB3: 2019 | CC3: 2020 | CD3: 2021 | CE3: 2022 | CF3: 2023 | CG3: 2024 | CH3: 2025
A4: Transaction volume | B4: - | C4: - | D4: - | E4: - | F4: - | G4: - | H4: - | W4: 57.8 | X4: 65.6 | Y4: 72.8
A5: Gross booking value(mn) | B5: - | C5: - | D5: - | E5: - | F5: =(260945.1+52365.7)/1000 -> 313.3108 | G5: =(408603.1+57273.1)/1000 -> 465.8762 | H5: =(647846.9+94608.2)/1000 -> 742.4551 | I5: 992.9575 | J5: 1169.5586 | W5: 21811.1 | X5: 25965.4 | Y5: 29181.4 | Z5: 33959 | AA5: 39443 | AB5: 50447 | AC5: 14986 | AD5: 15063 | AE5: 15393 | AF5: 14950 | AG5: 59680 | AH5: 18882 | AI5: 18860.8 | AJ5: 18585 | AK5: 16104 | AL5: 23610.3 | AM5: 22837.7 | AN5: 22196.5 | AO5: 19765.9 | AP5: 27196 | AQ5: 25898 | AR5: 24676 | AS5: 21957 | AT5: 29409 | AU5: 28292 | AV5: 26927 | AW5: 23245 | AX5: 17885 | AY5: 2713 | AZ5: 8631 | BA5: 7567 | BB5: 15422 | BC5: 20815 | BD5: 18725 | BE5: 17463 | BF5: 24412 | BG5: 26139 | BH5: 23987 | BI5: 20511 | BJ5: 29401 | BK5: 27321 | BL5: 25685 | BM5: 21672 | BN5: 30164 | BO5: 28837 | BP5: 27498 | BQ5: 24422 | BR5: 31451 | BS5: 30409 | BT5: 30727 | BU5: 27003 | BV5: 35530 | BW5: 33928 | BY5: 72431 | BZ5: 88410.5 | CA5: =SUM(AP5:AS5) -> 99727 | CB5: 107873 | CC5: 36796 | CD5: 72425 | CE5: =SUM(BF5:BI5) -> 95049 | CF5: 104079 | CG5: 110921 | CH5: 119590
A6: Gross booking value YoY Growth on a non-constant currency basis | AB6: 0.28 | AC6: 0.19 | AD6: 0.2 | AE6: 0.21 | AF6: 0.4 | AG6: 0.24 | AH6: 0.32 | AI6: 0.25 | AJ6: 0.21 | AK6: 0.08 | AL6: 0.14 | AM6: 0.12 | AN6: 0.11 | AO6: 0.14 | AP6: 0.11 | AQ6: 0.13 | AR6: 0.11 | AS6: 0.11 | AT6: 0.08 | AU6: 0.09 | AV6: 0.09 | AW6: 0.06 | AX6: -0.39 | AY6: -0.9 | AZ6: -0.68 | BA6: -0.67 | BB6: -0.14 | BC6: 6.67 | BD6: 1.17 | BE6: 1.31 | BF6: 0.58 | BG6: 0.26 | BH6: 0.28 | BI6: 0.17 | BJ6: 0.2 | BK6: 0.05 | BL6: 0.07 | BM6: 0.06 | BN6: =BN5/BJ5-1 -> 0.025951498 | BO6: =BO5/BK5-1 -> 0.055488452 | BP6: =BP5/BL5-1 -> 0.070585945 | BQ6: =BQ5/BM5-1 -> 0.12689184 | BR6: =BR5/BN5-1 -> 0.042666755 | BS6: =BS5/BO5-1 -> 0.054513299 | BT6: =BT5/BP5-1 -> 0.11742672 | BU6: =BU5/BQ5-1 -> 0.1056834 | ... BW6: =BW5/BS5-1 -> 0.11572232 | BY6: 0.21 | BZ6: 0.13 | CA6: 0.13 | CB6: 0.11 | CC6: -0.66 | CD6: 0.97 | CE6: =CE5/CD5-1 -> 0.31237832 | CF6: 0.1 | CG6: =CG5/CF5-1 -> 0.065738526 | CH6: =CH5/CG5-1 -> 0.078154723
A7: Gross booking value YoY Growth on a constant currency basis | Y7: 0.1 | Z7: 0.18 | AA7: 0.16 | AB7: 0.29 | AC7: 0.25 | AD7: 0.28 | AE7: 0.26 | AF7: 0.46 | AG7: 0.3 | AH7: 0.34 | AI7: 0.26 | AJ7: 0.21 | AK7: 0.09 | AL7: 0.15 | AM7: 0.13 | AN7: 0.1 | AO7: 0.12 | AP7: 0.15 | AQ7: 0.11 | AR7: 0.12 | AS7: 0.13 | AT7: 0.11 | AU7: 0.11 | AV7: 0.1 | AW7: 0.06 | AX7: -0.39 | AY7: -0.9 | AZ7: -0.68 | BA7: -0.67 | BB7: -0.14 | BC7: 6.67 | BD7: 1.17 | BE7: 1.31 | BF7: 0.58 | BG7: 0.26 | BH7: 0.28 | BI7: 0.17 | BJ7: 0.2 | BK7: 0.05 | BL7: 0.07 | BM7: 0.06 | BN7: 0.03 | BO7: 0.06 | BP7: 0.07 | BQ7: 0.13 | BR7: 0.04 | BS7: 0.05 | BT7: =BT6 -> 0.11742672 | BU7: =BU6 -> 0.1056834 | BV7: =BV6 -> 0.12969381 | BW7: =BW6 -> 0.11572232 | BY7: 0.22 | BZ7: 0.13 | CA7: 0.12 | CB7: 0.11 | CC7: -0.66 | CD7: 0.97 | CE7: 0.31 | CF7: 0.1 | CG7: 0.07 | CH7: 0.07
A8: Growth vs.2019 | BB8: =BB5/AT5-1 -> -0.47560271 | BC8: =BC5/AU5-1 -> -0.26427966 | BD8: =BD5/AV5-1 -> -0.30460133 | BE8: =BE5/AW5-1 -> -0.24874166 | BF8: =BF5/AT5-1 -> -0.16991397 | BG8: =BG5/AU5-1 -> -0.076099251 | BH8: =BH5/AV5-1 -> -0.10918409 | BI8: =BI5/AW5-1 -> -0.11761669 | BJ8: =BJ5/AT5-1 -> -0.00027202557 | BK8: =BK5/AU5-1 -> -0.034320656 | BL8: =BL5/AV5-1 -> -0.046124708 | BM8: =BM5/AW5-1 -> -0.067670467 | BN8: =BN5/AT5-1 -> 0.025672413 | BO8: =BO5/AU5-1 -> 0.019263396 | BP8: =BP5/AV5-1 -> 0.021205481 | BQ8: =BQ5/AW5-1 -> 0.050634545 | BR8: =BR5/AT5-1 -> 0.069434527 | BS8: =BS5/AU5-1 -> 0.074826806 | BT8: =BT5/AV5-1 -> 0.14112229 | BU8: =BU5/AW5-1 -> 0.16166918 | BV8: =BV5/AT5-1 -> 0.20813356 | BW8: =BW5/AU5-1 -> 0.19920826 | CC8: =CC5/CB5-1 -> -0.65889518 | CD8: =CD5/CB5-1 -> -0.32860864 | CE8: =CE5/CB5-1 -> -0.11888054 | CF8: =CF5/CB5-1 -> -0.035170988 | CG8: =CG5/CB5-1 -> 0.028255449 | CH8: =CH5/CB5-1 -> 0.10861847
A10: Revenue / Gross booking ratio | B10: - | C10: - | D10: - | E10: - | F10: =F59/F5 -> 0.21879776 | G10: =G59/G5 -> 0.1793614 | H10: =H59/H5 -> 0.16798509 | I10: =I59/I5 -> 0.19799363 | J10: =J59/J5 -> 0.19564808 | W10: =W59/W5 -> 0.13550101 | X10: =X59/X5 -> 0.11683413 | Y10: =Y59/Y5 -> 0.11819203 | Z10: =Z59/Z5 -> 0.11868274 | AA10: =AA59/AA5 -> 0.12095936 | AB10: =AB59/AB5 -> 0.11424832 | AD10: =AD59/AD5 -> 0.11037642 | AE10: =AE59/AE5 -> 0.12588534 | AF10: =AF59/AF5 -> 0.11361652 | AG10: =AG59/AG5 -> 0.11110925 | AH10: =AH59/AH5 -> 0.10083471 | AI10: =AI59/AI5 -> 0.11642502 | AJ10: =AJ59/AJ5 -> 0.13887033 | AK10: =AK59/AK5 -> 0.12996771 | ... AN10: =AN59/AN5 -> 0.13362467 | AO10: 0.11732327 | AP10: =AP59/AP5 -> 0.092219444 | AQ10: =AQ59/AQ5 -> 0.1112055 | AR10: =AR59/AR5 -> 0.13276058 | AS10: =AS59/AS5 -> 0.11654598 | AT10: =AT59/AT5 -> 0.088714339 | AU10: =AU59/AU5 -> 0.11144493 | AV10: =AV59/AV5 -> 0.13213503 | AW10: =AW59/AW5 -> 0.11817595 | ... BM10: =BM59/BM5 -> 0.13321336 | BO10: =BO59/BO5 -> 0.12338315 | BP10: =BP59/BP5 -> 0.1476471 | BQ10: =BQ59/BQ5 -> 0.13037425 | BR10: =BR59/BR5 -> 0.095004928 | BS10: =BS59/BS5 -> 0.12450261 | BT10: =BT59/BT5 -> 0.14358707 | BU10: =BU59/BU5 -> 0.13135578 | BV10: =BV59/BV5 -> 0.096425556 | BW10: =BW59/BW5 -> 0.12718109 | BY10: =BY59/BY5 -> 0.12113232 | BZ10: 0.11378513 | CA10: =CA59/CA5 -> 0.11253723 | CB10: =CB59/CB5 -> 0.11186302 | CC10: =CC59/CC5 -> 0.14129253 | CD10: =CD59/CD5 -> 0.11871591 | CE10: =CE59/CE5 -> 0.12274721 | CF10: =CF59/CF5 -> 0.12335822 | CG10: =CG59/CG5 -> 0.12343019 | CH10: =CH59/CH5 -> 0.12319592
A11: Gross profit / Gross booking ratio | F11: =F143/F5 -> 0.079763293 | G11: =G143/G5 -> 0.086466117 | H11: =H143/H5 -> 0.082254788 | I11: =I143/I5 -> 0.088810361 | W11: =W143/W5 -> 0.10765963 | X11: =X143/X5 -> 0.090434116 | Y11: =Y143/Y5 -> 0.092104457 | Z11: =Z143/Z5 -> 0.092221296 | AA11: =AA143/AA5 -> 0.094642902 | AB11: =AB143/AB5 -> 0.090875652 | AD11: =AD143/AD5 -> 0.089060479 | AE11: =AE143/AE5 -> 0.10457266 | AF11: =AF143/AF5 -> 0.090974849 | AG11: =AG143/AG5 -> 0.089858546 | AH11: =AH143/AH5 -> 0.079514405 | AI11: =AI143/AI5 -> 0.094878743 | AJ11: =AJ143/AJ5 -> 0.11643788 | AK11: =AK143/AK5 -> 0.10693983 | ... AN11: =AN143/AN5 -> 0.1129656 | AO11: 0.095214486 | AP11: =AP143/AP5 -> 0.074312399 | AQ11: =AQ143/AQ5 -> 0.091976214 | AR11: =AR143/AR5 -> 0.11233587 | AS11: =AS143/AS5 -> 0.094867241 | AT11: =AT143/AT5 -> 0.072052773 | AU11: =AU143/AU5 -> 0.093772091 | AV11: =AV143/AV5 -> 0.11178371 | AW11: =AW143/AW5 -> 0.094988169 | ... BM11: =BM143/BM5 -> 0.11752492 | BO11: =BO143/BO5 -> 0.11082984 | BP11: =BP143/BP5 -> 0.13353698 | BQ11: =BQ143/BQ5 -> 0.11665711 | BR11: =BR143/BR5 -> 0.083653938 | BS11: =BS143/BS5 -> 0.11210497 | BT11: =BT143/BT5 -> 0.13135028 | BU11: =BU143/BU5 -> 0.11869052 | BV11: =BV143/BV5 -> 0.085814804 | BW11: =BW143/BW5 -> 0.11530299 | BY11: =BY143/BY5 -> 0.099087918 | BZ11: 0.093922634 | CA11: =CA143/CA5 -> 0.092833435 | CB11: =CB143/CB5 -> 0.091811667 | CC11: =CC143/CC5 -> 0.095635395 | CD11: =CD143/CD5 -> 0.09770107 | CE11: =CE143/CE5 -> 0.1053141 | CF11: =CF143/CF5 -> 0.1082447 | CG11: =CG143/CG5 -> 0.11042093 | CH11: =CH143/CH5 -> 0.11102099
I12: =
A13: Gross booking breakdown by geography
A14: US | AC14: 8887 | AD14: 9301 | AE14: 9584 | AF14: 9616 | AG14: 37388 | AH14: 12288 | AI14: 12179 | AJ14: 11793 | AK14: 10050 | AL14: 15128 | AM14: 14730 | AN14: 13540 | AO14: 11800 | AP14: 16582 | AQ14: 16213 | AR14: 15232 | AS14: 13362 | AT14: 18363 | AU14: 17962 | AV14: 16793 | AW14: 14315 | BY14: 51053 | BZ14: 55198 | CA14: =SUM(AP14:AS14) -> 61389 | CB14: 67433
A15: US YoY growth | AH15: =AH14/AC14-1 -> 0.38269382 | AI15: =AI14/AD14-1 -> 0.30942909 | AJ15: =AJ14/AE14-1 -> 0.23048831 | AK15: =AK14/AF14-1 -> 0.045133111 | AL15: 0.10069849 | AM15: 0.10585586 | AN15: 0.048393341 | AO15: 0.065558967 | AP15: =AP14/AL14-1 -> 0.096113168 | AQ15: =AQ14/AM14-1 -> 0.10067889 | AR15: =AR14/AN14-1 -> 0.12496307 | AS15: =AS14/AO14-1 -> 0.13237288 | AT15: =AT14/AP14-1 -> 0.10740562 | AU15: =AU14/AQ14-1 -> 0.1078764 | AV15: =AV14/AR14-1 -> 0.10248162 | AW15: =AW14/AS14-1 -> 0.071321658 | BY15: =BY14/AG14-1 -> 0.3654916 | BZ15: =BZ14/BY14-1 -> 0.081190136 | CA15: =CA14/BZ14-1 -> 0.11215986 | CB15: =CB14/CA14-1 -> 0.09845412
A16: US contribution | AH16: =AH14/AH5 -> 0.65077852 | AI16: =AI14/AI5 -> 0.64573083 | AJ16: =AJ14/AJ5 -> 0.63454399 | AK16: =AK14/AK5 -> 0.62406855 | AL16: =AL14/AL5 -> 0.64073731 | AM16: =AM14/AM5 -> 0.64498614 | AN16: =AN14/AN5 -> 0.61000608 | AO16: =AO14/AO5 -> 0.59698774 | ... AW16: =AW14/AW5 -> 0.61583136 | BY16: =BY14/BY5 -> 0.70485013 | BZ16: =BZ14/BZ5 -> 0.62433761 | CA16: =CA14/CA5 -> 0.61557051 | CB16: =CB14/CB5 -> 0.62511472
A17: International | AC17: 6098 | AD17: 5762 | AE17: 5809 | AF17: 5335 | AG17: 22292 | AH17: 6594 | AI17: 6682 | AJ17: 6793 | AK17: 6054 | AL17: 8483 | AM17: 8108 | AN17: 8657 | AO17: 7966 | AP17: 10614 | AQ17: 9685 | AR17: 9444 | AS17: 8595 | AT17: 11046 | AU17: 10330 | AV17: 10134 | AW17: 8930 | BY17: 27358 | BZ17: 7966 | CA17: =SUM(AP17:AS17) -> 38338 | CB17: 40440
A18: Int'l YoY growth | AH18: =AH17/AC17-1 -> 0.081338144 | AI18: =AI17/AD17-1 -> 0.15966678 | AJ18: =AJ17/AE17-1 -> 0.16939232 | AK18: =AK17/AF17-1 -> 0.13477038 | AL18: 0.21969806 | AM18: 0.15812027 | AN18: 0.22395023 | AO18: 0.25865066 | AP18: =AP17/AL17-1 -> 0.2512083 | AQ18: =AQ17/AM17-1 -> 0.19449926 | AR18: =AR17/AN17-1 -> 0.090909091 | AS18: =AS17/AO17-1 -> 0.078960582 | AT18: =AT17/AP17-1 -> 0.040700961 | AU18: =AU17/AQ17-1 -> 0.066597832 | AV18: =AV17/AR17-1 -> 0.073062262 | AW18: =AW17/AS17-1 -> 0.038976149 | BY18: =BY17/AG17-1 -> 0.22725641 | BZ18: =BZ17/BY17-1 -> -0.70882374 | CA18: =CA17/BZ17-1 -> 3.812704 | CB18: =CB17/CA17-1 -> 0.054828108
A19: Int'l contribution | AH19: =AH17/AH5 -> 0.34922148 | AI19: =AI17/AI5 -> 0.35427978 | AJ19: =AJ17/AJ5 -> 0.36550982 | AK19: =AK17/AK5 -> 0.37593145 | AL19: =AL17/AL5 -> 0.35929234 | AM19: =AM17/AM5 -> 0.35502699 | AN19: =AN17/AN5 -> 0.39001644 | AO19: =AO17/AO5 -> 0.40301732 | ... AW19: =AW17/AW5 -> 0.38416864 | BY19: =BY17/BY5 -> 0.3777112 | BZ19: =BZ17/BZ5 -> 0.09010242 | CA19: =CA17/CA5 -> 0.38442949 | CB19: =CB17/CB5 -> 0.37488528
A21: Gross booking breakdown by business model | AH21: =SUM(AH24,AH27,AH30) -> 1 | AI21: =SUM(AI24,AI27,AI30) -> 1.0000106 | AJ21: =SUM(AJ24,AJ27,AJ30) -> 1.0000538 | AK21: =SUM(AK24,AK27,AK30) -> 1 | AL21: =SUM(AL24,AL27,AL30) -> 1.0000296 | AM21: =SUM(AM24,AM27,AM30) -> 0.99996935 | AN21: =SUM(AN24,AN27,AN30) -> 1.0000225 | AO21: =SUM(AO24,AO27,AO30) -> 1.0000051 | ... AW21: =SUM(AW24,AW27,AW30) -> 1 | BY21: =SUM(BY24,BY27,BY30) -> 1.0000276 | BZ21: =SUM(BZ24,BZ27,BZ30) -> 1.0000057 | CA21: =SUM(CA24,CA27,CA30) -> 1 | CB21: =SUM(CB24,CB27,CB30) -> 1
A22: Agency | AC22: 8048 | AD22: 8175 | AE22: 8206 | AF22: 8430 | AG22: 32548 | AH22: 10640 | AI22: 10611 | AJ22: 10023 | AK22: 8869 | AL22: 11342 | AM22: 11168 | AN22: 10392 | AO22: 9493 | AP22: 12445 | AQ22: 12290 | AR22: 11442 | AS22: 10688 | AT22: 13727 | AU22: 13680 | AV22: 12588 | AW22: 11134 | BY22: 40143 | BZ22: 42395 | CA22: =SUM(AP22:AS22) -> 46865 | CB22: 51129
A23: Agency YoY growth | AH23: =AH22/AC22-1 -> 0.32206759 | AI23: =AI22/AD22-1 -> 0.29798165 | AJ23: =AJ22/AE22-1 -> 0.22142335 | AK23: =AK22/AF22-1 -> 0.052075919 | AL23: =AL22/AH22-1 -> 0.065977444 | AM23: =AM22/AI22-1 -> 0.052492696 | AN23: =AN22/AJ22-1 -> 0.036815325 | AO23: =AO22/AK22-1 -> 0.070357425 | AP23: =AP22/AL22-1 -> 0.097249162 | AQ23: =AQ22/AM22-1 -> 0.10046562 | AR23: =AR22/AN22-1 -> 0.10103926 | AS23: =AS22/AO22-1 -> 0.12588223 | ... AW23: =AW22/AS22-1 -> 0.041729042 | BY23: =BY22/AG22-1 -> 0.23334767 | BZ23: =BZ22/BY22-1 -> 0.056099444 | CA23: =CA22/BZ22-1 -> 0.10543696 | CB23: =CB22/CA22-1 -> 0.090984743
A24: Agency contribution | AH24: =AH22/AH$5 -> 0.56349963 | AI24: =AI22/AI$5 -> 0.56259544 | AJ24: =AJ22/AJ$5 -> 0.53930589 | AK24: =AK22/AK$5 -> 0.55073274 | AL24: =AL22/AL$5 -> 0.48038356 | AM24: =AM22/AM$5 -> 0.48901597 | AN24: =AN22/AN$5 -> 0.46818192 | AO24: =AO22/AO$5 -> 0.48027158 | ... AW24: =AW22/AW$5 -> 0.47898473 | BY24: =BY22/BY$5 -> 0.55422402 | BZ24: =BZ22/BZ$5 -> 0.47952449 | CA24: =CA22/CA$5 -> 0.46993292 | CB24: =CB22/CB$5 -> 0.47397403
A25: Merchant | AC25: 6937 | AD25: 6888 | AE25: 7187 | AF25: 6520 | AG25: 27131 | AH25: 8242 | AI25: 8250 | AJ25: 8563 | AK25: 7235 | AL25: 9572 | AM25: 9546 | AN25: 9792 | AO25: 8360 | AP25: 10803 | AQ25: 10794 | AR25: 10739 | AS25: 9077 | AT25: 11519 | AU25: 11750 | AV25: 11707 | AW25: 9835 | BY25: 32290 | BZ25: 37270 | CA25: =SUM(AP25:AS25) -> 41413 | CB25: 44811
A26: Merchant YoY growth | AH26: =AH25/AC25-1 -> 0.18812167 | AI26: =AI25/AD25-1 -> 0.19773519 | AJ26: =AJ25/AE25-1 -> 0.1914568 | AK26: =AK25/AF25-1 -> 0.10966258 | AL26: =AL25/AH25-1 -> 0.1613686 | AM26: =AM25/AI25-1 -> 0.15709091 | AN26: =AN25/AJ25-1 -> 0.14352447 | AO26: =AO25/AK25-1 -> 0.15549413 | AP26: =AP25/AL25-1 -> 0.12860426 | AQ26: =AQ25/AM25-1 -> 0.13073539 | AR26: =AR25/AN25-1 -> 0.096711601 | AS26: =AS25/AO25-1 -> 0.08576555 | ... AW26: =AW25/AS25-1 -> 0.083507767 | BY26: =BY25/AG25-1 -> 0.19015149 | BZ26: =BZ25/BY25-1 -> 0.15422731 | CA26: =CA25/BZ25-1 -> 0.11116179 | CB26: =CB25/CA25-1 -> 0.08205153
A27: Merchant contribution | AH27: =AH25/AH$5 -> 0.43650037 | AI27: =AI25/AI$5 -> 0.43741517 | AJ27: =AJ25/AJ$5 -> 0.46074791 | AK27: =AK25/AK$5 -> 0.44926726 | AL27: =AL25/AL$5 -> 0.40541628 | AM27: =AM25/AM$5 -> 0.41799306 | AN27: =AN25/AN$5 -> 0.44115063 | AO27: =AO25/AO$5 -> 0.42295064 | ... AW27: =AW25/AW$5 -> 0.42310174 | BY27: =BY25/BY$5 -> 0.44580359 | BZ27: =BZ25/BZ$5 -> 0.42155626 | CA27: =CA25/CA$5 -> 0.41526367 | CB27: =CB25/CB$5 -> 0.41540515
A28: Vrbo (HomeAway) | AH28: 1818 | AI28: 1460 | AJ28: 1403 | AK28: 1299 | AL28: 2697 | AM28: 2123 | AN28: 2013 | AO28: 1913 | AP28: 3947 | AQ28: 2814 | AR28: 2496 | AS28: 2192 | AT28: 4163 | AU28: 2862 | AV28: 2633 | AW28: 2276 | BZ28: 8746 | CA28: =SUM(AP28:AS28) -> 11449 | CB28: 11933
A29: Vrbo YoY growth | AL29: 0.48349835 | AM29: 0.45410959 | AN29: 0.43478261 | AO29: 0.48524845 | AP29: =AP28/AL28-1 -> 0.46347794 | AQ29: =AQ28/AM28-1 -> 0.32548281 | AR29: =AR28/AN28-1 -> 0.23994039 | AS29: =AS28/AO28-1 -> 0.14584422 | AT29: =AT28/AP28-1 -> 0.054725108 | AU29: =AU28/AQ28-1 -> 0.017057569 | AV29: =AV28/AR28-1 -> 0.054887821 | AW29: =AW28/AS28-1 -> 0.038321168 | BZ29: 0.46523706 | CA29: =CA28/BZ28-1 -> 0.30905557 | CB29: =CB28/CA28-1 -> 0.042274434
A30: Vrbo contribution | AL30: =AL28/AL$5 -> 0.11422981 | AM30: =AM28/AM$5 -> 0.092960324 | AN30: =AN28/AN$5 -> 0.090689974 | AO30: =AO28/AO$5 -> 0.096782843 | AP30: =AP28/AP$5 -> 0.14513164 | AQ30: =AQ28/AQ$5 -> 0.10865704 | AR30: =AR28/AR$5 -> 0.10115092 | AS30: =AS28/AS$5 -> 0.099831489 | ... AW30: =AW28/AW$5 -> 0.09791353 | BZ30: =BZ28/BZ$5 -> 0.098924901 | CA30: =CA28/CA$5 -> 0.11480341 | CB30: =CB28/CB$5 -> 0.11062082
A32: Gross booking breakdown by business model
A33: Agency | AP33: 16046 | AQ33: 14821 | AR33: 13663 | AS33: 12602 | AT33: 17352 | AU33: 16112 | AV33: 14585 | AW33: 11956 | AX33: 9823 | AY33: 1363 | AZ33: 3530 | BA33: 3405 | BB33: 6737 | BC33: 10362 | BD33: 8855 | BE33: 8325 | BF33: 11346 | BG33: 12773 | BH33: 10904 | BI33: 9469 | BJ33: 13425 | BK33: 12370 | BL33: 10927 | BM33: 9439 | BN33: 13301 | BO33: 12578 | BP33: 11379 | BQ33: 10376 | BR33: 13239 | BS33: 12376 | BT33: 11875 | BU33: 10517 | BV33: 14357 | BW33: 13317 | CA33: =SUM(AP33:AS33) -> 57132 | CB33: =SUM(AT33:AW33) -> 60005 | CC33: =SUM(AX33:BA33) -> 18121 | CD33: 34279 | CE33: =SUM(BF33:BI33) -> 44492 | CF33: 46161 | CG33: 47634 | CH33: 48007
A34: Agency YoY growth | AT34: =AT33/AP33-1 -> 0.081391001 | AU34: =AU33/AQ33-1 -> 0.087106133 | AV34: =AV33/AR33-1 -> 0.067481519 | AW34: =AW33/AS33-1 -> -0.051261704 | AX34: =AX33/AT33-1 -> -0.43389811 | AY34: =AY33/AU33-1 -> -0.91540467 | AZ34: =AZ33/AV33-1 -> -0.75797052 | BA34: =BA33/AW33-1 -> -0.71520575 | ... BC34: =BC33/AY33-1 -> 6.6023478 | BD34: 1.51 | BE34: 1.44 | BF34: 0.68 | BG34: 0.23 | BH34: 1.23 | BI34: 2.23 | BJ34: =BJ33/BF33-1 -> 0.18323638 | BK34: =BK33/BG33-1 -> -0.031550928 | BL34: =BL33/BH33-1 -> 0.0021093177 | BM34: =BM33/BI33-1 -> -0.0031682332 | BN34: =BN33/BJ33-1 -> -0.0092364991 | BO34: =BO33/BK33-1 -> 0.016814875 | BP34: =BP33/BL33-1 -> 0.041365425 | BQ34: =BQ33/BM33-1 -> 0.09926899 | ... BW34: =BW33/BS33-1 -> 0.07603426 | CC34: =CC33/CB33-1 -> -0.6980085 | CD34: =CD33/CC33-1 -> 0.89167264 | CE34: =CE33/CD33-1 -> 0.29793751 | CF34: =CF33/CE33-1 -> 0.037512362 | CG34: =CG33/CF33-1 -> 0.031910054 | CH34: =CH33/CG33-1 -> 0.0078305412
A35: Agency contribution | AP35: =AP33/AP$5 -> 0.59001324 | AQ35: =AQ33/AQ$5 -> 0.57228357 | AR35: =AR33/AR$5 -> 0.5536959 | AS35: =AS33/AS$5 -> 0.57393997 | AT35: =AT33/AT$5 -> 0.59002346 | AU35: =AU33/AU$5 -> 0.56948961 | AV35: =AV33/AV$5 -> 0.54164965 | AW35: =AW33/AW$5 -> 0.51434717 | ... BF35: =BF33/BF$5 -> 0.46477142 | BG35: =BG33/BG5 -> 0.4886568 | BH35: =BH33/BH5 -> 0.45457956 | BI35: =BI33/BI5 -> 0.46165472 | BJ35: =BJ33/BJ$5 -> 0.45661712 | BK35: =BK33/BK5 -> 0.45276527 | BL35: =BL33/BL5 -> 0.4254234 | BM35: =BM33/BM5 -> 0.43553894 | BN35: =BN33/BN5 -> 0.44095611 | BO35: =BO33/BO5 -> 0.43617575 | BP35: =BP33/BP5 -> 0.41381191 | BQ35: =BQ33/BQ5 -> 0.42486283 | BR35: =BR33/BR5 -> 0.42094051 | ... BW35: =BW33/BW5 -> 0.39250766 | CC35: =CC33/CC$5 -> 0.49247201 | CD35: =CD33/CD$5 -> 0.47330342 | CE35: =CE33/CE$5 -> 0.4680954 | CF35: =CF33/CF$5 -> 0.44351887 | CG35: =CG33/CG$5 -> 0.42944077 | CH35: =CH33/CH$5 -> 0.40142989
A36: Growth vs.2019 | BI36: =BI33/AW33-1 -> -0.20801271 | BJ36: =BJ33/AT33-1 -> -0.22631397 | BK36: =BK33/AU33-1 -> -0.23224926 | BL36: =BL33/AV33-1 -> -0.25080562 | BM36: =BM33/AW33-1 -> -0.21052191 | BO36: =BO33/AU33-1 -> -0.21933962 | BP36: =BP33/AV33-1 -> -0.21981488 | BQ36: =BQ33/AW33-1 -> -0.13215122 | BR36: =BR33/AT33-1 -> -0.2370332 | BS36: =BS33/AU33-1 -> -0.23187686 | BT36: =BT33/AV33-1 -> -0.18580734 | BU36: =BU33/AW33-1 -> -0.12035798 | BV36: =BV33/AT33-1 -> -0.17260258 | BW36: =BW33/AU33-1 -> -0.17347319
A37: Merchant | AP37: 11150 | AQ37: 11077 | AR37: 11013 | AS37: 9355 | AT37: 12057 | AU37: 12180 | AV37: 12342 | AW37: 11289 | AX37: 8062 | AY37: 1350 | AZ37: 5101 | BA37: 4162 | BB37: 8685 | BC37: 10453 | BD37: 9870 | BE37: 9138 | BF37: 13066 | BG37: 13366 | BH37: 13083 | BI37: 11042 | BJ37: 15976 | BK37: 14951 | BL37: 14758 | BM37: 12233 | BN37: 16863 | BO37: 16259 | BP37: 16119 | BQ37: 14046 | BR37: 18212 | BS37: 18033 | BT37: 18852 | BU37: 16486 | BV37: 21173 | BW37: 20611 | CA37: =SUM(AP37:AS37) -> 42595 | CB37: =SUM(AT37:AW37) -> 47868 | CC37: =SUM(AX37:BA37) -> 18675 | CD37: 38146 | CE37: 50557 | CF37: 57918 | CG37: 63287 | CH37: 71583
A38: Merchant YoY growth | AT38: =AT37/AP37-1 -> 0.081345291 | AU38: =AU37/AQ37-1 -> 0.099575697 | AV38: =AV37/AR37-1 -> 0.12067557 | AW38: =AW37/AS37-1 -> 0.20673437 | AX38: =AX37/AT37-1 -> -0.33134279 | AY38: =AY37/AU37-1 -> -0.88916256 | AZ38: =AZ37/AV37-1 -> -0.58669584 | BA38: =BA37/AW37-1 -> -0.63132253 | ... BC38: =BC37/AY37-1 -> 6.742963 | BD38: 0.93 | BE38: 1.2 | BF38: 0.5 | BG38: 0.28 | BH38: 1.28 | BI38: 2.28 | BJ38: =BJ37/BF37-1 -> 0.22271544 | BK38: =BK37/BG37-1 -> 0.11858447 | BL38: =BL37/BH37-1 -> 0.12802874 | BM38: =BM37/BI37-1 -> 0.10786089 | BN38: =BN37/BJ37-1 -> 0.055520781 | BO38: =BO37/BK37-1 -> 0.087485787 | BP38: =BP37/BL37-1 -> 0.092221168 | BQ38: =BQ37/BM37-1 -> 0.14820567 | ... BW38: =BW37/BS37-1 -> 0.14296013 | CC38: =CC37/CB37-1 -> -0.60986463 | CD38: =CD37/CC37-1 -> 1.0426238 | CE38: =CE37/CD37-1 -> 0.32535521 | CF38: =CF37/CE37-1 -> 0.14559804 | CG38: =CG37/CF37-1 -> 0.092700024 | CH38: =CH37/CG37-1 -> 0.13108537
A39: Merchant contribution | AP39: =AP37/AP$5 -> 0.40998676 | AQ39: =AQ37/AQ$5 -> 0.42771643 | AR39: =AR37/AR$5 -> 0.4463041 | AS39: =AS37/AS$5 -> 0.42606003 | AT39: =AT37/AT$5 -> 0.40997654 | AU39: =AU37/AU$5 -> 0.43051039 | AV39: =AV37/AV$5 -> 0.45835035 | AW39: =AW37/AW$5 -> 0.48565283 | ... BF39: =BF37/BF$5 -> 0.53522858 | BG39: =BG37/BG5 -> 0.5113432 | BH39: =BH37/BH5 -> 0.54542044 | BI39: =BI37/BI5 -> 0.53834528 | BJ39: =BJ37/BJ$5 -> 0.54338288 | BK39: =BK37/BK5 -> 0.54723473 | BL39: =BL37/BL5 -> 0.5745766 | BM39: =BM37/BM5 -> 0.56446106 | BN39: =BN37/BN5 -> 0.55904389 | BO39: =BO37/BO5 -> 0.56382425 | BP39: =BP37/BP5 -> 0.58618809 | BQ39: =BQ37/BQ5 -> 0.57513717 | BR39: =BR37/BR5 -> 0.57905949 | ... BW39: =BW37/BW5 -> 0.60749234 | CC39: =CC37/CC$5 -> 0.50752799 | CD39: =CD37/CD$5 -> 0.52669658 | CE39: =CE37/CE$5 -> 0.5319046 | CF39: =CF37/CF$5 -> 0.55648113 | CG39: =CG37/CG$5 -> 0.57055923 | CH39: =CH37/CH$5 -> 0.59857011
A40: Growth vs.2019 | BI40: =BI37/AW37-1 -> -0.021879706 | BJ40: =BJ37/AT37-1 -> 0.3250394 | BK40: =BK37/AU37-1 -> 0.22750411 | BL40: =BL37/AV37-1 -> 0.19575433 | BM40: =BM37/AW37-1 -> 0.083621224 | BO40: =BO37/AU37-1 -> 0.33489327 | BP40: =BP37/AV37-1 -> 0.3060282 | BQ40: =BQ37/AW37-1 -> 0.24422004 | BR40: =BR37/AT37-1 -> 0.51049183 | BS40: =BS37/AU37-1 -> 0.48054187 | BT40: =BT37/AV37-1 -> 0.52746719 | BU40: =BU37/AW37-1 -> 0.46035964 | BV40: =BV37/AT37-1 -> 0.75607531 | BW40: =BW37/AU37-1 -> 0.69220033
A41: Gross booking breakdown by product lines (MS Estimates)
A42: Hotel | AD42: 6477.8318 | AE42: 8348.7978 | AF42: 6252.3237 | AH42: =7588.52564986386-AH28 -> 5770.5256 | AI42: =8364.85231097333-AI28 -> 6904.8523 | AJ42: =10996.2490689578-AJ28 -> 9593.2491 | AK42: =7685.14781995506-AK28 -> 6386.1478 | AL42: 8630.2954 | AM42: 10329.072 | AN42: 13332.609 | AO42: 9211.7568 | AP42: 9607 | AQ42: 11916.8 | AR42: 14004.9 | AS42: 10764 | AT42: 10398.96 | AU42: 13313.3 | AV42: 15339.555 | AW42: 11908 | AX42: 5927.4072 | BY42: =SUM(AH42:AK42) -> 28654.775 | BZ42: =SUM(AL42:AO42) -> 41503.733 | CA42: =SUM(AP42:AS42) -> 46292.7 | CB42: 53869.1
A43: Hotel YoY growth | AI43: =AI42/AD42-1 -> 0.065920291 | AJ43: =AJ42/AE42-1 -> 0.14905754 | AK43: =AK42/AF42-1 -> 0.02140391 | AL43: =AL42/AH42-1 -> 0.49558219 | AM43: =AM42/AI42-1 -> 0.49591494 | AN43: =AN42/AJ42-1 -> 0.38979079 | AO43: =AO42/AK42-1 -> 0.44245907 | AP43: =AP42/AL42-1 -> 0.11317163 | AQ43: =AQ42/AM42-1 -> 0.15371452 | AR43: =AR42/AN42-1 -> 0.050424547 | AS43: =AS42/AO42-1 -> 0.16850674 | ... AX43: =AX42/AT42-1 -> -0.43 | BY43: =BY42/AG42-1 -> #DIV/0! | BZ43: =BZ42/BY42-1 -> 0.44840549 | CA43: =CA42/BZ42-1 -> 0.11538641 | CB43: =CB42/CA42-1 -> 0.16366295
A44: Hotel contribution | AH44: =AH42/AH$5 -> 0.30560987 | AI44: =AI42/AI$5 -> 0.36609541 | AJ44: =AJ42/AJ$5 -> 0.51618236 | AK44: =AK42/AK$5 -> 0.39655662 | AL44: =AL42/AL$5 -> 0.36553095 | AM44: =AM42/AM$5 -> 0.45228161 | AN44: =AN42/AN$5 -> 0.60066268 | AO44: =AO42/AO$5 -> 0.46604287 | ... AX44: =AX42/AX$5 -> 0.33141779 | BY44: =BY42/BY$5 -> 0.39561479 | BZ44: =BZ42/BZ$5 -> 0.46944348 | CA44: =CA42/CA$5 -> 0.46419425 | CB44: =CB42/CB$5 -> 0.49937519
A45: Air | AD45: 6798.7607 | AE45: 6223.9168 | AF45: 6840.7576 | AH45: 9136.1607 | AI45: 9069.5468 | AJ45: 7722.636 | AK45: 6961.155 | AL45: 9571.042 | AM45: 9343.4471 | AN45: 7870.9106 | AO45: 7241.6895 | AP45: 9956.755 | AQ45: 10003.094 | AR45: 8513.1769 | AS45: 8125.1756 | AT45: 10941.5 | AU45: 11113.4 | AV45: 9194.2 | AW45: 8206.4 | AX45: 5908.3981 | BY45: =SUM(AH45:AK45) -> 32889.498 | BZ45: =SUM(AL45:AO45) -> 34027.089 | CA45: =SUM(AP45:AS45) -> 36598.202 | CB45: 39455.6
