Workbook

Sheet Tongchengelong
B1: eLong Only | P1: Tongcheng Only | U1: eLong only | V1: Tongcheng-eLong | W1: Tongcheng-eLong | Z1: Tongcheng-eLong | AA1: Tongcheng-eLong | BD1: Tongcheng-eLong
A2: (RMB in thousands, expect for Share/pershare data) | B2: 2015-1H | C2: 2015-2H | D2: 2016-1H | E2: 2016-2H | F2: 2017-1H | G2: 2017-2H | H2: 2018-1H | I2: 2018-2H | K2: 2015 | L2: 2016 | M2: 2017 | N2: 2018 | P2: 2015 | Q2: 2016 | R2: 2017 | S2: 2018.3.9 | U2: 1Q18 | V2: 1Q18E | W2: 2Q18 | X2: 3Q18 | Y2: 4Q18 | Z2: 1Q19 | AA2: 2Q19 | AB2: 3Q19 | AC2: 4Q19 | AD2: 1Q20 | AE2: 2Q20 | AF2: 3Q20 | AG2: 4Q20 | AH2: 1Q21 | AI2: 2Q21 | AJ2: 3Q21 | AK2: 4Q21 | AL2: 1Q22 | AM2: 2Q22 | AN2: 3Q22 | AO2: 4Q22 | AP2: 1Q23 | AQ2: 2Q23 | AR2: 3Q23 | AS2: 4Q23 | AT2: 1Q24 | AU2: 2Q24 | AV2: 3Q24 | AW2: 4Q24 | AX2: 1Q25 | AY2: 2Q25 | AZ2: 3Q25 | BA2: 4Q25 | BB2: 1Q26 | BC2: 2Q26 | BD2: 2018-1H | BE2: 2018-2H | BF2: 2019-1H | BG2: 2019-2H | BI2: 2015 | BJ2: 2016 | BK2: 2017 | BL2: 2018 | BM2: 2019 | BN2: 2020 | BO2: 2021 | BP2: 2022
A3: Transaction Volume | Z3: =Z11/Z4 -> 0.049677187 | AN3: =AN11/AN4 -> 0.050442143 | AO3: =AO11/AO4 -> 0.059057717
A4: GMV【公司仅披露总GMV，不拆分业务线】 | K4: =K5+K6 -> 17105500 | L4: =L5+L6 -> 18347200 | M4: =M5+M6 -> 22551400 | V4: 29000000 | W4: 28900000 | X4: 39100000 | Y4: 34500000 | Z4: 35900000 | AA4: 41300000 | AB4: 47600000 | AC4: 41300000 | AD4: 18200000 | AE4: 22400000 | AF4: 39700000 | AG4: 36100000 | AH4: 33300000 | AI4: 43900000 | AJ4: 41100000 | AK4: 31900000 | AL4: 32400000 | AM4: 24300000 | AN4: 40600000 | AO4: 25400000 | AP4: 57200000 | AQ4: 59700000 | AR4: 71100000 | AS4: 53500000 | AT4: 65900000 | AU4: 62300000 | AV4: 72800000 | AW4: 54700000 | AX4: =AT4*(1+AX77) -> 64582000 | AY4: =AU4*(1+AY77) -> 62923000 | AZ4: =AV4*(1+AZ77) -> 76440000 | BA4: =AW4*(1+BA77) -> 57161500 | BB4: =AX4*(1+BB77) -> 67811100 | BD4: =BD6+BD5 -> 57962900 | BI4: =BI6+BI5 -> 36831500 | BJ4: =BJ6+BJ5 -> 67795600 | BK4: =BK6+BK5 -> 102313600 | BL4: 131500000 | BM4: 166100000 | BN4: 116400000 | BO4: =SUM(AH4:AK4) -> 150200000 | BP4: =SUM(AL4:AO4) -> 122700000
A5: -Transportation ticketing | K5: 3729100 | L5: 2456500 | M5: 2035700 | Z5: =Z4*Z8 -> 30154502 | AA5: =AA4*AA8 -> 33765813 | AB5: =AB4*AB8 -> 38121813 | AC5: 34410000 | AD5: =AD4*AD8 -> 14721594 | AE5: =AE4*AE8 -> 17423618 | AF5: =AF4*AF8 -> 30403937 | AG5: =AG8*AG4 -> 27329524 | AH5: =AH4*AH8 -> 26567686 | AI5: =AI4*AI8 -> 33720448 | AJ5: =AJ4*AJ8 -> 31760015 | AK5: =AK4*AK8 -> 24256434 | AL5: =AL4*AL8 -> 25197751 | AM5: =AM8*AM4 -> 17907268 | AN5: =AN8*AN4 -> 30248720 | AO5: =AO8*AO4 -> 18458214 | AP5: =AP4*AP8 -> 43122298 | AQ5: =AQ4*AQ8 -> 42987733 | AR5: =AR4*AR8 -> 51890606 | AS5: =AS4*AS8 -> 38894412 | AT5: =AT4*AT8 -> 49425000 | AU5: =AU4*AU8 -> 44357600 | AV5: =AV4*AV8 -> 52707200 | AW5: =AW4*AW8 -> 38837000 | ... BB5: =BB4*BB8 -> 48145881 | BD5: 47231000 | BI5: 22553700 | BJ5: 50525100 | BK5: 80013400 | BM5: =BM4-BM6 -> 140002000 | BN5: =SUM(AD5:AG5) -> 89878673 | BO5: =SUM(AH5:AK5) -> 1.1630458e+08 | BP5: =SUM(AL5:AO5) -> 91811953
A6: -Accommodation | K6: 13376400 | L6: 15890700 | M6: 20515700 | Z6: 5205000 | AA6: 5911000 | AB6: 8092000 | AC6: 6890000 | AD6: 2430000 | AE6: 3696000 | AF6: 6193200 | AG6: 7039500 | AH6: 5994000 | AI6: 8341000 | AJ6: 7809000 | AK6: 6539500 | AL6: 5670000 | AM6: 5224500 | AN6: 8404200 | AO6: 5334000 | AP6: 10296000 | AQ6: 11641500 | AR6: 13864500 | AS6: 10860500 | AT6: 11466600 | AU6: =AU4*AU9 -> 12584600 | AV6: 14196000 | AW6: 11760500 | AX6: 12270580 | AY6: =AY4*AY9 -> 13654291 | AZ6: =AZ4*AZ9 -> 16434600 | BA6: =BA4*BA9 -> 13432952 | BB6: =BB4*BB9 -> 13969087 | BD6: 10731900 | BI6: 14277800 | BJ6: 17270500 | BK6: 22300200 | BM6: =SUM(Z6:AC6) -> 26098000 | BN6: =SUM(AD6:AG6) -> 19358700 | BO6: =SUM(AH6:AK6) -> 28683500 | BP6: =SUM(AL6:AO6) -> 24632700
A7: -Others | AT7: =AT4-AT5-AT6 -> 5008400 | AU7: =AU4-AU5-AU6 -> 5357800 | AV7: =AV4-AV5-AV6 -> 5896800 | AW7: =AW4-AW5-AW6 -> 4102500 | AX7: =AX4-AX5-AX6 -> 5166560 | AY7: =AY4-AY5-AY6 -> 5222609 | AZ7: =AZ4-AZ5-AZ6 -> 8790600 | BA7: =BA4-BA5-BA6 -> 4858727.5 | BB7: =BB4-BB5-BB6 -> 5696132.4
A8: 机票占比 为估算，非实际数 | Z8: 0.83995827 | AA8: 0.81757418 | AB8: 0.80087843 | AC8: 0.7952497 | AD8: 0.80887879 | AE8: 0.77784007 | AF8: 0.76584225 | AG8: 0.75705052 | AH8: 0.7978284 | AI8: 0.76811955 | AJ8: 0.77274976 | AK8: 0.76038979 | AL8: 0.77770838 | AM8: 0.7369246 | AN8: 0.74504236 | AO8: 0.72670133 | AP8: 0.75388634 | AQ8: 0.72006253 | AR8: 0.72982569 | AS8: 0.72699836 | AT8: 0.75 | AU8: 0.712 | AV8: 0.724 | AW8: 0.71 | AX8: 0.73 | AY8: 0.7 | AZ8: 0.67 | BA8: 0.68 | BB8: 0.71
A9: 酒店占比 为估算，非实际数 | AS9: =AS6/AS4 -> 0.203 | AT9: =AT6/AT4 -> 0.174 | AU9: 0.202 | AV9: =AV6/AV4 -> 0.195 | AW9: =AW6/AW4 -> 0.215 | AX9: =AX6/AX4 -> 0.19 | AY9: 0.217 | AZ9: 0.215 | BA9: 0.235 | BB9: 0.206
A10: P&L | AH10: From MS | AI10: =35120/43900 -> 0.8
A11: Total Revenue | F11: 1245814 | G11: =M11-F11 -> 1272777 | H11: 1996844 | I11: =N11-H11 -> 3258795 | K11: 1026124 | L11: 2204565 | M11: 2518591 | N11: 5255639 | P11: 580523 | Q11: 1434957 | R11: 2707499 | S11: 835148 | U11: 682364 | V11: =S11+U11 -> 1517512 | W11: 1314480 | X11: 1686397 | Y11: 1572398 | Z11: 1783411 | AA11: 1590898 | AB11: 2062130 | AC11: 1956493 | AD11: 1005116 | AE11: 1200106 | AF11: 1914518 | AG11: 1812851 | AH11: 1613763 | AI11: 2137977 | AJ11: 1939431 | AK11: 1846385 | AL11: 1717999 | AM11: 1318650 | AN11: 2047951 | AO11: 1500066 | AP11: 2586143 | AQ11: 2866269 | AR11: 3299290 | AS11: 3144542 | AT11: 3866278 | AU11: 4245357 | AV11: 4991496 | AW11: 4237555 | AX11: 4377432 | AY11: 4669431 | AZ11: 5509112 | BA11: 4839984 | BB11: 5005792 | BC11: 4987027 | BD11: 2831992 | BE11: =BL11-BD11 -> 2423647 | BF11: 3374309 | BI11: 1607000 | BJ11: 3640000 | BK11: 5226090 | BL11: 5255639 | BM11: 7392932 | BN11: 5932591 | BO11: =SUM(AH11:AK11) -> 7537556 | BP11: =SUM(AL11:AO11) -> 6584666 | BQ11: =BP11*(1+BR11) -> 9942845.7 | BR11: 0.51 | BS11: =BQ11/BM11-1 -> 0.34491236
A12: 1. Core OTA Platform
A13: -Accommodation Reservation | F13: 1187674 | G13: =M13-F13 -> 1173951 | H13: 890568 | I13: =N13-H13 -> 939802 | K13: 907649 | L13: 2094050 | M13: 2361625 | N13: 1830370 | U13: 449586 | W13: 440982 | X13: 515722 | Y13: 424080 | Z13: 489164 | AA13: 553360 | AB13: 693736 | AC13: 621863 | AD13: 229014 | AE13: 384298 | AF13: 684559 | AG13: 647282 | AH13: 458537 | AI13: 742892 | AJ13: 644940 | AK13: 562360 | AL13: 543082 | AM13: 543526 | AN13: 818709 | AO13: 509430 | AP13: 834261 | AQ13: 1055396 | AR13: 1127401 | AS13: 882456 | AT13: 964683 | AU13: 1190879 | AV13: 1377541 | AW13: 1135076 | AX13: 1189642 | AY13: 1371367 | AZ13: 1579472 | BA13: 1310303 | BB13: 1364460 | BC13: 1480655 | BI13: 978000 | BJ13: 2176000 | BK13: 2643000 | BL13: 1830370 | BM13: 2358123 | BN13: 1945153 | BO13: =SUM(AH13:AK13) -> 2408729 | BP13: =SUM(AL13:AO13) -> 2414747
A14: of which, Net commissions earned from accommodation reservation | F14: 861193 | G14: =M14-F14 -> 967562 | H14: 824568 | I14: =N14-H14 -> 817732 | K14: 667963 | L14: 1416691 | M14: 1828755 | N14: 1642300 | BI14: 738000 | BJ14: 1499000 | BK14: 1930000
A15: -Transportation Ticketing | F15: 32122 | G15: =M15-F15 -> 29173 | H15: 1037656 | I15: =N15-H15 -> 2194865 | K15: 89378 | L15: 86650 | M15: 61295 | N15: 3232521 | U15: 208169 | W15: 829487 | X15: 1122150 | Y15: 1072715 | Z15: 1258948 | AA15: 937092 | AB15: 1139621 | AC15: 1181997 | AD15: 686768 | AE15: 725822 | AF15: 1055118 | AG15: 1003421 | AH15: 1023426 | AI15: 1234750 | AJ15: 1124724 | AK15: 1074837 | AL15: 1017219 | AM15: 619521 | AN15: 986646 | AO15: 755548 | AP15: 1382694 | AQ15: 1494582 | AR15: 1679948 | AS15: 1472823 | AT15: 1736504 | AU15: 1742736 | AV15: 2026751 | AW15: 1723040 | AX15: 2000211 | AY15: 1881010 | AZ15: 2208716 | BA15: 1835511 | BB15: 2124018 | BC15: 1838210 | BI15: 599000 | BJ15: 1435000 | BK15: 2530000 | BL15: 3232521 | BM15: 4517658 | BN15: 3471129 | BO15: =SUM(AH15:AK15) -> 4457737 | BP15: =SUM(AL15:AO15) -> 3378934
A16: -Others | F16: 26018 | G16: =M16-F16 -> 69653 | H16: 68620 | I16: =N16-H16 -> 124128 | K16: 29097 | L16: 23865 | M16: 95671 | N16: 192748 | U16: 24609 | W16: 44011 | X16: 48525 | Y16: 75603 | Z16: 35299 | AA16: 100446 | AB16: 228773 | AC16: 152633 | AD16: 89334 | AE16: 89986 | AF16: 174841 | AG16: 162148 | AH16: 131800 | AI16: 160335 | AJ16: 169767 | AK16: 209188 | AL16: 157698 | AM16: 155603 | AN16: 242596 | AO16: 235088 | AP16: 369188 | AQ16: 316291 | AR16: 491941 | AS16: 521945 | AT16: 502157 | AU16: 592344 | AV16: 608518 | AW16: 599216 | AX16: 602577 | AY16: 755398 | AZ16: 820608 | BA16: 916662 | BB16: 961421 | BC16: 1025369 | BI16: 30000 | BJ16: 28000 | BK16: 233000 | BL16: =AW16*1.5 -> 898824 | BM16: 517151 | BN16: 516309 | BO16: =SUM(AH16:AK16) -> 671090 | BP16: =SUM(AL16:AO16) -> 790985
A17: Core OTA Platform Total | AN17: =SUM(AN13:AN16) -> 2047951 | AO17: =SUM(AO13:AO16) -> 1500066 | AP17: =SUM(AP13:AP16) -> 2586143 | AQ17: =SUM(AQ13:AQ16) -> 2866269 | AR17: =SUM(AR13:AR16) -> 3299290 | AS17: =SUM(AS13:AS16) -> 2877224 | AT17: =SUM(AT13:AT16) -> 3203344 | AU17: =SUM(AU13:AU16) -> 3525959 | ... BC17: =SUM(BC13:BC16) -> 4344234
A18: YoY | AT18: =AT17/AP17-1 -> 0.23865695 | AU18: =AU17/AQ17-1 -> 0.23015635 | AV18: =AV17/AR17-1 -> 0.21626471 | AW18: =AW17/AS17-1 -> 0.20162073 | AX18: =AX17/AT17-1 -> 0.1838972 | AY18: =AY17/AU17-1 -> 0.13664821 | AZ18: =AZ17/AV17-1 -> 0.14852086 | BA18: =BA17/AW17-1 -> 0.17503208 | ... BC18: =BC17/AY17-1 -> 0.083951569
A19: 2. 度假 | AS19: 267318 | AT19: 662934 | AU19: 719398 | AV19: 978686 | AW19: =AW11-AW17 -> 780223 | AX19: 585002 | AY19: 661656 | AZ19: 900316 | BA19: 777508 | BB19: 555893 | BC19: 642793
AX20: =AX19/AX11 -> 0.13364045 | AY20: =AY19/AY11 -> 0.14169949 | AZ20: =AZ19/AZ11 -> 0.16342307 | BA20: =BA19/BA11 -> 0.16064268 | BB20: =BB19/BB11 -> 0.11104996 | BC20: =BC19/BC11 -> 0.12889303
A21: Cost of revenue | F21: -465692 | G21: =M21-F21 -> -346089 | H21: -564616 | I21: =N21-H21 -> -1035897 | K21: -639723 | L21: -1032913 | M21: -811781 | N21: -1600513 | P21: -228465 | Q21: -530211 | R21: -858806 | S21: -223013 | U21: -194085 | V21: =S21+U21 -> -417098 | W21: -370531 | X21: -479543 | Y21: -556354 | Z21: -498270 | AA21: -561160 | AB21: -682530 | AC21: -575015 | AD21: -351267 | AE21: -332453 | AF21: -535315 | AG21: -477571 | AH21: -409082 | AI21: -505447 | AJ21: -506590 | AK21: -468562 | AL21: -471610 | AM21: -383230 | AN21: -502871 | AO21: -448929 | AP21: -645282 | AQ21: -703284 | AR21: -839728 | AS21: -969739 | AT21: -1351484 | AU21: -1501022 | AV21: -1826821 | AW21: -1547872 | AX21: -1364955 | AY21: -1633149 | AZ21: -1887277 | BA21: -1652826 | BB21: -1509526 | BC21: -1660405 | BD21: -787629 | BE21: =BL21-BD21 -> -812884 | BI21: -868000 | BJ21: -1563000 | BK21: -1670587 | BL21: -1600513 | BM21: -2316975 | BN21: -1696606 | BO21: =SUM(AH21:AK21) -> -1889681 | BP21: =SUM(AL21:AO21) -> -1806640
A22: Gross Profit | B22: =IFERROR(B11+B21,"n.a.") -> 0 | C22: =IFERROR(C11+C21,"n.a.") -> 0 | D22: =IFERROR(D11+D21,"n.a.") -> 0 | E22: =IFERROR(E11+E21,"n.a.") -> 0 | F22: =IFERROR(F11+F21,"n.a.") -> 780122 | G22: =IFERROR(G11+G21,"n.a.") -> 926688 | H22: =IFERROR(H11+H21,"n.a.") -> 1432228 | I22: =IFERROR(I11+I21,"n.a.") -> 2222898 | K22: =IFERROR(K11+K21,"n.a.") -> 386401 | L22: =IFERROR(L11+L21,"n.a.") -> 1171652 | M22: =IFERROR(M11+M21,"n.a.") -> 1706810 | N22: =IFERROR(N11+N21,"n.a.") -> 3655126 | P22: =IFERROR(P11+P21,"n.a.") -> 352058 | Q22: =IFERROR(Q11+Q21,"n.a.") -> 904746 | R22: =IFERROR(R11+R21,"n.a.") -> 1848693 | S22: =IFERROR(S11+S21,"n.a.") -> 612135 | U22: =IFERROR(U11+U21,"n.a.") -> 488279 | V22: =IFERROR(V11+V21,"n.a.") -> 1100414 | W22: =IFERROR(W11+W21,"n.a.") -> 943949 | X22: =IFERROR(X11+X21,"n.a.") -> 1206854 | Y22: =IFERROR(Y11+Y21,"n.a.") -> 1016044 | Z22: =IFERROR(Z11+Z21,"n.a.") -> 1285141 | AA22: =IFERROR(AA11+AA21,"n.a.") -> 1029738 | AB22: =IFERROR(AB11+AB21,"n.a.") -> 1379600 | ... AS22: =IFERROR(AS11+AS21,"n.a.") -> 2174803 | AT22: 2514794 | AU22: =AU11+AU21 -> 2744335 | AV22: =AV11+AV21 -> 3164675 | AW22: =AW11+AW21 -> 2689683 | AX22: =AX11+AX21 -> 3012477 | AY22: =AY11+AY21 -> 3036282 | AZ22: =AZ11+AZ21 -> 3621835 | BA22: =BA11+BA21 -> 3187158 | BB22: =BB11+BB21 -> 3496266 | BC22: =BC11+BC21 -> 3326622 | BD22: =IFERROR(BD11+BD21,"n.a.") -> 2044363 | BE22: =IFERROR(BE11+BE21,"n.a.") -> 1610763 | BF22: =IFERROR(BF11+BF21,"n.a.") -> 3374309 | BG22: =IFERROR(BG11+BG21,"n.a.") -> 0 | BI22: =IFERROR(BI11+BI21,"n.a.") -> 739000 | BJ22: =IFERROR(BJ11+BJ21,"n.a.") -> 2077000 | BK22: =IFERROR(BK11+BK21,"n.a.") -> 3555503 | BL22: =IFERROR(BL11+BL21,"n.a.") -> 3655126 | BM22: =IFERROR(BM11+BM21,"n.a.") -> 5075957 | BN22: =IFERROR(BN11+BN21,"n.a.") -> 4235985 | BO22: =IFERROR(BO11+BO21,"n.a.") -> 5647875 | BP22: =IFERROR(BP11+BP21,"n.a.") -> 4778026
A23: Service development expenses | F23: -245421 | G23: =M23-F23 -> -276597 | H23: -506734 | I23: =N23-H23 -> -843201 | K23: -399073 | L23: -517648 | M23: -522018 | N23: -1349935 | P23: -164277 | Q23: -371720 | R23: -514800 | S23: -118448 | U23: -189234 | V23: =S23+U23 -> -307682 | W23: -317500 | X23: -403346 | Y23: -439855 | Z23: -430052 | AA23: -352154 | AB23: -358993 | AC23: -371592 | AD23: -287449 | AE23: -300363 | AF23: -301834 | AG23: -355860 | AH23: -306953 | AI23: -330201 | AJ23: -322924 | AK23: -384390 | AL23: -351821 | AM23: -324879 | AN23: -370926 | AO23: -366508 | AP23: -411140 | AQ23: -427826 | AR23: -466330 | AS23: -515273 | AT23: -486775 | AU23: -494281 | AV23: -505072 | AW23: -514766 | AX23: -495120 | AY23: -504524 | AZ23: -514544 | BA23: -524863 | BB23: -524331 | BC23: -528173 | BD23: -656809 | BE23: =BL23-BD23 -> -693126 | BK23: -1191509 | BL23: -1349935 | BM23: -1512792 | BN23: -1245506 | BO23: =SUM(AH23:AK23) -> -1344468 | BP23: =SUM(AL23:AO23) -> -1414134
A24: Selling and marketing expenses | F24: -511960 | G24: =M24-F24 -> -583017 | H24: -706087 | I24: =N24-H24 -> -1135227 | K24: -775464 | L24: -1882779 | M24: -1094977 | N24: -1841314 | P24: -580764 | Q24: -515174 | R24: -670732 | S24: -189827 | U24: -241991 | V24: =S24+U24 -> -431818 | W24: -464096 | X24: -576207 | Y24: -559020 | Z24: -469723 | AA24: -407187 | AB24: -627565 | AC24: -640041 | AD24: -291194 | AE24: -369489 | AF24: -724938 | AG24: -745655 | AH24: -618071 | AI24: -884584 | AJ24: -786927 | AK24: -746874 | AL24: -636961 | AM24: -574681 | AN24: -937280 | AO24: -652322 | AP24: -966236 | AQ24: -1107860 | AR24: -1271545 | AS24: -1127174 | AT24: -1368203 | AU24: -1501710 | AV24: -1467569 | AW24: -1283228 | AX24: -1453540 | AY24: -1538292 | AZ24: -1715364 | BA24: -1574110 | BB24: -1691405 | BC24: -1627575 | BD24: -905094 | BE24: =BL24-BD24 -> -936220 | BK24: -1803050 | BL24: -1841314 | BM24: -2244516 | BN24: -2131276 | BO24: =SUM(AH24:AK24) -> -3036456 | BP24: =SUM(AL24:AO24) -> -2801244
A25: Administrative expenses | F25: -35541 | G25: =M25-F25 -> -61838 | H25: -515878 | I25: =N25-H25 -> -419047 | K25: -272584 | L25: -898337 | M25: -97379 | N25: -934925 | P25: -56830 | Q25: -91119 | R25: -132772 | S25: -23566 | U25: -382129 | V25: =S25+U25 -> -405695 | W25: -133749 | X25: -163476 | Y25: -255571 | Z25: -228322 | AA25: -99805 | AB25: -96270 | AC25: -174281 | AD25: =-208584-116023-AE25 -> -120034 | AE25: =-106328-98245 -> -204573 | AF25: =-101391-11638 -> -113029 | AG25: =BN25-AD25-AE25-AF25 -> -224505 | AH25: =-108346-16811 -> -125157 | AI25: =-126243-11919 -> -138162 | AJ25: =-115779-25579 -> -141358 | AK25: =-221288-36419 -> -257707 | AL25: =-188245+2278 -> -185967 | AM25: =-134877-15322 -> -150199 | AN25: -182789 | AO25: -195230 | AP25: -192266 | AQ25: -207641 | AR25: -196536 | AS25: -114751 | AT25: -265303 | AU25: -272193 | AV25: -327745 | AW25: -340938 | AX25: -307438 | AY25: -277742 | AZ25: -291445 | BA25: -389291 | BB25: -326830 | BC25: -385704 | BD25: -533527 | BE25: 3258795 | BK25: -297681 | BL25: -934925 | BM25: =-594217-39958 -> -634175 | BN25: =-521728-140413 -> -662141 | BO25: =SUM(AH25:AK25) -> -662384 | BP25: =SUM(AL25:AO25) -> -714185
A26: Operating Profit/(Loss) | B26: =IFERROR(B22+B23+B24+B25,"n.a.") -> 0 | C26: =IFERROR(C22+C23+C24+C25,"n.a.") -> 0 | D26: =IFERROR(D22+D23+D24+D25,"n.a.") -> 0 | E26: =IFERROR(E22+E23+E24+E25,"n.a.") -> 0 | F26: =IFERROR(F22+F23+F24+F25,"n.a.") -> -12800 | G26: =IFERROR(G22+G23+G24+G25,"n.a.") -> 5236 | H26: =IFERROR(H22+H23+H24+H25,"n.a.") -> -296471 | I26: =IFERROR(I22+I23+I24+I25,"n.a.") -> -174577 | K26: =IFERROR(K22+K23+K24+K25,"n.a.") -> -1060720 | L26: =IFERROR(L22+L23+L24+L25,"n.a.") -> -2127112 | M26: =IFERROR(M22+M23+M24+M25,"n.a.") -> -7564 | N26: =IFERROR(N22+N23+N24+N25,"n.a.") -> -471048 | P26: =IFERROR(P22+P23+P24+P25,"n.a.") -> -449813 | Q26: =IFERROR(Q22+Q23+Q24+Q25,"n.a.") -> -73267 | R26: =IFERROR(R22+R23+R24+R25,"n.a.") -> 530389 | S26: =IFERROR(S22+S23+S24+S25,"n.a.") -> 280294 | U26: =IFERROR(U22+U23+U24+U25,"n.a.") -> -325075 | V26: =IFERROR(V22+V23+V24+V25,"n.a.") -> -44781 | W26: =IFERROR(W22+W23+W24+W25,"n.a.") -> 28604 | X26: =IFERROR(X22+X23+X24+X25,"n.a.") -> 63825 | Y26: =IFERROR(Y22+Y23+Y24+Y25,"n.a.") -> -238402 | Z26: =IFERROR(Z22+Z23+Z24+Z25,"n.a.") -> 157044 | AA26: =IFERROR(AA22+AA23+AA24+AA25,"n.a.") -> 170592 | AB26: =IFERROR(AB22+AB23+AB24+AB25,"n.a.") -> 296772 | ... AY26: =IFERROR(AY22+AY23+AY24+AY25,"n.a.") -> 715724 | AZ26: 1163166 | BA26: 347616 | BB26: 993042 | BC26: 853398 | BD26: =IFERROR(BD22+BD23+BD24+BD25,"n.a.") -> -51067 | BE26: =IFERROR(BE22+BE23+BE24+BE25,"n.a.") -> 3240212 | BF26: =IFERROR(BF22+BF23+BF24+BF25,"n.a.") -> 3374309 | BG26: =IFERROR(BG22+BG23+BG24+BG25,"n.a.") -> 0 | BI26: =IFERROR(BI22+BI23+BI24+BI25,"n.a.") -> 739000 | BJ26: =IFERROR(BJ22+BJ23+BJ24+BJ25,"n.a.") -> 2077000 | BK26: =IFERROR(BK22+BK23+BK24+BK25,"n.a.") -> 263263 | BL26: =IFERROR(BL22+BL23+BL24+BL25,"n.a.") -> -471048 | BM26: =IFERROR(BM22+BM23+BM24+BM25,"n.a.") -> 684474 | BN26: =IFERROR(BN22+BN23+BN24+BN25,"n.a.") -> 197062 | BO26: =IFERROR(BO22+BO23+BO24+BO25,"n.a.") -> 604567 | BP26: =IFERROR(BP22+BP23+BP24+BP25,"n.a.") -> -151537
A27: Net provision for impairment loss on financial assets | AN27: -4474 | AO27: -10843 | AQ27: 4290 | AR27: -7189 | AS27: 2308 | AT27: 6431 | AU27: 8267 | AV27: 1382 | AW27: 1711 | AX27: -8844 | AY27: 8745 | AZ27: -17594 | BA27: 592 | BB27: -14683 | BC27: -5233
A28: Other income | F28: 4809 | G28: =M28-F28 -> 7996 | H28: 8700 | I28: =N28-H28 -> 24696 | K28: 49006 | L28: 10547 | M28: 12805 | N28: 33396 | P28: 3574 | Q28: 2097 | R28: 7583 | S28: 1001 | U28: 1291 | V28: =S28+U28 -> 2292 | W28: 7409 | X28: 9135 | Y28: 15561 | Z28: 4131 | AA28: 13667 | AB28: 25820 | AC28: 45002 | AD28: 11359 | AE28: 41784 | AF28: 25892 | AG28: 19829 | AH28: 21163 | AI28: 16808 | AJ28: 41044 | AK28: 18582 | AL28: 34679 | AM28: 44782 | AN28: 25595 | AO28: 48712 | AP28: 22656 | AQ28: 40408 | AR28: 27328 | AS28: 32391 | AT28: 14344 | AU28: 27708 | AV28: 37192 | AW28: 25013 | AX28: 17896 | AY28: 17399 | AZ28: 12577 | BA28: 56753 | BB28: 12544 | BC28: 42351 | BD28: 9701 | BE28: =BL28-BD28 -> 23695 | BK28: 20388 | BL28: 33396 | BM28: 88620 | BN28: 98864 | BO28: =SUM(AH28:AK28) -> 97597 | BP28: =SUM(AL28:AO28) -> 153768
A29: Other gains/(losses), net | F29: 3576 | G29: =M29-F29 -> 19034 | H29: 11932 | I29: =N29-H29 -> 35956 | K29: 51107 | L29: 4689 | M29: 22610 | N29: 47888 | P29: 516 | Q29: -1864 | R29: 31545 | S29: 4189 | U29: 3183 | V29: =S29+U29 -> 7372 | W29: 8749 | X29: 4748 | Y29: 31208 | Z29: 2870 | AA29: 7811 | AB29: -474 | AC29: -29780 | AD29: 9662 | AE29: -3991 | AF29: 6029 | AG29: 8851 | AH29: 437 | AI29: 21117 | AJ29: 18867 | AK29: 28815 | AL29: 27836 | AM29: -87654 | AN29: -126173 | AO29: 72450 | AP29: 62717 | AQ29: -80147 | AR29: 37262 | AS29: 43092 | AT29: 563 | AU29: -14569 | AV29: 32276 | AW29: -29525 | AX29: 31019 | AY29: 19240 | AZ29: 18722 | BA29: -442766 | BB29: 16772 | BC29: -10416 | BD29: 16121 | BE29: =BL29-BD29 -> 31767 | BK29: 54155 | BL29: 47888 | BM29: -19573 | BN29: 20551 | BO29: =SUM(AH29:AK29) -> 69236 | BP29: =SUM(AL29:AO29) -> -113541
A30: Finance income | F30: 2900 | G30: =M30-F30 -> 7245 | H30: 4514 | I30: =N30-H30 -> 8374 | K30: 9156 | L30: 8402 | M30: 10145 | N30: 12888 | P30: 2177 | Q30: 2732 | R30: 2955 | S30: 575 | U30: 1701 | V30: =S30+U30 -> 2276 | W30: 2813 | X30: 3919 | Y30: 4455 | Z30: 13987 | AA30: 10455 | AB30: 10791 | AC30: 11871 | AD30: 12222 | AE30: 10445 | AF30: 6123 | AG30: 8851 | AH30: 7844 | AI30: 9403 | AJ30: 12602 | AK30: 9126 | AL30: 7768 | AM30: 9678 | AN30: 19487 | AO30: 21040 | AP30: 27937 | AQ30: 41488 | AR30: 55954 | AS30: 49397 | AT30: 47775 | AU30: 55055 | AV30: 46841 | AW30: 44953 | AX30: 49051 | AY30: 43161 | AZ30: 45445 | BA30: 34071 | BB30: 23263 | BC30: 26467 | BD30: 5089 | BE30: =BL30-BD30 -> 7799 | BK30: 13100 | BL30: 12888 | BM30: 47104 | BN30: 37641 | BO30: =SUM(AH30:AK30) -> 38975 | BP30: =SUM(AL30:AO30) -> 57973
A31: Finance costs | F31: -420 | G31: =M31-F31 -> 257 | H31: -224 | I31: =N31-H31 -> -3112 | K31: -5831 | L31: -4114 | M31: -163 | N31: -3336 | P31: 0 | Q31: 0 | R31: 0 | S31: 0 | U31: -964 | V31: =S31+U31 -> -964 | W31: 740 | X31: -576 | Y31: -2536 | Z31: -2900 | AA31: -3829 | AB31: -2679 | AC31: -3021 | AD31: -2986 | AE31: -2592 | AF31: -3524 | AG31: -5680 | AH31: -4670 | AI31: -4661 | AJ31: -8190 | AK31: -8976 | AL31: -17091 | AM31: -23283 | AN31: -40895 | AO31: -55468 | AP31: -40172 | AQ31: -43215 | AR31: -38712 | AS31: -34951 | AT31: -56341 | AU31: -37929 | AV31: -60267 | AW31: -76358 | AX31: -73758 | AY31: -77710 | AZ31: -76462 | BA31: -116091 | BB31: -56362 | BC31: -57604 | BD31: -224 | BE31: =BL31-BD31 -> -3112 | BK31: -163 | BL31: =N31+S31 -> -3336 | BM31: -12429 | BN31: -14782 | BO31: =SUM(AH31:AK31) -> -26497 | BP31: =SUM(AL31:AO31) -> -136737
A32: Fair value change on investments measured at fair value through profit or loss | F32: -446 | G32: =M32-F32 -> 1309 | H32: 27428 | I32: =N32-H32 -> 51144 | K32: 17646 | L32: -4031 | M32: 863 | N32: 78572 | P32: 0 | Q32: 0 | R32: 0 | S32: 0 | U32: 8573 | V32: =S32+U32 -> 8573 | W32: 18855 | X32: 26807 | Y32: 24337 | Z32: 23407 | AA32: 26104 | AB32: 27666 | AC32: 28829 | AD32: -28865 | AE32: 18155 | AF32: 21689 | AG32: 54466 | AH32: 39307 | AI32: 17251 | AJ32: 38570 | AK32: 28762 | AL32: 3665 | AM32: 28759 | AN32: 11921 | AO32: 58092 | AP32: 25720 | AQ32: 32932 | AR32: 16331 | AS32: -107476 | AT32: 39174 | AU32: 19468 | AV32: 41971 | AW32: -73612 | AX32: 20833 | AY32: 48208 | AZ32: 48979 | BA32: 34143 | BB32: 24709 | BC32: 41526 | BD32: 27428 | BE32: =BL32-BD32 -> 51144 | BK32: 863 | BL32: =N32+S32 -> 78572 | BM32: 106006 | BN32: 65445 | BO32: =SUM(AH32:AK32) -> 123890 | BP32: =SUM(AL32:AO32) -> 102437
A33: Fair value change on redeemable convertible preferred shares measured at fair value through profit or loss | F33: -144664 | G33: =M33-F33 -> 242240 | H33: 907734 | I33: =N33-H33 -> 0 | K33: 0 | L33: -36781 | M33: 97576 | N33: 907734 | P33: 0 | Q33: 0 | R33: 0 | S33: 0 | U33: 907734 | V33: =S33+U33 -> 907734 | W33: 0 | X33: 0 | Y33: 0 | Z33: 0 | AA33: 0 | AB33: 0 | AC33: 0 | AD33: 0 | AE33: 0 | BD33: 907734 | BE33: =BL33-BD33 -> 0 | BK33: 97576 | BL33: =N33+S33 -> 907734 | BM33: 0 | BN33: 0 | BO33: =SUM(AH33:AK33) -> 0
A34: Share of results of associates | F34: -2583 | G34: =M34-F34 -> 332 | H34: -1718 | I34: =N34-H34 -> -2850 | K34: -18177 | L34: -11218 | M34: -2251 | N34: -4568 | P34: 0 | Q34: 0 | R34: 0 | S34: 0 | U34: 851 | V34: =S34+U34 -> 851 | W34: -2569 | X34: -136 | Y34: -2714 | Z34: -3061 | AA34: -3003 | AB34: -5841 | AC34: -786 | AD34: -5854 | AE34: -36 | AF34: 882 | AG34: -2196 | AH34: -7408 | AI34: -18133 | AJ34: -2735 | AK34: -4593 | AL34: 13679 | AM34: -19911 | AN34: -4257 | AO34: -3637 | AP34: -9089 | AQ34: 11139 | AR34: -18269 | AS34: -17183 | AT34: 5871 | AU34: 4977 | AV34: -8363 | AW34: 8114 | AX34: 12486 | AY34: 10978 | AZ34: 27757 | BA34: 4691 | BB34: -4875 | BC34: -13524 | BD34: -1718 | BE34: =BL34-BD34 -> -2850 | BK34: -2251 | BL34: =N34+S34 -> -4568 | BM34: -12691 | BN34: -7204 | BO34: =SUM(AH34:AK34) -> -32869 | BP34: =SUM(AL34:AO34) -> -14126
A35: (Loss)/profit before income tax | B35: =IFERROR(B26+B28+B29+B30+B31+B32+B33+B34,"n.a.") -> 0 | C35: =IFERROR(C26+C28+C29+C30+C31+C32+C33+C34,"n.a.") -> 0 | D35: =IFERROR(D26+D28+D29+D30+D31+D32+D33+D34,"n.a.") -> 0 | E35: =IFERROR(E26+E28+E29+E30+E31+E32+E33+E34,"n.a.") -> 0 | F35: =IFERROR(F26+F28+F29+F30+F31+F32+F33+F34,"n.a.") -> -149628 | G35: =IFERROR(G26+G28+G29+G30+G31+G32+G33+G34,"n.a.") -> 283649 | H35: =IFERROR(H26+H28+H29+H30+H31+H32+H33+H34,"n.a.") -> 661895 | I35: =IFERROR(I26+I28+I29+I30+I31+I32+I33+I34,"n.a.") -> -60369 | K35: =IFERROR(K26+K28+K29+K30+K31+K32+K33+K34,"n.a.") -> -957813 | L35: =IFERROR(L26+L28+L29+L30+L31+L32+L33+L34,"n.a.") -> -2159618 | M35: =IFERROR(M26+M28+M29+M30+M31+M32+M33+M34,"n.a.") -> 134021 | N35: =IFERROR(N26+N28+N29+N30+N31+N32+N33+N34,"n.a.") -> 601526 | P35: =IFERROR(P26+P28+P29+P30+P31+P32+P33+P34,"n.a.") -> -443546 | Q35: =IFERROR(Q26+Q28+Q29+Q30+Q31+Q32+Q33+Q34,"n.a.") -> -70302 | R35: =IFERROR(R26+R28+R29+R30+R31+R32+R33+R34,"n.a.") -> 572472 | S35: =IFERROR(S26+S28+S29+S30+S31+S32+S33+S34,"n.a.") -> 286059 | U35: =IFERROR(U26+U28+U29+U30+U31+U32+U33+U34,"n.a.") -> 597294 | V35: =IFERROR(V26+V28+V29+V30+V31+V32+V33+V34,"n.a.") -> 883353 | W35: =IFERROR(W26+W28+W29+W30+W31+W32+W33+W34,"n.a.") -> 64601 | X35: =IFERROR(X26+X28+X29+X30+X31+X32+X33+X34,"n.a.") -> 107722 | Y35: =IFERROR(Y26+Y28+Y29+Y30+Y31+Y32+Y33+Y34,"n.a.") -> -168091 | Z35: =IFERROR(Z26+Z28+Z29+Z30+Z31+Z32+Z33+Z34,"n.a.") -> 195478 | AA35: =IFERROR(AA26+AA28+AA29+AA30+AA31+AA32+AA33+AA34,"n.a.") -> 221797 | AB35: =IFERROR(AB26+AB28+AB29+AB30+AB31+AB32+AB33+AB34,"n.a.") -> 352055 | ... AL35: =IFERROR(AL26+AL28+AL29+AL30+AL31+AL32+AL33+AL34,"n.a.") -> 142176 | AM35: =IFERROR(AM26+AM27+AM28+AM29+AM30+AM31+AM32+AM33+AM34,"n.a.") -> -161968 | AN35: =IFERROR(AN26+AN27+AN28+AN29+AN30+AN31+AN32+AN33+AN34,"n.a.") -> -64711 | AO35: =IFERROR(AO26+AO27+AO28+AO29+AO30+AO31+AO32+AO33+AO34,"n.a.") -> -32577 | AP35: =IFERROR(AP26+AP27+AP28+AP29+AP30+AP31+AP32+AP33+AP34,"n.a.") -> 460988 | AQ35: =IFERROR(AQ26+AQ27+AQ28+AQ29+AQ30+AQ31+AQ32+AQ33+AQ34,"n.a.") -> 426553 | AR35: =IFERROR(AR26+AR27+AR28+AR29+AR30+AR31+AR32+AR33+AR34,"n.a.") -> 597856 | AS35: =IFERROR(AS26+AS27+AS28+AS29+AS30+AS31+AS32+AS33+AS34,"n.a.") -> 385183 | AT35: =IFERROR(AT26+AT27+AT28+AT29+AT30+AT31+AT32+AT33+AT34,"n.a.") -> 452330 | ... AY35: =IFERROR(AY26+AY27+AY28+AY29+AY30+AY31+AY32+AY33+AY34,"n.a.") -> 785745 | AZ35: 1159906 | BA35: 270287 | BB35: 955068 | BC35: 808737 | BD35: =IFERROR(BD26+BD28+BD29+BD30+BD31+BD32+BD33+BD34,"n.a.") -> 913064 | BE35: =IFERROR(BE26+BE28+BE29+BE30+BE31+BE32+BE33+BE34,"n.a.") -> 3348655 | BF35: =IFERROR(BF26+BF28+BF29+BF30+BF31+BF32+BF33+BF34,"n.a.") -> 3374309 | BG35: =IFERROR(BG26+BG28+BG29+BG30+BG31+BG32+BG33+BG34,"n.a.") -> 0 | BI35: =IFERROR(BI26+BI28+BI29+BI30+BI31+BI32+BI33+BI34,"n.a.") -> 739000 | BJ35: =IFERROR(BJ26+BJ28+BJ29+BJ30+BJ31+BJ32+BJ33+BJ34,"n.a.") -> 2077000 | BK35: =IFERROR(BK26+BK28+BK29+BK30+BK31+BK32+BK33+BK34,"n.a.") -> 446931 | BL35: =IFERROR(BL26+BL28+BL29+BL30+BL31+BL32+BL33+BL34,"n.a.") -> 601526 | BM35: =IFERROR(BM26+BM28+BM29+BM30+BM31+BM32+BM33+BM34,"n.a.") -> 881511 | BN35: =IFERROR(BN26+BN28+BN29+BN30+BN31+BN32+BN33+BN34,"n.a.") -> 397577 | BO35: =IFERROR(BO26+BO28+BO29+BO30+BO31+BO32+BO33+BO34,"n.a.") -> 874899 | BP35: =IFERROR(BP26+BP28+BP29+BP30+BP31+BP32+BP33+BP34,"n.a.") -> -101763
A36: Income tax (expense)/credit | F36: 39718 | G36: =M36-F36 -> 20638 | H36: -12510 | I36: =N36-H36 -> -54477 | K36: -5206 | L36: -978 | M36: 60356 | N36: -66987 | P36: 108437 | Q36: -20796 | R36: -81134 | S36: -61315 | U36: 84801 | V36: =S36+U36 -> 23486 | W36: -97311 | X36: -45827 | Y36: -8650 | Z36: -98038 | AA36: -23636 | AB36: -55441 | AC36: -17874 | AD36: -7899 | AE36: -1865 | AF36: -48541 | AG36: -13739 | AH36: -42045 | AI36: -30134 | AJ36: -55474 | AK36: -33721 | AL36: -44939 | AM36: 26764 | AN36: -29229 | AO36: 914 | AP36: -65129 | AQ36: -66572 | AR36: -82368 | AS36: -74057 | AT36: -52074 | AU36: -109798 | AV36: -152087 | AW36: -95601 | AX36: -126561 | AY36: -143640 | AZ36: -174658 | BA36: -167039 | BB36: -170839 | BC36: -175013 | BD36: -67704 | BE36: =BL36-BD36 -> 717 | BK36: 8027 | BL36: -66987 | BM36: -194989 | BN36: -72044 | BO36: =SUM(AH36:AK36) -> -161374 | BP36: =SUM(AL36:AO36) -> -46490
A37: Net income | V37: =V35+V36 -> 906839 | W37: =W35+W36 -> -32710 | X37: =X35+X36 -> 61895 | Y37: =Y35+Y36 -> -176741 | Z37: =Z35+Z36 -> 97440 | AA37: =AA35+AA36 -> 198161 | AB37: =AB35+AB36 -> 296614 | AC37: =AC35+AC36 -> 229805 | ... BC37: =BC35+BC36 -> 633724
A38: Other comprehensive income/(loss) | F38: -31448 | G38: =M38-F38 -> -15144 | H38: 932 | I38: =N38-H38 -> -15917 | K38: 0 | L38: 36781 | M38: -46592 | N38: -14985 | P38: 0 | Q38: 0 | R38: 0 | S38: 0 | U38: 0 | V38: =S38+U38 -> 0 | BD38: 932 | BE38: =BL38-BD38 -> -932
A39: Non-controlling interests | F39: -1510 | G39: =M39-F39 -> 312 | H39: -400 | I39: =N39-H39 -> 4982 | K39: -46753 | L39: -21329 | M39: -1198 | N39: 4582 | P39: 0 | Q39: 0 | R39: 0 | S39: 0 | U39: -374 | V39: =S39+U39 -> -374 | W39: -26 | X39: -440 | Y39: 5422 | Z39: 118 | AA39: -1119 | AB39: -152 | AC39: -423 | AD39: -1556 | AE39: 398 | AF39: 206 | AG39: -1108 | AH39: -420 | AI39: -117 | AJ39: -4958 | AK39: -4384 | AL39: -3907 | AM39: -3066 | AN39: -3552 | AO39: -7036 | AP39: 1056 | AQ39: 4061 | AR39: 5290 | AS39: 1025 | AT39: 3622 | AU39: -4361 | AV39: 10053 | AW39: 4596 | AX39: 9579 | AY39: 292 | AZ39: 9296 | BA39: 18701 | BB39: 4895 | BC39: 1813 | BD39: -400 | BE39: =BL39-BD39 -> 4982 | BK39: -1198 | BL39: =N39+S39 -> 4582 | BM39: -1575 | BN39: -2060 | BO39: =SUM(AH39:AK39) -> -9879 | BP39: =SUM(AL39:AO39) -> -17561
A40: (Loss)/profit attributable to equity holders of the Company | B40: =IFERROR(B35+B38+B36-B39,"n.a.") -> 0 | C40: =IFERROR(C35+C38+C36-C39,"n.a.") -> 0 | D40: =IFERROR(D35+D38+D36-D39,"n.a.") -> 0 | E40: =IFERROR(E35+E38+E36-E39,"n.a.") -> 0 | F40: =IFERROR(F35+F38+F36-F39,"n.a.") -> -139848 | G40: =IFERROR(G35+G38+G36-G39,"n.a.") -> 288831 | H40: =IFERROR(H35+H38+H36-H39,"n.a.") -> 650717 | I40: =IFERROR(I35+I38+I36-I39,"n.a.") -> -135745 | K40: =IFERROR(K35+K38+K36-K39,"n.a.") -> -916266 | L40: =IFERROR(L35+L38+L36-L39,"n.a.") -> -2102486 | M40: =IFERROR(M35+M38+M36-M39,"n.a.") -> 148983 | N40: =IFERROR(N35+N38+N36-N39,"n.a.") -> 514972 | P40: =IFERROR(P35+P38+P36-P39,"n.a.") -> -335109 | Q40: =IFERROR(Q35+Q38+Q36-Q39,"n.a.") -> -91098 | R40: =IFERROR(R35+R38+R36-R39,"n.a.") -> 491338 | S40: =IFERROR(S35+S38+S36-S39,"n.a.") -> 224744 | U40: =IFERROR(U35+U38+U36-U39,"n.a.") -> 682469 | V40: =IFERROR(V35+V38+V36-V39,"n.a.") -> 907213 | W40: =IFERROR(W35+W38+W36-W39,"n.a.") -> -32684 | X40: =IFERROR(X35+X38+X36-X39,"n.a.") -> 62335 | Y40: =IFERROR(Y35+Y38+Y36-Y39,"n.a.") -> -182163 | Z40: =IFERROR(Z35+Z38+Z36-Z39,"n.a.") -> 97322 | AA40: =IFERROR(AA35+AA38+AA36-AA39,"n.a.") -> 199280 | AB40: =IFERROR(AB35+AB38+AB36-AB39,"n.a.") -> 296766 | ... AY40: =IFERROR(AY35+AY38+AY36-AY39,"n.a.") -> 641813 | AZ40: 975952 | BA40: 84547 | BB40: 779334 | BC40: 631911 | BD40: =IFERROR(BD35+BD38+BD36-BD39,"n.a.") -> 846692 | BE40: =IFERROR(BE35+BE38+BE36-BE39,"n.a.") -> 3343458 | BF40: =IFERROR(BF35+BF38+BF36-BF39,"n.a.") -> 3374309 | BG40: =IFERROR(BG35+BG38+BG36-BG39,"n.a.") -> 0 | BI40: =IFERROR(BI35+BI38+BI36-BI39,"n.a.") -> 739000 | BJ40: =IFERROR(BJ35+BJ38+BJ36-BJ39,"n.a.") -> 2077000 | BK40: =IFERROR(BK35+BK38+BK36-BK39,"n.a.") -> 456156 | BL40: =IFERROR(BL35+BL38+BL36-BL39,"n.a.") -> 529957 | BM40: =IFERROR(BM35+BM38+BM36-BM39,"n.a.") -> 688097 | BN40: =IFERROR(BN35+BN38+BN36-BN39,"n.a.") -> 327593 | BO40: =IFERROR(BO35+BO38+BO36-BO39,"n.a.") -> 723404 | BP40: =IFERROR(BP35+BP38+BP36-BP39,"n.a.") -> -130692
A41: (Loss)/earnings per share -Basic (expressed in RMB per share) | F41: -4.16 | H41: 5.11 | K41: -12.5 | L41: -46.01 | M41: 0.75 | N41: 0.33 | BM41: 0.33 | BN41: 0.15
A42: (Loss)/earnings per share -Diluted (expressed in RMB per share) | F42: -4.16 | H42: -1.72 | K42: -12.5 | L42: -46.01 | M42: 0.11 | N42: -0.22 | BM42: 0.33 | BN42: 0.15
AD43: =AD45/Z45-1 -> -0.95231191
A44: Share-based compensation | F44: 9643 | G44: =M44-F44 -> 47140 | H44: 124857 | I44: =N44-H44 -> 447334 | K44: 211500 | L44: 72343 | M44: 56783 | N44: 572191 | U44: 47705 | W44: 77152 | X44: 179594 | Y44: 267740 | Z44: 285750 | AA44: 76106 | AB44: 54736 | AC44: 125618 | AD44: 65944 | AE44: 71749 | AF44: 55239 | AG44: 189215 | AH44: 57365 | AI44: 50202 | AJ44: 63505 | AK44: 158956 | AL44: 94914 | AM44: 101886 | AN44: 133825 | AO44: 110466 | AP44: 90659 | AQ44: 77954 | AR44: 62900 | AS44: 116623 | AT44: 114214 | AU44: 107910 | AV44: 112581 | AW44: 73624 | AX44: 75179 | AY44: 73878 | AZ44: 55694 | BA44: 347616 | BB44: 38478 | BC44: 43573 | BD44: 124857 | BK44: 56783 | BL44: 572191 | BM44: 542210 | BN44: 382147
A45: Adjusted EBIT | B45: =IFERROR(B26+B44,"n.a.") -> 0 | C45: =IFERROR(C26+C44,"n.a.") -> 0 | D45: =IFERROR(D26+D44,"n.a.") -> 0 | E45: =IFERROR(E26+E44,"n.a.") -> 0 | F45: =IFERROR(F26+F44,"n.a.") -> -3157 | G45: =IFERROR(G26+G44,"n.a.") -> 52376 | H45: =IFERROR(H26+H44,"n.a.") -> -171614 | I45: =IFERROR(I26+I44,"n.a.") -> 272757 | K45: =IFERROR(K26+K44,"n.a.") -> -849220 | L45: =IFERROR(L26+L44,"n.a.") -> -2054769 | M45: =IFERROR(M26+M44,"n.a.") -> 49219 | N45: =IFERROR(N26+N44,"n.a.") -> 101143 | U45: =IFERROR(U26+U44,"n.a.") -> -277370 | W45: =IFERROR(W26+W44,"n.a.") -> 105756 | X45: =IFERROR(X26+X44,"n.a.") -> 243419 | Y45: =IFERROR(Y26+Y44,"n.a.") -> 29338 | Z45: =IFERROR(Z26+Z44,"n.a.") -> 442794 | AA45: =IFERROR(AA26+AA44,"n.a.") -> 246698 | AB45: =IFERROR(AB26+AB44,"n.a.") -> 351508 | AC45: =IFERROR(AC26+AC44,"n.a.") -> 321182 | AD45: =IFERROR(AD26+AD44,"n.a.") -> 21116 | ... BG45: =IFERROR(BG26+BG44,"n.a.") -> 0 | BL45: =IFERROR(BL26+BL44,"n.a.") -> 101143 | BM45: =IFERROR(BM26+BM44,"n.a.") -> 1226684 | BN45: =IFERROR(BN26+BN44,"n.a.") -> 579209 | BO45: =IFERROR(BO26+BO44,"n.a.") -> 604567 | BP45: =IFERROR(BP26+BP44,"n.a.") -> -151537
A46: Depreciation of property, plant and equipment | F46: 23762 | G46: =M46-F46 -> 21315 | H46: 45363 | I46: =N46-H46 -> 71292 | K46: 52067 | L46: 52845 | M46: 45077 | N46: 116655 | U46: 13706 | W46: 31657 | X46: 32580 | Y46: 38712 | Z46: 40418 | AA46: 43348 | AB46: 40717 | AC46: 43637 | AD46: 42103 | AE46: 42928 | AF46: 47508 | AG46: 55029 | AH46: 40561 | AI46: 40962 | AJ46: 42734 | AK46: 45579 | AL46: 49862 | AM46: 51731 | AN46: 50759 | AO46: 48060 | AP46: 51516 | AQ46: 52977 | AR46: 57455 | AS46: 70193 | AT46: 81491 | AU46: 84815 | AV46: 93194 | AW46: 96320 | AX46: 90748 | AY46: 135807 | AZ46: 134565 | BA46: 138986 | BB46: 133038 | BC46: 130830 | BL46: 116655 | BM46: 168120 | BN46: 187568 | BO46: =SUM(AH46:AK46) -> 169836 | BP46: =SUM(AL46:AO46) -> 200412
A47: Amortization of intangible assets from acquisition | F47: 19536 | G47: =M47-F47 -> 19537 | H47: 137589 | I47: =N47-H47 -> 201448 | K47: 21225 | L47: 24488 | M47: 39073 | N47: 339037 | U47: 36616 | W47: 100973 | X47: 100763 | Y47: 100685 | Z47: 101950 | AA47: 102362 | AB47: 104645 | AC47: 104062 | AD47: 103527 | AE47: 103496 | AF47: 103524 | AG47: 103895 | AH47: 104011 | AI47: 104158 | AJ47: 139676 | AK47: 152161 | AL47: 156772 | AM47: 157155 | AN47: 159749 | AO47: 166100 | AP47: 167976 | AQ47: 168771 | AR47: 169090 | AS47: 172779 | AT47: 176678 | AU47: 170092 | AV47: 185842 | AW47: 194174 | AX47: 194828 | AY47: 195058 | AZ47: 194702 | BA47: 214510 | BB47: 216705 | BC47: 217114 | BD47: 130860 | BK47: 231105 | BL47: 339037 | BM47: 413019 | BN47: 414442 | BO47: =SUM(AH47:AK47) -> 500006 | BP47: =SUM(AL47:AO47) -> 639776
A48: Aquisition related cost | AA48: 0.546 | AG48: 405 | AJ48: 231 | AK48: 75 | BO48: =SUM(AH48:AK48) -> 306
A49: EBITDA | B49: =IFERROR(B26+B47,"n.a.") -> 0 | C49: =IFERROR(C26+C47,"n.a.") -> 0 | D49: =IFERROR(D26+D47,"n.a.") -> 0 | E49: =IFERROR(E26+E47,"n.a.") -> 0 | F49: =IFERROR(F26+F46+F47,"n.a.") -> 30498 | G49: =IFERROR(G26+G46+G47,"n.a.") -> 46088 | H49: =IFERROR(H26+H46+H47,"n.a.") -> -113519 | I49: =IFERROR(I26+I46+I47,"n.a.") -> 98163 | K49: =IFERROR(K26+K46+K47,"n.a.") -> -987428 | L49: =IFERROR(L26+L46+L47,"n.a.") -> -2049779 | M49: =IFERROR(M26+M46+M47,"n.a.") -> 76586 | N49: =IFERROR(N26+N46+N47,"n.a.") -> -15356 | U49: =IFERROR(U26+U46+U47,"n.a.") -> -274753 | W49: =IFERROR(W26+W46+W47,"n.a.") -> 161234 | X49: =IFERROR(X26+X46+X47,"n.a.") -> 197168 | Y49: =IFERROR(Y26+Y46+Y47,"n.a.") -> -99005 | Z49: =IFERROR(Z26+Z46+Z47,"n.a.") -> 299412 | AA49: =IFERROR(AA26+AA46+AA47,"n.a.") -> 316302 | AB49: =IFERROR(AB26+AB46+AB47,"n.a.") -> 442134 | AC49: =IFERROR(AC26+AC46+AC47,"n.a.") -> 343263 | AD49: =IFERROR(AD26+AD46+AD47,"n.a.") -> 100802 | ... AI49: =IFERROR(AI26+AI46+AI47,"n.a.") -> 424703 | AJ49: =IFERROR(AJ26+AJ46+AJ47+AJ48,"n.a.") -> 364273 | AK49: =IFERROR(AK26+AK46+AK47+AK48,"n.a.") -> 186667 | AL49: =IFERROR(AL26+AL46+AL47+AL48,"n.a.") -> 278274 | AM49: =IFERROR(AM26+AM46+AM47+AM48,"n.a.") -> 94547 | AN49: =IFERROR(AN26+AN46+AN47+AN48,"n.a.") -> 264593 | AO49: =IFERROR(AO26+AO46+AO47+AO48,"n.a.") -> 51237 | AP49: =IFERROR(AP26+AP46+AP47+AP48,"n.a.") -> 590711 | AQ49: =IFERROR(AQ26+AQ46+AQ47+AQ48,"n.a.") -> 641406 | ... BC49: =IFERROR(BC26+BC46+BC47+BC48,"n.a.") -> 1201342 | BD49: =IFERROR(BD26+BD46+BD47,"n.a.") -> 79793 | BE49: =IFERROR(BE26+BE47,"n.a.") -> 3240212 | BF49: =IFERROR(BF26+BF47,"n.a.") -> 3374309 | BG49: =IFERROR(BG26+BG47,"n.a.") -> 0 | BK49: =IFERROR(BK26+BK46+BK47,"n.a.") -> 494368 | BL49: =IFERROR(BL26+BL46+BL47,"n.a.") -> -15356 | BM49: =IFERROR(BM26+BM46+BM47,"n.a.") -> 1265613 | BN49: =IFERROR(BN26+BN46+BN47,"n.a.") -> 799072 | BO49: =IFERROR(BO26+BO46+BO47,"n.a.") -> 1274409 | BP49: =IFERROR(BP26+BP46+BP47,"n.a.") -> 688651
A50: Adjusted EBITDA | B50: =IFERROR(B49+B44,"n.a.") -> 0 | C50: =IFERROR(C49+C44,"n.a.") -> 0 | D50: =IFERROR(D49+D44,"n.a.") -> 0 | E50: =IFERROR(E49+E44,"n.a.") -> 0 | F50: =IFERROR(F49+F44,"n.a.") -> 40141 | G50: =IFERROR(G49+G44,"n.a.") -> 93228 | H50: =IFERROR(H49+H44,"n.a.") -> 11338 | I50: =IFERROR(I49+I44,"n.a.") -> 545497 | K50: =IFERROR(K49+K44,"n.a.") -> -775928 | L50: =IFERROR(L49+L44,"n.a.") -> -1977436 | M50: =IFERROR(M49+M44,"n.a.") -> 133369 | N50: =IFERROR(N49+N44,"n.a.") -> 556835 | U50: =IFERROR(U49+U44,"n.a.") -> -227048 | W50: =IFERROR(W49+W44,"n.a.") -> 238386 | X50: =IFERROR(X49+X44,"n.a.") -> 376762 | Y50: =IFERROR(Y49+Y44,"n.a.") -> 168735 | Z50: =IFERROR(Z49+Z44,"n.a.") -> 585162 | AA50: =IFERROR(AA49+AA44,"n.a.") -> 392408 | AB50: =IFERROR(AB49+AB44,"n.a.") -> 496870 | AC50: =IFERROR(AC49+AC44,"n.a.") -> 468881 | AD50: =IFERROR(AD49+AD44,"n.a.") -> 166746 | ... AY50: =IFERROR(AY49+AY44,"n.a.") -> 1120467 | AZ50: 1510264 | BA50: =IFERROR(BA49+BA44,"n.a.") -> 1048728 | BB50: =IFERROR(BB49+BB44,"n.a.") -> 1381263 | BC50: =IFERROR(BC49+BC44,"n.a.") -> 1244915 | BD50: =IFERROR(BD49+BD44,"n.a.") -> 204650 | BE50: =IFERROR(BE49+BE44,"n.a.") -> 3240212 | BF50: =IFERROR(BF49+BF44,"n.a.") -> 3374309 | BG50: =IFERROR(BG49+BG44,"n.a.") -> 0 | BI50: =IFERROR(BI49+BI44,"n.a.") -> 0 | BJ50: =IFERROR(BJ49+BJ44,"n.a.") -> 0 | BK50: =IFERROR(BK49+BK44,"n.a.") -> 551151 | BL50: =IFERROR(BL49+BL44,"n.a.") -> 556835 | BM50: =IFERROR(BM49+BM44,"n.a.") -> 1807823 | BN50: =IFERROR(BN49+BN44,"n.a.") -> 1181219 | BO50: =IFERROR(BO49+BO44,"n.a.") -> 1274409 | BP50: =IFERROR(BP49+BP44,"n.a.") -> 688651
A51: Adjusted EBITDA (Reported) | F51: 48080 | G51: =M51-F51 -> 121567 | H51: 442639 | I51: =N51-H51 -> 709495 | K51: -658169 | L51: -178856 | M51: 169647 | N51: 1152134 | U51: 129934 | V51: =Z51/1.34 -> 459380.6 | W51: 312705 | X51: 428471 | Y51: 281024 | Z51: 615570 | AA51: 440536 | AB51: 547317 | AC51: 415109 | AD51: 158902 | AE51: 267349 | AF51: 499283 | AG51: 440950 | AH51: 420024 | AI51: 549726 | AJ51: 517708 | AK51: 421782 | AL51: 438436 | AM51: 292234 | AN51: 462180 | AO51: 244324 | AP51: 732205 | AQ51: 805839 | AR51: 869999 | AS51: 715851 | AT51: 820228 | AU51: 913465 | AV51: 1318796 | AW51: 997667 | AX51: 1159384 | AY51: 1185177 | AZ51: 1510264 | BA51: 1282894 | BB51: 1389043 | BC51: 1271643 | BK51: 952054 | BL51: 1152134 | BM51: 2018532 | BN51: 1366484 | BO51: =SUM(AH51:AK51) -> 1909240 | BP51: =SUM(AL51:AO51) -> 1437174
Z52: =Z45/Z11 -> 0.24828489 | AA52: =AA45/AA11 -> 0.1550684 | AB52: =AB45/AB11 -> 0.1704587 | AC52: =AC45/AC11 -> 0.1641621 | AD52: =AD45/AD11 -> 0.02100852 | AE52: =AE45/AE11 -> 0.054142717 | AF52: =AF45/AF11 -> 0.15389827 | AG52: =AG45/AG11 -> 0.10948225 | ... AJ52: =AJ45/AJ11 -> 0.12639635 | AT52: =AT51/AT11 -> 0.21214926 | AU52: =AU51/AU11 -> 0.21516801 | AV52: =AV51/AV11 -> 0.26420857 | AW52: =AW51/AW11 -> 0.23543458 | AX52: =AX51/AX11 -> 0.26485483 | AY52: =AY51/AY11 -> 0.25381615 | AZ52: =AZ51/AZ11 -> 0.27413928 | BA52: =BA51/BA11 -> 0.26506162 | ... BC52: =BC51/BC11 -> 0.2549902 | BN52: =BN45/BN11 -> 0.097631709
A53: Balance Sheet
A54: ASSETS
A55: Cash and cash equivalents | H55: 2326321 | K55: 710403 | L55: 339299 | M55: 701748 | N55: 3143883 | P55: 243169 | Q55: 947340 | R55: 1268206 | S55: 941181 | U55: 2326321 | V55: 2326321 | Z55: 2326321 | BD55: 2326321
A56: Restricted cash | H56: 144409 | K56: 146480 | L56: 153606 | M56: 170541 | N56: 140930 | P56: 5740 | Q56: 7394 | R56: 18076 | S56: 11067 | U56: 144409 | V56: 144409 | Z56: 144409 | BD56: 144409
A57: Short-term investments measured at amortized cost | H57: 20099 | K57: 224507 | L57: 0 | M57: 0 | N57: 261086 | U57: 20099 | V57: 20099 | Z57: 20099 | BD57: 20099
A58: Short-term investments measured at fair value through profit or loss | H58: 1258721 | K58: 21046 | L58: 71041 | M58: 236107 | N58: 2570170 | P58: 0 | Q58: 35000 | R58: 204650 | S58: 537000 | U58: 1258721 | V58: 1258721 | Z58: 1258721 | BD58: 1258721
A59: Cash, Cash Equivalents and S-T investments | H59: =IFERROR(H58+H57+H56+H55,"n.a.") -> 3749550 | I59: =IFERROR(I58+I57+I56+I55,"n.a.") -> 0 | K59: =IFERROR(K58+K57+K56+K55,"n.a.") -> 1102436 | L59: =IFERROR(L58+L57+L56+L55,"n.a.") -> 563946 | M59: =IFERROR(M58+M57+M56+M55,"n.a.") -> 1108396 | N59: =IFERROR(N58+N57+N56+N55,"n.a.") -> 6116069 | P59: =IFERROR(P58+P57+P56+P55,"n.a.") -> 248909 | Q59: =IFERROR(Q58+Q57+Q56+Q55,"n.a.") -> 989734 | R59: =IFERROR(R58+R57+R56+R55,"n.a.") -> 1490932 | S59: =IFERROR(S58+S57+S56+S55,"n.a.") -> 1489248 | U59: =IFERROR(U58+U57+U56+U55,"n.a.") -> 3749550 | V59: =IFERROR(V58+V57+V56+V55,"n.a.") -> 3749550 | Z59: =IFERROR(Z58+Z57+Z56+Z55,"n.a.") -> 3749550 | BD59: =IFERROR(BD58+BD57+BD56+BD55,"n.a.") -> 3749550 | BE59: =IFERROR(BE58+BE57+BE56+BE55,"n.a.") -> 0 | BF59: =IFERROR(BF58+BF57+BF56+BF55,"n.a.") -> 0 | BG59: =IFERROR(BG58+BG57+BG56+BG55,"n.a.") -> 0 | BL59: =IFERROR(BL58+BL57+BL56+BL55,"n.a.") -> 0 | BM59: =IFERROR(BM58+BM57+BM56+BM55,"n.a.") -> 0
A60: Current assets | H60: 5035611 | M60: 1843551 | N60: 7496865 | P60: 674297 | Q60: 2466635 | R60: 2106004 | S60: 2173290 | U60: 5035611 | V60: 5035611 | Z60: 5035611 | BD60: 5035611
A61: Property, plant and equipment | H61: 782981 | K61: 98800 | L61: 101074 | M61: 441722 | N61: 934361 | P61: 93989 | Q61: 145596 | R61: 207777 | S61: 235527 | U61: 782981 | V61: 782981 | Z61: 782981 | BD61: 782981
A62: Total assets | H62: 14360623 | K62: 2256797 | L62: 2305809 | M62: 2768010 | N62: 16791343 | P62: 1638610 | Q62: 3340010 | R62: 2825322 | S62: 2896521 | U62: 14360623 | V62: 14360623 | Z62: 14360623 | BD62: 14360623
A63: LIABILITIES
A64: Borrowings (Short-term) | H64: 2312305 | K64: 658566 | L64: 921633 | M64: 19692 | N64: 19692 | U64: 2312305 | V64: 2312305 | Z64: 2312305 | BD64: 2312305
A65: Borrowings (Long-term) | H65: 162459 | K65: 0 | L65: 0 | M65: 172305 | N65: 152613 | U65: 162459 | V65: 162459 | Z65: 162459 | BD65: 162459
A66: Total liabilities | H66: 4484387 | K66: 1208410 | L66: 7837929 | M66: 8099944 | N66: 5263532 | P66: 372715 | Q66: 1221125 | R66: 1380355 | S66: 1226810 | U66: 4484387 | V66: 4484387 | Z66: 4484387 | BD66: 4484387
A67: EQUITY
A68: Total equity | H68: 9876236 | K68: 1048387 | L68: -5532120 | M68: -5331934 | N68: 11527811 | P68: 1265895 | Q68: 2118885 | R68: 1444967 | S68: 1669711 | U68: 9876236 | V68: 9876236 | Z68: 9876236 | BD68: 9876236
A69: Check | B69: =IF(B62=B66+B68,"","ERROR") | C69: =IF(C62=C66+C68,"","ERROR") | D69: =IF(D62=D66+D68,"","ERROR") | E69: =IF(E62=E66+E68,"","ERROR") | F69: =IF(F62=F66+F68,"","ERROR") | G69: =IF(G62=G66+G68,"","ERROR") | H69: =IF(BD62=BD66+BD68,"","ERROR") | I69: =IF(BE62=BE66+BE68,"","ERROR") | K69: =IF(K62=K66+K68,"","ERROR") | L69: =IF(L62=L66+L68,"","ERROR") | M69: =IF(M62=M66+M68,"","ERROR") | N69: =IF(N62=N66+N68,"","ERROR") | P69: =IF(P62=P66+P68,"","ERROR") | Q69: =IF(Q62=Q66+Q68,"","ERROR") | R69: =IF(R62=R66+R68,"","ERROR") | S69: =IF(S62=S66+S68,"","ERROR") | BE69: =IF(BE62=BE66+BE68,"","ERROR") | BF69: =IF(BF62=BF66+BF68,"","ERROR") | BG69: =IF(BG62=BG66+BG68,"","ERROR") | BL69: =IF(BL62=BL66+BL68,"","ERROR") | BM69: =IF(BM62=BM66+BM68,"","ERROR")
A71: Cash Flow
A72: Net cash (outflow)/inflow from operating activities | F72: 510155 | H72: 1066165 | K72: -776192 | L72: -410161 | M72: 719894 | N72: 2360953 | P72: 905264 | Q72: 372107 | R72: 1303940 | S72: 38047
A73: Net cash inflow/(outflow) from investing activities | F73: -38766 | H73: 374445 | K73: 1125147 | L73: 117400 | M73: -541955 | N73: -1400497 | P73: -669953 | Q73: -612024 | R73: 182182 | S73: -365072
A74: Net cash (outflow)/inflow from financing activities | F74: -4312 | H74: 174639 | K74: -61183 | L74: -79905 | M74: 185875 | N74: 1480861 | P74: -111440 | Q74: 944088 | R74: -1165256 | S74: 0
A76: YoY Growth
A77: GMV | D77: =IFERROR(D4/B4-1,"n.a.") -> n.a. | E77: =IFERROR(E4/C4-1,"n.a.") -> n.a. | F77: =IFERROR(F4/D4-1,"n.a.") -> n.a. | G77: =IFERROR(G4/E4-1,"n.a.") -> n.a. | H77: =IFERROR(H4/F4-1,"n.a.") -> n.a. | I77: =IFERROR(I4/G4-1,"n.a.") -> n.a. | L77: =IFERROR(L4/K4-1,"n.a.") -> 0.072590687 | M77: =IFERROR(M4/L4-1,"n.a.") -> 0.22914668 | Q77: =IFERROR(Q4/P4-1,"n.a.") -> n.a. | R77: =IFERROR(R4/Q4-1,"n.a.") -> n.a. | Z77: =IFERROR(Z4/V4-1,"n.a.") -> 0.23793103 | AA77: =IFERROR(AA4/W4-1,"n.a.") -> 0.42906574 | AB77: =IFERROR(AB4/X4-1,"n.a.") -> 0.2173913 | AC77: =IFERROR(AC4/Y4-1,"n.a.") -> 0.19710145 | AD77: =IFERROR(AD4/Z4-1,"n.a.") -> -0.49303621 | AE77: =IFERROR(AE4/AA4-1,"n.a.") -> -0.45762712 | AF77: =IFERROR(AF4/AB4-1,"n.a.") -> -0.16596639 | AG77: =IFERROR(AG4/AC4-1,"n.a.") -> -0.12590799 | ... AW77: =IFERROR(AW4/AS4-1,"n.a.") -> 0.022429907 | AX77: -0.02 | AY77: 0.01 | AZ77: 0.05 | BA77: 0.045 | BB77: 0.05 | BJ77: =IFERROR(BJ4/BI4-1,"n.a.") -> 0.84069614 | BK77: =IFERROR(BK4/BJ4-1,"n.a.") -> 0.50914809 | BL77: =IFERROR(BL4/BK4-1,"n.a.") -> 0.28526413 | BM77: =IFERROR(BM4/BL4-1,"n.a.") -> 0.26311787 | BN77: =IFERROR(BN4/BM4-1,"n.a.") -> -0.29921734 | BO77: =IFERROR(BO4/BN4-1,"n.a.") -> 0.29037801 | BP77: =IFERROR(BP4/BO4-1,"n.a.") -> -0.18308921
A78: GMV vs 2019 | AH78: =AH4/Z4-1 -> -0.072423398 | AI78: =AI4/AA4-1 -> 0.062953995 | AJ78: =AJ4/AB4-1 -> -0.13655462 | AK78: =AK4/AC4-1 -> -0.22760291 | AL78: =AL4/$Z$4-1 -> -0.097493036 | AM78: =AM4/$AA$4-1 -> -0.41162228 | AN78: =AN4/$AB$4-1 -> -0.14705882 | AO78: =AO4/$AC$4-1 -> -0.38498789 | AP78: =AP4/$AB$4-1 -> 0.20168067 | AQ78: =AQ4/$AB$4-1 -> 0.25420168 | AR78: =AR4/$AB$4-1 -> 0.49369748 | AS78: =AS4/$AB$4-1 -> 0.12394958 | AT78: =AT4/Z4-1 -> 0.8356546 | AU78: =AU4/AC4-1 -> 0.50847458 | AV78: =AV4/AB4-1 -> 0.52941176 | BO78: =IFERROR(BO4/BM4-1,"n.a.") -> -0.095725467 | BP78: =IFERROR(BP4/BM4-1,"n.a.") -> -0.26128838
A79: -Transportation ticketing | D79: =IFERROR(D5/B5-1,"n.a.") -> n.a. | E79: =IFERROR(E5/C5-1,"n.a.") -> n.a. | F79: =IFERROR(F5/D5-1,"n.a.") -> n.a. | G79: =IFERROR(G5/E5-1,"n.a.") -> n.a. | H79: =IFERROR(H5/F5-1,"n.a.") -> n.a. | I79: =IFERROR(I5/G5-1,"n.a.") -> n.a. | L79: =IFERROR(L5/K5-1,"n.a.") -> -0.34126197 | M79: =IFERROR(M5/L5-1,"n.a.") -> -0.17130063 | Q79: =IFERROR(Q5/P5-1,"n.a.") -> n.a. | R79: =IFERROR(R5/Q5-1,"n.a.") -> n.a. | Z79: =IFERROR(Z5/V5-1,"n.a.") -> n.a. | AA79: =IFERROR(AA5/W5-1,"n.a.") -> n.a. | AB79: =IFERROR(AB5/X5-1,"n.a.") -> n.a. | AC79: =IFERROR(AC5/Y5-1,"n.a.") -> n.a. | AD79: =IFERROR(AD5/Z5-1,"n.a.") -> -0.51179449 | AE79: =IFERROR(AE5/AA5-1,"n.a.") -> -0.48398644 | AF79: =IFERROR(AF5/AB5-1,"n.a.") -> -0.20245301 | AG79: =IFERROR(AG5/AC5-1,"n.a.") -> -0.20576798 | ... AT79: =IFERROR(AT5/AP5-1,"n.a.") -> 0.14615876 | BJ79: =IFERROR(BJ5/BI5-1,"n.a.") -> 1.2402134 | BK79: =IFERROR(BK5/BJ5-1,"n.a.") -> 0.58363665 | BM79: =IFERROR(BM5/BL5-1,"n.a.") -> n.a. | BN79: =IFERROR(BN5/BM5-1,"n.a.") -> -0.35801865 | BO79: =IFERROR(BO5/BN5-1,"n.a.") -> 0.29401759 | BP79: =IFERROR(BP5/BO5-1,"n.a.") -> -0.21059041
A80: -Accommodation | D80: =IFERROR(D6/B6-1,"n.a.") -> n.a. | E80: =IFERROR(E6/C6-1,"n.a.") -> n.a. | F80: =IFERROR(F6/D6-1,"n.a.") -> n.a. | G80: =IFERROR(G6/E6-1,"n.a.") -> n.a. | H80: =IFERROR(H6/F6-1,"n.a.") -> n.a. | I80: =IFERROR(I6/G6-1,"n.a.") -> n.a. | L80: =IFERROR(L6/K6-1,"n.a.") -> 0.18796537 | M80: =IFERROR(M6/L6-1,"n.a.") -> 0.29105074 | Q80: =IFERROR(Q6/P6-1,"n.a.") -> n.a. | R80: =IFERROR(R6/Q6-1,"n.a.") -> n.a. | Z80: =IFERROR(Z6/V6-1,"n.a.") -> n.a. | AA80: =IFERROR(AA6/W6-1,"n.a.") -> n.a. | AB80: =IFERROR(AB6/X6-1,"n.a.") -> n.a. | AC80: =IFERROR(AC6/Y6-1,"n.a.") -> n.a. | AD80: =IFERROR(AD6/Z6-1,"n.a.") -> -0.53314121 | AE80: =IFERROR(AE6/AA6-1,"n.a.") -> -0.37472509 | AF80: =IFERROR(AF6/AB6-1,"n.a.") -> -0.23465151 | AG80: =IFERROR(AG6/AC6-1,"n.a.") -> 0.021698113 | ... AT80: =IFERROR(AT6/AP6-1,"n.a.") -> 0.11369464 | BJ80: =IFERROR(BJ6/BI6-1,"n.a.") -> 0.20960512 | BK80: =IFERROR(BK6/BJ6-1,"n.a.") -> 0.29123071 | BM80: =IFERROR(BM6/BL6-1,"n.a.") -> n.a. | BN80: =IFERROR(BN6/BM6-1,"n.a.") -> -0.25823052 | BO80: =IFERROR(BO6/BN6-1,"n.a.") -> 0.48168524 | BP80: =IFERROR(BP6/BO6-1,"n.a.") -> -0.14122405
A82: Revenue | D82: =IFERROR(D11/B11-1,"n.a.") -> n.a. | E82: =IFERROR(E11/C11-1,"n.a.") -> n.a. | F82: =IFERROR(F11/D11-1,"n.a.") -> n.a. | G82: =IFERROR(G11/E11-1,"n.a.") -> n.a. | H82: =IFERROR(H11/F11-1,"n.a.") -> 0.6028428 | I82: =IFERROR(I11/G11-1,"n.a.") -> 1.5603817 | L82: =IFERROR(L11/K11-1,"n.a.") -> 1.1484392 | M82: =IFERROR(M11/L11-1,"n.a.") -> 0.14244352 | N82: =IFERROR(N11/M11-1,"n.a.") -> 1.0867378 | Q82: =IFERROR(Q11/P11-1,"n.a.") -> 1.4718349 | R82: =IFERROR(R11/Q11-1,"n.a.") -> 0.88681542 | Z82: =IFERROR(Z11/V11-1,"n.a.") -> 0.17522036 | AA82: =IFERROR(AA11/W11-1,"n.a.") -> 0.21028696 | AB82: =IFERROR(AB11/X11-1,"n.a.") -> 0.22280222 | AC82: =IFERROR(AC11/Y11-1,"n.a.") -> 0.2442734 | AD82: =IFERROR(AD11/Z11-1,"n.a.") -> -0.4364081 | AE82: =IFERROR(AE11/AA11-1,"n.a.") -> -0.2456424 | AF82: =IFERROR(AF11/AB11-1,"n.a.") -> -0.071582296 | AG82: =IFERROR(AG11/AC11-1,"n.a.") -> -0.073418101 | ... BC82: =IFERROR(BC11/AY11-1,"n.a.") -> 0.068015996 | BJ82: =IFERROR(BJ11/BI11-1,"n.a.") -> 1.2650902 | BK82: =IFERROR(BK11/BJ11-1,"n.a.") -> 0.43573901 | BL82: =IFERROR(BL11/BK11-1,"n.a.") -> 0.0056541315 | BM82: =IFERROR(BM11/BL11-1,"n.a.") -> 0.40666663 | BN82: =IFERROR(BN11/BM11-1,"n.a.") -> -0.19753205 | BO82: =IFERROR(BO11/BN11-1,"n.a.") -> 0.27053357 | BP82: =IFERROR(BP11/BO11-1,"n.a.") -> -0.12641896
A83: Revenue vs 2019 | AH83: =AH11/Z11-1 -> -0.095125577 | AI83: =AI11/AA11-1 -> 0.34388063 | AJ83: =AJ11/AB11-1 -> -0.059501098 | AK83: =AK11/AC11-1 -> -0.056278249 | AL83: =AL11/$Z$11-1 -> -0.036678029 | AM83: =AM11/$AA$11-1 -> -0.17112851 | AN83: =AN11/$AB$11-1 -> -0.0068759002 | AO83: =AO11/$AC$11-1 -> -0.23328834 | AP83: =AP11/$Z$11-1 -> 0.45011049 | AQ83: =AQ11/$AA$11-1 -> 0.80166736 | AR83: =AR11/$AB$11-1 -> 0.59994278 | AS83: =AS11/$AC$11-1 -> 0.60723396 | BO83: =IFERROR(BO11/BM11-1,"n.a.") -> 0.019562469 | BP83: =IFERROR(BP11/BM11-1,"n.a.") -> -0.10932956
A84: -Accommodation Reservation | D84: =IFERROR(D13/B13-1,"n.a.") -> n.a. | E84: =IFERROR(E13/C13-1,"n.a.") -> n.a. | F84: =IFERROR(F13/D13-1,"n.a.") -> n.a. | G84: =IFERROR(G13/E13-1,"n.a.") -> n.a. | H84: =IFERROR(H13/F13-1,"n.a.") -> -0.25015787 | I84: =IFERROR(I13/G13-1,"n.a.") -> -0.19945381 | L84: =IFERROR(L13/K13-1,"n.a.") -> 1.3071143 | M84: =IFERROR(M13/L13-1,"n.a.") -> 0.12777871 | N84: =IFERROR(N13/M13-1,"n.a.") -> -0.22495316 | Q84: =IFERROR(Q13/P13-1,"n.a.") -> n.a. | R84: =IFERROR(R13/Q13-1,"n.a.") -> n.a. | Z84: 0.42 | AA84: =IFERROR(AA13/W13-1,"n.a.") -> 0.2548358 | AB84: =IFERROR(AB13/X13-1,"n.a.") -> 0.34517434 | AC84: =IFERROR(AC13/Y13-1,"n.a.") -> 0.46638134 | AD84: =IFERROR(AD13/Z13-1,"n.a.") -> -0.53182573 | AE84: =IFERROR(AE13/AA13-1,"n.a.") -> -0.30551901 | AF84: =IFERROR(AF13/AB13-1,"n.a.") -> -0.013228375 | AG84: =IFERROR(AG13/AC13-1,"n.a.") -> 0.040875563 | AH84: =IFERROR(AH13/AD13-1,"n.a.") -> 1.0022226 | ... BC84: =IFERROR(BC13/AY13-1,"n.a.") -> 0.079692745 | BJ84: =IFERROR(BJ13/BI13-1,"n.a.") -> 1.2249489 | BK84: =IFERROR(BK13/BJ13-1,"n.a.") -> 0.21461397 | BL84: =IFERROR(BL13/BK13-1,"n.a.") -> -0.307465 | BM84: =IFERROR(BM13/BL13-1,"n.a.") -> 0.28833132 | BN84: =IFERROR(BN13/BM13-1,"n.a.") -> -0.17512657 | BO84: =IFERROR(BO13/BN13-1,"n.a.") -> 0.23832367 | BP84: =IFERROR(BP13/BO13-1,"n.a.") -> 0.0024984131
A85: -Accommodation Reservation vs 2019 | AH85: =AH13/Z13-1 -> -0.062610904 | AI85: =AI13/AA13-1 -> 0.3425112 | AJ85: =AJ13/AB13-1 -> -0.070337996 | AK85: =AK13/AC13-1 -> -0.095685062 | AL85: =AL13/$Z$13-1 -> 0.11022479 | AM85: =AM13/$AA$13-1 -> -0.017771433 | AN85: =AN13/$AB$13-1 -> 0.1801449 | AO85: =AO13/$AC$13-1 -> -0.18080027 | AP85: =AP13/$AC$13-1 -> 0.34155111 | AQ85: =AQ13/$AC$13-1 -> 0.69715195 | AR85: =AR13/$AC$13-1 -> 0.81294111 | AS85: =AS13/$AC$13-1 -> 0.41905211 | BO85: =IFERROR(BO13/BM13-1,"n.a.") -> 0.021460289 | BP85: =IFERROR(BP13/BM13-1,"n.a.") -> 0.024012318
A86: of which, Net commissions earned from accommodation reservation | D86: =IFERROR(D14/B14-1,"n.a.") -> n.a. | E86: =IFERROR(E14/C14-1,"n.a.") -> n.a. | F86: =IFERROR(F14/D14-1,"n.a.") -> n.a. | G86: =IFERROR(G14/E14-1,"n.a.") -> n.a. | H86: =IFERROR(H14/F14-1,"n.a.") -> -0.042528214 | I86: =IFERROR(I14/G14-1,"n.a.") -> -0.15485313 | L86: =IFERROR(L14/K14-1,"n.a.") -> 1.1209124 | M86: =IFERROR(M14/L14-1,"n.a.") -> 0.29086371 | N86: =IFERROR(N15/M14-1,"n.a.") -> 0.76760747 | Q86: =IFERROR(Q14/P14-1,"n.a.") -> n.a. | R86: =IFERROR(R14/Q14-1,"n.a.") -> n.a. | Z86: =IFERROR(Z14/V14-1,"n.a.") -> n.a. | AA86: =IFERROR(AA14/W14-1,"n.a.") -> n.a. | AB86: =IFERROR(AB14/X14-1,"n.a.") -> n.a. | AC86: =IFERROR(AC14/Y14-1,"n.a.") -> n.a. | AD86: =IFERROR(AD14/Z14-1,"n.a.") -> n.a. | AE86: =IFERROR(AE14/AA14-1,"n.a.") -> n.a. | AF86: =IFERROR(AF14/AB14-1,"n.a.") -> n.a. | AG86: =IFERROR(AG14/AC14-1,"n.a.") -> n.a. | ... AT86: =IFERROR(AT14/AP14-1,"n.a.") -> n.a. | BM86: =IFERROR(BM14/BL14-1,"n.a.") -> n.a. | BN86: =IFERROR(BN14/BM14-1,"n.a.") -> n.a. | BO86: =IFERROR(BO14/BN14-1,"n.a.") -> n.a. | BP86: =IFERROR(BP14/BO14-1,"n.a.") -> n.a.
A87: -Transportation Ticketing | D87: =IFERROR(D15/B15-1,"n.a.") -> n.a. | E87: =IFERROR(E15/C15-1,"n.a.") -> n.a. | F87: =IFERROR(F15/D15-1,"n.a.") -> n.a. | G87: =IFERROR(G15/E15-1,"n.a.") -> n.a. | H87: =IFERROR(H15/F15-1,"n.a.") -> 31.303593 | I87: =IFERROR(I15/G15-1,"n.a.") -> 74.236177 | L87: =IFERROR(L15/K15-1,"n.a.") -> -0.030522052 | M87: =IFERROR(M15/L15-1,"n.a.") -> -0.29261396 | N87: =IFERROR(N16/M15-1,"n.a.") -> 2.1445958 | Q87: =IFERROR(Q15/P15-1,"n.a.") -> n.a. | R87: =IFERROR(R15/Q15-1,"n.a.") -> n.a. | Z87: 0.3 | AA87: =AA15/W15-1 -> 0.12972476 | AB87: =AB15/X15-1 -> 0.01556922 | AC87: =AC15/Y15-1 -> 0.10187422 | AD87: =AD15/Z15-1 -> -0.45449057 | AE87: =AE15/AA15-1 -> -0.22545278 | AF87: =AF15/AB15-1 -> -0.07415009 | AG87: =AG15/AC15-1 -> -0.15107991 | AH87: =AH15/AD15-1 -> 0.4902063 | ... BC87: =BC15/AY15-1 -> -0.022753733 | BJ87: =IFERROR(BJ15/BI15-1,"n.a.") -> 1.3956594 | BK87: =IFERROR(BK15/BJ15-1,"n.a.") -> 0.7630662 | BL87: =IFERROR(BL15/BK15-1,"n.a.") -> 0.27767628 | BM87: =IFERROR(BM15/BL15-1,"n.a.") -> 0.39756493 | BN87: =IFERROR(BN15/BM15-1,"n.a.") -> -0.23165299 | BO87: =IFERROR(BO15/BN15-1,"n.a.") -> 0.28423259 | BP87: =IFERROR(BP15/BO15-1,"n.a.") -> -0.24200687
A88: -Transportation Ticketing vs 2019 | AH88: =AH15/Z15-1 -> -0.18707842 | AI88: =AI15/AA15-1 -> 0.3176401 | AJ88: =AJ15/AB15-1 -> -0.01307189 | AK88: =AK15/AC15-1 -> -0.090660129 | AL88: =AL15/$Z$15-1 -> -0.19200872 | AM88: =AM15/$AA$15-1 -> -0.33888988 | AN88: =AN15/$AB$15-1 -> -0.13423322 | AO88: =AO15/$AC$15-1 -> -0.36078687 | AP88: =AP15/$Z$15-1 -> 0.098293178 | AQ88: =AQ15/$AA$15-1 -> 0.59491491 | AR88: =AR15/$AC$15-1 -> 0.42127941 | AS88: =AS15/$AC$15-1 -> 0.24604631 | BO88: =IFERROR(BO15/BM15-1,"n.a.") -> -0.013263731 | BP88: =IFERROR(BP15/BM15-1,"n.a.") -> -0.25206069
A89: -Others | D89: =IFERROR(D16/B16-1,"n.a.") -> n.a. | E89: =IFERROR(E16/C16-1,"n.a.") -> n.a. | F89: =IFERROR(F16/D16-1,"n.a.") -> n.a. | G89: =IFERROR(G16/E16-1,"n.a.") -> n.a. | H89: =IFERROR(H16/F16-1,"n.a.") -> 1.6374049 | I89: =IFERROR(I16/G16-1,"n.a.") -> 0.78209122 | L89: =IFERROR(L16/K16-1,"n.a.") -> -0.17981235 | M89: =IFERROR(M16/L16-1,"n.a.") -> 3.0088414 | N89: =IFERROR(#REF!/M16-1,"n.a.") -> n.a. | Q89: =IFERROR(Q16/P16-1,"n.a.") -> n.a. | R89: =IFERROR(R16/Q16-1,"n.a.") -> n.a. | Z89: =IFERROR(Z16/V16-1,"n.a.") -> n.a. | AA89: =IFERROR(AA16/W16-1,"n.a.") -> 1.2822931 | AB89: =IFERROR(AB16/X16-1,"n.a.") -> 3.7145389 | AC89: =IFERROR(AC16/Y16-1,"n.a.") -> 1.0188749 | AD89: =IFERROR(AD16/Z16-1,"n.a.") -> 1.5307799 | AE89: =IFERROR(AE16/AA16-1,"n.a.") -> -0.10413556 | AF89: =IFERROR(AF16/AB16-1,"n.a.") -> -0.2357446 | AG89: =IFERROR(AG16/AC16-1,"n.a.") -> 0.062339075 | ... BC89: =IFERROR(BC16/AY16-1,"n.a.") -> 0.35738908 | BM89: =IFERROR(BM16/BL16-1,"n.a.") -> -0.42463597 | BN89: =IFERROR(BN16/BM16-1,"n.a.") -> -0.0016281512 | BO89: =IFERROR(BO16/BN16-1,"n.a.") -> 0.29978366 | BP89: =IFERROR(BP16/BO16-1,"n.a.") -> 0.17865711
A90: -Others vs 2019 | AH90: =AH16/Z16-1 -> 2.7338168 | AI90: =AI16/AA16-1 -> 0.59623081 | AJ90: =AJ16/AB16-1 -> -0.25792379 | AK90: =AK16/AC16-1 -> 0.37052931 | AL90: =AL16/$Z$16-1 -> 3.467492 | AM90: =AM16/$AA$16-1 -> 0.54912092 | AN90: =AN16/$AB$16-1 -> 0.06042234 | AO90: =AO16/$AC$16-1 -> 0.54021738 | AP90: =AP16/$Z$16-1 -> 9.4588799 | AQ90: =AQ16/$AA$16-1 -> 2.1488661 | AR90: =AR16/$AB$16-1 -> 1.1503455 | AS90: =AS16/$AB$16-1 -> 1.2814974 | BO90: =IFERROR(BO16/BM16-1,"n.a.") -> 0.29766741 | BP90: =IFERROR(BP16/BM16-1,"n.a.") -> 0.52950492
A91: Cost of revenue | D91: =IFERROR(D21/B21-1,"n.a.") -> n.a. | E91: =IFERROR(E21/C21-1,"n.a.") -> n.a. | F91: =IFERROR(F21/D21-1,"n.a.") -> n.a. | G91: =IFERROR(G21/E21-1,"n.a.") -> n.a. | H91: =IFERROR(H21/F21-1,"n.a.") -> 0.21242366 | I91: =IFERROR(I21/G21-1,"n.a.") -> 1.9931521 | L91: =IFERROR(L21/K21-1,"n.a.") -> 0.61462539 | M91: =IFERROR(M21/L21-1,"n.a.") -> -0.21408579 | N91: =IFERROR(N21/M21-1,"n.a.") -> 0.97160687 | Q91: =IFERROR(Q21/P21-1,"n.a.") -> 1.3207537 | R91: =IFERROR(R21/Q21-1,"n.a.") -> 0.61974384 | Z91: =IFERROR(Z21/V21-1,"n.a.") -> 0.19461134 | AA91: =IFERROR(AA21/W21-1,"n.a.") -> 0.51447517 | AB91: =IFERROR(AB21/X21-1,"n.a.") -> 0.42329259 | AC91: =IFERROR(AC21/Y21-1,"n.a.") -> 0.033541594 | AD91: =IFERROR(AD21/Z21-1,"n.a.") -> -0.29502679 | AE91: =IFERROR(AE21/AA21-1,"n.a.") -> -0.40756112 | AF91: =IFERROR(AF21/AB21-1,"n.a.") -> -0.21569015 | AG91: =IFERROR(AG21/AC21-1,"n.a.") -> -0.16946341 | ... BC91: =IFERROR(BC21/AY21-1,"n.a.") -> 0.01668923 | BL91: =IFERROR(BL21/BK21-1,"n.a.") -> -0.041945735 | BM91: =IFERROR(BM21/BL21-1,"n.a.") -> 0.44764522 | BN91: =IFERROR(BN21/BM21-1,"n.a.") -> -0.26774954 | BO91: =IFERROR(BO21/BN21-1,"n.a.") -> 0.11380073 | BP91: =IFERROR(BP21/BO21-1,"n.a.") -> -0.043944454
A92: Gross Profit | D92: =IFERROR(D22/B22-1,"n.a.") -> n.a. | E92: =IFERROR(E22/C22-1,"n.a.") -> n.a. | F92: =IFERROR(F22/D22-1,"n.a.") -> n.a. | G92: =IFERROR(G22/E22-1,"n.a.") -> n.a. | H92: =IFERROR(H22/F22-1,"n.a.") -> 0.83590259 | I92: =IFERROR(I22/G22-1,"n.a.") -> 1.3987556 | L92: =IFERROR(L22/K22-1,"n.a.") -> 2.0322178 | M92: =IFERROR(M22/L22-1,"n.a.") -> 0.45675508 | N92: =IFERROR(N22/M22-1,"n.a.") -> 1.1414955 | Q92: =IFERROR(Q22/P22-1,"n.a.") -> 1.5698777 | R92: =IFERROR(R22/Q22-1,"n.a.") -> 1.0433282 | Z92: =IFERROR(Z22/V22-1,"n.a.") -> 0.16787046 | AA92: =IFERROR(AA22/W22-1,"n.a.") -> 0.090883088 | AB92: =IFERROR(AB22/X22-1,"n.a.") -> 0.14313745 | AC92: =IFERROR(AC22/Y22-1,"n.a.") -> 0.35966356 | AD92: =IFERROR(AD22/Z22-1,"n.a.") -> -0.49122392 | AE92: =IFERROR(AE22/AA22-1,"n.a.") -> -0.15740412 | AF92: =IFERROR(AF22/AB22-1,"n.a.") -> -0.00028776457 | AG92: =IFERROR(AG22/AC22-1,"n.a.") -> -0.033440996 | ... BC92: =IFERROR(BC22/AY22-1,"n.a.") -> 0.095623529 | BL92: =IFERROR(BL22/BK22-1,"n.a.") -> 0.028019383 | BM92: =IFERROR(BM22/BL22-1,"n.a.") -> 0.38872285 | BN92: =IFERROR(BN22/BM22-1,"n.a.") -> -0.16548052 | BO92: =IFERROR(BO22/BN22-1,"n.a.") -> 0.33330855 | BP92: =IFERROR(BP22/BO22-1,"n.a.") -> -0.1540135
A93: Service development expenses | D93: =IFERROR(D23/B23-1,"n.a.") -> n.a. | E93: =IFERROR(E23/C23-1,"n.a.") -> n.a. | F93: =IFERROR(F23/D23-1,"n.a.") -> n.a. | G93: =IFERROR(G23/E23-1,"n.a.") -> n.a. | H93: =IFERROR(H23/F23-1,"n.a.") -> 1.064754 | I93: =IFERROR(I23/G23-1,"n.a.") -> 2.0484821 | L93: =IFERROR(L23/K23-1,"n.a.") -> 0.29712609 | M93: =IFERROR(M23/L23-1,"n.a.") -> 0.0084420301 | N93: =IFERROR(N23/M23-1,"n.a.") -> 1.5859932 | Q93: =IFERROR(Q23/P23-1,"n.a.") -> 1.2627635 | R93: =IFERROR(R23/Q23-1,"n.a.") -> 0.38491338 | Z93: =IFERROR(Z23/V23-1,"n.a.") -> 0.39771582 | AA93: =IFERROR(AA23/W23-1,"n.a.") -> 0.10914646 | AB93: =IFERROR(AB23/X23-1,"n.a.") -> -0.10996266 | AC93: =IFERROR(AC23/Y23-1,"n.a.") -> -0.15519433 | AD93: =IFERROR(AD23/Z23-1,"n.a.") -> -0.33159478 | AE93: =IFERROR(AE23/AA23-1,"n.a.") -> -0.14706918 | AF93: =IFERROR(AF23/AB23-1,"n.a.") -> -0.15922037 | AG93: =IFERROR(AG23/AC23-1,"n.a.") -> -0.042336756 | ... BC93: =IFERROR(BC23/AY23-1,"n.a.") -> 0.046873885 | BI93: =AH23/AG23-1 -> -0.13743326 | BL93: =IFERROR(BL23/BK23-1,"n.a.") -> 0.13296249 | BM93: =IFERROR(BM23/BL23-1,"n.a.") -> 0.12064062 | BN93: =IFERROR(BN23/BM23-1,"n.a.") -> -0.17668391 | BO93: =IFERROR(BO23/BN23-1,"n.a.") -> 0.079455258 | BP93: =IFERROR(BP23/BO23-1,"n.a.") -> 0.051816778
A94: Selling and marketing expenses | D94: =IFERROR(D24/B24-1,"n.a.") -> n.a. | E94: =IFERROR(E24/C24-1,"n.a.") -> n.a. | F94: =IFERROR(F24/D24-1,"n.a.") -> n.a. | G94: =IFERROR(G24/E24-1,"n.a.") -> n.a. | H94: =IFERROR(H24/F24-1,"n.a.") -> 0.37918392 | I94: =IFERROR(I24/G24-1,"n.a.") -> 0.94715935 | L94: =IFERROR(L24/K24-1,"n.a.") -> 1.4279386 | M94: =IFERROR(M24/L24-1,"n.a.") -> -0.4184251 | N94: =IFERROR(N24/M24-1,"n.a.") -> 0.68160062 | Q94: =IFERROR(Q24/P24-1,"n.a.") -> -0.11293744 | R94: =IFERROR(R24/Q24-1,"n.a.") -> 0.30195235 | Z94: =IFERROR(Z24/V24-1,"n.a.") -> 0.087780037 | AA94: =IFERROR(AA24/W24-1,"n.a.") -> -0.12262334 | AB94: =IFERROR(AB24/X24-1,"n.a.") -> 0.089131163 | AC94: =IFERROR(AC24/Y24-1,"n.a.") -> 0.14493399 | AD94: =IFERROR(AD24/Z24-1,"n.a.") -> -0.38007294 | AE94: =IFERROR(AE24/AA24-1,"n.a.") -> -0.092581541 | AF94: =IFERROR(AF24/AB24-1,"n.a.") -> 0.15516002 | AG94: =IFERROR(AG24/AC24-1,"n.a.") -> 0.1650113 | ... BC94: =IFERROR(BC24/AY24-1,"n.a.") -> 0.058040346 | BI94: =AH24/AG24-1 -> -0.17110326 | BL94: =IFERROR(BL24/BK24-1,"n.a.") -> 0.021221819 | BM94: =IFERROR(BM24/BL24-1,"n.a.") -> 0.21897514 | BN94: =IFERROR(BN24/BM24-1,"n.a.") -> -0.050451857 | BO94: =IFERROR(BO24/BN24-1,"n.a.") -> 0.42471271 | BP94: =IFERROR(BP24/BO24-1,"n.a.") -> -0.077462674
A95: Administrative expenses | D95: =IFERROR(D25/B25-1,"n.a.") -> n.a. | E95: =IFERROR(E25/C25-1,"n.a.") -> n.a. | F95: =IFERROR(F25/D25-1,"n.a.") -> n.a. | G95: =IFERROR(G25/E25-1,"n.a.") -> n.a. | H95: =IFERROR(H25/F25-1,"n.a.") -> 13.515011 | I95: =IFERROR(I25/G25-1,"n.a.") -> 5.776529 | L95: =IFERROR(L25/K25-1,"n.a.") -> 2.2956336 | M95: =IFERROR(M25/L25-1,"n.a.") -> -0.89160081 | N95: =IFERROR(N25/M25-1,"n.a.") -> 8.6008893 | Q95: =IFERROR(Q25/P25-1,"n.a.") -> 0.6033609 | R95: =IFERROR(R25/Q25-1,"n.a.") -> 0.45712749 | Z95: =IFERROR(Z25/V25-1,"n.a.") -> -0.43720775 | AA95: =IFERROR(AA25/W25-1,"n.a.") -> -0.25378881 | AB95: =IFERROR(AB25/X25-1,"n.a.") -> -0.41110622 | AC95: =IFERROR(AC25/Y25-1,"n.a.") -> -0.31807208 | AD95: =IFERROR(AD25/Z25-1,"n.a.") -> -0.47427756 | AE95: =IFERROR(AE25/AA25-1,"n.a.") -> 1.049727 | AF95: =IFERROR(AF25/AB25-1,"n.a.") -> 0.17408331 | AG95: =IFERROR(AG25/AC25-1,"n.a.") -> 0.28817829 | ... BC95: =IFERROR(BC25/AY25-1,"n.a.") -> 0.38871327 | BI95: =AH25/AG25-1 -> -0.44252021 | BL95: =IFERROR(BL25/BK25-1,"n.a.") -> 2.1406942 | BM95: =IFERROR(BM25/BL25-1,"n.a.") -> -0.32168356 | BN95: =IFERROR(BN25/BM25-1,"n.a.") -> 0.044098238 | BO95: =IFERROR(BO25/BN25-1,"n.a.") -> 0.00036699132 | BP95: =IFERROR(BP25/BO25-1,"n.a.") -> 0.078203882
A96: Operating Profit/(Loss) | D96: =IFERROR(D26/B26-1,"n.a.") -> n.a. | E96: =IFERROR(E26/C26-1,"n.a.") -> n.a. | F96: =IFERROR(F26/D26-1,"n.a.") -> n.a. | G96: =IFERROR(G26/E26-1,"n.a.") -> n.a. | H96: =IFERROR(H26/F26-1,"n.a.") -> 22.161797 | I96: =IFERROR(I26/G26-1,"n.a.") -> -34.341673 | L96: =IFERROR(L26/K26-1,"n.a.") -> 1.0053473 | M96: =IFERROR(M26/L26-1,"n.a.") -> -0.996444 | N96: =IFERROR(N26/M26-1,"n.a.") -> 61.274987 | Q96: =IFERROR(Q26/P26-1,"n.a.") -> -0.83711676 | R96: =IFERROR(R26/Q26-1,"n.a.") -> -8.2391254 | Z96: =IFERROR(Z26/V26-1,"n.a.") -> -4.5069337 | AA96: =IFERROR(AA26/W26-1,"n.a.") -> 4.9639211 | AB96: =IFERROR(AB26/X26-1,"n.a.") -> 3.6497767 | AC96: =IFERROR(AC26/Y26-1,"n.a.") -> -1.8203119 | AD96: =IFERROR(AD26/Z26-1,"n.a.") -> -1.2854487 | AE96: =IFERROR(AE26/AA26-1,"n.a.") -> -1.0396971 | AF96: =IFERROR(AF26/AB26-1,"n.a.") -> -0.19331339 | AG96: =IFERROR(AG26/AC26-1,"n.a.") -> -0.95264977 | ... BC96: =IFERROR(BC26/AY26-1,"n.a.") -> 0.19235627 | BL96: =IFERROR(BL26/BK26-1,"n.a.") -> -2.7892678 | BM96: =IFERROR(BM26/BL26-1,"n.a.") -> -2.4530876 | BN96: =IFERROR(BN26/BM26-1,"n.a.") -> -0.71209717 | BO96: =IFERROR(BO26/BN26-1,"n.a.") -> 2.0679025 | BP96: =IFERROR(BP26/BO26-1,"n.a.") -> -1.2506538
A97: (Loss)/profit attributable to quity holders of the Company | D97: =IFERROR(D40/B40-1,"n.a.") -> n.a. | E97: =IFERROR(E40/C40-1,"n.a.") -> n.a. | F97: =IFERROR(F40/D40-1,"n.a.") -> n.a. | G97: =IFERROR(G40/E40-1,"n.a.") -> n.a. | H97: =IFERROR(H40/F40-1,"n.a.") -> -5.6530304 | I97: =IFERROR(I40/G40-1,"n.a.") -> -1.4699807 | L97: =IFERROR(L40/K40-1,"n.a.") -> 1.2946241 | M97: =IFERROR(M40/L40-1,"n.a.") -> -1.0708604 | N97: =IFERROR(N40/M40-1,"n.a.") -> 2.4565823 | Q97: =IFERROR(Q40/P40-1,"n.a.") -> -0.72815412 | R97: =IFERROR(R40/Q40-1,"n.a.") -> -6.3935103 | Z97: =IFERROR(Z40/V40-1,"n.a.") -> -0.8927242 | AA97: =IFERROR(AA40/W40-1,"n.a.") -> -7.0971729 | AB97: =IFERROR(AB40/X40-1,"n.a.") -> 3.7608246 | AC97: =IFERROR(AC40/Y40-1,"n.a.") -> -2.2638571 | AD97: =IFERROR(AD40/Z40-1,"n.a.") -> -1.5716385 | AE97: =IFERROR(AE40/AA40-1,"n.a.") -> -0.7253613 | AF97: =IFERROR(AF40/AB40-1,"n.a.") -> -0.16518065 | AG97: =IFERROR(AG40/AC40-1,"n.a.") -> -0.64926073 | ... BA97: =IFERROR(BA40/AW40-1,"n.a.") -> -0.75902237 | BB97: =IFERROR(BB40/AX39-1,"n.a.") -> 80.358597 | BC97: =IFERROR(BC40/AY40-1,"n.a.") -> -0.01542817 | BL97: =IFERROR(BL40/BK40-1,"n.a.") -> 0.16178895 | BM97: =IFERROR(BM40/BL40-1,"n.a.") -> 0.29840157 | BN97: =IFERROR(BN40/BM40-1,"n.a.") -> -0.52391451 | BO97: =IFERROR(BO40/BN40-1,"n.a.") -> 1.2082401 | BP97: =IFERROR(BP40/BO40-1,"n.a.") -> -1.1806625
A98: (Loss)/earnings per share -Basic (expressed in RMB per share) | D98: =IFERROR(D41/B41-1,"n.a.") -> n.a. | E98: =IFERROR(E41/C41-1,"n.a.") -> n.a. | F98: =IFERROR(F41/D41-1,"n.a.") -> n.a. | G98: =IFERROR(G41/E41-1,"n.a.") -> n.a. | H98: =IFERROR(H41/F41-1,"n.a.") -> -2.2283654 | I98: =IFERROR(I41/G41-1,"n.a.") -> n.a. | L98: =IFERROR(L41/K41-1,"n.a.") -> 2.6808 | M98: =IFERROR(M41/L41-1,"n.a.") -> -1.0163008 | N98: =IFERROR(N41/M41-1,"n.a.") -> -0.56 | Q98: =IFERROR(Q41/P41-1,"n.a.") -> n.a. | R98: =IFERROR(R41/Q41-1,"n.a.") -> n.a. | Z98: =IFERROR(Z41/V41-1,"n.a.") -> n.a. | AA98: =IFERROR(AA41/W41-1,"n.a.") -> n.a. | AB98: =IFERROR(AB41/X41-1,"n.a.") -> n.a. | AC98: =IFERROR(AC41/Y41-1,"n.a.") -> n.a. | AD98: =IFERROR(AD41/Z41-1,"n.a.") -> n.a. | AE98: =IFERROR(AE41/AA41-1,"n.a.") -> n.a. | AF98: =IFERROR(AF41/AB41-1,"n.a.") -> n.a. | AG98: =IFERROR(AG41/AC41-1,"n.a.") -> n.a. | ... AY98: =IFERROR(AY41/AU41-1,"n.a.") -> n.a. | BJ98: =IFERROR(BJ41/BI41-1,"n.a.") -> n.a. | BK98: =IFERROR(BK41/BJ41-1,"n.a.") -> n.a. | BL98: =IFERROR(BL41/BK41-1,"n.a.") -> n.a. | BM98: =IFERROR(BM41/BL41-1,"n.a.") -> n.a. | BN98: =IFERROR(BN41/BM41-1,"n.a.") -> -0.54545455 | BP98: =IFERROR(BP41/BO41-1,"n.a.") -> n.a.
A99: (Loss)/earnings per share -Diluted (expressed in RMB per share) | D99: =IFERROR(D42/B42-1,"n.a.") -> n.a. | E99: =IFERROR(E42/C42-1,"n.a.") -> n.a. | F99: =IFERROR(F42/D42-1,"n.a.") -> n.a. | G99: =IFERROR(G42/E42-1,"n.a.") -> n.a. | H99: =IFERROR(H42/F42-1,"n.a.") -> -0.58653846 | I99: =IFERROR(I42/G42-1,"n.a.") -> n.a. | L99: =IFERROR(L42/K42-1,"n.a.") -> 2.6808 | M99: =IFERROR(M42/L42-1,"n.a.") -> -1.0023908 | N99: =IFERROR(N42/M42-1,"n.a.") -> -3 | Q99: =IFERROR(Q42/P42-1,"n.a.") -> n.a. | R99: =IFERROR(R42/Q42-1,"n.a.") -> n.a. | Z99: =IFERROR(Z42/V42-1,"n.a.") -> n.a. | AA99: =IFERROR(AA42/W42-1,"n.a.") -> n.a. | AB99: =IFERROR(AB42/X42-1,"n.a.") -> n.a. | AC99: =IFERROR(AC42/Y42-1,"n.a.") -> n.a. | AD99: =IFERROR(AD42/Z42-1,"n.a.") -> n.a. | AE99: =IFERROR(AE42/AA42-1,"n.a.") -> n.a. | AF99: =IFERROR(AF42/AB42-1,"n.a.") -> n.a. | AG99: =IFERROR(AG42/AC42-1,"n.a.") -> n.a. | ... AY99: =IFERROR(AY42/AU42-1,"n.a.") -> n.a. | BJ99: =IFERROR(BJ42/BI42-1,"n.a.") -> n.a. | BK99: =IFERROR(BK42/BJ42-1,"n.a.") -> n.a. | BL99: =IFERROR(BL42/BK42-1,"n.a.") -> n.a. | BM99: =IFERROR(BM42/BL42-1,"n.a.") -> n.a. | BN99: =IFERROR(BN42/BM42-1,"n.a.") -> -0.54545455 | BP99: =IFERROR(BP42/BO42-1,"n.a.") -> n.a.
A100: Adjusted EBIT | D100: =IFERROR(D45/B45-1,"n.a.") -> n.a. | E100: =IFERROR(E45/C45-1,"n.a.") -> n.a. | F100: =IFERROR(F45/D45-1,"n.a.") -> n.a. | G100: =IFERROR(G45/E45-1,"n.a.") -> n.a. | H100: =IFERROR(H45/F45-1,"n.a.") -> 53.359835 | I100: =IFERROR(I45/G45-1,"n.a.") -> 4.2076715 | L100: =IFERROR(L45/K45-1,"n.a.") -> 1.4195956 | M100: =IFERROR(M45/L45-1,"n.a.") -> -1.0239535 | N100: =IFERROR(N45/M45-1,"n.a.") -> 1.0549585 | Q100: =IFERROR(Q45/P45-1,"n.a.") -> n.a. | R100: =IFERROR(R45/Q45-1,"n.a.") -> n.a. | Z100: =IFERROR(Z45/V45-1,"n.a.") -> n.a. | AA100: =IFERROR(AA45/W45-1,"n.a.") -> 1.3327093 | AB100: =IFERROR(AB45/X45-1,"n.a.") -> 0.44404504 | AC100: =IFERROR(AC45/Y45-1,"n.a.") -> 9.9476447 | AD100: =IFERROR(AD45/Z45-1,"n.a.") -> -0.95231191 | AE100: =IFERROR(AE45/AA45-1,"n.a.") -> -0.73661319 | AF100: =IFERROR(AF45/AB45-1,"n.a.") -> -0.1617801 | AG100: =IFERROR(AG45/AC45-1,"n.a.") -> -0.38204818 | ... BA100: =IFERROR(BA45/AW45-1,"n.a.") -> 0.11348468 | BB100: =IFERROR(BB45/AX44-1,"n.a.") -> 12.720853 | BC100: =IFERROR(BC45/AY45-1,"n.a.") -> 0.13597863 | BJ100: =IFERROR(BJ45/BI45-1,"n.a.") -> n.a. | BK100: =IFERROR(BK45/BJ45-1,"n.a.") -> n.a. | BL100: =IFERROR(BL45/BK45-1,"n.a.") -> n.a. | BM100: =IFERROR(BM45/BL45-1,"n.a.") -> 11.128215 | BN100: =IFERROR(BN45/BM45-1,"n.a.") -> -0.52782542 | BO100: =IFERROR(BO45/BN45-1,"n.a.") -> 0.043780397 | BP100: =IFERROR(BP45/BO45-1,"n.a.") -> -1.2506538
A101: Adjusted EBIT vs 2019 | AH101: =AH45/Z45-1 -> -0.52152694 | AI101: =AI45/AA45-1 -> 0.33679641 | AJ101: =AJ45/AB45-1 -> -0.30261331 | AK101: =AK45/AC45-1 -> -0.53979986 | AL101: =AL45/$Z$45-1 -> -0.62385669 | AM101: =AM45/$AA$45-1 -> -1.0504787 | AN101: =AN45/$AB$45-1 -> -0.46541757 | AO101: =AO45/$AC$45-1 -> -1.1633248 | AP101: =AP45/$Z$45-1 -> 0.043099048 | AQ101: =AQ45/$AA$45-1 -> 1.0170897 | AR101: =AR45/$AB$45-1 -> 0.67293774 | AS101: =AS45/$AB$45-1 -> 0.51981747 | AT101: =AT45/$Z$45-1 -> 0.1489022 | AU101: =AU45/$AA$45-1 -> 1.3675141 | AV101: =AV45/$AB$45-1 -> 1.7790833 | AW101: =AW45/$AC$45-1 -> 0.94399126 | AX101: =AX45/$AB$45-1 -> 1.3656873 | AY101: =AY45/$AA$45-1 -> 2.2006826 | AZ101: =AZ45/AB$45-1 -> 2.4675171 | BA101: =BA45/AC$45-1 -> 1.1646045 | BB101: =BB45/Z$44-1 -> 2.6098688 | BC101: =BC45/$AA$45-1 -> 2.6359071
A102: EBITDA | D102: =IFERROR(D49/B49-1,"n.a.") -> n.a. | E102: =IFERROR(E49/C49-1,"n.a.") -> n.a. | F102: =IFERROR(F49/D49-1,"n.a.") -> n.a. | G102: =IFERROR(G49/E49-1,"n.a.") -> n.a. | H102: =IFERROR(H49/F49-1,"n.a.") -> -4.7221785 | I102: =IFERROR(I49/G49-1,"n.a.") -> 1.1299037 | L102: =IFERROR(L49/K49-1,"n.a.") -> 1.0758769 | M102: =IFERROR(M49/L49-1,"n.a.") -> -1.0373631 | N102: =IFERROR(N49/M49-1,"n.a.") -> -1.2005066 | Q102: =IFERROR(Q49/P49-1,"n.a.") -> n.a. | R102: =IFERROR(R49/Q49-1,"n.a.") -> n.a. | Z102: =IFERROR(Z49/V49-1,"n.a.") -> n.a. | AA102: =IFERROR(AA49/W49-1,"n.a.") -> 0.96175745 | AB102: =IFERROR(AB49/X49-1,"n.a.") -> 1.2424227 | AC102: =IFERROR(AC49/Y49-1,"n.a.") -> -4.4671279 | AD102: =IFERROR(AD49/Z49-1,"n.a.") -> -0.66333347 | AE102: =IFERROR(AE49/AA49-1,"n.a.") -> -0.55848525 | AF102: =IFERROR(AF49/AB49-1,"n.a.") -> -0.11693288 | AG102: =IFERROR(AG49/AC49-1,"n.a.") -> -0.51004332 | ... BA102: =IFERROR(BA49/AW49-1,"n.a.") -> -0.16657811 | BB102: =IFERROR(BB49/AX48-1,"n.a.") -> n.a. | BC102: =IFERROR(BC49/AY49-1,"n.a.") -> 0.14786416 | BJ102: =IFERROR(BJ49/BI49-1,"n.a.") -> n.a. | BK102: =IFERROR(BK49/BJ49-1,"n.a.") -> n.a. | BL102: =IFERROR(BL49/BK49-1,"n.a.") -> -1.0310619 | BM102: =IFERROR(BM49/BL49-1,"n.a.") -> -83.418143 | BN102: =IFERROR(BN49/BM49-1,"n.a.") -> -0.36862848 | BO102: =IFERROR(BO49/BN49-1,"n.a.") -> 0.59486129 | BP102: =IFERROR(BP49/BO49-1,"n.a.") -> -0.45963109
A103: EBITDAvs 2019 | AH103: =AH49/Z49-1 -> -0.001135559 | AI103: =AI49/AA49-1 -> 0.34271361 | AJ103: =AJ49/AB49-1 -> -0.17610272 | AK103: =AK49/AC49-1 -> -0.45619831 | AL103: =AL49/$Z$49-1 -> -0.070598373 | AM103: =AM49/$AA$49-1 -> -0.7010863 | AN103: =AN49/$AB$49-1 -> -0.40155473 | AO103: =AO49/$AC$49-1 -> -0.85073544 | AP103: =AP49/$Z$49-1 -> 0.97290356 | AQ103: =AQ49/$AA$49-1 -> 1.0278278 | AR103: =AR49/$AB$49-1 -> 0.70015425 | AS103: =AS49/$AB$49-1 -> 0.49406515 | AT103: =AT49/$Z$49-1 -> 1.1798792 | AU103: =AU49/$AA$49-1 -> 1.3112658 | AV103: =AV49/$AB$49-1 -> 1.5859242 | AW103: =AW49/$AC$49-1 -> 1.4507302 | AX103: =AX49/$Z$49-1 -> 2.4800041 | AY103: =AY49/$AA$49-1 -> 2.3088283 | AZ103: =AZ49/AB$49-1 -> 2.3755219 | BA103: =BA49/AC$49-1 -> 1.0424922 | BB103: =BB49/Z$48-1 -> #DIV/0! | BC103: =BC49/$AA$49-1 -> 2.7980854
...

Sheet Sheet6
D10: 21Q3 | E10: 22Q3 | F10: YoY
C11: 订单处理成本 | D11: 239662 | E11: 232616 | F11: =E11/D11-1 -> -0.029399738
C12: 雇员福利开支 | D12: 66466 | E12: 83591 | F12: =E12/D12-1 -> 0.25765053
C13: 采购成本 | D13: 38880 | E13: 53060 | F13: =E13/D13-1 -> 0.36471193
C14: 带宽及服务器保管费 | F14: =E14/D14-1 -> #DIV/0! | J14: 21Q2 | K14: 21Q3 | L14: 21Q4 | M14: 22Q1 | N14: 22Q2 | O14: 22Q3
C15: 资产折旧 | F15: =E15/D15-1 -> #DIV/0! | I15: VAS占比酒店收入 | J15: 0.12 | K15: 0.11 | L15: 0.1 | M15: 0.12 | N15: 0.15 | O15: 0.15
C16: 买断成本 | F16: =E16/D16-1 -> #DIV/0!
C17: 其他 | F17: =E17/D17-1 -> #DIV/0!

Sheet Comp
C6: Unit: RMB Mn | E6: 2017 | F6: 2018 | G6: 1Q17 | H6: 2Q17 | I6: 3Q17 | J6: 4Q17 | K6: 1Q18 | L6: 2Q18 | M6: 3Q18 | N6: 4Q18 | O6: 1Q19 | P6: 2Q19 | Q6: 3Q19 | R6: 4Q19
C7: Ctrip domestic air + train
C8: C+Q+Z
D9: GMV | E9: =E21+E33 -> 234949.65 | F9: =F21+F33 -> 302679.11 | G9: =G21+G33 -> 48502.455 | H9: =H21+H33 -> 48416.55 | I9: =I21+I33 -> 65791.709 | J9: =J21+J33 -> 52280.255 | K9: =K21+K33 -> 75115.939 | L9: =L21+L33 -> 68012.504 | ... R9: =R21+R33 -> 78223.633
D10: YoY | F10: =F9/E9-1 -> 0.2882722 | K10: =K9/G9-1 -> 0.54870385 | L10: =L9/H9-1 -> 0.40473668 | M10: =M9/I9-1 -> 0.37176778 | N10: =N9/J9-1 -> 0.33495767 | O10: =O9/K9-1 -> 0.073596012 | P10: =P9/L9-1 -> 0.1125466 | Q10: =Q9/M9-1 -> 0.074652564 | R10: =R9/N9-1 -> 0.12081203
D11: Take rate | E11: =E12/E9 -> 0.034333472 | F11: =F12/F9 -> 0.024466198 | G11: =G12/G9 -> 0.045185704 | H11: =H12/H9 -> 0.039813298 | I11: =I12/I9 -> 0.036944354 | J11: =J12/J9 -> 0.030692693 | K11: =K12/K9 -> 0.0246851 | L11: =L12/L9 -> 0.023895248 | ... R11: =R12/R9 -> 0.023979976
D12: Revenue | E12: =E24+E36 -> 8066.6372 | F12: =F24+F36 -> 7405.407 | G12: =G24+G36 -> 2191.6176 | H12: =H24+H36 -> 1927.6225 | I12: =I24+I36 -> 2430.6322 | J12: =J24+J36 -> 1604.6218 | K12: =K24+K36 -> 1854.2445 | L12: =L24+L36 -> 1625.1757 | ... R12: =R24+R36 -> 1875.8008
D13: YoY | F13: =F12/E12-1 -> -0.081970993 | K13: =K12/G12-1 -> -0.15393795 | L13: =L12/H12-1 -> -0.1569015 | M13: =M12/I12-1 -> -0.11246249 | N13: =N12/J12-1 -> 0.10146401 | O13: =O12/K12-1 -> 0.075462087 | P13: =P12/L12-1 -> 0.081269794 | Q13: =Q12/M12-1 -> -0.011726644 | R13: =R12/N12-1 -> 0.061313546
C15: Air
C16: C+Q domestic
D17: Volume | E17: =SUM(G17:J17) -> 203.07165 | F17: =SUM(K17:N17) -> 242.3365 | G17: ='[1]OP DATA Combined'!L$226 -> 45.102163 | H17: ='[1]OP DATA Combined'!O$226 -> 47.695248 | I17: ='[1]OP DATA Combined'!Q$226 -> 55.730358 | J17: ='[1]OP DATA Combined'!S$226 -> 54.543881 | K17: ='[1]OP DATA Combined'!T$226 -> 59.15375 | L17: ='[1]OP DATA Combined'!U$226 -> 56.384886 | M17: ='[2]OP DATA Combined'!$V$297 -> 64.939151 | N17: ='[1]OP DATA Combined'!W$226 -> 61.85871 | O17: ='[1]OP DATA Combined'!X$226 -> 61.195596 | P17: ='[3]OP DATA Combined'!$Y$292 -> 60.862553 | Q17: ='[2]OP DATA Combined'!$Z$297 -> 70.350445 | R17: 68.84
D18: YoY | F18: =F17/E17-1 -> 0.19335465 | K18: =K17/G17-1 -> 0.31155018 | L18: =L17/H17-1 -> 0.18219085 | M18: =M17/I17-1 -> 0.16523836 | N18: =N17/J17-1 -> 0.13410907 | O18: =O17/K17-1 -> 0.034517609 | P18: =P17/L17-1 -> 0.07941254 | Q18: =Q17/M17-1 -> 0.083328684 | R18: =R17/N17-1 -> 0.11285864
D19: ASP | E19: =E21/E17 -> 818.67878 | F19: =F21/F17 -> 831.43629 | G19: =G21/G17 -> 840.53376 | H19: =H21/H17 -> 800.55276 | I19: =I21/I17 -> 885.85079 | J19: =J21/J17 -> 747.82385 | K19: =K21/K17 -> 849.61964 | L19: =L21/L17 -> 814.86043 | ... Q19: =Q21/Q17 -> 878.48702 | R19: 754
D20: YoY | F20: =F19/E19-1 -> 0.015583049 | K20: =K19/G19-1 -> 0.01080966 | L20: =L19/H19-1 -> 0.017872244 | M20: =M19/I19-1 -> 0.019246359 | N20: =N19/J19-1 -> 0.0084386266 | O20: =O19/K19-1 -> -0.023198278 | P20: =P19/L19-1 -> -0.019437227 | Q20: =Q19/M19-1 -> -0.027038616 | R20: =R19/N19-1 -> -0.00017829388
D21: GMV | E21: =SUM(G21:J21) -> 166250.45 | F21: =SUM(K21:N21) -> 201487.36 | G21: ='[1]OP DATA Combined'!L$243*(1-'[1]OP DATA Combined'!L$356)/1000000 -> 37909.891 | H21: ='[1]OP DATA Combined'!O$243*(1-'[1]OP DATA Combined'!O$356)/1000000 -> 38182.562 | I21: ='[1]OP DATA Combined'!Q$243*(1-'[1]OP DATA Combined'!Q$356)/1000000 -> 49368.782 | J21: ='[1]OP DATA Combined'!S$243*(1-'[1]OP DATA Combined'!S$356)/1000000 -> 40789.215 | K21: ='[1]OP DATA Combined'!T$243*(1-'[1]OP DATA Combined'!T$356)/1000000 -> 50258.188 | L21: ='[1]OP DATA Combined'!U$243*(1-'[1]OP DATA Combined'!U$356)/1000000 -> 45945.813 | M21: ='[2]OP DATA Combined'!$V$314*(1-'[2]OP DATA Combined'!$V$425)/1000000 -> 58633.572 | N21: ='[1]OP DATA Combined'!W$243*(1-'[1]OP DATA Combined'!W$356)/1000000 -> 46649.785 | O21: ='[1]OP DATA Combined'!X$243*(1-'[1]OP DATA Combined'!X$356)/1000000 -> 50786.833 | P21: ='[3]OP DATA Combined'!$Y$309*(1-'[3]OP DATA Combined'!$Y$420)/1000000 -> 48630.507 | Q21: ='[2]OP DATA Combined'!$Z$314*(1-'[2]OP DATA Combined'!$Z$425)/1000000 -> 61801.953 | R21: ='[4]OP DATA Combined'!$AA$315*(1-'[4]OP DATA Combined'!$AA$426)/1000000 -> 51933.486
D22: YoY | F22: =F21/E21-1 -> 0.21195075 | K22: =K21/G21-1 -> 0.32572759 | L22: =L21/H21-1 -> 0.20331926 | M22: =M21/I21-1 -> 0.18766496 | N22: =N21/J21-1 -> 0.14367939 | O22: =O21/K21-1 -> 0.010518582 | P22: =P21/L21-1 -> 0.058431754 | Q22: =Q21/M21-1 -> 0.054036976 | R22: =R21/N21-1 -> 0.11326315
D23: Take rate | E23: =E24/E21 -> 0.037242286 | F23: =F24/F21 -> 0.024091667 | G23: =G24/G21 -> 0.044234106 | H23: =H24/H21 -> 0.040590168 | I23: =I24/I21 -> 0.036180926 | J23: =J24/J21 -> 0.028894693 | K23: =K24/K21 -> 0.022047402 | L23: =L24/L21 -> 0.025033848 | ... R23: =R24/R21 -> 0.023056058
D24: Revenue | E24: =SUM(G24:J24) -> 6191.5468 | F24: =SUM(K24:N24) -> 4854.1663 | G24: ='[1]OP DATA Combined'!L$297/1000000 -> 1676.9101 | H24: ='[1]OP DATA Combined'!O$297/1000000 -> 1549.8366 | I24: ='[1]OP DATA Combined'!Q$297/1000000 -> 1786.2082 | J24: ='[1]OP DATA Combined'!S$297/1000000 -> 1178.5918 | K24: ='[1]OP DATA Combined'!T$297/1000000 -> 1108.0625 | L24: ='[1]OP DATA Combined'!U$297/1000000 -> 1150.2005 | M24: ='[1]OP DATA Combined'!V$297/1000000 -> 1384.6743 | N24: ='[1]OP DATA Combined'!W$297/1000000 -> 1211.229 | O24: ='[1]OP DATA Combined'!X$297/1000000 -> 1118.9678 | P24: ='[3]OP DATA Combined'!$Y$363/1000000 -> 1161.7926 | Q24: ='[2]OP DATA Combined'!$Z$368/1000000 -> 1281.5218 | R24: ='[4]OP DATA Combined'!$AA$369/1000000 -> 1197.3814
D25: YoY | F25: =F24/E24-1 -> -0.21600103 | K25: =K24/G24-1 -> -0.33922369 | L25: =L24/H24-1 -> -0.25785693 | M25: =M24/I24-1 -> -0.22479682 | N25: =N24/J24-1 -> 0.027691675 | O25: =O24/K24-1 -> 0.0098418062 | P25: =P24/L24-1 -> 0.01007829 | Q25: =Q24/M24-1 -> -0.074495872 | R25: =R24/N24-1 -> -0.011432661
C27: Train
C28: CZQ domestic
D29: Volume | E29: 500.38848 | F29: 683.62621 | G29: ='[5]OP DATA Combined'!$L$398 -> 113.3814 | H29: ='[1]OP DATA Combined'!O$398-'[1]OP DATA Combined'!O$399 -> 115.92271 | I29: ='[1]OP DATA Combined'!Q$398-'[1]OP DATA Combined'!Q$399 -> 148.58671 | J29: ='[1]OP DATA Combined'!S$398-'[1]OP DATA Combined'!S$399 -> 121.25867 | K29: ='[1]OP DATA Combined'!T$398-'[1]OP DATA Combined'!T$399 -> 160.6952 | L29: ='[3]OP DATA Combined'!$U$465-'[3]OP DATA Combined'!$U$466 -> 155.4413 | M29: ='[2]OP DATA Combined'!$V$470-'[2]OP DATA Combined'!$V$471 -> 203.08102 | N29: ='[4]OP DATA Combined'!$W$471-'[4]OP DATA Combined'!$W$472 -> 163.00811 | O29: ='[1]OP DATA Combined'!X$398-'[1]OP DATA Combined'!X$399 -> 198.25417 | P29: ='[3]OP DATA Combined'!$Y$465-'[3]OP DATA Combined'!$Y$466 -> 191.16848 | Q29: ='[2]OP DATA Combined'!$Z$470-'[2]OP DATA Combined'!$Z$471 -> 235.41808 | R29: ='[4]OP DATA Combined'!$AA$471-'[4]OP DATA Combined'!$AA$472 -> 180.38649
D30: YoY | F30: =F29/E29-1 -> 0.36619092 | K30: =K29/G29-1 -> 0.41729774 | L30: =L29/H29-1 -> 0.34090459 | M30: =M29/I29-1 -> 0.36675098 | N30: =N29/J29-1 -> 0.34430066 | O30: =O29/K29-1 -> 0.23372803 | P30: =P29/L29-1 -> 0.22984358 | Q30: =Q29/M29-1 -> 0.1592323 | R30: =R29/N29-1 -> 0.10661055
D31: ASP | E31: =E33/E29 -> 137.29173 | F31: =F33/F29 -> 148.02205 | G31: =G33/G29 -> 93.424184 | H31: =H33/H29 -> 88.282854 | I31: =I33/I29 -> 110.52757 | J31: =J33/J29 -> 94.764692 | K31: =K33/K29 -> 154.68882 | L31: =L33/L29 -> 141.96157 | ... R31: =R33/R29 -> 145.74343
D32: YoY | F32: =F31/E31-1 -> 0.078157014 | K32: =K31/G31-1 -> 0.65576851 | L32: =L31/H31-1 -> 0.6080311 | M32: =M31/I31-1 -> 0.40859401 | N32: =N31/J31-1 -> 0.49812418 | O32: =O31/K31-1 -> -0.026424035 | P32: =P31/L31-1 -> -0.0037586868 | Q32: =Q31/M31-1 -> -0.039982225 | R32: =R31/N31-1 -> 0.026584311
D33: GMV | E33: 68699.202 | F33: 101191.75 | G33: ='[1]OP DATA Combined'!L$413/1000000 -> 10592.565 | H33: ='[1]OP DATA Combined'!O$413/1000000 -> 10233.988 | I33: ='[1]OP DATA Combined'!Q$413/1000000 -> 16422.928 | J33: ='[1]OP DATA Combined'!S$413/1000000 -> 11491.04 | K33: ='[1]OP DATA Combined'!T$413/1000000 -> 24857.751 | L33: ='[3]OP DATA Combined'!$U$480/1000000 -> 22066.691 | M33: ='[2]OP DATA Combined'!$V$485/1000000 -> 31617.375 | N33: ='[4]OP DATA Combined'!$W$486/1000000 -> 23142.143 | O33: ='[1]OP DATA Combined'!X$413/1000000 -> 29857.34 | P33: ='[3]OP DATA Combined'!$Y$480/1000000 -> 27036.573 | Q33: ='[2]OP DATA Combined'!$Z$485/1000000 -> 35186.458 | R33: ='[4]OP DATA Combined'!$AA$486/1000000 -> 26290.146
D34: YoY | F34: =F33/E33-1 -> 0.47296833 | K34: =K33/G33-1 -> 1.346717 | L34: =L33/H33-1 -> 1.1562163 | M34: =M33/I33-1 -> 0.92519723 | N34: =N33/J33-1 -> 1.0139293 | O34: =O33/K33-1 -> 0.20112796 | P34: =P33/L33-1 -> 0.22522098 | Q34: =Q33/M33-1 -> 0.11288362 | R34: =R33/N33-1 -> 0.13602903
D35: Take rate | E35: =E36/E33 -> 0.02729421 | F35: =F36/F33 -> 0.025211944 | G35: =G36/G33 -> 0.048591395 | H35: =H36/H33 -> 0.03691483 | I35: =I36/I33 -> 0.039239286 | J35: =J36/J33 -> 0.037074972 | K35: =K36/K33 -> 0.030018082 | L35: =L36/L33 -> 0.02152453 | ... R35: =R36/R33 -> 0.025805081
D36: Revenue | E36: 1875.0904 | F36: 2551.2407 | G36: ='[1]OP DATA Combined'!L$427/1000000 -> 514.70749 | H36: ='[1]OP DATA Combined'!O$427/1000000 -> 377.78592 | I36: ='[1]OP DATA Combined'!Q$427/1000000 -> 644.42395 | J36: ='[1]OP DATA Combined'!S$427/1000000 -> 426.03 | K36: =('[5]OP DATA Combined'!$T$415+'[5]OP DATA Combined'!$T$419+'[5]OP DATA Combined'!$T$424)/1000000 -> 746.18201 | L36: =('[3]OP DATA Combined'!$U$482+'[3]OP DATA Combined'!$U$487+'[3]OP DATA Combined'!$U$492)/1000000 -> 474.97516 | M36: ='[2]OP DATA Combined'!$V$502/1000000 -> 772.60292 | N36: ='[4]OP DATA Combined'!$W$503/1000000 -> 556.20418 | O36: =('[5]OP DATA Combined'!$X$415+'[5]OP DATA Combined'!$X$419+'[5]OP DATA Combined'!$X$424)/1000000 -> 875.20183 | P36: =('[3]OP DATA Combined'!$Y$482+'[3]OP DATA Combined'!$Y$487+'[3]OP DATA Combined'!$Y$492)/1000000 -> 595.4608 | Q36: ='[2]OP DATA Combined'!$Z$502/1000000 -> 850.45782 | R36: ='[4]OP DATA Combined'!$AA$503/1000000 -> 678.41935
D37: YoY | F37: =F36/E36-1 -> 0.36059607 | K37: =K36/G36-1 -> 0.44972051 | L37: =L36/H36-1 -> 0.25726008 | M37: =M36/I36-1 -> 0.19890474 | N37: =N36/J36-1 -> 0.30555167 | O37: =O36/K36-1 -> 0.17290664 | P37: =P36/L36-1 -> 0.25366724 | Q37: =Q36/M36-1 -> 0.10076961 | R37: =R36/N36-1 -> 0.21973076
C39: TCEL transportation
C40: TCEL
D41: GMV | E41: =Tongchengelong!BK5/1000 -> 80013.4 | F41: =E41*(1+F42) -> 110818.56 | K41: =K44/K43 -> 23543.846 | L41: =L53+L65 -> 24517.943 | M41: =M44/M43 -> 31170.833 | N41: =N44/N43 -> 29797.639 | O41: 30607 | P41: 34865 | Q41: 39390 | R41: =Tongchengelong!AC5/1000 -> 34410
D42: YoY | F42: 0.385 | O42: =O41/K41-1 -> 0.3 | P42: =P41/L41-1 -> 0.42201978 | Q42: =Q41/M41-1 -> 0.26368133 | R42: =R41/N41-1 -> 0.15478948
D43: Take rate | E43: =E44/E41 -> 0.031619704 | F43: =F44/F41 -> 0.029169491 | K43: =O43 -> 0.041132682 | L43: =L44/L41 -> 0.033831835 | M43: 0.036 | N43: 0.036 | O43: =O44/O41 -> 0.041132682 | P43: =P44/P41 -> 0.026877728 | Q43: =Q44/Q41 -> 0.028931734 | R43: =R44/R41 -> 0.034350392
D44: Revenue | E44: =Tongchengelong!BK15/1000 -> 2530 | F44: =Tongchengelong!BL15/1000 -> 3232.521 | K44: =O44/(1+O45) -> 968.42154 | L44: =Tongchengelong!W15/1000 -> 829.487 | M44: =Tongchengelong!X15/1000 -> 1122.15 | N44: =Tongchengelong!Y15/1000 -> 1072.715 | O44: =Tongchengelong!Z15/1000 -> 1258.948 | P44: =Tongchengelong!AA15/1000 -> 937.092 | Q44: =Tongchengelong!AB15/1000 -> 1139.621 | R44: =Tongchengelong!AC15/1000 -> 1181.997
D45: YoY | F45: =F44/E44-1 -> 0.27767628 | O45: =Tongchengelong!Z87 -> 0.3 | P45: =P44/L44-1 -> 0.12972476 | Q45: =Q44/M44-1 -> 0.01556922 | R45: =R44/N44-1 -> 0.10187422
C47: Air
C48: TCEL
D49: Volume | E49: 48.5 | F49: =F53/F51 -> 66.986026 | K49: =K53/K51 -> 13.926871 | L49: =(AVERAGE(K77,F77)+0.025)*L17 -> 15.839996 | M49: =(AVERAGE(L77,F77)+0.01)*M17 -> 18.746104 | N49: =(AVERAGE(M77,G77)+0.01)*N17 -> 18.475455 | O49: =O53/O51 -> 16.68142 | P49: =L49*(1+P50) -> 20.433595 | Q49: =M49*(1+Q50) -> 22.682786 | R49: 17
D50: YoY | F50: =F49/E49-1 -> 0.38115518 | O50: =O49/K49-1 -> 0.19778659 | P50: 0.29 | Q50: 0.21 | R50: 0.27
D51: ASP | E51: =E53/E49 -> 814.48454 | F51: =E51*F19/E19 -> 827.17669 | K51: =F51*K19/F19 -> 845.26689 | L51: =L19*(K51/K19+0.001) -> 811.50062 | M51: =L51*M19/L19 -> 899.17737 | N51: =M51*N19/M19 -> 751.02503 | O51: =K51*O19/K19 -> 825.65815 | P51: =L51*P19/L19 -> 795.7273 | Q51: =M51*Q19/M19 -> 874.86486 | R51: 500
D52: YoY | F52: =F51/E51-1 -> 0.015583049 | O52: =O51/K51-1 -> -0.023198278 | P52: =P51/L51-1 -> -0.019437227 | Q52: =Q51/M51-1 -> -0.027038616 | R52: =R51/N51-1 -> -0.33424322
D53: GMV | E53: 39502.5 | F53: =F41*0.5 -> 55409.279 | K53: =K41*F53/F41 -> 11771.923 | L53: =L49*L51 -> 12854.166 | M53: =M49*M51 -> 16856.073 | N53: =N49*N51 -> 13875.529 | O53: =O41*0.45 -> 13773.15 | P53: =P49*P51 -> 16259.569 | Q53: =Q49*Q51 -> 19844.372 | R53: =R49*R51 -> 8500
D54: YoY | F54: =F53/E53-1 -> 0.40267779 | O54: =O53/K53-1 -> 0.17 | P54: =P53/L53-1 -> 0.26492598 | Q54: =Q53/M53-1 -> 0.17728328 | R54: =R53/N53-1 -> -0.38741074
D55: Take rate | E55: 0.035 | F55: =E55+0.0014 -> 0.0364 | K55: =O55 -> 0.041 | L55: =P55 -> 0.033 | M55: 0.031 | N55: 0.035 | O55: 0.041 | P55: 0.033 | Q55: 0.032 | R55: 0.035
D56: Revenue | E56: =E53*E55 -> 1382.5875 | F56: =F53*F55 -> 2016.8978 | K56: =K53*K55 -> 482.64885 | L56: =L53*L55 -> 424.18749 | M56: =M53*M55 -> 522.53825 | N56: =N53*N55 -> 485.64351 | O56: =O53*O55 -> 564.69915 | P56: =P53*P55 -> 536.56578 | Q56: =Q53*Q55 -> 635.01992 | R56: =R53*R55 -> 297.5
D57: YoY | F57: =F56/E56-1 -> 0.4587849 | O57: =O56/K56-1 -> 0.17 | P57: =P56/L56-1 -> 0.26492598 | Q57: =Q56/M56-1 -> 0.21526016 | R57: =R56/N56-1 -> -0.38741074
C59: Train
C60: TCEL
D61: Volume | E61: =E65/E63 -> 327.8574 | F61: =F65/F63 -> 415.92363 | K61: =K65/K63 -> 84.5563 | L61: =(AVERAGE(K83,F83)+0.02)*L29 -> 91.290561 | M61: =AVERAGE(L83,F83)*M29 -> 121.41273 | N61: =AVERAGE(M83,G83)*N29 -> 97.454987 | O61: =O65/O63 -> 124.1973 | P61: =P65/P63 -> 139.95117 | Q61: =Q65/Q63 -> 145.30193 | R61: =R65/R63 -> 197.5313
D62: YoY | F62: =F61/E61-1 -> 0.26861137 | O62: =O61/K61-1 -> 0.46881194 | P62: =P61/L61-1 -> 0.53302998 | Q62: =Q61/M61-1 -> 0.19676027 | R62: =R61/N61-1 -> 1.0268978
D63: ASP | E63: =E31*0.9 -> 123.56256 | F63: =F31*0.9 -> 133.21984 | K63: =K31*0.9 -> 139.21994 | L63: =L31*0.9 -> 127.76542 | M63: =M31*0.9 -> 140.11963 | N63: =N31*0.9 -> 127.77235 | O63: =O31*0.9 -> 135.54119 | P63: =P31*0.94 -> 132.94231 | Q63: =Q31*0.9 -> 134.51733 | R63: =R31*0.9 -> 131.16909
D64: YoY | F64: =F63/E63-1 -> 0.078157014 | O64: =O63/K63-1 -> -0.026424035 | P64: =P63/L63-1 -> 0.040518705 | Q64: =Q63/M63-1 -> -0.039982225 | R64: =R63/N63-1 -> 0.026584311
D65: GMV | E65: =E41-E53 -> 40510.9 | F65: =F41-F53 -> 55409.279 | K65: =K41-K53 -> 11771.923 | L65: =L61*L63 -> 11663.777 | M65: =M61*M63 -> 17012.306 | N65: =N61*N63 -> 12452.053 | O65: =O41-O53 -> 16833.85 | P65: =P41-P53 -> 18605.431 | Q65: =Q41-Q53 -> 19545.628 | R65: =R41-R53 -> 25910
D66: YoY | F66: =F65/E65-1 -> 0.36776224 | O66: =O65/K65-1 -> 0.43 | P66: =P65/L65-1 -> 0.59514637 | Q66: =Q65/M65-1 -> 0.14891113 | R66: =R65/N65-1 -> 1.0807814
D67: Take rate | E67: =E68/E65 -> 0.02832355 | F67: =F68/F65 -> 0.021938983 | K67: =K68/K65 -> 0.041265364 | L67: =L68/L65 -> 0.034748566 | M67: =M68/M65 -> 0.035245766 | N67: 0.03 | O67: =O68/O65 -> 0.04124124 | P67: =P68/P65 -> 0.021527382 | Q67: 0.0265 | R67: 0.035
D68: Revenue | E68: =E44-E56 -> 1147.4125 | F68: =F44-F56 -> 1215.6232 | K68: =K44-K56 -> 485.77269 | L68: =L44-L56 -> 405.29951 | M68: =M44-M56 -> 599.61175 | N68: =N44-N56 -> 587.07149 | O68: =O44-O56 -> 694.24885 | P68: =P44-P56 -> 400.52622 | Q68: =Q65*Q67 -> 517.95913 | R68: =R65*R67 -> 906.85
D69: YoY | F69: =F68/E68-1 -> 0.059447432 | O69: =O68/K68-1 -> 0.42916401 | P69: =P68/L68-1 -> -0.011777182 | Q69: =Q68/M68-1 -> -0.13617581 | R69: =R68/N68-1 -> 0.54470114
C71: TCEL transportation as % of Ctrip domestic air+train
D72: GMV | E72: =E41/E9 -> 0.34055552 | F72: =F41/F9 -> 0.36612557 | K72: =K41/K9 -> 0.31343343 | L72: =L41/L9 -> 0.3604917 | M72: =M41/M9 -> 0.34537957 | N72: =N41/N9 -> 0.42694965 | O72: =O41/O9 -> 0.37953145 | P72: =P41/P9 -> 0.46076841 | Q72: =Q41/Q9 -> 0.406131 | R72: =R41/R9 -> 0.43989264
D73: Take rate | E73: =E43/E11 -> 0.92095853 | F73: =F43/F11 -> 1.1922364 | K73: =K43/K11 -> 1.6662959 | L73: =L43/L11 -> 1.4158394 | M73: =M43/M11 -> 1.5060809 | N73: =N43/N11 -> 1.4215583 | O73: =O43/O11 -> 1.6634047 | P73: =P43/P11 -> 1.1573512 | Q73: =Q43/Q11 -> 1.3161678 | R73: =R43/R11 -> 1.4324615
D74: Revenue | E74: =E44/E12 -> 0.31363751 | F74: =F44/F12 -> 0.43650822 | K74: =K44/K12 -> 0.52227284 | L74: =L44/L12 -> 0.51039836 | M74: =M44/M12 -> 0.52016958 | N74: =N44/N12 -> 0.60693383 | O74: =O44/O12 -> 0.6313144 | P74: =P44/P12 -> 0.53327085 | Q74: =Q44/Q12 -> 0.53453654 | R74: =R44/R12 -> 0.63012928
C76: Air
D77: Volume | E77: =E49/E17 -> 0.23883196 | F77: =F49/F17 -> 0.27641741 | K77: =K49/K17 -> 0.23543514 | L77: =L49/L17 -> 0.28092627 | M77: =M49/M17 -> 0.28867184 | N77: =N49/N17 -> 0.29867184 | O77: =O49/O17 -> 0.27259183 | P77: =P49/P17 -> 0.33573345 | Q77: =Q49/Q17 -> 0.32242562 | R77: =R49/R17 -> 0.24694945
D78: ASP | E78: =E51/E19 -> 0.99487682 | F78: =F51/F19 -> 0.99487682 | K78: =K51/K19 -> 0.99487682 | L78: =L51/L19 -> 0.99587682 | M78: =M51/M19 -> 0.99587682 | N78: =N51/N19 -> 0.99587682 | O78: =O51/O19 -> 0.99487682 | P78: =P51/P19 -> 0.99587682 | Q78: =Q51/Q19 -> 0.99587682 | R78: =R51/R19 -> 0.66312997
D79: Take rate | E79: =E55/E23 -> 0.93979193 | F79: =F55/F23 -> 1.5108959 | K79: =K55/K23 -> 1.8596295 | L79: =L55/L23 -> 1.3182152 | M79: =M55/M23 -> 1.3126847 | N79: =N55/N23 -> 1.3480047 | O79: =O55/O23 -> 1.8608758 | P79: =P55/P23 -> 1.3813195 | Q79: =Q55/Q23 -> 1.5432141 | R79: =R55/R23 -> 1.5180392
D80: Revenue | E80: =E56/E24 -> 0.22330244 | F80: =F56/F24 -> 0.41549828 | K80: =K56/K24 -> 0.43557909 | L80: =L56/L24 -> 0.36879439 | M80: =M56/M24 -> 0.37737268 | N80: =N56/N24 -> 0.40095102 | O80: =O56/O24 -> 0.50466077 | P80: =P56/P24 -> 0.46184301 | Q80: =Q56/Q24 -> 0.49552019 | R80: =R56/R24 -> 0.24845883
C82: Train
D83: Volume | E83: =E61/E29 -> 0.65520573 | F83: =F61/F29 -> 0.60840796 | K83: =K61/K29 -> 0.52619059 | L83: =L61/L29 -> 0.58729927 | M83: =M61/M29 -> 0.59785362 | N83: =N61/N29 -> 0.59785362 | O83: =O61/O29 -> 0.62645494 | P83: =P61/P29 -> 0.73208285 | Q83: =Q61/Q29 -> 0.61720801 | R83: =R61/R29 -> 1.0950448
D84: ASP | E84: =E63/E31 -> 0.9 | F84: =F63/F31 -> 0.9 | K84: =K63/K31 -> 0.9 | L84: =L63/L31 -> 0.9 | M84: =M63/M31 -> 0.9 | N84: =N63/N31 -> 0.9 | O84: =O63/O31 -> 0.9 | P84: =P63/P31 -> 0.94 | Q84: =Q63/Q31 -> 0.9 | R84: =R63/R31 -> 0.9
D85: Take rate | E85: =E67/E35 -> 1.0377128 | F85: =F67/F35 -> 0.87018213 | K85: =K67/K35 -> 1.3746836 | L85: =L67/L35 -> 1.6143705 | M85: =M67/M35 -> 1.4423691 | N85: =N67/N35 -> 1.2482184 | O85: =O67/O35 -> 1.4069369 | P85: =P67/P35 -> 0.97743906 | Q85: =Q67/Q35 -> 1.096399 | R85: =R67/R35 -> 1.3563221
D86: Revenue | E86: =E68/E36 -> 0.61192382 | F86: =F68/F36 -> 0.47648316 | K86: =K68/K36 -> 0.65101099 | L86: =L68/L36 -> 0.85330674 | M86: =M68/M36 -> 0.77609303 | N86: =N68/N36 -> 1.0554964 | O86: =O68/O36 -> 0.79324428 | P86: =P68/P36 -> 0.67263239 | Q86: =Q68/Q36 -> 0.60903565 | R86: =R68/R36 -> 1.3367101

Sheet TCEL charts

Sheet 交通业务拆分
C1: Unit: RMB Mn | E1: 1Q19 | F1: 2Q19 | G1: 3Q19 | H1: 4Q19 | I1: 20Q1 | J1: 20Q2 | K1: 20Q3 | L1: 20Q4 | M1: 21Q1 | N1: 21Q2 | O1: 21Q3 | P1: 21Q4 | Q1: 22Q1 | R1: 22Q2 | S1: 22Q3 | T1: 22Q4 | U1: 23Q1 | V1: 23Q2 | W1: 23Q3 | X1: 23Q4 | Y1: 24Q1 | Z1: 24Q2 | AA1: 24Q3 | AB1: 24Q4 | AC1: 25Q1 | AD1: 25Q2 | AE1: 25Q3 | AF1: 25Q4 | AG1: 26Q1 | AI1: 2019 | AJ1: 2020 | AK1: 2021 | AL1: 2022 | AM1: 2023 | AN1: 2024
C2: Check | E2: =E102+E25 -> 1161.5514 | F2: =F102+F25 -> 854.44391 | G2: =G102+G25 -> 1035.7697 | H2: =H102+H25 -> 1096.8187 | I2: =I102+I25 -> 635.53121 | J2: =J102+J25 -> 668.19574 | K2: =K102+K25 -> 930.36048 | L2: =L102+L25 -> 914.99246 | ... AG2: =AG102+AG25 -> 1647.0706 | AI2: =AI102+AI37 -> 3858.2408 | AJ2: =AJ102+AJ37 -> 3149.0799 | AK2: =AK102+AK37 -> 3998.0976 | AL2: =AL102+AL37 -> 2875.672
C3: 汽车票收入（含小交通） | E3: =E14-E2 -> 97.396583 | F3: =F14-F2 -> 82.64809 | G3: =G14-G2 -> 103.85134 | H3: =H14-H2 -> 85.17825 | I3: =I14-I2 -> 51.236791 | J3: =J14-J2 -> 57.626264 | K3: =K14-K2 -> 124.75752 | L3: =L14-L2 -> 88.428541 | ... S3: =S14-S2 -> 73.890877 | T3: =T14-T2-5%*T14 -> 121.62567 | U3: =U14-U2 -> 145.94648 | V3: =V14-V2 -> 173.56896 | W3: =W14-W2 -> 171.48808 | X3: =X14-X2 -> 238.31436 | Y3: =Y14-Y2 -> 190.73712 | Z3: =Z14-Z2 -> 263.41004 | AA3: =AA14-AA2 -> 208.61614 | AB3: =AB14-AB2 -> 295.39188 | ... AG3: =AG14-AG2 -> 476.94741 | AI3: =AI14-AI2 -> 659.41716
C4: 汽车票收入占比 | E4: =E3/E14 -> 0.077363468 | F4: =F3/F14 -> 0.088196346 | G4: =G3/G14 -> 0.091127959 | H4: =H3/H14 -> 0.072063 | I4: =I3/I14 -> 0.074605677 | J4: =J3/J14 -> 0.079394485 | K4: =K3/K14 -> 0.11824035 | L4: =L3/L14 -> 0.088127058 | ... AG4: =AG3/AG14 -> 0.22454961
C5: 汽车票GMV | E5: =E6*E11 -> 0 | F5: =F6*F11 -> 337.65813 | G5: =G6*G11 -> 381.21813 | H5: =H6*H11 -> 344.1 | I5: =I6*I11 -> 147.21594 | J5: =J6*J11 -> 348.47235 | K5: =K6*K11 -> 304.03937 | L5: =L6*L11 -> 546.59048 | ... AG5: =AG6*AG11 -> 2407.294
C6: 汽车票GMV 占比 | E6: =E96 -> 0 | F6: =F96 -> 0.01 | G6: =G96 -> 0.01 | H6: =H96 -> 0.01 | I6: =I96 -> 0.01 | J6: =J96 -> 0.02 | K6: =K96 -> 0.01 | L6: =L96 -> 0.02 | ... AG6: =AG96 -> 0.05
M7: =M3/M5 -> 0.038018232 | N7: =N3/N5 -> 0.043715596 | O7: =O3/O5 -> 0.039924526 | P7: =P3/P5 -> 0.060514178 | Q7: =Q3/Q5 -> 0.056286962 | R7: =R3/R5 -> 0.046429708 | S7: =S3/S5 -> 0.027141967 | T7: =T3/T5 -> 0.054910362 | ... AG7: =AG3/AG5 -> 0.19812595
C8: 同程交通业务 | E8: 1Q19 | F8: 2Q19 | G8: 3Q19 | H8: 4Q19 | I8: 20Q1 | J8: 20Q2 | K8: 20Q3 | L8: 20Q4 | M8: 21Q1 | N8: 21Q2 | O8: 21Q3 | P8: 21Q4 | Q8: 22Q1 | R8: 22Q2 | S8: 22Q3 | T8: 22Q4 | U8: 23Q1 | V8: 23Q2 | W8: 23Q3 | X8: 23Q4 | Y8: 24Q1 | Z8: 24Q2 | AA8: 24Q3 | AB8: 24Q4 | AC8: 25Q1 | AD8: 25Q2 | AE8: 25Q3 | AF8: 25Q4 | AG8: 26Q1 | AI8: 2019 | AJ8: 2020 | AK8: 2021 | AL8: 2022 | AM8: 2023 | AN8: 2024 | AO8: 2025
C9: TCEL (from financials and trans GMV est.)
E10: 30575.377 | F10: 35201.647 | G10: 37987.367 | H10: 34072.5 | I10: 15971.349
D11: GMV (mm) | E11: =Tongchengelong!Z5/1000 -> 30154.502 | F11: =Tongchengelong!AA5/1000 -> 33765.813 | G11: =Tongchengelong!AB5/1000 -> 38121.813 | H11: =Tongchengelong!AC5/1000 -> 34410 | I11: =Tongchengelong!AD5/1000 -> 14721.594 | J11: =Tongchengelong!AE5/1000 -> 17423.618 | K11: =Tongchengelong!AF5/1000 -> 30403.937 | L11: =Tongchengelong!AG5/1000 -> 27329.524 | ... AG11: =Tongchengelong!BB5/1000 -> 48145.881 | AH11: 估算 | AI11: =SUM(E11:H11) -> 136452.13 | AJ11: =SUM(I11:L11) -> 89878.673 | AK11: =SUM(M11:P11) -> 116304.58 | AL11: =SUM(Q11:T11) -> 91811.953 | AM11: =SUM(U11:X11) -> 176895.05 | AN11: =SUM(Y11:AB11) -> 185326.8
A12: 1000 | D12: YoY | J12: =J11/F11-1 -> -0.48398644 | K12: =K11/G11-1 -> -0.20245301 | L12: =L11/H11-1 -> -0.20576798 | M12: =M11/E11-1 -> -0.11894796 | N12: =N11/F11-1 -> -0.0013435286 | O12: =O11/G11-1 -> -0.16688078 | P12: =P11/H11-1 -> -0.29507601 | Q12: =Q11/E11-1 -> -0.16437846 | R12: =R11/F11-1 -> -0.46966278 | S12: =S11/G11-1 -> -0.20652463 | T12: =T11/H11-1 -> -0.46357995 | U12: =U11/E11-1 -> 0.43004512 | V12: =V11/F11-1 -> 0.2731141 | W12: =W11/G11-1 -> 0.36117886 | X12: =X11/H11-1 -> 0.13032293 | Y12: =Y11/U11-1 -> 0.14615876 | Z12: =Z11/V11-1 -> 0.031866455 | AA12: =AA11/W11-1 -> 0.015736832 | AB12: =AB11/X11-1 -> -0.0014760989 | AC12: =AC11/Y11-1 -> -0.046133333 | AD12: =AD11/Z11-1 -> -0.0070224719 | AE12: =AE11/AA11-1 -> -0.028314917 | AF12: =AF11/AB11-1 -> 0.00084507042 | AG12: =AG11/AC11-1 -> 0.021232877 | AH12: From Analyst: 交通LSD | AN12: =AN11/AM11-1 -> 0.047665268
D13: Take rate | E13: =E14/E11 -> 0.041749918 | F13: =F14/F11 -> 0.027752685 | G13: =G14/G11 -> 0.029894197 | H13: =H14/H11 -> 0.034350392 | I13: =I14/I11 -> 0.046650383 | J13: =J14/J11 -> 0.041657365 | K13: =K14/K11 -> 0.034703334 | L13: 0.035 | M13: =M14/M11 -> 0.038521459 | N13: =N14/N11 -> 0.036617248 | O13: =O14/O11 -> 0.035413207 | P13: =P14/P11 -> 0.044311418 | Q13: =Q14/Q11 -> 0.040369435 | R13: =R14/R11 -> 0.034596065 | S13: =S14/S11 -> 0.032617777 | T13: =T14/T11 -> 0.040932888 | ... AG13: =AG14/AG11 -> 0.044116297 | AI13: =AI14/AI11 -> 0.033108007 | AJ13: =AJ14/AJ11 -> 0.038620163 | AK13: =AK14/AK11 -> 0.038328128 | AL13: =AL14/AL11 -> 0.036802768 | AM13: =AM14/AM11 -> 0.034088274 | AN13: =AN14/AN11 -> 0.039006938
D14: Revenue (mm) | E14: =Tongchengelong!Z15/1000 -> 1258.948 | F14: =Tongchengelong!AA15/1000 -> 937.092 | G14: =Tongchengelong!AB15/1000 -> 1139.621 | H14: =Tongchengelong!AC15/1000 -> 1181.997 | I14: =Tongchengelong!AD15/1000 -> 686.768 | J14: =Tongchengelong!AE15/1000 -> 725.822 | K14: =Tongchengelong!AF15/1000 -> 1055.118 | L14: =Tongchengelong!AG15/1000 -> 1003.421 | ... AB14: =Tongchengelong!AW15/1000 -> 1723.04 | AC14: 2000.211 | AD14: =Tongchengelong!AY15/1000 -> 1881.01 | AE14: =Tongchengelong!AZ15/1000 -> 2208.716 | AF14: =Tongchengelong!BA15/1000 -> 1835.511 | AG14: =Tongchengelong!BB15/1000 -> 2124.018 | AH14: 公司公布 | AI14: =+SUM(E14:H14) -> 4517.658 | AJ14: =SUM(I14:L14) -> 3471.129 | AK14: =SUM(M14:P14) -> 4457.737 | AL14: =SUM(Q14:T14) -> 3378.934 | AM14: =SUM(U14:X14) -> 6030.047 | AN14: =SUM(Y14:AB14) -> 7229.031
D15: Air+ Ground | F15: =F25+F102 -> 854.44391 | G15: =G25+G102 -> 1035.7697 | H15: =H25+H102 -> 1096.8187 | I15: =I25+I102 -> 635.53121 | J15: =J25+J102 -> 668.19574 | K15: =K25+K102 -> 930.36048 | L15: =L25+L102 -> 914.99246 | M15: =M25+M102 -> 942.62149 | ... AG15: =AG25+AG102 -> 1647.0706
C16: Air | E16: 1Q19 | F16: 2Q19 | G16: 3Q19 | H16: 4Q19 | I16: 20Q1 | J16: 20Q2 | K16: 20Q3 | L16: 20Q4 | M16: 21Q1 | N16: 21Q2 | O16: 21Q3 | P16: 21Q4 | Q16: 22Q1 | R16: 22Q2 | S16: 22Q3 | T16: 22Q4 | U16: 23Q1 | V16: 23Q2 | W16: 23Q3 | X16: 23Q4 | Y16: 24Q1 | Z16: 24Q2 | AA16: 24Q3 | AB16: 24Q4 | AC16: 25Q1 | AD16: 25Q2 | AE16: 25Q3 | AF16: 25Q4 | AG16: 26Q1 | AI16: 2019 | AJ16: 2020 | AK16: 2021 | AL16: 2022 | AM16: 2023 | AN16: 2024
C17: TCEL-机票整体
D18: GMV (mm) - net | E18: =E11*E20 -> 12966.436 | F18: =F11*F20 -> 15194.616 | G18: =G11*G20 -> 17345.425 | H18: =H11*H20 -> 16344.75 | I18: =I11*I20 -> 6771.9332 | J18: =J11*J20 -> 7840.6279 | K18: =K11*K20 -> 13681.772 | L18: =L11*L20 -> 12571.581 | ... AG18: =AG11*AG20 -> 27443.152 | AI18: =SUM(E18:H18) -> 61851.227 | AJ18: =SUM(I18:L18) -> 40865.914 | AK18: =SUM(M18:P18) -> 54686.267 | AL18: =SUM(Q18:T18) -> 43173.654 | AM18: =SUM(U18:X18) -> 83912.745 | AN18: =SUM(Y18:AB18) -> 90457.127
D19: YoY | I19: =+I18/E18-1 -> -0.47773364 | J19: =+J18/F18-1 -> -0.48398644 | K19: =+K18/G18-1 -> -0.21121727 | L19: =+L18/H18-1 -> -0.23084899 | M19: =M18/E18-1 -> -0.016500044 | N19: =N18/F18-1 -> 0.043041203 | O19: =O18/G18-1 -> -0.13941532 | P19: =P18/H18-1 -> -0.31733677 | Q19: =Q18/E18-1 -> -0.086646222 | R19: =R18/F18-1 -> -0.44609223 | S19: =S18/G18-1 -> -0.17164659 | T19: =T18/H18-1 -> -0.47713162 | U19: =U18/E18-1 -> 0.59632944 | V19: =V18/F18-1 -> 0.3862798 | W19: =W18/G18-1 -> 0.37613687 | X19: =X18/H18-1 -> 0.11842479 | Y19: =Y18/U18-1 -> 0.1342196 | Z19: =Z18/V18-1 -> 0.031866455 | AA19: =AA18/W18-1 -> 0.081980538 | AB19: =AB18/X18-1 -> 0.062259469 | AC19: =AC18/Y18-1 -> -0.036092632 | AD19: =AD18/Z18-1 -> 0.074036918 | AE19: =AE18/AA18-1 -> -0.0084846093 | AF19: =AF18/AB18-1 -> 0.052889014 | AG19: =AG18/AC18-1 -> 0.21271404
D20: % of Trans GMV | E20: 0.43 | F20: 0.45 | G20: 0.455 | H20: 0.475 | I20: 0.46 | J20: 0.45 | K20: 0.45 | L20: 0.46 | M20: 0.48 | N20: 0.47 | O20: 0.47 | P20: 0.46 | Q20: 0.47 | R20: 0.47 | S20: 0.475 | T20: 0.463 | U20: 0.48 | V20: 0.49 | W20: 0.46 | X20: 0.47 | Y20: 0.475 | Z20: 0.49 | AA20: 0.49 | AB20: 0.5 | AC20: 0.48 | AD20: 0.53 | AE20: 0.5 | AF20: 0.526 | AG20: 0.57 | AH20: 估算 | AI20: =AI18/AI11 -> 0.45328151 | AJ20: =AJ18/AJ11 -> 0.45467865 | AK20: =AK18/AK11 -> 0.47019872 | AL20: =AL18/AL11 -> 0.47024001 | AM20: =AM18/AM11 -> 0.47436457 | AN20: =AN18/AN11 -> 0.48809523
D21: Volume (mm) | E21: =E18/E23 -> 18.134875 | F21: =F18/F23 -> 22.021183 | G21: =G18/G23 -> 23.127233 | H21: =H18/H23 -> 24.036397 | I21: =I18/I23 -> 9.9587253 | J21: =J18/J23 -> 12.646174 | K21: =K18/K23 -> 26.3111 | L21: =L18/L23 -> 21.67514 | ... P21: =P18/P23 -> 18.5966 | Q21: =M21*(1-14%) -> 18.278568 | R21: =N21*(1-55%) -> 11.886458 | S21: =O21*(1+-16%) -> 19.027092 | T21: =P21*(1-35%) -> 12.08779 | U21: =E21*(1+U22) -> 24.482082 | V21: =F21*(1+V22) -> 30.389232 | W21: =G21*(1+W22) -> 30.527948 | X21: =H21*(1+X22) -> 28.122585 | Y21: =U21*(1+Y22) -> 33.540452 | Z21: =V21*(1+Z22) -> 35.251509 | AA21: =W21*(1+AA22) -> 37.091457 | AB21: =AB32+AB45 -> 30.895471 | AC21: =AC32+AC45 -> 35.626668 | AD21: =AD32+AD45 -> 36.818086 | AE21: =AE32+AE45 -> 38.210098 | AF21: =AF32+AF45 -> 31.590859 | AG21: =AG32+AG45 -> 36.451347 | AH21: 用增速倒算 | AI21: =SUM(E21:H21) -> 87.319688 | AJ21: =SUM(I21:L21) -> 70.591138 | AK21: =SUM(M21:P21) -> 88.9164 | AL21: =SUM(Q21:T21) -> 61.279908 | AM21: =SUM(U21:X21) -> 113.52185 | AN21: =SUM(Y21:AB21) -> 136.77889
D22: YoY | I22: =I21/E21-1 -> -0.45085229 | J22: =J21/F21-1 -> -0.42572684 | K22: =K21/G21-1 -> 0.1376674 | L22: =L21/H21-1 -> -0.098236746 | M22: =M21/E21-1 -> 0.17200411 | N22: =N21/F21-1 -> 0.19949738 | O22: =O21/G21-1 -> -0.020578888 | P22: =P21/H21-1 -> -0.22631501 | Q22: =Q21/E21-1 -> 0.0079235386 | R22: =R21/F21-1 -> -0.46022618 | S22: =S21/G21-1 -> -0.17728627 | T22: =T21/H21-1 -> -0.49710475 | U22: 0.35 | V22: 0.38 | W22: 0.32 | X22: 0.17 | Y22: 0.37 | Z22: 0.16 | AA22: 0.215 | AB22: =AB21/X21-1 -> 0.0986 | AC22: =AC21/Y21-1 -> 0.0622 | AD22: =AD21/Z21-1 -> 0.04444 | AE22: =AE21/AA21-1 -> 0.030159 | AF22: =AF21/AB21-1 -> 0.022507737 | AG22: =AG21/AC21-1 -> 0.023147806 | AN22: =AN21/AM21-1 -> 0.20486844
D23: ASP | E23: 715 | F23: 690 | G23: 750 | H23: 680 | I23: 680 | J23: 620 | K23: 520 | L23: 580 | M23: 600 | N23: 600 | O23: 659 | P23: 600 | Q23: 706 | R23: =R18/R21 -> 708.06761 | S23: =S18/S21 -> 755.14123 | T23: =T18/T21 -> 707.00708 | U23: =U18/U21 -> 845.46337 | V23: =V18/V21 -> 693.1399 | W23: =W18/W21 -> 781.89595 | X23: =X18/X21 -> 650.02467 | Y23: =Y18/Y21 -> 699.95703 | ... AG23: =AG18/AG21 -> 752.87072
D24: Take rate | E24: 0.04 | F24: 0.035 | G24: 0.032 | H24: 0.0348 | I24: 0.042 | J24: 0.044 | K24: 0.038 | L24: 0.04 | M24: 0.04 | N24: 0.036 | O24: 0.034 | P24: 0.043 | Q24: 0.0375 | R24: 0.0336 | S24: 0.034 | T24: 0.038 | U24: 0.0305 | V24: 0.0345 | W24: 0.032 | X24: 0.036 | Y24: 0.033 | Z24: 0.035 | AA24: 0.0355 | AB24: 0.038 | AC24: 0.038 | AD24: 0.038 | AE24: 0.038 | AF24: 0.041 | AG24: 0.033
D25: Revenue (mm) | E25: =E18*E24 -> 518.65743 | F25: =F18*F24 -> 531.81156 | G25: =G18*G24 -> 555.0536 | H25: =H18*H24 -> 568.7973 | I25: =I18*I24 -> 284.42119 | J25: =J18*J24 -> 344.98763 | K25: =K18*K24 -> 519.90733 | L25: =L24*L18 -> 502.86324 | M25: =M18*M24 -> 510.09956 | N25: =N18*N24 -> 570.54998 | O25: =O18*O24 -> 507.52504 | P25: =P18*P24 -> 479.79227 | Q25: =Q18*Q24 -> 444.11037 | R25: =R18*R24 -> 282.79157 | S25: =S18*S24 -> 488.51683 | T25: =T18*T24 -> 324.75382 | ... AG25: =AG18*AG24 -> 905.62402 | AI25: =SUM(E25:H25) -> 2174.3199 | AJ25: =SUM(I25:L25) -> 1652.1794 | AK25: =SUM(M25:P25) -> 2067.9669 | AL25: =SUM(Q25:T25) -> 1540.1726 | AM25: =SUM(U25:X25) -> 2779.9413 | AN25: =SUM(Y25:AB25) -> 3190.2145
D26: YoY | I26: =+I25/E25-1 -> -0.45162033 | J26: =+J25/F25-1 -> -0.35129724 | K26: =+K25/G25-1 -> -0.063320504 | L26: =L25/H25-1 -> -0.11591838 | M26: =M25/E25-1 -> -0.016500044 | N26: =N25/F25-1 -> 0.072842381 | O26: =O25/G25-1 -> -0.085628773 | P26: =P25/H25-1 -> -0.15647934 | Q26: =Q25/E25-1 -> -0.14373083 | R26: =R25/F25-1 -> -0.46824854 | S26: =S25/G25-1 -> -0.1198745 | T26: =T25/H25-1 -> -0.42905176 | U26: =U25/E25-1 -> 0.2172012 | V26: =V25/F25-1 -> 0.3664758 | W26: =W25/G25-1 -> 0.37613687 | X26: =X25/H25-1 -> 0.15699117 | Y26: =Y25/U25-1 -> 0.22718842 | Z26: =Z25/V25-1 -> 0.046821042 | AA26: =AA25/W25-1 -> 0.20032216 | AB26: =AB25/X25-1 -> 0.12127388 | AC26: =AC25/Y25-1 -> 0.10995394 | AD26: =AD25/Z25-1 -> 0.16609723 | AE26: =AE25/AA25-1 -> 0.061340418 | AF26: =AF25/AB25-1 -> 0.13601183 | AG26: =AG25/AC25-1 -> 0.053146404
D27: 单票收入 | E27: =E25/E21 -> 28.6 | F27: =F25/F21 -> 24.15 | G27: =G25/G21 -> 24 | H27: =H25/H21 -> 23.664 | I27: =I25/I21 -> 28.56 | J27: =J25/J21 -> 27.28 | K27: =K25/K21 -> 19.76 | L27: =L25/L21 -> 23.2 | ... AG27: =AG25/AG21 -> 24.844734 | AI27: =AI25/AI21 -> 24.900683 | AJ27: =AJ25/AJ21 -> 23.404912 | AK27: =AK25/AK21 -> 23.257429 | AL27: =AL25/AL21 -> 25.133402 | AM27: =AM25/AM21 -> 24.488161 | AN27: =AN25/AN21 -> 23.32388
C28: TCEL-国内
D29: GMV (mm) - net | E29: =E18-E42 -> 11604.96 | F29: =F18-F42 -> 13568.792 | G29: =G18-G42 -> 15437.428 | H29: =H18-H42 -> 14465.104 | I29: =I18-I42 -> 6771.9332 | J29: =J18-J42 -> 7840.6279 | K29: =K18-K42 -> 13681.772 | L29: =L18-L42 -> 12571.581 | ... AG29: =AG18-AG42 -> 22091.737 | AI29: =SUM(E29:H29) -> 55076.284 | AJ29: =SUM(I29:L29) -> 40865.914 | AK29: =SUM(M29:P29) -> 54686.267 | AL29: =SUM(Q29:T29) -> 43173.654 | AM29: =SUM(U29:X29) -> 74243.927 | AN29: =SUM(Y29:AB29) -> 74699.754 | BC29: =U11 -> 43122.298
D30: % of Total Air | U30: =1-U43 -> 0.915 | V30: =1-V43 -> 0.885 | W30: =1-W43 -> 0.885 | X30: =1-X43 -> 0.85 | Y30: =1-Y43 -> 0.835 | Z30: =1-Z43 -> 0.825 | AA30: =1-AA43 -> 0.83 | AB30: =1-AB43 -> 0.81 | ... AG30: =1-AG43 -> 0.805
D31: YoY | I31: =I29/E29-1 -> -0.41646217 | J31: =J29/F29-1 -> -0.42215727 | K31: =K29/G29-1 -> -0.11372727 | L31: =L29/H29-1 -> -0.13090281 | M31: =M29/E29-1 -> 0.098882633 | N31: =N29/F29-1 -> 0.16801926 | O31: =O29/G29-1 -> -0.033050917 | P31: =P29/H29-1 -> -0.22862912 | Q31: =Q29/E29-1 -> 0.020507015 | R31: =R29/F29-1 -> -0.37972254 | S31: =S29/G29-1 -> -0.069265831 | T31: =T29/H29-1 -> -0.40918827 | U31: =U29/E29-1 -> 0.6320016 | V31: =V29/F29-1 -> 0.37386072 | W31: =W29/G29-1 -> 0.36840577 | X31: =X29/H29-1 -> 0.074193304 | Y31: =Y29/U29-1 -> 0.035052863 | Z31: =Z29/V29-1 -> -0.038090593 | AA31: =AA29/W29-1 -> 0.01473881 | AB31: =AB29/X29-1 -> 0.012270788 | AC31: =AC29/Y29-1 -> -0.076495934 | AD31: =AD29/Z29-1 -> 0.028471716 | AE31: =AE29/AA29-1 -> -0.062241468 | AF31: =AF29/AB29-1 -> 0.013893125 | AG31: =AG29/AC29-1 -> 0.2202935 | AJ31: =AJ29/AI29-1 -> -0.25801251 | AK31: =AK29/AI29-1 -> -0.0070814071 | AL31: =AL29/AI29-1 -> -0.21611171 | AM31: =AM29/AI29-1 -> 0.3480199 | AN31: =AN29/AM29-1 -> 0.006139576 | BC31: =U14 -> 1382.694
D32: Volume (mm) | E32: =E21-E45 -> 17.028648 | F32: =F21-F45 -> 20.898102 | G32: =G21-G45 -> 21.392691 | H32: =H21-H45 -> 22.353849 | I32: =I21-I45 -> 9.9587253 | J32: =J21-J45 -> 12.646174 | K32: =K21-K45 -> 26.3111 | L32: =L21-L45 -> 21.67514 | ... AA32: =AA21-AA45 -> 33.156053 | AB32: =X32*(1+AB34) -> 28.13524 | AC32: =Y32*(1+AC34) -> 31.368372 | AD32: =Z32*(1+AD34) -> 32.576625 | AE32: =AA32*(1+AE34) -> 33.487614 | AF32: =AB32*(1+AF34) -> 28.416592 | AG32: =AC32*(1+AG34) -> 31.682056 | AI32: =SUM(E32:H32) -> 81.67329 | AJ32: =SUM(I32:L32) -> 70.591138 | AK32: =SUM(M32:P32) -> 88.9164 | AL32: =SUM(Q32:T32) -> 61.279908 | AM32: =SUM(U32:X32) -> 107.6528 | AN32: =SUM(Y32:AB32) -> 123.68389 | BB32: 机票 | BC32: 火车 | BD32: 汽车等
D33: % of Total Air | U33: =1-U46 -> 0.965 | V33: =1-V46 -> 0.957 | W33: =1-W46 -> 0.9385 | X33: =1-X46 -> 0.935 | Y33: =1-Y46 -> 0.908 | Z33: =1-Z46 -> 0.906 | AA33: =1-AA46 -> 0.8939 | AB33: =1-AB46 -> 0.91065902 | ... AG33: =1-AG46 -> 0.86916008
D34: YoY | I34: =I32/E32-1 -> -0.41517816 | J34: =J32/F32-1 -> -0.39486496 | K34: =K32/G32-1 -> 0.22991071 | L34: =L32/H32-1 -> -0.030362093 | M34: =M32/E32-1 -> 0.2481407 | N34: =N32/F32-1 -> 0.26395931 | O34: =O32/G32-1 -> 0.058833635 | P34: =P32/H32-1 -> -0.16808065 | Q34: =Q32/E32-1 -> 0.073401 | R34: =R32/F32-1 -> -0.43121831 | S34: =S32/G32-1 -> -0.11057975 | T34: =T32/H32-1 -> -0.45925242 | U34: =U32/E32-1 -> 0.38738019 | V34: =V32/F32-1 -> 0.3916333 | W34: =W32/G32-1 -> 0.33926486 | X34: =X32/H32-1 -> 0.17629032 | Y34: =Y32/U32-1 -> 0.28907772 | Z34: =Z32/V32-1 -> 0.098181818 | AA34: =AA32/W32-1 -> 0.15725999 | AB34: 0.07 | AC34: 0.03 | AD34: 0.02 | AE34: 0.01 | AF34: 0.01 | AG34: 0.01 | AJ34: =AJ32/AI32-1 -> -0.13568881 | AK34: =AK32/AI32-1 -> 0.088683943 | AL34: =AL32/AI32-1 -> -0.24969463 | AM34: =AM32/AI32-1 -> 0.31809064 | AN34: =AN32/AM32-1 -> 0.14891476 | BB34: =U18 -> 20698.703 | BC34: =U94 -> 16817.696 | BD34: =U5 -> 4743.4528 | BE34: =BC29-BD34-BC34-BB34 -> 862.44597 | BF34: =BE34/BC29 -> 0.02
D35: ASP | E35: =E29/E32 -> 681.49627 | F35: =F29/F32 -> 649.28346 | G35: =G29/G32 -> 721.62162 | H35: =H29/H32 -> 647.09677 | I35: =I29/I32 -> 680 | J35: =J29/J32 -> 620 | K35: =K29/K32 -> 520 | L35: =L29/L32 -> 580 | ... AG35: =AG29/AG32 -> 697.29495 | AI35: =+AI29/AI32 -> 674.34879 | AJ35: =+AJ29/AJ32 -> 578.90997 | AK35: =+AK29/AK32 -> 615.03015 | AL35: =+AL29/AL32 -> 704.53197 | AM35: =+AM29/AM32 -> 689.66091 | AN35: =+AN29/AN32 -> 603.95702 | BB35: =U25 -> 631.31045 | BC35: =U102 -> 605.43707 | BD35: =U3 -> 145.94648 | BE35: =BC31-BB35-BC35-BD35 -> 0
D36: Take rate | E36: =E37/E29 -> 0.039413408 | F36: =F37/F29 -> 0.034041433 | G36: =G37/G29 -> 0.030393258 | H36: =H37/H29 -> 0.034254237 | I36: =I37/I29 -> 0.042 | J36: =J37/J29 -> 0.044 | K36: =K37/K29 -> 0.038 | L36: =L37/L29 -> 0.04 | ... AG36: =AG37/AG29 -> 0.033726708 | AI36: =+AI37/AI29 -> 0.034206683 | AJ36: =+AJ37/AJ29 -> 0.040429278 | AK36: =+AK37/AK29 -> 0.037815104 | AL36: =+AL37/AL29 -> 0.035673899 | AM36: =+AM37/AM29 -> 0.033905767 | AN36: =+AN37/AN29 -> 0.038261592
D37: Revenue (mm) | E37: =E25-E51 -> 457.39102 | F37: =F25-F51 -> 461.90113 | G37: =G25-G51 -> 469.19375 | H37: =H25-H51 -> 495.4911 | I37: =I25-I51 -> 284.42119 | J37: =J25-J51 -> 344.98763 | K37: =K25-K51 -> 519.90733 | L37: =L25-L51 -> 502.86324 | ... AG37: =AG25-AG51 -> 745.08158 | AH37: =AG37/AG14 -> 0.35078873 | AI37: =SUM(E37:H37) -> 1883.977 | AJ37: =SUM(I37:L37) -> 1652.1794 | AK37: =SUM(M37:P37) -> 2067.9669 | AL37: =SUM(Q37:T37) -> 1540.1726 | AM37: =SUM(U37:X37) -> 2517.2973 | AN37: =SUM(Y37:AB37) -> 2858.1315
D38: YoY | I38: =+I37/E37-1 -> -0.37816621 | J38: =+J37/F37-1 -> -0.2531137 | K38: =+K37/G37-1 -> 0.10808665 | L38: =L37/H37-1 -> 0.014878457 | M38: =M37/E37-1 -> 0.11523737 | N38: =N37/F37-1 -> 0.235221 | O38: =O37/G37-1 -> 0.081696091 | P38: =P37/H37-1 -> -0.031683361 | Q38: =Q37/E37-1 -> -0.029035671 | R38: =R37/F37-1 -> -0.38776601 | S38: =S37/G37-1 -> 0.041183584 | T38: =T37/H37-1 -> -0.34458194 | U38: =U37/E37-1 -> 0.26484501 | V38: =V37/F37-1 -> 0.41596723 | W38: =W37/G37-1 -> 0.4524476 | X38: =X37/H37-1 -> 0.21748369 | Y38: =Y37/U37-1 -> 0.21862664 | Z38: =Z37/V37-1 -> 0.046821042 | AA38: =AA37/W37-1 -> 0.21007491 | AB38: =AB37/X37-1 -> 0.06724887 | AC38: =AC37/Y37-1 -> 0.084917384 | AD38: =AD37/Z37-1 -> 0.13813817 | AE38: =AE37/AA37-1 -> 0.019773424 | AF38: =AF37/AB37-1 -> 0.099412386 | AG38: =AG37/AC37-1 -> -0.025882065 | AJ38: =AJ37/AI37-1 -> -0.12303633
D39: 单票收入 | E39: =E37/E32 -> 26.860091 | F39: =F37/F32 -> 22.10254 | G39: =G37/G32 -> 21.932432 | H39: =H37/H32 -> 22.165806 | I39: =I37/I32 -> 28.56 | J39: =J37/J32 -> 27.28 | K39: =K37/K32 -> 19.76 | L39: =L37/L32 -> 23.2 | ... AG39: =AG37/AG32 -> 23.517463 | AI39: =AI37/AI32 -> 23.067235 | AJ39: =AJ37/AJ32 -> 23.404912 | AK39: =AK37/AK32 -> 23.257429 | AL39: =AL37/AL32 -> 25.133402 | AM39: =AM37/AM32 -> 23.383482 | AN39: =AN37/AN32 -> 23.108357
D40: YoY | U40: =U39/Q39-1 -> 0.0078607739 | V40: =V39/R39-1 -> -0.054728505 | W40: =W39/S39-1 -> -0.073567672 | X40: =X39/T39-1 -> -0.14606502 | Y40: =Y39/U39-1 -> -0.05465231 | Z40: =Z39/V39-1 -> -0.046768919 | AA40: =AA39/W39-1 -> 0.045637901 | AB40: =AB39/X39-1 -> -0.0025711498 | ... AG40: =AG39/AC39-1 -> -0.035526797
C41: TCEL-国际
D42: GMV (mm) - net | E42: =E18*E43 -> 1361.4758 | F42: =F18*F43 -> 1625.8239 | G42: =G18*G43 -> 1907.9967 | H42: =H18*H43 -> 1879.6463 | U42: =U18*U43 -> 1759.3898 | V42: =V18*V43 -> 2422.3588 | W42: =W18*W43 -> 2745.0131 | X42: =X18*X43 -> 2742.056 | Y42: =Y18*Y43 -> 3873.6844 | Z42: =Z18*Z43 -> 3803.6642 | AA42: =AA18*AA43 -> 4390.5098 | AB42: =AB18*AB43 -> 3689.515 | ... AG42: =AG18*AG43 -> 5351.4147 | AI42: =SUM(E42:H42) -> 6774.9427 | AM42: =SUM(U42:X42) -> 9668.8177 | AN42: =SUM(Y42:AB42) -> 15757.373
D43: % of Total Air | E43: 0.105 | F43: 0.107 | G43: 0.11 | H43: 0.115 | U43: 0.085 | V43: 0.115 | W43: 0.115 | X43: 0.15 | Y43: 0.165 | Z43: 0.175 | AA43: 0.17 | AB43: 0.19 | AC43: 0.2 | AD43: 0.21 | AE43: 0.215 | AF43: 0.22 | AG43: 0.195 | AH43: 估算
D44: YoY | U44: =U42/E42-1 -> 0.29226669 | V44: =V42/F42-1 -> 0.48992689 | W44: =W42/G42-1 -> 0.43868855 | X44: =X42/H42-1 -> 0.45881495 | Y44: =Y42/U42-1 -> 1.2017204 | Z44: =Z42/V42-1 -> 0.57023156 | AA44: =AA42/W42-1 -> 0.59944949 | AB44: =AB42/X42-1 -> 0.34552866 | AC44: =AC42/Y42-1 -> 0.16837257 | AD44: =AD42/Z42-1 -> 0.2888443 | AE44: =AE42/AA42-1 -> 0.25397535 | AF44: =AF42/AB42-1 -> 0.21913465 | AG44: =AG42/AC42-1 -> 0.18239619
D45: Volume (mm) | E45: =E46*E21 -> 1.1062274 | F45: =F46*F21 -> 1.1230803 | G45: =G46*G21 -> 1.7345425 | H45: =H46*H21 -> 1.6825478 | U45: =U46*U21 -> 0.85687286 | V45: =V46*V21 -> 1.306737 | W45: =W46*W21 -> 1.8774688 | X45: =X46*X21 -> 1.827968 | Y45: =Y46*Y21 -> 3.0857216 | Z45: =Z46*Z21 -> 3.3136419 | AA45: =AA46*AA21 -> 3.9354036 | AB45: =X45*(1+AB47) -> 2.7602317 | AC45: =Y45*(1+AC47) -> 4.2582958 | AD45: =Z45*(1+AD47) -> 4.2414616 | AE45: =AA45*(1+AE47) -> 4.7224843 | AF45: =AB45*(1+AF47) -> 3.1742664 | AG45: =AC45*(1+AG47) -> 4.7692913 | AI45: =SUM(E45:H45) -> 5.646398 | AM45: =SUM(U45:X45) -> 5.8690466 | AN45: =SUM(Y45:AB45) -> 13.094999 | AO45: =SUM(AC45:AF45) -> 16.396508
D46: % of Total Air | E46: 0.061 | F46: 0.051 | G46: 0.075 | H46: 0.07 | U46: 0.035 | V46: 0.043 | W46: 0.0615 | X46: 0.065 | Y46: 0.092 | Z46: 0.094 | AA46: 0.1061 | AB46: =AB45/AB21 -> 0.089340979 | AC46: =AC45/AC21 -> 0.11952551 | AD46: =AD45/AD21 -> 0.11520049 | AE46: =AE45/AE21 -> 0.12359257 | AF46: =AF45/AF21 -> 0.10048054 | AG46: =AG45/AG21 -> 0.13083992 | AI46: =AI45/AI21 -> 0.064663515 | AM46: =AM45/AM21 -> 0.051699711 | AN46: =AN45/AN21 -> 0.095738449 | AO46: =AO45/AO21 -> #DIV/0!
D47: YoY | U47: =U45/E45-1 -> -0.22540984 | V47: =V45/F45-1 -> 0.16352941 | W47: =W45/G45-1 -> 0.0824 | X47: =X45/H45-1 -> 0.086428571 | Y47: =Y45/U45-1 -> 2.6011429 | Z47: =Z45/V45-1 -> 1.535814 | AA47: =AA45/W45-1 -> 1.096122 | AB47: 0.51 | AC47: 0.38 | AD47: 0.28 | AE47: 0.2 | AF47: 0.15 | AG47: 0.12 | AN47: =AN45/AM45-1 -> 1.2311969 | AO47: =AO45/AN45-1 -> 0.25211987 | AP47: From 公司：2025年国际机票票量增速约25%
D48: ASP | E48: =E42/E45 -> 1230.7377 | F48: =F42/F45 -> 1447.6471 | G48: =G42/G45 -> 1100 | H48: =H42/H45 -> 1117.1429 | U48: =U42/U45 -> 2053.2682 | V48: =V42/V45 -> 1853.7462 | W48: =W42/W45 -> 1462.0819 | X48: =X42/X45 -> 1500.0569 | Y48: =Y42/Y45 -> 1255.3577 | Z48: =Z42/Z45 -> 1147.8803 | AA48: =AA42/AA45 -> 1115.6441 | AB48: =AB42/AB45 -> 1336.6686 | ... AG48: =AG42/AG45 -> 1122.0566 | AI48: =AI42/AI45 -> 1199.8698 | AM48: =AM42/AM45 -> 1647.4256 | AN48: =AN42/AN45 -> 1203.3123
D49: YoY | U49: =U48/E48-1 -> 0.66832313 | V49: =V48/F48-1 -> 0.28052362 | W49: =W48/G48-1 -> 0.32916532 | X49: =X48/H48-1 -> 0.34276195 | Y49: =Y48/U48-1 -> -0.38860509 | Z49: =Z48/V48-1 -> -0.38077809 | AA49: =AA48/W48-1 -> -0.23694827 | AB49: =AB48/X48-1 -> -0.10892142 | AC49: =AC48/Y48-1 -> -0.15335321 | AD49: =AD48/Z48-1 -> 0.0069096108 | AE49: =AE48/AA48-1 -> 0.044979456 | AF49: =AF48/AB48-1 -> 0.060117085 | AG49: =AG48/AC48-1 -> 0.055710884
D50: Take rate | E50: 0.045 | F50: 0.043 | G50: 0.045 | H50: 0.039 | U50: 0.03 | V50: 0.03 | W50: 0.03 | X50: 0.02 | Y50: 0.018 | Z50: 0.02 | AA50: 0.021 | AB50: 0.0255 | AC50: 0.021 | AD50: 0.022 | AE50: 0.024 | AF50: 0.029 | AG50: 0.03 | AH50: =AG51/AG14 -> 0.075584312 | AI50: =AI51/AI42 -> 0.042855402 | AM50: =AM51/AM42 -> 0.027164021 | AN50: =AN51/AN42 -> 0.021074765
D51: Revenue (mm) | E51: =E50*E42 -> 61.266409 | F51: =F50*F42 -> 69.910428 | G51: =G50*G42 -> 85.859854 | H51: =H50*H42 -> 73.306204 | U51: =U50*U42 -> 52.781693 | V51: =V50*V42 -> 72.670763 | W51: =W50*W42 -> 82.350392 | X51: =X50*X42 -> 54.841121 | Y51: =Y50*Y42 -> 69.726319 | Z51: =Z50*Z42 -> 76.073284 | AA51: =AA50*AA42 -> 92.200705 | AB51: =AB50*AB42 -> 94.082632 | ... AG51: =AG50*AG42 -> 160.54244 | AH51: 国际机票占比总交通收入7-8% | AI51: =SUM(E51:H51) -> 290.3429 | AM51: =SUM(U51:X51) -> 262.64397 | AN51: =SUM(Y51:AB51) -> 332.08294 | AO51: =SUM(AC51:AF51) -> 465.47195
D52: YoY | U52: =U51/E51-1 -> -0.13848888 | V52: =V51/F51-1 -> 0.039483876 | W52: =W51/G51-1 -> -0.040874302 | X52: =X51/H51-1 -> -0.25188977 | Y52: =Y51/U51-1 -> 0.32103224 | Z52: =Z51/V51-1 -> 0.046821042 | AA52: =AA51/W51-1 -> 0.11961464 | AB52: =AB51/X51-1 -> 0.71554904 | AC52: =AC51/Y51-1 -> 0.36310133 | AD52: =AD51/Z51-1 -> 0.41772873 | AE52: =AE51/AA51-1 -> 0.43311468 | AF52: =AF51/AB51-1 -> 0.38646685 | AG52: =AG51/AC51-1 -> 0.68913741
D53: 单票收入 | E53: =E51/E45 -> 55.383197 | F53: =F51/F45 -> 62.248824 | G53: =G51/G45 -> 49.5 | H53: =H51/H45 -> 43.568571 | U53: =U51/U45 -> 61.598045 | V53: =V51/V45 -> 55.612387 | W53: =W51/W45 -> 43.862456 | X53: =X51/X45 -> 30.001138 | Y53: =Y51/Y45 -> 22.596439 | Z53: =Z51/Z45 -> 22.957606 | AA53: =AA51/AA45 -> 23.428526 | AB53: =AB51/AB45 -> 34.085049 | ... AG53: =AG51/AG45 -> 33.661698 | AI53: =AI51/AI45 -> 51.420905 | AM53: =AM51/AM45 -> 44.750704 | AN53: =AN51/AN45 -> 25.359525 | AO53: =K39/J39-1 -> -0.27565982
D54: YoY | Y54: =Y53/U53-1 -> -0.63316305 | Z54: =Z53/V53-1 -> -0.58718539 | AA54: =AA53/W53-1 -> -0.46586379 | AB54: =AB53/X53-1 -> 0.13612519 | AC54: =AC53/Y53-1 -> -0.012245414 | AD54: =AD53/Z53-1 -> 0.10760057 | AE54: =AE53/AA53-1 -> 0.19426224 | AF54: =AF53/AB53-1 -> 0.20562335 | AG54: =AG53/AC53-1 -> 0.50815841
C55: TCOM - C+Q Domestic Air
D56: GMV (mm) | E56: 50786.833 | F56: 48630.507 | G56: 61801.953 | H56: 51699.843 | I56: 16248.724 | J56: 20455.033 | K56: 44241.095 | L56: 37969.413 | M56: 33559.04 | N56: 51702.991 | O56: 43811.585 | P56: 29840.289 | Q56: 26168.167 | R56: 20903.894 | S56: 40178.061 | T56: 21858.835 | U56: 58753.418 | V56: 65551.884 | W56: =[6]机票!$V$54 -> 86039.071 | X56: 57224.751 | Y56: =[7]机票!$X$54 -> 72594.774 | Z56: =[8]机票!$Y$54 -> 63094.626 | AA56: 80171.899 | AB56: 56145.347 | AC56: 63421.733 | AD56: =[9]机票!$AC$62 -> 63002.921 | AE56: 75432.462 | AF56: =[10]机票!$AE$62 -> 51727.908 | AG56: =[11]机票!$AF$62 -> 64288.372 | AI56: =+SUM(E56:H56) -> 212919.14 | AJ56: =SUM(I56:L56) -> 118914.27 | AK56: =SUM(M56:P56) -> 158913.9 | AL56: =SUM(Q56:T56) -> 109108.96 | AM56: =SUM(U56:X56) -> 267569.12 | AN56: =SUM(Y56:AB56) -> 272006.65
D57: YoY | I57: =+I56/E56-1 -> -0.6800603 | J57: =+J56/F56-1 -> -0.57937857 | K57: =+K56/G56-1 -> -0.28414729 | L57: =+L56/H56-1 -> -0.26557972 | M57: =M56/E56-1 -> -0.33921771 | N57: =N56/F56-1 -> 0.063180171 | O57: =O56/G56-1 -> -0.29109707 | P57: =P56/H56-1 -> -0.42281665 | Q57: =Q56/E56-1 -> -0.48474504 | R57: =R56/F56-1 -> -0.57014855 | S57: =S56/G56-1 -> -0.34989011 | T57: =T56/H56-1 -> -0.57719727 | U57: =U56/E56-1 -> 0.1568632 | V57: =V56/F56-1 -> 0.34795807 | W57: =W56/G56-1 -> 0.39217398 | X57: =X56/H56-1 -> 0.10686508 | Y57: =Y56/U56-1 -> 0.23558384 | Z57: =Z56/V56-1 -> -0.037485696 | AA57: =AA56/W56-1 -> -0.068191949 | AB57: =AB56/X56-1 -> -0.018862548 | AC57: =AC56/Y56-1 -> -0.12635951 | AD57: =AD56/Z56-1 -> -0.0014534633 | AE57: =AE56/AA56-1 -> -0.059115933 | AF57: =AF56/AB56-1 -> -0.078678627 | AG57: =AG56/AC56-1 -> 0.0136647 | AJ57: =AJ56/AI56-1 -> -0.44150503 | AK57: =AK56/AI56-1 -> -0.25364198 | AL57: =AL56/AI56-1 -> -0.48755683 | AM57: =AM56/AI56-1 -> 0.25667016 | AN57: =AN56/AM56-1 -> 0.016584579
D58: Volume (mm) | E58: 61.195596 | F58: 60.862553 | G58: 70.350445 | H58: 68.839945 | I58: 19.844603 | J58: 36.435656 | K58: 67.954652 | L58: 62.295738 | M58: ='[12]OP DATA Combined'!$AJ$302 -> 50.494954 | N58: ='[13]OP DATA Combined'!$AK$302 -> 67.682373 | O58: 53.878776 | P58: ='[14]OP DATA'!$N$243 -> 43.118697 | Q58: =34901727/1000000 -> 34.901727 | R58: =(14565516+9201968)/1000000 -> 23.767484 | S58: 44.401354 | T58: =[15]机票!$S$17 -> 25.621592 | U58: =[16]机票!$T$17 -> 62.979381 | V58: 73.177451 | W58: =[6]机票!$V$17 -> 85.172816 | X58: =[17]机票!$W$17 -> 72.212789 | Y58: =[7]机票!$X$17 -> 80.208497 | Z58: =[8]机票!$Y$17 -> 75.868562 | AA58: =[18]机票!$Z$17 -> 90.492216 | AB58: =[19]机票!$AA$17 -> 77.280211 | AC58: =[20]机票!$AB$17 -> 77.920537 | AD58: =[9]机票!$AC$17 -> 77.002369 | AE58: 86.00031 | AF58: =[10]机票!$AE$17 -> 70.655404 | AG58: =[11]机票!$AF$17 -> 74.599907 | AI58: =+SUM(E58:H58) -> 261.24854 | AJ58: =SUM(I58:L58) -> 186.53065 | AK58: =SUM(M58:P58) -> 215.1748 | AL58: =SUM(Q58:T58) -> 128.69216 | AM58: =SUM(U58:X58) -> 293.54244 | AN58: =SUM(Y58:AB58) -> 323.84949
D59: YoY | I59: =+I58/E58-1 -> -0.67571844 | J59: =+J58/F58-1 -> -0.40134526 | K59: =+K58/G58-1 -> -0.034055122 | L59: =+L58/H58-1 -> -0.095064094 | M59: =M58/E58-1 -> -0.17485967 | N59: =N58/F58-1 -> 0.11205281 | O59: =O58/G58-1 -> -0.23413738 | P59: =P58/H58-1 -> -0.37363842 | Q59: =Q58/E58-1 -> -0.4296693 | R59: =R58/F58-1 -> -0.6094892 | S59: =S58/G58-1 -> -0.36885468 | T59: =T58/H58-1 -> -0.62780923 | U59: =U58/E58-1 -> 0.029148911 | V59: =V58/F58-1 -> 0.20233949 | W59: =W58/G58-1 -> 0.21069335 | X59: =X58/H58-1 -> 0.048995449 | Y59: =Y58/U58-1 -> 0.27356757 | Z59: =Z58/V58-1 -> 0.03677514 | AA59: =AA58/W58-1 -> 0.062454199 | AB59: =AB58/X58-1 -> 0.07017347 | AC59: =AC58/Y58-1 -> -0.028525157 | AD59: =AD58/Z58-1 -> 0.014944359 | AE59: =AE58/AA58-1 -> -0.04963859 | AF59: =AF58/AB58-1 -> -0.085724494 | AG59: =AG58/AC58-1 -> -0.042615594 | AJ59: =AJ58/AI58-1 -> -0.28600309 | AK59: =AK58/AI58-1 -> -0.1763598 | AL59: =AL58/AI58-1 -> -0.50739569 | AM59: =AM58/AI58-1 -> 0.1236137 | AN59: =AN58/AM58-1 -> 0.10324589
D60: ASP | E60: 829.90993 | F60: 799.02181 | G60: 878.48702 | H60: 753.3808 | I60: 818.79814 | J60: 561.40154 | K60: 651.03851 | L60: 609.50258 | M60: ='[12]OP DATA Combined'!$AJ$334 -> 664.60185 | N60: ='[13]OP DATA Combined'!$AK$334 -> 763.9063 | O60: =+O56/O58 -> 813.15109 | P60: =+P56/P58 -> 692.04987 | Q60: =+Q56/Q58 -> 749.76712 | R60: =+R56/R58 -> 879.51649 | S60: =+S56/S58 -> 904.88368 | T60: =[15]机票!$S$66 -> 853.14115 | U60: =+U56/U58 -> 932.89926 | V60: =+V56/V58 -> 895.79349 | W60: =+W56/W58 -> 1010.1706 | X60: 795.11382 | Y60: =+Y56/Y58 -> 905.07585 | Z60: =+Z56/Z58 -> 831.63071 | AA60: 889.17723 | AB60: 726.51648 | AC60: 813.92834 | AD60: =[9]机票!$AC$74 -> 818.19458 | AE60: 877.11849 | AF60: =[10]机票!$AE$75 -> 732.11538 | AG60: =[11]机票!$AF$75 -> 861.7755 | AH60: =AG60/AC60-1 -> 0.058785472 | AI60: =+AI56/AI58 -> 815.00603 | AJ60: =+AJ56/AJ58 -> 637.50524 | AK60: =+AK56/AK58 -> 738.53399 | AL60: =+AL56/AL58 -> 847.82911 | AM60: =+AM56/AM58 -> 911.51769 | AN60: =+AN56/AN58 -> 839.91687
D61: Take Rate | E61: 0.022076504 | F61: 0.023921865 | G61: 0.020702206 | H61: 0.022867981 | I61: 0.023654553 | J61: 0.034390431 | K61: 0.030205156 | L61: 0.033595329 | M61: 0.030173708 | N61: 0.027587814 | O61: 0.025546473 | P61: 0.028538218 | Q61: 0.027439329 | R61: 0.027038227 | S61: 0.028137736 | T61: 0.032130097 | U61: 0.028621411 | V61: 0.028080244 | W61: =[6]机票!$V$159 -> 0.021568785 | X61: =[17]机票!$W$159 -> 0.022395271 | Y61: =Y62/Y56 -> 0.021244288 | Z61: =Z62/Z56 -> 0.022489457 | AA61: =AA62/AA56 -> 0.020151003 | AB61: =AB62/AB56 -> 0.025029348 | AC61: =AC62/AC56 -> 0.023097154 | AD61: =AD62/AD56 -> 0.022576001 | AE61: =AE62/AE56 -> 0.021190034 | AF61: =AF62/AF56 -> 0.025158164 | AG61: =AG62/AG56 -> 0.019965496 | AI61: =+AI62/AI56 -> 0.022265471 | AJ61: =+AJ62/AJ56 -> 0.031112481 | AK61: =+AK62/AK56 -> 0.027749575 | AL61: =+AL62/AL56 -> 0.028559409 | AM61: =+AM62/AM56 -> 0.024880366 | AN61: =+AN62/AN56 -> 0.02199216
D62: Revenue (mm) | E62: 1121.1957 | F62: 1163.3324 | G62: 1279.4368 | H62: 1176.7798 | I62: 384.35631 | J62: 703.45741 | K62: 1336.3092 | L62: 1275.5949 | M62: 1012.6007 | N62: 1426.3725 | O62: 1119.2315 | P62: 851.58865 | Q62: 718.03695 | R62: 565.20423 | S62: 1130.5197 | T62: 702.32648 | U62: 1681.6057 | V62: 1840.7129 | W62: =[6]机票!$V$155 -> 1855.7582 | X62: 1279.1409 | Y62: =[7]机票!$X$155 -> 1542.2243 | Z62: =[8]机票!$Y$155 -> 1418.9639 | AA62: 1615.5442 | AB62: 1405.2814 | AC62: 1464.8615 | AD62: =[9]机票!$AC$167 -> 1422.354 | AE62: 1598.4165 | AF62: =[10]机票!$AE$105 -> 1301.3792 | AG62: =[11]机票!$AF$105 -> 1283.5493 | AI62: =+SUM(E62:H62) -> 4740.7448 | AJ62: =SUM(I62:L62) -> 3699.7178 | AK62: =SUM(M62:P62) -> 4409.7933 | AL62: =SUM(Q62:T62) -> 3116.0873 | AM62: =SUM(U62:X62) -> 6657.2178 | AN62: =SUM(Y62:AB62) -> 5982.0138 | AO62: gmv
D63: YoY | I63: =+I62/E62-1 -> -0.65719071 | J63: =+J62/F62-1 -> -0.39530835 | K63: =+K62/G62-1 -> 0.044451127 | L63: =+L62/H62-1 -> 0.083970749 | M63: =M62/E62-1 -> -0.096856471 | N63: =N62/F62-1 -> 0.22610913 | O63: =O62/G62-1 -> -0.1252155 | P63: =P62/H62-1 -> -0.27633988 | Q63: =Q62/E62-1 -> -0.35957931 | R63: =R62/F62-1 -> -0.51415072 | S63: =S62/G62-1 -> -0.11639271 | T63: =T62/H62-1 -> -0.40317937 | U63: =U62/E62-1 -> 0.49983244 | V63: =V62/F62-1 -> 0.58227592 | W63: =W62/G62-1 -> 0.45044935 | X63: =X62/H62-1 -> 0.086984066 | Y63: =Y62/U62-1 -> -0.08288592 | Z63: =Z62/V62-1 -> -0.22912266 | AA63: =AA62/W62-1 -> -0.12944255 | AB63: =AB62/X62-1 -> 0.098613445 | AC63: =AC62/Y62-1 -> -0.050163098 | AD63: =AD62/Z62-1 -> 0.002389174 | AE63: =AE62/AA62-1 -> -0.010601822 | AF63: =AF62/AB62-1 -> -0.073936956 | AG63: =AG62/AC62-1 -> -0.12377435 | AJ63: =AJ62/AI62-1 -> -0.21959144 | AK63: =AK62/AI62-1 -> -0.069810021 | AL63: =AL62/AI62-1 -> -0.34270089 | AM63: =AM62/AI62-1 -> 0.40425568 | AN63: =AN62/AM62-1 -> -0.10142436
D64: 单票收入 | E64: =E62/E58 -> 18.32151 | F64: =F62/F58 -> 19.114092 | G64: =G62/G58 -> 18.18662 | H64: =H62/H58 -> 17.094433 | I64: =I62/I58 -> 19.368304 | J64: =J62/J58 -> 19.306841 | K64: =K62/K58 -> 19.66472 | L64: =L62/L58 -> 20.47644 | ... AG64: =AG62/AG58 -> 17.205776 | AI64: =AI62/AI58 -> 18.146493 | AJ64: =AJ62/AJ58 -> 19.83437 | AK64: =AK62/AK58 -> 20.494004 | AL64: =AL62/AL58 -> 24.213498 | AM64: =AM62/AM58 -> 22.678894 | AN64: =AN62/AN58 -> 18.471586
D65: YoY | U65: =U64/Q64-1 -> 0.29785423 | V65: =V64/R64-1 -> 0.057758655 | W65: =W64/S64-1 -> -0.14426659 | X65: =X64/T64-1 -> -0.35379346 | Y65: =Y64/U64-1 -> -0.27988581 | Z65: =Z64/V64-1 -> -0.25646621 | AA65: =AA64/W64-1 -> -0.18061649 | AB65: =AB64/X64-1 -> 0.026575107 | ... AG65: =AG64/AC64-1 -> -0.084771339
D66: 同程-CQ单票收入 | E66: =E39-E64 -> 8.5385804 | F66: =F39-F64 -> 2.9884475 | G66: =G39-G64 -> 3.7458129 | H66: =H39-H64 -> 5.0713732 | I66: =I39-I64 -> 9.1916957 | J66: =J39-J64 -> 7.9731592 | K66: =K39-K64 -> 0.095280321 | L66: =L39-L64 -> 2.7235602 | ... AG66: =AG39-AG64 -> 6.3116875
D67: 同程-CQ ASP | U67: =U35-U60 -> -131.24228 | V67: =V35-V60 -> -254.80205 | W67: =W35-W60 -> -272.84726 | X67: =X35-X60 -> -204.18231 | Y67: =Y35-Y60 -> -261.3929 | Z67: =Z35-Z60 -> -270.17933 | AA67: =AA35-AA60 -> -242.65824 | AB67: =AB35-AB60 -> -167.46721 | ... AG67: =AG35-AG60 -> -164.48056
C68: TCEL AS % of C+Q Domestic
D69: GMV | E69: =E29/E56 -> 0.22850332 | F69: =F29/F56 -> 0.27901811 | G69: =G29/G56 -> 0.24978868 | H69: =H29/H56 -> 0.27979009 | I69: =I29/I56 -> 0.41676707 | J69: =J29/J56 -> 0.38331044 | K69: =K29/K56 -> 0.30925482 | L69: =L29/L56 -> 0.33109759 | ... AG69: =AG29/AG56 -> 0.34363504 | AI69: =+AI29/AI56 -> 0.25867231 | AJ69: =+AJ29/AJ56 -> 0.34365863 | AK69: =+AK29/AK56 -> 0.34412512 | AL69: =+AL29/AL56 -> 0.39569303 | AM69: =+AM29/AM56 -> 0.27747569 | AN69: =+AN29/AN56 -> 0.27462474
D70: Rev | E70: =E37/E62 -> 0.40794931 | F70: =F37/F62 -> 0.39704999 | G70: =G37/G62 -> 0.36671898 | H70: =H37/H62 -> 0.42105675 | I70: =I37/I62 -> 0.73999356 | J70: =J37/J62 -> 0.49041722 | K70: =K37/K62 -> 0.38906215 | L70: =L37/L62 -> 0.39421859 | ... AG70: =AG37/AG62 -> 0.58048538 | AI70: =AI37/AI62 -> 0.39740106 | AJ70: =AJ37/AJ62 -> 0.44656903 | AK70: =AK37/AK62 -> 0.46894871 | AL70: =AL37/AL62 -> 0.4942649 | AM70: =AM37/AM62 -> 0.37813053 | AN70: =AN37/AN62 -> 0.47778752
D71: Volume | E71: =E32/E58 -> 0.27826591 | F71: =F32/F58 -> 0.34336552 | G71: =G32/G58 -> 0.3040875 | H71: =H32/H58 -> 0.32472207 | I71: =I32/I58 -> 0.50183545 | J71: =J32/J58 -> 0.34708238 | K71: =K32/K58 -> 0.38718614 | L71: =L32/L58 -> 0.34793937 | ... AG71: =AG32/AG58 -> 0.42469297 | AI71: =AI32/AI58 -> 0.31262678 | AJ71: =AJ32/AJ58 -> 0.37844257 | AK71: =AK32/AK58 -> 0.41322869 | AL71: =AL32/AL58 -> 0.47617438 | AM71: =AM32/AM58 -> 0.36673675 | AN71: =AN32/AN58 -> 0.38191782
D72: ASP | E72: =E35/E60 -> 0.82116896 | F72: =F35/F60 -> 0.81259792 | G72: =G35/G60 -> 0.82143686 | H72: =H35/H60 -> 0.8589239 | I72: =I35/I60 -> 0.83048552 | J72: =J35/J60 -> 1.1043789 | K72: =K35/K60 -> 0.79872388 | L72: =L35/L60 -> 0.95159564 | ... AG72: =AG35/AG60 -> 0.80913758 | AI72: =AI35/AI60 -> 0.8274157 | AJ72: =AJ35/AJ60 -> 0.90808661 | AK72: =AK35/AK60 -> 0.83277162 | AL72: =AL35/AL60 -> 0.83098346 | AM72: =AM35/AM60 -> 0.75660726 | AN72: =AN35/AN60 -> 0.71906761
C73: TCOM - C+Q Outboud Air
D74: GMV (mm) - | E74: 17407.188 | F74: 19305.643 | G74: 19380.72 | H74: 18486.232 | I74: 6810.338 | J74: -838.19865 | K74: 646.47272 | L74: 880.72042 | M74: 850.06299 | N74: 1971.8064 | O74: 2066.507 | P74: 1729.3273 | Q74: 2010.1297 | R74: 2916.2623 | S74: 4587.367 | T74: 5662.1591 | U74: 11337.618 | V74: 17269.917 | W74: 20071.77 | X74: 17551.761 | Y74: 20866.269 | Z74: 23166.573 | AA74: 24510.721 | AB74: 23617.52 | AC74: 21526.292 | AD74: =[9]机票!$AC$63 -> 25799.984 | AE74: 28737.641 | AF74: =[10]机票!$AE$63 -> 25733.454 | AG74: =[11]机票!$AF$63 -> 28080.293 | AH74: op data机票63 | AI74: =+SUM(E74:H74) -> 74579.782 | AJ74: =SUM(I74:L74) -> 7499.3325 | AK74: =SUM(M74:P74) -> 6617.7037 | AL74: =SUM(Q74:T74) -> 15175.918 | AM74: =SUM(U74:X74) -> 66231.065 | AN74: =SUM(Y74:AB74) -> 92161.083
D75: YoY | M75: =M74/E74-1 -> -0.95116598 | N75: =N74/F74-1 -> -0.89786372 | O75: =O74/G74-1 -> -0.89337305 | P75: =P74/H74-1 -> -0.90645323 | Q75: =Q74/E74-1 -> -0.88452301 | R75: =R74/F74-1 -> -0.84894249 | S75: =S74/G74-1 -> -0.76330254 | T75: =T74/H74-1 -> -0.6937094 | U75: =U74/E74-1 -> -0.34868185 | V75: =V74/F74-1 -> -0.1054472 | W75: =W74/G74-1 -> 0.035656592 | X75: =X74/H74-1 -> -0.050549573 | Y75: =Y74/U74-1 -> 0.84044564 | Z75: =Z74/V74-1 -> 0.34144096 | AA75: =AA74/W74-1 -> 0.22115394 | AB75: =AB74/X74-1 -> 0.34559259 | AC75: =AC74/Y74-1 -> 0.031631086 | AD75: =AD74/Z74-1 -> 0.11367285 | AE75: =AE74/AA74-1 -> 0.17245186 | AF75: =AF74/AB74-1 -> 0.089591727 | AG75: =AG74/AC74-1 -> 0.30446496
D76: Volume (mm) | E76: 13.055273 | F76: 13.999423 | G76: 13.865315 | H76: 14.399249 | I76: 2.60131 | J76: -0.413359 | K76: 0.104582 | L76: 0.295057 | M76: 0.345412 | N76: 0.682022 | O76: 0.614088 | P76: 0.686068 | Q76: 0.703622 | R76: 1.000128 | S76: 1.483552 | T76: 2.207107 | U76: 5.423551 | V76: 9.172843 | W76: 10.694162 | X76: 10.835566 | Y76: 13.30611 | Z76: 14.86663 | AA76: 16.062876 | AB76: 16.43386 | AC76: 14.837998 | AD76: =[9]机票!$AC$18 -> 17.648578 | AE76: 19.159963 | AF76: =[10]机票!$AE$18 -> 17.404578 | AG76: =[11]机票!$AF$18 -> 18.657011 | AI76: =+SUM(E76:H76) -> 55.31926 | AJ76: =SUM(I76:L76) -> 2.58759 | AK76: =SUM(M76:P76) -> 2.32759 | AL76: =SUM(Q76:T76) -> 5.394409 | AM76: =SUM(U76:X76) -> 36.126122 | AN76: =SUM(Y76:AB76) -> 60.669476
D77: YoY vs 2019 | M77: =M76/E76-1 -> -0.97354234 | N77: =N76/F76-1 -> -0.95128213 | O77: =O76/G76-1 -> -0.95571049 | P77: =P76/H76-1 -> -0.9523539 | Q77: =Q76/E76-1 -> -0.94610438 | R77: =R76/F76-1 -> -0.92855934 | S77: =S76/G76-1 -> -0.89300265 | T77: =T76/H76-1 -> -0.84672069 | U77: =U76/E76-1 -> -0.58457008 | V77: =V76/F76-1 -> -0.34476992 | W77: =W76/G76-1 -> -0.22871121 | X77: =X76/H76-1 -> -0.24749089 | Y77: =Y76/U76-1 -> 1.4533945 | Z77: =Z76/V76-1 -> 0.62072217 | AA77: =AA76/W76-1 -> 0.50202288 | AB77: =AB76/X76-1 -> 0.51665912 | AC77: =AC76/Y76-1 -> 0.11512666 | AD77: =AD76/Z76-1 -> 0.18712701 | AE77: =AE76/AA76-1 -> 0.19281024 | AF77: =AF76/AB76-1 -> 0.059068168 | AG77: =AG76/AC76-1 -> 0.25738061
D78: ASP | E78: 1333.3454 | F78: 1379.0313 | G78: 1397.7843 | H78: 1283.8331 | I78: 2618.0417 | J78: 2027.774 | K78: 6181.4912 | L78: 2984.9162 | M78: 2461.0118 | N78: 2891.1185 | O78: 3365.1642 | P78: 2520.6355 | Q78: 2856.8318 | R78: 2915.8891 | S78: 3092.1512 | T78: 2565.4212 | U78: 2090.4418 | V78: 1882.7223 | W78: 1876.8904 | X78: 1619.8287 | Y78: 1568.172 | Z78: 1558.2935 | AA78: 1525.9236 | AB78: 1437.1255 | AC78: 1450.7545 | AD78: =[9]机票!$AC$75 -> 1461.8732 | AE78: 1499.8798 | AF78: =[10]机票!$AE$76 -> 1478.5451 | AG78: =[11]机票!$AF$76 -> 1505.08 | AI78: =AI74/AI76 -> 1348.1703 | AJ78: =AJ74/AJ76 -> 2898.192 | AK78: =AK74/AK76 -> 2843.157 | AL78: =AL74/AL76 -> 2813.268 | AM78: =AM74/AM76 -> 1833.3289 | AN78: =AN74/AN76 -> 1519.0684
D79: Take Rate | E79: 0.034457988 | F79: 0.038588789 | G79: 0.037804801 | H79: 0.037992169 | I79: 0.056526205 | J79: -0.095705551 | K79: 0.088868385 | L79: 0.059336752 | M79: 0.077315431 | N79: 0.0370226 | O79: 0.028709945 | P79: 0.030897794 | Q79: 0.030088508 | R79: 0.039777002 | S79: 0.035758672 | T79: 0.039768847 | U79: 0.03746522 | V79: 0.035353126 | W79: 0.036241547 | X79: 0.040943273 | Y79: 0.039479226 | Z79: 0.03861342 | AA79: 0.039012319 | AB79: 0.039291585 | AC79: 0.03841887 | AD79: =[9]机票!$AC$172 -> 0.036060867 | AE79: 0.035929501 | AF79: =[10]机票!$AE$81 -> 0.036219568 | AG79: =[11]机票!$AF$81 -> 0.034269621 | AI79: =AI80/AI74 -> 0.037273028 | AJ79: =AJ80/AJ74 -> 0.07665921 | AK79: =AK80/AK74 -> 0.038002017 | AL79: =AL80/AL74 -> 0.037276009 | AM79: =AM80/AM74 -> 0.037465355 | AN79: =AN80/AN74 -> 0.039089326
D80: Revenue (mm) | E80: 599.81669 | F80: 744.98136 | G80: 732.68425 | H80: 702.33205 | I80: 384.96257 | J80: 80.220263 | K80: 57.450986 | L80: 52.25909 | M80: 65.722987 | N80: 73.0014 | O80: 59.329303 | P80: 53.432399 | Q80: 60.481802 | R80: 116.00017 | S80: 164.03815 | T80: 225.17754 | U80: 424.76634 | V80: 610.54553 | W80: 727.43199 | X80: 718.62654 | Y80: 823.78416 | Z80: 894.54062 | AA80: 956.22006 | AB80: 927.96978 | AC80: 827.0158 | AD80: =[9]机票!$AC$168 -> 930.36978 | AE80: 1032.5291 | AF80: =[10]机票!$AE$106 -> 932.05459 | AG80: =[11]机票!$AF$106 -> 962.30101 | AI80: =+SUM(E80:H80) -> 2779.8144 | AJ80: =SUM(I80:L80) -> 574.8929 | AK80: =SUM(M80:P80) -> 251.48609 | AL80: =SUM(Q80:T80) -> 565.69766 | AM80: =SUM(U80:X80) -> 2481.3704 | AN80: =SUM(Y80:AB80) -> 3602.5146
D81: YoY | M81: =M80/E80-1 -> -0.89042821 | N81: =N80/F80-1 -> -0.90200909 | O81: =O80/G80-1 -> -0.91902473 | P81: =P80/H80-1 -> -0.92392146 | Q81: =Q80/E80-1 -> -0.89916619 | R81: =R80/F80-1 -> -0.84429118 | S81: =S80/G80-1 -> -0.77611345 | T81: =T80/H80-1 -> -0.67938593 | U81: =U80/E80-1 -> -0.29183974 | V81: =V80/F80-1 -> -0.18045529 | W81: =W80/G80-1 -> -0.0071685193 | X81: =X80/H80-1 -> 0.023200545 | Y81: =Y80/U80-1 -> 0.93938192 | Z81: =Z80/V80-1 -> 0.46514972 | AA81: =AA80/W80-1 -> 0.31451472 | AB81: =AB80/X80-1 -> 0.2913102 | AC81: =AC80/Y80-1 -> 0.0039229219 | AD81: =AD80/Z80-1 -> 0.040053136 | AE81: =AE80/AA80-1 -> 0.079802781 | AF81: =AF80/AB80-1 -> 0.004401879 | AG81: =AG80/AC80-1 -> 0.16358238
D82: 单票收入 | E82: =E80/E76 -> 45.9444 | F82: =F80/F76 -> 53.215148 | G82: =G80/G76 -> 52.842958 | H82: =H80/H76 -> 48.775603 | I82: =I80/I76 -> 147.98796 | J82: =J80/J76 -> -194.06923 | K82: =K80/K76 -> 549.33914 | L82: =L80/L76 -> 177.11523 | ... AG82: =AG80/AG76 -> 51.57852 | AI82: =AI80/AI76 -> 50.250389 | AJ82: =AJ80/AJ76 -> 222.17311 | AK82: =AK80/AK76 -> 108.0457 | AL82: =AL80/AL76 -> 104.8674 | AM82: =AM80/AM76 -> 68.686321 | AN82: =AN80/AN76 -> 59.379359
D83: YoY | U83: =U82/Q82-1 -> -0.08886852 | V83: =V82/R82-1 -> -0.42613325 | W83: =W82/S82-1 -> -0.38481811 | X83: =X82/T82-1 -> -0.3499452 | Y83: =Y82/U82-1 -> -0.20951076 | Z83: =Z82/V82-1 -> -0.095989585 | AA83: =AA82/W82-1 -> -0.12483709 | AB83: =AB82/X82-1 -> -0.14858244 | ... AG83: =AG82/AC82-1 -> -0.074598118
D84: 同程-CQ单票收入 | E84: =E53-E82 -> 9.4387965 | F84: =F53-F82 -> 9.0336758 | G84: =G53-G82 -> -3.3429577 | H84: =H53-H82 -> -5.2070314 | I84: =I53-I82 -> -147.98796 | J84: =J53-J82 -> 194.06923 | K84: =K53-K82 -> -549.33914 | L84: =L53-L82 -> -177.11523 | ... AG84: =AG53-AG82 -> -17.916822
D85: 同程-CQ ASP | U85: =U48-U78 -> -37.17361 | V85: =V48-V78 -> -28.976104 | W85: =W48-W78 -> -414.80855 | X85: =X48-X78 -> -119.77179 | Y85: =Y48-Y78 -> -312.81428 | Z85: =Z48-Z78 -> -410.41324 | AA85: =AA48-AA78 -> -410.27947 | AB85: =AB48-AB78 -> -100.45692 | ... AG85: =AG48-AG78 -> -383.02337
C86: TCEL AS % of C+Q Outbound Air
D87: GMV | E87: =E42/E74 -> 0.078213423 | F87: =F42/F74 -> 0.08421496 | G87: =G42/G74 -> 0.098448189 | H87: =H42/H74 -> 0.10167817 | U87: =U42/U74 -> 0.15518161 | V87: =V42/V74 -> 0.14026465 | W87: =W42/W74 -> 0.13675989 | X87: =X42/X74 -> 0.15622683 | Y87: =Y42/Y74 -> 0.18564336 | Z87: =Z42/Z74 -> 0.16418761 | AA87: =AA42/AA74 -> 0.1791261 | AB87: =AB42/AB74 -> 0.15621941 | ... AG87: =AG42/AG74 -> 0.19057546 | AI87: =AI42/AI74 -> 0.090841545 | AM87: =AM42/AM74 -> 0.14598614 | AN87: =AN42/AN74 -> 0.17097643
D88: Rev | E88: =E51/E80 -> 0.10214189 | F88: =F51/F80 -> 0.093841849 | G88: =G51/G80 -> 0.11718534 | H88: =H51/H80 -> 0.10437542 | U88: =U51/U80 -> 0.12426054 | V88: =V51/V80 -> 0.11902595 | W88: =W51/W80 -> 0.113207 | X88: =X51/X80 -> 0.076313799 | Y88: =Y51/Y80 -> 0.084641491 | Z88: =Z51/Z80 -> 0.085041732 | AA88: =AA51/AA80 -> 0.096422057 | AB88: =AB51/AB80 -> 0.10138545 | ... AG88: =AG51/AG80 -> 0.16683183 | AI88: =AI51/AI80 -> 0.10444687 | AM88: =AM51/AM80 -> 0.10584634 | AN88: =AN51/AN80 -> 0.092180872
D89: Volume | E89: =E45/E76 -> 0.084734145 | F89: =F45/F76 -> 0.080223329 | G89: =G45/G76 -> 0.12509939 | H89: =H45/H76 -> 0.11684969 | U89: =U45/U76 -> 0.15799111 | V89: =V45/V76 -> 0.14245714 | W89: =W45/W76 -> 0.17556016 | X89: =X45/X76 -> 0.16870074 | Y89: =Y45/Y76 -> 0.23190261 | Z89: =Z45/Z76 -> 0.22289126 | AA89: =AA45/AA76 -> 0.24499993 | AB89: =AB45/AB76 -> 0.16796003 | ... AG89: =AG45/AG76 -> 0.25562998 | AI89: =AI45/AI76 -> 0.1020693 | AM89: =AM45/AM76 -> 0.16245991 | AN89: =AN45/AN76 -> 0.21584163
D90: ASP | E90: =E48/E78 -> 0.92304493 | F90: =F48/F78 -> 1.0497565 | G90: =G48/G78 -> 0.78695976 | H90: =H48/H78 -> 0.87016208 | U90: =U48/U78 -> 0.98221734 | V90: =V48/V78 -> 0.98460947 | W90: =W48/W78 -> 0.7789916 | X90: =X48/X78 -> 0.92605898 | Y90: =Y48/Y78 -> 0.80052298 | Z90: =Z48/Z78 -> 0.73662649 | AA90: =AA48/AA78 -> 0.73112712 | AB90: =AB48/AB78 -> 0.93009872 | ... AG90: =AG48/AG78 -> 0.74551294 | AI90: =AI48/AI78 -> 0.88999873 | AM90: =AM48/AM78 -> 0.89859793 | AN90: =AN48/AN78 -> 0.79213835
L91: =L112+L62 -> 1539.4025
C92: Train | E92: 1Q19 | F92: 2Q19 | G92: 3Q19 | H92: 4Q19 | I92: 20Q1 | J92: 20Q2 | K92: 20Q3 | L92: 20Q4 | M92: 21Q1 | N92: 21Q2 | O92: 21Q3 | P92: 21Q4 | Q92: 22Q1 | R92: 22Q2 | S92: 22Q3 | T92: 22Q4 | U92: 23Q1 | V92: 23Q2 | W92: 23Q3 | X92: 23Q4 | Y92: 24Q1 | Z92: 24Q2 | AA92: 24Q3 | AB92: 24Q4 | AC92: 25Q1 | AD92: 25Q2 | AE92: 25Q3 | AF92: 25Q4 | AG92: 26Q1 | AI92: 2019 | AJ92: 2020 | AK92: 2021 | AL92: 2022 | AM92: 2023 | AN92: 2024
C93: TCEL | I93: =I96*I94 -> 78.024448
D94: GMV (mm RMB, net, 扣除退票) | E94: =+E11*E97 -> 15680.341 | F94: =+F11*F97 -> 16545.249 | G94: =+G11*G97 -> 18489.079 | H94: =+H11*H97 -> 16000.65 | I94: =+I11*I97 -> 7802.4448 | J94: =+J11*J97 -> 9234.5173 | K94: =+K11*K97 -> 16418.126 | L94: =+L11*L97 -> 14211.352 | M94: =+M11*M97 -> 11689.782 | N94: =N11*N97 -> 15174.202 | O94: =O11*O97 -> 13974.407 | P94: =P11*P97 -> 10672.831 | Q94: =Q11*Q97 -> 10331.078 | R94: =R11*R97 -> 7073.3708 | S94: =S11*S97 -> 12855.706 | T94: =T11*T97 -> 6958.7466 | U94: =U11*U97 -> 16817.696 | ... AG94: =AG11*AG97 -> 16851.058 | AI94: =+SUM(E94:H94) -> 66715.319 | AJ94: =SUM(I94:L94) -> 47666.441 | AK94: =SUM(M94:P94) -> 51511.221 | AL94: =SUM(Q94:T94) -> 37218.901 | AM94: =SUM(U94:X94) -> 70241.82 | AN94: =SUM(Y94:AB94) -> 70137.162
D95: YoY | I95: =+I94/E94-1 -> -0.50240593 | J95: =+J94/F94-1 -> -0.44186288 | K95: =+K94/G94-1 -> -0.11200954 | L95: =+L94/H94-1 -> -0.11182656 | M95: =M94/E94-1 -> -0.25449442 | N95: =N94/F94-1 -> -0.082866506 | O95: =O94/G94-1 -> -0.24418051 | P95: =P94/H94-1 -> -0.33297515 | Q95: =Q94/E94-1 -> -0.34114455 | R95: =R94/F94-1 -> -0.57248326 | S95: =S94/G94-1 -> -0.30468653 | T95: =T94/H94-1 -> -0.565096 | U95: =U94/E94-1 -> 0.07253384 | V95: =V94/F94-1 -> 0.026285859 | W95: =W94/G94-1 -> 0.15068729 | X95: =X94/H94-1 -> -0.051987221 | Y95: =Y94/U94-1 -> 0.17554744 | Z95: =Z94/V94-1 -> -0.05956475 | AA95: =AA94/W94-1 -> -0.058585376 | AB95: =AB94/X94-1 -> -0.052682453 | AC95: =AC94/Y94-1 -> -0.06998 | AD95: =AD94/Z94-1 -> -0.034605181 | AE95: =AE94/AA94-1 -> -0.028314917 | AF95: =AF94/AB94-1 -> -0.042434716 | AG95: =AG94/AC94-1 -> -0.083508957 | AJ95: =AJ94/AI94-1 -> -0.2855248 | AK95: =AK94/AI94-1 -> -0.22789515 | AL95: =AL94/AI94-1 -> -0.44212361 | AM95: =AM94/AI94-1 -> 0.052858943 | AN95: =AN94/AM94-1 -> -0.0014899713
D96: 汽车票占交通GMV | E96: 0 | F96: 0.01 | G96: 0.01 | H96: 0.01 | I96: 0.01 | J96: 0.02 | K96: 0.01 | L96: 0.02 | M96: 0.08 | N96: 0.08 | O96: 0.09 | P96: 0.1 | Q96: 0.12 | R96: 0.12 | S96: 0.09 | T96: 0.12 | U96: 0.11 | V96: 0.1 | W96: 0.1 | X96: 0.11 | Y96: 0.1 | Z96: 0.1 | AA96: 0.1 | AB96: 0.11 | AC96: 0.12 | AD96: 0.11 | AE96: 0.11 | AF96: 0.1 | AG96: 0.05
D97: % of Trans GMV | E97: =1-E20-E96-5% -> 0.52 | F97: =1-F20-F96-5% -> 0.49 | G97: =1-G20-G96-5% -> 0.485 | H97: =1-H20-H96-5% -> 0.465 | I97: =1-I20-I96 -> 0.53 | J97: =1-J20-J96 -> 0.53 | K97: =1-K20-K96 -> 0.54 | L97: =1-L20-L96 -> 0.52 | M97: =1-M20-M96 -> 0.44 | N97: =1-N20-N96 -> 0.45 | O97: =1-O20-O96 -> 0.44 | P97: =1-P20-P96 -> 0.44 | Q97: =1-Q20-Q96 -> 0.41 | R97: =1-R20-R96-1.5% -> 0.395 | S97: =1-1%-S96-S20 -> 0.425 | T97: =1-4%-T96-T20 -> 0.377 | U97: =1-2%-U20-U96 -> 0.39 | V97: =1-V20-V96-1.5% -> 0.395 | W97: =1-W20-W96-3% -> 0.41 | X97: =1-X20-X96-3% -> 0.39 | Y97: =1-2.5%-Y20-Y96 -> 0.4 | Z97: =1-5%-Z20-Z96 -> 0.36 | AA97: =1-3%-AA20-AA96 -> 0.38 | AB97: =1-2%-AB20-AB96 -> 0.37 | AC97: =1-1%-AC20-AC96 -> 0.39 | AD97: =1-1%-AD20-AD96 -> 0.35 | AE97: =1-1%-AE20-AE96 -> 0.38 | AF97: =1-2%-AF20-AF96 -> 0.354 | AG97: =1-3%-AG20-AG96 -> 0.35 | AH97: 假设用车占比提升至3% | AI97: =AI94/AI11 -> 0.48892839 | AJ97: =AJ94/AJ11 -> 0.53034206 | AK97: =AK94/AK11 -> 0.44289932 | AL97: =AL94/AL11 -> 0.40538187 | AM97: =AM94/AM11 -> 0.39708189 | AN97: =AN94/AN11 -> 0.37845127
D98: Volume (mm, net, 扣除退票） | E98: =E94/E100 -> 110.42494 | F98: =F94/F100 -> 124.40037 | G98: =G94/G100 -> 132.06485 | H98: =H94/H100 -> 118.52333 | I98: =I94/I100 -> 55.731748 | J98: =J94/J100 -> 71.034749 | K98: =K94/K100 -> 123.44456 | L98: =L94/L100 -> 111.02619 | ... AG98: =AG94/AG100 -> 105.31911 | AI98: =+SUM(E98:H98) -> 485.41349 | AJ98: =SUM(I98:L98) -> 361.23724 | AK98: =SUM(M98:P98) -> 371.63423 | AL98: =SUM(Q98:T98) -> 235.58443 | AM98: =SUM(U98:X98) -> 462.52134 | AN98: =SUM(Y98:AB98) -> 471.51597 | AP98: 21年票量比20年微降
D99: YoY | I99: =+I98/E98-1 -> -0.49529744 | J99: =+J98/F98-1 -> -0.4289828 | K99: =+K98/G98-1 -> -0.065273201 | L99: =L98/H98-1 -> -0.063254571 | M99: =M98/E98-1 -> -0.24384434 | N99: =N98/F98-1 -> -0.12872318 | O99: =O98/G98-1 -> -0.21618719 | P99: =P98/H98-1 -> -0.35679747 | Q99: =Q98/E98-1 -> -0.39248394 | R99: =R98/F98-1 -> -0.6283678 | S99: =S98/G98-1 -> -0.39160071 | T99: =T98/H98-1 -> -0.64631301 | U99: =U98/E98-1 -> -0.059877745 | V99: =V98/F98-1 -> -0.090026539 | W99: =W98/G98-1 -> 0.032668077 | X99: =X98/H98-1 -> -0.079268164 | Y99: =Y98/U98-1 -> 0.20530814 | Z99: =Z98/V98-1 -> -0.013529458 | AA99: =AA98/W98-1 -> -0.020928791 | AB99: =AB98/X98-1 -> -0.072696204 | AC99: =AC98/Y98-1 -> -0.06998 | AD99: =AD98/Z98-1 -> -0.060874428 | AE99: =AE98/AA98-1 -> -0.089045235 | AF99: =AF98/AB98-1 -> -0.028755212 | AG99: =AG98/AC98-1 -> -0.094965095 | AH99: 火车票票量整体下降 | AJ99: =AJ98/AI98-1 -> -0.2558154 | AK99: =AK98/AI98-1 -> -0.23439658 | AL99: =AL98/AI98-1 -> -0.51467268 | AM99: =AM98/AI98-1 -> -0.047160109 | AN99: =AN98/AM98-1 -> 0.019446964
D100: ASP | E100: 142 | F100: 133 | G100: 140 | H100: 135 | I100: 140 | J100: 130 | K100: 133 | L100: 128 | M100: 140 | N100: 140 | O100: 135 | P100: 140 | Q100: 154 | R100: 153 | S100: 160 | T100: 166 | U100: 162 | V100: 150 | W100: 156 | X100: 139 | Y100: 158 | Z100: 143 | AA100: 150 | AB100: 142 | AC100: 158 | AD100: 147 | AE100: 160 | AF100: 140 | AG100: 160 | AH100: 价格略有提升 | AI100: =+AI94/AI98 -> 137.44018 | AJ100: =+AJ94/AJ98 -> 131.95328 | AK100: =+AK94/AK98 -> 138.60731 | AL100: =+AL94/AL98 -> 157.98541 | AM100: =+AM94/AM98 -> 151.8672 | AN100: =+AN94/AN98 -> 148.74822
...

Sheet Sheet8

Sheet 酒店业务国际拆分
A1: 同程酒店业务（mn RMB) | C1: 23Q1 | D1: 23Q2 | E1: 23Q3 | F1: 23Q4 | G1: 24Q1 | H1: 24Q2 | I1: 24Q3 | J1: 24Q4 | K1: 25Q1 | L1: 25Q2 | M1: 25Q3
A2: TCEL-酒店整体
B3: GMV (mm) | C3: =Tongchengelong!AP6/1000 -> 10296 | D3: =Tongchengelong!AQ6/1000 -> 11641.5 | E3: =Tongchengelong!AR6/1000 -> 13864.5 | F3: =Tongchengelong!AS6/1000 -> 10860.5 | G3: =Tongchengelong!AT6/1000 -> 11466.6 | H3: =Tongchengelong!AU6/1000 -> 12584.6 | I3: =Tongchengelong!AV6/1000 -> 14196 | J3: =Tongchengelong!AW6/1000 -> 11760.5 | ... M3: =Tongchengelong!AZ6/1000 -> 16434.6
B4: YoY | G4: =G3/C3-1 -> 0.11369464 | H4: =H3/D3-1 -> 0.081011897 | I4: =I3/E3-1 -> 0.023909986 | J4: =J3/F3-1 -> 0.082869113 | K4: =K3/G3-1 -> 0.070114943 | L4: =L3/H3-1 -> 0.085 | M4: =M3/I3-1 -> 0.15769231
B5: Volume (mm) | C5: =[24]TTM国内酒店对比!$D$111 -> 47.30544 | D5: =[24]TTM国内酒店对比!$D$118 -> 54.162 | E5: =[24]TTM国内酒店对比!$D$125 -> 57.6665 | F5: =[24]TTM国内酒店对比!$D$132 -> 47.988 | G5: =G15/G16 -> 52.350718 | H5: =D5*(1+H6) -> 59.5782 | K5: =K15+K26 -> 59.332209 | L5: =L15+L26 -> 67.488517 | M5: =M15+M26 -> 0
B6: YoY | H6: 0.1
B7: ADR
B8: Take rate | C8: =C9/C3 -> 0.081027681 | D8: =D9/D3 -> 0.090658077 | E8: =E9/E3 -> 0.081315662 | F8: =F9/F3 -> 0.081253718 | G8: =G9/G3 -> 0.084129821 | H8: =H9/H3 -> 0.094629865 | I8: =I9/I3 -> 0.097037264 | J8: =J9/J3 -> 0.096515964 | ... M8: =M9/M3 -> 0.096106507 | Q8: 24Q1： 国际机票+国际酒店的收入占整体酒店+交通的3-4%，机票占比更高，酒店占比低一些。
B9: Revenue (mm) | C9: =Tongchengelong!AP13/1000 -> 834.261 | D9: =Tongchengelong!AQ13/1000 -> 1055.396 | E9: =Tongchengelong!AR13/1000 -> 1127.401 | F9: =Tongchengelong!AS13/1000 -> 882.456 | G9: =Tongchengelong!AT13/1000 -> 964.683 | H9: =Tongchengelong!AU13/1000 -> 1190.879 | I9: =Tongchengelong!AV13/1000 -> 1377.541 | J9: =Tongchengelong!AW13/1000 -> 1135.076 | ... M9: =Tongchengelong!AZ13/1000 -> 1579.472 | N9: 公司披露 | R9: 国际酒店量占比1-2%
B10: YoY | G10: =G9/C9-1 -> 0.15633237 | H10: =H9/D9-1 -> 0.12837172 | I10: =I9/E9-1 -> 0.22187314 | J10: =J9/F9-1 -> 0.28626923 | K10: =K9/G9-1 -> 0.23319474 | L10: =L9/H9-1 -> 0.15155864
A11: TCEL-国内
B12: GMV (mm) - net
B13: % of Total hotel
B14: YoY
B15: Volume (mm) | C15: =C5*C16 -> 47.210829 | D15: =D5*D16 -> 53.999514 | E15: =E5*E16 -> 57.435834 | F15: =F5*F16 -> 47.844036 | G15: =C15*(1+G17) -> 51.931912 | H15: =H5-H26 -> 59.184984 | I15: =I5-I26 -> -0.53514512 | J15: =J5-J26 -> -0.20442888 | K15: =(1+K17)*G15 -> 58.683061 | L15: =(1+L17)*H15 -> 66.879032
B16: % of Total hotel | C16: =1-C27 -> 0.998 | D16: =1-D27 -> 0.997 | E16: =1-E27 -> 0.996 | F16: =1-F27 -> 0.997 | G16: =1-G27 -> 0.992 | H16: =1-H27 -> 0.99 | I16: =1-I27 -> 0.988 | J16: =1-J27 -> 0.985 | ... L16: =1-L27 -> 0.985
B17: YoY | G17: 0.1 | H17: =H15/D15-1 -> 0.096028084 | K17: 0.13 | L17: 0.13
B18: ADR
B19: Take rate
B20: Revenue (mm)
B21: YoY
A22: TCEL-国际
B23: GMV (mm) - net
B24: % of Total Air
B25: YoY
B26: Volume (mm) | C26: =C5-C15 -> 0.09461088 | D26: =D5-D15 -> 0.162486 | E26: =E5-E15 -> 0.230666 | F26: =F5-F15 -> 0.143964 | G26: =G5-G15 -> 0.41880574 | H26: =D26*(1+H28) -> 0.39321612 | I26: =E26*(1+I28) -> 0.53514512 | J26: =F26*(1+J28) -> 0.20442888 | K26: =G26*(1+K28) -> 0.6491489 | L26: =H26*(1+L28) -> 0.60948499
B27: % of Total Hotel | C27: 0.002 | D27: 0.003 | E27: 0.004 | F27: 0.003 | G27: 0.008 | H27: 0.01 | I27: 0.012 | J27: 0.015 | K27: 0.015 | L27: 0.015
B28: YoY | H28: 1.42 | I28: 1.32 | J28: 0.42 | K28: 0.55 | L28: 0.55
B29: ASP
B31: Take rate
B32: Revenue (mm)
B33: YoY

Sheet Summary
B2: TC国内 | D2: 1Q19 | E2: 2Q19 | F2: 3Q19 | G2: 4Q19 | H2: 20Q1 | I2: 20Q2 | J2: 20Q3 | K2: 20Q4 | L2: 21Q1 | M2: 21Q2 | N2: 21Q3 | O2: 21Q4 | P2: 22Q1 | Q2: 22Q2 | R2: 22Q3 | S2: 22Q4 | T2: 23Q1 | U2: 23Q2 | V2: 23Q3 | W2: 23Q4 | X2: 24Q1 | Y2: 24Q2 | Z2: 24Q3 | AA2: 24Q4 | AB2: 25Q1 | AC2: 25Q2 | AD2: 25Q3 | AE2: 25Q4 | AF2: 26Q1
B3: TC国内
C4: 占TC机票GMV比 | T4: =+交通业务拆分!U30 -> 0.915 | U4: =+交通业务拆分!V30 -> 0.885 | V4: =+交通业务拆分!W30 -> 0.885 | W4: =+交通业务拆分!X30 -> 0.85 | X4: =+交通业务拆分!Y30 -> 0.835 | Y4: =+交通业务拆分!Z30 -> 0.825 | Z4: =+交通业务拆分!AA30 -> 0.83 | AA4: =+交通业务拆分!AB30 -> 0.81 | ... AF4: =+交通业务拆分!AG30 -> 0.805
C6: 票量(mm) | D6: =+交通业务拆分!E32 -> 17.028648 | E6: =+交通业务拆分!F32 -> 20.898102 | F6: =+交通业务拆分!G32 -> 21.392691 | G6: =+交通业务拆分!H32 -> 22.353849 | H6: =+交通业务拆分!I32 -> 9.9587253 | I6: =+交通业务拆分!J32 -> 12.646174 | J6: =+交通业务拆分!K32 -> 26.3111 | K6: =+交通业务拆分!L32 -> 21.67514 | ... AF6: =+交通业务拆分!AG32 -> 31.682056
C7: 票量YoY | T7: =+交通业务拆分!U34 -> 0.38738019 | U7: =+交通业务拆分!V34 -> 0.3916333 | V7: =+交通业务拆分!W34 -> 0.33926486 | W7: =+交通业务拆分!X34 -> 0.17629032 | X7: =+交通业务拆分!Y34 -> 0.28907772 | Y7: =+交通业务拆分!Z34 -> 0.098181818 | Z7: =+交通业务拆分!AA34 -> 0.15725999 | AA7: =+交通业务拆分!AB34 -> 0.07 | ... AF7: =+交通业务拆分!AG34 -> 0.01
C8: 占总票量比例 | T8: =交通业务拆分!U33 -> 0.965 | U8: =交通业务拆分!V33 -> 0.957 | V8: =交通业务拆分!W33 -> 0.9385 | W8: =交通业务拆分!X33 -> 0.935 | X8: =交通业务拆分!Y33 -> 0.908 | Y8: =交通业务拆分!Z33 -> 0.906 | Z8: =交通业务拆分!AA33 -> 0.8939 | AA8: =交通业务拆分!AB33 -> 0.91065902 | ... AF8: =交通业务拆分!AG33 -> 0.86916008
C10: 收入(mm) | D10: =+交通业务拆分!E37 -> 457.39102 | E10: =+交通业务拆分!F37 -> 461.90113 | F10: =+交通业务拆分!G37 -> 469.19375 | G10: =+交通业务拆分!H37 -> 495.4911 | H10: =+交通业务拆分!I37 -> 284.42119 | I10: =+交通业务拆分!J37 -> 344.98763 | J10: =+交通业务拆分!K37 -> 519.90733 | K10: =+交通业务拆分!L37 -> 502.86324 | ... AF10: =+交通业务拆分!AG37 -> 745.08158
C11: 收入YoY | X11: =+X10/T10-1 -> 0.21862664 | Y11: =+Y10/U10-1 -> 0.046821042 | Z11: =+Z10/V10-1 -> 0.21007491 | AA11: =+AA10/W10-1 -> 0.06724887 | AB11: =+AB10/X10-1 -> 0.084917384 | AC11: =+AC10/Y10-1 -> 0.13813817 | AD11: =+AD10/Z10-1 -> 0.019773424 | AE11: =+AE10/AA10-1 -> 0.099412386 | AF11: =+AF10/AB10-1 -> -0.025882065
C12: Take rate | T12: =+交通业务拆分!U36 -> 0.030546448 | U12: =+交通业务拆分!V36 -> 0.035084746 | V12: =+交通业务拆分!W36 -> 0.032259887 | W12: =+交通业务拆分!X36 -> 0.038823529 | X12: =+交通业务拆分!Y36 -> 0.035964072 | Y12: =+交通业务拆分!Z36 -> 0.038181818 | Z12: =+交通业务拆分!AA36 -> 0.03846988 | AA12: =+交通业务拆分!AB36 -> 0.040932099 | ... AF12: =+交通业务拆分!AG36 -> 0.033726708
C14: 单段收入 | D14: =+交通业务拆分!E39 -> 26.860091 | E14: =+交通业务拆分!F39 -> 22.10254 | F14: =+交通业务拆分!G39 -> 21.932432 | G14: =+交通业务拆分!H39 -> 22.165806 | H14: =+交通业务拆分!I39 -> 28.56 | I14: =+交通业务拆分!J39 -> 27.28 | J14: =+交通业务拆分!K39 -> 19.76 | K14: =+交通业务拆分!L39 -> 23.2 | ... AF14: =+交通业务拆分!AG39 -> 23.517463
C15: 单段收入YoY | X15: =+X14/T14-1 -> -0.05465231 | Y15: =+Y14/U14-1 -> -0.046768919 | Z15: =+Z14/V14-1 -> 0.045637901 | AA15: =+AA14/W14-1 -> -0.0025711498 | AB15: =+AB14/X14-1 -> 0.053317849 | AC15: =+AC14/Y14-1 -> 0.11582173 | AD15: =+AD14/Z14-1 -> 0.0096766575 | AE15: =+AE14/AA14-1 -> 0.088527115 | AF15: =+AF14/AB14-1 -> -0.035526797
C17: 平均票价 | T17: =+交通业务拆分!U35 -> 801.65698 | U17: =+交通业务拆分!V35 -> 640.99144 | V17: =+交通业务拆分!W35 -> 737.3233 | W17: =+交通业务拆分!X35 -> 590.93151 | X17: =+交通业务拆分!Y35 -> 643.68295 | Y17: =+交通业务拆分!Z35 -> 561.45138 | Z17: =+交通业务拆分!AA35 -> 646.519 | AA17: =+交通业务拆分!AB35 -> 559.04926 | ... AF17: =+交通业务拆分!AG35 -> 697.29495
C19: TC VS C+Q
C20: GMV | T20: =+交通业务拆分!U69 -> 0.32235254 | U20: =+交通业务拆分!V69 -> 0.28437978 | V20: =+交通业务拆分!W69 -> 0.2455241 | W20: =+交通业务拆分!X69 -> 0.27153141 | X20: =+交通业务拆分!Y69 -> 0.27003584 | Y20: =+交通业务拆分!Z69 -> 0.28420106 | Z20: =+交通业务拆分!AA69 -> 0.26737571 | AA20: =+交通业务拆分!AB69 -> 0.28014762 | ... AF20: =+交通业务拆分!AG69 -> 0.34363504
C21: 收入 | T21: =+交通业务拆分!U70 -> 0.34403353 | U21: =+交通业务拆分!V70 -> 0.35531715 | V21: =+交通业务拆分!W70 -> 0.3672242 | W21: =+交通业务拆分!X70 -> 0.4716074 | X21: =+交通业务拆分!Y70 -> 0.45713879 | Y21: =+交通业务拆分!Z70 -> 0.48250669 | Z21: =+交通业务拆分!AA70 -> 0.51044166 | AA21: =+交通业务拆分!AB70 -> 0.45814337 | ... AF21: =+交通业务拆分!AG70 -> 0.58048538
C22: 票量 | T22: =+交通业务拆分!U71 -> 0.37512609 | U22: =+交通业务拆分!V71 -> 0.39742427 | V22: =+交通业务拆分!W71 -> 0.33638056 | W22: =+交通业务拆分!X71 -> 0.36412687 | X22: =+交通业务拆分!Y71 -> 0.37969456 | Y22: =+交通业务拆分!Z71 -> 0.42096313 | Z22: =+交通业务拆分!AA71 -> 0.36639674 | AA22: =+交通业务拆分!AB71 -> 0.36406784 | ... AF22: =+交通业务拆分!AG71 -> 0.42469297
C23: 平均票价 | T23: =+交通业务拆分!U72 -> 0.85931784 | U23: =+交通业务拆分!V72 -> 0.71555716 | V23: =+交通业务拆分!W72 -> 0.72989981 | W23: =+交通业务拆分!X72 -> 0.74320368 | X23: =+交通业务拆分!Y72 -> 0.71119227 | Y23: =+交通业务拆分!Z72 -> 0.67512103 | Z23: =+交通业务拆分!AA72 -> 0.72709801 | AA23: =+交通业务拆分!AB72 -> 0.76949289 | ... AF23: =+交通业务拆分!AG72 -> 0.80913758
C24: 单段收入差异（同程-C+Q） | T24: =+交通业务拆分!U66 -> -2.2131201 | U24: =+交通业务拆分!V66 -> -2.6650779 | V24: =+交通业务拆分!W66 -> 1.9978145 | W24: =+交通业务拆分!X66 -> 5.2285512 | X24: =+交通业务拆分!Y66 -> 3.9217676 | Y24: =+交通业务拆分!Z66 -> 2.7343116 | Z24: =+交通业务拆分!AA66 -> 7.0186556 | AA24: =+交通业务拆分!AB66 -> 4.6988257 | ... AF24: =+交通业务拆分!AG66 -> 6.3116875
C25: 平均票价差异（同程-C+Q） | T25: =+交通业务拆分!U67 -> -131.24228 | U25: =+交通业务拆分!V67 -> -254.80205 | V25: =+交通业务拆分!W67 -> -272.84726 | W25: =+交通业务拆分!X67 -> -204.18231 | X25: =+交通业务拆分!Y67 -> -261.3929 | Y25: =+交通业务拆分!Z67 -> -270.17933 | Z25: =+交通业务拆分!AA67 -> -242.65824 | AA25: =+交通业务拆分!AB67 -> -167.46721 | ... AF25: =+交通业务拆分!AG67 -> -164.48056
C27: TC YoY
C28: GMV | T28: =+交通业务拆分!U31 -> 0.6320016 | U28: =+交通业务拆分!V31 -> 0.37386072 | V28: =+交通业务拆分!W31 -> 0.36840577 | W28: =+交通业务拆分!X31 -> 0.074193304 | X28: =+交通业务拆分!Y31 -> 0.035052863 | Y28: =+交通业务拆分!Z31 -> -0.038090593 | Z28: =+交通业务拆分!AA31 -> 0.01473881 | AA28: =+交通业务拆分!AB31 -> 0.012270788 | ... AF28: =+交通业务拆分!AG31 -> 0.2202935
C29: 收入 | T29: =+交通业务拆分!U38 -> 0.26484501 | U29: =+交通业务拆分!V38 -> 0.41596723 | V29: =+交通业务拆分!W38 -> 0.4524476 | W29: =+交通业务拆分!X38 -> 0.21748369 | X29: =+交通业务拆分!Y38 -> 0.21862664 | Y29: =+交通业务拆分!Z38 -> 0.046821042 | Z29: =+交通业务拆分!AA38 -> 0.21007491 | AA29: =+交通业务拆分!AB38 -> 0.06724887 | ... AF29: =+交通业务拆分!AG38 -> -0.025882065
C30: 票量 | T30: =+交通业务拆分!U34 -> 0.38738019 | U30: =+交通业务拆分!V34 -> 0.3916333 | V30: =+交通业务拆分!W34 -> 0.33926486 | W30: =+交通业务拆分!X34 -> 0.17629032 | X30: =+交通业务拆分!Y34 -> 0.28907772 | Y30: =+交通业务拆分!Z34 -> 0.098181818 | Z30: =+交通业务拆分!AA34 -> 0.15725999 | AA30: =+交通业务拆分!AB34 -> 0.07 | ... AF30: =+交通业务拆分!AG34 -> 0.01
C31: 单段收入 | T31: =交通业务拆分!U40 -> 0.0078607739 | U31: =交通业务拆分!V40 -> -0.054728505 | V31: =交通业务拆分!W40 -> -0.073567672 | W31: =交通业务拆分!X40 -> -0.14606502 | X31: =交通业务拆分!Y40 -> -0.05465231 | Y31: =交通业务拆分!Z40 -> -0.046768919 | Z31: =交通业务拆分!AA40 -> 0.045637901 | AA31: =交通业务拆分!AB40 -> -0.0025711498 | ... AF31: =交通业务拆分!AG40 -> -0.035526797
B32: TC国际 | D32: 1Q19 | E32: 2Q19 | F32: 3Q19 | G32: 4Q19 | H32: 20Q1 | I32: 20Q2 | J32: 20Q3 | K32: 20Q4 | L32: 21Q1 | M32: 21Q2 | N32: 21Q3 | O32: 21Q4 | P32: 22Q1 | Q32: 22Q2 | R32: 22Q3 | S32: 22Q4 | T32: 23Q1 | U32: 23Q2 | V32: 23Q3 | W32: 23Q4 | X32: 24Q1 | Y32: 24Q2 | Z32: 24Q3 | AA32: 24Q4 | AB32: 25Q1 | AC32: 25Q2 | AD32: 25Q3 | AE32: 25Q4 | AF32: 26Q1
B33: TC国际
C34: 占TC机票GMV比 | T34: =交通业务拆分!U43 -> 0.085 | U34: =交通业务拆分!V43 -> 0.115 | V34: =交通业务拆分!W43 -> 0.115 | W34: =交通业务拆分!X43 -> 0.15 | X34: =交通业务拆分!Y43 -> 0.165 | Y34: =交通业务拆分!Z43 -> 0.175 | Z34: =交通业务拆分!AA43 -> 0.17 | AA34: =交通业务拆分!AB43 -> 0.19 | ... AF34: =交通业务拆分!AG43 -> 0.195
C36: 票量(mm) | T36: =交通业务拆分!U45 -> 0.85687286 | U36: =交通业务拆分!V45 -> 1.306737 | V36: =交通业务拆分!W45 -> 1.8774688 | W36: =交通业务拆分!X45 -> 1.827968 | X36: =交通业务拆分!Y45 -> 3.0857216 | Y36: =交通业务拆分!Z45 -> 3.3136419 | Z36: =交通业务拆分!AA45 -> 3.9354036 | AA36: =交通业务拆分!AB45 -> 2.7602317 | ... AF36: =交通业务拆分!AG45 -> 4.7692913 | AG36: =AD36/90 -> 0.052472048
C37: 票量YoY | T37: =交通业务拆分!U47 -> -0.22540984 | U37: =交通业务拆分!V47 -> 0.16352941 | V37: =交通业务拆分!W47 -> 0.0824 | W37: =交通业务拆分!X47 -> 0.086428571 | X37: =交通业务拆分!Y47 -> 2.6011429 | Y37: =交通业务拆分!Z47 -> 1.535814 | Z37: =交通业务拆分!AA47 -> 1.096122 | AA37: =交通业务拆分!AB47 -> 0.51 | ... AF37: =交通业务拆分!AG47 -> 0.12
C38: 占总票量比例 | T38: =交通业务拆分!U46 -> 0.035 | U38: =交通业务拆分!V46 -> 0.043 | V38: =交通业务拆分!W46 -> 0.0615 | W38: =交通业务拆分!X46 -> 0.065 | X38: =交通业务拆分!Y46 -> 0.092 | Y38: =交通业务拆分!Z46 -> 0.094 | Z38: =交通业务拆分!AA46 -> 0.1061 | AA38: =交通业务拆分!AB46 -> 0.089340979 | ... AF38: =交通业务拆分!AG46 -> 0.13083992
C40: 收入(mm) | T40: =交通业务拆分!U51 -> 52.781693 | U40: =交通业务拆分!V51 -> 72.670763 | V40: =交通业务拆分!W51 -> 82.350392 | W40: =交通业务拆分!X51 -> 54.841121 | X40: =交通业务拆分!Y51 -> 69.726319 | Y40: =交通业务拆分!Z51 -> 76.073284 | Z40: =交通业务拆分!AA51 -> 92.200705 | AA40: =交通业务拆分!AB51 -> 94.082632 | ... AF40: =交通业务拆分!AG51 -> 160.54244
C41: 收入YoY | X41: =+X40/T40-1 -> 0.32103224 | Y41: =+Y40/U40-1 -> 0.046821042 | Z41: =+Z40/V40-1 -> 0.11961464 | AA41: =+AA40/W40-1 -> 0.71554904 | AB41: =+AB40/X40-1 -> 0.36310133 | AC41: =+AC40/Y40-1 -> 0.41772873 | AD41: =+AD40/Z40-1 -> 0.43311468 | AE41: =+AE40/AA40-1 -> 0.38646685 | AF41: =+AF40/AB40-1 -> 0.68913741 | AI41: 1 | AJ41: 3
C42: Take rate | T42: =交通业务拆分!U50 -> 0.03 | U42: =交通业务拆分!V50 -> 0.03 | V42: =交通业务拆分!W50 -> 0.03 | W42: =交通业务拆分!X50 -> 0.02 | X42: =交通业务拆分!Y50 -> 0.018 | Y42: =交通业务拆分!Z50 -> 0.02 | Z42: =交通业务拆分!AA50 -> 0.021 | AA42: =交通业务拆分!AB50 -> 0.0255 | ... AF42: =交通业务拆分!AG50 -> 0.03 | AI42: 1 | AJ42: 1.5
AI43: 1 | AJ43: =+AJ41+AJ42 -> 4.5 | AK43: =AI43/AJ43 -> 0.22222222
C44: 单段收入 | T44: =交通业务拆分!U53 -> 61.598045 | U44: =交通业务拆分!V53 -> 55.612387 | V44: =交通业务拆分!W53 -> 43.862456 | W44: =交通业务拆分!X53 -> 30.001138 | X44: =交通业务拆分!Y53 -> 22.596439 | Y44: =交通业务拆分!Z53 -> 22.957606 | Z44: =交通业务拆分!AA53 -> 23.428526 | AA44: =交通业务拆分!AB53 -> 34.085049 | ... AF44: =交通业务拆分!AG53 -> 33.661698
C45: 单段收入YoY | X45: =+X44/T44-1 -> -0.63316305 | Y45: =+Y44/U44-1 -> -0.58718539 | Z45: =+Z44/V44-1 -> -0.46586379 | AA45: =+AA44/W44-1 -> 0.13612519 | AB45: =+AB44/X44-1 -> -0.012245414 | AC45: =+AC44/Y44-1 -> 0.10760057 | AD45: =+AD44/Z44-1 -> 0.19426224 | AE45: =+AE44/AA44-1 -> 0.20562335 | AF45: =+AF44/AB44-1 -> 0.50815841
C47: 平均票价 | T47: =交通业务拆分!U48 -> 2053.2682 | U47: =交通业务拆分!V48 -> 1853.7462 | V47: =交通业务拆分!W48 -> 1462.0819 | W47: =交通业务拆分!X48 -> 1500.0569 | X47: =交通业务拆分!Y48 -> 1255.3577 | Y47: =交通业务拆分!Z48 -> 1147.8803 | Z47: =交通业务拆分!AA48 -> 1115.6441 | AA47: =交通业务拆分!AB48 -> 1336.6686 | ... AF47: =交通业务拆分!AG48 -> 1122.0566
C49: TC VS C+Q
C50: GMV | T50: =交通业务拆分!U87 -> 0.15518161 | U50: =交通业务拆分!V87 -> 0.14026465 | V50: =交通业务拆分!W87 -> 0.13675989 | W50: =交通业务拆分!X87 -> 0.15622683 | X50: =交通业务拆分!Y87 -> 0.18564336 | Y50: =交通业务拆分!Z87 -> 0.16418761 | Z50: =交通业务拆分!AA87 -> 0.1791261 | AA50: =交通业务拆分!AB87 -> 0.15621941 | ... AF50: =交通业务拆分!AG87 -> 0.19057546
C51: 收入 | T51: =交通业务拆分!U88 -> 0.12426054 | U51: =交通业务拆分!V88 -> 0.11902595 | V51: =交通业务拆分!W88 -> 0.113207 | W51: =交通业务拆分!X88 -> 0.076313799 | X51: =交通业务拆分!Y88 -> 0.084641491 | Y51: =交通业务拆分!Z88 -> 0.085041732 | Z51: =交通业务拆分!AA88 -> 0.096422057 | AA51: =交通业务拆分!AB88 -> 0.10138545 | ... AF51: =交通业务拆分!AG88 -> 0.16683183
C52: 票量 | T52: =交通业务拆分!U89 -> 0.15799111 | U52: =交通业务拆分!V89 -> 0.14245714 | V52: =交通业务拆分!W89 -> 0.17556016 | W52: =交通业务拆分!X89 -> 0.16870074 | X52: =交通业务拆分!Y89 -> 0.23190261 | Y52: =交通业务拆分!Z89 -> 0.22289126 | Z52: =交通业务拆分!AA89 -> 0.24499993 | AA52: =交通业务拆分!AB89 -> 0.16796003 | ... AF52: =交通业务拆分!AG89 -> 0.25562998
C53: 平均票价 | T53: =交通业务拆分!U90 -> 0.98221734 | U53: =交通业务拆分!V90 -> 0.98460947 | V53: =交通业务拆分!W90 -> 0.7789916 | W53: =交通业务拆分!X90 -> 0.92605898 | X53: =交通业务拆分!Y90 -> 0.80052298 | Y53: =交通业务拆分!Z90 -> 0.73662649 | Z53: =交通业务拆分!AA90 -> 0.73112712 | AA53: =交通业务拆分!AB90 -> 0.93009872 | ... AF53: =交通业务拆分!AG90 -> 0.74551294
C54: 单段收入差异（同程-C+Q） | T54: =交通业务拆分!U84 -> -16.720816 | U54: =交通业务拆分!V84 -> -10.947733 | V54: =交通业务拆分!W84 -> -24.158956 | W54: =交通业务拆分!X84 -> -36.319951 | X54: =交通业务拆分!Y84 -> -39.313778 | Y54: =交通业务拆分!Z84 -> -37.213436 | Z54: =交通业务拆分!AA84 -> -36.101291 | AA54: =交通业务拆分!AB84 -> -22.38189 | ... AF54: =交通业务拆分!AG84 -> -17.916822
C55: 平均票价差异（同程-C+Q） | T55: =交通业务拆分!U85 -> -37.17361 | U55: =交通业务拆分!V85 -> -28.976104 | V55: =交通业务拆分!W85 -> -414.80855 | W55: =交通业务拆分!X85 -> -119.77179 | X55: =交通业务拆分!Y85 -> -312.81428 | Y55: =交通业务拆分!Z85 -> -410.41324 | Z55: =交通业务拆分!AA85 -> -410.27947 | AA55: =交通业务拆分!AB85 -> -100.45692 | ... AF55: =交通业务拆分!AG85 -> -383.02337
C57: TC YoY
C58: GMV | T58: =交通业务拆分!U44 -> 0.29226669 | U58: =交通业务拆分!V44 -> 0.48992689 | V58: =交通业务拆分!W44 -> 0.43868855 | W58: =交通业务拆分!X44 -> 0.45881495 | X58: =交通业务拆分!Y44 -> 1.2017204 | Y58: =交通业务拆分!Z44 -> 0.57023156 | Z58: =交通业务拆分!AA44 -> 0.59944949 | AA58: =交通业务拆分!AB44 -> 0.34552866 | ... AF58: =交通业务拆分!AG44 -> 0.18239619
C59: 收入 | T59: =交通业务拆分!U52 -> -0.13848888 | U59: =交通业务拆分!V52 -> 0.039483876 | V59: =交通业务拆分!W52 -> -0.040874302 | W59: =交通业务拆分!X52 -> -0.25188977 | X59: =交通业务拆分!Y52 -> 0.32103224 | Y59: =交通业务拆分!Z52 -> 0.046821042 | Z59: =交通业务拆分!AA52 -> 0.11961464 | AA59: =交通业务拆分!AB52 -> 0.71554904 | ... AF59: =交通业务拆分!AG52 -> 0.68913741
C60: 票量 | T60: =交通业务拆分!U47 -> -0.22540984 | U60: =交通业务拆分!V47 -> 0.16352941 | V60: =交通业务拆分!W47 -> 0.0824 | W60: =交通业务拆分!X47 -> 0.086428571 | X60: =交通业务拆分!Y47 -> 2.6011429 | Y60: =交通业务拆分!Z47 -> 1.535814 | Z60: =交通业务拆分!AA47 -> 1.096122 | AA60: =交通业务拆分!AB47 -> 0.51 | ... AF60: =交通业务拆分!AG47 -> 0.12
C61: 单段收入 | X61: =交通业务拆分!Y54 -> -0.63316305 | Y61: =交通业务拆分!Z54 -> -0.58718539 | Z61: =交通业务拆分!AA54 -> -0.46586379 | AA61: =交通业务拆分!AB54 -> 0.13612519 | AB61: =交通业务拆分!AC54 -> -0.012245414 | AC61: =交通业务拆分!AD54 -> 0.10760057 | AD61: =交通业务拆分!AE54 -> 0.19426224 | AE61: =交通业务拆分!AF54 -> 0.20562335 | AF61: =交通业务拆分!AG54 -> 0.50815841
B64: 国内chart | D64: 1Q19 | E64: 2Q19 | F64: 3Q19 | G64: 4Q19 | H64: 20Q1 | I64: 20Q2 | J64: 20Q3 | K64: 20Q4 | L64: 21Q1 | M64: 21Q2 | N64: 21Q3 | O64: 21Q4 | P64: 22Q1 | Q64: 22Q2 | R64: 22Q3 | S64: 22Q4 | T64: 23Q1 | U64: 23Q2 | V64: 23Q3 | W64: 23Q4 | X64: 24Q1 | Y64: 24Q2 | Z64: 24Q3 | AA64: 24Q4 | AB64: 25Q1 | AC64: 25Q2 | AD64: 25Q3 | AE64: 25Q4 | AF64: 26Q1
C65: 同程国内票量(mm)-左轴 | D65: =D6 -> 17.028648 | E65: =E6 -> 20.898102 | F65: =F6 -> 21.392691 | G65: =G6 -> 22.353849 | H65: =H6 -> 9.9587253 | I65: =I6 -> 12.646174 | J65: =J6 -> 26.3111 | K65: =K6 -> 21.67514 | ... AF65: =AF6 -> 31.682056
C66: C+Q国内票量(mm)-左轴 | D66: =交通业务拆分!E58 -> 61.195596 | E66: =交通业务拆分!F58 -> 60.862553 | F66: =交通业务拆分!G58 -> 70.350445 | G66: =交通业务拆分!H58 -> 68.839945 | H66: =交通业务拆分!I58 -> 19.844603 | I66: =交通业务拆分!J58 -> 36.435656 | J66: =交通业务拆分!K58 -> 67.954652 | K66: =交通业务拆分!L58 -> 62.295738 | ... AF66: =交通业务拆分!AG58 -> 74.599907
C67: T / C+Q 票量比例-右轴 | D67: =D65/D66 -> 0.27826591 | E67: =E65/E66 -> 0.34336552 | F67: =F65/F66 -> 0.3040875 | G67: =G65/G66 -> 0.32472207 | H67: =H65/H66 -> 0.50183545 | I67: =I65/I66 -> 0.34708238 | J67: =J65/J66 -> 0.38718614 | K67: =K65/K66 -> 0.34793937 | ... AF67: =AF65/AF66 -> 0.42469297
C68: CHECK | D68: =交通业务拆分!E71 -> 0.27826591 | E68: =交通业务拆分!F71 -> 0.34336552 | F68: =交通业务拆分!G71 -> 0.3040875 | G68: =交通业务拆分!H71 -> 0.32472207 | H68: =交通业务拆分!I71 -> 0.50183545 | I68: =交通业务拆分!J71 -> 0.34708238 | J68: =交通业务拆分!K71 -> 0.38718614 | K68: =交通业务拆分!L71 -> 0.34793937 | ... AF68: =交通业务拆分!AG71 -> 0.42469297
C70: 同程单段收入 | D70: =D14 -> 26.860091 | E70: =E14 -> 22.10254 | F70: =F14 -> 21.932432 | G70: =G14 -> 22.165806 | H70: =H14 -> 28.56 | I70: =I14 -> 27.28 | J70: =J14 -> 19.76 | K70: =K14 -> 23.2 | ... AF70: =AF14 -> 23.517463
C71: C+Q单段收入 | D71: =交通业务拆分!E64 -> 18.32151 | E71: =交通业务拆分!F64 -> 19.114092 | F71: =交通业务拆分!G64 -> 18.18662 | G71: =交通业务拆分!H64 -> 17.094433 | H71: =交通业务拆分!I64 -> 19.368304 | I71: =交通业务拆分!J64 -> 19.306841 | J71: =交通业务拆分!K64 -> 19.66472 | K71: =交通业务拆分!L64 -> 20.47644 | ... AF71: =交通业务拆分!AG64 -> 17.205776
C72: T / C+Q 单段收入比例-右轴 | D72: =D70/D71 -> 1.4660413 | E72: =E70/E71 -> 1.1563479 | F72: =F70/F71 -> 1.2059653 | G72: =G70/G71 -> 1.2966681 | H72: =H70/H71 -> 1.4745741 | I72: =I70/I71 -> 1.4129707 | J72: =J70/J71 -> 1.0048452 | K72: =K70/K71 -> 1.1330095 | ... AF72: =AF70/AF71 -> 1.3668354
X74: =X65/T65-1 -> 0.28907772 | Y74: =Y65/U65-1 -> 0.098181818 | Z74: =Z65/V65-1 -> 0.15725999 | AA74: =AA65/W65-1 -> 0.07 | AB74: =AB65/X65-1 -> 0.03 | AC74: =AC65/Y65-1 -> 0.02 | AD74: =AD65/Z65-1 -> 0.01 | AE74: =AE65/AA65-1 -> 0.01 | AF74: =AF65/AB65-1 -> 0.01
X75: =X66/T66-1 -> 0.27356757 | Y75: =Y66/U66-1 -> 0.03677514 | Z75: =Z66/V66-1 -> 0.062454199 | AA75: =AA66/W66-1 -> 0.07017347 | AB75: =AB66/X66-1 -> -0.028525157 | AC75: =AC66/Y66-1 -> 0.014944359 | AD75: =AD66/Z66-1 -> -0.04963859 | AE75: =AE66/AA66-1 -> -0.085724494 | AF75: =AF66/AB66-1 -> -0.042615594

Sheet intl business
C2: 24Q4 | D2: Note & Assumption | F2: 2024
B3: 出境机票
B4: GMV | C4: =+交通业务拆分!AB42 -> 3689.515 | F4: =SUM(交通业务拆分!Y42:AB42) -> 15757.373
B5: Volume | C5: =+交通业务拆分!AB45 -> 2.7602317 | D5: 占比总机票票量10% | F5: =SUM(交通业务拆分!Y45:AB45) -> 13.094999 | G5: =F5/SUM(交通业务拆分!Y21:AB21) -> 0.095738449
B6: ASP | C6: =C4/C5 -> 1336.6686 | F6: =F4/F5 -> 1203.3123
B7: Take Rate | C7: =+交通业务拆分!AB50 -> 0.0255
B8: Rev | C8: =C5*C7*C6 -> 94.082632 | D8: 占比总交通收入5% | F8: =SUM(交通业务拆分!Y51:AB51) -> 332.08294 | G8: =F8/SUM(交通业务拆分!Y14:AB14) -> 0.045937407
C9: =C8/(Tongchengelong!AW15/1000) -> 0.054602698
B11: 出境酒店
B12: GMV | C12: =C13*C15 -> 904.8
B13: Volume | C13: =2%*58 -> 1.16 | D13: 占比总间夜2%
B14: Take Rate | C14: 0.09
B15: ADR | C15: 780 | D15: 参考Q 房价
B16: Rev | C16: =C13*C14*C15 -> 81.432
B18: 整体国际收入 | C18: =C16+C8 -> 175.51463
B19: Core OTA Rev | C19: =Tongchengelong!AW17/1000 -> 3457.332
B20: 国际收入占比 | C20: =C18/C19 -> 0.050765918

Sheet Sheet7
D5: 19Q1 | E5: 23Q1 | F5: YoY
C6: 国际 | D6: =D8-D7 -> 0.90674377 | E6: =D6*(1+F6) -> 1.6321388 | F6: 0.8
B7: 0.95 | C7: 国内 | D7: =B7*D8 -> 17.228132 | E7: =D7*(1+F7) -> 22.913415 | F7: 0.33
C8: Total | D8: =交通业务拆分!E21 -> 18.134875 | E8: =E6+E7 -> 24.545554 | F8: =E8/D8-1 -> 0.3535
D10: 19Q1 | E10: 23Q1 | F10: YoY
C11: 国际
B12: 0.95 | C12: 国内
C13: Total

Sheet Sheet4
A3: VAS 占比酒店收入 | B3: 21Q2 | C3: 21Q3 | D3: 21Q4 | E3: 22Q1 | F3: 22Q2 | I3: 6月 | J3: 7月 | K3: 8月
B4: 0.12 | C4: 0.11 | D4: 0.1 | E4: 0.12 | F4: 0.15 | H4: 同程 | I4: ‘-5% YoY | J4: Flat YoY；up 60%-70% vs 2019
H5: CQ Domestic
B9: TCOm | C9: 9961
B10: 4072755 | C10: 509934 | D10: =C10/(B10+C10) -> 0.11127397

Sheet Sheet5
A2: Transportation Vol | B2: 19Q1 | C2: 19Q2 | D2: 19Q3 | E2: 19Q4 | F2: 20Q1 | G2: 20Q2 | H2: 20Q3 | I2: 20Q4 | J2: 21Q1 | K2: 21Q2 | L2: 21Q3 | M2: 21Q4 | N2: 22Q1
A3: 机票 | B3: =交通业务拆分!E21 -> 18.134875 | C3: =交通业务拆分!F21 -> 22.021183 | D3: =交通业务拆分!G21 -> 23.127233 | E3: =交通业务拆分!H21 -> 24.036397 | F3: =交通业务拆分!I21 -> 9.9587253 | G3: =交通业务拆分!J21 -> 12.646174 | H3: =交通业务拆分!K21 -> 26.3111 | I3: =交通业务拆分!L21 -> 21.67514 | ... M3: =交通业务拆分!P21 -> 18.5966
A4: 火车票 | B4: =交通业务拆分!E98 -> 110.42494 | C4: =交通业务拆分!F98 -> 124.40037 | D4: =交通业务拆分!G98 -> 132.06485 | E4: =交通业务拆分!H98 -> 118.52333 | F4: =交通业务拆分!I98 -> 55.731748 | G4: =交通业务拆分!J98 -> 71.034749 | H4: =交通业务拆分!K98 -> 123.44456 | I4: =交通业务拆分!L98 -> 111.02619 | ... M4: =交通业务拆分!P98 -> 76.234508 | N4: =(J4+J5)*1.6 -> 133.5975
J5: =交通业务拆分!M93/80 -> 0
A6: 汽车票 | F6: =SUM(F3:F4) -> 65.690474 | J6: =SUM(J3:J5) -> 104.75259 | N6: =J6*1.15 -> 120.46548 | O6: =N6/J6-1 -> 0.15
A8: 机票 | B8: =B3/(B3+B4+B6) -> 0.14106178 | C8: =C3/(C3+C4+C6) -> 0.15039578 | D8: =D3/(D3+D4+D6) -> 0.14902328 | E8: =E3/(E3+E4+E6) -> 0.1686058 | F8: =F3/(F3+F4+F6) -> 0.075800377 | G8: =G3/(G3+G4+G6) -> 0.15112374 | H8: =H3/(H3+H4+H6) -> 0.17569353 | I8: =I3/(I3+I4+I6) -> 0.16333777 | ... M8: =M3/(M3+M4+M6) -> 0.19610231
A9: 火车票 | B9: =B4/(B3+B4+B6) -> 0.85893822 | C9: =C4/(C3+C4+C6) -> 0.84960422 | D9: =D4/(D3+D4+D6) -> 0.85097672 | E9: =E4/(E3+E4+E6) -> 0.8313942 | F9: =F4/(F3+F4+F6) -> 0.42419962 | G9: =G4/(G3+G4+G6) -> 0.84887626 | H9: =H4/(H3+H4+H6) -> 0.82430647 | I9: =I4/(I3+I4+I6) -> 0.83666223 | ... M9: =M4/(M3+M4+M6) -> 0.80389769
A10: 汽车票
L13: =0.15-(0.8*60%) -> -0.33

Sheet Sheet3
B2: 21Q1 | C2: YoY
B3: 订单处理成本
B4: 采购成本
B5: 销售成本总额

Sheet Sheet2
B1: 20Q3 | C1: 19Q3 | D1: YoY
A2: 订单处理成本 | B2: 231685 | C2: 277125 | D2: =B2/C2-1 -> -0.16396933 | E2: 主要由于交易额下降
A3: 承担存货风险的买断产品成本 | B3: 113475 | C3: 151619 | D3: =B3/C3-1 -> -0.25157797
A4: 雇员福利开支 | B4: 50323 | C4: 68342 | D4: =B4/C4-1 -> -0.26365924
A5: 资产折旧 | B5: 32689 | C5: 29519 | D5: =B5/C5-1 -> 0.10738846
A6: 采购成本 | B6: 36324 | C6: 77336 | D6: =B6/C6-1 -> -0.5303093 | E6: VAS相关销售下降
A7: 其他 | B7: 70819 | C7: 78589 | D7: =B7/C7-1 -> -0.098868798
A8: 销售成本总额 | B8: =SUM(B2:B7) -> 535315 | C8: =SUM(C2:C7) -> 682530 | D8: =B8/C8-1 -> -0.21569015

Sheet Breakdown
C2: Unit: RMB Mn | E2: 1Q19 | F2: 2Q19 | G2: 3Q19 | H2: 4Q19 | I2: 20Q1 | J2: 2019
C3: TCEL transportation
C4: TCEL
D5: GMV | E5: =Tongchengelong!Z4 -> 35900000 | F5: =Tongchengelong!AA5 -> 33765813 | G5: =Tongchengelong!AB5 -> 38121813 | H5: =Tongchengelong!AC5 -> 34410000 | I5: =Tongchengelong!AD5 -> 14721594 | J5: =Tongchengelong!BM5 -> 140002000
D6: YoY
D7: Take rate | E7: =E8/E5 -> 0.035068189 | F7: =F8/F5 -> 0.027752685 | G7: =G8/G5 -> 0.029894197 | H7: =H8/H5 -> 0.034350392 | I7: =I8/I5 -> 0.046650383 | J7: =J8/J5 -> 0.032268525
D8: Revenue | E8: =Tongchengelong!Z15 -> 1258948 | F8: =Tongchengelong!AA15 -> 937092 | G8: =Tongchengelong!AB15 -> 1139621 | H8: =Tongchengelong!AC15 -> 1181997 | I8: =Tongchengelong!AD15 -> 686768 | J8: =Tongchengelong!BM15 -> 4517658
D9: YoY
C10: Air
C11: TCEL
D12: Volume | E12: =E16/E14 -> 35900 | F12: =F16/F14 -> 30389.232 | G12: =G16/G14 -> 35834.504 | H12: =H16/H14 -> 33033.6 | I12: =I16/I14 -> 15548.65 | J12: =J16/J14 -> 127648.88
D13: YoY
D14: ASP | E14: 500 | F14: 500 | G14: 500 | H14: 500 | I14: 445 | J14: 510
D15: YoY
D16: GMV | E16: =E5*0.5 -> 17950000 | F16: =F5*0.45 -> 15194616 | G16: =G5*0.47 -> 17917252 | H16: =H5*0.48 -> 16516800 | I16: =I5*0.47 -> 6919149.1 | J16: =J5*0.465 -> 65100930
D17: YoY
D18: Take rate | E18: 0.03100429 | F18: 0.031 | G18: 0.030994792 | H18: 0.0341888 | I18: 0.04388 | J18: 0.03466777
D19: Revenue | E19: =E16*E18 -> 556527 | F19: =F16*F18 -> 471033.1 | G19: =G16*G18 -> 555341.5 | H19: =H16*H18 -> 564689.57 | I19: =I16*I18 -> 303612.26 | J19: =J16*J18 -> 2256904.1
D20: YoY | E20: =E21/E16 -> 0.03100429 | G20: =G21/G16 -> 0.032569001
E21: 556527 | F21: 493674 | G21: 583547 | H21: 578089 | I21: 318704
C22: Train
C23: TCEL
D24: Volume | E24: =E28/E26 -> 138076.92 | F24: =F28/F26 -> 140690.89 | G24: =G28/G26 -> 155419.7 | H24: =H28/H26 -> 137640 | I24: =I28/I26 -> 60018.806 | J24: =J28/J26 -> 567432.35
D25: YoY
D26: ASP | E26: 130 | F26: 132 | G26: 130 | H26: 130 | I26: 130 | J26: 132
D27: YoY
D28: GMV | E28: =E5-E16 -> 17950000 | F28: =F5-F16 -> 18571197 | G28: =G5-G16 -> 20204561 | H28: =H5-H16 -> 17893200 | I28: =I5-I16 -> 7802444.8 | J28: =J5-J16 -> 74901070
D29: YoY | G29: =G32/G28 -> 0
D30: Take rate | E30: 0.0391321 | F30: 0.02278138 | G30: 0.02619192 | H30: 0.03449958 | I30: 0.0432555 | J30: 0.03008582
D31: Revenue | E31: =E28*E30 -> 702421.2 | F31: =F28*F30 -> 423077.51 | G31: =G28*G30 -> 529196.24 | H31: =H28*H30 -> 617307.88 | I31: =I28*I30 -> 337498.65 | J31: =J28*J30 -> 2253460.1
D32: YoY
C33: Check | E33: =E31+E19 -> 1258948.2 | F33: =F31+F19 -> 894110.6 | G33: =G31+G19 -> 1084537.7 | H33: =H31+H19 -> 1181997.5 | I33: =I31+I19 -> 641110.91 | J33: =J31+J19 -> 4510364.2
E34: =E8-E33 -> -0.195 | F34: =F8-F33 -> 42981.397 | G34: =G8-G33 -> 55083.258 | H34: =H8-H33 -> -0.456696 | I34: =I8-I33 -> 45657.087 | J34: =J8-J33 -> 7293.8221

Sheet Guidance
E4: 2016 | F4: 2017 | G4: 2018 | H4: 2019E
D5: MAU (million) | E5: 99.5 | F5: 121.2 | G5: 175.2 | H5: =G5*(1+H6) -> 210.24
D6: MAU YoY | F6: =F5/E5-1 -> 0.21809045 | G6: =G5/F5-1 -> 0.44554455 | H6: 0.2
D7: MPU (月度交易用户, million) | E7: 9.1 | F7: 15.6 | G7: 20 | H7: 27~28 | I7: =20*1.35 -> 27
D8: MPY YoY | F8: =F7/E7-1 -> 0.71428571 | G8: =G7/F7-1 -> 0.28205128 | H8: 35%~40% | I8: =20*1.4 -> 28
D9: 交叉销售：
D10: 票务-酒店交叉销售比例 | F10: 0.05 | G10: 0.2 | H10: 0.25
D11: 票务增值业务(VAS)搭售比例 | G11: 0.35 | H11: 0.4
D12: 佣金率：持平
D13: 票务综合佣金率 | G13: 0.036 | H13: 0.036
D14: 酒店住宿佣金率 | G14: 8%~9% | H14: 8%~9%
F17: Consensus | G17: Actual
J18: =15.8/17.3 -> 0.9132948
D21: 400 mn re
F23: 20Q1 | G23: 19Q1 | H23: YOY | I23: % Rev | O23: 19Q1 | P23: 19Q4
D24: 订单处理成本 | F24: 115444 | G24: 233820 | H24: =F24/G24-1 -> -0.50626978 | K24: SM | L24: -0.36 | O24: 0.25 | P24: 0.33
D25: 雇员福利开支 | F25: 56375 | G25: 109567 | H25: =F25/G25-1 -> -0.48547464
D26: 承担存货风险的产品的成本 | F26: 40627 | G26: 44558 | H26: =F26/G26-1 -> -0.088222093
D27: 资产折旧 | F27: 29543 | G27: 32323 | H27: =F27/G27-1 -> -0.086006868
D28: 带宽及服务器费用 | F28: 29229 | G28: 50893 | H28: =F28/G28-1 -> -0.4256774
D29: 其他 | F29: 80049 | G29: 27109 | H29: =F29/G29-1 -> 1.952857
D30: 销售成本总额 | F30: 351267 | G30: 498270 | H30: =F30/G30-1 -> -0.29502679
I32: 1005116 | J32: 1783411
F33: 20Q1 | G33: 19Q1 | H33: YOY | I33: %Rev 20Q1 | J33: %Rev 19Q1
D34: 服务开发开支 | F34: 287449 | G34: 430052 | H34: =F34/G34-1 -> -0.33159478 | I34: =F34/$I$32 -> 0.2859859 | J34: =G34/$J$32 -> 0.24114015
D35: 销售及营销开支 | F35: 291194 | G35: 469723 | H35: =F35/G35-1 -> -0.38007294 | I35: =F35/$I$32 -> 0.28971183 | J35: =G35/$J$32 -> 0.2633846
D36: 行政开支 | F36: 120034 | G36: 228322 | H36: =F36/G36-1 -> -0.47427756 | I36: =F36/$I$32 -> 0.11942303 | J36: =G36/$J$32 -> 0.12802545
D40: SBC | F40: 20Q1 | G40: 19Q1 | H40: YOY
D41: 销售成本 | F41: 3176 | G41: 15723 | H41: =F41/G41-1 -> -0.79800293
D42: 服务开发开支 | F42: 18074 | G42: 96572 | H42: =F42/G42-1 -> -0.8128443
D43: 销售及营销开支 | F43: 8053 | G43: 24841 | H43: =F43/G43-1 -> -0.6758182
D44: 行政开支 | F44: 36641 | G44: 148614 | H44: =F44/G44-1 -> -0.75344853
F45: =SUM(F41:F44) -> 65944 | G45: =SUM(G41:G44) -> 285750
D47: Adjusted | F47: 20Q1 | G47: 19Q1 | H47: YOY
D48: 服务开发开支 | F48: =F34-F41 -> 284273 | G48: =G34-G41 -> 414329 | H48: =F48/G48-1 -> -0.31389548
D49: 销售及营销开支 | F49: =F35-F42 -> 273120 | G49: =G35-G42 -> 373151 | H49: =F49/G49-1 -> -0.2680711
D50: 行政开支 | F50: =F36-F43 -> 111981 | G50: =G36-G43 -> 203481 | H50: =F50/G50-1 -> -0.44967343

Sheet Reference from finance
E3: Y2017 | F3: Y2018 | G3: 18Q1 | H3: 19Q1
D4: Volume | E4: 500.38848 | F4: 683.62621 | G4: 160.94488 | H4: 199.09686
D5: C | E5: 198.02429 | F5: 284.55199 | G5: 62.541469 | H5: 84.425387
D6: Z | E6: 213.3642 | F6: 281.07422 | G6: 71.54598 | H6: 82.940158
D7: Q | E7: 89 | F7: 118 | G7: 26.857432 | H7: 31.731316
D9: GMV | E9: 68699202402 | F9: 1.0119175e+11 | G9: 24857750959 | H9: 29857339634
D10: C | E10: 3.1581578e+10 | F10: 45410787125 | G10: 10569508261 | H10: 13308481355
D11: Z | E11: 2.4249239e+10 | F11: 3.7968401e+10 | G11: 10381321698 | H11: 11844587807
D12: Q | E12: 12868386226 | F12: 17812561171 | G12: 3.906921e+09 | H12: 4704270472
D14: Revenue | E14: 1.8750904e+09 | F14: 2.5512407e+09 | G14: 7.4618201e+08 | H14: 8.7520183e+08
D15: C | E15: 1101147745 | F15: 1465061705 | G15: 415850280 | H15: 492194937
D16: Z | E16: 4.5990477e+08 | F16: 6.9317364e+08 | G16: 221990946 | H16: 250884909 | J16: Z Other revenue: air +hotel
D17: Q | E17: 314037918 | F17: 393005328 | G17: 1.0834078e+08 | H17: 1.3212199e+08
D19: ASP | E19: 137.29173 | F19: 148.02205 | G19: 154.44884 | H19: 149.96389
D20: C | E20: 159.48335 | F20: 159.58696 | G20: 169 | H20: 157.63601
D21: Z | E21: 113.65186 | F21: 135.08318 | G21: 145.1 | H21: 142.80884
D22: Q | E22: 144.58861 | F22: 150.95391 | G22: 145.4689 | H22: 148.25324
E26: =E15/E10 -> 0.034866774 | F26: =F15/F10 -> 0.032262416 | G26: =G15/G10 -> 0.039344336 | H26: =H15/H10 -> 0.036983554
E27: =E16/E11 -> 0.018965741 | F27: =F16/F11 -> 0.018256593 | G27: =G16/G11 -> 0.021383688 | H27: =H16/H11 -> 0.021181396
E28: =E17/E12 -> 0.024403831 | F28: =F17/F12 -> 0.022063381 | G28: =G17/G12 -> 0.027730477 | H28: =H17/H12 -> 0.028085542

Sheet Sheet1
A2: 同程艺龙 | B2: 19Q2 | C2: % Rev | D2: 20Q2 | E2: % Rev | F2: YoY | I2: 19Q1 | J2: % Rev | K2: 20Q1 | L2: % Rev | M2: YoY
A3: Revenue
A4: Accomodation | B4: 553360 | C4: =B4/$B$7 -> 0.34782871 | D4: =B4*(1+F4) -> 376284.8 | E4: =D4/$D$7 -> 0.33313172 | F4: -0.32 | I4: 553360 | J4: =I4/$B$7 -> 0.34782871 | K4: =I4*(1+M4) -> 376284.8 | L4: =K4/$D$7 -> 0.33313172 | M4: -0.32
A5: Transportation | B5: 937092 | C5: =B5/$B$7 -> 0.58903336 | D5: =B5*(1+F5) -> 702819 | E5: =D5/$D$7 -> 0.62221834 | F5: -0.25 | I5: 937092 | J5: =I5/$B$7 -> 0.58903336 | K5: =I5*(1+M5) -> 702819 | L5: =K5/$D$7 -> 0.62221834 | M5: -0.25
A6: Others | B6: 100446 | C6: =B6/$B$7 -> 0.063137926 | D6: =D7-D4-D5 -> 50433.78 | E6: =D6/$D$7 -> 0.044649935 | F6: =D6/B6-1 -> -0.49790156 | I6: 100446 | J6: =I6/$B$7 -> 0.063137926 | K6: =K7-K4-K5 -> -73987.8 | L6: =K6/$D$7 -> -0.065502734 | M6: =K6/I6-1 -> -1.7365928
A7: Total | B7: =SUM(B4:B6) -> 1590898 | D7: =B7*(1+F7) -> 1129537.6 | F7: -0.29 | I7: 1783411 | K7: 1005116 | M7: -0.29
A9: COGS | B9: 561160 | D9: =B9*(1+F9) -> 336696 | F9: -0.4 | I9: 498270 | K9: 351267 | M9: =K9/I9-1 -> -0.29502679
A11: OP Expense
A12: Serivces Development | B12: 352154 | D12: =B12*(1+F12) -> 281723.2 | F12: -0.2 | I12: 430052 | K12: 287449 | M12: =K12/I12-1 -> -0.33159478
A13: G&A | B13: 99805 | D13: =B13*(1+F13) -> 79844 | F13: -0.2 | I13: 228322 | K13: 120034 | M13: =K13/I13-1 -> -0.47427756
A14: S&M | B14: 407187 | D14: =B14*(1+F14) -> 386827.65 | F14: -0.05 | I14: 469723 | K14: 291194 | M14: =K14/I14-1 -> -0.38007294
B15: =SUM(B12:B14) -> 859146 | D15: =SUM(D12:D14) -> 748394.85 | F15: =D15/B15-1 -> -0.12890842
A17: EBIT | B17: =B7-B9-SUM(B12:B14) -> 170592 | D17: =D7-D9-SUM(D12:D14) -> 44446.73 | F17: =D17/B17-1 -> -0.73945595 | I17: =I7-I9-SUM(I12:I14) -> 157044 | K17: =K7-K9-SUM(K12:K14) -> -44828 | M17: =K17/I17-1 -> -1.2854487
A18: SBC | B18: 76106 | D18: =K18 -> 65944 | F18: =D18/B18-1 -> -0.1335243 | I18: 285750 | K18: 65944 | M18: =K18/I18-1 -> -0.76922485
A19: D&A | B19: =102362+43348 -> 145710 | D19: =K19 -> 145630 | F19: =D19/B19-1 -> -0.00054903576 | I19: =101950+40418 -> 142368 | K19: =103527+42103 -> 145630 | M19: =K19/I19-1 -> 0.022912452
A20: Adj. EBITDA | B20: =SUM(B17:B19) -> 392408 | D20: =SUM(D17:D19) -> 256020.73 | F20: =D20/B20-1 -> -0.34756496 | I20: 615570 | K20: 158902 | M20: =K20/I20-1 -> -0.74186201
B23: =SUM(B12:B14) -> 859146 | D23: =SUM(D12:D14) -> 748394.85 | F23: =D23/B23-1 -> -0.12890842 | K23: =SUM(K9:K14) -> 1049944 | M23: =K23/I23-1 -> #DIV/0!
A26: Booking
A27: Opex 同Ctrip口径： | B27: 19Q2 | C27: 20Q2 | I27: 19Q2 | J27: 20Q2
A28: Product development | B28: -70 | D28: =C28/B28-1 -> -1 | I28: 2603 | J28: 1063.2 | K28: =J28/I28-1 -> -0.59154821
A29: Sales and marketing | B29: -1615 | I29: 2880 | J29: 903 | K29: =J29/I29-1 -> -0.68645833
A30: General and administrative (& Personnel for PCLN) | B30: -799
A31: Amortization of intangible assets | B31: -119 | H31: BKNG | I31: 3850 | J31: 545.1 | K31: =J31/I31-1 -> -0.85841558
A32: Other expenses | H32: EXPE | I32: 3153 | J32: 600 | K32: =J32/I32-1 -> -0.80970504
A33: Impairment
A34: Share-based compensation | B34: 84
A35: Total operating expenses (GAAP) | B35: -2603
A36: Total operating expenses (non-GAAP) | B36: -2519
