Workbook

Sheet Top 20
B2: 核心股东持仓情况
B3: · 25Q4 -> 26Q1, Top 20股东持仓较之前季度波动较大
B4: 需关注Capital World 减持19%， Morgan Stanley 减持15%，Wellington减持68%，Capital International减持94%，Schroder UK减持68%，Arga减持27%
B5: 上季度加仓: CSOP 增持20%，Davis 增持31%
B6: · 26Q1 Top 20 view, Rothschild 增持42%， 华夏基金增持23%
B8: Top 20 25Q4 -> 26Q1
B10: Institution Name | C10: 25Q4 Rank | D10: 26Q1 Rank | E10: Rank Change | F10: % S/O 25Q4 | G10: % S/O 26Q1 | H10: % S/O Change
B11: Capital World Investors (U.S.) | C11: =INDEX('SH Summary'!A:A,MATCH(B11,'SH Summary'!C:C,0)) -> 0 | D11: =INDEX('SH Summary'!B:B,MATCH(B11,'SH Summary'!C:C,0)) -> 1 | E11: =C11-D11 -> -1 | F11: =VLOOKUP(B11,'SH Summary'!C:L,9,FALSE) -> 0 | G11: =VLOOKUP(B11,'SH Summary'!C:L,10,FALSE) -> 0.062420518 | H11: =G11/F11-1 -> #DIV/0!
B12: The Vanguard Group, Inc. | C12: =INDEX('SH Summary'!A:A,MATCH(B12,'SH Summary'!C:C,0)) -> 0 | D12: =INDEX('SH Summary'!B:B,MATCH(B12,'SH Summary'!C:C,0)) -> 2 | E12: =C12-D12 -> -2 | F12: =VLOOKUP(B12,'SH Summary'!C:L,9,FALSE) -> 0 | G12: =VLOOKUP(B12,'SH Summary'!C:L,10,FALSE) -> 0.032561846 | H12: =G12/F12-1 -> #DIV/0!
B13: BlackRock Fund Advisors | C13: =INDEX('SH Summary'!A:A,MATCH(B13,'SH Summary'!C:C,0)) -> 0 | D13: =INDEX('SH Summary'!B:B,MATCH(B13,'SH Summary'!C:C,0)) -> 3 | E13: =C13-D13 -> -3 | F13: =VLOOKUP(B13,'SH Summary'!C:L,9,FALSE) -> 0 | G13: =VLOOKUP(B13,'SH Summary'!C:L,10,FALSE) -> 0.026587593 | H13: =G13/F13-1 -> #DIV/0!
B14: Morgan Stanley Investment Management Inc. | C14: =INDEX('SH Summary'!A:A,MATCH(B14,'SH Summary'!C:C,0)) -> 0 | D14: =INDEX('SH Summary'!B:B,MATCH(B14,'SH Summary'!C:C,0)) -> 4 | E14: =C14-D14 -> -4 | F14: =VLOOKUP(B14,'SH Summary'!C:L,9,FALSE) -> 0 | G14: =VLOOKUP(B14,'SH Summary'!C:L,10,FALSE) -> 0.017337715 | H14: =G14/F14-1 -> #DIV/0!
B15: Norges Bank Investment Management (Norway) | C15: =INDEX('SH Summary'!A:A,MATCH(B15,'SH Summary'!C:C,0)) -> 0 | D15: =INDEX('SH Summary'!B:B,MATCH(B15,'SH Summary'!C:C,0)) -> 5 | E15: =C15-D15 -> -5 | F15: =VLOOKUP(B15,'SH Summary'!C:L,9,FALSE) -> 0 | G15: =VLOOKUP(B15,'SH Summary'!C:L,10,FALSE) -> 0.016915321 | H15: =G15/F15-1 -> #DIV/0!
B16: Sanders Capital, LLC | C16: =INDEX('SH Summary'!A:A,MATCH(B16,'SH Summary'!C:C,0)) -> 0 | D16: =INDEX('SH Summary'!B:B,MATCH(B16,'SH Summary'!C:C,0)) -> 6 | E16: =C16-D16 -> -6 | F16: =VLOOKUP(B16,'SH Summary'!C:L,9,FALSE) -> 0 | G16: =VLOOKUP(B16,'SH Summary'!C:L,10,FALSE) -> 0.016395866 | H16: =G16/F16-1 -> #DIV/0!
B17: Wellington Management Company, LLP | C17: =INDEX('SH Summary'!A:A,MATCH(B17,'SH Summary'!C:C,0)) -> 0 | D17: =INDEX('SH Summary'!B:B,MATCH(B17,'SH Summary'!C:C,0)) -> 31 | E17: =C17-D17 -> -31 | F17: =VLOOKUP(B17,'SH Summary'!C:L,9,FALSE) -> 0 | G17: =VLOOKUP(B17,'SH Summary'!C:L,10,FALSE) -> 0.0036509181 | H17: =G17/F17-1 -> #DIV/0!
B18: BlackRock Advisors (U.K.), LTD | C18: =INDEX('SH Summary'!A:A,MATCH(B18,'SH Summary'!C:C,0)) -> 0 | D18: =INDEX('SH Summary'!B:B,MATCH(B18,'SH Summary'!C:C,0)) -> 10 | E18: =C18-D18 -> -10 | F18: =VLOOKUP(B18,'SH Summary'!C:L,9,FALSE) -> 0 | G18: =VLOOKUP(B18,'SH Summary'!C:L,10,FALSE) -> 0.009917748 | H18: =G18/F18-1 -> #DIV/0!
B19: E Fund Management Company, LTD | C19: =INDEX('SH Summary'!A:A,MATCH(B19,'SH Summary'!C:C,0)) -> 0 | D19: =INDEX('SH Summary'!B:B,MATCH(B19,'SH Summary'!C:C,0)) -> 7 | E19: =C19-D19 -> -7 | F19: =VLOOKUP(B19,'SH Summary'!C:L,9,FALSE) -> 0 | G19: =VLOOKUP(B19,'SH Summary'!C:L,10,FALSE) -> 0.010429944 | H19: =G19/F19-1 -> #DIV/0!
B20: Capital International Investors | C20: =INDEX('SH Summary'!A:A,MATCH(B20,'SH Summary'!C:C,0)) -> 0 | D20: =INDEX('SH Summary'!B:B,MATCH(B20,'SH Summary'!C:C,0)) -> 125 | E20: =C20-D20 -> -125 | F20: =VLOOKUP(B20,'SH Summary'!C:L,9,FALSE) -> 0 | G20: =VLOOKUP(B20,'SH Summary'!C:L,10,FALSE) -> 0.00058282755 | H20: =G20/F20-1 -> #DIV/0!
B21: Krane Funds Advisors, LLC | C21: =INDEX('SH Summary'!A:A,MATCH(B21,'SH Summary'!C:C,0)) -> 0 | D21: =INDEX('SH Summary'!B:B,MATCH(B21,'SH Summary'!C:C,0)) -> 11 | E21: =C21-D21 -> -11 | F21: =VLOOKUP(B21,'SH Summary'!C:L,9,FALSE) -> 0 | G21: =VLOOKUP(B21,'SH Summary'!C:L,10,FALSE) -> 0.0091786626 | H21: =G21/F21-1 -> #DIV/0!
B22: Fidelity International Limited - FIL Investment Services (U.K.), LTD | C22: =INDEX('SH Summary'!A:A,MATCH(B22,'SH Summary'!C:C,0)) -> 0 | D22: =INDEX('SH Summary'!B:B,MATCH(B22,'SH Summary'!C:C,0)) -> 13 | E22: =C22-D22 -> -13 | F22: =VLOOKUP(B22,'SH Summary'!C:L,9,FALSE) -> 0 | G22: =VLOOKUP(B22,'SH Summary'!C:L,10,FALSE) -> 0.0084033763 | H22: =G22/F22-1 -> #DIV/0!
... B30: Arga Investment Management, L.P. | C30: =INDEX('SH Summary'!A:A,MATCH(B30,'SH Summary'!C:C,0)) -> 0 | D30: =INDEX('SH Summary'!B:B,MATCH(B30,'SH Summary'!C:C,0)) -> 25 | E30: =C30-D30 -> -25 | F30: =VLOOKUP(B30,'SH Summary'!C:L,9,FALSE) -> 0 | G30: =VLOOKUP(B30,'SH Summary'!C:L,10,FALSE) -> 0.0044093304 | H30: =G30/F30-1 -> #DIV/0!
B32: Top 20 26Q1
B34: Institution Name | C34: 25Q4 Rank | D34: 26Q1 Rank | E34: Rank Change | F34: % S/O 25Q4 | G34: % S/O 26Q1 | H34: % S/O Change
B35: Capital World Investors (U.S.) | C35: =INDEX('SH Summary'!A:A,MATCH(B35,'SH Summary'!C:C,0)) -> 0 | D35: =INDEX('SH Summary'!B:B,MATCH(B35,'SH Summary'!C:C,0)) -> 1 | E35: =C35-D35 -> -1 | F35: =VLOOKUP(B35,'SH Summary'!C:L,9,FALSE) -> 0 | G35: =VLOOKUP(B35,'SH Summary'!C:L,10,FALSE) -> 0.062420518 | H35: =G35/F35-1 -> #DIV/0!
B36: The Vanguard Group, Inc. | C36: =INDEX('SH Summary'!A:A,MATCH(B36,'SH Summary'!C:C,0)) -> 0 | D36: =INDEX('SH Summary'!B:B,MATCH(B36,'SH Summary'!C:C,0)) -> 2 | E36: =C36-D36 -> -2 | F36: =VLOOKUP(B36,'SH Summary'!C:L,9,FALSE) -> 0 | G36: =VLOOKUP(B36,'SH Summary'!C:L,10,FALSE) -> 0.032561846 | H36: =G36/F36-1 -> #DIV/0!
B37: BlackRock Fund Advisors | C37: =INDEX('SH Summary'!A:A,MATCH(B37,'SH Summary'!C:C,0)) -> 0 | D37: =INDEX('SH Summary'!B:B,MATCH(B37,'SH Summary'!C:C,0)) -> 3 | E37: =C37-D37 -> -3 | F37: =VLOOKUP(B37,'SH Summary'!C:L,9,FALSE) -> 0 | G37: =VLOOKUP(B37,'SH Summary'!C:L,10,FALSE) -> 0.026587593 | H37: =G37/F37-1 -> #DIV/0!
B38: Morgan Stanley Investment Management Inc. | C38: =INDEX('SH Summary'!A:A,MATCH(B38,'SH Summary'!C:C,0)) -> 0 | D38: =INDEX('SH Summary'!B:B,MATCH(B38,'SH Summary'!C:C,0)) -> 4 | E38: =C38-D38 -> -4 | F38: =VLOOKUP(B38,'SH Summary'!C:L,9,FALSE) -> 0 | G38: =VLOOKUP(B38,'SH Summary'!C:L,10,FALSE) -> 0.017337715 | H38: =G38/F38-1 -> #DIV/0!
B39: Norges Bank Investment Management (Norway) | C39: =INDEX('SH Summary'!A:A,MATCH(B39,'SH Summary'!C:C,0)) -> 0 | D39: =INDEX('SH Summary'!B:B,MATCH(B39,'SH Summary'!C:C,0)) -> 5 | E39: =C39-D39 -> -5 | F39: =VLOOKUP(B39,'SH Summary'!C:L,9,FALSE) -> 0 | G39: =VLOOKUP(B39,'SH Summary'!C:L,10,FALSE) -> 0.016915321 | H39: =G39/F39-1 -> #DIV/0!
B40: Sanders Capital, LLC | C40: =INDEX('SH Summary'!A:A,MATCH(B40,'SH Summary'!C:C,0)) -> 0 | D40: =INDEX('SH Summary'!B:B,MATCH(B40,'SH Summary'!C:C,0)) -> 6 | E40: =C40-D40 -> -6 | F40: =VLOOKUP(B40,'SH Summary'!C:L,9,FALSE) -> 0 | G40: =VLOOKUP(B40,'SH Summary'!C:L,10,FALSE) -> 0.016395866 | H40: =G40/F40-1 -> #DIV/0!
B41: E Fund Management Company, LTD | C41: =INDEX('SH Summary'!A:A,MATCH(B41,'SH Summary'!C:C,0)) -> 0 | D41: =INDEX('SH Summary'!B:B,MATCH(B41,'SH Summary'!C:C,0)) -> 7 | E41: =C41-D41 -> -7 | F41: =VLOOKUP(B41,'SH Summary'!C:L,9,FALSE) -> 0 | G41: =VLOOKUP(B41,'SH Summary'!C:L,10,FALSE) -> 0.010429944 | H41: =G41/F41-1 -> #DIV/0!
B42: Davis Selected Advisers, L.P. | C42: =INDEX('SH Summary'!A:A,MATCH(B42,'SH Summary'!C:C,0)) -> 0 | D42: =INDEX('SH Summary'!B:B,MATCH(B42,'SH Summary'!C:C,0)) -> 8 | E42: =C42-D42 -> -8 | F42: =VLOOKUP(B42,'SH Summary'!C:L,9,FALSE) -> 0 | G42: =VLOOKUP(B42,'SH Summary'!C:L,10,FALSE) -> 0.010100462 | H42: =G42/F42-1 -> #DIV/0!
B43: CSOP Asset Management, LTD | C43: =INDEX('SH Summary'!A:A,MATCH(B43,'SH Summary'!C:C,0)) -> 0 | D43: =INDEX('SH Summary'!B:B,MATCH(B43,'SH Summary'!C:C,0)) -> 9 | E43: =C43-D43 -> -9 | F43: =VLOOKUP(B43,'SH Summary'!C:L,9,FALSE) -> 0 | G43: =VLOOKUP(B43,'SH Summary'!C:L,10,FALSE) -> 0.010071001 | H43: =G43/F43-1 -> #DIV/0!
B44: BlackRock Advisors (U.K.), LTD | C44: =INDEX('SH Summary'!A:A,MATCH(B44,'SH Summary'!C:C,0)) -> 0 | D44: =INDEX('SH Summary'!B:B,MATCH(B44,'SH Summary'!C:C,0)) -> 10 | E44: =C44-D44 -> -10 | F44: =VLOOKUP(B44,'SH Summary'!C:L,9,FALSE) -> 0 | G44: =VLOOKUP(B44,'SH Summary'!C:L,10,FALSE) -> 0.009917748 | H44: =G44/F44-1 -> #DIV/0!
B45: Krane Funds Advisors, LLC | C45: =INDEX('SH Summary'!A:A,MATCH(B45,'SH Summary'!C:C,0)) -> 0 | D45: =INDEX('SH Summary'!B:B,MATCH(B45,'SH Summary'!C:C,0)) -> 11 | E45: =C45-D45 -> -11 | F45: =VLOOKUP(B45,'SH Summary'!C:L,9,FALSE) -> 0 | G45: =VLOOKUP(B45,'SH Summary'!C:L,10,FALSE) -> 0.0091786626 | H45: =G45/F45-1 -> #DIV/0!
B46: FIL Investment Management (Hong Kong), LTD | C46: =INDEX('SH Summary'!A:A,MATCH(B46,'SH Summary'!C:C,0)) -> 0 | D46: =INDEX('SH Summary'!B:B,MATCH(B46,'SH Summary'!C:C,0)) -> 12 | E46: =C46-D46 -> -12 | F46: =VLOOKUP(B46,'SH Summary'!C:L,9,FALSE) -> 0 | G46: =VLOOKUP(B46,'SH Summary'!C:L,10,FALSE) -> 0.0090069222 | H46: =G46/F46-1 -> #DIV/0!
... B54: Geode Capital Management, LLC | C54: =INDEX('SH Summary'!A:A,MATCH(B54,'SH Summary'!C:C,0)) -> 0 | D54: =INDEX('SH Summary'!B:B,MATCH(B54,'SH Summary'!C:C,0)) -> 20 | E54: =C54-D54 -> -20 | F54: =VLOOKUP(B54,'SH Summary'!C:L,9,FALSE) -> 0 | G54: =VLOOKUP(B54,'SH Summary'!C:L,10,FALSE) -> 0.0051372924 | H54: =G54/F54-1 -> #DIV/0!

Sheet SH Summary
C1: Trip.com Group
C2: 26Q1 Institutional Ownership
F3: 648991284 | G3: updated as of 2026/03/31
D4: 7 | E4: 10 | M4: 9 | N4: 12 | O4: 14 | P4: 16 | Q4: 17 | R4: 18 | S4: 13
A5: 25Q4 Rank | B5: 26Q1 Rank | C5: Institution Name | D5: TCOM | E5: 9961 | F5: Total Shares 26Q1 | G5: Total Shares 25Q4 | H5: QoQ | I5: % S/O 25Q2 | J5: % S/O 25Q3 | K5: % S/O 25Q4 | L5: % S/O 26Q1 | M5: Position Date (TCOM) | N5: Position Date (9961) | O5: Dominant Style | P5: City | Q5: State | R5: Country | S5: Equity AUM $bn
B6: 1 | C6: Capital World Investors (U.S.) | D6: =VLOOKUP($C6,'Data_TCOM+9961'!$A:$U,'SH Summary'!D$4,FALSE) -> 36115209 | E6: =VLOOKUP($C6,'Data_TCOM+9961'!$A:$U,'SH Summary'!E$4,FALSE) -> 4395163 | F6: =D6+E6 -> 40510372 | H6: =F6-G6 -> 40510372 | L6: =F6/$F$3 -> 0.062420518 | M6: =VLOOKUP($C6,'Data_TCOM+9961'!$A:$U,'SH Summary'!M$4,FALSE) -> 03/31/2026 | N6: =VLOOKUP($C6,'Data_TCOM+9961'!$A:$U,'SH Summary'!N$4,FALSE) -> 03/31/2026 | O6: =VLOOKUP($C6,'Data_TCOM+9961'!$A:$U,'SH Summary'!O$4,FALSE) -> Value | P6: =VLOOKUP($C6,'Data_TCOM+9961'!$A:$U,'SH Summary'!P$4,FALSE) -> Los Angeles | Q6: =VLOOKUP($C6,'Data_TCOM+9961'!$A:$U,'SH Summary'!Q$4,FALSE) -> California | R6: =VLOOKUP($C6,'Data_TCOM+9961'!$A:$U,'SH Summary'!R$4,FALSE) -> United States | S6: =VLOOKUP($C6,'Data_TCOM+9961'!$A:$U,'SH Summary'!S$4,FALSE)/1000000000 -> 1022.5949
B7: 2 | C7: The Vanguard Group, Inc. | D7: =VLOOKUP($C7,'Data_TCOM+9961'!$A:$U,'SH Summary'!D$4,FALSE) -> 0 | E7: =VLOOKUP($C7,'Data_TCOM+9961'!$A:$U,'SH Summary'!E$4,FALSE) -> 21132354 | F7: =D7+E7 -> 21132354 | H7: =F7-G7 -> 21132354 | L7: =F7/$F$3 -> 0.032561846 | M7: =VLOOKUP($C7,'Data_TCOM+9961'!$A:$U,'SH Summary'!M$4,FALSE) -> 0 | N7: =VLOOKUP($C7,'Data_TCOM+9961'!$A:$U,'SH Summary'!N$4,FALSE) -> 03/31/2026 | O7: =VLOOKUP($C7,'Data_TCOM+9961'!$A:$U,'SH Summary'!O$4,FALSE) -> Index | P7: =VLOOKUP($C7,'Data_TCOM+9961'!$A:$U,'SH Summary'!P$4,FALSE) -> Malvern | Q7: =VLOOKUP($C7,'Data_TCOM+9961'!$A:$U,'SH Summary'!Q$4,FALSE) -> Pennsylvania | R7: =VLOOKUP($C7,'Data_TCOM+9961'!$A:$U,'SH Summary'!R$4,FALSE) -> United States | S7: =VLOOKUP($C7,'Data_TCOM+9961'!$A:$U,'SH Summary'!S$4,FALSE)/1000000000 -> 7960.9296
B8: 3 | C8: BlackRock Fund Advisors | D8: =VLOOKUP($C8,'Data_TCOM+9961'!$A:$U,'SH Summary'!D$4,FALSE) -> 594873 | E8: =VLOOKUP($C8,'Data_TCOM+9961'!$A:$U,'SH Summary'!E$4,FALSE) -> 16660243 | F8: =D8+E8 -> 17255116 | H8: =F8-G8 -> 17255116 | L8: =F8/$F$3 -> 0.026587593 | M8: =VLOOKUP($C8,'Data_TCOM+9961'!$A:$U,'SH Summary'!M$4,FALSE) -> 03/31/2026 | N8: =VLOOKUP($C8,'Data_TCOM+9961'!$A:$U,'SH Summary'!N$4,FALSE) -> 05/12/2026 | O8: =VLOOKUP($C8,'Data_TCOM+9961'!$A:$U,'SH Summary'!O$4,FALSE) -> Index | P8: =VLOOKUP($C8,'Data_TCOM+9961'!$A:$U,'SH Summary'!P$4,FALSE) -> San Francisco | Q8: =VLOOKUP($C8,'Data_TCOM+9961'!$A:$U,'SH Summary'!Q$4,FALSE) -> California | R8: =VLOOKUP($C8,'Data_TCOM+9961'!$A:$U,'SH Summary'!R$4,FALSE) -> United States | S8: =VLOOKUP($C8,'Data_TCOM+9961'!$A:$U,'SH Summary'!S$4,FALSE)/1000000000 -> 4837.4638
B9: 4 | C9: Morgan Stanley Investment Management Inc. | D9: =VLOOKUP($C9,'Data_TCOM+9961'!$A:$U,'SH Summary'!D$4,FALSE) -> 11223376 | E9: =VLOOKUP($C9,'Data_TCOM+9961'!$A:$U,'SH Summary'!E$4,FALSE) -> 28650 | F9: =D9+E9 -> 11252026 | H9: =F9-G9 -> 11252026 | L9: =F9/$F$3 -> 0.017337715 | M9: =VLOOKUP($C9,'Data_TCOM+9961'!$A:$U,'SH Summary'!M$4,FALSE) -> 03/31/2026 | N9: =VLOOKUP($C9,'Data_TCOM+9961'!$A:$U,'SH Summary'!N$4,FALSE) -> 07/31/2024 | O9: =VLOOKUP($C9,'Data_TCOM+9961'!$A:$U,'SH Summary'!O$4,FALSE) -> Growth | P9: =VLOOKUP($C9,'Data_TCOM+9961'!$A:$U,'SH Summary'!P$4,FALSE) -> New York | Q9: =VLOOKUP($C9,'Data_TCOM+9961'!$A:$U,'SH Summary'!Q$4,FALSE) -> New York | R9: =VLOOKUP($C9,'Data_TCOM+9961'!$A:$U,'SH Summary'!R$4,FALSE) -> United States | S9: =VLOOKUP($C9,'Data_TCOM+9961'!$A:$U,'SH Summary'!S$4,FALSE)/1000000000 -> 117.75848
B10: 5 | C10: Norges Bank Investment Management (Norway) | D10: =VLOOKUP($C10,'Data_TCOM+9961'!$A:$U,'SH Summary'!D$4,FALSE) -> 164868 | E10: =VLOOKUP($C10,'Data_TCOM+9961'!$A:$U,'SH Summary'!E$4,FALSE) -> 10813028 | F10: =D10+E10 -> 10977896 | H10: =F10-G10 -> 10977896 | L10: =F10/$F$3 -> 0.016915321 | M10: =VLOOKUP($C10,'Data_TCOM+9961'!$A:$U,'SH Summary'!M$4,FALSE) -> 12/31/2025 | N10: =VLOOKUP($C10,'Data_TCOM+9961'!$A:$U,'SH Summary'!N$4,FALSE) -> 12/31/2025 | O10: =VLOOKUP($C10,'Data_TCOM+9961'!$A:$U,'SH Summary'!O$4,FALSE) -> Value | P10: =VLOOKUP($C10,'Data_TCOM+9961'!$A:$U,'SH Summary'!P$4,FALSE) -> Oslo | Q10: =VLOOKUP($C10,'Data_TCOM+9961'!$A:$U,'SH Summary'!Q$4,FALSE) -> 0 | R10: =VLOOKUP($C10,'Data_TCOM+9961'!$A:$U,'SH Summary'!R$4,FALSE) -> Norway | S10: =VLOOKUP($C10,'Data_TCOM+9961'!$A:$U,'SH Summary'!S$4,FALSE)/1000000000 -> 1551.8473
B11: 6 | C11: Sanders Capital, LLC | D11: =VLOOKUP($C11,'Data_TCOM+9961'!$A:$U,'SH Summary'!D$4,FALSE) -> 10640774 | E11: =VLOOKUP($C11,'Data_TCOM+9961'!$A:$U,'SH Summary'!E$4,FALSE) -> 0 | F11: =D11+E11 -> 10640774 | H11: =F11-G11 -> 10640774 | L11: =F11/$F$3 -> 0.016395866 | M11: =VLOOKUP($C11,'Data_TCOM+9961'!$A:$U,'SH Summary'!M$4,FALSE) -> 03/31/2026 | N11: =VLOOKUP($C11,'Data_TCOM+9961'!$A:$U,'SH Summary'!N$4,FALSE) -> 0 | O11: =VLOOKUP($C11,'Data_TCOM+9961'!$A:$U,'SH Summary'!O$4,FALSE) -> Value | P11: =VLOOKUP($C11,'Data_TCOM+9961'!$A:$U,'SH Summary'!P$4,FALSE) -> West Palm Beach | Q11: =VLOOKUP($C11,'Data_TCOM+9961'!$A:$U,'SH Summary'!Q$4,FALSE) -> Florida | R11: =VLOOKUP($C11,'Data_TCOM+9961'!$A:$U,'SH Summary'!R$4,FALSE) -> United States | S11: =VLOOKUP($C11,'Data_TCOM+9961'!$A:$U,'SH Summary'!S$4,FALSE)/1000000000 -> 89.446668
B12: 7 | C12: E Fund Management Company, LTD | D12: =VLOOKUP($C12,'Data_TCOM+9961'!$A:$U,'SH Summary'!D$4,FALSE) -> 1294 | E12: =VLOOKUP($C12,'Data_TCOM+9961'!$A:$U,'SH Summary'!E$4,FALSE) -> 6767649 | F12: =D12+E12 -> 6768943 | H12: =F12-G12 -> 6768943 | L12: =F12/$F$3 -> 0.010429944 | M12: =VLOOKUP($C12,'Data_TCOM+9961'!$A:$U,'SH Summary'!M$4,FALSE) -> 12/31/2025 | N12: =VLOOKUP($C12,'Data_TCOM+9961'!$A:$U,'SH Summary'!N$4,FALSE) -> 12/31/2025 | O12: =VLOOKUP($C12,'Data_TCOM+9961'!$A:$U,'SH Summary'!O$4,FALSE) -> Growth | P12: =VLOOKUP($C12,'Data_TCOM+9961'!$A:$U,'SH Summary'!P$4,FALSE) -> Guangzhou | Q12: =VLOOKUP($C12,'Data_TCOM+9961'!$A:$U,'SH Summary'!Q$4,FALSE) -> 0 | R12: =VLOOKUP($C12,'Data_TCOM+9961'!$A:$U,'SH Summary'!R$4,FALSE) -> China (Mainland) | S12: =VLOOKUP($C12,'Data_TCOM+9961'!$A:$U,'SH Summary'!S$4,FALSE)/1000000000 -> 123.95179
B13: 8 | C13: Davis Selected Advisers, L.P. | D13: =VLOOKUP($C13,'Data_TCOM+9961'!$A:$U,'SH Summary'!D$4,FALSE) -> 6555112 | E13: =VLOOKUP($C13,'Data_TCOM+9961'!$A:$U,'SH Summary'!E$4,FALSE) -> 0 | F13: =D13+E13 -> 6555112 | H13: =F13-G13 -> 6555112 | L13: =F13/$F$3 -> 0.010100462 | M13: =VLOOKUP($C13,'Data_TCOM+9961'!$A:$U,'SH Summary'!M$4,FALSE) -> 03/31/2026 | N13: =VLOOKUP($C13,'Data_TCOM+9961'!$A:$U,'SH Summary'!N$4,FALSE) -> 0 | O13: =VLOOKUP($C13,'Data_TCOM+9961'!$A:$U,'SH Summary'!O$4,FALSE) -> Value | P13: =VLOOKUP($C13,'Data_TCOM+9961'!$A:$U,'SH Summary'!P$4,FALSE) -> New York | Q13: =VLOOKUP($C13,'Data_TCOM+9961'!$A:$U,'SH Summary'!Q$4,FALSE) -> New York | R13: =VLOOKUP($C13,'Data_TCOM+9961'!$A:$U,'SH Summary'!R$4,FALSE) -> United States | S13: =VLOOKUP($C13,'Data_TCOM+9961'!$A:$U,'SH Summary'!S$4,FALSE)/1000000000 -> 25.230328
B14: 9 | C14: CSOP Asset Management, LTD | D14: =VLOOKUP($C14,'Data_TCOM+9961'!$A:$U,'SH Summary'!D$4,FALSE) -> 26844 | E14: =VLOOKUP($C14,'Data_TCOM+9961'!$A:$U,'SH Summary'!E$4,FALSE) -> 6509148 | F14: =D14+E14 -> 6535992 | H14: =F14-G14 -> 6535992 | L14: =F14/$F$3 -> 0.010071001 | M14: =VLOOKUP($C14,'Data_TCOM+9961'!$A:$U,'SH Summary'!M$4,FALSE) -> 08/31/2024 | N14: =VLOOKUP($C14,'Data_TCOM+9961'!$A:$U,'SH Summary'!N$4,FALSE) -> 05/14/2026 | O14: =VLOOKUP($C14,'Data_TCOM+9961'!$A:$U,'SH Summary'!O$4,FALSE) -> Value | P14: =VLOOKUP($C14,'Data_TCOM+9961'!$A:$U,'SH Summary'!P$4,FALSE) -> Central | Q14: =VLOOKUP($C14,'Data_TCOM+9961'!$A:$U,'SH Summary'!Q$4,FALSE) -> 0 | R14: =VLOOKUP($C14,'Data_TCOM+9961'!$A:$U,'SH Summary'!R$4,FALSE) -> Hong Kong SAR | S14: =VLOOKUP($C14,'Data_TCOM+9961'!$A:$U,'SH Summary'!S$4,FALSE)/1000000000 -> 20.343937
B15: 10 | C15: BlackRock Advisors (U.K.), LTD | D15: =VLOOKUP($C15,'Data_TCOM+9961'!$A:$U,'SH Summary'!D$4,FALSE) -> 21485 | E15: =VLOOKUP($C15,'Data_TCOM+9961'!$A:$U,'SH Summary'!E$4,FALSE) -> 6415047 | F15: =D15+E15 -> 6436532 | H15: =F15-G15 -> 6436532 | L15: =F15/$F$3 -> 0.009917748 | M15: =VLOOKUP($C15,'Data_TCOM+9961'!$A:$U,'SH Summary'!M$4,FALSE) -> 06/30/2025 | N15: =VLOOKUP($C15,'Data_TCOM+9961'!$A:$U,'SH Summary'!N$4,FALSE) -> 05/12/2026 | O15: =VLOOKUP($C15,'Data_TCOM+9961'!$A:$U,'SH Summary'!O$4,FALSE) -> Index | P15: =VLOOKUP($C15,'Data_TCOM+9961'!$A:$U,'SH Summary'!P$4,FALSE) -> London | Q15: =VLOOKUP($C15,'Data_TCOM+9961'!$A:$U,'SH Summary'!Q$4,FALSE) -> 0 | R15: =VLOOKUP($C15,'Data_TCOM+9961'!$A:$U,'SH Summary'!R$4,FALSE) -> United Kingdom | S15: =VLOOKUP($C15,'Data_TCOM+9961'!$A:$U,'SH Summary'!S$4,FALSE)/1000000000 -> 441.93474
B16: 11 | C16: Krane Funds Advisors, LLC | D16: =VLOOKUP($C16,'Data_TCOM+9961'!$A:$U,'SH Summary'!D$4,FALSE) -> 0 | E16: =VLOOKUP($C16,'Data_TCOM+9961'!$A:$U,'SH Summary'!E$4,FALSE) -> 5956872 | F16: =D16+E16 -> 5956872 | H16: =F16-G16 -> 5956872 | L16: =F16/$F$3 -> 0.0091786626 | M16: =VLOOKUP($C16,'Data_TCOM+9961'!$A:$U,'SH Summary'!M$4,FALSE) -> 0 | N16: =VLOOKUP($C16,'Data_TCOM+9961'!$A:$U,'SH Summary'!N$4,FALSE) -> 05/13/2026 | O16: =VLOOKUP($C16,'Data_TCOM+9961'!$A:$U,'SH Summary'!O$4,FALSE) -> Index | P16: =VLOOKUP($C16,'Data_TCOM+9961'!$A:$U,'SH Summary'!P$4,FALSE) -> New York | Q16: =VLOOKUP($C16,'Data_TCOM+9961'!$A:$U,'SH Summary'!Q$4,FALSE) -> New York | R16: =VLOOKUP($C16,'Data_TCOM+9961'!$A:$U,'SH Summary'!R$4,FALSE) -> United States | S16: =VLOOKUP($C16,'Data_TCOM+9961'!$A:$U,'SH Summary'!S$4,FALSE)/1000000000 -> 9.4875478
B17: 12 | C17: FIL Investment Management (Hong Kong), LTD | D17: =VLOOKUP($C17,'Data_TCOM+9961'!$A:$U,'SH Summary'!D$4,FALSE) -> 0 | E17: =VLOOKUP($C17,'Data_TCOM+9961'!$A:$U,'SH Summary'!E$4,FALSE) -> 5845414 | F17: =D17+E17 -> 5845414 | H17: =F17-G17 -> 5845414 | L17: =F17/$F$3 -> 0.0090069222 | M17: =VLOOKUP($C17,'Data_TCOM+9961'!$A:$U,'SH Summary'!M$4,FALSE) -> 06/30/2025 | N17: =VLOOKUP($C17,'Data_TCOM+9961'!$A:$U,'SH Summary'!N$4,FALSE) -> 03/31/2026 | O17: =VLOOKUP($C17,'Data_TCOM+9961'!$A:$U,'SH Summary'!O$4,FALSE) -> Growth | P17: =VLOOKUP($C17,'Data_TCOM+9961'!$A:$U,'SH Summary'!P$4,FALSE) -> Admiralty | Q17: =VLOOKUP($C17,'Data_TCOM+9961'!$A:$U,'SH Summary'!Q$4,FALSE) -> 0 | R17: =VLOOKUP($C17,'Data_TCOM+9961'!$A:$U,'SH Summary'!R$4,FALSE) -> Hong Kong SAR | S17: =VLOOKUP($C17,'Data_TCOM+9961'!$A:$U,'SH Summary'!S$4,FALSE)/1000000000 -> 22.289992
... B870: 865 | C870: The Huntington Investment Company (Asset Management) | D870: =VLOOKUP($C870,'Data_TCOM+9961'!$A:$U,'SH Summary'!D$4,FALSE) -> 1 | E870: =VLOOKUP($C870,'Data_TCOM+9961'!$A:$U,'SH Summary'!E$4,FALSE) -> 0 | F870: =D870+E870 -> 1 | H870: =F870-G870 -> 1 | L870: =F870/$F$3 -> 1.5408527e-09 | M870: =VLOOKUP($C870,'Data_TCOM+9961'!$A:$U,'SH Summary'!M$4,FALSE) -> 03/31/2026 | N870: =VLOOKUP($C870,'Data_TCOM+9961'!$A:$U,'SH Summary'!N$4,FALSE) -> 0 | O870: =VLOOKUP($C870,'Data_TCOM+9961'!$A:$U,'SH Summary'!O$4,FALSE) -> Growth | P870: =VLOOKUP($C870,'Data_TCOM+9961'!$A:$U,'SH Summary'!P$4,FALSE) -> Columbus | Q870: =VLOOKUP($C870,'Data_TCOM+9961'!$A:$U,'SH Summary'!Q$4,FALSE) -> Ohio | R870: =VLOOKUP($C870,'Data_TCOM+9961'!$A:$U,'SH Summary'!R$4,FALSE) -> United States | S870: =VLOOKUP($C870,'Data_TCOM+9961'!$A:$U,'SH Summary'!S$4,FALSE)/1000000000 -> 18.117657
L871: =F871/$F$3 -> 0
L872: =F872/$F$3 -> 0
F911: =SUM(F6:F910) -> 341246350 | L911: =F911/$F$3 -> 0.52581037
F912: =F911/F3 -> 0.52581037
F913: =50*F912 -> 26.290519

Sheet Data_TCOM+9961
A1: Combined Ownership | B1: Combined Ownership | C1: Combined Ownership | D1: Combined Ownership | E1: Combined Ownership | F1: Combined Ownership | G1: Combined Ownership | H1: Combined Ownership | I1: Combined Ownership | J1: Combined Ownership | K1: Combined Ownership | L1: Combined Ownership | M1: Combined Ownership | N1: Combined Ownership | O1: Combined Ownership | P1: Combined Ownership | Q1: Combined Ownership | R1: Combined Ownership
A2: 1 | B2: 2 | C2: 3 | D2: 4 | E2: 5 | F2: 6 | G2: 7 | H2: 8 | I2: 9 | J2: 10 | K2: 11 | L2: 12 | M2: 13 | N2: 14 | O2: 15 | P2: 16 | Q2: 17 | R2: 18 | S2: 19 | T2: 20 | U2: 21
A3: Institution | B3: Sustainability Considered | C3: Holder Rank (Combined) | D3: Shares (Combined) | E3: Share Change (Combined) | F3: % S/O (Combined) | G3: TCOM Shares | H3: TCOM Share Change | I3: TCOM Reported Date | J3: 9961_XHKG Shares | K3: 9961_XHKG Share Change | L3: 9961_XHKG Reported Date | M3: Equity Assets USD, mm | N3: Style | O3: Turnover | P3: City | Q3: State/Province | R3: Country/Territory | S3: Fund Size | T3: Region | U3: Fund Style
A4: Baidu Holdings, LTD | B4: no | C4: 1 | D4: 45953524 | E4: 0 | F4: 6.67 | J4: 45953524 | K4: 0 | L4: 02/28/2025 | M4: 2925117269 | R4: China (Mainland) | S4: =IF(M4>100000000000, "100bn", IF(M4>50000000000, "50bn - 100bn",IF(M4>1000000000, "1bn - 50bn", IF(M4>500000000, "500mn - 1bn", "500mn")))) -> 1bn - 50bn | T4: =VLOOKUP(R4,Mapping!B:C,2,FALSE) -> CN | U4: =VLOOKUP(N4,Mapping!H:I,2,FALSE) -> #N/A
A5: Capital World Investors (U.S.) | B5: no | C5: 2 | D5: 40510372 | E5: -9927305 | F5: 5.88 | G5: 36115209 | H5: 3305361 | I5: 03/31/2026 | J5: 4395163 | K5: -13232666 | L5: 03/31/2026 | M5: 1022594898625 | N5: Value | O5: 34.246 | P5: Los Angeles | Q5: California | R5: United States | S5: =IF(M5>100000000000, "100bn", IF(M5>50000000000, "50bn - 100bn",IF(M5>1000000000, "1bn - 50bn", IF(M5>500000000, "500mn - 1bn", "500mn")))) -> 100bn | T5: =VLOOKUP(R5,Mapping!B:C,2,FALSE) -> US/CA | U5: =VLOOKUP(N5,Mapping!H:I,2,FALSE) -> Value
A6: The Vanguard Group, Inc. | B6: yes | C6: 3 | D6: 21132354 | E6: 327200 | F6: 3.07 | J6: 21132354 | K6: 327200 | L6: 03/31/2026 | M6: 7960929576394 | N6: Index | O6: 4.761 | P6: Malvern | Q6: Pennsylvania | R6: United States | S6: =IF(M6>100000000000, "100bn", IF(M6>50000000000, "50bn - 100bn",IF(M6>1000000000, "1bn - 50bn", IF(M6>500000000, "500mn - 1bn", "500mn")))) -> 100bn | T6: =VLOOKUP(R6,Mapping!B:C,2,FALSE) -> US/CA | U6: =VLOOKUP(N6,Mapping!H:I,2,FALSE) -> Index
A7: BlackRock Fund Advisors | B7: yes | C7: 4 | D7: 17255116 | E7: -121808 | F7: 2.5 | G7: 594873 | H7: -104775 | I7: 03/31/2026 | J7: 16660243 | K7: -17033 | L7: 05/12/2026 | M7: 4837463753757 | N7: Index | O7: 7.486 | P7: San Francisco | Q7: California | R7: United States | S7: =IF(M7>100000000000, "100bn", IF(M7>50000000000, "50bn - 100bn",IF(M7>1000000000, "1bn - 50bn", IF(M7>500000000, "500mn - 1bn", "500mn")))) -> 100bn | T7: =VLOOKUP(R7,Mapping!B:C,2,FALSE) -> US/CA | U7: =VLOOKUP(N7,Mapping!H:I,2,FALSE) -> Index
A8: Morgan Stanley Investment Management Inc. | B8: yes | C8: 5 | D8: 11252026 | E8: -2058757 | F8: 1.63 | G8: 11223376 | H8: -2087407 | I8: 03/31/2026 | J8: 28650 | K8: 28650 | L8: 07/31/2024 | M8: 117758479640 | N8: Growth | O8: 53.081 | P8: New York | Q8: New York | R8: United States | S8: =IF(M8>100000000000, "100bn", IF(M8>50000000000, "50bn - 100bn",IF(M8>1000000000, "1bn - 50bn", IF(M8>500000000, "500mn - 1bn", "500mn")))) -> 100bn | T8: =VLOOKUP(R8,Mapping!B:C,2,FALSE) -> US/CA | U8: =VLOOKUP(N8,Mapping!H:I,2,FALSE) -> Growth
A9: Norges Bank Investment Management (Norway) | B9: yes | C9: 6 | D9: 10977896 | E9: -925944 | F9: 1.59 | G9: 164868 | H9: -606028 | I9: 12/31/2025 | J9: 10813028 | K9: -319916 | L9: 12/31/2025 | M9: 1551847282513 | N9: Value | O9: 20.194 | P9: Oslo | R9: Norway | S9: =IF(M9>100000000000, "100bn", IF(M9>50000000000, "50bn - 100bn",IF(M9>1000000000, "1bn - 50bn", IF(M9>500000000, "500mn - 1bn", "500mn")))) -> 100bn | T9: =VLOOKUP(R9,Mapping!B:C,2,FALSE) -> EU | U9: =VLOOKUP(N9,Mapping!H:I,2,FALSE) -> Value
A10: Sanders Capital, LLC | B10: no | C10: 7 | D10: 10640774 | E10: 750137 | F10: 1.54 | G10: 10640774 | H10: 750137 | I10: 03/31/2026 | M10: 89446668161 | N10: Value | O10: 26.849 | P10: West Palm Beach | Q10: Florida | R10: United States | S10: =IF(M10>100000000000, "100bn", IF(M10>50000000000, "50bn - 100bn",IF(M10>1000000000, "1bn - 50bn", IF(M10>500000000, "500mn - 1bn", "500mn")))) -> 50bn - 100bn | T10: =VLOOKUP(R10,Mapping!B:C,2,FALSE) -> US/CA | U10: =VLOOKUP(N10,Mapping!H:I,2,FALSE) -> Value
A11: E Fund Management Company, LTD | B11: yes | C11: 8 | D11: 6768943 | E11: 501944 | F11: 0.98 | G11: 1294 | H11: 1294 | I11: 12/31/2025 | J11: 6767649 | K11: 500650 | L11: 12/31/2025 | M11: 123951792127 | N11: Growth | O11: 26.808 | P11: Guangzhou | R11: China (Mainland) | S11: =IF(M11>100000000000, "100bn", IF(M11>50000000000, "50bn - 100bn",IF(M11>1000000000, "1bn - 50bn", IF(M11>500000000, "500mn - 1bn", "500mn")))) -> 100bn | T11: =VLOOKUP(R11,Mapping!B:C,2,FALSE) -> CN | U11: =VLOOKUP(N11,Mapping!H:I,2,FALSE) -> Growth
A12: Davis Selected Advisers, L.P. | B12: no | C12: 9 | D12: 6555112 | E12: 1501723 | F12: 0.95 | G12: 6555112 | H12: 1501723 | I12: 03/31/2026 | M12: 25230328351 | N12: Value | O12: 26.916 | P12: New York | Q12: New York | R12: United States | S12: =IF(M12>100000000000, "100bn", IF(M12>50000000000, "50bn - 100bn",IF(M12>1000000000, "1bn - 50bn", IF(M12>500000000, "500mn - 1bn", "500mn")))) -> 1bn - 50bn | T12: =VLOOKUP(R12,Mapping!B:C,2,FALSE) -> US/CA | U12: =VLOOKUP(N12,Mapping!H:I,2,FALSE) -> Value
A13: CSOP Asset Management, LTD | B13: yes | C13: 10 | D13: 6535992 | E13: -258986 | F13: 0.95 | G13: 26844 | H13: -1062 | I13: 08/31/2024 | J13: 6509148 | K13: -257924 | L13: 05/14/2026 | M13: 20343937181 | N13: Value | O13: 55.36 | P13: Central | R13: Hong Kong SAR | S13: =IF(M13>100000000000, "100bn", IF(M13>50000000000, "50bn - 100bn",IF(M13>1000000000, "1bn - 50bn", IF(M13>500000000, "500mn - 1bn", "500mn")))) -> 1bn - 50bn | T13: =VLOOKUP(R13,Mapping!B:C,2,FALSE) -> HK | U13: =VLOOKUP(N13,Mapping!H:I,2,FALSE) -> Value
A14: BlackRock Advisors (U.K.), LTD | B14: yes | C14: 11 | D14: 6436532 | E14: -105415 | F14: 0.93 | G14: 21485 | H14: -23515 | I14: 06/30/2025 | J14: 6415047 | K14: -81900 | L14: 05/12/2026 | M14: 441934744795 | N14: Index | O14: 16.499 | P14: London | R14: United Kingdom | S14: =IF(M14>100000000000, "100bn", IF(M14>50000000000, "50bn - 100bn",IF(M14>1000000000, "1bn - 50bn", IF(M14>500000000, "500mn - 1bn", "500mn")))) -> 100bn | T14: =VLOOKUP(R14,Mapping!B:C,2,FALSE) -> EU | U14: =VLOOKUP(N14,Mapping!H:I,2,FALSE) -> Index
A15: Krane Funds Advisors, LLC | B15: yes | C15: 12 | D15: 5956872 | E15: 557950 | F15: 0.86 | J15: 5956872 | K15: 557950 | L15: 05/13/2026 | M15: 9487547762 | N15: Index | O15: 40.029 | P15: New York | Q15: New York | R15: United States | S15: =IF(M15>100000000000, "100bn", IF(M15>50000000000, "50bn - 100bn",IF(M15>1000000000, "1bn - 50bn", IF(M15>500000000, "500mn - 1bn", "500mn")))) -> 1bn - 50bn | T15: =VLOOKUP(R15,Mapping!B:C,2,FALSE) -> US/CA | U15: =VLOOKUP(N15,Mapping!H:I,2,FALSE) -> Index
A16: FIL Investment Management (Hong Kong), LTD | B16: yes | C16: 13 | D16: 5845414 | E16: -601235 | F16: 0.85 | G16: 0 | H16: -167735 | I16: 06/30/2025 | J16: 5845414 | K16: -433500 | L16: 03/31/2026 | M16: 22289992322 | N16: Growth | O16: 36.77 | P16: Admiralty | R16: Hong Kong SAR | S16: =IF(M16>100000000000, "100bn", IF(M16>50000000000, "50bn - 100bn",IF(M16>1000000000, "1bn - 50bn", IF(M16>500000000, "500mn - 1bn", "500mn")))) -> 1bn - 50bn | T16: =VLOOKUP(R16,Mapping!B:C,2,FALSE) -> HK | U16: =VLOOKUP(N16,Mapping!H:I,2,FALSE) -> Growth
A17: Fidelity International Limited - FIL Investment Services (U.K.), LTD | B17: yes | C17: 14 | D17: 5453718 | E17: -323506 | F17: 0.79 | G17: 0 | H17: -240490 | I17: 09/30/2025 | J17: 5453718 | K17: -83016 | L17: 03/31/2026 | M17: 152579846744 | N17: Growth | O17: 43.975 | P17: London | R17: United Kingdom | S17: =IF(M17>100000000000, "100bn", IF(M17>50000000000, "50bn - 100bn",IF(M17>1000000000, "1bn - 50bn", IF(M17>500000000, "500mn - 1bn", "500mn")))) -> 100bn | T17: =VLOOKUP(R17,Mapping!B:C,2,FALSE) -> EU | U17: =VLOOKUP(N17,Mapping!H:I,2,FALSE) -> Growth
A18: Schroder Investment Management (Hong Kong), LTD | B18: yes | C18: 15 | D18: 5105592 | E18: -4950 | F18: 0.74 | G18: 1156692 | H18: 0 | I18: 03/31/2026 | J18: 3948900 | K18: -4950 | L18: 04/30/2026 | M18: 20277427178 | N18: GARP | O18: 60.416 | P18: Admiralty | R18: Hong Kong SAR | S18: =IF(M18>100000000000, "100bn", IF(M18>50000000000, "50bn - 100bn",IF(M18>1000000000, "1bn - 50bn", IF(M18>500000000, "500mn - 1bn", "500mn")))) -> 1bn - 50bn | T18: =VLOOKUP(R18,Mapping!B:C,2,FALSE) -> HK | U18: =VLOOKUP(N18,Mapping!H:I,2,FALSE) -> Growth
A19: Rothschild & Co Asset Management Europe SCS | B19: yes | C19: 16 | D19: 4894574 | E19: 1399867 | F19: 0.71 | G19: 4894574 | H19: 1399867 | I19: 03/31/2026 | M19: 14841382794 | N19: GARP | O19: 37.46 | P19: Paris | R19: France | S19: =IF(M19>100000000000, "100bn", IF(M19>50000000000, "50bn - 100bn",IF(M19>1000000000, "1bn - 50bn", IF(M19>500000000, "500mn - 1bn", "500mn")))) -> 1bn - 50bn | T19: =VLOOKUP(R19,Mapping!B:C,2,FALSE) -> EU | U19: =VLOOKUP(N19,Mapping!H:I,2,FALSE) -> Growth
A20: Cantillon Capital Management, LLC (U.S.) | B20: no | C20: 17 | D20: 4589621 | E20: -80157 | F20: 0.67 | G20: 4589621 | H20: -80157 | I20: 03/31/2026 | M20: 16051141096 | N20: GARP | O20: 16.613 | P20: New York | Q20: New York | R20: United States | S20: =IF(M20>100000000000, "100bn", IF(M20>50000000000, "50bn - 100bn",IF(M20>1000000000, "1bn - 50bn", IF(M20>500000000, "500mn - 1bn", "500mn")))) -> 1bn - 50bn | T20: =VLOOKUP(R20,Mapping!B:C,2,FALSE) -> US/CA | U20: =VLOOKUP(N20,Mapping!H:I,2,FALSE) -> Growth
A21: Hang Seng Investment Management, LTD | B21: yes | C21: 18 | D21: 4143897 | E21: -10134 | F21: 0.6 | G21: 9476 | H21: 640 | I21: 03/31/2026 | J21: 4134421 | K21: -10774 | L21: 04/30/2026 | M21: 33631465024 | N21: Index | O21: 19.867 | P21: Central | R21: Hong Kong SAR | S21: =IF(M21>100000000000, "100bn", IF(M21>50000000000, "50bn - 100bn",IF(M21>1000000000, "1bn - 50bn", IF(M21>500000000, "500mn - 1bn", "500mn")))) -> 1bn - 50bn | T21: =VLOOKUP(R21,Mapping!B:C,2,FALSE) -> HK | U21: =VLOOKUP(N21,Mapping!H:I,2,FALSE) -> Index
A22: China Asset Management Corporation, LTD | B22: yes | C22: 19 | D22: 3614450 | E22: -37004 | F22: 0.52 | J22: 3614450 | K22: -37004 | L22: 02/28/2026 | M22: 135091551532 | N22: Aggressive Growth | O22: 22.83 | P22: Beijing | R22: China (Mainland) | S22: =IF(M22>100000000000, "100bn", IF(M22>50000000000, "50bn - 100bn",IF(M22>1000000000, "1bn - 50bn", IF(M22>500000000, "500mn - 1bn", "500mn")))) -> 100bn | T22: =VLOOKUP(R22,Mapping!B:C,2,FALSE) -> CN | U22: =VLOOKUP(N22,Mapping!H:I,2,FALSE) -> Growth
A23: Dimensional Fund Advisors, L.P. (U.S.) | B23: yes | C23: 20 | D23: 3418881 | E23: 64818 | F23: 0.5 | G23: 2353134 | H23: -25232 | I23: 03/31/2026 | J23: 1065747 | K23: 90050 | L23: 05/14/2026 | M23: 707377951370 | N23: Value | O23: 11.636 | P23: Austin | Q23: Texas | R23: United States | S23: =IF(M23>100000000000, "100bn", IF(M23>50000000000, "50bn - 100bn",IF(M23>1000000000, "1bn - 50bn", IF(M23>500000000, "500mn - 1bn", "500mn")))) -> 100bn | T23: =VLOOKUP(R23,Mapping!B:C,2,FALSE) -> US/CA | U23: =VLOOKUP(N23,Mapping!H:I,2,FALSE) -> Value
A24: Geode Capital Management, LLC | B24: yes | C24: 21 | D24: 3334058 | E24: -6309 | F24: 0.48 | G24: 208476 | H24: 2054 | I24: 03/31/2026 | J24: 3125582 | K24: -8363 | L24: 04/30/2026 | M24: 1890862823441 | N24: Index | O24: 6.84 | P24: Boston | Q24: Massachusetts | R24: United States | S24: =IF(M24>100000000000, "100bn", IF(M24>50000000000, "50bn - 100bn",IF(M24>1000000000, "1bn - 50bn", IF(M24>500000000, "500mn - 1bn", "500mn")))) -> 100bn | T24: =VLOOKUP(R24,Mapping!B:C,2,FALSE) -> US/CA | U24: =VLOOKUP(N24,Mapping!H:I,2,FALSE) -> Index
A25: Robeco Institutional Asset Management BV | B25: yes | C25: 22 | D25: 3064434 | E25: 1302323 | F25: 0.44 | G25: 2611584 | H25: 1589575 | I25: 03/31/2026 | J25: 452850 | K25: -287252 | L25: 03/31/2026 | M25: 104891331129 | N25: Value | O25: 41.247 | P25: Rotterdam | R25: Netherlands | S25: =IF(M25>100000000000, "100bn", IF(M25>50000000000, "50bn - 100bn",IF(M25>1000000000, "1bn - 50bn", IF(M25>500000000, "500mn - 1bn", "500mn")))) -> 100bn | T25: =VLOOKUP(R25,Mapping!B:C,2,FALSE) -> EU | U25: =VLOOKUP(N25,Mapping!H:I,2,FALSE) -> Value
A26: J.P. Morgan Asset Management (Asia Pacific), LTD | B26: yes | C26: 23 | D26: 3052493 | E26: -254287 | F26: 0.44 | G26: 1170393 | H26: 0 | I26: 03/31/2026 | J26: 1882100 | K26: -254287 | L26: 03/31/2026 | M26: 36175085005 | N26: Growth | O26: 52.525 | P26: Central | R26: Hong Kong SAR | S26: =IF(M26>100000000000, "100bn", IF(M26>50000000000, "50bn - 100bn",IF(M26>1000000000, "1bn - 50bn", IF(M26>500000000, "500mn - 1bn", "500mn")))) -> 1bn - 50bn | T26: =VLOOKUP(R26,Mapping!B:C,2,FALSE) -> HK | U26: =VLOOKUP(N26,Mapping!H:I,2,FALSE) -> Growth
A27: First Sentier Investors (Hong Kong), LTD | B27: yes | C27: 24 | D27: 2939550 | E27: 5500 | F27: 0.43 | J27: 2939550 | K27: 5500 | L27: 03/31/2026 | M27: 10823127754 | N27: Growth | O27: 31.714 | P27: Central | R27: Hong Kong SAR | S27: =IF(M27>100000000000, "100bn", IF(M27>50000000000, "50bn - 100bn",IF(M27>1000000000, "1bn - 50bn", IF(M27>500000000, "500mn - 1bn", "500mn")))) -> 1bn - 50bn | T27: =VLOOKUP(R27,Mapping!B:C,2,FALSE) -> HK | U27: =VLOOKUP(N27,Mapping!H:I,2,FALSE) -> Growth
A28: Legal & General Investment Management, LTD | B28: yes | C28: 25 | D28: 2899010 | E28: -32391 | F28: 0.42 | G28: 2634410 | H28: -32291 | I28: 03/31/2026 | J28: 264600 | K28: -100 | L28: 05/13/2026 | M28: 516627888777 | N28: Index | O28: 9.411 | P28: London | R28: United Kingdom | S28: =IF(M28>100000000000, "100bn", IF(M28>50000000000, "50bn - 100bn",IF(M28>1000000000, "1bn - 50bn", IF(M28>500000000, "500mn - 1bn", "500mn")))) -> 100bn | T28: =VLOOKUP(R28,Mapping!B:C,2,FALSE) -> EU | U28: =VLOOKUP(N28,Mapping!H:I,2,FALSE) -> Index
A29: Arga Investment Management, L.P. | B29: yes | C29: 26 | D29: 2861617 | E29: -1082568 | F29: 0.42 | G29: 2861617 | H29: -1082568 | I29: 03/31/2026 | M29: 6544176802 | N29: Value | O29: 59.284 | P29: Stamford | Q29: Connecticut | R29: United States | S29: =IF(M29>100000000000, "100bn", IF(M29>50000000000, "50bn - 100bn",IF(M29>1000000000, "1bn - 50bn", IF(M29>500000000, "500mn - 1bn", "500mn")))) -> 1bn - 50bn | T29: =VLOOKUP(R29,Mapping!B:C,2,FALSE) -> US/CA | U29: =VLOOKUP(N29,Mapping!H:I,2,FALSE) -> Value
A30: Principal Global Investors, LLC | B30: yes | C30: 27 | D30: 2768761 | E30: -119877 | F30: 0.4 | G30: 0 | H30: -257077 | I30: 06/30/2025 | J30: 2768761 | K30: 137200 | L30: 05/09/2026 | M30: 206814740967 | N30: Growth | O30: 21.796 | P30: Des Moines | Q30: Iowa | R30: United States | S30: =IF(M30>100000000000, "100bn", IF(M30>50000000000, "50bn - 100bn",IF(M30>1000000000, "1bn - 50bn", IF(M30>500000000, "500mn - 1bn", "500mn")))) -> 100bn | T30: =VLOOKUP(R30,Mapping!B:C,2,FALSE) -> US/CA | U30: =VLOOKUP(N30,Mapping!H:I,2,FALSE) -> Growth
A31: Greenwoods Asset Management, LTD (China) | B31: no | C31: 28 | D31: 2604281 | E31: 2604281 | F31: 0.38 | G31: 2604281 | H31: 2604281 | I31: 03/31/2026 | M31: 4004956787 | N31: Alternative | O31: 73.415 | P31: Shanghai | R31: China (Mainland) | S31: =IF(M31>100000000000, "100bn", IF(M31>50000000000, "50bn - 100bn",IF(M31>1000000000, "1bn - 50bn", IF(M31>500000000, "500mn - 1bn", "500mn")))) -> 1bn - 50bn | T31: =VLOOKUP(R31,Mapping!B:C,2,FALSE) -> CN | U31: =VLOOKUP(N31,Mapping!H:I,2,FALSE) -> Alternative/Specialty
A32: UBS Asset Management Switzerland AG | B32: yes | C32: 29 | D32: 2591763 | E32: 970174 | F32: 0.38 | G32: 938824 | H32: 938824 | I32: 03/31/2026 | J32: 1652939 | K32: 31350 | L32: 05/12/2026 | M32: 333635647497 | N32: Value | O32: 32.088 | P32: Zurich | R32: Switzerland | S32: =IF(M32>100000000000, "100bn", IF(M32>50000000000, "50bn - 100bn",IF(M32>1000000000, "1bn - 50bn", IF(M32>500000000, "500mn - 1bn", "500mn")))) -> 100bn | T32: =VLOOKUP(R32,Mapping!B:C,2,FALSE) -> EU | U32: =VLOOKUP(N32,Mapping!H:I,2,FALSE) -> Value
A33: J.P. Morgan Investment Management, Inc. | B33: yes | C33: 30 | D33: 2457425 | E33: -3489 | F33: 0.36 | G33: 2269598 | H33: -2789 | I33: 03/31/2026 | J33: 187827 | K33: -700 | L33: 05/13/2026 | M33: 846468087667 | N33: Growth | O33: 29.371 | P33: New York | Q33: New York | R33: United States | S33: =IF(M33>100000000000, "100bn", IF(M33>50000000000, "50bn - 100bn",IF(M33>1000000000, "1bn - 50bn", IF(M33>500000000, "500mn - 1bn", "500mn")))) -> 100bn | T33: =VLOOKUP(R33,Mapping!B:C,2,FALSE) -> US/CA | U33: =VLOOKUP(N33,Mapping!H:I,2,FALSE) -> Growth
A34: BlackRock Asset Management North Asia, LTD (Hong Kong) | B34: yes | C34: 31 | D34: 2411675 | E34: 49026 | F34: 0.35 | G34: 268146 | H34: -18060 | I34: 03/31/2026 | J34: 2143529 | K34: 67086 | L34: 05/12/2026 | M34: 29688090454 | N34: Index | O34: 29.223 | P34: Central | R34: Hong Kong SAR | S34: =IF(M34>100000000000, "100bn", IF(M34>50000000000, "50bn - 100bn",IF(M34>1000000000, "1bn - 50bn", IF(M34>500000000, "500mn - 1bn", "500mn")))) -> 1bn - 50bn | T34: =VLOOKUP(R34,Mapping!B:C,2,FALSE) -> HK | U34: =VLOOKUP(N34,Mapping!H:I,2,FALSE) -> Index
A35: Wellington Management Company, LLP | B35: yes | C35: 32 | D35: 2369414 | E35: -5307857 | F35: 0.34 | G35: 1390436 | H35: -5307857 | I35: 03/31/2026 | J35: 978978 | K35: 0 | L35: 04/30/2026 | M35: 593050582169 | N35: Value | O35: 43.659 | P35: Boston | Q35: Massachusetts | R35: United States | S35: =IF(M35>100000000000, "100bn", IF(M35>50000000000, "50bn - 100bn",IF(M35>1000000000, "1bn - 50bn", IF(M35>500000000, "500mn - 1bn", "500mn")))) -> 100bn | T35: =VLOOKUP(R35,Mapping!B:C,2,FALSE) -> US/CA | U35: =VLOOKUP(N35,Mapping!H:I,2,FALSE) -> Value
A36: Brandes Investment Partners, L.P. | B36: yes | C36: 33 | D36: 2346562 | E36: 860162 | F36: 0.34 | G36: 867912 | H36: 838012 | I36: 03/31/2026 | J36: 1478650 | K36: 22150 | L36: 04/30/2026 | M36: 25276657622 | N36: Deep Value | O36: 43.178 | P36: La Jolla | Q36: California | R36: United States | S36: =IF(M36>100000000000, "100bn", IF(M36>50000000000, "50bn - 100bn",IF(M36>1000000000, "1bn - 50bn", IF(M36>500000000, "500mn - 1bn", "500mn")))) -> 1bn - 50bn | T36: =VLOOKUP(R36,Mapping!B:C,2,FALSE) -> US/CA | U36: =VLOOKUP(N36,Mapping!H:I,2,FALSE) -> Value
A37: Aspex Management (HK), LTD | B37: no | C37: 34 | D37: 2329290 | E37: 2329290 | F37: 0.34 | G37: 2329290 | H37: 2329290 | I37: 03/31/2026 | M37: 7574057446 | N37: Growth | O37: 118.608 | P37: Central | R37: Hong Kong SAR | S37: =IF(M37>100000000000, "100bn", IF(M37>50000000000, "50bn - 100bn",IF(M37>1000000000, "1bn - 50bn", IF(M37>500000000, "500mn - 1bn", "500mn")))) -> 1bn - 50bn | T37: =VLOOKUP(R37,Mapping!B:C,2,FALSE) -> HK | U37: =VLOOKUP(N37,Mapping!H:I,2,FALSE) -> Growth
A38: Black Creek Investment Management, Inc. | B38: no | C38: 35 | D38: 2314583 | E38: 1552 | F38: 0.34 | G38: 0 | H38: -2573 | I38: 09/30/2024 | J38: 2314583 | K38: 4125 | L38: 03/31/2026 | M38: 5724272211 | N38: Growth | O38: 33.193 | P38: Toronto | Q38: Ontario | R38: Canada | S38: =IF(M38>100000000000, "100bn", IF(M38>50000000000, "50bn - 100bn",IF(M38>1000000000, "1bn - 50bn", IF(M38>500000000, "500mn - 1bn", "500mn")))) -> 1bn - 50bn | T38: =VLOOKUP(R38,Mapping!B:C,2,FALSE) -> US/CA | U38: =VLOOKUP(N38,Mapping!H:I,2,FALSE) -> Growth
A39: Vontobel Asset Management AG (Switzerland) | B39: yes | C39: 36 | D39: 2266973 | E39: 138350 | F39: 0.33 | G39: 1383213 | H39: 117615 | I39: 03/31/2026 | J39: 883760 | K39: 20735 | L39: 01/31/2026 | M39: 31983266955 | N39: Growth | O39: 34.725 | P39: Zürich | R39: Switzerland | S39: =IF(M39>100000000000, "100bn", IF(M39>50000000000, "50bn - 100bn",IF(M39>1000000000, "1bn - 50bn", IF(M39>500000000, "500mn - 1bn", "500mn")))) -> 1bn - 50bn | T39: =VLOOKUP(R39,Mapping!B:C,2,FALSE) -> EU | U39: =VLOOKUP(N39,Mapping!H:I,2,FALSE) -> Growth
A40: Temasek Holdings Pte., LTD | B40: no | C40: 37 | D40: 2239671 | E40: 0 | F40: 0.32 | G40: 2239671 | H40: 0 | I40: 03/31/2026 | M40: 151489365884 | N40: Value | O40: 11.68 | P40: Singapore | R40: Singapore | S40: =IF(M40>100000000000, "100bn", IF(M40>50000000000, "50bn - 100bn",IF(M40>1000000000, "1bn - 50bn", IF(M40>500000000, "500mn - 1bn", "500mn")))) -> 100bn | T40: =VLOOKUP(R40,Mapping!B:C,2,FALSE) -> SG | U40: =VLOOKUP(N40,Mapping!H:I,2,FALSE) -> Value
A41: Federated Hermes, LTD (HIML) | B41: yes | C41: 38 | D41: 2206490 | E41: 243400 | F41: 0.32 | G41: 1777374 | H41: 165450 | I41: 03/31/2026 | J41: 429116 | K41: 77950 | L41: 02/28/2026 | M41: 16922880638 | N41: GARP | O41: 48.423 | P41: London | R41: United Kingdom | S41: =IF(M41>100000000000, "100bn", IF(M41>50000000000, "50bn - 100bn",IF(M41>1000000000, "1bn - 50bn", IF(M41>500000000, "500mn - 1bn", "500mn")))) -> 1bn - 50bn | T41: =VLOOKUP(R41,Mapping!B:C,2,FALSE) -> EU | U41: =VLOOKUP(N41,Mapping!H:I,2,FALSE) -> Growth
A42: DWS Investment GmbH | B42: yes | C42: 39 | D42: 2030639 | E42: -4000 | F42: 0.29 | G42: 0 | H42: -4000 | I42: 03/31/2026 | J42: 2030639 | K42: 0 | L42: 04/30/2026 | M42: 186603245107 | N42: Value | O42: 30.764 | P42: Frankfurt am Main | R42: Germany | S42: =IF(M42>100000000000, "100bn", IF(M42>50000000000, "50bn - 100bn",IF(M42>1000000000, "1bn - 50bn", IF(M42>500000000, "500mn - 1bn", "500mn")))) -> 100bn | T42: =VLOOKUP(R42,Mapping!B:C,2,FALSE) -> EU | U42: =VLOOKUP(N42,Mapping!H:I,2,FALSE) -> Value
A43: Russell Investment Management, LLC | B43: no | C43: 40 | D43: 1917605 | E43: -124965 | F43: 0.28 | G43: 1917605 | H43: -124965 | I43: 03/31/2026 | M43: 95903858678 | N43: Externally Managed | O43: 27.454 | P43: Seattle | Q43: Washington | R43: United States | S43: =IF(M43>100000000000, "100bn", IF(M43>50000000000, "50bn - 100bn",IF(M43>1000000000, "1bn - 50bn", IF(M43>500000000, "500mn - 1bn", "500mn")))) -> 50bn - 100bn | T43: =VLOOKUP(R43,Mapping!B:C,2,FALSE) -> US/CA | U43: =VLOOKUP(N43,Mapping!H:I,2,FALSE) -> Others
A44: HSBC Global Asset Management (UK), LTD | B44: yes | C44: 41 | D44: 1729270 | E44: 90163 | F44: 0.25 | G44: 130223 | H44: 65312 | I44: 03/31/2026 | J44: 1599047 | K44: 24851 | L44: 05/13/2026 | M44: 233905177705 | N44: Growth | O44: 31.429 | P44: London | R44: United Kingdom | S44: =IF(M44>100000000000, "100bn", IF(M44>50000000000, "50bn - 100bn",IF(M44>1000000000, "1bn - 50bn", IF(M44>500000000, "500mn - 1bn", "500mn")))) -> 100bn | T44: =VLOOKUP(R44,Mapping!B:C,2,FALSE) -> EU | U44: =VLOOKUP(N44,Mapping!H:I,2,FALSE) -> Growth
A45: J.P. Morgan Asset Management (UK), LTD | B45: yes | C45: 42 | D45: 1639665 | E45: 35835 | F45: 0.24 | G45: 714299 | H45: 27414 | I45: 03/31/2026 | J45: 925366 | K45: 8421 | L45: 03/31/2026 | M45: 165171115115 | N45: Growth | O45: 37.677 | P45: London | R45: United Kingdom | S45: =IF(M45>100000000000, "100bn", IF(M45>50000000000, "50bn - 100bn",IF(M45>1000000000, "1bn - 50bn", IF(M45>500000000, "500mn - 1bn", "500mn")))) -> 100bn | T45: =VLOOKUP(R45,Mapping!B:C,2,FALSE) -> EU | U45: =VLOOKUP(N45,Mapping!H:I,2,FALSE) -> Growth
A46: BlackRock Advisors, LLC | B46: yes | C46: 43 | D46: 1606814 | E46: 47198 | F46: 0.23 | G46: 91151 | H46: 43548 | I46: 03/31/2026 | J46: 1515663 | K46: 3650 | L46: 03/31/2026 | M46: 551759284573 | N46: Value | O46: 26.926 | P46: New York | Q46: New York | R46: United States | S46: =IF(M46>100000000000, "100bn", IF(M46>50000000000, "50bn - 100bn",IF(M46>1000000000, "1bn - 50bn", IF(M46>500000000, "500mn - 1bn", "500mn")))) -> 100bn | T46: =VLOOKUP(R46,Mapping!B:C,2,FALSE) -> US/CA | U46: =VLOOKUP(N46,Mapping!H:I,2,FALSE) -> Value
A47: State Street Global Advisors, LTD | B47: yes | C47: 44 | D47: 1590204 | E47: 2900 | F47: 0.23 | J47: 1590204 | K47: 2900 | L47: 04/30/2026 | M47: 198437858364 | N47: Index | O47: 17.785 | P47: London | R47: United Kingdom | S47: =IF(M47>100000000000, "100bn", IF(M47>50000000000, "50bn - 100bn",IF(M47>1000000000, "1bn - 50bn", IF(M47>500000000, "500mn - 1bn", "500mn")))) -> 100bn | T47: =VLOOKUP(R47,Mapping!B:C,2,FALSE) -> EU | U47: =VLOOKUP(N47,Mapping!H:I,2,FALSE) -> Index
A48: Capital Research Global Investors (U.S.) | B48: no | C48: 45 | D48: 1589921 | E48: 1580121 | F48: 0.23 | G48: 1580121 | H48: 1580121 | I48: 03/31/2026 | J48: 9800 | K48: 0 | L48: 03/31/2026 | M48: 718227362777 | N48: GARP | O48: 42.718 | P48: Los Angeles | Q48: California | R48: United States | S48: =IF(M48>100000000000, "100bn", IF(M48>50000000000, "50bn - 100bn",IF(M48>1000000000, "1bn - 50bn", IF(M48>500000000, "500mn - 1bn", "500mn")))) -> 100bn | T48: =VLOOKUP(R48,Mapping!B:C,2,FALSE) -> US/CA | U48: =VLOOKUP(N48,Mapping!H:I,2,FALSE) -> Growth
A49: D.E. Shaw & Company, L.P. | B49: no | C49: 46 | D49: 1542512 | E49: 692608 | F49: 0.22 | G49: 1542512 | H49: 692608 | I49: 03/31/2026 | M49: 127071829111 | N49: Alternative | O49: 127.009 | P49: New York | Q49: New York | R49: United States | S49: =IF(M49>100000000000, "100bn", IF(M49>50000000000, "50bn - 100bn",IF(M49>1000000000, "1bn - 50bn", IF(M49>500000000, "500mn - 1bn", "500mn")))) -> 100bn | T49: =VLOOKUP(R49,Mapping!B:C,2,FALSE) -> US/CA | U49: =VLOOKUP(N49,Mapping!H:I,2,FALSE) -> Alternative/Specialty
A50: Marshall Wace North America, L.P. | B50: no | C50: 47 | D50: 1533164 | E50: -1951888 | F50: 0.22 | G50: 1533164 | H50: -1951888 | I50: 03/31/2026 | M50: 93255633648 | N50: Alternative | O50: 127.124 | P50: New York | Q50: New York | R50: United States | S50: =IF(M50>100000000000, "100bn", IF(M50>50000000000, "50bn - 100bn",IF(M50>1000000000, "1bn - 50bn", IF(M50>500000000, "500mn - 1bn", "500mn")))) -> 50bn - 100bn | T50: =VLOOKUP(R50,Mapping!B:C,2,FALSE) -> US/CA | U50: =VLOOKUP(N50,Mapping!H:I,2,FALSE) -> Alternative/Specialty
A51: Amundi Asset Management S.A.S. | B51: yes | C51: 48 | D51: 1529268 | E51: 20427 | F51: 0.22 | G51: 308690 | H51: -5173 | I51: 12/31/2025 | J51: 1220578 | K51: 25600 | L51: 05/12/2026 | M51: 512485377814 | N51: Value | O51: 30.276 | P51: Paris | R51: France | S51: =IF(M51>100000000000, "100bn", IF(M51>50000000000, "50bn - 100bn",IF(M51>1000000000, "1bn - 50bn", IF(M51>500000000, "500mn - 1bn", "500mn")))) -> 100bn | T51: =VLOOKUP(R51,Mapping!B:C,2,FALSE) -> EU | U51: =VLOOKUP(N51,Mapping!H:I,2,FALSE) -> Value
A52: FIAM, LLC | B52: yes | C52: 49 | D52: 1516957 | E52: -748830 | F52: 0.22 | G52: 1329517 | H52: -231649 | I52: 03/31/2026 | J52: 187440 | K52: -517181 | L52: 03/31/2026 | M52: 223746859411 | N52: Growth | O52: 38.744 | P52: Smithfield | Q52: Rhode Island | R52: United States | S52: =IF(M52>100000000000, "100bn", IF(M52>50000000000, "50bn - 100bn",IF(M52>1000000000, "1bn - 50bn", IF(M52>500000000, "500mn - 1bn", "500mn")))) -> 100bn | T52: =VLOOKUP(R52,Mapping!B:C,2,FALSE) -> US/CA | U52: =VLOOKUP(N52,Mapping!H:I,2,FALSE) -> Growth
A53: APG Asset Management N.V. | B53: yes | C53: 50 | D53: 1435380 | E53: -36560 | F53: 0.21 | G53: 0 | H53: -246400 | I53: 09/30/2025 | J53: 1435380 | K53: 209840 | L53: 12/31/2025 | M53: 108431834004 | N53: Specialty | O53: 31.807 | P53: Amsterdam | R53: Netherlands | S53: =IF(M53>100000000000, "100bn", IF(M53>50000000000, "50bn - 100bn",IF(M53>1000000000, "1bn - 50bn", IF(M53>500000000, "500mn - 1bn", "500mn")))) -> 100bn | T53: =VLOOKUP(R53,Mapping!B:C,2,FALSE) -> EU | U53: =VLOOKUP(N53,Mapping!H:I,2,FALSE) -> Alternative/Specialty
A54: Goldman Sachs & Co., LLC | B54: no | C54: 51 | D54: 1390899 | E54: 400182 | F54: 0.2 | G54: 1390899 | H54: 400182 | I54: 03/31/2026 | M54: 349088389004 | N54: Broker | O54: 68.297 | P54: New York | Q54: New York | R54: United States | S54: =IF(M54>100000000000, "100bn", IF(M54>50000000000, "50bn - 100bn",IF(M54>1000000000, "1bn - 50bn", IF(M54>500000000, "500mn - 1bn", "500mn")))) -> 100bn | T54: =VLOOKUP(R54,Mapping!B:C,2,FALSE) -> US/CA | U54: =VLOOKUP(N54,Mapping!H:I,2,FALSE) -> Broker
A55: Schroder Investment Management, LTD | B55: yes | C55: 52 | D55: 1355998 | E55: -2879962 | F55: 0.2 | G55: 87 | H55: 0 | I55: 03/31/2026 | J55: 1355911 | K55: -2879962 | L55: 03/31/2026 | M55: 204649980773 | N55: GARP | O55: 35.768 | P55: London | R55: United Kingdom | S55: =IF(M55>100000000000, "100bn", IF(M55>50000000000, "50bn - 100bn",IF(M55>1000000000, "1bn - 50bn", IF(M55>500000000, "500mn - 1bn", "500mn")))) -> 100bn | T55: =VLOOKUP(R55,Mapping!B:C,2,FALSE) -> EU | U55: =VLOOKUP(N55,Mapping!H:I,2,FALSE) -> Growth
A56: GF Fund Management Company, LTD | B56: yes | C56: 53 | D56: 1342531 | E56: 347400 | F56: 0.19 | G56: 2500 | H56: 2500 | I56: 03/31/2026 | J56: 1340031 | K56: 344900 | L56: 12/31/2025 | M56: 74732230941 | N56: Growth | O56: 45.866 | P56: Guangzhou | R56: China (Mainland) | S56: =IF(M56>100000000000, "100bn", IF(M56>50000000000, "50bn - 100bn",IF(M56>1000000000, "1bn - 50bn", IF(M56>500000000, "500mn - 1bn", "500mn")))) -> 50bn - 100bn | T56: =VLOOKUP(R56,Mapping!B:C,2,FALSE) -> CN | U56: =VLOOKUP(N56,Mapping!H:I,2,FALSE) -> Growth
A57: State Street Investment Management | B57: yes | C57: 54 | D57: 1335357 | E57: -6400 | F57: 0.19 | G57: 14425 | H57: -5500 | I57: 03/31/2026 | J57: 1320932 | K57: -900 | L57: 05/14/2026 | M57: 3127653596080 | N57: Index | O57: 4.987 | P57: Boston | Q57: Massachusetts | R57: United States | S57: =IF(M57>100000000000, "100bn", IF(M57>50000000000, "50bn - 100bn",IF(M57>1000000000, "1bn - 50bn", IF(M57>500000000, "500mn - 1bn", "500mn")))) -> 100bn | T57: =VLOOKUP(R57,Mapping!B:C,2,FALSE) -> US/CA | U57: =VLOOKUP(N57,Mapping!H:I,2,FALSE) -> Index
A58: Dacheng Fund Management Company, LTD | B58: yes | C58: 55 | D58: 1289750 | E58: 544100 | F58: 0.19 | J58: 1289750 | K58: 544100 | L58: 12/31/2025 | M58: 20050944495 | N58: Growth | O58: 43.026 | P58: Shenzhen | R58: China (Mainland) | S58: =IF(M58>100000000000, "100bn", IF(M58>50000000000, "50bn - 100bn",IF(M58>1000000000, "1bn - 50bn", IF(M58>500000000, "500mn - 1bn", "500mn")))) -> 1bn - 50bn | T58: =VLOOKUP(R58,Mapping!B:C,2,FALSE) -> CN | U58: =VLOOKUP(N58,Mapping!H:I,2,FALSE) -> Growth
A59: Point72 Asset Management, L.P. | B59: yes | C59: 56 | D59: 1088184 | E59: 1021418 | F59: 0.16 | G59: 1088184 | H59: 1021418 | I59: 03/31/2026 | M59: 57864544749 | N59: Alternative | O59: 173.037 | P59: Stamford | Q59: Connecticut | R59: United States | S59: =IF(M59>100000000000, "100bn", IF(M59>50000000000, "50bn - 100bn",IF(M59>1000000000, "1bn - 50bn", IF(M59>500000000, "500mn - 1bn", "500mn")))) -> 50bn - 100bn | T59: =VLOOKUP(R59,Mapping!B:C,2,FALSE) -> US/CA | U59: =VLOOKUP(N59,Mapping!H:I,2,FALSE) -> Alternative/Specialty
A60: MFS International Singapore Pte., LTD | B60: no | C60: 57 | D60: 1050500 | E60: -28547 | F60: 0.15 | G60: 0 | H60: -7347 | I60: 03/31/2025 | J60: 1050500 | K60: -21200 | L60: 03/31/2026 | M60: 9322869263 | N60: Growth | O60: 47.495 | P60: Singapore | R60: Singapore | S60: =IF(M60>100000000000, "100bn", IF(M60>50000000000, "50bn - 100bn",IF(M60>1000000000, "1bn - 50bn", IF(M60>500000000, "500mn - 1bn", "500mn")))) -> 1bn - 50bn | T60: =VLOOKUP(R60,Mapping!B:C,2,FALSE) -> SG | U60: =VLOOKUP(N60,Mapping!H:I,2,FALSE) -> Growth
A61: Mirae Asset Global Investments (Hong Kong), LTD | B61: yes | C61: 58 | D61: 1025957 | E61: -28412 | F61: 0.15 | G61: 14322 | H61: -51964 | I61: 03/31/2026 | J61: 1011635 | K61: 23552 | L61: 05/14/2026 | M61: 6771517296 | N61: Aggressive Growth | O61: 70.616 | P61: Causeway Bay | R61: Hong Kong SAR | S61: =IF(M61>100000000000, "100bn", IF(M61>50000000000, "50bn - 100bn",IF(M61>1000000000, "1bn - 50bn", IF(M61>500000000, "500mn - 1bn", "500mn")))) -> 1bn - 50bn | T61: =VLOOKUP(R61,Mapping!B:C,2,FALSE) -> HK | U61: =VLOOKUP(N61,Mapping!H:I,2,FALSE) -> Growth
A62: Tianhong Asset Management Company, LTD | B62: yes | C62: 59 | D62: 1020700 | E62: 7600 | F62: 0.15 | J62: 1020700 | K62: 7600 | L62: 12/31/2025 | M62: 22891925601 | N62: Aggressive Growth | O62: 30.865 | P62: Tianjin | R62: China (Mainland) | S62: =IF(M62>100000000000, "100bn", IF(M62>50000000000, "50bn - 100bn",IF(M62>1000000000, "1bn - 50bn", IF(M62>500000000, "500mn - 1bn", "500mn")))) -> 1bn - 50bn | T62: =VLOOKUP(R62,Mapping!B:C,2,FALSE) -> CN | U62: =VLOOKUP(N62,Mapping!H:I,2,FALSE) -> Growth
A63: Fidelity Investments Canada ULC | B63: yes | C63: 60 | D63: 1016655 | E63: -912378 | F63: 0.15 | G63: 0 | H63: -881892 | I63: 09/30/2025 | J63: 1016655 | K63: -30486 | L63: 02/28/2026 | M63: 92161044648 | N63: Growth | O63: 55.459 | P63: Toronto | Q63: Ontario | R63: Canada | S63: =IF(M63>100000000000, "100bn", IF(M63>50000000000, "50bn - 100bn",IF(M63>1000000000, "1bn - 50bn", IF(M63>500000000, "500mn - 1bn", "500mn")))) -> 50bn - 100bn | T63: =VLOOKUP(R63,Mapping!B:C,2,FALSE) -> US/CA | U63: =VLOOKUP(N63,Mapping!H:I,2,FALSE) -> Growth
A64: Goldman Sachs Asset Management International | B64: yes | C64: 61 | D64: 1015403 | E64: 1500 | F64: 0.15 | G64: 105954 | H64: 0 | I64: 03/31/2026 | J64: 909449 | K64: 1500 | L64: 05/14/2026 | M64: 32488066366 | N64: Growth | O64: 78.98 | P64: London | R64: United Kingdom | S64: =IF(M64>100000000000, "100bn", IF(M64>50000000000, "50bn - 100bn",IF(M64>1000000000, "1bn - 50bn", IF(M64>500000000, "500mn - 1bn", "500mn")))) -> 1bn - 50bn | T64: =VLOOKUP(R64,Mapping!B:C,2,FALSE) -> EU | U64: =VLOOKUP(N64,Mapping!H:I,2,FALSE) -> Growth
A65: ClearBridge Investment Management, LTD | B65: yes | C65: 62 | D65: 1006385 | E65: -97325 | F65: 0.15 | G65: 1006385 | H65: -97325 | I65: 03/31/2026 | M65: 5951610575 | N65: Growth | O65: 45.033 | P65: Edinburgh | R65: United Kingdom | S65: =IF(M65>100000000000, "100bn", IF(M65>50000000000, "50bn - 100bn",IF(M65>1000000000, "1bn - 50bn", IF(M65>500000000, "500mn - 1bn", "500mn")))) -> 1bn - 50bn | T65: =VLOOKUP(R65,Mapping!B:C,2,FALSE) -> EU | U65: =VLOOKUP(N65,Mapping!H:I,2,FALSE) -> Growth
A66: Northern Trust Global Investments, LTD | B66: yes | C66: 63 | D66: 1000238 | E66: 1400 | F66: 0.15 | J66: 1000238 | K66: 1400 | L66: 04/30/2026 | M66: 119980886873 | N66: Index | O66: 20.117 | P66: London | R66: United Kingdom | S66: =IF(M66>100000000000, "100bn", IF(M66>50000000000, "50bn - 100bn",IF(M66>1000000000, "1bn - 50bn", IF(M66>500000000, "500mn - 1bn", "500mn")))) -> 100bn | T66: =VLOOKUP(R66,Mapping!B:C,2,FALSE) -> EU | U66: =VLOOKUP(N66,Mapping!H:I,2,FALSE) -> Index
A67: Polar Capital, LLP | B67: yes | C67: 64 | D67: 991406 | E67: -7623 | F67: 0.14 | G67: 991406 | H67: -7623 | I67: 03/31/2026 | M67: 37954600290 | N67: Growth | O67: 71.317 | P67: London | R67: United Kingdom | S67: =IF(M67>100000000000, "100bn", IF(M67>50000000000, "50bn - 100bn",IF(M67>1000000000, "1bn - 50bn", IF(M67>500000000, "500mn - 1bn", "500mn")))) -> 1bn - 50bn | T67: =VLOOKUP(R67,Mapping!B:C,2,FALSE) -> EU | U67: =VLOOKUP(N67,Mapping!H:I,2,FALSE) -> Growth
A68: Intermede Investment Partners, LTD | B68: no | C68: 65 | D68: 979652 | E68: -85501 | F68: 0.14 | G68: 979652 | H68: -85501 | I68: 03/31/2026 | M68: 2323863785 | N68: Value | O68: 58.254 | P68: London | R68: United Kingdom | S68: =IF(M68>100000000000, "100bn", IF(M68>50000000000, "50bn - 100bn",IF(M68>1000000000, "1bn - 50bn", IF(M68>500000000, "500mn - 1bn", "500mn")))) -> 1bn - 50bn | T68: =VLOOKUP(R68,Mapping!B:C,2,FALSE) -> EU | U68: =VLOOKUP(N68,Mapping!H:I,2,FALSE) -> Value
A69: Loomis Sayles & Company, L.P. | B69: yes | C69: 66 | D69: 976211 | E69: 102424 | F69: 0.14 | G69: 976211 | H69: 102424 | I69: 03/31/2026 | M69: 76831751480 | N69: Aggressive Growth | O69: 11.957 | P69: Boston | Q69: Massachusetts | R69: United States | S69: =IF(M69>100000000000, "100bn", IF(M69>50000000000, "50bn - 100bn",IF(M69>1000000000, "1bn - 50bn", IF(M69>500000000, "500mn - 1bn", "500mn")))) -> 50bn - 100bn | T69: =VLOOKUP(R69,Mapping!B:C,2,FALSE) -> US/CA | U69: =VLOOKUP(N69,Mapping!H:I,2,FALSE) -> Growth
A70: Morgan Stanley & Company, LLC | B70: no | C70: 67 | D70: 970349 | E70: -657849 | F70: 0.14 | G70: 970349 | H70: -657849 | I70: 03/31/2026 | M70: 1040234684579 | N70: Broker | O70: 23.235 | P70: New York | Q70: New York | R70: United States | S70: =IF(M70>100000000000, "100bn", IF(M70>50000000000, "50bn - 100bn",IF(M70>1000000000, "1bn - 50bn", IF(M70>500000000, "500mn - 1bn", "500mn")))) -> 100bn | T70: =VLOOKUP(R70,Mapping!B:C,2,FALSE) -> US/CA | U70: =VLOOKUP(N70,Mapping!H:I,2,FALSE) -> Broker
A71: Public Mutual Bhd. | B71: yes | C71: 68 | D71: 955315 | E71: 102764 | F71: 0.14 | J71: 955315 | K71: 102764 | L71: 01/31/2026 | M71: 16343943823 | N71: Growth | O71: 34.088 | P71: Kuala Lumpur | R71: Malaysia | S71: =IF(M71>100000000000, "100bn", IF(M71>50000000000, "50bn - 100bn",IF(M71>1000000000, "1bn - 50bn", IF(M71>500000000, "500mn - 1bn", "500mn")))) -> 1bn - 50bn | T71: =VLOOKUP(R71,Mapping!B:C,2,FALSE) -> Asia | U71: =VLOOKUP(N71,Mapping!H:I,2,FALSE) -> Growth
A72: British Columbia Investment Management Corporation | B72: yes | C72: 69 | D72: 950938 | E72: -435429 | F72: 0.14 | J72: 950938 | K72: -435429 | L72: 03/31/2025 | M72: 25098830831 | N72: Growth | O72: 33.056 | P72: Victoria | Q72: British Columbia | R72: Canada | S72: =IF(M72>100000000000, "100bn", IF(M72>50000000000, "50bn - 100bn",IF(M72>1000000000, "1bn - 50bn", IF(M72>500000000, "500mn - 1bn", "500mn")))) -> 1bn - 50bn | T72: =VLOOKUP(R72,Mapping!B:C,2,FALSE) -> US/CA | U72: =VLOOKUP(N72,Mapping!H:I,2,FALSE) -> Growth
A73: Coronation Asset Management Pty., LTD | B73: yes | C73: 70 | D73: 945623 | E73: 158544 | F73: 0.14 | G73: 71644 | H73: 71644 | I73: 10/31/2025 | J73: 873979 | K73: 86900 | L73: 03/31/2026 | M73: 15959905769 | N73: GARP | O73: 29.622 | P73: Cape Town | R73: South Africa | S73: =IF(M73>100000000000, "100bn", IF(M73>50000000000, "50bn - 100bn",IF(M73>1000000000, "1bn - 50bn", IF(M73>500000000, "500mn - 1bn", "500mn")))) -> 1bn - 50bn | T73: =VLOOKUP(R73,Mapping!B:C,2,FALSE) -> Africa | U73: =VLOOKUP(N73,Mapping!H:I,2,FALSE) -> Growth
A74: Platinum Asset Management | B74: no | C74: 71 | D74: 942582 | E74: -144331 | F74: 0.14 | G74: 379718 | H74: -64000 | I74: 03/31/2026 | J74: 562864 | K74: -80331 | L74: 12/31/2025 | M74: 1531148502 | N74: GARP | O74: 81.244 | P74: Sydney | Q74: New South Wales | R74: Australia | S74: =IF(M74>100000000000, "100bn", IF(M74>50000000000, "50bn - 100bn",IF(M74>1000000000, "1bn - 50bn", IF(M74>500000000, "500mn - 1bn", "500mn")))) -> 1bn - 50bn | T74: =VLOOKUP(R74,Mapping!B:C,2,FALSE) -> Oceania | U74: =VLOOKUP(N74,Mapping!H:I,2,FALSE) -> Growth
A75: UBS Financial Services, Inc. (Investment Advisor) | B75: yes | C75: 72 | D75: 889177 | E75: -1205042 | F75: 0.13 | G75: 889177 | H75: -1205042 | I75: 03/31/2026 | M75: 561788085142 | N75: GARP | O75: 40.091 | P75: Weehawken | Q75: New Jersey | R75: United States | S75: =IF(M75>100000000000, "100bn", IF(M75>50000000000, "50bn - 100bn",IF(M75>1000000000, "1bn - 50bn", IF(M75>500000000, "500mn - 1bn", "500mn")))) -> 100bn | T75: =VLOOKUP(R75,Mapping!B:C,2,FALSE) -> US/CA | U75: =VLOOKUP(N75,Mapping!H:I,2,FALSE) -> Growth
A76: Fidelity Management & Research Company, LLC | B76: yes | C76: 73 | D76: 850617 | E76: -1047648 | F76: 0.12 | G76: 705854 | H76: -819268 | I76: 03/31/2026 | J76: 144763 | K76: -228380 | L76: 03/31/2026 | M76: 1923778537161 | N76: Growth | O76: 24.363 | P76: Boston | Q76: Massachusetts | R76: United States | S76: =IF(M76>100000000000, "100bn", IF(M76>50000000000, "50bn - 100bn",IF(M76>1000000000, "1bn - 50bn", IF(M76>500000000, "500mn - 1bn", "500mn")))) -> 100bn | T76: =VLOOKUP(R76,Mapping!B:C,2,FALSE) -> US/CA | U76: =VLOOKUP(N76,Mapping!H:I,2,FALSE) -> Growth
A77: Northern Trust Investments, Inc. | B77: yes | C77: 74 | D77: 801306 | E77: -8968 | F77: 0.12 | G77: 645033 | H77: -8818 | I77: 03/31/2026 | J77: 156273 | K77: -150 | L77: 05/14/2026 | M77: 702140847245 | N77: Index | O77: 6.8 | P77: Chicago | Q77: Illinois | R77: United States | S77: =IF(M77>100000000000, "100bn", IF(M77>50000000000, "50bn - 100bn",IF(M77>1000000000, "1bn - 50bn", IF(M77>500000000, "500mn - 1bn", "500mn")))) -> 100bn | T77: =VLOOKUP(R77,Mapping!B:C,2,FALSE) -> US/CA | U77: =VLOOKUP(N77,Mapping!H:I,2,FALSE) -> Index
A78: Nomura Investment Management Business Trust | B78: yes | C78: 75 | D78: 788403 | E78: -81734 | F78: 0.11 | G78: 788403 | H78: -81734 | I78: 03/31/2026 | M78: 60127247228 | N78: Growth | O78: 46.585 | P78: Philadelphia | Q78: Pennsylvania | R78: United States | S78: =IF(M78>100000000000, "100bn", IF(M78>50000000000, "50bn - 100bn",IF(M78>1000000000, "1bn - 50bn", IF(M78>500000000, "500mn - 1bn", "500mn")))) -> 50bn - 100bn | T78: =VLOOKUP(R78,Mapping!B:C,2,FALSE) -> US/CA | U78: =VLOOKUP(N78,Mapping!H:I,2,FALSE) -> Growth
A79: Goldman Sachs Asset Management, L.P. (U.S.) | B79: yes | C79: 76 | D79: 775205 | E79: 9222 | F79: 0.11 | G79: 127326 | H79: 8363 | I79: 03/31/2026 | J79: 647879 | K79: 859 | L79: 05/14/2026 | M79: 473293107964 | N79: GARP | O79: 27.668 | P79: New York | Q79: New York | R79: United States | S79: =IF(M79>100000000000, "100bn", IF(M79>50000000000, "50bn - 100bn",IF(M79>1000000000, "1bn - 50bn", IF(M79>500000000, "500mn - 1bn", "500mn")))) -> 100bn | T79: =VLOOKUP(R79,Mapping!B:C,2,FALSE) -> US/CA | U79: =VLOOKUP(N79,Mapping!H:I,2,FALSE) -> Growth
A80: MainFirst Affiliated Fund Managers (Deutschland) GmbH | B80: yes | C80: 77 | D80: 775000 | E80: 0 | F80: 0.11 | J80: 775000 | K80: 0 | L80: 03/31/2026 | M80: 1351069644 | N80: Growth | O80: 62.815 | P80: Frankfurt am Main | R80: Germany | S80: =IF(M80>100000000000, "100bn", IF(M80>50000000000, "50bn - 100bn",IF(M80>1000000000, "1bn - 50bn", IF(M80>500000000, "500mn - 1bn", "500mn")))) -> 1bn - 50bn | T80: =VLOOKUP(R80,Mapping!B:C,2,FALSE) -> EU | U80: =VLOOKUP(N80,Mapping!H:I,2,FALSE) -> Growth
A81: Charles Schwab Investment Management, Inc. | B81: yes | C81: 78 | D81: 771282 | E81: 0 | F81: 0.11 | J81: 771282 | K81: 0 | L81: 05/14/2026 | M81: 787363814294 | N81: Index | O81: 12.032 | P81: San Francisco | Q81: California | R81: United States | S81: =IF(M81>100000000000, "100bn", IF(M81>50000000000, "50bn - 100bn",IF(M81>1000000000, "1bn - 50bn", IF(M81>500000000, "500mn - 1bn", "500mn")))) -> 100bn | T81: =VLOOKUP(R81,Mapping!B:C,2,FALSE) -> US/CA | U81: =VLOOKUP(N81,Mapping!H:I,2,FALSE) -> Index
A82: CIBC Private Wealth Advisors, Inc. | B82: yes | C82: 79 | D82: 760366 | E82: -246639 | F82: 0.11 | G82: 760366 | H82: 34361 | I82: 09/30/2025 | J82: 0 | K82: -281000 | L82: 01/31/2026 | M82: 77102606553 | N82: Growth | O82: 47.453 | P82: Chicago | Q82: Illinois | R82: United States | S82: =IF(M82>100000000000, "100bn", IF(M82>50000000000, "50bn - 100bn",IF(M82>1000000000, "1bn - 50bn", IF(M82>500000000, "500mn - 1bn", "500mn")))) -> 50bn - 100bn | T82: =VLOOKUP(R82,Mapping!B:C,2,FALSE) -> US/CA | U82: =VLOOKUP(N82,Mapping!H:I,2,FALSE) -> Growth
A83: SRS Investment Management, LLC | B83: no | C83: 80 | D83: 757817 | E83: 1632 | F83: 0.11 | G83: 757817 | H83: 1632 | I83: 03/31/2026 | M83: 9466014804 | N83: Alternative | O83: 39.9 | P83: New York | Q83: New York | R83: United States | S83: =IF(M83>100000000000, "100bn", IF(M83>50000000000, "50bn - 100bn",IF(M83>1000000000, "1bn - 50bn", IF(M83>500000000, "500mn - 1bn", "500mn")))) -> 1bn - 50bn | T83: =VLOOKUP(R83,Mapping!B:C,2,FALSE) -> US/CA | U83: =VLOOKUP(N83,Mapping!H:I,2,FALSE) -> Alternative/Specialty
A84: Lazard Asset Management, LLC (U.S.) | B84: yes | C84: 81 | D84: 731119 | E84: -111824 | F84: 0.11 | G84: 707519 | H84: -112424 | I84: 03/31/2026 | J84: 23600 | K84: 600 | L84: 05/09/2026 | M84: 80222089946 | N84: Value | O84: 49.368 | P84: New York | Q84: New York | R84: United States | S84: =IF(M84>100000000000, "100bn", IF(M84>50000000000, "50bn - 100bn",IF(M84>1000000000, "1bn - 50bn", IF(M84>500000000, "500mn - 1bn", "500mn")))) -> 50bn - 100bn | T84: =VLOOKUP(R84,Mapping!B:C,2,FALSE) -> US/CA | U84: =VLOOKUP(N84,Mapping!H:I,2,FALSE) -> Value
A85: BlackRock Investment Management (U.K.), LTD | B85: yes | C85: 82 | D85: 716423 | E85: -205821 | F85: 0.1 | G85: 524212 | H85: -205821 | I85: 03/31/2026 | J85: 192211 | K85: 0 | L85: 04/30/2026 | M85: 1184413742089 | N85: Growth | O85: 12.186 | P85: London | R85: United Kingdom | S85: =IF(M85>100000000000, "100bn", IF(M85>50000000000, "50bn - 100bn",IF(M85>1000000000, "1bn - 50bn", IF(M85>500000000, "500mn - 1bn", "500mn")))) -> 100bn | T85: =VLOOKUP(R85,Mapping!B:C,2,FALSE) -> EU | U85: =VLOOKUP(N85,Mapping!H:I,2,FALSE) -> Growth
A86: Susquehanna Financial Group, LLLP (Broker) | B86: no | C86: 83 | D86: 698994 | E86: 362726 | F86: 0.1 | G86: 698994 | H86: 362726 | I86: 03/31/2026 | M86: 89792953670 | N86: Broker | O86: 110.036 | P86: Bala Cynwyd | Q86: Pennsylvania | R86: United States | S86: =IF(M86>100000000000, "100bn", IF(M86>50000000000, "50bn - 100bn",IF(M86>1000000000, "1bn - 50bn", IF(M86>500000000, "500mn - 1bn", "500mn")))) -> 50bn - 100bn | T86: =VLOOKUP(R86,Mapping!B:C,2,FALSE) -> US/CA | U86: =VLOOKUP(N86,Mapping!H:I,2,FALSE) -> Broker
A87: Perseverance Asset Management | B87: no | C87: 84 | D87: 674999 | E87: 674999 | F87: 0.1 | G87: 674999 | H87: 674999 | I87: 03/31/2026 | M87: 6657177552 | N87: Growth | O87: 27.222 | P87: Shanghai | R87: China (Mainland) | S87: =IF(M87>100000000000, "100bn", IF(M87>50000000000, "50bn - 100bn",IF(M87>1000000000, "1bn - 50bn", IF(M87>500000000, "500mn - 1bn", "500mn")))) -> 1bn - 50bn | T87: =VLOOKUP(R87,Mapping!B:C,2,FALSE) -> CN | U87: =VLOOKUP(N87,Mapping!H:I,2,FALSE) -> Growth
A88: Invesco Advisers, Inc. | B88: yes | C88: 85 | D88: 663254 | E88: -463343 | F88: 0.1 | G88: 119954 | H88: -100343 | I88: 03/31/2026 | J88: 543300 | K88: -363000 | L88: 03/31/2026 | M88: 235654473842 | N88: Growth | O88: 37.378 | P88: Atlanta | Q88: Georgia | R88: United States | S88: =IF(M88>100000000000, "100bn", IF(M88>50000000000, "50bn - 100bn",IF(M88>1000000000, "1bn - 50bn", IF(M88>500000000, "500mn - 1bn", "500mn")))) -> 100bn | T88: =VLOOKUP(R88,Mapping!B:C,2,FALSE) -> US/CA | U88: =VLOOKUP(N88,Mapping!H:I,2,FALSE) -> Growth
A89: Aperio Group, LLC | B89: yes | C89: 86 | D89: 662487 | E89: 28330 | F89: 0.1 | G89: 662487 | H89: 28330 | I89: 03/31/2026 | M89: 142156703870 | N89: Index | O89: 13.702 | P89: Sausalito | Q89: California | R89: United States | S89: =IF(M89>100000000000, "100bn", IF(M89>50000000000, "50bn - 100bn",IF(M89>1000000000, "1bn - 50bn", IF(M89>500000000, "500mn - 1bn", "500mn")))) -> 100bn | T89: =VLOOKUP(R89,Mapping!B:C,2,FALSE) -> US/CA | U89: =VLOOKUP(N89,Mapping!H:I,2,FALSE) -> Index
A90: Capital International Sàrl (Switzerland) | B90: no | C90: 87 | D90: 660014 | E90: 14771 | F90: 0.1 | G90: 660014 | H90: 14771 | I90: 03/31/2026 | M90: 6756621863 | N90: Value | O90: 34.196 | P90: Geneva | R90: Switzerland | S90: =IF(M90>100000000000, "100bn", IF(M90>50000000000, "50bn - 100bn",IF(M90>1000000000, "1bn - 50bn", IF(M90>500000000, "500mn - 1bn", "500mn")))) -> 1bn - 50bn | T90: =VLOOKUP(R90,Mapping!B:C,2,FALSE) -> EU | U90: =VLOOKUP(N90,Mapping!H:I,2,FALSE) -> Value
A91: Headwater Capital Company, LTD | B91: no | C91: 88 | D91: 660000 | E91: 335000 | F91: 0.1 | G91: 660000 | H91: 335000 | I91: 03/31/2026 | M91: 621950350 | O91: 151.653 | P91: Wanchai | R91: Hong Kong SAR | S91: =IF(M91>100000000000, "100bn", IF(M91>50000000000, "50bn - 100bn",IF(M91>1000000000, "1bn - 50bn", IF(M91>500000000, "500mn - 1bn", "500mn")))) -> 500mn - 1bn | T91: =VLOOKUP(R91,Mapping!B:C,2,FALSE) -> HK | U91: =VLOOKUP(N91,Mapping!H:I,2,FALSE) -> #N/A
A92: UBS Asset Management (U.K.), LTD | B92: yes | C92: 89 | D92: 658490 | E92: 99613 | F92: 0.1 | G92: 93813 | H92: 93813 | I92: 03/31/2026 | J92: 564677 | K92: 5800 | L92: 05/11/2026 | M92: 236706850323 | N92: Index | O92: 33.318 | P92: London | R92: United Kingdom | S92: =IF(M92>100000000000, "100bn", IF(M92>50000000000, "50bn - 100bn",IF(M92>1000000000, "1bn - 50bn", IF(M92>500000000, "500mn - 1bn", "500mn")))) -> 100bn | T92: =VLOOKUP(R92,Mapping!B:C,2,FALSE) -> EU | U92: =VLOOKUP(N92,Mapping!H:I,2,FALSE) -> Index
A93: Two Sigma Advisers, L.P. | B93: no | C93: 90 | D93: 655400 | E93: 212800 | F93: 0.1 | G93: 655400 | H93: 212800 | I93: 12/31/2025 | M93: 51341638158 | N93: Alternative | O93: 117.287 | P93: New York | Q93: New York | R93: United States | S93: =IF(M93>100000000000, "100bn", IF(M93>50000000000, "50bn - 100bn",IF(M93>1000000000, "1bn - 50bn", IF(M93>500000000, "500mn - 1bn", "500mn")))) -> 50bn - 100bn | T93: =VLOOKUP(R93,Mapping!B:C,2,FALSE) -> US/CA | U93: =VLOOKUP(N93,Mapping!H:I,2,FALSE) -> Alternative/Specialty
A94: Handelsbanken Asset Management (Sweden) | B94: yes | C94: 91 | D94: 655000 | E94: 1200 | F94: 0.1 | G94: 412000 | H94: 0 | I94: 03/31/2026 | J94: 243000 | K94: 1200 | L94: 04/30/2026 | M94: 90902689582 | N94: Value | O94: 29.484 | P94: Stockholm | R94: Sweden | S94: =IF(M94>100000000000, "100bn", IF(M94>50000000000, "50bn - 100bn",IF(M94>1000000000, "1bn - 50bn", IF(M94>500000000, "500mn - 1bn", "500mn")))) -> 50bn - 100bn | T94: =VLOOKUP(R94,Mapping!B:C,2,FALSE) -> EU | U94: =VLOOKUP(N94,Mapping!H:I,2,FALSE) -> Value
A95: DWS Investments UK, LTD | B95: yes | C95: 92 | D95: 654030 | E95: 31393 | F95: 0.09 | G95: 0 | H95: -4617 | I95: 06/30/2025 | J95: 654030 | K95: 36010 | L95: 03/31/2026 | M95: 191317387484 | N95: Index | O95: 32.027 | P95: London | R95: United Kingdom | S95: =IF(M95>100000000000, "100bn", IF(M95>50000000000, "50bn - 100bn",IF(M95>1000000000, "1bn - 50bn", IF(M95>500000000, "500mn - 1bn", "500mn")))) -> 100bn | T95: =VLOOKUP(R95,Mapping!B:C,2,FALSE) -> EU | U95: =VLOOKUP(N95,Mapping!H:I,2,FALSE) -> Index
A96: C WorldWide Asset Management Fondsmæglerselskab A/S | B96: yes | C96: 93 | D96: 610617 | E96: -12552 | F96: 0.09 | G96: 601167 | H96: -12302 | I96: 03/31/2026 | J96: 9450 | K96: -250 | L96: 05/09/2026 | M96: 7441091963 | N96: Growth | O96: 41.21 | P96: Copenhagen | R96: Denmark | S96: =IF(M96>100000000000, "100bn", IF(M96>50000000000, "50bn - 100bn",IF(M96>1000000000, "1bn - 50bn", IF(M96>500000000, "500mn - 1bn", "500mn")))) -> 1bn - 50bn | T96: =VLOOKUP(R96,Mapping!B:C,2,FALSE) -> EU | U96: =VLOOKUP(N96,Mapping!H:I,2,FALSE) -> Growth
A97: Schroder Investment Management (Singapore), LTD | B97: yes | C97: 94 | D97: 610515 | E97: 0 | F97: 0.09 | G97: 76565 | H97: 0 | I97: 03/31/2026 | J97: 533950 | K97: 0 | L97: 04/30/2026 | M97: 14802321497 | N97: GARP | O97: 35.863 | P97: Singapore | R97: Singapore | S97: =IF(M97>100000000000, "100bn", IF(M97>50000000000, "50bn - 100bn",IF(M97>1000000000, "1bn - 50bn", IF(M97>500000000, "500mn - 1bn", "500mn")))) -> 1bn - 50bn | T97: =VLOOKUP(R97,Mapping!B:C,2,FALSE) -> SG | U97: =VLOOKUP(N97,Mapping!H:I,2,FALSE) -> Growth
A98: abrdn Investment Management, LTD | B98: yes | C98: 95 | D98: 609261 | E98: -18386 | F98: 0.09 | G98: 15383 | H98: -11436 | I98: 03/31/2026 | J98: 593878 | K98: -6950 | L98: 04/30/2026 | M98: 137802863701 | N98: Growth | O98: 21.72 | P98: London | R98: United Kingdom | S98: =IF(M98>100000000000, "100bn", IF(M98>50000000000, "50bn - 100bn",IF(M98>1000000000, "1bn - 50bn", IF(M98>500000000, "500mn - 1bn", "500mn")))) -> 100bn | T98: =VLOOKUP(R98,Mapping!B:C,2,FALSE) -> EU | U98: =VLOOKUP(N98,Mapping!H:I,2,FALSE) -> Growth
A99: Aviva Investors Global Services, LTD (U.K.) | B99: yes | C99: 96 | D99: 608521 | E99: 9279 | F99: 0.09 | J99: 608521 | K99: 9279 | L99: 03/31/2026 | M99: 91342112159 | N99: Growth | O99: 22.521 | P99: London | R99: United Kingdom | S99: =IF(M99>100000000000, "100bn", IF(M99>50000000000, "50bn - 100bn",IF(M99>1000000000, "1bn - 50bn", IF(M99>500000000, "500mn - 1bn", "500mn")))) -> 50bn - 100bn | T99: =VLOOKUP(R99,Mapping!B:C,2,FALSE) -> EU | U99: =VLOOKUP(N99,Mapping!H:I,2,FALSE) -> Growth
A100: M&G Investment Management, LTD | B100: yes | C100: 97 | D100: 605521 | E100: 87776 | F100: 0.09 | G100: 261593 | H100: 40410 | I100: 03/31/2026 | J100: 343928 | K100: 47366 | L100: 03/31/2026 | M100: 72191477160 | N100: Growth | O100: 32.459 | P100: London | R100: United Kingdom | S100: =IF(M100>100000000000, "100bn", IF(M100>50000000000, "50bn - 100bn",IF(M100>1000000000, "1bn - 50bn", IF(M100>500000000, "500mn - 1bn", "500mn")))) -> 50bn - 100bn | T100: =VLOOKUP(R100,Mapping!B:C,2,FALSE) -> EU | U100: =VLOOKUP(N100,Mapping!H:I,2,FALSE) -> Growth
...

Sheet 全球投资人地图
B2: 全球投资人地图
B3: updated as of 26Q1
B5: # of Institutions | C5: 5452
B6: Total SH Equity AUM ($bn) | C6: =DATA_ALL!CL5455/1000000000 -> 79423.874
B7: TCOM SH Equity AUM ($bn) | C7: =(C6*1000000000-D18)/1000000000 -> 61377.191
B8: Total TCOM Holding ($bn) | C8: =(DATA_ALL!G5455+DATA_ALL!I5455)/1000000000 -> 20.761221 | D8: *小于Total Market Cap, 由于目前可以抓取到的公开披露信息，cover约53%的股东持仓数据
B9: Holding % | C9: =C8/C7 -> 0.0003382563
C11: Position (in $bn) | D11: Total Equity AUM (in $bn) | E11: Holding % | F11: Avg Holding%
B12: Total Peer (14家) | C12: =C13+C14 -> 824.60342 | D12: =C6 -> 79423.874 | E12: =C12/D12 -> 0.010382312 | F12: =E12/14 -> 0.0007415937
B13: ADR Peer (7家) | C13: =SUM(DATA_ALL!G5455:AF5455)/1000000000 -> 608.09085 | D13: =(D12*1000000000-D16)/1000000000 -> 74954.706 | E13: =C13/D13 -> 0.0081127775 | F13: =E13/7 -> 0.0011589682
B14: Travel Peer (7家) | C14: =SUM(DATA_ALL!AH5455:AX5455)/1000000000 -> 216.51257 | D14: =(D12*1000000000-D17)/1000000000 -> 75590.369 | E14: =C14/D14 -> 0.0028642878 | F14: =E14/7 -> 0.00040918397
D16: 4469167890168 | E16: no ADR holding Equity AUM
D17: 3833504796936 | E17: no Travel holding Equity AUM
D18: 18046683025877 | E18: no TCOM holding

Sheet US&CA
B2: US&CA Top Investors
B3: As of 2026Q1, AUM > $50bn
D5: 85 | E5: 90 | F5: 89 | G5: 7 | H5: 9 | J5: 31240000000 | L5: 11 | M5: =4058000000000/7.83 -> 5.1826309e+11 | N5: 13 | O5: 15 | Q5: 318100000000 | R5: 18 | S5: =507200000000/7.83 -> 6.4776501e+10 | T5: 20 | U5: 22 | W5: 72350000000 | X5: 24 | Y5: 136400000000 | Z5: 26 | AA5: 28 | AC5: 43230000000 | AD5: 30 | AE5: 32 | AG5: 46050000000 | AH5: 34 | AI5: 78850000000 | AJ5: 40 | AK5: 119400000000 | AL5: 42 | AM5: 26130000000 | AN5: 44 | AO5: 4108000000 | AP5: 46 | AQ5: 1101000000 | AR5: 48 | AS5: 217100000 | AT5: 50 | AU5: =38560000000/7.83 -> 4.9246488e+09
C6: Institution/Fund Name | D6: Dominant Style | E6: Equity AUM, $bn | F6: Country | I6: TCOM | L6: ADR Peers | AH6: Travel Peers
D7: Dominant Style | G7: TCOM | H7: 9961 | I7: Position | J7: % Mkt Cap | K7: SH Rank | L7: Tencent Position | M7: Tencent % Mkt Cap | N7: BABA | O7: 9988 | P7: BABA Position | Q7: BABA % Mkt Cap | R7: Meituan Position | S7: Meituan % Mkt Cap | T7: NTES | U7: 9999 | V7: NTES Position | W7: NTES % Mkt Cap | X7: PDD Position | Y7: PDD % Mkt Cap | Z7: JD | AA7: 9618 | AB7: JD Position | AC7: JD % Mkt Cap | AD7: BIDU | AE7: 9888 | AF7: BIDU Position | AG7: BIDU % Mkt Cap | AH7: ABNB Position | AI7: Avg % Mkt Cap | AJ7: BKNG Position | AK7: BKNG % Mkt Cap | AL7: EXPE Position | AM7: EXPE % Mkt Cap | AN7: MMYT Position | AO7: MMYT % Mkt Cap | AP7: TRIP Position | AQ7: TRIP % Mkt Cap | AR7: TRVG Position | AS7: TRVG % Mkt Cap | AT7: TC Position | AU7: TC % Mkt Cap
B8: 1 | C8: The Vanguard Group, Inc. | D8: =VLOOKUP($C8,DATA_ALL!$A:$CU,D$5,FALSE) -> Index | E8: =VLOOKUP($C8,DATA_ALL!$A:$CU,E$5,FALSE)/1000000000 -> 7960.9296 | F8: =VLOOKUP($C8,DATA_ALL!$A:$CU,F$5,FALSE) -> United States | G8: =IF(VLOOKUP($C8,DATA_ALL!$A:$CU,G$5,FALSE)="N/A",0,VLOOKUP($C8,DATA_ALL!$A:$CU,G$5,FALSE)) -> 0 | H8: =VLOOKUP($C8,DATA_ALL!$A:$CU,H$5,FALSE) -> 1026978790 | I8: =G8+H8 -> 1026978790 | J8: =I8/$J$5 -> 0.032873841 | K8: =IFERROR(INDEX('SH Summary'!B:B,MATCH('US&CA'!C8,'SH Summary'!C:C,0)), "N/A") -> 2 | L8: =VLOOKUP($C8,DATA_ALL!$A:$CU,L$5,FALSE) -> 13476680302 | M8: =L8/M$5 -> 0.02600355 | N8: =VLOOKUP($C8,DATA_ALL!$A:$CU,N$5,FALSE) -> 64361 | O8: =VLOOKUP($C8,DATA_ALL!$A:$CU,O$5,FALSE) -> 9594202081 | P8: =N8+O8 -> 9594266442 | Q8: =P8/Q$5 -> 0.030161165 | R8: =VLOOKUP($C8,DATA_ALL!$A:$CU,R$5,FALSE) -> 1990217324 | S8: =R8/S$5 -> 0.030724372 | T8: =VLOOKUP($C8,DATA_ALL!$A:$CU,T$5,FALSE) -> 0 | U8: =VLOOKUP($C8,DATA_ALL!$A:$CU,U$5,FALSE) -> 1399520043 | V8: =T8+U8 -> 1399520043 | W8: =V8/W$5 -> 0.019343746 | X8: =VLOOKUP($C8,DATA_ALL!$A:$CU,X$5,FALSE) -> 3367130490 | Y8: =X8/Y$5 -> 0.024685707 | Z8: =VLOOKUP($C8,DATA_ALL!$A:$CU,Z$5,FALSE) -> 1479 | AA8: =VLOOKUP($C8,DATA_ALL!$A:$CU,AA$5,FALSE) -> 1250721183 | AB8: =Z8+AA8 -> 1250722662 | AC8: =AB8/AC$5 -> 0.028931822 | AD8: =VLOOKUP($C8,DATA_ALL!$A:$CU,AD$5,FALSE) -> 2786 | AE8: =VLOOKUP($C8,DATA_ALL!$A:$CU,AE$5,FALSE) -> 1020628020 | AF8: =AD8+AE8 -> 1020630806 | AG8: =AF8/AG$5 -> 0.022163535 | AH8: =VLOOKUP($C8,DATA_ALL!$A:$CU,AH$5,FALSE) -> 4796747947 | AI8: =AH8/AI$5 -> 0.060833836 | AJ8: =VLOOKUP($C8,DATA_ALL!$A:$CU,AJ$5,FALSE) -> 12543301138 | AK8: =AJ8/AK$5 -> 0.10505277 | AL8: =VLOOKUP($C8,DATA_ALL!$A:$CU,AL$5,FALSE) -> 3381632257 | AM8: =AL8/AM$5 -> 0.1294157 | AN8: =VLOOKUP($C8,DATA_ALL!$A:$CU,AN$5,FALSE) -> 3159582 | AO8: =AN8/AO$5 -> 0.00076912902 | AP8: =VLOOKUP($C8,DATA_ALL!$A:$CU,AP$5,FALSE) -> 134917256 | AQ8: =AP8/AQ$5 -> 0.12254065 | AR8: =VLOOKUP($C8,DATA_ALL!$A:$CU,AR$5,FALSE) -> 0 | AS8: =AR8/AS$5 -> 0 | AT8: =VLOOKUP($C8,DATA_ALL!$A:$CU,AT$5,FALSE) -> 101577826 | AU8: =AT8/AU$5 -> 0.02062641
B9: 2 | C9: BlackRock Fund Advisors | D9: =VLOOKUP($C9,DATA_ALL!$A:$CU,D$5,FALSE) -> Index | E9: =VLOOKUP($C9,DATA_ALL!$A:$CU,E$5,FALSE)/1000000000 -> 4837.4638 | F9: =VLOOKUP($C9,DATA_ALL!$A:$CU,F$5,FALSE) -> United States | G9: =IF(VLOOKUP($C9,DATA_ALL!$A:$CU,G$5,FALSE)="N/A",0,VLOOKUP($C9,DATA_ALL!$A:$CU,G$5,FALSE)) -> 29618727 | H9: =VLOOKUP($C9,DATA_ALL!$A:$CU,H$5,FALSE) -> 858321319 | I9: =G9+H9 -> 887940046 | J9: =I9/$J$5 -> 0.028423177 | K9: =IFERROR(INDEX('SH Summary'!B:B,MATCH('US&CA'!C9,'SH Summary'!C:C,0)), "N/A") -> 3 | L9: =VLOOKUP($C9,DATA_ALL!$A:$CU,L$5,FALSE) -> 8753867028 | M9: =L9/M$5 -> 0.016890778 | N9: =VLOOKUP($C9,DATA_ALL!$A:$CU,N$5,FALSE) -> 108616619 | O9: =VLOOKUP($C9,DATA_ALL!$A:$CU,O$5,FALSE) -> 6864586154 | P9: =N9+O9 -> 6973202773 | Q9: =P9/Q$5 -> 0.021921417 | R9: =VLOOKUP($C9,DATA_ALL!$A:$CU,R$5,FALSE) -> 1363990894 | S9: =R9/S$5 -> 0.021056878 | T9: =VLOOKUP($C9,DATA_ALL!$A:$CU,T$5,FALSE) -> 912423 | U9: =VLOOKUP($C9,DATA_ALL!$A:$CU,U$5,FALSE) -> 1146135089 | V9: =T9+U9 -> 1147047512 | W9: =V9/W$5 -> 0.015854147 | X9: =VLOOKUP($C9,DATA_ALL!$A:$CU,X$5,FALSE) -> 2385668497 | Y9: =X9/Y$5 -> 0.017490238 | Z9: =VLOOKUP($C9,DATA_ALL!$A:$CU,Z$5,FALSE) -> 4585154 | AA9: =VLOOKUP($C9,DATA_ALL!$A:$CU,AA$5,FALSE) -> 994000363 | AB9: =Z9+AA9 -> 998585517 | AC9: =AB9/AC$5 -> 0.023099364 | AD9: =VLOOKUP($C9,DATA_ALL!$A:$CU,AD$5,FALSE) -> 99411598 | AE9: =VLOOKUP($C9,DATA_ALL!$A:$CU,AE$5,FALSE) -> 1070697604 | AF9: =AD9+AE9 -> 1170109202 | AG9: =AF9/AG$5 -> 0.025409538 | AH9: =VLOOKUP($C9,DATA_ALL!$A:$CU,AH$5,FALSE) -> 2507658011 | AI9: =AH9/AI$5 -> 0.031802892 | AJ9: =VLOOKUP($C9,DATA_ALL!$A:$CU,AJ$5,FALSE) -> 6677058071 | AK9: =AJ9/AK$5 -> 0.055921759 | AL9: =VLOOKUP($C9,DATA_ALL!$A:$CU,AL$5,FALSE) -> 1620974559 | AM9: =AL9/AM$5 -> 0.062035 | AN9: =VLOOKUP($C9,DATA_ALL!$A:$CU,AN$5,FALSE) -> 4662592 | AO9: =AN9/AO$5 -> 0.0011350029 | AP9: =VLOOKUP($C9,DATA_ALL!$A:$CU,AP$5,FALSE) -> 165075526 | AQ9: =AP9/AQ$5 -> 0.14993236 | AR9: =VLOOKUP($C9,DATA_ALL!$A:$CU,AR$5,FALSE) -> 0 | AS9: =AR9/AS$5 -> 0 | AT9: =VLOOKUP($C9,DATA_ALL!$A:$CU,AT$5,FALSE) -> 76002098 | AU9: =AT9/AU$5 -> 0.015432999
B10: 3 | C10: State Street Investment Management | D10: =VLOOKUP($C10,DATA_ALL!$A:$CU,D$5,FALSE) -> Index | E10: =VLOOKUP($C10,DATA_ALL!$A:$CU,E$5,FALSE)/1000000000 -> 3127.6536 | F10: =VLOOKUP($C10,DATA_ALL!$A:$CU,F$5,FALSE) -> United States | G10: =IF(VLOOKUP($C10,DATA_ALL!$A:$CU,G$5,FALSE)="N/A",0,VLOOKUP($C10,DATA_ALL!$A:$CU,G$5,FALSE)) -> 718221 | H10: =VLOOKUP($C10,DATA_ALL!$A:$CU,H$5,FALSE) -> 68099849 | I10: =G10+H10 -> 68818070 | J10: =I10/$J$5 -> 0.0022028832 | K10: =IFERROR(INDEX('SH Summary'!B:B,MATCH('US&CA'!C10,'SH Summary'!C:C,0)), "N/A") -> 53 | L10: =VLOOKUP($C10,DATA_ALL!$A:$CU,L$5,FALSE) -> 872445888 | M10: =L10/M$5 -> 0.0016834035 | N10: =VLOOKUP($C10,DATA_ALL!$A:$CU,N$5,FALSE) -> 60529933 | O10: =VLOOKUP($C10,DATA_ALL!$A:$CU,O$5,FALSE) -> 704013706 | P10: =N10+O10 -> 764543639 | Q10: =P10/Q$5 -> 0.0024034695 | R10: =VLOOKUP($C10,DATA_ALL!$A:$CU,R$5,FALSE) -> 128450102 | S10: =R10/S$5 -> 0.0019829738 | T10: =VLOOKUP($C10,DATA_ALL!$A:$CU,T$5,FALSE) -> 3903012 | U10: =VLOOKUP($C10,DATA_ALL!$A:$CU,U$5,FALSE) -> 104596181 | V10: =T10+U10 -> 108499193 | W10: =V10/W$5 -> 0.0014996433 | X10: =VLOOKUP($C10,DATA_ALL!$A:$CU,X$5,FALSE) -> 1229603159 | Y10: =X10/Y$5 -> 0.0090146859 | Z10: =VLOOKUP($C10,DATA_ALL!$A:$CU,Z$5,FALSE) -> 4435145 | AA10: =VLOOKUP($C10,DATA_ALL!$A:$CU,AA$5,FALSE) -> 101549754 | AB10: =Z10+AA10 -> 105984899 | AC10: =AB10/AC$5 -> 0.0024516516 | AD10: =VLOOKUP($C10,DATA_ALL!$A:$CU,AD$5,FALSE) -> 9633707 | AE10: =VLOOKUP($C10,DATA_ALL!$A:$CU,AE$5,FALSE) -> 91757505 | AF10: =AD10+AE10 -> 101391212 | AG10: =AF10/AG$5 -> 0.0022017636 | AH10: =VLOOKUP($C10,DATA_ALL!$A:$CU,AH$5,FALSE) -> 2239349506 | AI10: =AH10/AI$5 -> 0.028400121 | AJ10: =VLOOKUP($C10,DATA_ALL!$A:$CU,AJ$5,FALSE) -> 5982005815 | AK10: =AJ10/AK$5 -> 0.050100551 | AL10: =VLOOKUP($C10,DATA_ALL!$A:$CU,AL$5,FALSE) -> 1291250709 | AM10: =AL10/AM$5 -> 0.049416407 | AN10: =VLOOKUP($C10,DATA_ALL!$A:$CU,AN$5,FALSE) -> 3801529 | AO10: =AN10/AO$5 -> 0.00092539654 | AP10: =VLOOKUP($C10,DATA_ALL!$A:$CU,AP$5,FALSE) -> 52111890 | AQ10: =AP10/AQ$5 -> 0.047331417 | AR10: =VLOOKUP($C10,DATA_ALL!$A:$CU,AR$5,FALSE) -> 0 | AS10: =AR10/AS$5 -> 0 | AT10: =VLOOKUP($C10,DATA_ALL!$A:$CU,AT$5,FALSE) -> 5136158 | AU10: =AT10/AU$5 -> 0.0010429491
B11: 4 | C11: Fidelity Management & Research Company, LLC | D11: =VLOOKUP($C11,DATA_ALL!$A:$CU,D$5,FALSE) -> Growth | E11: =VLOOKUP($C11,DATA_ALL!$A:$CU,E$5,FALSE)/1000000000 -> 1923.7785 | F11: =VLOOKUP($C11,DATA_ALL!$A:$CU,F$5,FALSE) -> United States | G11: =IF(VLOOKUP($C11,DATA_ALL!$A:$CU,G$5,FALSE)="N/A",0,VLOOKUP($C11,DATA_ALL!$A:$CU,G$5,FALSE)) -> 35144471 | H11: =VLOOKUP($C11,DATA_ALL!$A:$CU,H$5,FALSE) -> 7035115 | I11: =G11+H11 -> 42179586 | J11: =I11/$J$5 -> 0.0013501788 | K11: =IFERROR(INDEX('SH Summary'!B:B,MATCH('US&CA'!C11,'SH Summary'!C:C,0)), "N/A") -> 72 | L11: =VLOOKUP($C11,DATA_ALL!$A:$CU,L$5,FALSE) -> 2435922618 | M11: =L11/M$5 -> 0.0047001661 | N11: =VLOOKUP($C11,DATA_ALL!$A:$CU,N$5,FALSE) -> 692326420 | O11: =VLOOKUP($C11,DATA_ALL!$A:$CU,O$5,FALSE) -> 117834936 | P11: =N11+O11 -> 810161356 | Q11: =P11/Q$5 -> 0.0025468763 | R11: =VLOOKUP($C11,DATA_ALL!$A:$CU,R$5,FALSE) -> 6917848 | S11: =R11/S$5 -> 0.00010679564 | T11: =VLOOKUP($C11,DATA_ALL!$A:$CU,T$5,FALSE) -> 30443650 | U11: =VLOOKUP($C11,DATA_ALL!$A:$CU,U$5,FALSE) -> 30113333 | V11: =T11+U11 -> 60556983 | W11: =V11/W$5 -> 0.00083700046 | X11: =VLOOKUP($C11,DATA_ALL!$A:$CU,X$5,FALSE) -> 261077972 | Y11: =X11/Y$5 -> 0.0019140614 | Z11: =VLOOKUP($C11,DATA_ALL!$A:$CU,Z$5,FALSE) -> 7966513 | AA11: =VLOOKUP($C11,DATA_ALL!$A:$CU,AA$5,FALSE) -> 373591 | AB11: =Z11+AA11 -> 8340104 | AC11: =AB11/AC$5 -> 0.00019292399 | AD11: =VLOOKUP($C11,DATA_ALL!$A:$CU,AD$5,FALSE) -> 1913861 | AE11: =VLOOKUP($C11,DATA_ALL!$A:$CU,AE$5,FALSE) -> 8917061 | AF11: =AD11+AE11 -> 10830922 | AG11: =AF11/AG$5 -> 0.00023519917 | AH11: =VLOOKUP($C11,DATA_ALL!$A:$CU,AH$5,FALSE) -> 854168780 | AI11: =AH11/AI$5 -> 0.010832832 | AJ11: =VLOOKUP($C11,DATA_ALL!$A:$CU,AJ$5,FALSE) -> 1259315133 | AK11: =AJ11/AK$5 -> 0.010547028 | AL11: =VLOOKUP($C11,DATA_ALL!$A:$CU,AL$5,FALSE) -> 306660248 | AM11: =AL11/AM$5 -> 0.011735945 | AN11: =VLOOKUP($C11,DATA_ALL!$A:$CU,AN$5,FALSE) -> 45190446 | AO11: =AN11/AO$5 -> 0.011000595 | AP11: =VLOOKUP($C11,DATA_ALL!$A:$CU,AP$5,FALSE) -> 60869 | AQ11: =AP11/AQ$5 -> 5.5285195e-05 | AR11: =VLOOKUP($C11,DATA_ALL!$A:$CU,AR$5,FALSE) -> 0 | AS11: =AR11/AS$5 -> 0 | AT11: =VLOOKUP($C11,DATA_ALL!$A:$CU,AT$5,FALSE) -> 0 | AU11: =AT11/AU$5 -> 0
B12: 5 | C12: Geode Capital Management, LLC | D12: =VLOOKUP($C12,DATA_ALL!$A:$CU,D$5,FALSE) -> Index | E12: =VLOOKUP($C12,DATA_ALL!$A:$CU,E$5,FALSE)/1000000000 -> 1890.8628 | F12: =VLOOKUP($C12,DATA_ALL!$A:$CU,F$5,FALSE) -> United States | G12: =IF(VLOOKUP($C12,DATA_ALL!$A:$CU,G$5,FALSE)="N/A",0,VLOOKUP($C12,DATA_ALL!$A:$CU,G$5,FALSE)) -> 10380020 | H12: =VLOOKUP($C12,DATA_ALL!$A:$CU,H$5,FALSE) -> 152783674 | I12: =G12+H12 -> 163163694 | J12: =I12/$J$5 -> 0.0052229095 | K12: =IFERROR(INDEX('SH Summary'!B:B,MATCH('US&CA'!C12,'SH Summary'!C:C,0)), "N/A") -> 20 | L12: =VLOOKUP($C12,DATA_ALL!$A:$CU,L$5,FALSE) -> 2237948674 | M12: =L12/M$5 -> 0.004318171 | N12: =VLOOKUP($C12,DATA_ALL!$A:$CU,N$5,FALSE) -> 0 | O12: =VLOOKUP($C12,DATA_ALL!$A:$CU,O$5,FALSE) -> 1496259102 | P12: =N12+O12 -> 1496259102 | Q12: =P12/Q$5 -> 0.0047037381 | R12: =VLOOKUP($C12,DATA_ALL!$A:$CU,R$5,FALSE) -> 266774512 | S12: =R12/S$5 -> 0.0041183841 | T12: =VLOOKUP($C12,DATA_ALL!$A:$CU,T$5,FALSE) -> 7923561 | U12: =VLOOKUP($C12,DATA_ALL!$A:$CU,U$5,FALSE) -> 196254479 | V12: =T12+U12 -> 204178040 | W12: =V12/W$5 -> 0.0028220876 | X12: =VLOOKUP($C12,DATA_ALL!$A:$CU,X$5,FALSE) -> 700232081 | Y12: =X12/Y$5 -> 0.0051336663 | Z12: =VLOOKUP($C12,DATA_ALL!$A:$CU,Z$5,FALSE) -> 11906952 | AA12: =VLOOKUP($C12,DATA_ALL!$A:$CU,AA$5,FALSE) -> 332317094 | AB12: =Z12+AA12 -> 344224046 | AC12: =AB12/AC$5 -> 0.0079626196 | AD12: =VLOOKUP($C12,DATA_ALL!$A:$CU,AD$5,FALSE) -> 10521056 | AE12: =VLOOKUP($C12,DATA_ALL!$A:$CU,AE$5,FALSE) -> 273988693 | AF12: =AD12+AE12 -> 284509749 | AG12: =AF12/AG$5 -> 0.006178279 | AH12: =VLOOKUP($C12,DATA_ALL!$A:$CU,AH$5,FALSE) -> 1313449519 | AI12: =AH12/AI$5 -> 0.016657572 | AJ12: =VLOOKUP($C12,DATA_ALL!$A:$CU,AJ$5,FALSE) -> 3751980354 | AK12: =AJ12/AK$5 -> 0.031423621 | AL12: =VLOOKUP($C12,DATA_ALL!$A:$CU,AL$5,FALSE) -> 928927962 | AM12: =AL12/AM$5 -> 0.035550247 | AN12: =VLOOKUP($C12,DATA_ALL!$A:$CU,AN$5,FALSE) -> 14582590 | AO12: =AN12/AO$5 -> 0.0035498028 | AP12: =VLOOKUP($C12,DATA_ALL!$A:$CU,AP$5,FALSE) -> 30292916 | AQ12: =AP12/AQ$5 -> 0.027514002 | AR12: =VLOOKUP($C12,DATA_ALL!$A:$CU,AR$5,FALSE) -> 29721 | AS12: =AR12/AS$5 -> 0.00013690005 | AT12: =VLOOKUP($C12,DATA_ALL!$A:$CU,AT$5,FALSE) -> 17509966 | AU12: =AT12/AU$5 -> 0.0035555766
B13: 6 | C13: Morgan Stanley & Company, LLC | D13: =VLOOKUP($C13,DATA_ALL!$A:$CU,D$5,FALSE) -> Broker | E13: =VLOOKUP($C13,DATA_ALL!$A:$CU,E$5,FALSE)/1000000000 -> 1040.2347 | F13: =VLOOKUP($C13,DATA_ALL!$A:$CU,F$5,FALSE) -> United States | G13: =IF(VLOOKUP($C13,DATA_ALL!$A:$CU,G$5,FALSE)="N/A",0,VLOOKUP($C13,DATA_ALL!$A:$CU,G$5,FALSE)) -> 48313677 | H13: =VLOOKUP($C13,DATA_ALL!$A:$CU,H$5,FALSE) -> 0 | I13: =G13+H13 -> 48313677 | J13: =I13/$J$5 -> 0.0015465326 | K13: =IFERROR(INDEX('SH Summary'!B:B,MATCH('US&CA'!C13,'SH Summary'!C:C,0)), "N/A") -> 66 | L13: =VLOOKUP($C13,DATA_ALL!$A:$CU,L$5,FALSE) -> 0 | M13: =L13/M$5 -> 0 | N13: =VLOOKUP($C13,DATA_ALL!$A:$CU,N$5,FALSE) -> 600585049 | O13: =VLOOKUP($C13,DATA_ALL!$A:$CU,O$5,FALSE) -> 0 | P13: =N13+O13 -> 600585049 | Q13: =P13/Q$5 -> 0.0018880385 | R13: =VLOOKUP($C13,DATA_ALL!$A:$CU,R$5,FALSE) -> 0 | S13: =R13/S$5 -> 0 | T13: =VLOOKUP($C13,DATA_ALL!$A:$CU,T$5,FALSE) -> 46568831 | U13: =VLOOKUP($C13,DATA_ALL!$A:$CU,U$5,FALSE) -> 0 | V13: =T13+U13 -> 46568831 | W13: =V13/W$5 -> 0.00064366041 | X13: =VLOOKUP($C13,DATA_ALL!$A:$CU,X$5,FALSE) -> 509740359 | Y13: =X13/Y$5 -> 0.0037370994 | Z13: =VLOOKUP($C13,DATA_ALL!$A:$CU,Z$5,FALSE) -> 76065306 | AA13: =VLOOKUP($C13,DATA_ALL!$A:$CU,AA$5,FALSE) -> 0 | AB13: =Z13+AA13 -> 76065306 | AC13: =AB13/AC$5 -> 0.0017595491 | AD13: =VLOOKUP($C13,DATA_ALL!$A:$CU,AD$5,FALSE) -> 71150806 | AE13: =VLOOKUP($C13,DATA_ALL!$A:$CU,AE$5,FALSE) -> 0 | AF13: =AD13+AE13 -> 71150806 | AG13: =AF13/AG$5 -> 0.0015450772 | AH13: =VLOOKUP($C13,DATA_ALL!$A:$CU,AH$5,FALSE) -> 234082458 | AI13: =AH13/AI$5 -> 0.0029687059 | AJ13: =VLOOKUP($C13,DATA_ALL!$A:$CU,AJ$5,FALSE) -> 816107377 | AK13: =AJ13/AK$5 -> 0.0068350702 | AL13: =VLOOKUP($C13,DATA_ALL!$A:$CU,AL$5,FALSE) -> 186588443 | AM13: =AL13/AM$5 -> 0.0071407747 | AN13: =VLOOKUP($C13,DATA_ALL!$A:$CU,AN$5,FALSE) -> 45723245 | AO13: =AN13/AO$5 -> 0.011130293 | AP13: =VLOOKUP($C13,DATA_ALL!$A:$CU,AP$5,FALSE) -> 12022710 | AQ13: =AP13/AQ$5 -> 0.010919809 | AR13: =VLOOKUP($C13,DATA_ALL!$A:$CU,AR$5,FALSE) -> 845512 | AS13: =AR13/AS$5 -> 0.0038945739 | AT13: =VLOOKUP($C13,DATA_ALL!$A:$CU,AT$5,FALSE) -> 0 | AU13: =AT13/AU$5 -> 0
B14: 7 | C14: Capital World Investors (U.S.) | D14: =VLOOKUP($C14,DATA_ALL!$A:$CU,D$5,FALSE) -> Value | E14: =VLOOKUP($C14,DATA_ALL!$A:$CU,E$5,FALSE)/1000000000 -> 1022.5949 | F14: =VLOOKUP($C14,DATA_ALL!$A:$CU,F$5,FALSE) -> United States | G14: =IF(VLOOKUP($C14,DATA_ALL!$A:$CU,G$5,FALSE)="N/A",0,VLOOKUP($C14,DATA_ALL!$A:$CU,G$5,FALSE)) -> 1798176256 | H14: =VLOOKUP($C14,DATA_ALL!$A:$CU,H$5,FALSE) -> 213593771 | I14: =G14+H14 -> 2011770027 | J14: =I14/$J$5 -> 0.064397248 | K14: =IFERROR(INDEX('SH Summary'!B:B,MATCH('US&CA'!C14,'SH Summary'!C:C,0)), "N/A") -> 1 | L14: =VLOOKUP($C14,DATA_ALL!$A:$CU,L$5,FALSE) -> 3767409476 | M14: =L14/M$5 -> 0.0072692992 | N14: =VLOOKUP($C14,DATA_ALL!$A:$CU,N$5,FALSE) -> 521674850 | O14: =VLOOKUP($C14,DATA_ALL!$A:$CU,O$5,FALSE) -> 633177438 | P14: =N14+O14 -> 1154852288 | Q14: =P14/Q$5 -> 0.0036304693 | R14: =VLOOKUP($C14,DATA_ALL!$A:$CU,R$5,FALSE) -> 84785617 | S14: =R14/S$5 -> 0.0013088947 | T14: =VLOOKUP($C14,DATA_ALL!$A:$CU,T$5,FALSE) -> 60580585 | U14: =VLOOKUP($C14,DATA_ALL!$A:$CU,U$5,FALSE) -> 1087319590 | V14: =T14+U14 -> 1147900175 | W14: =V14/W$5 -> 0.015865932 | X14: =VLOOKUP($C14,DATA_ALL!$A:$CU,X$5,FALSE) -> 0 | Y14: =X14/Y$5 -> 0 | Z14: =VLOOKUP($C14,DATA_ALL!$A:$CU,Z$5,FALSE) -> 0 | AA14: =VLOOKUP($C14,DATA_ALL!$A:$CU,AA$5,FALSE) -> 0 | AB14: =Z14+AA14 -> 0 | AC14: =AB14/AC$5 -> 0 | AD14: =VLOOKUP($C14,DATA_ALL!$A:$CU,AD$5,FALSE) -> 133513583 | AE14: =VLOOKUP($C14,DATA_ALL!$A:$CU,AE$5,FALSE) -> 342567255 | AF14: =AD14+AE14 -> 476080838 | AG14: =AF14/AG$5 -> 0.010338346 | AH14: =VLOOKUP($C14,DATA_ALL!$A:$CU,AH$5,FALSE) -> 0 | AI14: =AH14/AI$5 -> 0 | AJ14: =VLOOKUP($C14,DATA_ALL!$A:$CU,AJ$5,FALSE) -> 3238413942 | AK14: =AJ14/AK$5 -> 0.027122395 | AL14: =VLOOKUP($C14,DATA_ALL!$A:$CU,AL$5,FALSE) -> 0 | AM14: =AL14/AM$5 -> 0 | AN14: =VLOOKUP($C14,DATA_ALL!$A:$CU,AN$5,FALSE) -> 0 | AO14: =AN14/AO$5 -> 0 | AP14: =VLOOKUP($C14,DATA_ALL!$A:$CU,AP$5,FALSE) -> 0 | AQ14: =AP14/AQ$5 -> 0 | AR14: =VLOOKUP($C14,DATA_ALL!$A:$CU,AR$5,FALSE) -> 0 | AS14: =AR14/AS$5 -> 0 | AT14: =VLOOKUP($C14,DATA_ALL!$A:$CU,AT$5,FALSE) -> 0 | AU14: =AT14/AU$5 -> 0
B15: 8 | C15: Invesco Capital Management, LLC | D15: =VLOOKUP($C15,DATA_ALL!$A:$CU,D$5,FALSE) -> Index | E15: =VLOOKUP($C15,DATA_ALL!$A:$CU,E$5,FALSE)/1000000000 -> 866.32891 | F15: =VLOOKUP($C15,DATA_ALL!$A:$CU,F$5,FALSE) -> United States | G15: =IF(VLOOKUP($C15,DATA_ALL!$A:$CU,G$5,FALSE)="N/A",0,VLOOKUP($C15,DATA_ALL!$A:$CU,G$5,FALSE)) -> 11833227 | H15: =VLOOKUP($C15,DATA_ALL!$A:$CU,H$5,FALSE) -> 10317926 | I15: =G15+H15 -> 22151153 | J15: =I15/$J$5 -> 0.0007090638 | K15: =IFERROR(INDEX('SH Summary'!B:B,MATCH('US&CA'!C15,'SH Summary'!C:C,0)), "N/A") -> 117 | L15: =VLOOKUP($C15,DATA_ALL!$A:$CU,L$5,FALSE) -> 334830016 | M15: =L15/M$5 -> 0.00064606186 | N15: =VLOOKUP($C15,DATA_ALL!$A:$CU,N$5,FALSE) -> 19435887 | O15: =VLOOKUP($C15,DATA_ALL!$A:$CU,O$5,FALSE) -> 119164271 | P15: =N15+O15 -> 138600158 | Q15: =P15/Q$5 -> 0.00043571254 | R15: =VLOOKUP($C15,DATA_ALL!$A:$CU,R$5,FALSE) -> 277033967 | S15: =R15/S$5 -> 0.0042767665 | T15: =VLOOKUP($C15,DATA_ALL!$A:$CU,T$5,FALSE) -> 23837637 | U15: =VLOOKUP($C15,DATA_ALL!$A:$CU,U$5,FALSE) -> 19518971 | V15: =T15+U15 -> 43356608 | W15: =V15/W$5 -> 0.00059926203 | X15: =VLOOKUP($C15,DATA_ALL!$A:$CU,X$5,FALSE) -> 2035832434 | Y15: =X15/Y$5 -> 0.014925458 | Z15: =VLOOKUP($C15,DATA_ALL!$A:$CU,Z$5,FALSE) -> 57162757 | AA15: =VLOOKUP($C15,DATA_ALL!$A:$CU,AA$5,FALSE) -> 11448235 | AB15: =Z15+AA15 -> 68610992 | AC15: =AB15/AC$5 -> 0.0015871152 | AD15: =VLOOKUP($C15,DATA_ALL!$A:$CU,AD$5,FALSE) -> 22552726 | AE15: =VLOOKUP($C15,DATA_ALL!$A:$CU,AE$5,FALSE) -> 273259595 | AF15: =AD15+AE15 -> 295812321 | AG15: =AF15/AG$5 -> 0.0064237203 | AH15: =VLOOKUP($C15,DATA_ALL!$A:$CU,AH$5,FALSE) -> 1909954728 | AI15: =AH15/AI$5 -> 0.024222634 | AJ15: =VLOOKUP($C15,DATA_ALL!$A:$CU,AJ$5,FALSE) -> 3626268203 | AK15: =AJ15/AK$5 -> 0.030370755 | AL15: =VLOOKUP($C15,DATA_ALL!$A:$CU,AL$5,FALSE) -> 352372501 | AM15: =AL15/AM$5 -> 0.013485362 | AN15: =VLOOKUP($C15,DATA_ALL!$A:$CU,AN$5,FALSE) -> 528325 | AO15: =AN15/AO$5 -> 0.00012860881 | AP15: =VLOOKUP($C15,DATA_ALL!$A:$CU,AP$5,FALSE) -> 14772116 | AQ15: =AP15/AQ$5 -> 0.013416999 | AR15: =VLOOKUP($C15,DATA_ALL!$A:$CU,AR$5,FALSE) -> 0 | AS15: =AR15/AS$5 -> 0 | AT15: =VLOOKUP($C15,DATA_ALL!$A:$CU,AT$5,FALSE) -> 185610 | AU15: =AT15/AU$5 -> 3.7689997e-05
B16: 9 | C16: J.P. Morgan Investment Management, Inc. | D16: =VLOOKUP($C16,DATA_ALL!$A:$CU,D$5,FALSE) -> Growth | E16: =VLOOKUP($C16,DATA_ALL!$A:$CU,E$5,FALSE)/1000000000 -> 846.46809 | F16: =VLOOKUP($C16,DATA_ALL!$A:$CU,F$5,FALSE) -> United States | G16: =IF(VLOOKUP($C16,DATA_ALL!$A:$CU,G$5,FALSE)="N/A",0,VLOOKUP($C16,DATA_ALL!$A:$CU,G$5,FALSE)) -> 113003284 | H16: =VLOOKUP($C16,DATA_ALL!$A:$CU,H$5,FALSE) -> 9341397 | I16: =G16+H16 -> 122344681 | J16: =I16/$J$5 -> 0.003916283 | K16: =IFERROR(INDEX('SH Summary'!B:B,MATCH('US&CA'!C16,'SH Summary'!C:C,0)), "N/A") -> 29 | L16: =VLOOKUP($C16,DATA_ALL!$A:$CU,L$5,FALSE) -> 224275442 | M16: =L16/M$5 -> 0.00043274438 | N16: =VLOOKUP($C16,DATA_ALL!$A:$CU,N$5,FALSE) -> 1771015065 | O16: =VLOOKUP($C16,DATA_ALL!$A:$CU,O$5,FALSE) -> 2918718602 | P16: =N16+O16 -> 4689733667 | Q16: =P16/Q$5 -> 0.014742954 | R16: =VLOOKUP($C16,DATA_ALL!$A:$CU,R$5,FALSE) -> 25587965 | S16: =R16/S$5 -> 0.00039501925 | T16: =VLOOKUP($C16,DATA_ALL!$A:$CU,T$5,FALSE) -> 3840885 | U16: =VLOOKUP($C16,DATA_ALL!$A:$CU,U$5,FALSE) -> 45747336 | V16: =T16+U16 -> 49588221 | W16: =V16/W$5 -> 0.00068539352 | X16: =VLOOKUP($C16,DATA_ALL!$A:$CU,X$5,FALSE) -> 76225565 | Y16: =X16/Y$5 -> 0.00055883845 | Z16: =VLOOKUP($C16,DATA_ALL!$A:$CU,Z$5,FALSE) -> 2987 | AA16: =VLOOKUP($C16,DATA_ALL!$A:$CU,AA$5,FALSE) -> 8699219 | AB16: =Z16+AA16 -> 8702206 | AC16: =AB16/AC$5 -> 0.00020130016 | AD16: =VLOOKUP($C16,DATA_ALL!$A:$CU,AD$5,FALSE) -> 74540 | AE16: =VLOOKUP($C16,DATA_ALL!$A:$CU,AE$5,FALSE) -> 8990398 | AF16: =AD16+AE16 -> 9064938 | AG16: =AF16/AG$5 -> 0.0001968499 | AH16: =VLOOKUP($C16,DATA_ALL!$A:$CU,AH$5,FALSE) -> 118073820 | AI16: =AH16/AI$5 -> 0.0014974486 | AJ16: =VLOOKUP($C16,DATA_ALL!$A:$CU,AJ$5,FALSE) -> 2277324195 | AK16: =AJ16/AK$5 -> 0.019073067 | AL16: =VLOOKUP($C16,DATA_ALL!$A:$CU,AL$5,FALSE) -> 479564764 | AM16: =AL16/AM$5 -> 0.018353033 | AN16: =VLOOKUP($C16,DATA_ALL!$A:$CU,AN$5,FALSE) -> 87313155 | AO16: =AN16/AO$5 -> 0.021254419 | AP16: =VLOOKUP($C16,DATA_ALL!$A:$CU,AP$5,FALSE) -> 541986 | AQ16: =AP16/AQ$5 -> 0.00049226703 | AR16: =VLOOKUP($C16,DATA_ALL!$A:$CU,AR$5,FALSE) -> 0 | AS16: =AR16/AS$5 -> 0 | AT16: =VLOOKUP($C16,DATA_ALL!$A:$CU,AT$5,FALSE) -> 383164 | AU16: =AT16/AU$5 -> 7.7805345e-05
B17: 10 | C17: T. Rowe Price Associates, Inc. | D17: =VLOOKUP($C17,DATA_ALL!$A:$CU,D$5,FALSE) -> Growth | E17: =VLOOKUP($C17,DATA_ALL!$A:$CU,E$5,FALSE)/1000000000 -> 791.41912 | F17: =VLOOKUP($C17,DATA_ALL!$A:$CU,F$5,FALSE) -> United States | G17: =IF(VLOOKUP($C17,DATA_ALL!$A:$CU,G$5,FALSE)="N/A",0,VLOOKUP($C17,DATA_ALL!$A:$CU,G$5,FALSE)) -> 1892 | H17: =VLOOKUP($C17,DATA_ALL!$A:$CU,H$5,FALSE) -> 0 | I17: =G17+H17 -> 1892 | J17: =I17/$J$5 -> 6.056338e-08 | K17: =IFERROR(INDEX('SH Summary'!B:B,MATCH('US&CA'!C17,'SH Summary'!C:C,0)), "N/A") -> 842 | L17: =VLOOKUP($C17,DATA_ALL!$A:$CU,L$5,FALSE) -> 458921196 | M17: =L17/M$5 -> 0.00088549851 | N17: =VLOOKUP($C17,DATA_ALL!$A:$CU,N$5,FALSE) -> 52886910 | O17: =VLOOKUP($C17,DATA_ALL!$A:$CU,O$5,FALSE) -> 184430096 | P17: =N17+O17 -> 237317006 | Q17: =P17/Q$5 -> 0.00074604529 | R17: =VLOOKUP($C17,DATA_ALL!$A:$CU,R$5,FALSE) -> 1827350 | S17: =R17/S$5 -> 2.8210076e-05 | T17: =VLOOKUP($C17,DATA_ALL!$A:$CU,T$5,FALSE) -> 0 | U17: =VLOOKUP($C17,DATA_ALL!$A:$CU,U$5,FALSE) -> 341922 | V17: =T17+U17 -> 341922 | W17: =V17/W$5 -> 4.7259433e-06 | X17: =VLOOKUP($C17,DATA_ALL!$A:$CU,X$5,FALSE) -> 77423727 | Y17: =X17/Y$5 -> 0.00056762263 | Z17: =VLOOKUP($C17,DATA_ALL!$A:$CU,Z$5,FALSE) -> 0 | AA17: =VLOOKUP($C17,DATA_ALL!$A:$CU,AA$5,FALSE) -> 0 | AB17: =Z17+AA17 -> 0 | AC17: =AB17/AC$5 -> 0 | AD17: =VLOOKUP($C17,DATA_ALL!$A:$CU,AD$5,FALSE) -> 0 | AE17: =VLOOKUP($C17,DATA_ALL!$A:$CU,AE$5,FALSE) -> 0 | AF17: =AD17+AE17 -> 0 | AG17: =AF17/AG$5 -> 0 | AH17: =VLOOKUP($C17,DATA_ALL!$A:$CU,AH$5,FALSE) -> 328017730 | AI17: =AH17/AI$5 -> 0.0041600219 | AJ17: =VLOOKUP($C17,DATA_ALL!$A:$CU,AJ$5,FALSE) -> 4687235577 | AK17: =AJ17/AK$5 -> 0.039256579 | AL17: =VLOOKUP($C17,DATA_ALL!$A:$CU,AL$5,FALSE) -> 73556244 | AM17: =AL17/AM$5 -> 0.0028150113 | AN17: =VLOOKUP($C17,DATA_ALL!$A:$CU,AN$5,FALSE) -> 4937681 | AO17: =AN17/AO$5 -> 0.0012019671 | AP17: =VLOOKUP($C17,DATA_ALL!$A:$CU,AP$5,FALSE) -> 0 | AQ17: =AP17/AQ$5 -> 0 | AR17: =VLOOKUP($C17,DATA_ALL!$A:$CU,AR$5,FALSE) -> 0 | AS17: =AR17/AS$5 -> 0 | AT17: =VLOOKUP($C17,DATA_ALL!$A:$CU,AT$5,FALSE) -> 67104277 | AU17: =AT17/AU$5 -> 0.013626206
B18: 11 | C18: Charles Schwab Investment Management, Inc. | D18: =VLOOKUP($C18,DATA_ALL!$A:$CU,D$5,FALSE) -> Index | E18: =VLOOKUP($C18,DATA_ALL!$A:$CU,E$5,FALSE)/1000000000 -> 787.36381 | F18: =VLOOKUP($C18,DATA_ALL!$A:$CU,F$5,FALSE) -> United States | G18: =IF(VLOOKUP($C18,DATA_ALL!$A:$CU,G$5,FALSE)="N/A",0,VLOOKUP($C18,DATA_ALL!$A:$CU,G$5,FALSE)) -> 0 | H18: =VLOOKUP($C18,DATA_ALL!$A:$CU,H$5,FALSE) -> 39887697 | I18: =G18+H18 -> 39887697 | J18: =I18/$J$5 -> 0.0012768149 | K18: =IFERROR(INDEX('SH Summary'!B:B,MATCH('US&CA'!C18,'SH Summary'!C:C,0)), "N/A") -> 77 | L18: =VLOOKUP($C18,DATA_ALL!$A:$CU,L$5,FALSE) -> 623265874 | M18: =L18/M$5 -> 0.0012026052 | N18: =VLOOKUP($C18,DATA_ALL!$A:$CU,N$5,FALSE) -> 0 | O18: =VLOOKUP($C18,DATA_ALL!$A:$CU,O$5,FALSE) -> 692500109 | P18: =N18+O18 -> 692500109 | Q18: =P18/Q$5 -> 0.0021769887 | R18: =VLOOKUP($C18,DATA_ALL!$A:$CU,R$5,FALSE) -> 102977697 | S18: =R18/S$5 -> 0.0015897385 | T18: =VLOOKUP($C18,DATA_ALL!$A:$CU,T$5,FALSE) -> 0 | U18: =VLOOKUP($C18,DATA_ALL!$A:$CU,U$5,FALSE) -> 88138414 | V18: =T18+U18 -> 88138414 | W18: =V18/W$5 -> 0.0012182227 | X18: =VLOOKUP($C18,DATA_ALL!$A:$CU,X$5,FALSE) -> 146988995 | Y18: =X18/Y$5 -> 0.0010776319 | Z18: =VLOOKUP($C18,DATA_ALL!$A:$CU,Z$5,FALSE) -> 159851339 | AA18: =VLOOKUP($C18,DATA_ALL!$A:$CU,AA$5,FALSE) -> 45878462 | AB18: =Z18+AA18 -> 205729801 | AC18: =AB18/AC$5 -> 0.0047589591 | AD18: =VLOOKUP($C18,DATA_ALL!$A:$CU,AD$5,FALSE) -> 0 | AE18: =VLOOKUP($C18,DATA_ALL!$A:$CU,AE$5,FALSE) -> 114146215 | AF18: =AD18+AE18 -> 114146215 | AG18: =AF18/AG$5 -> 0.0024787452 | AH18: =VLOOKUP($C18,DATA_ALL!$A:$CU,AH$5,FALSE) -> 395421195 | AI18: =AH18/AI$5 -> 0.0050148535 | AJ18: =VLOOKUP($C18,DATA_ALL!$A:$CU,AJ$5,FALSE) -> 1167344903 | AK18: =AJ18/AK$5 -> 0.009776758 | AL18: =VLOOKUP($C18,DATA_ALL!$A:$CU,AL$5,FALSE) -> 174562306 | AM18: =AL18/AM$5 -> 0.0066805322 | AN18: =VLOOKUP($C18,DATA_ALL!$A:$CU,AN$5,FALSE) -> 0 | AO18: =AN18/AO$5 -> 0 | AP18: =VLOOKUP($C18,DATA_ALL!$A:$CU,AP$5,FALSE) -> 18342449 | AQ18: =AP18/AQ$5 -> 0.016659808 | AR18: =VLOOKUP($C18,DATA_ALL!$A:$CU,AR$5,FALSE) -> 0 | AS18: =AR18/AS$5 -> 0 | AT18: =VLOOKUP($C18,DATA_ALL!$A:$CU,AT$5,FALSE) -> 3375641 | AU18: =AT18/AU$5 -> 0.00068545822
B19: 12 | C19: Capital Research Global Investors (U.S.) | D19: =VLOOKUP($C19,DATA_ALL!$A:$CU,D$5,FALSE) -> GARP | E19: =VLOOKUP($C19,DATA_ALL!$A:$CU,E$5,FALSE)/1000000000 -> 718.22736 | F19: =VLOOKUP($C19,DATA_ALL!$A:$CU,F$5,FALSE) -> United States | G19: =IF(VLOOKUP($C19,DATA_ALL!$A:$CU,G$5,FALSE)="N/A",0,VLOOKUP($C19,DATA_ALL!$A:$CU,G$5,FALSE)) -> 78674225 | H19: =VLOOKUP($C19,DATA_ALL!$A:$CU,H$5,FALSE) -> 476255 | I19: =G19+H19 -> 79150480 | J19: =I19/$J$5 -> 0.0025336261 | K19: =IFERROR(INDEX('SH Summary'!B:B,MATCH('US&CA'!C19,'SH Summary'!C:C,0)), "N/A") -> 44 | L19: =VLOOKUP($C19,DATA_ALL!$A:$CU,L$5,FALSE) -> 2754843 | M19: =L19/M$5 -> 5.31553e-06 | N19: =VLOOKUP($C19,DATA_ALL!$A:$CU,N$5,FALSE) -> 53184627 | O19: =VLOOKUP($C19,DATA_ALL!$A:$CU,O$5,FALSE) -> 0 | P19: =N19+O19 -> 53184627 | Q19: =P19/Q$5 -> 0.00016719468 | R19: =VLOOKUP($C19,DATA_ALL!$A:$CU,R$5,FALSE) -> 136560 | S19: =R19/S$5 -> 2.1081719e-06 | T19: =VLOOKUP($C19,DATA_ALL!$A:$CU,T$5,FALSE) -> 0 | U19: =VLOOKUP($C19,DATA_ALL!$A:$CU,U$5,FALSE) -> 71763706 | V19: =T19+U19 -> 71763706 | W19: =V19/W$5 -> 0.00099189642 | X19: =VLOOKUP($C19,DATA_ALL!$A:$CU,X$5,FALSE) -> 0 | Y19: =X19/Y$5 -> 0 | Z19: =VLOOKUP($C19,DATA_ALL!$A:$CU,Z$5,FALSE) -> 0 | AA19: =VLOOKUP($C19,DATA_ALL!$A:$CU,AA$5,FALSE) -> 0 | AB19: =Z19+AA19 -> 0 | AC19: =AB19/AC$5 -> 0 | AD19: =VLOOKUP($C19,DATA_ALL!$A:$CU,AD$5,FALSE) -> 0 | AE19: =VLOOKUP($C19,DATA_ALL!$A:$CU,AE$5,FALSE) -> 99147 | AF19: =AD19+AE19 -> 99147 | AG19: =AF19/AG$5 -> 2.1530293e-06 | AH19: =VLOOKUP($C19,DATA_ALL!$A:$CU,AH$5,FALSE) -> 0 | AI19: =AH19/AI$5 -> 0 | AJ19: =VLOOKUP($C19,DATA_ALL!$A:$CU,AJ$5,FALSE) -> 564843900 | AK19: =AJ19/AK$5 -> 0.0047306859 | AL19: =VLOOKUP($C19,DATA_ALL!$A:$CU,AL$5,FALSE) -> 0 | AM19: =AL19/AM$5 -> 0 | AN19: =VLOOKUP($C19,DATA_ALL!$A:$CU,AN$5,FALSE) -> 0 | AO19: =AN19/AO$5 -> 0 | AP19: =VLOOKUP($C19,DATA_ALL!$A:$CU,AP$5,FALSE) -> 0 | AQ19: =AP19/AQ$5 -> 0 | AR19: =VLOOKUP($C19,DATA_ALL!$A:$CU,AR$5,FALSE) -> 0 | AS19: =AR19/AS$5 -> 0 | AT19: =VLOOKUP($C19,DATA_ALL!$A:$CU,AT$5,FALSE) -> 0 | AU19: =AT19/AU$5 -> 0
... B163: 156 | C163: Two Sigma Advisers, L.P. | D163: =VLOOKUP($C163,DATA_ALL!$A:$CU,D$5,FALSE) -> Alternative | E163: =VLOOKUP($C163,DATA_ALL!$A:$CU,E$5,FALSE)/1000000000 -> 51.341638 | F163: =VLOOKUP($C163,DATA_ALL!$A:$CU,F$5,FALSE) -> United States | G163: =IF(VLOOKUP($C163,DATA_ALL!$A:$CU,G$5,FALSE)="N/A",0,VLOOKUP($C163,DATA_ALL!$A:$CU,G$5,FALSE)) -> 47129814 | H163: =VLOOKUP($C163,DATA_ALL!$A:$CU,H$5,FALSE) -> 0 | I163: =G163+H163 -> 47129814 | J163: =I163/$J$5 -> 0.0015086368 | K163: =IFERROR(INDEX('SH Summary'!B:B,MATCH('US&CA'!C163,'SH Summary'!C:C,0)), "N/A") -> 89 | L163: =VLOOKUP($C163,DATA_ALL!$A:$CU,L$5,FALSE) -> 0 | M163: =L163/M$5 -> 0 | N163: =VLOOKUP($C163,DATA_ALL!$A:$CU,N$5,FALSE) -> 0 | O163: =VLOOKUP($C163,DATA_ALL!$A:$CU,O$5,FALSE) -> 0 | P163: =N163+O163 -> 0 | Q163: =P163/Q$5 -> 0 | R163: =VLOOKUP($C163,DATA_ALL!$A:$CU,R$5,FALSE) -> 0 | S163: =R163/S$5 -> 0 | T163: =VLOOKUP($C163,DATA_ALL!$A:$CU,T$5,FALSE) -> 1389962 | U163: =VLOOKUP($C163,DATA_ALL!$A:$CU,U$5,FALSE) -> 0 | V163: =T163+U163 -> 1389962 | W163: =V163/W$5 -> 1.9211638e-05 | X163: =VLOOKUP($C163,DATA_ALL!$A:$CU,X$5,FALSE) -> 0 | Y163: =X163/Y$5 -> 0 | Z163: =VLOOKUP($C163,DATA_ALL!$A:$CU,Z$5,FALSE) -> 0 | AA163: =VLOOKUP($C163,DATA_ALL!$A:$CU,AA$5,FALSE) -> 0 | AB163: =Z163+AA163 -> 0 | AC163: =AB163/AC$5 -> 0 | AD163: =VLOOKUP($C163,DATA_ALL!$A:$CU,AD$5,FALSE) -> 0 | AE163: =VLOOKUP($C163,DATA_ALL!$A:$CU,AE$5,FALSE) -> 0 | AF163: =AD163+AE163 -> 0 | AG163: =AF163/AG$5 -> 0 | AH163: =VLOOKUP($C163,DATA_ALL!$A:$CU,AH$5,FALSE) -> 502991892 | AI163: =AH163/AI$5 -> 0.0063790982 | AJ163: =VLOOKUP($C163,DATA_ALL!$A:$CU,AJ$5,FALSE) -> 81936549 | AK163: =AJ163/AK$5 -> 0.00068623575 | AL163: =VLOOKUP($C163,DATA_ALL!$A:$CU,AL$5,FALSE) -> 0 | AM163: =AL163/AM$5 -> 0 | AN163: =VLOOKUP($C163,DATA_ALL!$A:$CU,AN$5,FALSE) -> 2323996 | AO163: =AN163/AO$5 -> 0.00056572444 | AP163: =VLOOKUP($C163,DATA_ALL!$A:$CU,AP$5,FALSE) -> 928928 | AQ163: =AP163/AQ$5 -> 0.00084371299 | AR163: =VLOOKUP($C163,DATA_ALL!$A:$CU,AR$5,FALSE) -> 0 | AS163: =AR163/AS$5 -> 0 | AT163: =VLOOKUP($C163,DATA_ALL!$A:$CU,AT$5,FALSE) -> 0 | AU163: =AT163/AU$5 -> 0

Sheet EU
B2: EU Top Investors
B3: As of 2026Q1, AUM > $50bn
D5: 85 | E5: 90 | F5: 89 | G5: 7 | H5: 9 | J5: 31240000000 | L5: 11 | M5: =4058000000000/7.83 -> 5.1826309e+11 | N5: 13 | O5: 15 | Q5: 318100000000 | R5: 18 | S5: =507200000000/7.83 -> 6.4776501e+10 | T5: 20 | U5: 22 | W5: 72350000000 | X5: 24 | Y5: 136400000000 | Z5: 26 | AA5: 28 | AC5: 43230000000 | AD5: 30 | AE5: 32 | AG5: 46050000000 | AH5: 34 | AI5: 78850000000 | AJ5: 40 | AK5: 119400000000 | AL5: 42 | AM5: 26130000000 | AN5: 44 | AO5: 4108000000 | AP5: 46 | AQ5: 1101000000 | AR5: 48 | AS5: 217100000 | AT5: 50 | AU5: =38560000000/7.83 -> 4.9246488e+09
C6: Institution/Fund Name | D6: Dominant Style | E6: Equity AUM, $bn | F6: Country | I6: TCOM | L6: ADR Peers | AH6: Travel Peers
D7: Dominant Style | G7: TCOM | H7: 9961 | I7: Position | J7: % Mkt Cap | K7: SH Rank | L7: Tencent Position | M7: Tencent % Mkt Cap | N7: BABA | O7: 9988 | P7: BABA Position | Q7: BABA % Mkt Cap | R7: Meituan Position | S7: Meituan % Mkt Cap | T7: NTES | U7: 9999 | V7: NTES Position | W7: NTES % Mkt Cap | X7: PDD Position | Y7: PDD % Mkt Cap | Z7: JD | AA7: 9618 | AB7: JD Position | AC7: JD % Mkt Cap | AD7: BIDU | AE7: 9888 | AF7: BIDU Position | AG7: BIDU % Mkt Cap | AH7: ABNB Position | AI7: Avg % Mkt Cap | AJ7: BKNG Position | AK7: BKNG % Mkt Cap | AL7: EXPE Position | AM7: EXPE % Mkt Cap | AN7: MMYT Position | AO7: MMYT % Mkt Cap | AP7: TRIP Position | AQ7: TRIP % Mkt Cap | AR7: TRVG Position | AS7: TRVG % Mkt Cap | AT7: TC Position | AU7: TC % Mkt Cap
B8: 1 | C8: Norges Bank Investment Management (Norway) | D8: =VLOOKUP($C8,DATA_ALL!$A:$CU,D$5,FALSE) -> Value | E8: =VLOOKUP($C8,DATA_ALL!$A:$CU,E$5,FALSE)/1000000000 -> 1551.8473 | F8: =VLOOKUP($C8,DATA_ALL!$A:$CU,F$5,FALSE) -> Norway | G8: =IF(VLOOKUP($C8,DATA_ALL!$A:$CU,G$5,FALSE)="N/A",0,VLOOKUP($C8,DATA_ALL!$A:$CU,G$5,FALSE)) -> 11855658 | H8: =IF(VLOOKUP($C8,DATA_ALL!$A:$CU,H$5,FALSE)="N/A",0,VLOOKUP($C8,DATA_ALL!$A:$CU,H$5,FALSE)) -> 769833066 | I8: =G8+H8 -> 781688724 | J8: =I8/$J$5 -> 0.025022046 | K8: =IFERROR(INDEX('SH Summary'!B:B,MATCH(EU!C8,'SH Summary'!C:C,0)), "N/A") -> 5 | L8: =VLOOKUP($C8,DATA_ALL!$A:$CU,L$5,FALSE) -> 9440457078 | M8: =L8/M$5 -> 0.018215569 | N8: =VLOOKUP($C8,DATA_ALL!$A:$CU,N$5,FALSE) -> 594477324 | O8: =VLOOKUP($C8,DATA_ALL!$A:$CU,O$5,FALSE) -> 7249634953 | P8: =N8+O8 -> 7844112277 | Q8: =P8/Q$5 -> 0.024659265 | R8: =VLOOKUP($C8,DATA_ALL!$A:$CU,R$5,FALSE) -> 1140758383 | S8: =R8/S$5 -> 0.017610682 | T8: =VLOOKUP($C8,DATA_ALL!$A:$CU,T$5,FALSE) -> 2299905 | U8: =VLOOKUP($C8,DATA_ALL!$A:$CU,U$5,FALSE) -> 627009631 | V8: =T8+U8 -> 629309536 | W8: =V8/W$5 -> 0.0086981277 | X8: =VLOOKUP($C8,DATA_ALL!$A:$CU,X$5,FALSE) -> 1065445550 | Y8: =X8/Y$5 -> 0.0078111844 | Z8: =VLOOKUP($C8,DATA_ALL!$A:$CU,Z$5,FALSE) -> 0 | AA8: =VLOOKUP($C8,DATA_ALL!$A:$CU,AA$5,FALSE) -> 750504103 | AB8: =Z8+AA8 -> 750504103 | AC8: =AB8/AC$5 -> 0.017360724 | AD8: =VLOOKUP($C8,DATA_ALL!$A:$CU,AD$5,FALSE) -> 0 | AE8: =VLOOKUP($C8,DATA_ALL!$A:$CU,AE$5,FALSE) -> 460620666 | AF8: =AD8+AE8 -> 460620666 | AG8: =AF8/AG$5 -> 0.01000262 | AH8: =VLOOKUP($C8,DATA_ALL!$A:$CU,AH$5,FALSE) -> 480331538 | AI8: =AH8/AI$5 -> 0.0060917126 | AJ8: =VLOOKUP($C8,DATA_ALL!$A:$CU,AJ$5,FALSE) -> 3271040919 | AK8: =AJ8/AK$5 -> 0.027395653 | AL8: =VLOOKUP($C8,DATA_ALL!$A:$CU,AL$5,FALSE) -> 861979458 | AM8: =AL8/AM$5 -> 0.032988115 | AN8: =VLOOKUP($C8,DATA_ALL!$A:$CU,AN$5,FALSE) -> 90283960 | AO8: =AN8/AO$5 -> 0.021977595 | AP8: =VLOOKUP($C8,DATA_ALL!$A:$CU,AP$5,FALSE) -> 0 | AQ8: =AP8/AQ$5 -> 0 | AR8: =VLOOKUP($C8,DATA_ALL!$A:$CU,AR$5,FALSE) -> 0 | AS8: =AR8/AS$5 -> 0 | AT8: =VLOOKUP($C8,DATA_ALL!$A:$CU,AT$5,FALSE) -> 47494900 | AU8: =AT8/AU$5 -> 0.0096443223
B9: 2 | C9: BlackRock Investment Management (U.K.), LTD | D9: =VLOOKUP($C9,DATA_ALL!$A:$CU,D$5,FALSE) -> Growth | E9: =VLOOKUP($C9,DATA_ALL!$A:$CU,E$5,FALSE)/1000000000 -> 1184.4137 | F9: =VLOOKUP($C9,DATA_ALL!$A:$CU,F$5,FALSE) -> United Kingdom | G9: =IF(VLOOKUP($C9,DATA_ALL!$A:$CU,G$5,FALSE)="N/A",0,VLOOKUP($C9,DATA_ALL!$A:$CU,G$5,FALSE)) -> 26100515 | H9: =IF(VLOOKUP($C9,DATA_ALL!$A:$CU,H$5,FALSE)="N/A",0,VLOOKUP($C9,DATA_ALL!$A:$CU,H$5,FALSE)) -> 11071095 | I9: =G9+H9 -> 37171610 | J9: =I9/$J$5 -> 0.0011898723 | K9: =IFERROR(INDEX('SH Summary'!B:B,MATCH(EU!C9,'SH Summary'!C:C,0)), "N/A") -> 81 | L9: =VLOOKUP($C9,DATA_ALL!$A:$CU,L$5,FALSE) -> 131954503 | M9: =L9/M$5 -> 0.00025460911 | N9: =VLOOKUP($C9,DATA_ALL!$A:$CU,N$5,FALSE) -> 30766430 | O9: =VLOOKUP($C9,DATA_ALL!$A:$CU,O$5,FALSE) -> 373143514 | P9: =N9+O9 -> 403909944 | Q9: =P9/Q$5 -> 0.0012697578 | R9: =VLOOKUP($C9,DATA_ALL!$A:$CU,R$5,FALSE) -> 75524698 | S9: =R9/S$5 -> 0.0011659274 | T9: =VLOOKUP($C9,DATA_ALL!$A:$CU,T$5,FALSE) -> 7917628 | U9: =VLOOKUP($C9,DATA_ALL!$A:$CU,U$5,FALSE) -> 21900967 | V9: =T9+U9 -> 29818595 | W9: =V9/W$5 -> 0.00041214368 | X9: =VLOOKUP($C9,DATA_ALL!$A:$CU,X$5,FALSE) -> 1231258271 | Y9: =X9/Y$5 -> 0.0090268202 | Z9: =VLOOKUP($C9,DATA_ALL!$A:$CU,Z$5,FALSE) -> 29184289 | AA9: =VLOOKUP($C9,DATA_ALL!$A:$CU,AA$5,FALSE) -> 16856502 | AB9: =Z9+AA9 -> 46040791 | AC9: =AB9/AC$5 -> 0.0010650195 | AD9: =VLOOKUP($C9,DATA_ALL!$A:$CU,AD$5,FALSE) -> 83207342 | AE9: =VLOOKUP($C9,DATA_ALL!$A:$CU,AE$5,FALSE) -> 4781617 | AF9: =AD9+AE9 -> 87988959 | AG9: =AF9/AG$5 -> 0.0019107266 | AH9: =VLOOKUP($C9,DATA_ALL!$A:$CU,AH$5,FALSE) -> 952390753 | AI9: =AH9/AI$5 -> 0.012078513 | AJ9: =VLOOKUP($C9,DATA_ALL!$A:$CU,AJ$5,FALSE) -> 2237376679 | AK9: =AJ9/AK$5 -> 0.018738498 | AL9: =VLOOKUP($C9,DATA_ALL!$A:$CU,AL$5,FALSE) -> 473003794 | AM9: =AL9/AM$5 -> 0.018101944 | AN9: =VLOOKUP($C9,DATA_ALL!$A:$CU,AN$5,FALSE) -> 1307425 | AO9: =AN9/AO$5 -> 0.00031826315 | AP9: =VLOOKUP($C9,DATA_ALL!$A:$CU,AP$5,FALSE) -> 5700510 | AQ9: =AP9/AQ$5 -> 0.0051775749 | AR9: =VLOOKUP($C9,DATA_ALL!$A:$CU,AR$5,FALSE) -> 0 | AS9: =AR9/AS$5 -> 0 | AT9: =VLOOKUP($C9,DATA_ALL!$A:$CU,AT$5,FALSE) -> 987005 | AU9: =AT9/AU$5 -> 0.0002004214
B10: 3 | C10: Legal & General Investment Management, LTD | D10: =VLOOKUP($C10,DATA_ALL!$A:$CU,D$5,FALSE) -> Index | E10: =VLOOKUP($C10,DATA_ALL!$A:$CU,E$5,FALSE)/1000000000 -> 516.62789 | F10: =VLOOKUP($C10,DATA_ALL!$A:$CU,F$5,FALSE) -> United Kingdom | G10: =IF(VLOOKUP($C10,DATA_ALL!$A:$CU,G$5,FALSE)="N/A",0,VLOOKUP($C10,DATA_ALL!$A:$CU,G$5,FALSE)) -> 131167274 | H10: =IF(VLOOKUP($C10,DATA_ALL!$A:$CU,H$5,FALSE)="N/A",0,VLOOKUP($C10,DATA_ALL!$A:$CU,H$5,FALSE)) -> 12950287 | I10: =G10+H10 -> 144117561 | J10: =I10/$J$5 -> 0.0046132382 | K10: =IFERROR(INDEX('SH Summary'!B:B,MATCH(EU!C10,'SH Summary'!C:C,0)), "N/A") -> 24 | L10: =VLOOKUP($C10,DATA_ALL!$A:$CU,L$5,FALSE) -> 280437461 | M10: =L10/M$5 -> 0.00054111023 | N10: =VLOOKUP($C10,DATA_ALL!$A:$CU,N$5,FALSE) -> 73299629 | O10: =VLOOKUP($C10,DATA_ALL!$A:$CU,O$5,FALSE) -> 192087365 | P10: =N10+O10 -> 265386994 | Q10: =P10/Q$5 -> 0.00083428794 | R10: =VLOOKUP($C10,DATA_ALL!$A:$CU,R$5,FALSE) -> 39382633 | S10: =R10/S$5 -> 0.00060797716 | T10: =VLOOKUP($C10,DATA_ALL!$A:$CU,T$5,FALSE) -> 10830307 | U10: =VLOOKUP($C10,DATA_ALL!$A:$CU,U$5,FALSE) -> 27403168 | V10: =T10+U10 -> 38233475 | W10: =V10/W$5 -> 0.00052845162 | X10: =VLOOKUP($C10,DATA_ALL!$A:$CU,X$5,FALSE) -> 434065340 | Y10: =X10/Y$5 -> 0.0031822972 | Z10: =VLOOKUP($C10,DATA_ALL!$A:$CU,Z$5,FALSE) -> 48478211 | AA10: =VLOOKUP($C10,DATA_ALL!$A:$CU,AA$5,FALSE) -> 25868676 | AB10: =Z10+AA10 -> 74346887 | AC10: =AB10/AC$5 -> 0.0017197985 | AD10: =VLOOKUP($C10,DATA_ALL!$A:$CU,AD$5,FALSE) -> 29861340 | AE10: =VLOOKUP($C10,DATA_ALL!$A:$CU,AE$5,FALSE) -> 15311642 | AF10: =AD10+AE10 -> 45172982 | AG10: =AF10/AG$5 -> 0.00098095509 | AH10: =VLOOKUP($C10,DATA_ALL!$A:$CU,AH$5,FALSE) -> 334869557 | AI10: =AH10/AI$5 -> 0.0042469189 | AJ10: =VLOOKUP($C10,DATA_ALL!$A:$CU,AJ$5,FALSE) -> 993361849 | AK10: =AJ10/AK$5 -> 0.0083196135 | AL10: =VLOOKUP($C10,DATA_ALL!$A:$CU,AL$5,FALSE) -> 214775956 | AM10: =AL10/AM$5 -> 0.0082195161 | AN10: =VLOOKUP($C10,DATA_ALL!$A:$CU,AN$5,FALSE) -> 3330743 | AO10: =AN10/AO$5 -> 0.0008107943 | AP10: =VLOOKUP($C10,DATA_ALL!$A:$CU,AP$5,FALSE) -> 2661610 | AQ10: =AP10/AQ$5 -> 0.0024174478 | AR10: =VLOOKUP($C10,DATA_ALL!$A:$CU,AR$5,FALSE) -> 0 | AS10: =AR10/AS$5 -> 0 | AT10: =VLOOKUP($C10,DATA_ALL!$A:$CU,AT$5,FALSE) -> 2187782 | AU10: =AT10/AU$5 -> 0.00044425138
B11: 4 | C11: Amundi Asset Management S.A.S. | D11: =VLOOKUP($C11,DATA_ALL!$A:$CU,D$5,FALSE) -> Value | E11: =VLOOKUP($C11,DATA_ALL!$A:$CU,E$5,FALSE)/1000000000 -> 512.48538 | F11: =VLOOKUP($C11,DATA_ALL!$A:$CU,F$5,FALSE) -> France | G11: =IF(VLOOKUP($C11,DATA_ALL!$A:$CU,G$5,FALSE)="N/A",0,VLOOKUP($C11,DATA_ALL!$A:$CU,G$5,FALSE)) -> 22197898 | H11: =IF(VLOOKUP($C11,DATA_ALL!$A:$CU,H$5,FALSE)="N/A",0,VLOOKUP($C11,DATA_ALL!$A:$CU,H$5,FALSE)) -> 71893112 | I11: =G11+H11 -> 94091010 | J11: =I11/$J$5 -> 0.0030118761 | K11: =IFERROR(INDEX('SH Summary'!B:B,MATCH(EU!C11,'SH Summary'!C:C,0)), "N/A") -> 47 | L11: =VLOOKUP($C11,DATA_ALL!$A:$CU,L$5,FALSE) -> 640733783 | M11: =L11/M$5 -> 0.0012363099 | N11: =VLOOKUP($C11,DATA_ALL!$A:$CU,N$5,FALSE) -> 96248386 | O11: =VLOOKUP($C11,DATA_ALL!$A:$CU,O$5,FALSE) -> 416846885 | P11: =N11+O11 -> 513095271 | Q11: =P11/Q$5 -> 0.0016129999 | R11: =VLOOKUP($C11,DATA_ALL!$A:$CU,R$5,FALSE) -> 161980998 | S11: =R11/S$5 -> 0.0025006136 | T11: =VLOOKUP($C11,DATA_ALL!$A:$CU,T$5,FALSE) -> 49841423 | U11: =VLOOKUP($C11,DATA_ALL!$A:$CU,U$5,FALSE) -> 140573501 | V11: =T11+U11 -> 190414924 | W11: =V11/W$5 -> 0.002631858 | X11: =VLOOKUP($C11,DATA_ALL!$A:$CU,X$5,FALSE) -> 63201046 | Y11: =X11/Y$5 -> 0.00046335078 | Z11: =VLOOKUP($C11,DATA_ALL!$A:$CU,Z$5,FALSE) -> 4563444 | AA11: =VLOOKUP($C11,DATA_ALL!$A:$CU,AA$5,FALSE) -> 36223903 | AB11: =Z11+AA11 -> 40787347 | AC11: =AB11/AC$5 -> 0.00094349635 | AD11: =VLOOKUP($C11,DATA_ALL!$A:$CU,AD$5,FALSE) -> 783045 | AE11: =VLOOKUP($C11,DATA_ALL!$A:$CU,AE$5,FALSE) -> 78903315 | AF11: =AD11+AE11 -> 79686360 | AG11: =AF11/AG$5 -> 0.0017304313 | AH11: =VLOOKUP($C11,DATA_ALL!$A:$CU,AH$5,FALSE) -> 581835440 | AI11: =AH11/AI$5 -> 0.0073790164 | AJ11: =VLOOKUP($C11,DATA_ALL!$A:$CU,AJ$5,FALSE) -> 1317271941 | AK11: =AJ11/AK$5 -> 0.011032428 | AL11: =VLOOKUP($C11,DATA_ALL!$A:$CU,AL$5,FALSE) -> 160166759 | AM11: =AL11/AM$5 -> 0.0061296119 | AN11: =VLOOKUP($C11,DATA_ALL!$A:$CU,AN$5,FALSE) -> 45128553 | AO11: =AN11/AO$5 -> 0.010985529 | AP11: =VLOOKUP($C11,DATA_ALL!$A:$CU,AP$5,FALSE) -> 300140 | AQ11: =AP11/AQ$5 -> 0.00027260672 | AR11: =VLOOKUP($C11,DATA_ALL!$A:$CU,AR$5,FALSE) -> 0 | AS11: =AR11/AS$5 -> 0 | AT11: =VLOOKUP($C11,DATA_ALL!$A:$CU,AT$5,FALSE) -> 8754469 | AU11: =AT11/AU$5 -> 0.0017776839
B12: 5 | C12: BlackRock Advisors (U.K.), LTD | D12: =VLOOKUP($C12,DATA_ALL!$A:$CU,D$5,FALSE) -> Index | E12: =VLOOKUP($C12,DATA_ALL!$A:$CU,E$5,FALSE)/1000000000 -> 441.93474 | F12: =VLOOKUP($C12,DATA_ALL!$A:$CU,F$5,FALSE) -> United Kingdom | G12: =IF(VLOOKUP($C12,DATA_ALL!$A:$CU,G$5,FALSE)="N/A",0,VLOOKUP($C12,DATA_ALL!$A:$CU,G$5,FALSE)) -> 1259880 | H12: =IF(VLOOKUP($C12,DATA_ALL!$A:$CU,H$5,FALSE)="N/A",0,VLOOKUP($C12,DATA_ALL!$A:$CU,H$5,FALSE)) -> 325447598 | I12: =G12+H12 -> 326707478 | J12: =I12/$J$5 -> 0.010457986 | K12: =IFERROR(INDEX('SH Summary'!B:B,MATCH(EU!C12,'SH Summary'!C:C,0)), "N/A") -> 10 | L12: =VLOOKUP($C12,DATA_ALL!$A:$CU,L$5,FALSE) -> 3640060672 | M12: =L12/M$5 -> 0.0070235769 | N12: =VLOOKUP($C12,DATA_ALL!$A:$CU,N$5,FALSE) -> 4384317 | O12: =VLOOKUP($C12,DATA_ALL!$A:$CU,O$5,FALSE) -> 15906732 | P12: =N12+O12 -> 20291049 | Q12: =P12/Q$5 -> 6.3788271e-05 | R12: =VLOOKUP($C12,DATA_ALL!$A:$CU,R$5,FALSE) -> 447940 | S12: =R12/S$5 -> 6.9151621e-06 | T12: =VLOOKUP($C12,DATA_ALL!$A:$CU,T$5,FALSE) -> 0 | U12: =VLOOKUP($C12,DATA_ALL!$A:$CU,U$5,FALSE) -> 580000794 | V12: =T12+U12 -> 580000794 | W12: =V12/W$5 -> 0.008016597 | X12: =VLOOKUP($C12,DATA_ALL!$A:$CU,X$5,FALSE) -> 573639 | Y12: =X12/Y$5 -> 4.2055645e-06 | Z12: =VLOOKUP($C12,DATA_ALL!$A:$CU,Z$5,FALSE) -> 0 | AA12: =VLOOKUP($C12,DATA_ALL!$A:$CU,AA$5,FALSE) -> 458098671 | AB12: =Z12+AA12 -> 458098671 | AC12: =AB12/AC$5 -> 0.010596777 | AD12: =VLOOKUP($C12,DATA_ALL!$A:$CU,AD$5,FALSE) -> 0 | AE12: =VLOOKUP($C12,DATA_ALL!$A:$CU,AE$5,FALSE) -> 474914251 | AF12: =AD12+AE12 -> 474914251 | AG12: =AF12/AG$5 -> 0.010313013 | AH12: =VLOOKUP($C12,DATA_ALL!$A:$CU,AH$5,FALSE) -> 3035519 | AI12: =AH12/AI$5 -> 3.8497387e-05 | AJ12: =VLOOKUP($C12,DATA_ALL!$A:$CU,AJ$5,FALSE) -> 36297169 | AK12: =AJ12/AK$5 -> 0.00030399639 | AL12: =VLOOKUP($C12,DATA_ALL!$A:$CU,AL$5,FALSE) -> 1534495 | AM12: =AL12/AM$5 -> 5.8725411e-05 | AN12: =VLOOKUP($C12,DATA_ALL!$A:$CU,AN$5,FALSE) -> 1510947 | AO12: =AN12/AO$5 -> 0.00036780599 | AP12: =VLOOKUP($C12,DATA_ALL!$A:$CU,AP$5,FALSE) -> 4242919 | AQ12: =AP12/AQ$5 -> 0.0038536957 | AR12: =VLOOKUP($C12,DATA_ALL!$A:$CU,AR$5,FALSE) -> 0 | AS12: =AR12/AS$5 -> 0 | AT12: =VLOOKUP($C12,DATA_ALL!$A:$CU,AT$5,FALSE) -> 29445756 | AU12: =AT12/AU$5 -> 0.0059792601
B13: 6 | C13: UBS Asset Management Switzerland AG | D13: =VLOOKUP($C13,DATA_ALL!$A:$CU,D$5,FALSE) -> Value | E13: =VLOOKUP($C13,DATA_ALL!$A:$CU,E$5,FALSE)/1000000000 -> 333.63565 | F13: =VLOOKUP($C13,DATA_ALL!$A:$CU,F$5,FALSE) -> Switzerland | G13: =IF(VLOOKUP($C13,DATA_ALL!$A:$CU,G$5,FALSE)="N/A",0,VLOOKUP($C13,DATA_ALL!$A:$CU,G$5,FALSE)) -> 46744047 | H13: =IF(VLOOKUP($C13,DATA_ALL!$A:$CU,H$5,FALSE)="N/A",0,VLOOKUP($C13,DATA_ALL!$A:$CU,H$5,FALSE)) -> 89574094 | I13: =G13+H13 -> 136318141 | J13: =I13/$J$5 -> 0.0043635769 | K13: =IFERROR(INDEX('SH Summary'!B:B,MATCH(EU!C13,'SH Summary'!C:C,0)), "N/A") -> 28 | L13: =VLOOKUP($C13,DATA_ALL!$A:$CU,L$5,FALSE) -> 1061297040 | M13: =L13/M$5 -> 0.0020477959 | N13: =VLOOKUP($C13,DATA_ALL!$A:$CU,N$5,FALSE) -> 285579831 | O13: =VLOOKUP($C13,DATA_ALL!$A:$CU,O$5,FALSE) -> 736071622 | P13: =N13+O13 -> 1021651453 | Q13: =P13/Q$5 -> 0.0032117304 | R13: =VLOOKUP($C13,DATA_ALL!$A:$CU,R$5,FALSE) -> 76096355 | S13: =R13/S$5 -> 0.0011747525 | T13: =VLOOKUP($C13,DATA_ALL!$A:$CU,T$5,FALSE) -> 436049397 | U13: =VLOOKUP($C13,DATA_ALL!$A:$CU,U$5,FALSE) -> 109561441 | V13: =T13+U13 -> 545610838 | W13: =V13/W$5 -> 0.0075412694 | X13: =VLOOKUP($C13,DATA_ALL!$A:$CU,X$5,FALSE) -> 338721591 | Y13: =X13/Y$5 -> 0.0024832961 | Z13: =VLOOKUP($C13,DATA_ALL!$A:$CU,Z$5,FALSE) -> 0 | AA13: =VLOOKUP($C13,DATA_ALL!$A:$CU,AA$5,FALSE) -> 88448162 | AB13: =Z13+AA13 -> 88448162 | AC13: =AB13/AC$5 -> 0.0020459903 | AD13: =VLOOKUP($C13,DATA_ALL!$A:$CU,AD$5,FALSE) -> 0 | AE13: =VLOOKUP($C13,DATA_ALL!$A:$CU,AE$5,FALSE) -> 86816788 | AF13: =AD13+AE13 -> 86816788 | AG13: =AF13/AG$5 -> 0.0018852723 | AH13: =VLOOKUP($C13,DATA_ALL!$A:$CU,AH$5,FALSE) -> 109735552 | AI13: =AH13/AI$5 -> 0.0013917001 | AJ13: =VLOOKUP($C13,DATA_ALL!$A:$CU,AJ$5,FALSE) -> 363822172 | AK13: =AJ13/AK$5 -> 0.0030470869 | AL13: =VLOOKUP($C13,DATA_ALL!$A:$CU,AL$5,FALSE) -> 50389664 | AM13: =AL13/AM$5 -> 0.0019284219 | AN13: =VLOOKUP($C13,DATA_ALL!$A:$CU,AN$5,FALSE) -> 0 | AO13: =AN13/AO$5 -> 0 | AP13: =VLOOKUP($C13,DATA_ALL!$A:$CU,AP$5,FALSE) -> 1706282 | AQ13: =AP13/AQ$5 -> 0.0015497566 | AR13: =VLOOKUP($C13,DATA_ALL!$A:$CU,AR$5,FALSE) -> 0 | AS13: =AR13/AS$5 -> 0 | AT13: =VLOOKUP($C13,DATA_ALL!$A:$CU,AT$5,FALSE) -> 7458410 | AU13: =AT13/AU$5 -> 0.001514506
B14: 7 | C14: UBS Asset Management (U.K.), LTD | D14: =VLOOKUP($C14,DATA_ALL!$A:$CU,D$5,FALSE) -> Index | E14: =VLOOKUP($C14,DATA_ALL!$A:$CU,E$5,FALSE)/1000000000 -> 236.70685 | F14: =VLOOKUP($C14,DATA_ALL!$A:$CU,F$5,FALSE) -> United Kingdom | G14: =IF(VLOOKUP($C14,DATA_ALL!$A:$CU,G$5,FALSE)="N/A",0,VLOOKUP($C14,DATA_ALL!$A:$CU,G$5,FALSE)) -> 4670949 | H14: =IF(VLOOKUP($C14,DATA_ALL!$A:$CU,H$5,FALSE)="N/A",0,VLOOKUP($C14,DATA_ALL!$A:$CU,H$5,FALSE)) -> 29636561 | I14: =G14+H14 -> 34307510 | J14: =I14/$J$5 -> 0.0010981917 | K14: =IFERROR(INDEX('SH Summary'!B:B,MATCH(EU!C14,'SH Summary'!C:C,0)), "N/A") -> 88 | L14: =VLOOKUP($C14,DATA_ALL!$A:$CU,L$5,FALSE) -> 353268239 | M14: =L14/M$5 -> 0.00068163882 | N14: =VLOOKUP($C14,DATA_ALL!$A:$CU,N$5,FALSE) -> 54781356 | O14: =VLOOKUP($C14,DATA_ALL!$A:$CU,O$5,FALSE) -> 276106600 | P14: =N14+O14 -> 330887956 | Q14: =P14/Q$5 -> 0.0010402011 | R14: =VLOOKUP($C14,DATA_ALL!$A:$CU,R$5,FALSE) -> 156308438 | S14: =R14/S$5 -> 0.0024130423 | T14: =VLOOKUP($C14,DATA_ALL!$A:$CU,T$5,FALSE) -> 25019821 | U14: =VLOOKUP($C14,DATA_ALL!$A:$CU,U$5,FALSE) -> 118808130 | V14: =T14+U14 -> 143827951 | W14: =V14/W$5 -> 0.0019879468 | X14: =VLOOKUP($C14,DATA_ALL!$A:$CU,X$5,FALSE) -> 135083288 | Y14: =X14/Y$5 -> 0.00099034669 | Z14: =VLOOKUP($C14,DATA_ALL!$A:$CU,Z$5,FALSE) -> 0 | AA14: =VLOOKUP($C14,DATA_ALL!$A:$CU,AA$5,FALSE) -> 82365576 | AB14: =Z14+AA14 -> 82365576 | AC14: =AB14/AC$5 -> 0.0019052874 | AD14: =VLOOKUP($C14,DATA_ALL!$A:$CU,AD$5,FALSE) -> 0 | AE14: =VLOOKUP($C14,DATA_ALL!$A:$CU,AE$5,FALSE) -> 58399950 | AF14: =AD14+AE14 -> 58399950 | AG14: =AF14/AG$5 -> 0.0012681857 | AH14: =VLOOKUP($C14,DATA_ALL!$A:$CU,AH$5,FALSE) -> 222019561 | AI14: =AH14/AI$5 -> 0.0028157205 | AJ14: =VLOOKUP($C14,DATA_ALL!$A:$CU,AJ$5,FALSE) -> 450213728 | AK14: =AJ14/AK$5 -> 0.0037706342 | AL14: =VLOOKUP($C14,DATA_ALL!$A:$CU,AL$5,FALSE) -> 59674213 | AM14: =AL14/AM$5 -> 0.0022837433 | AN14: =VLOOKUP($C14,DATA_ALL!$A:$CU,AN$5,FALSE) -> 0 | AO14: =AN14/AO$5 -> 0 | AP14: =VLOOKUP($C14,DATA_ALL!$A:$CU,AP$5,FALSE) -> 283823 | AQ14: =AP14/AQ$5 -> 0.00025778656 | AR14: =VLOOKUP($C14,DATA_ALL!$A:$CU,AR$5,FALSE) -> 0 | AS14: =AR14/AS$5 -> 0 | AT14: =VLOOKUP($C14,DATA_ALL!$A:$CU,AT$5,FALSE) -> 6924775 | AU14: =AT14/AU$5 -> 0.001406146
B15: 8 | C15: HSBC Global Asset Management (UK), LTD | D15: =VLOOKUP($C15,DATA_ALL!$A:$CU,D$5,FALSE) -> Growth | E15: =VLOOKUP($C15,DATA_ALL!$A:$CU,E$5,FALSE)/1000000000 -> 233.90518 | F15: =VLOOKUP($C15,DATA_ALL!$A:$CU,F$5,FALSE) -> United Kingdom | G15: =IF(VLOOKUP($C15,DATA_ALL!$A:$CU,G$5,FALSE)="N/A",0,VLOOKUP($C15,DATA_ALL!$A:$CU,G$5,FALSE)) -> 6483803 | H15: =IF(VLOOKUP($C15,DATA_ALL!$A:$CU,H$5,FALSE)="N/A",0,VLOOKUP($C15,DATA_ALL!$A:$CU,H$5,FALSE)) -> 84211010 | I15: =G15+H15 -> 90694813 | J15: =I15/$J$5 -> 0.002903163 | K15: =IFERROR(INDEX('SH Summary'!B:B,MATCH(EU!C15,'SH Summary'!C:C,0)), "N/A") -> 40 | L15: =VLOOKUP($C15,DATA_ALL!$A:$CU,L$5,FALSE) -> 593867401 | M15: =L15/M$5 -> 0.0011458802 | N15: =VLOOKUP($C15,DATA_ALL!$A:$CU,N$5,FALSE) -> 402194399 | O15: =VLOOKUP($C15,DATA_ALL!$A:$CU,O$5,FALSE) -> 513614585 | P15: =N15+O15 -> 915808984 | Q15: =P15/Q$5 -> 0.0028789971 | R15: =VLOOKUP($C15,DATA_ALL!$A:$CU,R$5,FALSE) -> 229443725 | S15: =R15/S$5 -> 0.0035420827 | T15: =VLOOKUP($C15,DATA_ALL!$A:$CU,T$5,FALSE) -> 1254847 | U15: =VLOOKUP($C15,DATA_ALL!$A:$CU,U$5,FALSE) -> 178009635 | V15: =T15+U15 -> 179264482 | W15: =V15/W$5 -> 0.0024777399 | X15: =VLOOKUP($C15,DATA_ALL!$A:$CU,X$5,FALSE) -> 154890575 | Y15: =X15/Y$5 -> 0.0011355614 | Z15: =VLOOKUP($C15,DATA_ALL!$A:$CU,Z$5,FALSE) -> 4996443 | AA15: =VLOOKUP($C15,DATA_ALL!$A:$CU,AA$5,FALSE) -> 140758240 | AB15: =Z15+AA15 -> 145754683 | AC15: =AB15/AC$5 -> 0.0033716096 | AD15: =VLOOKUP($C15,DATA_ALL!$A:$CU,AD$5,FALSE) -> 10903895 | AE15: =VLOOKUP($C15,DATA_ALL!$A:$CU,AE$5,FALSE) -> 121750979 | AF15: =AD15+AE15 -> 132654874 | AG15: =AF15/AG$5 -> 0.0028806704 | AH15: =VLOOKUP($C15,DATA_ALL!$A:$CU,AH$5,FALSE) -> 105818852 | AI15: =AH15/AI$5 -> 0.0013420273 | AJ15: =VLOOKUP($C15,DATA_ALL!$A:$CU,AJ$5,FALSE) -> 672320739 | AK15: =AJ15/AK$5 -> 0.005630827 | AL15: =VLOOKUP($C15,DATA_ALL!$A:$CU,AL$5,FALSE) -> 60206646 | AM15: =AL15/AM$5 -> 0.0023041196 | AN15: =VLOOKUP($C15,DATA_ALL!$A:$CU,AN$5,FALSE) -> 3729 | AO15: =AN15/AO$5 -> 9.0774099e-07 | AP15: =VLOOKUP($C15,DATA_ALL!$A:$CU,AP$5,FALSE) -> 0 | AQ15: =AP15/AQ$5 -> 0 | AR15: =VLOOKUP($C15,DATA_ALL!$A:$CU,AR$5,FALSE) -> 0 | AS15: =AR15/AS$5 -> 0 | AT15: =VLOOKUP($C15,DATA_ALL!$A:$CU,AT$5,FALSE) -> 14808008 | AU15: =AT15/AU$5 -> 0.0030069166
B16: 9 | C16: Schroder Investment Management, LTD | D16: =VLOOKUP($C16,DATA_ALL!$A:$CU,D$5,FALSE) -> GARP | E16: =VLOOKUP($C16,DATA_ALL!$A:$CU,E$5,FALSE)/1000000000 -> 204.64998 | F16: =VLOOKUP($C16,DATA_ALL!$A:$CU,F$5,FALSE) -> United Kingdom | G16: =IF(VLOOKUP($C16,DATA_ALL!$A:$CU,G$5,FALSE)="N/A",0,VLOOKUP($C16,DATA_ALL!$A:$CU,G$5,FALSE)) -> 4332 | H16: =IF(VLOOKUP($C16,DATA_ALL!$A:$CU,H$5,FALSE)="N/A",0,VLOOKUP($C16,DATA_ALL!$A:$CU,H$5,FALSE)) -> 65893835 | I16: =G16+H16 -> 65898167 | J16: =I16/$J$5 -> 0.0021094164 | K16: =IFERROR(INDEX('SH Summary'!B:B,MATCH(EU!C16,'SH Summary'!C:C,0)), "N/A") -> 51 | L16: =VLOOKUP($C16,DATA_ALL!$A:$CU,L$5,FALSE) -> 1799050778 | M16: =L16/M$5 -> 0.0034713079 | N16: =VLOOKUP($C16,DATA_ALL!$A:$CU,N$5,FALSE) -> 18078911 | O16: =VLOOKUP($C16,DATA_ALL!$A:$CU,O$5,FALSE) -> 459437910 | P16: =N16+O16 -> 477516821 | Q16: =P16/Q$5 -> 0.0015011532 | R16: =VLOOKUP($C16,DATA_ALL!$A:$CU,R$5,FALSE) -> 30999278 | S16: =R16/S$5 -> 0.00047855747 | T16: =VLOOKUP($C16,DATA_ALL!$A:$CU,T$5,FALSE) -> 2712306 | U16: =VLOOKUP($C16,DATA_ALL!$A:$CU,U$5,FALSE) -> 266087142 | V16: =T16+U16 -> 268799448 | W16: =V16/W$5 -> 0.0037152653 | X16: =VLOOKUP($C16,DATA_ALL!$A:$CU,X$5,FALSE) -> 119142084 | Y16: =X16/Y$5 -> 0.00087347569 | Z16: =VLOOKUP($C16,DATA_ALL!$A:$CU,Z$5,FALSE) -> 2204059 | AA16: =VLOOKUP($C16,DATA_ALL!$A:$CU,AA$5,FALSE) -> 3129577 | AB16: =Z16+AA16 -> 5333636 | AC16: =AB16/AC$5 -> 0.00012337812 | AD16: =VLOOKUP($C16,DATA_ALL!$A:$CU,AD$5,FALSE) -> 0 | AE16: =VLOOKUP($C16,DATA_ALL!$A:$CU,AE$5,FALSE) -> 65234590 | AF16: =AD16+AE16 -> 65234590 | AG16: =AF16/AG$5 -> 0.0014166035 | AH16: =VLOOKUP($C16,DATA_ALL!$A:$CU,AH$5,FALSE) -> 8784416 | AI16: =AH16/AI$5 -> 0.00011140667 | AJ16: =VLOOKUP($C16,DATA_ALL!$A:$CU,AJ$5,FALSE) -> 466777127 | AK16: =AJ16/AK$5 -> 0.0039093562 | AL16: =VLOOKUP($C16,DATA_ALL!$A:$CU,AL$5,FALSE) -> 13589955 | AM16: =AL16/AM$5 -> 0.00052009013 | AN16: =VLOOKUP($C16,DATA_ALL!$A:$CU,AN$5,FALSE) -> 107872102 | AO16: =AN16/AO$5 -> 0.026259032 | AP16: =VLOOKUP($C16,DATA_ALL!$A:$CU,AP$5,FALSE) -> 0 | AQ16: =AP16/AQ$5 -> 0 | AR16: =VLOOKUP($C16,DATA_ALL!$A:$CU,AR$5,FALSE) -> 0 | AS16: =AR16/AS$5 -> 0 | AT16: =VLOOKUP($C16,DATA_ALL!$A:$CU,AT$5,FALSE) -> 848107 | AU16: =AT16/AU$5 -> 0.00017221675
B17: 10 | C17: State Street Global Advisors, LTD | D17: =VLOOKUP($C17,DATA_ALL!$A:$CU,D$5,FALSE) -> Index | E17: =VLOOKUP($C17,DATA_ALL!$A:$CU,E$5,FALSE)/1000000000 -> 198.43786 | F17: =VLOOKUP($C17,DATA_ALL!$A:$CU,F$5,FALSE) -> United Kingdom | G17: =IF(VLOOKUP($C17,DATA_ALL!$A:$CU,G$5,FALSE)="N/A",0,VLOOKUP($C17,DATA_ALL!$A:$CU,G$5,FALSE)) -> 0 | H17: =IF(VLOOKUP($C17,DATA_ALL!$A:$CU,H$5,FALSE)="N/A",0,VLOOKUP($C17,DATA_ALL!$A:$CU,H$5,FALSE)) -> 93490582 | I17: =G17+H17 -> 93490582 | J17: =I17/$J$5 -> 0.0029926563 | K17: =IFERROR(INDEX('SH Summary'!B:B,MATCH(EU!C17,'SH Summary'!C:C,0)), "N/A") -> 43 | L17: =VLOOKUP($C17,DATA_ALL!$A:$CU,L$5,FALSE) -> 662894856 | M17: =L17/M$5 -> 0.0012790702 | N17: =VLOOKUP($C17,DATA_ALL!$A:$CU,N$5,FALSE) -> 0 | O17: =VLOOKUP($C17,DATA_ALL!$A:$CU,O$5,FALSE) -> 684508314 | P17: =N17+O17 -> 684508314 | Q17: =P17/Q$5 -> 0.0021518652 | R17: =VLOOKUP($C17,DATA_ALL!$A:$CU,R$5,FALSE) -> 135649407 | S17: =R17/S$5 -> 0.0020941145 | T17: =VLOOKUP($C17,DATA_ALL!$A:$CU,T$5,FALSE) -> 0 | U17: =VLOOKUP($C17,DATA_ALL!$A:$CU,U$5,FALSE) -> 157880272 | V17: =T17+U17 -> 157880272 | W17: =V17/W$5 -> 0.0021821738 | X17: =VLOOKUP($C17,DATA_ALL!$A:$CU,X$5,FALSE) -> 170288602 | Y17: =X17/Y$5 -> 0.0012484502 | Z17: =VLOOKUP($C17,DATA_ALL!$A:$CU,Z$5,FALSE) -> 148 | AA17: =VLOOKUP($C17,DATA_ALL!$A:$CU,AA$5,FALSE) -> 116878582 | AB17: =Z17+AA17 -> 116878730 | AC17: =AB17/AC$5 -> 0.0027036486 | AD17: =VLOOKUP($C17,DATA_ALL!$A:$CU,AD$5,FALSE) -> 0 | AE17: =VLOOKUP($C17,DATA_ALL!$A:$CU,AE$5,FALSE) -> 36683615 | AF17: =AD17+AE17 -> 36683615 | AG17: =AF17/AG$5 -> 0.00079660402 | AH17: =VLOOKUP($C17,DATA_ALL!$A:$CU,AH$5,FALSE) -> 88692050 | AI17: =AH17/AI$5 -> 0.0011248199 | AJ17: =VLOOKUP($C17,DATA_ALL!$A:$CU,AJ$5,FALSE) -> 366373951 | AK17: =AJ17/AK$5 -> 0.0030684586 | AL17: =VLOOKUP($C17,DATA_ALL!$A:$CU,AL$5,FALSE) -> 112598088 | AM17: =AL17/AM$5 -> 0.0043091499 | AN17: =VLOOKUP($C17,DATA_ALL!$A:$CU,AN$5,FALSE) -> 0 | AO17: =AN17/AO$5 -> 0 | AP17: =VLOOKUP($C17,DATA_ALL!$A:$CU,AP$5,FALSE) -> 2177117 | AQ17: =AP17/AQ$5 -> 0.0019773996 | AR17: =VLOOKUP($C17,DATA_ALL!$A:$CU,AR$5,FALSE) -> 0 | AS17: =AR17/AS$5 -> 0 | AT17: =VLOOKUP($C17,DATA_ALL!$A:$CU,AT$5,FALSE) -> 9541815 | AU17: =AT17/AU$5 -> 0.0019375625
B18: 11 | C18: DWS Investments UK, LTD | D18: =VLOOKUP($C18,DATA_ALL!$A:$CU,D$5,FALSE) -> Index | E18: =VLOOKUP($C18,DATA_ALL!$A:$CU,E$5,FALSE)/1000000000 -> 191.31739 | F18: =VLOOKUP($C18,DATA_ALL!$A:$CU,F$5,FALSE) -> United Kingdom | G18: =IF(VLOOKUP($C18,DATA_ALL!$A:$CU,G$5,FALSE)="N/A",0,VLOOKUP($C18,DATA_ALL!$A:$CU,G$5,FALSE)) -> 0 | H18: =IF(VLOOKUP($C18,DATA_ALL!$A:$CU,H$5,FALSE)="N/A",0,VLOOKUP($C18,DATA_ALL!$A:$CU,H$5,FALSE)) -> 31784199 | I18: =G18+H18 -> 31784199 | J18: =I18/$J$5 -> 0.0010174199 | K18: =IFERROR(INDEX('SH Summary'!B:B,MATCH(EU!C18,'SH Summary'!C:C,0)), "N/A") -> 91 | L18: =VLOOKUP($C18,DATA_ALL!$A:$CU,L$5,FALSE) -> 414689073 | M18: =L18/M$5 -> 0.00080015166 | N18: =VLOOKUP($C18,DATA_ALL!$A:$CU,N$5,FALSE) -> 252486494 | O18: =VLOOKUP($C18,DATA_ALL!$A:$CU,O$5,FALSE) -> 274687591 | P18: =N18+O18 -> 527174085 | Q18: =P18/Q$5 -> 0.001657259 | R18: =VLOOKUP($C18,DATA_ALL!$A:$CU,R$5,FALSE) -> 55471698 | S18: =R18/S$5 -> 0.00085635527 | T18: =VLOOKUP($C18,DATA_ALL!$A:$CU,T$5,FALSE) -> 140821 | U18: =VLOOKUP($C18,DATA_ALL!$A:$CU,U$5,FALSE) -> 39770902 | V18: =T18+U18 -> 39911723 | W18: =V18/W$5 -> 0.00055164786 | X18: =VLOOKUP($C18,DATA_ALL!$A:$CU,X$5,FALSE) -> 169865156 | Y18: =X18/Y$5 -> 0.0012453457 | Z18: =VLOOKUP($C18,DATA_ALL!$A:$CU,Z$5,FALSE) -> 240256 | AA18: =VLOOKUP($C18,DATA_ALL!$A:$CU,AA$5,FALSE) -> 36365431 | AB18: =Z18+AA18 -> 36605687 | AC18: =AB18/AC$5 -> 0.00084676583 | AD18: =VLOOKUP($C18,DATA_ALL!$A:$CU,AD$5,FALSE) -> 284121 | AE18: =VLOOKUP($C18,DATA_ALL!$A:$CU,AE$5,FALSE) -> 31555021 | AF18: =AD18+AE18 -> 31839142 | AG18: =AF18/AG$5 -> 0.00069140374 | AH18: =VLOOKUP($C18,DATA_ALL!$A:$CU,AH$5,FALSE) -> 144366958 | AI18: =AH18/AI$5 -> 0.0018309063 | AJ18: =VLOOKUP($C18,DATA_ALL!$A:$CU,AJ$5,FALSE) -> 216839901 | AK18: =AJ18/AK$5 -> 0.0018160796 | AL18: =VLOOKUP($C18,DATA_ALL!$A:$CU,AL$5,FALSE) -> 60404518 | AM18: =AL18/AM$5 -> 0.0023116922 | AN18: =VLOOKUP($C18,DATA_ALL!$A:$CU,AN$5,FALSE) -> 0 | AO18: =AN18/AO$5 -> 0 | AP18: =VLOOKUP($C18,DATA_ALL!$A:$CU,AP$5,FALSE) -> 1083856 | AQ18: =AP18/AQ$5 -> 0.0009844287 | AR18: =VLOOKUP($C18,DATA_ALL!$A:$CU,AR$5,FALSE) -> 0 | AS18: =AR18/AS$5 -> 0 | AT18: =VLOOKUP($C18,DATA_ALL!$A:$CU,AT$5,FALSE) -> 3111663 | AU18: =AT18/AU$5 -> 0.00063185481
B19: 12 | C19: DWS Investment GmbH | D19: =VLOOKUP($C19,DATA_ALL!$A:$CU,D$5,FALSE) -> Value | E19: =VLOOKUP($C19,DATA_ALL!$A:$CU,E$5,FALSE)/1000000000 -> 186.60325 | F19: =VLOOKUP($C19,DATA_ALL!$A:$CU,F$5,FALSE) -> Germany | G19: =IF(VLOOKUP($C19,DATA_ALL!$A:$CU,G$5,FALSE)="N/A",0,VLOOKUP($C19,DATA_ALL!$A:$CU,G$5,FALSE)) -> 0 | H19: =IF(VLOOKUP($C19,DATA_ALL!$A:$CU,H$5,FALSE)="N/A",0,VLOOKUP($C19,DATA_ALL!$A:$CU,H$5,FALSE)) -> 101781466 | I19: =G19+H19 -> 101781466 | J19: =I19/$J$5 -> 0.0032580495 | K19: =IFERROR(INDEX('SH Summary'!B:B,MATCH(EU!C19,'SH Summary'!C:C,0)), "N/A") -> 38 | L19: =VLOOKUP($C19,DATA_ALL!$A:$CU,L$5,FALSE) -> 639402926 | M19: =L19/M$5 -> 0.001233742 | N19: =VLOOKUP($C19,DATA_ALL!$A:$CU,N$5,FALSE) -> 10901094 | O19: =VLOOKUP($C19,DATA_ALL!$A:$CU,O$5,FALSE) -> 390932222 | P19: =N19+O19 -> 401833316 | Q19: =P19/Q$5 -> 0.0012632295 | R19: =VLOOKUP($C19,DATA_ALL!$A:$CU,R$5,FALSE) -> 52270441 | S19: =R19/S$5 -> 0.00080693524 | T19: =VLOOKUP($C19,DATA_ALL!$A:$CU,T$5,FALSE) -> 0 | U19: =VLOOKUP($C19,DATA_ALL!$A:$CU,U$5,FALSE) -> 71020285 | V19: =T19+U19 -> 71020285 | W19: =V19/W$5 -> 0.00098162108 | X19: =VLOOKUP($C19,DATA_ALL!$A:$CU,X$5,FALSE) -> 6701782 | Y19: =X19/Y$5 -> 4.9133299e-05 | Z19: =VLOOKUP($C19,DATA_ALL!$A:$CU,Z$5,FALSE) -> 0 | AA19: =VLOOKUP($C19,DATA_ALL!$A:$CU,AA$5,FALSE) -> 29794174 | AB19: =Z19+AA19 -> 29794174 | AC19: =AB19/AC$5 -> 0.00068920134 | AD19: =VLOOKUP($C19,DATA_ALL!$A:$CU,AD$5,FALSE) -> 0 | AE19: =VLOOKUP($C19,DATA_ALL!$A:$CU,AE$5,FALSE) -> 26623226 | AF19: =AD19+AE19 -> 26623226 | AG19: =AF19/AG$5 -> 0.00057813737 | AH19: =VLOOKUP($C19,DATA_ALL!$A:$CU,AH$5,FALSE) -> 22566994 | AI19: =AH19/AI$5 -> 0.00028620157 | AJ19: =VLOOKUP($C19,DATA_ALL!$A:$CU,AJ$5,FALSE) -> 1108589887 | AK19: =AJ19/AK$5 -> 0.0092846724 | AL19: =VLOOKUP($C19,DATA_ALL!$A:$CU,AL$5,FALSE) -> 31274743 | AM19: =AL19/AM$5 -> 0.0011968903 | AN19: =VLOOKUP($C19,DATA_ALL!$A:$CU,AN$5,FALSE) -> 2147680 | AO19: =AN19/AO$5 -> 0.00052280428 | AP19: =VLOOKUP($C19,DATA_ALL!$A:$CU,AP$5,FALSE) -> 408 | AQ19: =AP19/AQ$5 -> 3.7057221e-07 | AR19: =VLOOKUP($C19,DATA_ALL!$A:$CU,AR$5,FALSE) -> 0 | AS19: =AR19/AS$5 -> 0 | AT19: =VLOOKUP($C19,DATA_ALL!$A:$CU,AT$5,FALSE) -> 2621385 | AU19: =AT19/AU$5 -> 0.00053229887
... B59: 52 | C59: BlackRock Asset Management Ireland, LTD | D59: =VLOOKUP($C59,DATA_ALL!$A:$CU,D$5,FALSE) -> Other | E59: =VLOOKUP($C59,DATA_ALL!$A:$CU,E$5,FALSE)/1000000000 -> 50.560085 | F59: =VLOOKUP($C59,DATA_ALL!$A:$CU,F$5,FALSE) -> Ireland | G59: =IF(VLOOKUP($C59,DATA_ALL!$A:$CU,G$5,FALSE)="N/A",0,VLOOKUP($C59,DATA_ALL!$A:$CU,G$5,FALSE)) -> 0 | H59: =IF(VLOOKUP($C59,DATA_ALL!$A:$CU,H$5,FALSE)="N/A",0,VLOOKUP($C59,DATA_ALL!$A:$CU,H$5,FALSE)) -> 0 | I59: =G59+H59 -> 0 | J59: =I59/$J$5 -> 0 | K59: =IFERROR(INDEX('SH Summary'!B:B,MATCH(EU!C59,'SH Summary'!C:C,0)), "N/A") -> N/A | L59: =VLOOKUP($C59,DATA_ALL!$A:$CU,L$5,FALSE) -> 0 | M59: =L59/M$5 -> 0 | N59: =VLOOKUP($C59,DATA_ALL!$A:$CU,N$5,FALSE) -> 0 | O59: =VLOOKUP($C59,DATA_ALL!$A:$CU,O$5,FALSE) -> 2745021667 | P59: =N59+O59 -> 2745021667 | Q59: =P59/Q$5 -> 0.0086294299 | R59: =VLOOKUP($C59,DATA_ALL!$A:$CU,R$5,FALSE) -> 783992907 | S59: =R59/S$5 -> 0.012103045 | T59: =VLOOKUP($C59,DATA_ALL!$A:$CU,T$5,FALSE) -> 0 | U59: =VLOOKUP($C59,DATA_ALL!$A:$CU,U$5,FALSE) -> 0 | V59: =T59+U59 -> 0 | W59: =V59/W$5 -> 0 | X59: =VLOOKUP($C59,DATA_ALL!$A:$CU,X$5,FALSE) -> 0 | Y59: =X59/Y$5 -> 0 | Z59: =VLOOKUP($C59,DATA_ALL!$A:$CU,Z$5,FALSE) -> 0 | AA59: =VLOOKUP($C59,DATA_ALL!$A:$CU,AA$5,FALSE) -> 0 | AB59: =Z59+AA59 -> 0 | AC59: =AB59/AC$5 -> 0 | AD59: =VLOOKUP($C59,DATA_ALL!$A:$CU,AD$5,FALSE) -> 0 | AE59: =VLOOKUP($C59,DATA_ALL!$A:$CU,AE$5,FALSE) -> 0 | AF59: =AD59+AE59 -> 0 | AG59: =AF59/AG$5 -> 0 | AH59: =VLOOKUP($C59,DATA_ALL!$A:$CU,AH$5,FALSE) -> 0 | AI59: =AH59/AI$5 -> 0 | AJ59: =VLOOKUP($C59,DATA_ALL!$A:$CU,AJ$5,FALSE) -> 0 | AK59: =AJ59/AK$5 -> 0 | AL59: =VLOOKUP($C59,DATA_ALL!$A:$CU,AL$5,FALSE) -> 0 | AM59: =AL59/AM$5 -> 0 | AN59: =VLOOKUP($C59,DATA_ALL!$A:$CU,AN$5,FALSE) -> 0 | AO59: =AN59/AO$5 -> 0 | AP59: =VLOOKUP($C59,DATA_ALL!$A:$CU,AP$5,FALSE) -> 0 | AQ59: =AP59/AQ$5 -> 0 | AR59: =VLOOKUP($C59,DATA_ALL!$A:$CU,AR$5,FALSE) -> 0 | AS59: =AR59/AS$5 -> 0 | AT59: =VLOOKUP($C59,DATA_ALL!$A:$CU,AT$5,FALSE) -> 0 | AU59: =AT59/AU$5 -> 0

Sheet APAC
B2: APAC Top Investors
B3: As of 2026Q1, AUM > $50bn
D5: 85 | E5: 90 | F5: 89 | G5: 7 | H5: 9 | J5: 31240000000 | L5: 11 | M5: =4058000000000/7.83 -> 5.1826309e+11 | N5: 13 | O5: 15 | Q5: 318100000000 | R5: 18 | S5: =507200000000/7.83 -> 6.4776501e+10 | T5: 20 | U5: 22 | W5: 72350000000 | X5: 24 | Y5: 136400000000 | Z5: 26 | AA5: 28 | AC5: 43230000000 | AD5: 30 | AE5: 32 | AG5: 46050000000 | AH5: 34 | AI5: 78850000000 | AJ5: 40 | AK5: 119400000000 | AL5: 42 | AM5: 26130000000 | AN5: 44 | AO5: 4108000000 | AP5: 46 | AQ5: 1101000000 | AR5: 48 | AS5: 217100000 | AT5: 50 | AU5: =38560000000/7.83 -> 4.9246488e+09
C6: Institution/Fund Name | D6: Dominant Style | E6: Equity AUM, $bn | F6: Country | I6: TCOM | L6: ADR Peers | AH6: Travel Peers
D7: Dominant Style | G7: TCOM | H7: 9961 | I7: Position | J7: % Mkt Cap | K7: SH Rank | L7: Tencent Position | M7: Tencent % Mkt Cap | N7: BABA | O7: 9988 | P7: BABA Position | Q7: BABA % Mkt Cap | R7: Meituan Position | S7: Meituan % Mkt Cap | T7: NTES | U7: 9999 | V7: NTES Position | W7: NTES % Mkt Cap | X7: PDD Position | Y7: PDD % Mkt Cap | Z7: JD | AA7: 9618 | AB7: JD Position | AC7: JD % Mkt Cap | AD7: BIDU | AE7: 9888 | AF7: BIDU Position | AG7: BIDU % Mkt Cap | AH7: ABNB Position | AI7: Avg % Mkt Cap | AJ7: BKNG Position | AK7: BKNG % Mkt Cap | AL7: EXPE Position | AM7: EXPE % Mkt Cap | AN7: MMYT Position | AO7: MMYT % Mkt Cap | AP7: TRIP Position | AQ7: TRIP % Mkt Cap | AR7: TRVG Position | AS7: TRVG % Mkt Cap | AT7: TC Position | AU7: TC % Mkt Cap
B8: 1 | C8: Nomura Asset Management Company, LTD | D8: =VLOOKUP($C8,DATA_ALL!$A:$CU,D$5,FALSE) -> Deep Value | E8: =VLOOKUP($C8,DATA_ALL!$A:$CU,E$5,FALSE)/1000000000 -> 392.47262 | F8: =VLOOKUP($C8,DATA_ALL!$A:$CU,F$5,FALSE) -> Japan | G8: =IF(VLOOKUP($C8,DATA_ALL!$A:$CU,G$5,FALSE)="N/A",0,VLOOKUP($C8,DATA_ALL!$A:$CU,G$5,FALSE)) -> 1522656 | H8: =IF(VLOOKUP($C8,DATA_ALL!$A:$CU,H$5,FALSE)="N/A",0,VLOOKUP($C8,DATA_ALL!$A:$CU,H$5,FALSE)) -> 2555499 | I8: =G8+H8 -> 4078155 | J8: =I8/$J$5 -> 0.00013054273 | K8: =IFERROR(INDEX('SH Summary'!B:B,MATCH(APAC!C8,'SH Summary'!C:C,0)), "N/A") -> 266 | L8: =VLOOKUP($C8,DATA_ALL!$A:$CU,L$5,FALSE) -> 40449568 | M8: =L8/M$5 -> 7.8048329e-05 | N8: =VLOOKUP($C8,DATA_ALL!$A:$CU,N$5,FALSE) -> 0 | O8: =VLOOKUP($C8,DATA_ALL!$A:$CU,O$5,FALSE) -> 19689423 | P8: =N8+O8 -> 19689423 | Q8: =P8/Q$5 -> 6.189696e-05 | R8: =VLOOKUP($C8,DATA_ALL!$A:$CU,R$5,FALSE) -> 10196953 | S8: =R8/S$5 -> 0.00015741747 | T8: =VLOOKUP($C8,DATA_ALL!$A:$CU,T$5,FALSE) -> 216044 | U8: =VLOOKUP($C8,DATA_ALL!$A:$CU,U$5,FALSE) -> 4317585 | V8: =T8+U8 -> 4533629 | W8: =V8/W$5 -> 6.266246e-05 | X8: =VLOOKUP($C8,DATA_ALL!$A:$CU,X$5,FALSE) -> 13193788 | Y8: =X8/Y$5 -> 9.6728651e-05 | Z8: =VLOOKUP($C8,DATA_ALL!$A:$CU,Z$5,FALSE) -> 1079305 | AA8: =VLOOKUP($C8,DATA_ALL!$A:$CU,AA$5,FALSE) -> 249472 | AB8: =Z8+AA8 -> 1328777 | AC8: =AB8/AC$5 -> 3.0737381e-05 | AD8: =VLOOKUP($C8,DATA_ALL!$A:$CU,AD$5,FALSE) -> 0 | AE8: =VLOOKUP($C8,DATA_ALL!$A:$CU,AE$5,FALSE) -> 77917 | AF8: =AD8+AE8 -> 77917 | AG8: =AF8/AG$5 -> 1.6920087e-06 | AH8: =VLOOKUP($C8,DATA_ALL!$A:$CU,AH$5,FALSE) -> 20799958 | AI8: =AH8/AI$5 -> 0.00026379148 | AJ8: =VLOOKUP($C8,DATA_ALL!$A:$CU,AJ$5,FALSE) -> 62102220 | AK8: =AJ8/AK$5 -> 0.0005201191 | AL8: =VLOOKUP($C8,DATA_ALL!$A:$CU,AL$5,FALSE) -> 9403457 | AM8: =AL8/AM$5 -> 0.00035987206 | AN8: =VLOOKUP($C8,DATA_ALL!$A:$CU,AN$5,FALSE) -> 0 | AO8: =AN8/AO$5 -> 0 | AP8: =VLOOKUP($C8,DATA_ALL!$A:$CU,AP$5,FALSE) -> 0 | AQ8: =AP8/AQ$5 -> 0 | AR8: =VLOOKUP($C8,DATA_ALL!$A:$CU,AR$5,FALSE) -> 0 | AS8: =AR8/AS$5 -> 0 | AT8: =VLOOKUP($C8,DATA_ALL!$A:$CU,AT$5,FALSE) -> 293305 | AU8: =AT8/AU$5 -> 5.9558562e-05
B9: 2 | C9: National Pension Service (Korea) | D9: =VLOOKUP($C9,DATA_ALL!$A:$CU,D$5,FALSE) -> Value | E9: =VLOOKUP($C9,DATA_ALL!$A:$CU,E$5,FALSE)/1000000000 -> 342.66659 | F9: =VLOOKUP($C9,DATA_ALL!$A:$CU,F$5,FALSE) -> South Korea | G9: =IF(VLOOKUP($C9,DATA_ALL!$A:$CU,G$5,FALSE)="N/A",0,VLOOKUP($C9,DATA_ALL!$A:$CU,G$5,FALSE)) -> 0 | H9: =VLOOKUP($C9,DATA_ALL!$A:$CU,H$5,FALSE) -> 0 | I9: =G9+H9 -> 0 | J9: =I9/$J$5 -> 0 | K9: =IFERROR(INDEX('SH Summary'!B:B,MATCH(APAC!C9,'SH Summary'!C:C,0)), "N/A") -> N/A | L9: =VLOOKUP($C9,DATA_ALL!$A:$CU,L$5,FALSE) -> 0 | M9: =L9/M$5 -> 0 | N9: =VLOOKUP($C9,DATA_ALL!$A:$CU,N$5,FALSE) -> 0 | O9: =VLOOKUP($C9,DATA_ALL!$A:$CU,O$5,FALSE) -> 0 | P9: =N9+O9 -> 0 | Q9: =P9/Q$5 -> 0 | R9: =VLOOKUP($C9,DATA_ALL!$A:$CU,R$5,FALSE) -> 0 | S9: =R9/S$5 -> 0 | T9: =VLOOKUP($C9,DATA_ALL!$A:$CU,T$5,FALSE) -> 0 | U9: =VLOOKUP($C9,DATA_ALL!$A:$CU,U$5,FALSE) -> 0 | V9: =T9+U9 -> 0 | W9: =V9/W$5 -> 0 | X9: =VLOOKUP($C9,DATA_ALL!$A:$CU,X$5,FALSE) -> 21473638 | Y9: =X9/Y$5 -> 0.00015743136 | Z9: =VLOOKUP($C9,DATA_ALL!$A:$CU,Z$5,FALSE) -> 0 | AA9: =VLOOKUP($C9,DATA_ALL!$A:$CU,AA$5,FALSE) -> 0 | AB9: =Z9+AA9 -> 0 | AC9: =AB9/AC$5 -> 0 | AD9: =VLOOKUP($C9,DATA_ALL!$A:$CU,AD$5,FALSE) -> 0 | AE9: =VLOOKUP($C9,DATA_ALL!$A:$CU,AE$5,FALSE) -> 0 | AF9: =AD9+AE9 -> 0 | AG9: =AF9/AG$5 -> 0 | AH9: =VLOOKUP($C9,DATA_ALL!$A:$CU,AH$5,FALSE) -> 91274300 | AI9: =AH9/AI$5 -> 0.0011575688 | AJ9: =VLOOKUP($C9,DATA_ALL!$A:$CU,AJ$5,FALSE) -> 329642794 | AK9: =AJ9/AK$5 -> 0.0027608274 | AL9: =VLOOKUP($C9,DATA_ALL!$A:$CU,AL$5,FALSE) -> 70915324 | AM9: =AL9/AM$5 -> 0.0027139427 | AN9: =VLOOKUP($C9,DATA_ALL!$A:$CU,AN$5,FALSE) -> 0 | AO9: =AN9/AO$5 -> 0 | AP9: =VLOOKUP($C9,DATA_ALL!$A:$CU,AP$5,FALSE) -> 0 | AQ9: =AP9/AQ$5 -> 0 | AR9: =VLOOKUP($C9,DATA_ALL!$A:$CU,AR$5,FALSE) -> 0 | AS9: =AR9/AS$5 -> 0 | AT9: =VLOOKUP($C9,DATA_ALL!$A:$CU,AT$5,FALSE) -> 0 | AU9: =AT9/AU$5 -> 0
B10: 3 | C10: Sumitomo Mitsui Trust Asset Management Company, LTD | D10: =VLOOKUP($C10,DATA_ALL!$A:$CU,D$5,FALSE) -> Value | E10: =VLOOKUP($C10,DATA_ALL!$A:$CU,E$5,FALSE)/1000000000 -> 311.62487 | F10: =VLOOKUP($C10,DATA_ALL!$A:$CU,F$5,FALSE) -> Japan | G10: =IF(VLOOKUP($C10,DATA_ALL!$A:$CU,G$5,FALSE)="N/A",0,VLOOKUP($C10,DATA_ALL!$A:$CU,G$5,FALSE)) -> 0 | H10: =VLOOKUP($C10,DATA_ALL!$A:$CU,H$5,FALSE) -> 0 | I10: =G10+H10 -> 0 | J10: =I10/$J$5 -> 0 | K10: =IFERROR(INDEX('SH Summary'!B:B,MATCH(APAC!C10,'SH Summary'!C:C,0)), "N/A") -> N/A | L10: =VLOOKUP($C10,DATA_ALL!$A:$CU,L$5,FALSE) -> 100217582 | M10: =L10/M$5 -> 0.00019337202 | N10: =VLOOKUP($C10,DATA_ALL!$A:$CU,N$5,FALSE) -> 67095255 | O10: =VLOOKUP($C10,DATA_ALL!$A:$CU,O$5,FALSE) -> 64367309 | P10: =N10+O10 -> 131462564 | Q10: =P10/Q$5 -> 0.00041327433 | R10: =VLOOKUP($C10,DATA_ALL!$A:$CU,R$5,FALSE) -> 13259231 | S10: =R10/S$5 -> 0.00020469199 | T10: =VLOOKUP($C10,DATA_ALL!$A:$CU,T$5,FALSE) -> 0 | U10: =VLOOKUP($C10,DATA_ALL!$A:$CU,U$5,FALSE) -> 9955805 | V10: =T10+U10 -> 9955805 | W10: =V10/W$5 -> 0.00013760615 | X10: =VLOOKUP($C10,DATA_ALL!$A:$CU,X$5,FALSE) -> 173927322 | Y10: =X10/Y$5 -> 0.001275127 | Z10: =VLOOKUP($C10,DATA_ALL!$A:$CU,Z$5,FALSE) -> 0 | AA10: =VLOOKUP($C10,DATA_ALL!$A:$CU,AA$5,FALSE) -> 6835302 | AB10: =Z10+AA10 -> 6835302 | AC10: =AB10/AC$5 -> 0.00015811478 | AD10: =VLOOKUP($C10,DATA_ALL!$A:$CU,AD$5,FALSE) -> 0 | AE10: =VLOOKUP($C10,DATA_ALL!$A:$CU,AE$5,FALSE) -> 7396764 | AF10: =AD10+AE10 -> 7396764 | AG10: =AF10/AG$5 -> 0.00016062463 | AH10: =VLOOKUP($C10,DATA_ALL!$A:$CU,AH$5,FALSE) -> 164028123 | AI10: =AH10/AI$5 -> 0.0020802552 | AJ10: =VLOOKUP($C10,DATA_ALL!$A:$CU,AJ$5,FALSE) -> 318780168 | AK10: =AJ10/AK$5 -> 0.0026698507 | AL10: =VLOOKUP($C10,DATA_ALL!$A:$CU,AL$5,FALSE) -> 65124833 | AM10: =AL10/AM$5 -> 0.0024923396 | AN10: =VLOOKUP($C10,DATA_ALL!$A:$CU,AN$5,FALSE) -> 0 | AO10: =AN10/AO$5 -> 0 | AP10: =VLOOKUP($C10,DATA_ALL!$A:$CU,AP$5,FALSE) -> 0 | AQ10: =AP10/AQ$5 -> 0 | AR10: =VLOOKUP($C10,DATA_ALL!$A:$CU,AR$5,FALSE) -> 0 | AS10: =AR10/AS$5 -> 0 | AT10: =VLOOKUP($C10,DATA_ALL!$A:$CU,AT$5,FALSE) -> 689224 | AU10: =AT10/AU$5 -> 0.00013995394
B11: 4 | C11: Mitsubishi UFJ Asset Management Company, LTD | D11: =VLOOKUP($C11,DATA_ALL!$A:$CU,D$5,FALSE) -> Deep Value | E11: =VLOOKUP($C11,DATA_ALL!$A:$CU,E$5,FALSE)/1000000000 -> 281.61467 | F11: =VLOOKUP($C11,DATA_ALL!$A:$CU,F$5,FALSE) -> Japan | G11: =IF(VLOOKUP($C11,DATA_ALL!$A:$CU,G$5,FALSE)="N/A",0,VLOOKUP($C11,DATA_ALL!$A:$CU,G$5,FALSE)) -> 672165 | H11: =VLOOKUP($C11,DATA_ALL!$A:$CU,H$5,FALSE) -> 190277 | I11: =G11+H11 -> 862442 | J11: =I11/$J$5 -> 2.7606978e-05 | K11: =IFERROR(INDEX('SH Summary'!B:B,MATCH(APAC!C11,'SH Summary'!C:C,0)), "N/A") -> 487 | L11: =VLOOKUP($C11,DATA_ALL!$A:$CU,L$5,FALSE) -> 14762060 | M11: =L11/M$5 -> 2.8483719e-05 | N11: =VLOOKUP($C11,DATA_ALL!$A:$CU,N$5,FALSE) -> 3992514 | O11: =VLOOKUP($C11,DATA_ALL!$A:$CU,O$5,FALSE) -> 2581189 | P11: =N11+O11 -> 6573703 | Q11: =P11/Q$5 -> 2.0665523e-05 | R11: =VLOOKUP($C11,DATA_ALL!$A:$CU,R$5,FALSE) -> 1626712 | S11: =R11/S$5 -> 2.5112687e-05 | T11: =VLOOKUP($C11,DATA_ALL!$A:$CU,T$5,FALSE) -> 635483 | U11: =VLOOKUP($C11,DATA_ALL!$A:$CU,U$5,FALSE) -> 755290 | V11: =T11+U11 -> 1390773 | W11: =V11/W$5 -> 1.9222847e-05 | X11: =VLOOKUP($C11,DATA_ALL!$A:$CU,X$5,FALSE) -> 96271339 | Y11: =X11/Y$5 -> 0.00070580161 | Z11: =VLOOKUP($C11,DATA_ALL!$A:$CU,Z$5,FALSE) -> 0 | AA11: =VLOOKUP($C11,DATA_ALL!$A:$CU,AA$5,FALSE) -> 833374 | AB11: =Z11+AA11 -> 833374 | AC11: =AB11/AC$5 -> 1.9277678e-05 | AD11: =VLOOKUP($C11,DATA_ALL!$A:$CU,AD$5,FALSE) -> 3196194 | AE11: =VLOOKUP($C11,DATA_ALL!$A:$CU,AE$5,FALSE) -> 134541 | AF11: =AD11+AE11 -> 3330735 | AG11: =AF11/AG$5 -> 7.2328664e-05 | AH11: =VLOOKUP($C11,DATA_ALL!$A:$CU,AH$5,FALSE) -> 134515855 | AI11: =AH11/AI$5 -> 0.0017059715 | AJ11: =VLOOKUP($C11,DATA_ALL!$A:$CU,AJ$5,FALSE) -> 547716318 | AK11: =AJ11/AK$5 -> 0.0045872388 | AL11: =VLOOKUP($C11,DATA_ALL!$A:$CU,AL$5,FALSE) -> 61599836 | AM11: =AL11/AM$5 -> 0.0023574373 | AN11: =VLOOKUP($C11,DATA_ALL!$A:$CU,AN$5,FALSE) -> 541992 | AO11: =AN11/AO$5 -> 0.00013193574 | AP11: =VLOOKUP($C11,DATA_ALL!$A:$CU,AP$5,FALSE) -> 0 | AQ11: =AP11/AQ$5 -> 0 | AR11: =VLOOKUP($C11,DATA_ALL!$A:$CU,AR$5,FALSE) -> 0 | AS11: =AR11/AS$5 -> 0 | AT11: =VLOOKUP($C11,DATA_ALL!$A:$CU,AT$5,FALSE) -> 14678 | AU11: =AT11/AU$5 -> 2.9805171e-06
B12: 5 | C12: Daiwa Asset Management Company, LTD | D12: =VLOOKUP($C12,DATA_ALL!$A:$CU,D$5,FALSE) -> Value | E12: =VLOOKUP($C12,DATA_ALL!$A:$CU,E$5,FALSE)/1000000000 -> 201.97459 | F12: =VLOOKUP($C12,DATA_ALL!$A:$CU,F$5,FALSE) -> Japan | G12: =IF(VLOOKUP($C12,DATA_ALL!$A:$CU,G$5,FALSE)="N/A",0,VLOOKUP($C12,DATA_ALL!$A:$CU,G$5,FALSE)) -> 617396 | H12: =VLOOKUP($C12,DATA_ALL!$A:$CU,H$5,FALSE) -> 980175 | I12: =G12+H12 -> 1597571 | J12: =I12/$J$5 -> 5.1138636e-05 | K12: =IFERROR(INDEX('SH Summary'!B:B,MATCH(APAC!C12,'SH Summary'!C:C,0)), "N/A") -> 425 | L12: =VLOOKUP($C12,DATA_ALL!$A:$CU,L$5,FALSE) -> 10043442 | M12: =L12/M$5 -> 1.9379042e-05 | N12: =VLOOKUP($C12,DATA_ALL!$A:$CU,N$5,FALSE) -> 0 | O12: =VLOOKUP($C12,DATA_ALL!$A:$CU,O$5,FALSE) -> 10780740 | P12: =N12+O12 -> 10780740 | Q12: =P12/Q$5 -> 3.3891041e-05 | R12: =VLOOKUP($C12,DATA_ALL!$A:$CU,R$5,FALSE) -> 1205325 | S12: =R12/S$5 -> 1.8607442e-05 | T12: =VLOOKUP($C12,DATA_ALL!$A:$CU,T$5,FALSE) -> 596640 | U12: =VLOOKUP($C12,DATA_ALL!$A:$CU,U$5,FALSE) -> 2393502 | V12: =T12+U12 -> 2990142 | W12: =V12/W$5 -> 4.1328846e-05 | X12: =VLOOKUP($C12,DATA_ALL!$A:$CU,X$5,FALSE) -> 10177128 | Y12: =X12/Y$5 -> 7.4612375e-05 | Z12: =VLOOKUP($C12,DATA_ALL!$A:$CU,Z$5,FALSE) -> 0 | AA12: =VLOOKUP($C12,DATA_ALL!$A:$CU,AA$5,FALSE) -> 3026995 | AB12: =Z12+AA12 -> 3026995 | AC12: =AB12/AC$5 -> 7.0020703e-05 | AD12: =VLOOKUP($C12,DATA_ALL!$A:$CU,AD$5,FALSE) -> 2398427 | AE12: =VLOOKUP($C12,DATA_ALL!$A:$CU,AE$5,FALSE) -> 3503237 | AF12: =AD12+AE12 -> 5901664 | AG12: =AF12/AG$5 -> 0.00012815774 | AH12: =VLOOKUP($C12,DATA_ALL!$A:$CU,AH$5,FALSE) -> 22670291 | AI12: =AH12/AI$5 -> 0.00028751162 | AJ12: =VLOOKUP($C12,DATA_ALL!$A:$CU,AJ$5,FALSE) -> 1882013 | AK12: =AJ12/AK$5 -> 1.5762253e-05 | AL12: =VLOOKUP($C12,DATA_ALL!$A:$CU,AL$5,FALSE) -> 11937013 | AM12: =AL12/AM$5 -> 0.00045683173 | AN12: =VLOOKUP($C12,DATA_ALL!$A:$CU,AN$5,FALSE) -> 0 | AO12: =AN12/AO$5 -> 0 | AP12: =VLOOKUP($C12,DATA_ALL!$A:$CU,AP$5,FALSE) -> 0 | AQ12: =AP12/AQ$5 -> 0 | AR12: =VLOOKUP($C12,DATA_ALL!$A:$CU,AR$5,FALSE) -> 0 | AS12: =AR12/AS$5 -> 0 | AT12: =VLOOKUP($C12,DATA_ALL!$A:$CU,AT$5,FALSE) -> 0 | AU12: =AT12/AU$5 -> 0
B13: 6 | C13: BlackRock Japan Company, LTD | D13: =VLOOKUP($C13,DATA_ALL!$A:$CU,D$5,FALSE) -> Index | E13: =VLOOKUP($C13,DATA_ALL!$A:$CU,E$5,FALSE)/1000000000 -> 192.18591 | F13: =VLOOKUP($C13,DATA_ALL!$A:$CU,F$5,FALSE) -> Japan | G13: =IF(VLOOKUP($C13,DATA_ALL!$A:$CU,G$5,FALSE)="N/A",0,VLOOKUP($C13,DATA_ALL!$A:$CU,G$5,FALSE)) -> 0 | H13: =VLOOKUP($C13,DATA_ALL!$A:$CU,H$5,FALSE) -> 0 | I13: =G13+H13 -> 0 | J13: =I13/$J$5 -> 0 | K13: =IFERROR(INDEX('SH Summary'!B:B,MATCH(APAC!C13,'SH Summary'!C:C,0)), "N/A") -> N/A | L13: =VLOOKUP($C13,DATA_ALL!$A:$CU,L$5,FALSE) -> 0 | M13: =L13/M$5 -> 0 | N13: =VLOOKUP($C13,DATA_ALL!$A:$CU,N$5,FALSE) -> 0 | O13: =VLOOKUP($C13,DATA_ALL!$A:$CU,O$5,FALSE) -> 345956614 | P13: =N13+O13 -> 345956614 | Q13: =P13/Q$5 -> 0.0010875719 | R13: =VLOOKUP($C13,DATA_ALL!$A:$CU,R$5,FALSE) -> 50476379 | S13: =R13/S$5 -> 0.00077923905 | T13: =VLOOKUP($C13,DATA_ALL!$A:$CU,T$5,FALSE) -> 0 | U13: =VLOOKUP($C13,DATA_ALL!$A:$CU,U$5,FALSE) -> 0 | V13: =T13+U13 -> 0 | W13: =V13/W$5 -> 0 | X13: =VLOOKUP($C13,DATA_ALL!$A:$CU,X$5,FALSE) -> 65609165 | Y13: =X13/Y$5 -> 0.00048100561 | Z13: =VLOOKUP($C13,DATA_ALL!$A:$CU,Z$5,FALSE) -> 0 | AA13: =VLOOKUP($C13,DATA_ALL!$A:$CU,AA$5,FALSE) -> 0 | AB13: =Z13+AA13 -> 0 | AC13: =AB13/AC$5 -> 0 | AD13: =VLOOKUP($C13,DATA_ALL!$A:$CU,AD$5,FALSE) -> 0 | AE13: =VLOOKUP($C13,DATA_ALL!$A:$CU,AE$5,FALSE) -> 0 | AF13: =AD13+AE13 -> 0 | AG13: =AF13/AG$5 -> 0 | AH13: =VLOOKUP($C13,DATA_ALL!$A:$CU,AH$5,FALSE) -> 60584724 | AI13: =AH13/AI$5 -> 0.00076835414 | AJ13: =VLOOKUP($C13,DATA_ALL!$A:$CU,AJ$5,FALSE) -> 183982563 | AK13: =AJ13/AK$5 -> 0.0015408925 | AL13: =VLOOKUP($C13,DATA_ALL!$A:$CU,AL$5,FALSE) -> 31510944 | AM13: =AL13/AM$5 -> 0.0012059297 | AN13: =VLOOKUP($C13,DATA_ALL!$A:$CU,AN$5,FALSE) -> 0 | AO13: =AN13/AO$5 -> 0 | AP13: =VLOOKUP($C13,DATA_ALL!$A:$CU,AP$5,FALSE) -> 0 | AQ13: =AP13/AQ$5 -> 0 | AR13: =VLOOKUP($C13,DATA_ALL!$A:$CU,AR$5,FALSE) -> 0 | AS13: =AR13/AS$5 -> 0 | AT13: =VLOOKUP($C13,DATA_ALL!$A:$CU,AT$5,FALSE) -> 0 | AU13: =AT13/AU$5 -> 0
B14: 7 | C14: Amova Asset Management Company, LTD | D14: =VLOOKUP($C14,DATA_ALL!$A:$CU,D$5,FALSE) -> Value | E14: =VLOOKUP($C14,DATA_ALL!$A:$CU,E$5,FALSE)/1000000000 -> 186.5004 | F14: =VLOOKUP($C14,DATA_ALL!$A:$CU,F$5,FALSE) -> Japan | G14: =IF(VLOOKUP($C14,DATA_ALL!$A:$CU,G$5,FALSE)="N/A",0,VLOOKUP($C14,DATA_ALL!$A:$CU,G$5,FALSE)) -> 0 | H14: =VLOOKUP($C14,DATA_ALL!$A:$CU,H$5,FALSE) -> 12576803 | I14: =G14+H14 -> 12576803 | J14: =I14/$J$5 -> 0.00040258652 | K14: =IFERROR(INDEX('SH Summary'!B:B,MATCH(APAC!C14,'SH Summary'!C:C,0)), "N/A") -> 200 | L14: =VLOOKUP($C14,DATA_ALL!$A:$CU,L$5,FALSE) -> 61573731 | M14: =L14/M$5 -> 0.00011880786 | N14: =VLOOKUP($C14,DATA_ALL!$A:$CU,N$5,FALSE) -> 12928356 | O14: =VLOOKUP($C14,DATA_ALL!$A:$CU,O$5,FALSE) -> 34600159 | P14: =N14+O14 -> 47528515 | Q14: =P14/Q$5 -> 0.00014941375 | R14: =VLOOKUP($C14,DATA_ALL!$A:$CU,R$5,FALSE) -> 7775409 | S14: =R14/S$5 -> 0.00012003441 | T14: =VLOOKUP($C14,DATA_ALL!$A:$CU,T$5,FALSE) -> 481566 | U14: =VLOOKUP($C14,DATA_ALL!$A:$CU,U$5,FALSE) -> 6684380 | V14: =T14+U14 -> 7165946 | W14: =V14/W$5 -> 9.9045556e-05 | X14: =VLOOKUP($C14,DATA_ALL!$A:$CU,X$5,FALSE) -> 8365828 | Y14: =X14/Y$5 -> 6.133305e-05 | Z14: =VLOOKUP($C14,DATA_ALL!$A:$CU,Z$5,FALSE) -> 0 | AA14: =VLOOKUP($C14,DATA_ALL!$A:$CU,AA$5,FALSE) -> 4844982 | AB14: =Z14+AA14 -> 4844982 | AC14: =AB14/AC$5 -> 0.00011207453 | AD14: =VLOOKUP($C14,DATA_ALL!$A:$CU,AD$5,FALSE) -> 63261825 | AE14: =VLOOKUP($C14,DATA_ALL!$A:$CU,AE$5,FALSE) -> 4256030 | AF14: =AD14+AE14 -> 67517855 | AG14: =AF14/AG$5 -> 0.0014661858 | AH14: =VLOOKUP($C14,DATA_ALL!$A:$CU,AH$5,FALSE) -> 33958668 | AI14: =AH14/AI$5 -> 0.00043067429 | AJ14: =VLOOKUP($C14,DATA_ALL!$A:$CU,AJ$5,FALSE) -> 23264675 | AK14: =AJ14/AK$5 -> 0.00019484652 | AL14: =VLOOKUP($C14,DATA_ALL!$A:$CU,AL$5,FALSE) -> 1862804 | AM14: =AL14/AM$5 -> 7.1289858e-05 | AN14: =VLOOKUP($C14,DATA_ALL!$A:$CU,AN$5,FALSE) -> 0 | AO14: =AN14/AO$5 -> 0 | AP14: =VLOOKUP($C14,DATA_ALL!$A:$CU,AP$5,FALSE) -> 0 | AQ14: =AP14/AQ$5 -> 0 | AR14: =VLOOKUP($C14,DATA_ALL!$A:$CU,AR$5,FALSE) -> 0 | AS14: =AR14/AS$5 -> 0 | AT14: =VLOOKUP($C14,DATA_ALL!$A:$CU,AT$5,FALSE) -> 399520 | AU14: =AT14/AU$5 -> 8.1126598e-05
B15: 8 | C15: Temasek Holdings Pte., LTD | D15: =VLOOKUP($C15,DATA_ALL!$A:$CU,D$5,FALSE) -> Value | E15: =VLOOKUP($C15,DATA_ALL!$A:$CU,E$5,FALSE)/1000000000 -> 151.48937 | F15: =VLOOKUP($C15,DATA_ALL!$A:$CU,F$5,FALSE) -> Singapore | G15: =IF(VLOOKUP($C15,DATA_ALL!$A:$CU,G$5,FALSE)="N/A",0,VLOOKUP($C15,DATA_ALL!$A:$CU,G$5,FALSE)) -> 111513219 | H15: =VLOOKUP($C15,DATA_ALL!$A:$CU,H$5,FALSE) -> 0 | I15: =G15+H15 -> 111513219 | J15: =I15/$J$5 -> 0.0035695653 | K15: =IFERROR(INDEX('SH Summary'!B:B,MATCH(APAC!C15,'SH Summary'!C:C,0)), "N/A") -> 36 | L15: =VLOOKUP($C15,DATA_ALL!$A:$CU,L$5,FALSE) -> 0 | M15: =L15/M$5 -> 0 | N15: =VLOOKUP($C15,DATA_ALL!$A:$CU,N$5,FALSE) -> 164761851 | O15: =VLOOKUP($C15,DATA_ALL!$A:$CU,O$5,FALSE) -> 0 | P15: =N15+O15 -> 164761851 | Q15: =P15/Q$5 -> 0.00051795615 | R15: =VLOOKUP($C15,DATA_ALL!$A:$CU,R$5,FALSE) -> 0 | S15: =R15/S$5 -> 0 | T15: =VLOOKUP($C15,DATA_ALL!$A:$CU,T$5,FALSE) -> 79266281 | U15: =VLOOKUP($C15,DATA_ALL!$A:$CU,U$5,FALSE) -> 0 | V15: =T15+U15 -> 79266281 | W15: =V15/W$5 -> 0.0010955948 | X15: =VLOOKUP($C15,DATA_ALL!$A:$CU,X$5,FALSE) -> 503344913 | Y15: =X15/Y$5 -> 0.003690212 | Z15: =VLOOKUP($C15,DATA_ALL!$A:$CU,Z$5,FALSE) -> 0 | AA15: =VLOOKUP($C15,DATA_ALL!$A:$CU,AA$5,FALSE) -> 0 | AB15: =Z15+AA15 -> 0 | AC15: =AB15/AC$5 -> 0 | AD15: =VLOOKUP($C15,DATA_ALL!$A:$CU,AD$5,FALSE) -> 0 | AE15: =VLOOKUP($C15,DATA_ALL!$A:$CU,AE$5,FALSE) -> 0 | AF15: =AD15+AE15 -> 0 | AG15: =AF15/AG$5 -> 0 | AH15: =VLOOKUP($C15,DATA_ALL!$A:$CU,AH$5,FALSE) -> 280618658 | AI15: =AH15/AI$5 -> 0.0035588923 | AJ15: =VLOOKUP($C15,DATA_ALL!$A:$CU,AJ$5,FALSE) -> 236076853 | AK15: =AJ15/AK$5 -> 0.0019771931 | AL15: =VLOOKUP($C15,DATA_ALL!$A:$CU,AL$5,FALSE) -> 0 | AM15: =AL15/AM$5 -> 0 | AN15: =VLOOKUP($C15,DATA_ALL!$A:$CU,AN$5,FALSE) -> 63447294 | AO15: =AN15/AO$5 -> 0.015444814 | AP15: =VLOOKUP($C15,DATA_ALL!$A:$CU,AP$5,FALSE) -> 0 | AQ15: =AP15/AQ$5 -> 0 | AR15: =VLOOKUP($C15,DATA_ALL!$A:$CU,AR$5,FALSE) -> 0 | AS15: =AR15/AS$5 -> 0 | AT15: =VLOOKUP($C15,DATA_ALL!$A:$CU,AT$5,FALSE) -> 0 | AU15: =AT15/AU$5 -> 0
B16: 9 | C16: China Asset Management Corporation, LTD | D16: =VLOOKUP($C16,DATA_ALL!$A:$CU,D$5,FALSE) -> Aggressive Growth | E16: =VLOOKUP($C16,DATA_ALL!$A:$CU,E$5,FALSE)/1000000000 -> 135.09155 | F16: =VLOOKUP($C16,DATA_ALL!$A:$CU,F$5,FALSE) -> China (Mainland) | G16: =IF(VLOOKUP($C16,DATA_ALL!$A:$CU,G$5,FALSE)="N/A",0,VLOOKUP($C16,DATA_ALL!$A:$CU,G$5,FALSE)) -> 0 | H16: =VLOOKUP($C16,DATA_ALL!$A:$CU,H$5,FALSE) -> 175653100 | I16: =G16+H16 -> 175653100 | J16: =I16/$J$5 -> 0.0056226985 | K16: =IFERROR(INDEX('SH Summary'!B:B,MATCH(APAC!C16,'SH Summary'!C:C,0)), "N/A") -> 18 | L16: =VLOOKUP($C16,DATA_ALL!$A:$CU,L$5,FALSE) -> 1533004186 | M16: =L16/M$5 -> 0.0029579652 | N16: =VLOOKUP($C16,DATA_ALL!$A:$CU,N$5,FALSE) -> 0 | O16: =VLOOKUP($C16,DATA_ALL!$A:$CU,O$5,FALSE) -> 1421540425 | P16: =N16+O16 -> 1421540425 | Q16: =P16/Q$5 -> 0.0044688476 | R16: =VLOOKUP($C16,DATA_ALL!$A:$CU,R$5,FALSE) -> 1020278130 | S16: =R16/S$5 -> 0.015750745 | T16: =VLOOKUP($C16,DATA_ALL!$A:$CU,T$5,FALSE) -> 0 | U16: =VLOOKUP($C16,DATA_ALL!$A:$CU,U$5,FALSE) -> 795534357 | V16: =T16+U16 -> 795534357 | W16: =V16/W$5 -> 0.010995637 | X16: =VLOOKUP($C16,DATA_ALL!$A:$CU,X$5,FALSE) -> 7248138 | Y16: =X16/Y$5 -> 5.3138842e-05 | Z16: =VLOOKUP($C16,DATA_ALL!$A:$CU,Z$5,FALSE) -> 0 | AA16: =VLOOKUP($C16,DATA_ALL!$A:$CU,AA$5,FALSE) -> 720899687 | AB16: =Z16+AA16 -> 720899687 | AC16: =AB16/AC$5 -> 0.016675912 | AD16: =VLOOKUP($C16,DATA_ALL!$A:$CU,AD$5,FALSE) -> 0 | AE16: =VLOOKUP($C16,DATA_ALL!$A:$CU,AE$5,FALSE) -> 489597900 | AF16: =AD16+AE16 -> 489597900 | AG16: =AF16/AG$5 -> 0.010631876 | AH16: =VLOOKUP($C16,DATA_ALL!$A:$CU,AH$5,FALSE) -> 5477931 | AI16: =AH16/AI$5 -> 6.9472809e-05 | AJ16: =VLOOKUP($C16,DATA_ALL!$A:$CU,AJ$5,FALSE) -> 16671142 | AK16: =AJ16/AK$5 -> 0.0001396243 | AL16: =VLOOKUP($C16,DATA_ALL!$A:$CU,AL$5,FALSE) -> 2828850 | AM16: =AL16/AM$5 -> 0.00010826062 | AN16: =VLOOKUP($C16,DATA_ALL!$A:$CU,AN$5,FALSE) -> 0 | AO16: =AN16/AO$5 -> 0 | AP16: =VLOOKUP($C16,DATA_ALL!$A:$CU,AP$5,FALSE) -> 0 | AQ16: =AP16/AQ$5 -> 0 | AR16: =VLOOKUP($C16,DATA_ALL!$A:$CU,AR$5,FALSE) -> 0 | AS16: =AR16/AS$5 -> 0 | AT16: =VLOOKUP($C16,DATA_ALL!$A:$CU,AT$5,FALSE) -> 97127900 | AU16: =AT16/AU$5 -> 0.019722807
B17: 10 | C17: E Fund Management Company, LTD | D17: =VLOOKUP($C17,DATA_ALL!$A:$CU,D$5,FALSE) -> Growth | E17: =VLOOKUP($C17,DATA_ALL!$A:$CU,E$5,FALSE)/1000000000 -> 123.95179 | F17: =VLOOKUP($C17,DATA_ALL!$A:$CU,F$5,FALSE) -> China (Mainland) | G17: =IF(VLOOKUP($C17,DATA_ALL!$A:$CU,G$5,FALSE)="N/A",0,VLOOKUP($C17,DATA_ALL!$A:$CU,G$5,FALSE)) -> 93052 | H17: =VLOOKUP($C17,DATA_ALL!$A:$CU,H$5,FALSE) -> 481822481 | I17: =G17+H17 -> 481915533 | J17: =I17/$J$5 -> 0.015426233 | K17: =IFERROR(INDEX('SH Summary'!B:B,MATCH(APAC!C17,'SH Summary'!C:C,0)), "N/A") -> 7 | L17: =VLOOKUP($C17,DATA_ALL!$A:$CU,L$5,FALSE) -> 3624433845 | M17: =L17/M$5 -> 0.0069934246 | N17: =VLOOKUP($C17,DATA_ALL!$A:$CU,N$5,FALSE) -> 0 | O17: =VLOOKUP($C17,DATA_ALL!$A:$CU,O$5,FALSE) -> 3197821079 | P17: =N17+O17 -> 3197821079 | Q17: =P17/Q$5 -> 0.01005288 | R17: =VLOOKUP($C17,DATA_ALL!$A:$CU,R$5,FALSE) -> 759769180 | S17: =R17/S$5 -> 0.011729087 | T17: =VLOOKUP($C17,DATA_ALL!$A:$CU,T$5,FALSE) -> 0 | U17: =VLOOKUP($C17,DATA_ALL!$A:$CU,U$5,FALSE) -> 498707377 | V17: =T17+U17 -> 498707377 | W17: =V17/W$5 -> 0.0068929838 | X17: =VLOOKUP($C17,DATA_ALL!$A:$CU,X$5,FALSE) -> 469318156 | Y17: =X17/Y$5 -> 0.0034407489 | Z17: =VLOOKUP($C17,DATA_ALL!$A:$CU,Z$5,FALSE) -> 0 | AA17: =VLOOKUP($C17,DATA_ALL!$A:$CU,AA$5,FALSE) -> 358458506 | AB17: =Z17+AA17 -> 358458506 | AC17: =AB17/AC$5 -> 0.0082918923 | AD17: =VLOOKUP($C17,DATA_ALL!$A:$CU,AD$5,FALSE) -> 0 | AE17: =VLOOKUP($C17,DATA_ALL!$A:$CU,AE$5,FALSE) -> 323460714 | AF17: =AD17+AE17 -> 323460714 | AG17: =AF17/AG$5 -> 0.0070241197 | AH17: =VLOOKUP($C17,DATA_ALL!$A:$CU,AH$5,FALSE) -> 1889528 | AI17: =AH17/AI$5 -> 2.3963576e-05 | AJ17: =VLOOKUP($C17,DATA_ALL!$A:$CU,AJ$5,FALSE) -> 4757662 | AK17: =AJ17/AK$5 -> 3.9846415e-05 | AL17: =VLOOKUP($C17,DATA_ALL!$A:$CU,AL$5,FALSE) -> 112474 | AM17: =AL17/AM$5 -> 4.3044011e-06 | AN17: =VLOOKUP($C17,DATA_ALL!$A:$CU,AN$5,FALSE) -> 0 | AO17: =AN17/AO$5 -> 0 | AP17: =VLOOKUP($C17,DATA_ALL!$A:$CU,AP$5,FALSE) -> 0 | AQ17: =AP17/AQ$5 -> 0 | AR17: =VLOOKUP($C17,DATA_ALL!$A:$CU,AR$5,FALSE) -> 0 | AS17: =AR17/AS$5 -> 0 | AT17: =VLOOKUP($C17,DATA_ALL!$A:$CU,AT$5,FALSE) -> 52792808 | AU17: =AT17/AU$5 -> 0.010720116
B18: 11 | C18: Vanguard Investments Australia, LTD | D18: =VLOOKUP($C18,DATA_ALL!$A:$CU,D$5,FALSE) -> Index | E18: =VLOOKUP($C18,DATA_ALL!$A:$CU,E$5,FALSE)/1000000000 -> 106.73354 | F18: =VLOOKUP($C18,DATA_ALL!$A:$CU,F$5,FALSE) -> Australia | G18: =IF(VLOOKUP($C18,DATA_ALL!$A:$CU,G$5,FALSE)="N/A",0,VLOOKUP($C18,DATA_ALL!$A:$CU,G$5,FALSE)) -> 0 | H18: =VLOOKUP($C18,DATA_ALL!$A:$CU,H$5,FALSE) -> 1656273 | I18: =G18+H18 -> 1656273 | J18: =I18/$J$5 -> 5.3017702e-05 | K18: =IFERROR(INDEX('SH Summary'!B:B,MATCH(APAC!C18,'SH Summary'!C:C,0)), "N/A") -> 396 | L18: =VLOOKUP($C18,DATA_ALL!$A:$CU,L$5,FALSE) -> 85721649 | M18: =L18/M$5 -> 0.0001654018 | N18: =VLOOKUP($C18,DATA_ALL!$A:$CU,N$5,FALSE) -> 0 | O18: =VLOOKUP($C18,DATA_ALL!$A:$CU,O$5,FALSE) -> 63153702 | P18: =N18+O18 -> 63153702 | Q18: =P18/Q$5 -> 0.00019853412 | R18: =VLOOKUP($C18,DATA_ALL!$A:$CU,R$5,FALSE) -> 2936706 | S18: =R18/S$5 -> 4.5335978e-05 | T18: =VLOOKUP($C18,DATA_ALL!$A:$CU,T$5,FALSE) -> 0 | U18: =VLOOKUP($C18,DATA_ALL!$A:$CU,U$5,FALSE) -> 2172005 | V18: =T18+U18 -> 2172005 | W18: =V18/W$5 -> 3.0020802e-05 | X18: =VLOOKUP($C18,DATA_ALL!$A:$CU,X$5,FALSE) -> 16621518 | Y18: =X18/Y$5 -> 0.00012185864 | Z18: =VLOOKUP($C18,DATA_ALL!$A:$CU,Z$5,FALSE) -> 0 | AA18: =VLOOKUP($C18,DATA_ALL!$A:$CU,AA$5,FALSE) -> 1818922 | AB18: =Z18+AA18 -> 1818922 | AC18: =AB18/AC$5 -> 4.2075457e-05 | AD18: =VLOOKUP($C18,DATA_ALL!$A:$CU,AD$5,FALSE) -> 0 | AE18: =VLOOKUP($C18,DATA_ALL!$A:$CU,AE$5,FALSE) -> 1671675 | AF18: =AD18+AE18 -> 1671675 | AG18: =AF18/AG$5 -> 3.6301303e-05 | AH18: =VLOOKUP($C18,DATA_ALL!$A:$CU,AH$5,FALSE) -> 27062814 | AI18: =AH18/AI$5 -> 0.00034321895 | AJ18: =VLOOKUP($C18,DATA_ALL!$A:$CU,AJ$5,FALSE) -> 67655632 | AK18: =AJ18/AK$5 -> 0.00056663008 | AL18: =VLOOKUP($C18,DATA_ALL!$A:$CU,AL$5,FALSE) -> 13529692 | AM18: =AL18/AM$5 -> 0.00051778385 | AN18: =VLOOKUP($C18,DATA_ALL!$A:$CU,AN$5,FALSE) -> 0 | AO18: =AN18/AO$5 -> 0 | AP18: =VLOOKUP($C18,DATA_ALL!$A:$CU,AP$5,FALSE) -> 285485 | AQ18: =AP18/AQ$5 -> 0.00025929609 | AR18: =VLOOKUP($C18,DATA_ALL!$A:$CU,AR$5,FALSE) -> 0 | AS18: =AR18/AS$5 -> 0 | AT18: =VLOOKUP($C18,DATA_ALL!$A:$CU,AT$5,FALSE) -> 138612 | AU18: =AT18/AU$5 -> 2.8146576e-05
B19: 12 | C19: Asset Management One Company, LTD | D19: =VLOOKUP($C19,DATA_ALL!$A:$CU,D$5,FALSE) -> Deep Value | E19: =VLOOKUP($C19,DATA_ALL!$A:$CU,E$5,FALSE)/1000000000 -> 105.01883 | F19: =VLOOKUP($C19,DATA_ALL!$A:$CU,F$5,FALSE) -> Japan | G19: =IF(VLOOKUP($C19,DATA_ALL!$A:$CU,G$5,FALSE)="N/A",0,VLOOKUP($C19,DATA_ALL!$A:$CU,G$5,FALSE)) -> 4740755 | H19: =VLOOKUP($C19,DATA_ALL!$A:$CU,H$5,FALSE) -> 3268179 | I19: =G19+H19 -> 8008934 | J19: =I19/$J$5 -> 0.00025636793 | K19: =IFERROR(INDEX('SH Summary'!B:B,MATCH(APAC!C19,'SH Summary'!C:C,0)), "N/A") -> 209 | L19: =VLOOKUP($C19,DATA_ALL!$A:$CU,L$5,FALSE) -> 55512313 | M19: =L19/M$5 -> 0.00010711223 | N19: =VLOOKUP($C19,DATA_ALL!$A:$CU,N$5,FALSE) -> 0 | O19: =VLOOKUP($C19,DATA_ALL!$A:$CU,O$5,FALSE) -> 25585106 | P19: =N19+O19 -> 25585106 | Q19: =P19/Q$5 -> 8.0431015e-05 | R19: =VLOOKUP($C19,DATA_ALL!$A:$CU,R$5,FALSE) -> 31320352 | S19: =R19/S$5 -> 0.00048351411 | T19: =VLOOKUP($C19,DATA_ALL!$A:$CU,T$5,FALSE) -> 0 | U19: =VLOOKUP($C19,DATA_ALL!$A:$CU,U$5,FALSE) -> 6259877 | V19: =T19+U19 -> 6259877 | W19: =V19/W$5 -> 8.6522142e-05 | X19: =VLOOKUP($C19,DATA_ALL!$A:$CU,X$5,FALSE) -> 12128562 | Y19: =X19/Y$5 -> 8.8919076e-05 | Z19: =VLOOKUP($C19,DATA_ALL!$A:$CU,Z$5,FALSE) -> 0 | AA19: =VLOOKUP($C19,DATA_ALL!$A:$CU,AA$5,FALSE) -> 3101629 | AB19: =Z19+AA19 -> 3101629 | AC19: =AB19/AC$5 -> 7.1747143e-05 | AD19: =VLOOKUP($C19,DATA_ALL!$A:$CU,AD$5,FALSE) -> 11887185 | AE19: =VLOOKUP($C19,DATA_ALL!$A:$CU,AE$5,FALSE) -> 148383 | AF19: =AD19+AE19 -> 12035568 | AG19: =AF19/AG$5 -> 0.0002613587 | AH19: =VLOOKUP($C19,DATA_ALL!$A:$CU,AH$5,FALSE) -> 24731307 | AI19: =AH19/AI$5 -> 0.00031365006 | AJ19: =VLOOKUP($C19,DATA_ALL!$A:$CU,AJ$5,FALSE) -> 70434443 | AK19: =AJ19/AK$5 -> 0.00058990321 | AL19: =VLOOKUP($C19,DATA_ALL!$A:$CU,AL$5,FALSE) -> 12894514 | AM19: =AL19/AM$5 -> 0.00049347547 | AN19: =VLOOKUP($C19,DATA_ALL!$A:$CU,AN$5,FALSE) -> 0 | AO19: =AN19/AO$5 -> 0 | AP19: =VLOOKUP($C19,DATA_ALL!$A:$CU,AP$5,FALSE) -> 0 | AQ19: =AP19/AQ$5 -> 0 | AR19: =VLOOKUP($C19,DATA_ALL!$A:$CU,AR$5,FALSE) -> 0 | AS19: =AR19/AS$5 -> 0 | AT19: =VLOOKUP($C19,DATA_ALL!$A:$CU,AT$5,FALSE) -> 269084 | AU19: =AT19/AU$5 -> 5.4640242e-05
B20: 13 | C20: BlackRock Investment Management (Australia), LTD | D20: =VLOOKUP($C20,DATA_ALL!$A:$CU,D$5,FALSE) -> Index | E20: =VLOOKUP($C20,DATA_ALL!$A:$CU,E$5,FALSE)/1000000000 -> 97.331988 | F20: =VLOOKUP($C20,DATA_ALL!$A:$CU,F$5,FALSE) -> Australia | G20: =IF(VLOOKUP($C20,DATA_ALL!$A:$CU,G$5,FALSE)="N/A",0,VLOOKUP($C20,DATA_ALL!$A:$CU,G$5,FALSE)) -> 0 | H20: =VLOOKUP($C20,DATA_ALL!$A:$CU,H$5,FALSE) -> 5734929 | I20: =G20+H20 -> 5734929 | J20: =I20/$J$5 -> 0.00018357647 | K20: =IFERROR(INDEX('SH Summary'!B:B,MATCH(APAC!C20,'SH Summary'!C:C,0)), "N/A") -> 246 | L20: =VLOOKUP($C20,DATA_ALL!$A:$CU,L$5,FALSE) -> 64196636 | M20: =L20/M$5 -> 0.00012386882 | N20: =VLOOKUP($C20,DATA_ALL!$A:$CU,N$5,FALSE) -> 89955 | O20: =VLOOKUP($C20,DATA_ALL!$A:$CU,O$5,FALSE) -> 137015827 | P20: =N20+O20 -> 137105782 | Q20: =P20/Q$5 -> 0.00043101472 | R20: =VLOOKUP($C20,DATA_ALL!$A:$CU,R$5,FALSE) -> 44977771 | S20: =R20/S$5 -> 0.00069435321 | T20: =VLOOKUP($C20,DATA_ALL!$A:$CU,T$5,FALSE) -> 0 | U20: =VLOOKUP($C20,DATA_ALL!$A:$CU,U$5,FALSE) -> 7300646 | V20: =T20+U20 -> 7300646 | W20: =V20/W$5 -> 0.00010090734 | X20: =VLOOKUP($C20,DATA_ALL!$A:$CU,X$5,FALSE) -> 20239814 | Y20: =X20/Y$5 -> 0.00014838573 | Z20: =VLOOKUP($C20,DATA_ALL!$A:$CU,Z$5,FALSE) -> 0 | AA20: =VLOOKUP($C20,DATA_ALL!$A:$CU,AA$5,FALSE) -> 7794848 | AB20: =Z20+AA20 -> 7794848 | AC20: =AB20/AC$5 -> 0.00018031108 | AD20: =VLOOKUP($C20,DATA_ALL!$A:$CU,AD$5,FALSE) -> 0 | AE20: =VLOOKUP($C20,DATA_ALL!$A:$CU,AE$5,FALSE) -> 7124119 | AF20: =AD20+AE20 -> 7124119 | AG20: =AF20/AG$5 -> 0.000154704 | AH20: =VLOOKUP($C20,DATA_ALL!$A:$CU,AH$5,FALSE) -> 47620441 | AI20: =AH20/AI$5 -> 0.00060393711 | AJ20: =VLOOKUP($C20,DATA_ALL!$A:$CU,AJ$5,FALSE) -> 176092424 | AK20: =AJ20/AK$5 -> 0.0014748109 | AL20: =VLOOKUP($C20,DATA_ALL!$A:$CU,AL$5,FALSE) -> 25275990 | AM20: =AL20/AM$5 -> 0.00096731688 | AN20: =VLOOKUP($C20,DATA_ALL!$A:$CU,AN$5,FALSE) -> 0 | AO20: =AN20/AO$5 -> 0 | AP20: =VLOOKUP($C20,DATA_ALL!$A:$CU,AP$5,FALSE) -> 11715 | AQ20: =AP20/AQ$5 -> 1.0640327e-05 | AR20: =VLOOKUP($C20,DATA_ALL!$A:$CU,AR$5,FALSE) -> 0 | AS20: =AR20/AS$5 -> 0 | AT20: =VLOOKUP($C20,DATA_ALL!$A:$CU,AT$5,FALSE) -> 132 | AU20: =AT20/AU$5 -> 2.6803942e-08
... B34: 27 | C34: Korea Investment Corporation. | D34: =VLOOKUP($C34,DATA_ALL!$A:$CU,D$5,FALSE) -> Growth | E34: =VLOOKUP($C34,DATA_ALL!$A:$CU,E$5,FALSE)/1000000000 -> 50.439971 | F34: =VLOOKUP($C34,DATA_ALL!$A:$CU,F$5,FALSE) -> South Korea | G34: =IF(VLOOKUP($C34,DATA_ALL!$A:$CU,G$5,FALSE)="N/A",0,VLOOKUP($C34,DATA_ALL!$A:$CU,G$5,FALSE)) -> 0 | H34: =VLOOKUP($C34,DATA_ALL!$A:$CU,H$5,FALSE) -> 0 | I34: =G34+H34 -> 0 | J34: =I34/$J$5 -> 0 | K34: =IFERROR(INDEX('SH Summary'!B:B,MATCH(APAC!C34,'SH Summary'!C:C,0)), "N/A") -> N/A | L34: =VLOOKUP($C34,DATA_ALL!$A:$CU,L$5,FALSE) -> 0 | M34: =L34/M$5 -> 0 | N34: =VLOOKUP($C34,DATA_ALL!$A:$CU,N$5,FALSE) -> 36516764 | O34: =VLOOKUP($C34,DATA_ALL!$A:$CU,O$5,FALSE) -> 0 | P34: =N34+O34 -> 36516764 | Q34: =P34/Q$5 -> 0.00011479649 | R34: =VLOOKUP($C34,DATA_ALL!$A:$CU,R$5,FALSE) -> 0 | S34: =R34/S$5 -> 0 | T34: =VLOOKUP($C34,DATA_ALL!$A:$CU,T$5,FALSE) -> 0 | U34: =VLOOKUP($C34,DATA_ALL!$A:$CU,U$5,FALSE) -> 0 | V34: =T34+U34 -> 0 | W34: =V34/W$5 -> 0 | X34: =VLOOKUP($C34,DATA_ALL!$A:$CU,X$5,FALSE) -> 59528740 | Y34: =X34/Y$5 -> 0.00043642771 | Z34: =VLOOKUP($C34,DATA_ALL!$A:$CU,Z$5,FALSE) -> 0 | AA34: =VLOOKUP($C34,DATA_ALL!$A:$CU,AA$5,FALSE) -> 0 | AB34: =Z34+AA34 -> 0 | AC34: =AB34/AC$5 -> 0 | AD34: =VLOOKUP($C34,DATA_ALL!$A:$CU,AD$5,FALSE) -> 0 | AE34: =VLOOKUP($C34,DATA_ALL!$A:$CU,AE$5,FALSE) -> 0 | AF34: =AD34+AE34 -> 0 | AG34: =AF34/AG$5 -> 0 | AH34: =VLOOKUP($C34,DATA_ALL!$A:$CU,AH$5,FALSE) -> 39797016 | AI34: =AH34/AI$5 -> 0.00050471802 | AJ34: =VLOOKUP($C34,DATA_ALL!$A:$CU,AJ$5,FALSE) -> 85629488 | AK34: =AJ34/AK$5 -> 0.00071716489 | AL34: =VLOOKUP($C34,DATA_ALL!$A:$CU,AL$5,FALSE) -> 23599960 | AM34: =AL34/AM$5 -> 0.00090317489 | AN34: =VLOOKUP($C34,DATA_ALL!$A:$CU,AN$5,FALSE) -> 0 | AO34: =AN34/AO$5 -> 0 | AP34: =VLOOKUP($C34,DATA_ALL!$A:$CU,AP$5,FALSE) -> 0 | AQ34: =AP34/AQ$5 -> 0 | AR34: =VLOOKUP($C34,DATA_ALL!$A:$CU,AR$5,FALSE) -> 0 | AS34: =AR34/AS$5 -> 0 | AT34: =VLOOKUP($C34,DATA_ALL!$A:$CU,AT$5,FALSE) -> 0 | AU34: =AT34/AU$5 -> 0

Sheet ROW
B2: ROW Top Investors
B3: As of 2026Q1, AUM > $50bn
D5: 85 | E5: 90 | F5: 89 | G5: 7 | H5: 9 | J5: 31240000000 | L5: 11 | M5: =4058000000000/7.83 -> 5.1826309e+11 | N5: 13 | O5: 15 | Q5: 318100000000 | R5: 18 | S5: =507200000000/7.83 -> 6.4776501e+10 | T5: 20 | U5: 22 | W5: 72350000000 | X5: 24 | Y5: 136400000000 | Z5: 26 | AA5: 28 | AC5: 43230000000 | AD5: 30 | AE5: 32 | AG5: 46050000000 | AH5: 34 | AI5: 78850000000 | AJ5: 40 | AK5: 119400000000 | AL5: 42 | AM5: 26130000000 | AN5: 44 | AO5: 4108000000 | AP5: 46 | AQ5: 1101000000 | AR5: 48 | AS5: 217100000 | AT5: 50 | AU5: =38560000000/7.83 -> 4.9246488e+09
C6: Institution/Fund Name | D6: Dominant Style | E6: Equity AUM, $bn | F6: Country | I6: TCOM | L6: ADR Peers | AH6: Travel Peers
D7: Dominant Style | G7: TCOM | H7: 9961 | I7: Position | J7: % Mkt Cap | K7: SH Rank | L7: Tencent Position | M7: Tencent % Mkt Cap | N7: BABA | O7: 9988 | P7: BABA Position | Q7: BABA % Mkt Cap | R7: Meituan Position | S7: Meituan % Mkt Cap | T7: NTES | U7: 9999 | V7: NTES Position | W7: NTES % Mkt Cap | X7: PDD Position | Y7: PDD % Mkt Cap | Z7: JD | AA7: 9618 | AB7: JD Position | AC7: JD % Mkt Cap | AD7: BIDU | AE7: 9888 | AF7: BIDU Position | AG7: BIDU % Mkt Cap | AH7: ABNB Position | AI7: Avg % Mkt Cap | AJ7: BKNG Position | AK7: BKNG % Mkt Cap | AL7: EXPE Position | AM7: EXPE % Mkt Cap | AN7: MMYT Position | AO7: MMYT % Mkt Cap | AP7: TRIP Position | AQ7: TRIP % Mkt Cap | AR7: TRVG Position | AS7: TRVG % Mkt Cap | AT7: TC Position | AU7: TC % Mkt Cap
B8: 1 | C8: Mubadala Investment Company, PJSC | D8: =VLOOKUP($C8,DATA_ALL!$A:$CU,D$5,FALSE) -> Growth | E8: =VLOOKUP($C8,DATA_ALL!$A:$CU,E$5,FALSE)/1000000000 -> 56.588896 | F8: =VLOOKUP($C8,DATA_ALL!$A:$CU,F$5,FALSE) -> United Arab Emirates | G8: =IF(VLOOKUP($C8,DATA_ALL!$A:$CU,G$5,FALSE)="N/A",0,VLOOKUP($C8,DATA_ALL!$A:$CU,G$5,FALSE)) -> 0 | H8: =VLOOKUP($C8,DATA_ALL!$A:$CU,H$5,FALSE) -> 0 | I8: =G8+H8 -> 0 | J8: =I8/$J$5 -> 0 | K8: =IFERROR(INDEX('SH Summary'!B:B,MATCH(ROW!C8,'SH Summary'!C:C,0)), "N/A") -> N/A | L8: =VLOOKUP($C8,DATA_ALL!$A:$CU,L$5,FALSE) -> 0 | M8: =L8/M$5 -> 0 | N8: =VLOOKUP($C8,DATA_ALL!$A:$CU,N$5,FALSE) -> 0 | O8: =VLOOKUP($C8,DATA_ALL!$A:$CU,O$5,FALSE) -> 0 | P8: =N8+O8 -> 0 | Q8: =P8/Q$5 -> 0 | R8: =VLOOKUP($C8,DATA_ALL!$A:$CU,R$5,FALSE) -> 0 | S8: =R8/S$5 -> 0 | T8: =VLOOKUP($C8,DATA_ALL!$A:$CU,T$5,FALSE) -> 0 | U8: =VLOOKUP($C8,DATA_ALL!$A:$CU,U$5,FALSE) -> 0 | V8: =T8+U8 -> 0 | W8: =V8/W$5 -> 0 | X8: =VLOOKUP($C8,DATA_ALL!$A:$CU,X$5,FALSE) -> 0 | Y8: =X8/Y$5 -> 0 | Z8: =VLOOKUP($C8,DATA_ALL!$A:$CU,Z$5,FALSE) -> 0 | AA8: =VLOOKUP($C8,DATA_ALL!$A:$CU,AA$5,FALSE) -> 0 | AB8: =Z8+AA8 -> 0 | AC8: =AB8/AC$5 -> 0 | AD8: =VLOOKUP($C8,DATA_ALL!$A:$CU,AD$5,FALSE) -> 0 | AE8: =VLOOKUP($C8,DATA_ALL!$A:$CU,AE$5,FALSE) -> 0 | AF8: =AD8+AE8 -> 0 | AG8: =AF8/AG$5 -> 0 | AH8: =VLOOKUP($C8,DATA_ALL!$A:$CU,AH$5,FALSE) -> 0 | AI8: =AH8/AI$5 -> 0 | AJ8: =VLOOKUP($C8,DATA_ALL!$A:$CU,AJ$5,FALSE) -> 0 | AK8: =AJ8/AK$5 -> 0 | AL8: =VLOOKUP($C8,DATA_ALL!$A:$CU,AL$5,FALSE) -> 0 | AM8: =AL8/AM$5 -> 0 | AN8: =VLOOKUP($C8,DATA_ALL!$A:$CU,AN$5,FALSE) -> 0 | AO8: =AN8/AO$5 -> 0 | AP8: =VLOOKUP($C8,DATA_ALL!$A:$CU,AP$5,FALSE) -> 0 | AQ8: =AP8/AQ$5 -> 0 | AR8: =VLOOKUP($C8,DATA_ALL!$A:$CU,AR$5,FALSE) -> 0 | AS8: =AR8/AS$5 -> 0 | AT8: =VLOOKUP($C8,DATA_ALL!$A:$CU,AT$5,FALSE) -> 0 | AU8: =AT8/AU$5 -> 0

Sheet DATA_ALL
A1: 1 | B1: 2 | C1: 3 | D1: 4 | E1: 5 | F1: 6 | G1: 7 | H1: 8 | I1: 9 | J1: 10 | K1: 11 | L1: 12 | M1: 13 | N1: 14 | O1: 15 | P1: 16 | Q1: 17 | R1: 18 | S1: 19 | T1: 20 | U1: 21 | V1: 22 | W1: 23 | X1: 24 | Y1: 25 | Z1: 26 | AA1: 27 | AB1: 28 | AC1: 29 | AD1: 30 | AE1: 31 | AF1: 32 | AG1: 33 | AH1: 34 | AI1: 35 | AJ1: 36 | AK1: 37 | AL1: 38 | AM1: 39 | AN1: 40 | AO1: 41 | AP1: 42 | AQ1: 43 | AR1: 44 | AS1: 45 | AT1: 46 | AU1: 47 | AV1: 48 | AW1: 49 | AX1: 50 | AY1: 51 | AZ1: 52 | BA1: 53 | BB1: 54 | BC1: 55 | BD1: 56 | BE1: 57 | BF1: 58 | BG1: 59 | BH1: 60 | BI1: 61 | BJ1: 62 | BK1: 63 | BL1: 64 | BM1: 65 | BN1: 66 | BO1: 67 | BP1: 68 | BQ1: 69 | BR1: 70 | BS1: 71 | BT1: 72 | BU1: 73 | BV1: 74 | BW1: 75 | BX1: 76 | BY1: 77 | BZ1: 78 | CA1: 79 | CB1: 80 | CC1: 81 | CD1: 82 | CE1: 83 | CF1: 84 | CG1: 85 | CH1: 86 | CI1: 87 | CJ1: 88 | CK1: 89 | CL1: 90 | CM1: 91 | CN1: 92 | CO1: 93 | CP1: 94 | CQ1: 95 | CR1: 96 | CS1: 97 | CT1: 98 | CU1: 99
A2: Institution | B2: Sustainability Considered | C2: Holder Rank | D2: Shares TCOM | E2: Aggregate Value USD, mm | F2: Shares 9961_XHKG | G2: Value TCOM USD, mm | H2: % Port TCOM | I2: Value 9961_XHKG USD, mm | J2: % Port 9961_XHKG | K2: Value 700_XHKG USD, mm | L2: % Port 700_XHKG | M2: Value BABA USD, mm | N2: % Port BABA | O2: Value 9988_XHKG USD, mm | P2: % Port 9988_XHKG | Q2: Shares ABNB | R2: Value 3690_XHKG USD, mm | S2: % Port 3690_XHKG | T2: Value NTES USD, mm | U2: % Port NTES | V2: Value 9999_XHKG USD, mm | W2: % Port 9999_XHKG | X2: Value PDD USD, mm | Y2: % Port PDD | Z2: Value JD USD, mm | AA2: % Port JD | AB2: Value 9618_XHKG USD, mm | AC2: % Port 9618_XHKG | AD2: Value BIDU USD, mm | AE2: % Port BIDU | AF2: Value 9888_XHKG USD, mm | AG2: % Port 9888_XHKG | AH2: Value ABNB USD, mm | AI2: % Port ABNB | AJ2: Shares 9618_XHKG | AK2: Shares 9999_XHKG | AL2: Shares 9988_XHKG | AM2: Shares 780_XHKG | AN2: Value BKNG USD, mm | AO2: % Port BKNG | AP2: Value EXPE USD, mm | AQ2: % Port EXPE | AR2: Value MMYT USD, mm | AS2: % Port MMYT | AT2: Value TRIP USD, mm | AU2: % Port TRIP | AV2: Value TRVG USD, mm | AW2: % Port TRVG | AX2: Value 780_XHKG USD, mm | AY2: % Port 780_XHKG | AZ2: Shares 3690_XHKG | BA2: Shares PDD | BB2: Shares BABA | BC2: Shares JD | BD2: Shares TRIP | BE2: Shares MMYT | BF2: Shares 9888_XHKG | BG2: Shares 700_XHKG | BH2: Shares EXPE | BI2: Shares BKNG | BJ2: Shares BIDU | BK2: Shares NTES | BL2: Shares TRVG | BM2: % S/O MMYT | BN2: % S/O TCOM | BO2: % S/O 9961_XHKG | BP2: % S/O 9888_XHKG | BQ2: % S/O ABNB | BR2: % S/O 9618_XHKG | BS2: % S/O 700_XHKG | BT2: % S/O 9999_XHKG | BU2: % S/O 9988_XHKG | BV2: % S/O EXPE | BW2: % S/O 780_XHKG | BX2: % S/O 3690_XHKG | BY2: % S/O BKNG | BZ2: % S/O PDD | CA2: % S/O TRVG | CB2: % S/O BIDU | CC2: % S/O BABA | CD2: % S/O JD | CE2: % S/O NTES | CF2: % S/O TRIP | CG2: Style | CH2: Turnover | CI2: City | CJ2: State/Province | CK2: Country/Territory | CL2: Equity Assets USD, mm | CM2: Opportunity Rank | CN2: Investor Type | CO2: Institution Rating | CP2: Purchasing Power | CQ2: Suitability Score | CR2: Last Date Met | CS2: Primary Contacts | CT2: Fund Size | CU2: Region
A3: The Vanguard Group, Inc. | B3: yes | E3: 54087482865 | F3: 21132354 | G3: N/A | I3: 1026978790 | J3: 0.01 | K3: 13476680302 | L3: 0.17 | M3: 64361 | N3: 0 | O3: 9594202081 | P3: 0.12 | Q3: 37985017 | R3: 1990217324 | S3: 0.02 | V3: 1399520043 | W3: 0.02 | X3: 3367130490 | Y3: 0.04 | Z3: 1479 | AA3: 0 | AB3: 1250721183 | AC3: 0.02 | AD3: 2786 | AE3: 0 | AF3: 1020628020 | AG3: 0.01 | AH3: 4796747947 | AI3: 0.06 | AJ3: 86575981 | AK3: 64318822 | AL3: 631749989 | AM3: 44219085 | AN3: 12543301138 | AO3: 0.16 | AP3: 3381632257 | AQ3: 0.04 | AR3: 3159582 | AS3: 0 | AT3: 134917256 | AU3: 0 | AX3: 101577826 | AY3: 0 | AZ3: 188004158 | BA3: 32952931 | BB3: 513 | BC3: 50 | BD3: 12656403 | BE3: 84730 | BF3: 75661656 | BG3: 218182999 | BH3: 14646075 | BI3: 74479500 | BJ3: 25 | BM3: 0.09 | BO3: 3.07 | BP3: 3.26 | BQ3: 9.07 | BR3: 3.47 | BS3: 2.39 | BT3: 2 | BU3: 3.29 | BV3: 12.52 | BW3: 1.88 | BX3: 3.36 | BY3: 9.61 | BZ3: 0.58 | CB3: 0 | CC3: 0 | CD3: 0 | CF3: 10.88 | CG3: Index | CH3: 4.761 | CI3: Malvern | CJ3: Pennsylvania | CK3: United States | CL3: 7960929576394 | CN3: Investment Manager-Mutual Fund | CT3: =IF(CL3>100000000000, "100bn", IF(CL3>50000000000, "50bn - 100bn",IF(CL3>1000000000, "1bn - 50bn", IF(CL3>500000000, "500mn - 1bn", "500mn")))) -> 100bn | CU3: =VLOOKUP(CK3,Mapping!B:C,2,FALSE) -> US/CA
A4: BlackRock Fund Advisors | B4: yes | C4: 49 | D4: 594873 | E4: 34731842326 | F4: 16660243 | G4: 29618727 | H4: 0 | I4: 858321319 | J4: 0.02 | K4: 8753867028 | L4: 0.18 | M4: 108616619 | N4: 0 | O4: 6864586154 | P4: 0.14 | Q4: 19857919 | R4: 1363990894 | S4: 0.03 | T4: 912423 | U4: 0 | V4: 1146135089 | W4: 0.02 | X4: 2385668497 | Y4: 0.05 | Z4: 4585154 | AA4: 0 | AB4: 994000363 | AC4: 0.02 | AD4: 99411598 | AE4: 0 | AF4: 1070697604 | AG4: 0.02 | AH4: 2507658011 | AI4: 0.05 | AJ4: 65812657 | AK4: 48812926 | AL4: 401928697 | AM4: 33362926 | AN4: 6677058071 | AO4: 0.14 | AP4: 1620974559 | AQ4: 0.03 | AR4: 4662592 | AS4: 0 | AT4: 165075526 | AU4: 0 | AX4: 76002098 | AY4: 0 | AZ4: 128561148 | BA4: 23347705 | BB4: 865747 | BC4: 155061 | BD4: 15485509 | BE4: 125036 | BF4: 59996540 | BG4: 147567428 | BH4: 7020549 | BI4: 39646975 | BJ4: 892224 | BK4: 8151 | BM4: 0.14 | BN4: 0.09 | BO4: 2.42 | BP4: 2.58 | BQ4: 4.74 | BR4: 2.64 | BS4: 1.62 | BT4: 1.52 | BU4: 2.09 | BV4: 6 | BW4: 1.42 | BX4: 2.3 | BY4: 5.12 | BZ4: 0.41 | CB4: 0.31 | CC4: 0.04 | CD4: 0.01 | CE4: 0 | CF4: 13.31 | CG4: Index | CH4: 7.486 | CI4: San Francisco | CJ4: California | CK4: United States | CL4: 4837463753757 | CM4: 10132 | CN4: Investment Manager-Mutual Fund | CO4: NR | CP4: 28201161 | CQ4: 70 | CT4: =IF(CL4>100000000000, "100bn", IF(CL4>50000000000, "50bn - 100bn",IF(CL4>1000000000, "1bn - 50bn", IF(CL4>500000000, "500mn - 1bn", "500mn")))) -> 100bn | CU4: =VLOOKUP(CK4,Mapping!B:C,2,FALSE) -> US/CA
A5: State Street Investment Management | B5: yes | C5: 287 | D5: 14425 | E5: 12953391769 | F5: 1320932 | G5: 718221 | H5: 0 | I5: 68099849 | J5: 0 | K5: 872445888 | L5: 0.03 | M5: 60529933 | N5: 0 | O5: 704013706 | P5: 0.02 | Q5: 17733208 | R5: 128450102 | S5: 0 | T5: 3903012 | U5: 0 | V5: 104596181 | W5: 0 | X5: 1229603159 | Y5: 0.04 | Z5: 4435145 | AA5: 0 | AB5: 101549754 | AC5: 0 | AD5: 9633707 | AE5: 0 | AF5: 91757505 | AG5: 0 | AH5: 2239349506 | AI5: 0.07 | AJ5: 6371146 | AK5: 4471403 | AL5: 42382774 | AM5: 2292507 | AN5: 5982005815 | AO5: 0.19 | AP5: 1291250709 | AQ5: 0.04 | AR5: 3801529 | AS5: 0 | AT5: 52111890 | AU5: 0 | AX5: 5136158 | AY5: 0 | AZ5: 11633686 | BA5: 12033697 | BB5: 482464 | BC5: 149988 | BD5: 4888545 | BE5: 101945 | BF5: 5485621 | BG5: 14643943 | BH5: 5592493 | BI5: 35519900 | BJ5: 86463 | BK5: 34867 | BM5: 0.11 | BN5: 0 | BO5: 0.19 | BP5: 0.24 | BQ5: 4.23 | BR5: 0.26 | BS5: 0.16 | BT5: 0.14 | BU5: 0.22 | BV5: 4.78 | BW5: 0.1 | BX5: 0.21 | BY5: 4.58 | BZ5: 0.21 | CB5: 0.03 | CC5: 0.02 | CD5: 0.01 | CE5: 0 | CF5: 4.2 | CG5: Index | CH5: 4.987 | CI5: Boston | CJ5: Massachusetts | CK5: United States | CL5: 3127653596080 | CM5: 10130 | CN5: Investment Manager-Mutual Fund | CO5: NR | CP5: 36086205 | CQ5: 72 | CT5: =IF(CL5>100000000000, "100bn", IF(CL5>50000000000, "50bn - 100bn",IF(CL5>1000000000, "1bn - 50bn", IF(CL5>500000000, "500mn - 1bn", "500mn")))) -> 100bn | CU5: =VLOOKUP(CK5,Mapping!B:C,2,FALSE) -> US/CA
A6: Davis Selected Advisers, L.P. | B6: no | C6: 4 | D6: 6555112 | E6: 439300001 | G6: 326379026 | H6: 1.3 | R6: 57221924 | S6: 0.23 | T6: 47318381 | U6: 0.19 | Z6: 8380670 | AA6: 0.03 | AZ6: 4763087 | BC6: 283418 | BK6: 422712 | BN6: 0.95 | BX6: 0.09 | CD6: 0.02 | CE6: 0.01 | CG6: Value | CH6: 26.916 | CI6: New York | CJ6: New York | CK6: United States | CL6: 25230328351 | CM6: 1260 | CN6: Investment Manager-Mutual Fund | CO6: HM | CP6: -4605870 | CQ6: 90 | CR6: 46042.542 | CT6: =IF(CL6>100000000000, "100bn", IF(CL6>50000000000, "50bn - 100bn",IF(CL6>1000000000, "1bn - 50bn", IF(CL6>500000000, "500mn - 1bn", "500mn")))) -> 1bn - 50bn | CU6: =VLOOKUP(CK6,Mapping!B:C,2,FALSE) -> US/CA
A7: Rothschild & Co Asset Management Europe SCS | B7: yes | C7: 5 | D7: 4894574 | E7: 887028777 | G7: 243700839 | H7: 1.64 | K7: 313822158 | L7: 2.11 | M7: 893650 | N7: 0.01 | O7: 325851365 | P7: 2.2 | AB7: 45378 | AC7: 0 | AJ7: 2785 | AL7: 21456354 | AM7: 755015 | AN7: 981005 | AO7: 0.01 | AX7: 1734382 | AY7: 0.01 | BB7: 5000 | BG7: 5080677 | BI7: 5825 | BN7: 0.71 | BR7: 0 | BS7: 0.06 | BU7: 0.11 | BW7: 0.03 | BY7: 0 | CC7: 0 | CG7: GARP | CH7: 37.46 | CI7: Paris | CK7: France | CL7: 14841382794 | CM7: 5290 | CN7: Investment Manager-Mutual Fund | CO7: HM | CP7: -4165851.9 | CQ7: 91 | CR7: 45996.417 | CT7: =IF(CL7>100000000000, "100bn", IF(CL7>50000000000, "50bn - 100bn",IF(CL7>1000000000, "1bn - 50bn", IF(CL7>500000000, "500mn - 1bn", "500mn")))) -> 1bn - 50bn | CU7: =VLOOKUP(CK7,Mapping!B:C,2,FALSE) -> EU
A8: Cantillon Capital Management, LLC (U.S.) | B8: no | C8: 6 | D8: 4589621 | E8: 228517230 | G8: 228517230 | H8: 1.42 | BN8: 0.67 | CG8: GARP | CH8: 16.613 | CI8: New York | CJ8: New York | CK8: United States | CL8: 16051141096 | CM8: 12 | CN8: Investment Manager | CO8: HT | CP8: 3394363.7 | CQ8: 98 | CR8: 46093.021 | CT8: =IF(CL8>100000000000, "100bn", IF(CL8>50000000000, "50bn - 100bn",IF(CL8>1000000000, "1bn - 50bn", IF(CL8>500000000, "500mn - 1bn", "500mn")))) -> 1bn - 50bn | CU8: =VLOOKUP(CK8,Mapping!B:C,2,FALSE) -> US/CA
A9: Arga Investment Management, L.P. | B9: yes | C9: 7 | D9: 2861617 | E9: 334100526 | G9: 142479910 | H9: 2.19 | K9: 85325633 | L9: 1.31 | M9: 21661924 | N9: 0.33 | O9: 84633059 | P9: 1.3 | AD9: 0 | AE9: 0 | AL9: 4970200 | BB9: 172660 | BG9: 1289679 | BJ9: 0 | BN9: 0.42 | BS9: 0.01 | BU9: 0.03 | CB9: 0 | CC9: 0.01 | CG9: Value | CH9: 59.284 | CI9: Stamford | CJ9: Connecticut | CK9: United States | CL9: 6544176802 | CM9: 3006 | CN9: Investment Manager | CO9: HM | CP9: -1938263.4 | CQ9: 91 | CR9: 45980.521 | CT9: =IF(CL9>100000000000, "100bn", IF(CL9>50000000000, "50bn - 100bn",IF(CL9>1000000000, "1bn - 50bn", IF(CL9>500000000, "500mn - 1bn", "500mn")))) -> 1bn - 50bn | CU9: =VLOOKUP(CK9,Mapping!B:C,2,FALSE) -> US/CA
A10: Norges Bank Investment Management (Norway) | B10: yes | C10: 106 | D10: 164868 | E10: 26864027092 | F10: 10813028 | G10: 11855658 | H10: 0 | I10: 769833066 | J10: 0.05 | K10: 9440457078 | L10: 0.6 | M10: 594477324 | N10: 0.04 | O10: 7249634953 | P10: 0.46 | Q10: 3539136 | R10: 1140758383 | S10: 0.07 | T10: 2299905 | U10: 0 | V10: 627009631 | W10: 0.04 | X10: 1065445550 | Y10: 0.07 | Z10: 0 | AA10: 0 | AB10: 750504103 | AC10: 0.05 | AF10: 460620666 | AG10: 0.03 | AH10: 480331538 | AI10: 0.03 | AJ10: 46060649 | AK10: 22735527 | AL10: 395046722 | AM10: 16469661 | AN10: 3271040919 | AO10: 0.21 | AP10: 861979458 | AQ10: 0.05 | AR10: 90283960 | AS10: 0.01 | AT10: 0 | AU10: 0 | AX10: 47494900 | AY10: 0 | AZ10: 85931794 | BA10: 9396292 | BB10: 4055651 | BC10: 0 | BD10: 0 | BE10: 1099415 | BF10: 27257009 | BG10: 122638472 | BH10: 3042531 | BI10: 15270025 | BK10: 16712 | BM10: 1.23 | BN10: 0.02 | BO10: 1.57 | BP10: 1.17 | BQ10: 0.84 | BR10: 1.84 | BS10: 1.35 | BT10: 0.71 | BU10: 2.06 | BV10: 2.6 | BW10: 0.7 | BX10: 1.54 | BY10: 1.97 | BZ10: 0.17 | CC10: 0.17 | CD10: 0 | CE10: 0 | CF10: 0 | CG10: Value | CH10: 20.194 | CI10: Oslo | CK10: Norway | CL10: 1551847282513 | CM10: 295 | CN10: Sovereign Wealth Fund | CO10: SWF | CP10: 776509.98 | CQ10: 77 | CR10: 45994.146 | CT10: =IF(CL10>100000000000, "100bn", IF(CL10>50000000000, "50bn - 100bn",IF(CL10>1000000000, "1bn - 50bn", IF(CL10>500000000, "500mn - 1bn", "500mn")))) -> 100bn | CU10: =VLOOKUP(CK10,Mapping!B:C,2,FALSE) -> EU
A11: BlackRock Investment Management (U.K.), LTD | B11: yes | C11: 50 | D11: 524212 | E11: 5714433537 | F11: 192211 | G11: 26100515 | H11: 0 | I11: 11071095 | J11: 0 | K11: 131954503 | L11: 0.01 | M11: 30766430 | N11: 0 | O11: 373143514 | P11: 0.03 | Q11: 7541897 | R11: 75524698 | S11: 0.01 | T11: 7917628 | U11: 0 | V11: 21900967 | W11: 0 | X11: 1231258271 | Y11: 0.1 | Z11: 29184289 | AA11: 0 | AB11: 16856502 | AC11: 0 | AD11: 83207342 | AE11: 0.01 | AF11: 4781617 | AG11: 0 | AH11: 952390753 | AI11: 0.08 | AJ11: 1136909 | AK11: 870618 | AL11: 26676023 | AM11: 356913 | AN11: 2237376679 | AO11: 0.19 | AP11: 473003794 | AQ11: 0.04 | AR11: 1307425 | AS11: 0 | AT11: 5700510 | AU11: 0 | AX11: 987005 | AY11: 0 | AZ11: 7118480 | BA11: 12049895 | BB11: 245229 | BC11: 986956 | BD11: 534757 | BE11: 35061 | BF11: 294577 | BG11: 2015676 | BH11: 2048611 | BI11: 13285075 | BJ11: 746790 | BK11: 70731 | BM11: 0.04 | BN11: 0.08 | BO11: 0.03 | BP11: 0.01 | BQ11: 1.8 | BR11: 0.05 | BS11: 0.02 | BT11: 0.03 | BU11: 0.14 | BV11: 1.75 | BW11: 0.02 | BX11: 0.13 | BY11: 1.71 | BZ11: 0.21 | CB11: 0.26 | CC11: 0.01 | CD11: 0.08 | CE11: 0 | CF11: 0.46 | CG11: Growth | CH11: 12.186 | CI11: London | CK11: United Kingdom | CL11: 1184413742089 | CM11: 38 | CN11: Investment Manager-Mutual Fund | CO11: HT | CP11: 13408319 | CQ11: 73 | CT11: =IF(CL11>100000000000, "100bn", IF(CL11>50000000000, "50bn - 100bn",IF(CL11>1000000000, "1bn - 50bn", IF(CL11>500000000, "500mn - 1bn", "500mn")))) -> 100bn | CU11: =VLOOKUP(CK11,Mapping!B:C,2,FALSE) -> EU
A12: Greenwoods Asset Management, LTD (China) | B12: no | C12: 10 | D12: 2604281 | E12: 1110951244 | G12: 129667151 | H12: 3.23 | M12: 88199509 | N12: 2.2 | T12: 357088600 | U12: 8.9 | X12: 521506693 | Y12: 12.99 | AR12: 14489291 | AS12: 0.36 | BA12: 5103804 | BB12: 703009 | BE12: 388557 | BK12: 3190000 | BM12: 0.43 | BN12: 0.38 | BZ12: 0.09 | CC12: 0.03 | CE12: 0.1 | CG12: Alternative | CH12: 73.415 | CI12: Shanghai | CK12: China (Mainland) | CL12: 4004956787 | CM12: 5305 | CN12: Hedge Fund | CO12: HM | CP12: -890086.21 | CQ12: 100 | CT12: =IF(CL12>100000000000, "100bn", IF(CL12>50000000000, "50bn - 100bn",IF(CL12>1000000000, "1bn - 50bn", IF(CL12>500000000, "500mn - 1bn", "500mn")))) -> 1bn - 50bn | CU12: =VLOOKUP(CK12,Mapping!B:C,2,FALSE) -> CN
A13: Fidelity Management & Research Company, LLC | B13: yes | C13: 40 | D13: 705854 | E13: 6101382865 | F13: 144763 | G13: 35144471 | H13: 0 | I13: 7035115 | J13: 0 | K13: 2435922618 | L13: 0.13 | M13: 692326420 | N13: 0.04 | O13: 117834936 | P13: 0.01 | Q13: 6764086 | R13: 6917848 | S13: 0 | T13: 30443650 | U13: 0 | V13: 30113333 | W13: 0 | X13: 261077972 | Y13: 0.01 | Z13: 7966513 | AA13: 0 | AB13: 373591 | AC13: 0 | AD13: 1913861 | AE13: 0 | AF13: 8917061 | AG13: 0 | AH13: 854168780 | AI13: 0.04 | AJ13: 23897 | AK13: 1278613 | AL13: 6537620 | AN13: 1259315133 | AO13: 0.07 | AP13: 306660248 | AQ13: 0.02 | AR13: 45190446 | AS13: 0 | AT13: 60869 | AU13: 0 | AZ13: 666133 | BA13: 2555079 | BB13: 5518304 | BC13: 269412 | BD13: 5710 | BE13: 1211865 | BF13: 570266 | BG13: 39070987 | BH13: 1328166 | BI13: 7477550 | BJ13: 17177 | BK13: 271964 | BM13: 1.35 | BN13: 0.1 | BO13: 0.02 | BP13: 0.02 | BQ13: 1.61 | BR13: 0 | BS13: 0.43 | BT13: 0.04 | BU13: 0.03 | BV13: 1.14 | BX13: 0.01 | BY13: 0.96 | BZ13: 0.04 | CB13: 0.01 | CC13: 0.23 | CD13: 0.02 | CE13: 0.01 | CF13: 0 | CG13: Growth | CH13: 24.363 | CI13: Boston | CJ13: Massachusetts | CK13: United States | CL13: 1923778537161 | CM13: 35 | CN13: Investment Manager-Mutual Fund | CO13: HT | CP13: 22696316 | CQ13: 67 | CR13: 46002.333 | CT13: =IF(CL13>100000000000, "100bn", IF(CL13>50000000000, "50bn - 100bn",IF(CL13>1000000000, "1bn - 50bn", IF(CL13>500000000, "500mn - 1bn", "500mn")))) -> 100bn | CU13: =VLOOKUP(CK13,Mapping!B:C,2,FALSE) -> US/CA
A14: Aspex Management (HK), LTD | B14: no | C14: 12 | D14: 2329290 | E14: 132503850 | G14: 115975349 | H14: 1.47 | T14: 16528501 | U14: 0.21 | X14: 0 | Y14: 0 | AD14: 0 | AE14: 0 | BA14: 0 | BJ14: 0 | BK14: 147655 | BN14: 0.34 | BZ14: 0 | CB14: 0 | CE14: 0 | CG14: Growth | CH14: 118.608 | CI14: Central | CK14: Hong Kong SAR | CL14: 7574057446 | CM14: 10154 | CN14: Family Office | CO14: NR | CP14: 5940207.1 | CQ14: 99 | CR14: 45988.292 | CT14: =IF(CL14>100000000000, "100bn", IF(CL14>50000000000, "50bn - 100bn",IF(CL14>1000000000, "1bn - 50bn", IF(CL14>500000000, "500mn - 1bn", "500mn")))) -> 1bn - 50bn | CU14: =VLOOKUP(CK14,Mapping!B:C,2,FALSE) -> HK
A15: Geode Capital Management, LLC | B15: yes | C15: 91 | D15: 208476 | E15: 11754062926 | F15: 3125582 | G15: 10380020 | H15: 0 | I15: 152783674 | J15: 0.01 | K15: 2237948674 | L15: 0.12 | O15: 1496259102 | P15: 0.08 | Q15: 10401089 | R15: 266774512 | S15: 0.01 | T15: 7923561 | U15: 0 | V15: 196254479 | W15: 0.01 | X15: 700232081 | Y15: 0.04 | Z15: 11906952 | AA15: 0 | AB15: 332317094 | AC15: 0.02 | AD15: 10521056 | AE15: 0 | AF15: 273988693 | AG15: 0.01 | AH15: 1313449519 | AI15: 0.07 | AJ15: 22988103 | AK15: 8975591 | AL15: 98235119 | AM15: 7660562 | AN15: 3751980354 | AO15: 0.2 | AP15: 928927962 | AQ15: 0.05 | AR15: 14582590 | AS15: 0 | AT15: 30292916 | AU15: 0 | AV15: 29721 | AW15: 0 | AX15: 17509966 | AY15: 0 | AZ15: 25178760 | BA15: 6852927 | BC15: 402670 | BD15: 2841737 | BE15: 391059 | BF15: 20186521 | BG15: 36272722 | BH15: 4023249 | BI15: 22278475 | BJ15: 94427 | BK15: 70784 | BL15: 10967 | BM15: 0.44 | BN15: 0.03 | BO15: 0.45 | BP15: 0.87 | BQ15: 2.48 | BR15: 0.92 | BS15: 0.4 | BT15: 0.28 | BU15: 0.51 | BV15: 3.44 | BW15: 0.33 | BX15: 0.45 | BY15: 2.88 | BZ15: 0.12 | CA15: 0.01 | CB15: 0.03 | CD15: 0.03 | CE15: 0 | CF15: 2.44 | CG15: Index | CH15: 6.84 | CI15: Boston | CJ15: Massachusetts | CK15: United States | CL15: 1890862823441 | CM15: 10135 | CN15: Investment Manager-Mutual Fund | CO15: NR | CP15: 17047970 | CQ15: 71 | CT15: =IF(CL15>100000000000, "100bn", IF(CL15>50000000000, "50bn - 100bn",IF(CL15>1000000000, "1bn - 50bn", IF(CL15>500000000, "500mn - 1bn", "500mn")))) -> 100bn | CU15: =VLOOKUP(CK15,Mapping!B:C,2,FALSE) -> US/CA
A16: Nomura Asset Management Company, LTD | B16: yes | C16: 230 | D16: 25621 | E16: 186147150 | F16: 62697 | G16: 1522656 | H16: 0 | I16: 2555499 | J16: 0 | K16: 40449568 | L16: 0.01 | O16: 19689423 | P16: 0.01 | Q16: 164713 | R16: 10196953 | S16: 0 | T16: 216044 | U16: 0 | V16: 4317585 | W16: 0 | X16: 13193788 | Y16: 0 | Z16: 1079305 | AA16: 0 | AB16: 249472 | AC16: 0 | AF16: 77917 | AG16: 0 | AH16: 20799958 | AI16: 0.01 | AJ16: 263587 | AK16: 218569 | AL16: 1866056 | AM16: 128369 | AN16: 62102220 | AO16: 0.02 | AP16: 9403457 | AQ16: 0 | AR16: 0 | AS16: 0 | AX16: 293305 | AY16: 0 | AZ16: 719427 | BA16: 129123 | BC16: 36500 | BE16: 0 | BF16: 5092 | BG16: 866320 | BH16: 40727 | BI16: 368750 | BK16: 1930 | BM16: 0 | BN16: 0 | BO16: 0.01 | BP16: 0 | BQ16: 0.04 | BR16: 0.01 | BS16: 0.01 | BT16: 0.01 | BU16: 0.01 | BV16: 0.03 | BW16: 0.01 | BX16: 0.01 | BY16: 0.05 | BZ16: 0 | CD16: 0 | CE16: 0 | CG16: Deep Value | CH16: 10.268 | CI16: Tokyo | CK16: Japan | CL16: 392472623476 | CM16: 153 | CN16: Investment Manager-Mutual Fund | CO16: NR | CP16: 14992516 | CQ16: 68 | CT16: =IF(CL16>100000000000, "100bn", IF(CL16>50000000000, "50bn - 100bn",IF(CL16>1000000000, "1bn - 50bn", IF(CL16>500000000, "500mn - 1bn", "500mn")))) -> 100bn | CU16: =VLOOKUP(CK16,Mapping!B:C,2,FALSE) -> Asia
A17: Morgan Stanley & Company, LLC | B17: no | C17: 31 | D17: 970349 | E17: 2647793773 | G17: 48313677 | H17: 0 | M17: 600585049 | N17: 0.06 | Q17: 1853678 | T17: 46568831 | U17: 0 | X17: 509740359 | Y17: 0.05 | Z17: 76065306 | AA17: 0.01 | AD17: 71150806 | AE17: 0.01 | AH17: 234082458 | AI17: 0.02 | AN17: 816107377 | AO17: 0.08 | AP17: 186588443 | AQ17: 0.02 | AR17: 45723245 | AS17: 0 | AT17: 12022710 | AU17: 0 | AV17: 845512 | AW17: 0 | BA17: 4988651 | BB17: 4787064 | BC17: 2572381 | BD17: 1127834 | BE17: 1226153 | BH17: 808127 | BI17: 4845875 | BJ17: 638582 | BK17: 416016 | BL17: 311997 | BM17: 1.37 | BN17: 0.14 | BQ17: 0.44 | BV17: 0.69 | BY17: 0.63 | BZ17: 0.09 | CA17: 0.27 | CB17: 0.22 | CC17: 0.2 | CD17: 0.21 | CE17: 0.01 | CF17: 0.97 | CG17: Broker | CH17: 23.235 | CI17: New York | CJ17: New York | CK17: United States | CL17: 1040234684579 | CN17: Broker | CT17: =IF(CL17>100000000000, "100bn", IF(CL17>50000000000, "50bn - 100bn",IF(CL17>1000000000, "1bn - 50bn", IF(CL17>500000000, "500mn - 1bn", "500mn")))) -> 100bn | CU17: =VLOOKUP(CK17,Mapping!B:C,2,FALSE) -> US/CA
A18: Federated Hermes, LTD (HIML) | B18: yes | C18: 16 | D18: 1777374 | E18: 968715976 | F18: 429116 | G18: 88495451 | H18: 0.52 | I18: 20853949 | J18: 0.12 | K18: 490568942 | L18: 2.89 | M18: 47009987 | N18: 0.28 | O18: 69920018 | P18: 0.41 | Q18: 27260 | R18: 0 | S18: 0 | Z18: 83619791 | AA18: 0.49 | AB18: 145103423 | AC18: 0.85 | AD18: 1537150 | AE18: 0.01 | AF18: 293771 | AG18: 0 | AH18: 3442393 | AI18: 0.02 | AJ18: 10044182 | AL18: 3909696 | AN18: 8471164 | AO18: 0.05 | AP18: 2839023 | AQ18: 0.02 | AR18: 6560914 | AS18: 0.04 | AZ18: 0 | BB18: 374701 | BC18: 2827859 | BE18: 175943 | BF18: 21778 | BG18: 7942149 | BH18: 12296 | BI18: 50300 | BJ18: 13796 | BM18: 0.2 | BN18: 0.26 | BO18: 0.06 | BP18: 0 | BQ18: 0.01 | BR18: 0.4 | BS18: 0.09 | BU18: 0.02 | BV18: 0.01 | BX18: 0 | BY18: 0.01 | CB18: 0 | CC18: 0.02 | CD18: 0.23 | CG18: GARP | CH18: 48.423 | CI18: London | CK18: United Kingdom | CL18: 16922880638 | CM18: 5313 | CN18: Investment Manager-Mutual Fund | CO18: HM | CP18: -1643968 | CQ18: 89 | CR18: 45993.625 | CT18: =IF(CL18>100000000000, "100bn", IF(CL18>50000000000, "50bn - 100bn",IF(CL18>1000000000, "1bn - 50bn", IF(CL18>500000000, "500mn - 1bn", "500mn")))) -> 1bn - 50bn | CU18: =VLOOKUP(CK18,Mapping!B:C,2,FALSE) -> EU
A19: Capital World Investors (U.S.) | B19: no | C19: 1 | D19: 36115209 | E19: 11881212363 | F19: 4395163 | G19: 1798176256 | H19: 0.18 | I19: 213593771 | J19: 0.02 | K19: 3767409476 | L19: 0.37 | M19: 521674850 | N19: 0.05 | O19: 633177438 | P19: 0.06 | R19: 84785617 | S19: 0.01 | T19: 60580585 | U19: 0.01 | V19: 1087319590 | W19: 0.11 | AD19: 133513583 | AE19: 0.01 | AF19: 342567255 | AG19: 0.03 | AK19: 49970785 | AL19: 41692872 | AN19: 3238413942 | AO19: 0.32 | AR19: 0 | AS19: 0 | AZ19: 8009200 | BB19: 4158097 | BE19: 0 | BF19: 25395350 | BG19: 60993114 | BI19: 19229025 | BJ19: 1198291 | BK19: 541188 | BM19: 0 | BN19: 5.24 | BO19: 0.64 | BP19: 1.09 | BS19: 0.67 | BT19: 1.55 | BU19: 0.22 | BX19: 0.14 | BY19: 2.48 | CB19: 0.41 | CC19: 0.17 | CE19: 0.02 | CG19: Value | CH19: 34.246 | CI19: Los Angeles | CJ19: California | CK19: United States | CL19: 1022594898625 | CM19: 1631 | CN19: Investment Manager-Mutual Fund | CO19: HM | CP19: -26018654 | CQ19: 90 | CR19: 45994.049 | CT19: =IF(CL19>100000000000, "100bn", IF(CL19>50000000000, "50bn - 100bn",IF(CL19>1000000000, "1bn - 50bn", IF(CL19>500000000, "500mn - 1bn", "500mn")))) -> 100bn | CU19: =VLOOKUP(CK19,Mapping!B:C,2,FALSE) -> US/CA
A20: Invesco Capital Management, LLC | B20: yes | C20: 87 | D20: 226256 | E20: 9120309132 | F20: 197863 | G20: 11833227 | H20: 0 | I20: 10317926 | J20: 0 | K20: 334830016 | L20: 0.04 | M20: 19435887 | N20: 0 | O20: 119164271 | P20: 0.01 | Q20: 14370959 | R20: 277033967 | S20: 0.03 | T20: 23837637 | U20: 0 | V20: 19518971 | W20: 0 | X20: 2035832434 | Y20: 0.23 | Z20: 57162757 | AA20: 0.01 | AB20: 11448235 | AC20: 0 | AD20: 22552726 | AE20: 0 | AF20: 273259595 | AG20: 0.03 | AH20: 1909954728 | AI20: 0.22 | AJ20: 708138 | AK20: 818116 | AL20: 7102277 | AM20: 82425 | AN20: 3626268203 | AO20: 0.42 | AP20: 352372501 | AQ20: 0.04 | AR20: 528325 | AS20: 0 | AT20: 14772116 | AU20: 0 | AX20: 185610 | AY20: 0 | AZ20: 24706586 | BA20: 20439007 | BB20: 154917 | BC20: 1693012 | BD20: 1385752 | BE20: 14168 | BF20: 15581369 | BG20: 5657205 | BH20: 1615425 | BI20: 23377742 | BJ20: 149852 | BK20: 198879 | BM20: 0.02 | BN20: 0.03 | BO20: 0.03 | BP20: 0.67 | BQ20: 3.43 | BR20: 0.03 | BS20: 0.06 | BT20: 0.03 | BU20: 0.04 | BV20: 1.38 | BW20: 0 | BX20: 0.44 | BY20: 3.02 | BZ20: 0.36 | CB20: 0.05 | CC20: 0.01 | CD20: 0.14 | CE20: 0.01 | CF20: 1.19 | CG20: Index | CH20: 16.381 | CI20: Downers Grove | CJ20: Illinois | CK20: United States | CL20: 866328911040 | CM20: 10141 | CN20: Investment Manager-Mutual Fund | CO20: NR | CP20: 10023627 | CQ20: 80 | CT20: =IF(CL20>100000000000, "100bn", IF(CL20>50000000000, "50bn - 100bn",IF(CL20>1000000000, "1bn - 50bn", IF(CL20>500000000, "500mn - 1bn", "500mn")))) -> 100bn | CU20: =VLOOKUP(CK20,Mapping!B:C,2,FALSE) -> US/CA
A21: J.P. Morgan Investment Management, Inc. | B21: yes | C21: 13 | D21: 2269598 | E21: 8168723769 | F21: 187827 | G21: 113003284 | H21: 0.01 | I21: 9341397 | J21: 0 | K21: 224275442 | L21: 0.03 | M21: 1771015065 | N21: 0.21 | O21: 2918718602 | P21: 0.34 | Q21: 935016 | R21: 25587965 | S21: 0 | T21: 3840885 | U21: 0 | V21: 45747336 | W21: 0.01 | X21: 76225565 | Y21: 0.01 | Z21: 2987 | AA21: 0 | AB21: 8699219 | AC21: 0 | AD21: 74540 | AE21: 0 | AF21: 8990398 | AG21: 0 | AH21: 118073820 | AI21: 0.01 | AJ21: 580050 | AK21: 2081387 | AL21: 173461351 | AM21: 166800 | AN21: 2277324195 | AO21: 0.27 | AP21: 479564764 | AQ21: 0.06 | AR21: 87313155 | AS21: 0.01 | AT21: 541986 | AU21: 0 | AX21: 383164 | AY21: 0 | AZ21: 2417145 | BA21: 745993 | BB21: 14116173 | BC21: 101 | BD21: 50843 | BE21: 2341463 | BF21: 621450 | BG21: 3619242 | BH21: 2077027 | BI21: 13522275 | BJ21: 669 | BK21: 34312 | BM21: 2.61 | BN21: 0.33 | BO21: 0.03 | BP21: 0.03 | BQ21: 0.22 | BR21: 0.02 | BS21: 0.04 | BT21: 0.06 | BU21: 0.9 | BV21: 1.78 | BW21: 0.01 | BX21: 0.04 | BY21: 1.75 | BZ21: 0.01 | CB21: 0 | CC21: 0.59 | CD21: 0 | CE21: 0 | CF21: 0.04 | CG21: Growth | CH21: 29.371 | CI21: New York | CJ21: New York | CK21: United States | CL21: 846468087667 | CM21: 29 | CN21: Investment Manager-Mutual Fund | CO21: HT | CP21: 8218660.4 | CQ21: 76 | CT21: =IF(CL21>100000000000, "100bn", IF(CL21>50000000000, "50bn - 100bn",IF(CL21>1000000000, "1bn - 50bn", IF(CL21>500000000, "500mn - 1bn", "500mn")))) -> 100bn | CU21: =VLOOKUP(CK21,Mapping!B:C,2,FALSE) -> US/CA
A22: T. Rowe Price Associates, Inc. | B22: yes | C22: 523 | D22: 38 | E22: 5936684602 | F22: 0 | G22: 1892 | H22: 0 | I22: 0 | J22: 0 | K22: 458921196 | L22: 0.06 | M22: 52886910 | N22: 0.01 | O22: 184430096 | P22: 0.02 | Q22: 2597543 | R22: 1827350 | S22: 0 | V22: 341922 | W22: 0 | X22: 77423727 | Y22: 0.01 | AH22: 328017730 | AI22: 0.04 | AK22: 16750 | AL22: 12065097 | AM22: 29212000 | AN22: 4687235577 | AO22: 0.59 | AP22: 73556244 | AQ22: 0.01 | AR22: 4937681 | AS22: 0 | AX22: 67104277 | AY22: 0.01 | AZ22: 136100 | BA22: 757719 | BB22: 421544 | BE22: 132413 | BG22: 7323481 | BH22: 318577 | BI22: 27831825 | BM22: 0.15 | BN22: 0 | BO22: 0 | BQ22: 0.62 | BS22: 0.08 | BT22: 0 | BU22: 0.06 | BV22: 0.27 | BW22: 1.24 | BX22: 0 | BY22: 3.59 | BZ22: 0.01 | CC22: 0.02 | CG22: Growth | CH22: 31.665 | CI22: Baltimore | CJ22: Maryland | CK22: United States | CL22: 791419115054 | CM22: 7 | CN22: Investment Manager-Mutual Fund | CO22: HT | CP22: 12070201 | CQ22: 87 | CR22: 45994.097 | CT22: =IF(CL22>100000000000, "100bn", IF(CL22>50000000000, "50bn - 100bn",IF(CL22>1000000000, "1bn - 50bn", IF(CL22>500000000, "500mn - 1bn", "500mn")))) -> 100bn | CU22: =VLOOKUP(CK22,Mapping!B:C,2,FALSE) -> US/CA
A23: Charles Schwab Investment Management, Inc. | B23: yes | E23: 3772681296 | F23: 771282 | G23: N/A | I23: 39887697 | J23: 0.01 | K23: 623265874 | L23: 0.08 | O23: 692500109 | P23: 0.09 | Q23: 3131305 | R23: 102977697 | S23: 0.01 | V23: 88138414 | W23: 0.01 | X23: 146988995 | Y23: 0.02 | Z23: 159851339 | AA23: 0.02 | AB23: 45878462 | AC23: 0.01 | AF23: 114146215 | AG23: 0.01 | AH23: 395421195 | AI23: 0.05 | AJ23: 2801671 | AK23: 3737698 | AL23: 41139865 | AM23: 1519683 | AN23: 1167344903 | AO23: 0.15 | AP23: 174562306 | AQ23: 0.02 | AT23: 18342449 | AU23: 0 | AX23: 3375641 | AY23: 0 | AZ23: 9227019 | BA23: 1438530 | BC23: 5405862 | BD23: 1720680 | BF23: 6642803 | BG23: 10524585 | BH23: 756041 | BI23: 6931450 | BO23: 0.11 | BP23: 0.29 | BQ23: 0.75 | BR23: 0.11 | BS23: 0.12 | BT23: 0.12 | BU23: 0.21 | BV23: 0.65 | BW23: 0.06 | BX23: 0.16 | BY23: 0.89 | BZ23: 0.03 | CD23: 0.43 | CF23: 1.48 | CG23: Index | CH23: 12.032 | CI23: San Francisco | CJ23: California | CK23: United States | CL23: 787363814294 | CN23: Investment Manager-Mutual Fund | CT23: =IF(CL23>100000000000, "100bn", IF(CL23>50000000000, "50bn - 100bn",IF(CL23>1000000000, "1bn - 50bn", IF(CL23>500000000, "500mn - 1bn", "500mn")))) -> 100bn | CU23: =VLOOKUP(CK23,Mapping!B:C,2,FALSE) -> US/CA
A24: Vontobel Asset Management AG (Switzerland) | B24: yes | C24: 22 | D24: 1383213 | E24: 495964042 | F24: 883760 | G24: 68870175 | H24: 0.22 | I24: 42948494 | J24: 0.13 | K24: 159842671 | L24: 0.5 | M24: 54762161 | N24: 0.17 | O24: 107470252 | P24: 0.34 | Q24: 15669 | T24: 4487898 | U24: 0.01 | X24: 7210025 | Y24: 0.02 | Z24: 6502236 | AA24: 0.02 | AD24: 7826364 | AE24: 0.02 | AH24: 1978681 | AI24: 0.01 | AL24: 7076600 | AN24: 17317046 | AO24: 0.05 | AP24: 9418927 | AQ24: 0.03 | AR24: 429171 | AS24: 0 | AT24: 6899941 | AU24: 0.02 | BA24: 70562 | BB24: 436491 | BC24: 219893 | BD24: 647274 | BE24: 11509 | BG24: 2587800 | BH24: 40794 | BI24: 102825 | BJ24: 70242 | BK24: 40092 | BM24: 0.01 | BN24: 0.2 | BO24: 0.13 | BQ24: 0 | BS24: 0.03 | BU24: 0.04 | BV24: 0.03 | BY24: 0.01 | BZ24: 0 | CB24: 0.02 | CC24: 0.02 | CD24: 0.02 | CE24: 0 | CF24: 0.56 | CG24: Growth | CH24: 34.725 | CI24: Zürich | CK24: Switzerland | CL24: 31983266955 | CM24: 4620 | CN24: Investment Manager-Mutual Fund | CO24: HM | CP24: -1783465.9 | CQ24: 76 | CT24: =IF(CL24>100000000000, "100bn", IF(CL24>50000000000, "50bn - 100bn",IF(CL24>1000000000, "1bn - 50bn", IF(CL24>500000000, "500mn - 1bn", "500mn")))) -> 1bn - 50bn | CU24: =VLOOKUP(CK24,Mapping!B:C,2,FALSE) -> EU
A25: Capital Research Global Investors (U.S.) | B25: no | C25: 17 | D25: 1580121 | E25: 771933263 | F25: 9800 | G25: 78674225 | H25: 0.01 | I25: 476255 | J25: 0 | K25: 2754843 | L25: 0 | M25: 53184627 | N25: 0.01 | R25: 136560 | S25: 0 | V25: 71763706 | W25: 0.01 | AF25: 99147 | AG25: 0 | AK25: 3298100 | AN25: 564843900 | AO25: 0.08 | AR25: 0 | AS25: 0 | AZ25: 12900 | BB25: 423917 | BE25: 0 | BF25: 7350 | BG25: 44600 | BI25: 3353925 | BM25: 0 | BN25: 0.23 | BO25: 0 | BP25: 0 | BS25: 0 | BT25: 0.1 | BX25: 0 | BY25: 0.43 | CC25: 0.02 | CG25: GARP | CH25: 42.718 | CI25: Los Angeles | CJ25: California | CK25: United States | CL25: 718227362777 | CM25: 28 | CN25: Investment Manager-Mutual Fund | CO25: HT | CP25: 11713881 | CQ25: 70 | CT25: =IF(CL25>100000000000, "100bn", IF(CL25>50000000000, "50bn - 100bn",IF(CL25>1000000000, "1bn - 50bn", IF(CL25>500000000, "500mn - 1bn", "500mn")))) -> 100bn | CU25: =VLOOKUP(CK25,Mapping!B:C,2,FALSE) -> US/CA
